Workbook
Name _______MDO1: [1]INSUMOS!$C$8
Name _______MDO2: [2]INSUMOS!$C$6
Name _______R: #REF!
Name ______MDO1: [1]INSUMOS!$C$8
Name ______MDO2: [2]INSUMOS!$C$6
Name ______R: #REF!
Name ______R: #REF!
Name ______rua1: #REF!
Name ______rua1: #REF!
Name _____MDO1: [1]INSUMOS!$C$8
Name _____MDO2: [2]INSUMOS!$C$6
Name _____R: #REF!
Name _____R: #REF!
Name _____rua1: #REF!
Name _____rua1: #REF!
Name ____MDO1: [1]INSUMOS!$C$8
Name ____MDO2: [2]INSUMOS!$C$6
Name ____R: #REF!
Name ____R: #REF!
Name ____rua1: #REF!
Name ____rua1: #REF!
Name ___MDO1: [1]INSUMOS!$C$8
Name ___MDO2: [2]INSUMOS!$C$6
Name ___R: #REF!
Name ___R: #REF!
Name ___rua1: #REF!
Name ___rua1: #REF!
Name __MDO1: [3]INSUMOS!$C$8
Name __MDO1: [3]INSUMOS!$C$8
Name __MDO2: [2]INSUMOS!$C$6
Name __R: #REF!
Name __R: #REF!
Name __rua1: #REF!
Name __rua1: #REF!
Name __xlnm.Print_Titles_2: #REF!
Name __xlnm.Print_Titles_2: #REF!
Name _MDO1: [3]INSUMOS!$C$8
Name _MDO1: [3]INSUMOS!$C$8
Name _MDO2: [2]INSUMOS!$C$6
Name _R: #REF!
Name _R: #REF!
Name _rua1: #REF!
Name _rua1: #REF!
Name A: #REF!
Name AA: [4]CUBACAO!#REF!
Name AA: [4]CUBACAO!#REF!
Name AAA: [4]CUBACAO!#REF!
Name AAA: [4]CUBACAO!#REF!
Name Ac: #REF!
Name Ac: #REF!
Name artFiscal: [5]DADOS!$D$23
Name ASDFASDFAS: #REF!
Name ASDFASDFAS: #REF!
Name BB: [4]CUBACAO!#REF!
Name BB: [4]CUBACAO!#REF!
Name BBB: [4]CUBACAO!#REF!
Name BBB: [4]CUBACAO!#REF!
Name bdi: [6]Orçamento!$J$10
Name bdi: [6]Orçamento!$J$10
Name BDIc: #REF!

Sheet BM-03
A1: ESTADO DA PARAÍBA
A2: PREFEITURA MUNICIPAL DE COREMAS | Q2: VALOR EDITAL | R2: R$ 1.252.370,60
A3: CONTRATO Nº 10004/2023 | Q3: VALOR C/DESC. | R3: =L236 -> 1249356.4
A4: OBRA: CONSTRUÇÃO DE UMA UNIDADE ESCOLAR DE 06 (SEIS) SALAS DE AULA PARA O MUNICÍPIO DE COREMAS-PB | J4: BDI = | K4: 0.25
A5: LOCAL: MUNICÍPIO DE COREMAS-PB | Q5: DESCONTO: | R5: 0.17
A6: BOLETIM DE MEDIÇÃO - BM-03
A7: ITEM | B7: CÓDIGO | C7: REFERÊNCIA | D7: DESCRIÇÃO | E7: ORIGEM | F7: UNID | G7: QUANTIDADES | K7: VALOR UNIT COM BDI | L7: VALORES TOTAIS
G8: LICITADA | H8: ACUMULADA ATÉ O PERÍODO | I8: MEDIDA NO PERÍODO | J8: ACUMULADA INCLUINDO O PERÍODO | L8: LICITADO | M8: ACUMULADO ATÉ O PERÍODO | N8: MEDIDO NO PERÍODO | O8: ACUMULADO INCLUINDO O PERÍODO
A9: 1 ETAPA 01: GERAL | L9: =SUM(L10,L16) -> 66229.186 | M9: =SUM(M10,M16) -> 21240.562 | N9: =SUM(N10,N16) -> 10942.107 | O9: =SUM(O10,O16) -> 32182.669 | P9: =IF(O9<>L9,O9/L9,"") -> 0.4859288
A10: 1.1 1 ADMINISTRACAO LOCAL | L10: =SUM(L11:L15) -> 64365.338 | M10: =SUM(M11:M15) -> 21240.562 | N10: =SUM(N11:N15) -> 10942.107 | O10: =SUM(O11:O15) -> 32182.669 | P10: =IF(O10<>L10,O10/L10,"") -> 0.5
A11: 1.1.1 | B11: 164471 | C11: O13221 | D11: ADMINSTRACAO LOCAL - PESSOAL | E11: SUPLAN | F11: UN | G11: 8 | H11: 2.64 | I11: ='MEMORIAL DE CÁLCULOS'!J11 -> 1.36 | J11: =H11+I11 -> 4 | K11: 4208.9549 | L11: =G11*K11 -> 33671.639 | M11: =H11*K11 -> 11111.641 | N11: =I11*K11 -> 5724.1787 | O11: =J11*K11 -> 16835.82 | P11: =IF(O11<>L11,O11/L11,"") -> 0.5 | V11: 5071.03 | W11: =V11-V11*$R$5 -> 4208.9549
A12: 1.1.2 | B12: 164472 | C12: O13221 | D12: ADMINISTRACAO LOCAL - DESPESAS GERAIS MENSAIS | E12: SUPLAN | F12: UN | G12: 8 | H12: 2.64 | I12: ='MEMORIAL DE CÁLCULOS'!J14 -> 1.36 | J12: =H12+I12 -> 4 | K12: 1588.6449 | L12: =G12*K12 -> 12709.159 | M12: =H12*K12 -> 4194.0225 | N12: =I12*K12 -> 2160.5571 | O12: =J12*K12 -> 6354.5796 | P12: =IF(O12<>L12,O12/L12,"") -> 0.5 | V12: 1914.03 | W12: =V12-V12*$R$5 -> 1588.6449
A13: 1.1.3 | B13: 164473 | C13: O13221 | D13: ADMINISTRACAO LOCAL - DESPESAS GERAIS FIXAS | E13: SUPLAN | F13: UN | G13: 1 | H13: 0.33 | I13: ='MEMORIAL DE CÁLCULOS'!J17 -> 0.17 | J13: =H13+I13 -> 0.5 | K13: 2489.2862 | L13: =G13*K13 -> 2489.2862 | M13: =H13*K13 -> 821.46445 | N13: =I13*K13 -> 423.17865 | O13: =J13*K13 -> 1244.6431 | P13: =IF(O13<>L13,O13/L13,"") -> 0.5 | V13: 2999.14 | W13: =V13-V13*$R$5 -> 2489.2862
A14: 1.1.4 | B14: 164474 | C14: O13221 | D14: ADMINISTRACAO LOCAL - VECULOS E EQUIPAMENTOS | E14: SUPLAN | F14: UN | G14: 8 | H14: 2.64 | I14: ='MEMORIAL DE CÁLCULOS'!J20 -> 1.36 | J14: =H14+I14 -> 4 | K14: 1279.8185 | L14: =G14*K14 -> 10238.548 | M14: =H14*K14 -> 3378.7208 | N14: =I14*K14 -> 1740.5532 | O14: =J14*K14 -> 5119.274 | P14: =IF(O14<>L14,O14/L14,"") -> 0.5 | V14: 1541.95 | W14: =V14-V14*$R$5 -> 1279.8185
A15: 1.1.5 | B15: 164475 | C15: O13221 | D15: ADMINISTRACAO LOCAL - MOVEIS E UTENSILIOS | E15: SUPLAN | F15: UN | G15: 1 | H15: 0.33 | I15: ='MEMORIAL DE CÁLCULOS'!J23 -> 0.17 | J15: =H15+I15 -> 0.5 | K15: 5256.7054 | L15: =G15*K15 -> 5256.7054 | M15: =H15*K15 -> 1734.7128 | N15: =I15*K15 -> 893.63992 | O15: =J15*K15 -> 2628.3527 | P15: =IF(O15<>L15,O15/L15,"") -> 0.5 | V15: 6333.38 | W15: =V15-V15*$R$5 -> 5256.7054
A16: 1.2 DIVERSOS | L16: =SUM(L17) -> 1863.848 | M16: =SUM(M17) -> 0 | N16: =SUM(N17) -> 0 | O16: =SUM(O17) -> 0 | P16: =IF(O16<>L16,O16/L16,"") -> 0
A17: 1.2.1 | B17: 164476 | D17: "AS BUILT" DO PROJETO ARQUITETONICO E DOS PROJETOS DE ENGENHARIA DE ESTRUTURAS E DE INSTALACOES ELETRICAS, INSTALACOES HIDRAULICAS E INSTALACOES SANITARIAS - ESCOLAS | E17: SINAPI | F17: UN | G17: 1 | H17: 0 | J17: =H17+I17 -> 0 | K17: 1863.848 | L17: =G17*K17 -> 1863.848 | M17: =H17*K17 -> 0 | N17: =I17*K17 -> 0 | O17: =J17*K17 -> 0 | P17: =IF(O17<>L17,O17/L17,"") -> 0 | V17: 2245.6 | W17: =V17-V17*$R$5 -> 1863.848
A18: 2 ETAPA 02: CONSTRUCAO DA ESCOLA | L18: =SUM(L19,L29,L33,L40,L55,L66,L79,L89,L98,L111,L122,L153,L162,L186,L197,) -> 1144166 | M18: =SUM(M19,M29,M33,M40,M55,M66,M79,M89,M98,M111,M122,M153,M162,M186,M197,) -> 354180.12 | N18: =SUM(N19,N29,N33,N40,N55,N66,N79,N89,N98,N111,N122,N153,N162,N186,N197,) -> 225472.35 | O18: =SUM(O19,O29,O33,O40,O55,O66,O79,O89,O98,O111,O122,O153,O162,O186,O197,) -> 579652.47 | P18: =IF(O18<>L18,O18/L18,"") -> 0.50661571
A19: 2.1 1 SERVICOS PRELIMINARES | L19: =SUM(L20:L28) -> 21969.068 | M19: =SUM(M20:M28) -> 20020.236 | N19: =SUM(N20:N28) -> 0 | O19: =SUM(O20:O28) -> 20020.236 | P19: =IF(O19<>L19,O19/L19,"") -> 0.91129202
A20: 2.1.1 | B20: 132583 | C20: 74209/001 | D20: PLACA DE OBRA EM CHAPA DE ACO GALVANIZADO | E20: SINAPI | F20: M2 | G20: 10 | H20: 10 | J20: =H20+I20 -> 10 | K20: 342.8979 | L20: =G20*K20 -> 3428.979 | M20: =H20*K20 -> 3428.979 | N20: =I20*K20 -> 0 | O20: =J20*K20 -> 3428.979 | P20: =IF(O20<>L20,O20/L20,"") | V20: 413.13 | W20: =V20-V20*$R$5 -> 342.8979
A21: 2.1.2 | B21: 163387 | C21: 74077/3 | D21: LOCACAO CONVENCIONAL DE OBRA, ATRAVES DE GABARITO DE TABUAS CORRIDAS PONTALETADAS, COM REAPROVEITAMENTO DE 3 VEZES - | E21: SINAPI | F21: M2 | G21: 771.45 | H21: 771.45 | J21: =H21+I21 -> 771.45 | K21: 4.9551 | L21: =G21*K21 -> 3822.6119 | M21: =H21*K21 -> 3822.6119 | N21: =I21*K21 -> 0 | O21: =J21*K21 -> 3822.6119 | P21: =IF(O21<>L21,O21/L21,"") | V21: 5.97 | W21: =V21-V21*$R$5 -> 4.9551
A22: 2.1.3 | B22: 137043 | C22: 73822/002 | D22: LIMPEZA MECANIZADA DE TERRENO COM REMOCAO DE CAMADA VEGETAL, UTILIZAND O MOTONIVELADORA | E22: SINAPI | F22: M2 | G22: 2000 | H22: 2000 | J22: =H22+I22 -> 2000 | K22: 0.2739 | L22: =G22*K22 -> 547.8 | M22: =H22*K22 -> 547.8 | N22: =I22*K22 -> 0 | O22: =J22*K22 -> 547.8 | P22: =IF(O22<>L22,O22/L22,"") | V22: 0.33 | W22: =V22-V22*$R$5 -> 0.2739
A23: 2.1.4 | B23: 163443 | C23: C2851 | D23: INSTALACOES PROVISORIAS DE AGUA, INCLUSIVE CAIXA DAGUA DE 1000L | E23: SINAPI | F23: UN | G23: 1 | H23: 1 | J23: =H23+I23 -> 1 | K23: 1390.1255 | L23: =G23*K23 -> 1390.1255 | M23: =H23*K23 -> 1390.1255 | N23: =I23*K23 -> 0 | O23: =J23*K23 -> 1390.1255 | P23: =IF(O23<>L23,O23/L23,"") | V23: 1674.85 | W23: =V23-V23*$R$5 -> 1390.1255
A24: 2.1.5 | B24: 163442 | C24: 11122/ORS | D24: ENTRADA DE ENERGIA ELETRICA MONOFASICA COM POSTE DE CONCRETO, INCLUSIVE CABEAMENTO, CAIXA DE PROTECAO PARA MEDIDOR E | E24: SINAPI | F24: UN | G24: 1 | H24: 0 | J24: =H24+I24 -> 0 | K24: 1506.3255 | L24: =G24*K24 -> 1506.3255 | M24: =H24*K24 -> 0 | N24: =I24*K24 -> 0 | O24: =J24*K24 -> 0 | P24: =IF(O24<>L24,O24/L24,"") -> 0 | V24: 1814.85 | W24: =V24-V24*$R$5 -> 1506.3255
A25: 2.1.6 | B25: 135723 | C25: 73658 | D25: LIGACAO DOMICILIAR DE ESGOTO DN 100MM, DA CASA ATE A CAIXA, COMPOSTO P OR 10,0M TUBO DE PVC ESGOTO PREDIAL DN 100MM E CAIXA DE ALVENARIA COM TAMPA DE CONCRETO - FORNECIMENTO E | E25: SINAPI | F25: UN | G25: 1 | H25: 0 | J25: =H25+I25 -> 0 | K25: 442.5062 | L25: =G25*K25 -> 442.5062 | M25: =H25*K25 -> 0 | N25: =I25*K25 -> 0 | O25: =J25*K25 -> 0 | P25: =IF(O25<>L25,O25/L25,"") -> 0 | V25: 533.14 | W25: =V25-V25*$R$5 -> 442.5062
A26: 2.1.7 | B26: 162175 | D26: LOCACAO DE CONTAINER 2,30 X 4,30 M, ALT. 2,50 M, P/ SANITARIO, C/ 5 BACIAS, 1 LAVATORIO E 4 MICTORIOS, INCLUSIVE TRANSP/CARGA/DESCARGA | E26: SUPLAN | F26: MÊS | G26: 0 | H26: 0 | J26: =H26+I26 -> 0 | K26: 654.9198 | L26: =G26*K26 -> 0 | M26: =H26*K26 -> 0 | N26: =I26*K26 -> 0 | O26: =J26*K26 -> 0 | P26: =IF(O26<>L26,O26/L26,"") | V26: 789.06 | W26: =V26-V26*$R$5 -> 654.9198
A27: 2.1.8 | B27: 163536 | D27: ALUGUEL CONTAINER/ESCRIT INCL INST ELET LARG=2,20 COMP=6,20M ALT=2,50M CHAPA ACO C/NERV TRAPEZ FORRO C/ISOLTERMO/ACUSTICO CHASSIS REFORC P I S O C O M P E N S N A V A L I N C T R A N S P / C A R G A / D E S C A R G A | E27: SINAPI | F27: MÊS | G27: 0 | H27: 0 | J27: =H27+I27 -> 0 | K27: 565.4375 | L27: =G27*K27 -> 0 | M27: =H27*K27 -> 0 | N27: =I27*K27 -> 0 | O27: =J27*K27 -> 0 | P27: =IF(O27<>L27,O27/L27,"") | V27: 681.25 | W27: =V27-V27*$R$5 -> 565.4375
A28: 2.1.9 | C28: 93206/SINAPI (ALTERADA) | D28: EXECUÇÃO DE DEPÓSITO EM CANTEIRO DE OBRA EM ALVENARIA | E28: SINAPI | F28: M2 | G28: 32 | H28: 32 | J28: =H28+I28 -> 32 | K28: 338.46 | L28: =G28*K28 -> 10830.72 | M28: =H28*K28 -> 10830.72 | N28: =I28*K28 -> 0 | O28: =J28*K28 -> 10830.72 | P28: =IF(O28<>L28,O28/L28,"")
A29: 2.2 2 MOVIMENTO DE TERRA | L29: =SUM(L30:L32) -> 173993.72 | M29: =SUM(M30:M32) -> 166157.8 | N29: =SUM(N30:N32) -> 7835.917 | O29: =SUM(O30:O32) -> 173993.72 | P29: =IF(O29<>L29,O29/L29,"")
A30: 2.2.1 | B30: 160239 | D30: ESCAVACAO MANUAL DE VALA EM MATERIAL DE QUALQUER CATEGORIA, EXCETO ROCHA COM PROFUNDIDADE ATE 2M. | E30: SINAPI | F30: M3 | G30: 225.25 | H30: 225.25 | J30: =H30+I30 -> 225.25 | K30: 63.1132 | L30: =G30*K30 -> 14216.248 | M30: =H30*K30 -> 14216.248 | N30: =I30*K30 -> 0 | O30: =J30*K30 -> 14216.248 | P30: =IF(O30<>L30,O30/L30,"") | V30: 76.04 | W30: =V30-V30*$R$5 -> 63.1132
A31: 2.2.2 | B31: 164368 | C31: 24824/SIN | D31: ATERRO DO CAIXAO SEM AQUISICAO DO MATERIAL (REATERRO MANUAL) | E31: SINAPI | F31: M3 | G31: 205.7 | H31: 205.7 | J31: =H31+I31 -> 205.7 | K31: 38.1717 | L31: =G31*K31 -> 7851.9187 | M31: =H31*K31 -> 7851.9187 | N31: =I31*K31 -> 0 | O31: =J31*K31 -> 7851.9187 | P31: =IF(O31<>L31,O31/L31,"") | V31: 45.99 | W31: =V31-V31*$R$5 -> 38.1717
A32: 2.2.3 | B32: 153622 | D32: ATERRO DO CAIXAO COM AQUISICAO DO MATERIAL/AREIA, APILOADO EM CAMADAS DE 0,20M | E32: SINAPI | F32: M3 | G32: 1072.37 | H32: 1017.06 | I32: ='MEMORIAL DE CÁLCULOS'!J28 -> 55.31 | J32: =H32+I32 -> 1072.37 | K32: 141.6727 | L32: =G32*K32 -> 151925.55 | M32: =H32*K32 -> 144089.64 | N32: =I32*K32 -> 7835.917 | O32: =J32*K32 -> 151925.55 | P32: =IF(O32<>L32,O32/L32,"") | V32: 170.69 | W32: =V32-V32*$R$5 -> 141.6727
A33: 2.3 3 INFRAESTRUTURA | L33: =SUM(L34:L39) -> 97254.846 | M33: =SUM(M34:M39) -> 87752.738 | N33: =SUM(N34:N39) -> 4440.2844 | O33: =SUM(O34:O39) -> 92193.022 | P33: =IF(O33<>L33,O33/L33,"") -> 0.94795299
A34: 2.3.1 | B34: 146934 | C34: 95467 | D34: EMBASAMENTO C/PEDRA ARGAMASSADA UTILIZANDO ARG.CIM/AREIA 1:4 | E34: SINAPI | F34: M3 | G34: 105.04 | H34: 105.04 | J34: =H34+I34 -> 105.04 | K34: 316.5952 | L34: =G34*K34 -> 33255.16 | M34: =H34*K34 -> 33255.16 | N34: =I34*K34 -> 0 | O34: =J34*K34 -> 33255.16 | P34: =IF(O34<>L34,O34/L34,"") | V34: 381.44 | W34: =V34-V34*$R$5 -> 316.5952
A35: 2.3.2 | B35: 160126 | D35: ALVENARIA DE 1 VEZ VEDACAO COM BLOCOS CERAMICO FURADOS 9 X 19 X 19 CM FUROS HORIZONTAIS, ESPESSURA DA PAREDE 19 CM, JUNTAS DE 10 MM COM ARGAMASSA TRACO 1:2:8 (CIMENTO, CAL E AREIA MEDIA) | E35: SINAPI | F35: M2 | G35: 451.79 | H35: 242.65 | I35: ='MEMORIAL DE CÁLCULOS'!J36 -> 97.73 | J35: =H35+I35 -> 340.38 | K35: 45.4342 | L35: =G35*K35 -> 20526.717 | M35: =H35*K35 -> 11024.609 | N35: =I35*K35 -> 4440.2844 | O35: =J35*K35 -> 15464.893 | P35: =IF(O35<>L35,O35/L35,"") -> 0.75340313 | V35: 54.74 | W35: =V35-V35*$R$5 -> 45.4342
A36: 2.3.3 | B36: 154476 | C36: 96616 | D36: LASTRO DE CONCRETO MAGRO, APLICADO EM BLOCOS DE COROAMENTO OU SAPATAS.AF_08/2017 | E36: SINAPI | F36: M3 | G36: 6.13 | H36: 6.13 | J36: =H36+I36 -> 6.13 | K36: 463.804 | L36: =G36*K36 -> 2843.1185 | M36: =H36*K36 -> 2843.1185 | N36: =I36*K36 -> 0 | O36: =J36*K36 -> 2843.1185 | P36: =IF(O36<>L36,O36/L36,"") | V36: 558.8 | W36: =V36-V36*$R$5 -> 463.804
A37: 2.3.4 | B37: 161024 | D37: CONCRETO ARMADO (PREPARO E LANCAMENTO)PARA SAPATAS COM FCK >= 25MPA, COM FORMA DE TABUA, COM APROVEI TAMENTO DE 2 VEZES, COM BETONEIRA - | E37: SINAPI | F37: M3 | G37: 19.55 | H37: 19.55 | J37: =H37+I37 -> 19.55 | K37: 1008.533 | L37: =G37*K37 -> 19716.82 | M37: =H37*K37 -> 19716.82 | N37: =I37*K37 -> 0 | O37: =J37*K37 -> 19716.82 | P37: =IF(O37<>L37,O37/L37,"") | V37: 1215.1 | W37: =V37-V37*$R$5 -> 1008.533
A38: 2.3.5 | B38: 161026 | D38: CONCRETO ARMADO (PREPARO E LANCAMENTO) PARA RADIER COM FCK>=25MPA, COM TABUA DE MADEIRA, COM APROVEITAMENTO DE 3 VEZES COM BETONEIRA - | E38: SINAPI | F38: M3 | G38: 15.2 | H38: 15.2 | J38: =H38+I38 -> 15.2 | K38: 1006.9477 | L38: =G38*K38 -> 15305.605 | M38: =H38*K38 -> 15305.605 | N38: =I38*K38 -> 0 | O38: =J38*K38 -> 15305.605 | P38: =IF(O38<>L38,O38/L38,"") | V38: 1213.19 | W38: =V38-V38*$R$5 -> 1006.9477
A39: 2.3.6 | C39: 98557 | D39: IMPERMEABILIZAÇÃO DE SUPERFÍCIE COM EMULSÃO ASFÁLTICA, 2 DEMÃOS AF_06/2018 | E39: SINAPI | F39: M2 | G39: 195.79 | H39: 195.79 | J39: =H39+I39 -> 195.79 | K39: 28.64 | L39: =G39*K39 -> 5607.4256 | M39: =H39*K39 -> 5607.4256 | N39: =I39*K39 -> 0 | O39: =J39*K39 -> 5607.4256 | P39: =IF(O39<>L39,O39/L39,"")
A40: 2.4 4 SUPER-ESTRUTURA | L40: =SUM(L41:L54) -> 201473.62 | M40: =SUM(M41:M54) -> 42615.483 | N40: =SUM(N41:N54) -> 144001.76 | O40: =SUM(O41:O54) -> 186617.25 | P40: =IF(O40<>L40,O40/L40,"") -> 0.92626146
A41: 2.4.1 | B41: 161030 | D41: CONCRETO ARMADO (PREPARO E LANCAMENTO) PARA VIGA COM FCK>=30MPA, COM FORMA EM CHAPA DE MADEIRA COM- P E N S A D A R E S I N A D A , C O M APROVEITAMENTO DE 3 VEZES COM BETONEIRA - | E41: SINAPI | F41: M3 | G41: 26.13 | H41: 0 | I41: ='MEMORIAL DE CÁLCULOS'!J42 -> 24.23 | J41: =H41+I41 -> 24.23 | K41: 2838.0273 | L41: =G41*K41 -> 74157.653 | M41: =H41*K41 -> 0 | N41: =I41*K41 -> 68765.401 | O41: =J41*K41 -> 68765.401 | P41: =IF(O41<>L41,O41/L41,"") -> 0.92728664 | V41: 3419.31 | W41: =V41-V41*$R$5 -> 2838.0273
A42: 2.4.2 | B42: 161031 | D42: CONCRETO ARMADO (PREPARO E LANCAMENTO) P/ PILARES COM FCK>=30MPA, COM FORMA EM CHAPA DE MADEIRA COM- P E N S A D A R E S I N A D A , C O M APROVEITAMENTO DE 3 VEZES, COM BETONEIRA - | E42: SUPLAN | F42: M3 | G42: 15.84 | H42: 15.15 | J42: =H42+I42 -> 15.15 | K42: 2812.9032 | L42: =G42*K42 -> 44556.387 | M42: =H42*K42 -> 42615.483 | N42: =I42*K42 -> 0 | O42: =J42*K42 -> 42615.483 | P42: =IF(O42<>L42,O42/L42,"") -> 0.95643939 | V42: 3389.04 | W42: =V42-V42*$R$5 -> 2812.9032
A43: 2.4.3 | B43: 161027 | D43: CONCRETO ARMADO (PREPARO E LANCAMENTO) PARA CINTA COM FCK>=30MPA, COM TABUA DE MADEIRA, COM APROVEITAMENTO DE 3 VEZES COM BETONEIRA - | E43: SINAPI | F43: M3 | G43: 0 | H43: 0 | J43: =H43+I43 -> 0 | K43: 2012.5259 | L43: =G43*K43 -> 0 | M43: =H43*K43 -> 0 | N43: =I43*K43 -> 0 | O43: =J43*K43 -> 0 | P43: =IF(O43<>L43,O43/L43,"") | V43: 2424.73 | W43: =V43-V43*$R$5 -> 2012.5259
A44: 2.4.4 | B44: 134255 | C44: 74202/001 | D44: LAJE PRE-MOLDADA P/FORRO, SOBRECARGA 100KG/M2, VAOS ATE 3,50M/E=8CM, C /LAJOTAS E CAP.C/CONC FCK=20MPA, 3CM, INTER-EIXO 38CM, C/ESCORAMENTO ( REAPR.3X) E FERRAGEM NEGATIVA | E44: SINAPI | F44: M2 | G44: 21.78 | H44: 0 | J44: =H44+I44 -> 0 | K44: 112.9215 | L44: =G44*K44 -> 2459.4303 | M44: =H44*K44 -> 0 | N44: =I44*K44 -> 0 | O44: =J44*K44 -> 0 | P44: =IF(O44<>L44,O44/L44,"") -> 0 | V44: 136.05 | W44: =V44-V44*$R$5 -> 112.9215
A45: 2.4.5 | B45: 145501 | D45: PRATELEIRA EM CONCRETO ARMADO COM E=0,05M E L=0,40M COM REVESTIMENTO CERAMICA | E45: SINAPI | F45: M | G45: 17.85 | H45: 0 | J45: =H45+I45 -> 0 | K45: 119.1548 | L45: =G45*K45 -> 2126.9132 | M45: =H45*K45 -> 0 | N45: =I45*K45 -> 0 | O45: =J45*K45 -> 0 | P45: =IF(O45<>L45,O45/L45,"") -> 0 | V45: 143.56 | W45: =V45-V45*$R$5 -> 119.1548
A46: 2.4.6 | B46: 145226 | D46: PRATELEIRA EM CONCRETO ARMADO COM E=0,05M E L=0,45M COM REVESTIMENTO CERAMICA | E46: SINAPI | F46: M | G46: 9.9 | H46: 0 | J46: =H46+I46 -> 0 | K46: 119.1548 | L46: =G46*K46 -> 1179.6325 | M46: =H46*K46 -> 0 | N46: =I46*K46 -> 0 | O46: =J46*K46 -> 0 | P46: =IF(O46<>L46,O46/L46,"") -> 0 | V46: 143.56 | W46: =V46-V46*$R$5 -> 119.1548
A47: 2.4.7 | B47: 144469 | D47: PRATELEIRA EM CONCRETO ARMADO COM E=0,05M E L=0,50M E REVESTIMENTO EM CERAMICA | E47: SINAPI | F47: M | G47: 1.6 | H47: 0 | J47: =H47+I47 -> 0 | K47: 194.1702 | L47: =G47*K47 -> 310.67232 | M47: =H47*K47 -> 0 | N47: =I47*K47 -> 0 | O47: =J47*K47 -> 0 | P47: =IF(O47<>L47,O47/L47,"") -> 0 | V47: 233.94 | W47: =V47-V47*$R$5 -> 194.1702
A48: 2.4.8 | B48: 144116 | D48: PRATELEIRA EM CONCRETO ARMADO COM E=0,05M E L=0,60M E REVESTIMENTO EM CERAMICA | E48: SINAPI | F48: M | G48: 7.45 | H48: 0 | J48: =H48+I48 -> 0 | K48: 194.1702 | L48: =G48*K48 -> 1446.568 | M48: =H48*K48 -> 0 | N48: =I48*K48 -> 0 | O48: =J48*K48 -> 0 | P48: =IF(O48<>L48,O48/L48,"") -> 0 | V48: 233.94 | W48: =V48-V48*$R$5 -> 194.1702
A49: 2.4.9 | C49: 92510 | D49: MONTAGEM E DESMONTAGEM DE FÔRMA DE LAJE MACIÇA COM ÁREA MÉDIA MAIOR QUE 20 M², PÉ-DIREITO SIMPLES, EM CHAPA DE MADEIRA COMPENSADA RESINADA, 2 UTILIZAÇÕES | E49: SINAPI | F49: M2 | G49: 560.03 | H49: 0 | I49: ='MEMORIAL DE CÁLCULOS'!J45 -> 560.03 | J49: =H49+I49 -> 560.03 | K49: 36.3 | L49: =G49*K49 -> 20329.089 | M49: =H49*K49 -> 0 | N49: =I49*K49 -> 20329.089 | O49: =J49*K49 -> 20329.089 | P49: =IF(O49<>L49,O49/L49,"")
A50: 2.4.10 | C50: 92784 | D50: ARMAÇÃO DE LAJE DE UMA ESTRUTURA CONVENCIONAL DE CONCRETO ARMADO EM UMA EDIFICAÇÃO TÉRREA OU SOBRADO UTILIZANDO AÇO CA-60 DE 5,0 MM - MONTAGEM. AF_12/2015 | E50: SINAPI | F50: KG | G50: 8.8 | H50: 0 | I50: ='MEMORIAL DE CÁLCULOS'!J48 -> 8.8 | J50: =H50+I50 -> 8.8 | K50: 17.24 | L50: =G50*K50 -> 151.712 | M50: =H50*K50 -> 0 | N50: =I50*K50 -> 151.712 | O50: =J50*K50 -> 151.712 | P50: =IF(O50<>L50,O50/L50,"")
A51: 2.4.11 | C51: 92785 | D51: ARMAÇÃO DE LAJE DE UMA ESTRUTURA CONVENCIONAL DE CONCRETO ARMADO EM UMA EDIFICAÇÃO TÉRREA OU SOBRADO UTILIZANDO AÇO CA-50 DE 6,3 MM - MONTAGEM. AF_12/2015 | E51: SINAPI | F51: KG | G51: 1103.2 | H51: 0 | I51: ='MEMORIAL DE CÁLCULOS'!J51 -> 1103.2 | J51: =H51+I51 -> 1103.2 | K51: 17.16 | L51: =G51*K51 -> 18930.912 | M51: =H51*K51 -> 0 | N51: =I51*K51 -> 18930.912 | O51: =J51*K51 -> 18930.912 | P51: =IF(O51<>L51,O51/L51,"")
A52: 2.4.12 | C52: 92786 | D52: ARMAÇÃO DE LAJE DE UMA ESTRUTURA CONVENCIONAL DE CONCRETO ARMADO EM UMA EDIFICAÇÃO TÉRREA OU SOBRADO UTILIZANDO AÇO CA-50 DE 8,0 MM - MONTAGEM. AF_12/2015 | E52: SINAPI | F52: KG | G52: 740 | H52: 0 | I52: ='MEMORIAL DE CÁLCULOS'!J54 -> 740 | J52: =H52+I52 -> 740 | K52: 16.71 | L52: =G52*K52 -> 12365.4 | M52: =H52*K52 -> 0 | N52: =I52*K52 -> 12365.4 | O52: =J52*K52 -> 12365.4 | P52: =IF(O52<>L52,O52/L52,"")
A53: 2.4.13 | C53: 92787 | D53: ARMAÇÃO DE LAJE DE UMA ESTRUTURA CONVENCIONAL DE CONCRETO ARMADO EM UMA EDIFICAÇÃO TÉRREA OU SOBRADO UTILIZANDO AÇO CA-50 DE 10,0 MM - MONTAGEM. AF_12/2015 | E53: SINAPI | F53: KG | G53: 227.6 | H53: 0 | I53: ='MEMORIAL DE CÁLCULOS'!J57 -> 227.6 | J53: =H53+I53 -> 227.6 | K53: 15.21 | L53: =G53*K53 -> 3461.796 | M53: =H53*K53 -> 0 | N53: =I53*K53 -> 3461.796 | O53: =J53*K53 -> 3461.796 | P53: =IF(O53<>L53,O53/L53,"")
A54: 2.4.14 | C54: 92726 | D54: CONCRETAGEM DE VIGAS E LAJES, FCK=20 MPA, PARA LAJES MACIÇAS OU NERVURADAS COM USO DE BOMBA EM EDIFICAÇÃO COM ÁREA MÉDIA DE LAJES MAIOR QUE 20 M² - LANÇAMENTO, ADENSAMENTO E ACABAMENTO. AF_12/2015 | E54: SINAPI | F54: M3 | G54: 50.36 | H54: 0 | I54: ='MEMORIAL DE CÁLCULOS'!J60 -> 50.36 | J54: =H54+I54 -> 50.36 | K54: 397.09 | L54: =G54*K54 -> 19997.452 | M54: =H54*K54 -> 0 | N54: =I54*K54 -> 19997.452 | O54: =J54*K54 -> 19997.452 | P54: =IF(O54<>L54,O54/L54,"")
A55: 2.5 5 PAREDES E PAINEIS | L55: =SUM(L56:L65) -> 97923.544 | M55: =SUM(M56:M65) -> 37633.856 | N55: =SUM(N56:N65) -> 37087.361 | O55: =SUM(O56:O65) -> 74721.216 | P55: =IF(O55<>L55,O55/L55,"") -> 0.7630567
A56: 2.5.1 | B56: 160118 | D56: ALVENARIA DE 1/2 VEZ VEDACAO COM BLOCOS CERAMICO FURADOS 9 X 19 X 19 CM FUROS HORIZONTAIS, ESPESSURA DA PAREDE 9 CM, JUNTAS DE 10 MM COM ARGAMASSA TRACO 1:2:8 (CIMENTO, CAL E | E56: SINAPI | F56: M2 | G56: 954.17 | H56: 750.85 | I56: ='MEMORIAL DE CÁLCULOS'!J64 -> 83.43 | J56: =H56+I56 -> 834.28 | K56: 34.0632 | L56: =G56*K56 -> 32502.084 | M56: =H56*K56 -> 25576.354 | N56: =I56*K56 -> 2841.8928 | O56: =J56*K56 -> 28418.246 | P56: =IF(O56<>L56,O56/L56,"") -> 0.87435153 | V56: 41.04 | W56: =V56-V56*$R$5 -> 34.0632
A57: 2.5.2 | B57: 136101 | C57: 73937/005 | D57: COBOGO DE CONCRETO (ELEMENTO VAZADO), 10X29X39CM ABERTURA COM VIDRO, A SSENTADO COM ARGAMASSA TRACO 1:4 (CIMENTO E AREIA MEDIA NAO PENEIRADA) | E57: SINAPI | F57: M2 | G57: 37.44 | H57: 0 | J57: =H57+I57 -> 0 | K57: 149.2423 | L57: =G57*K57 -> 5587.6317 | M57: =H57*K57 -> 0 | N57: =I57*K57 -> 0 | O57: =J57*K57 -> 0 | P57: =IF(O57<>L57,O57/L57,"") -> 0 | V57: 179.81 | W57: =V57-V57*$R$5 -> 149.2423
A58: 2.5.3 | B58: 164273 | D58: MURO EM ALVENARIA DE 1/2 VEZ COM TIJOLOS DE 8 FUROS COM LOCACAO E I N C L U S I V E E X E C U C A O D E GABARITO,ESCAVACAO MANUAL DE VALAS, ALVENARIA DE PEDRA ARGAMASSADA, EMBASAMENTO EM ALVENARIA DE 1 VEZ, CONCRETO ARMADOPARA RADIER E CINTA SUPERIOR, COLUNAS DE CONCRETO ARMADO A CADA 3,0M, CHAPISCADO, REBOCADO, SELADOR ACRILICO EPINTADO, | E58: SINAPI | F58: M | G58: 150 | H58: 0 | I58: ='MEMORIAL DE CÁLCULOS'!J97 -> 120 | J58: =H58+I58 -> 120 | K58: 285.3789 | L58: =G58*K58 -> 42806.835 | M58: =H58*K58 -> 0 | N58: =I58*K58 -> 34245.468 | O58: =J58*K58 -> 34245.468 | P58: =IF(O58<>L58,O58/L58,"") -> 0.8 | V58: 343.83 | W58: =V58-V58*$R$5 -> 285.3789
A59: 2.5.4 | B59: 151091 | D59: MURETA EM ALVENARIA DE 1 VEZ COM TIJOLO DE 8 FUROS (H=0,50M)(ESCAVACAO, ALVENARIA DE PEDRA ARGAMASSADA, ALVENARIA, CHAPISCO, REBOCO E PINTURA PVA) | E59: SINAPI | F59: M | G59: 58 | H59: 0 | J59: =H59+I59 -> 0 | K59: 85.6809 | L59: =G59*K59 -> 4969.4922 | M59: =H59*K59 -> 0 | N59: =I59*K59 -> 0 | O59: =J59*K59 -> 0 | P59: =IF(O59<>L59,O59/L59,"") -> 0 | V59: 103.23 | W59: =V59-V59*$R$5 -> 85.6809
A60: 2.5.5 | C60: 93188 | D60: VERGA MOLDADA IN LOCO EM CONCRETO PARA PORTAS COM ATÉ 1,5 M DE VÃO. AF_03/2016 | E60: SINAPI | F60: M | G60: 24.4 | H60: 24.4 | J60: =H60+I60 -> 24.4 | K60: 74.39 | L60: =G60*K60 -> 1815.116 | M60: =H60*K60 -> 1815.116 | N60: =I60*K60 -> 0 | O60: =J60*K60 -> 1815.116 | P60: =IF(O60<>L60,O60/L60,"")
A61: 2.5.6 | C61: 93189 | D61: VERGA MOLDADA IN LOCO EM CONCRETO PARA PORTAS COM MAIS DE 1,5 M DE VÃO. AF_03/2016 | E61: SINAPI | F61: M | G61: 2.2 | H61: 2.2 | J61: =H61+I61 -> 2.2 | K61: 88.1 | L61: =G61*K61 -> 193.82 | M61: =H61*K61 -> 193.82 | N61: =I61*K61 -> 0 | O61: =J61*K61 -> 193.82 | P61: =IF(O61<>L61,O61/L61,"")
A62: 2.5.7 | C62: 93186 | D62: VERGA MOLDADA IN LOCO EM CONCRETO PARA JANELAS COM ATÉ 1,5 M DE VÃO. AF_03/2016 | E62: SINAPI | F62: M | G62: 19.4 | H62: 19.4 | J62: =H62+I62 -> 19.4 | K62: 75.2 | L62: =G62*K62 -> 1458.88 | M62: =H62*K62 -> 1458.88 | N62: =I62*K62 -> 0 | O62: =J62*K62 -> 1458.88 | P62: =IF(O62<>L62,O62/L62,"")
A63: 2.5.8 | C63: 93187 | D63: VERGA MOLDADA IN LOCO EM CONCRETO PARA JANELAS COM MAIS DE 1,5 M DE VÃO. AF_03/2016 | E63: SINAPI | F63: M | G63: 45.1 | H63: 45.1 | J63: =H63+I63 -> 45.1 | K63: 86.43 | L63: =G63*K63 -> 3897.993 | M63: =H63*K63 -> 3897.993 | N63: =I63*K63 -> 0 | O63: =J63*K63 -> 3897.993 | P63: =IF(O63<>L63,O63/L63,"")
A64: 2.5.9 | C64: 93196 | D64: CONTRAVERGA MOLDADA IN LOCO EM CONCRETO PARA VÃOS DE ATÉ 1,5 M DE COMPRIMENTO. AF_03/2016 | E64: SINAPI | F64: M | G64: 25.4 | H64: 25.4 | J64: =H64+I64 -> 25.4 | K64: 70.95 | L64: =G64*K64 -> 1802.13 | M64: =H64*K64 -> 1802.13 | N64: =I64*K64 -> 0 | O64: =J64*K64 -> 1802.13 | P64: =IF(O64<>L64,O64/L64,"")
A65: 2.5.10 | C65: 93197 | D65: CONTRAVERGA MOLDADA IN LOCO EM CONCRETO PARA VÃOS DE MAIS DE 1,5 M DE COMPRIMENTO. AF_03/2016 | E65: SINAPI | F65: M | G65: 36.42 | H65: 36.42 | J65: =H65+I65 -> 36.42 | K65: 79.34 | L65: =G65*K65 -> 2889.5628 | M65: =H65*K65 -> 2889.5628 | N65: =I65*K65 -> 0 | O65: =J65*K65 -> 2889.5628 | P65: =IF(O65<>L65,O65/L65,"")
A66: 2.6 6 ESQUADRIAS, FERRAGENS E VIDROS | L66: =SUM(L67:L78) -> 97054.049 | M66: =SUM(M67:M78) -> 0 | N66: =SUM(N67:N78) -> 0 | O66: =SUM(O67:O78) -> 0 | P66: =IF(O66<>L66,O66/L66,"") -> 0
A67: 2.6.1 | B67: 153844 | D67: PORTA MADEIRA DE LEI TIPO MACICA, INCLUSO ARO/FORRA, ALIZAR, DOBRADICAS, PARAFUSOS DE FIXACAO, EXCLUSIVE FECHADURA - FORNECIMENTO E | E67: SINAPI | F67: M2 | G67: 31.92 | H67: 0 | J67: =H67+I67 -> 0 | K67: 538.836 | L67: =G67*K67 -> 17199.645 | M67: =H67*K67 -> 0 | N67: =I67*K67 -> 0 | O67: =J67*K67 -> 0 | P67: =IF(O67<>L67,O67/L67,"") -> 0 | V67: 649.2 | W67: =V67-V67*$R$5 -> 538.836
A68: 2.6.2 | B68: 146852 | C68: 94559 | D68: JANELA DE ACO BASCULANTE, FIXACAO COM ARGAMASSA, SEM VIDROS, PADRONIZA DA. AF_07/2016 | E68: SINAPI | F68: M2 | G68: 59.11 | H68: 0 | J68: =H68+I68 -> 0 | K68: 622.5415 | L68: =G68*K68 -> 36798.428 | M68: =H68*K68 -> 0 | N68: =I68*K68 -> 0 | O68: =J68*K68 -> 0 | P68: =IF(O68<>L68,O68/L68,"") -> 0 | V68: 750.05 | W68: =V68-V68*$R$5 -> 622.5415
A69: 2.6.3 | B69: 145509 | D69: GRADIL NYLOFOR 3D, MALHA 20X5CM, 5MM 250X243 CM, PINTURA BRANCA, VERDE E PRETA, BELGO OU SIMILAR, INCLUSIVE POSTES (SECCAO 60X40MM E H=3,20M) E ACESSORIOS | E69: SUPLAN | F69: M2 | G69: 3 | H69: 0 | J69: =H69+I69 -> 0 | K69: 200.8683 | L69: =G69*K69 -> 602.6049 | M69: =H69*K69 -> 0 | N69: =I69*K69 -> 0 | O69: =J69*K69 -> 0 | P69: =IF(O69<>L69,O69/L69,"") -> 0 | V69: 242.01 | W69: =V69-V69*$R$5 -> 200.8683
A70: 2.6.4 | B70: 151970 | D70: MONTANTE E PAINEL BELGO LINHA NYLOFOR OU SIMILAR NA COR BRANCA, COM CHUMBADORES, INCLUSIVE POSTES (SECCAO 60X40MM) E ACESSORIOS | E70: SUPLAN | F70: M2 | G70: 0 | H70: 0 | J70: =H70+I70 -> 0 | K70: 242.4762 | L70: =G70*K70 -> 0 | M70: =H70*K70 -> 0 | N70: =I70*K70 -> 0 | O70: =J70*K70 -> 0 | P70: =IF(O70<>L70,O70/L70,"") | V70: 292.14 | W70: =V70-V70*$R$5 -> 242.4762
A71: 2.6.5 | B71: 151982 | D71: PORTAO EM GRADIL BELGO NYLOFOR 3D, DE CORRER,SOLDADO EM QUADRO DE TUBO GALVANIZADO 2" COM CANTONEIRA 3/4", MONTANTES EM TUBO DE FERRO GALVANIZADO DE 4", INCLUSIVE FERROLHO E RODIZIOS | E71: SUPLAN | F71: M2 | G71: 0 | H71: 0 | J71: =H71+I71 -> 0 | K71: 605.4435 | L71: =G71*K71 -> 0 | M71: =H71*K71 -> 0 | N71: =I71*K71 -> 0 | O71: =J71*K71 -> 0 | P71: =IF(O71<>L71,O71/L71,"") | V71: 729.45 | W71: =V71-V71*$R$5 -> 605.4435
A72: 2.6.6 | B72: 163453 | C72: 08492/ORS | D72: BARRA DE APOIO RETA, EM ACO INOX POLIDO PARA PCD, DIAMETRO =1 1/2" | E72: SINAPI | F72: M | G72: 3.4 | H72: 0 | J72: =H72+I72 -> 0 | K72: 126.2264 | L72: =G72*K72 -> 429.16976 | M72: =H72*K72 -> 0 | N72: =I72*K72 -> 0 | O72: =J72*K72 -> 0 | P72: =IF(O72<>L72,O72/L72,"") -> 0 | V72: 152.08 | W72: =V72-V72*$R$5 -> 126.2264
A73: 2.6.7 | B73: 133889 | C73: 72122 | D73: VIDRO FANTASIA TIPO CANELADO, ESPESSURA 4MM | E73: SINAPI | F73: M2 | G73: 59.11 | H73: 0 | J73: =H73+I73 -> 0 | K73: 203.8812 | L73: =G73*K73 -> 12051.418 | M73: =H73*K73 -> 0 | N73: =I73*K73 -> 0 | O73: =J73*K73 -> 0 | P73: =IF(O73<>L73,O73/L73,"") -> 0 | V73: 245.64 | W73: =V73-V73*$R$5 -> 203.8812
A74: 2.6.8 | B74: 138518 | C74: 5085 | D74: CADEADO SIMPLES, EM LATAO MACICO CROMADO, LARGURA DE 35 MM, HASTE DE ACO TEMPERADO, CEMENTADO (NAO LONGA), INCLUI 2 CHAVES | E74: SINAPI | F74: UN | G74: 2 | H74: 0 | J74: =H74+I74 -> 0 | K74: 17.8118 | L74: =G74*K74 -> 35.6236 | M74: =H74*K74 -> 0 | N74: =I74*K74 -> 0 | O74: =J74*K74 -> 0 | P74: =IF(O74<>L74,O74/L74,"") -> 0 | V74: 21.46 | W74: =V74-V74*$R$5 -> 17.8118
A75: 2.6.9 | B75: 163824 | D75: FECHADURA PARA PORTA EXTERNA , COM CILINDRO E MACANETA TIPO TACO DE GOLFE, PADRAO MEDIO - FORNECIMENTO E INSTALACAO | E75: SINAPI | F75: UN | G75: 17 | H75: 0 | J75: =H75+I75 -> 0 | K75: 118.8975 | L75: =G75*K75 -> 2021.2575 | M75: =H75*K75 -> 0 | N75: =I75*K75 -> 0 | O75: =J75*K75 -> 0 | P75: =IF(O75<>L75,O75/L75,"") -> 0 | V75: 143.25 | W75: =V75-V75*$R$5 -> 118.8975
A76: 2.6.10 | B76: 163827 | D76: FECHADURA DE EMBUTIR PARA PORTA EXTERNA / ENTRADA, MAQUINA 55 MM, COM CJ 60,39CILINDRO, MACANETA TIPOO TACO DE GOLFE E ESPELHO EM METAL CROMADO - NIVEL SEGURANCAMEDIO - COMPLETA | E76: SUPLAN | F76: UN | G76: 2 | H76: 0 | J76: =H76+I76 -> 0 | K76: 62.3828 | L76: =G76*K76 -> 124.7656 | M76: =H76*K76 -> 0 | N76: =I76*K76 -> 0 | O76: =J76*K76 -> 0 | P76: =IF(O76<>L76,O76/L76,"") -> 0 | V76: 75.16 | W76: =V76-V76*$R$5 -> 62.3828
A77: 2.6.11 | C77: 100701 | D77: PORTA DE FERRO, DE ABRIR, TIPO GRADE COM CHAPA, COM GUARNIÇÕES. AF_12/2019 | E77: SINAPI | F77: M2 | G77: 8.82 | H77: 0 | J77: =H77+I77 -> 0 | K77: 404.01 | L77: =G77*K77 -> 3563.3682 | M77: =H77*K77 -> 0 | N77: =I77*K77 -> 0 | O77: =J77*K77 -> 0 | P77: =IF(O77<>L77,O77/L77,"") -> 0
A78: 2.6.12 | C78: 7763 | D78: Gradil de ferro c/barra chata 2"x1/4" verticais espaç.10cm, montante em perfil seção quadrada de 1" vertical espaç.3 m, barras paralelas horizontais 2"x1/4", incl.portão, mureta h=30cm em alv.bloco e=19cm, chapiscada e rebocada, exclusive pintura | E78: ORSE | F78: m2 | G78: 47.1 | H78: 0 | J78: =H78+I78 -> 0 | K78: 514.39 | L78: =G78*K78 -> 24227.769 | M78: =H78*K78 -> 0 | N78: =I78*K78 -> 0 | O78: =J78*K78 -> 0 | P78: =IF(O78<>L78,O78/L78,"") -> 0
A79: 2.7 COBERTA | L79: =SUM(L80:L88) -> 92265.667 | M79: =SUM(M80:M88) -> 0 | N79: =SUM(N80:N88) -> 0 | O79: =SUM(O80:O88) -> 0 | P79: =IF(O79<>L79,O79/L79,"") -> 0
A80: 2.7.1 | B80: 133392 | C80: 92565 | D80: FABRICACAO E INTALACAO DE ESTRUTURA PONTALETADA DE MADEIRA NAO APAREL HADA PARA TELHADOS COM ATE 2 AGUAS E PARA TELHA CERAMICA OU DE CONCRET O, INCLUSO TRANSPORTE VERTICAL. | E80: SINAPI | F80: M2 | G80: 0 | H80: 0 | J80: =H80+I80 -> 0 | K80: 28.967 | L80: =G80*K80 -> 0 | M80: =H80*K80 -> 0 | N80: =I80*K80 -> 0 | O80: =J80*K80 -> 0 | P80: =IF(O80<>L80,O80/L80,"") | V80: 34.9 | W80: =V80-V80*$R$5 -> 28.967
A81: 2.7.2 | B81: 133371 | C81: 92542 | D81: TRAMA DE MADEIRA COMPOSTA POR RIPAS, CAIBROS E TERCAS PARA TELHADOS DE MAIS QUE 2 AGUAS PARA TELHA CERAMICA CAPA-CANAL, INCLUSO TRANSPORTE V ERTICAL. AF_12/2015 | E81: SINAPI | F81: M2 | G81: 672.85 | H81: 0 | J81: =H81+I81 -> 0 | K81: 74.43025 | L81: =G81*K81 -> 50080.394 | M81: =H81*K81 -> 0 | N81: =I81*K81 -> 0 | O81: =J81*K81 -> 0 | P81: =IF(O81<>L81,O81/L81,"") -> 0 | V81: 89.675 | W81: =V81-V81*$R$5 -> 74.43025
A82: 2.7.3 | B82: 146764 | C82: 94445 | D82: TELHAMENTO COM TELHA CERAMICA CAPA- CANAL, TIPO PLAN, COM ATE 2 AGUAS, INCLUSO TRANSPORTE VERTICAL. | E82: SINAPI | F82: M2 | G82: 672.85 | H82: 0 | J82: =H82+I82 -> 0 | K82: 30.544 | L82: =G82*K82 -> 20551.53 | M82: =H82*K82 -> 0 | N82: =I82*K82 -> 0 | O82: =J82*K82 -> 0 | P82: =IF(O82<>L82,O82/L82,"") -> 0 | V82: 36.8 | W82: =V82-V82*$R$5 -> 30.544
A83: 2.7.4 | B83: 146775 | C83: 94221 | D83: CUMEEIRA PARA TELHA CERAMICA EMBOCADA COM ARGAMASSA TRACO 1:2:9 (CIMEN TO, CAL E AREIA) PARA TELHADOS COM ATE 2 AGUAS, INCLUSO TRANSPORTE VER TICAL. AF_06/2016 | E83: SINAPI | F83: M | G83: 64.61 | H83: 0 | J83: =H83+I83 -> 0 | K83: 16.6 | L83: =G83*K83 -> 1072.526 | M83: =H83*K83 -> 0 | N83: =I83*K83 -> 0 | O83: =J83*K83 -> 0 | P83: =IF(O83<>L83,O83/L83,"") -> 0 | V83: 20 | W83: =V83-V83*$R$5 -> 16.6
A84: 2.7.5 | B84: 163731 | D84: ALGEROZ/RUFO DE CONCRETO ARMADO FCK=20MPA L=40CM, E=5CM | E84: SINAPI | F84: M | G84: 41.57 | H84: 0 | J84: =H84+I84 -> 0 | K84: 18.6418 | L84: =G84*K84 -> 774.93963 | M84: =H84*K84 -> 0 | N84: =I84*K84 -> 0 | O84: =J84*K84 -> 0 | P84: =IF(O84<>L84,O84/L84,"") -> 0 | V84: 22.46 | W84: =V84-V84*$R$5 -> 18.6418
A85: 2.7.6 | B85: 146757 | C85: 94224 | D85: EMBOCAMENTO COM ARGAMASSA TRACO 1:2:9 (CIMENTO, CAL E AREIA). AF_06/20 16 | E85: SINAPI | F85: M | G85: 122.62 | H85: 0 | J85: =H85+I85 -> 0 | K85: 18.592 | L85: =G85*K85 -> 2279.751 | M85: =H85*K85 -> 0 | N85: =I85*K85 -> 0 | O85: =J85*K85 -> 0 | P85: =IF(O85<>L85,O85/L85,"") -> 0 | V85: 22.4 | W85: =V85-V85*$R$5 -> 18.592
A86: 2.7.7 | B86: 161738 | D86: IMPERMEABILIZACAO COM APLICACAO DE ARGAMASSA POLIMERICA TIPO DENVERTEC 100 OU SIMILAR | E86: SINAPI | F86: M2 | G86: 8.31 | H86: 0 | J86: =H86+I86 -> 0 | K86: 38.3377 | L86: =G86*K86 -> 318.58629 | M86: =H86*K86 -> 0 | N86: =I86*K86 -> 0 | O86: =J86*K86 -> 0 | P86: =IF(O86<>L86,O86/L86,"") -> 0 | V86: 46.19 | W86: =V86-V86*$R$5 -> 38.3377
A87: 2.7.8 | B87: 153541 | C87: 96111 | D87: FORRO EM REGUAS DE PVC, PARA AMBIENTES RESIDENCIAIS, INCLUSIVE ESTRUTURA DE FIXACAO. AF_05/2017_P | E87: SINAPI | F87: M2 | G87: 0 | H87: 0 | J87: =H87+I87 -> 0 | K87: 62.43675 | L87: =G87*K87 -> 0 | M87: =H87*K87 -> 0 | N87: =I87*K87 -> 0 | O87: =J87*K87 -> 0 | P87: =IF(O87<>L87,O87/L87,"") | V87: 75.225 | W87: =V87-V87*$R$5 -> 62.43675
A88: 2.7.9 | C88: 96113 | D88: FORRO EM PLACAS DE GESSO, PARA AMBIENTES COMERCIAIS. AF_05/2017_P | E88: SINAPI | F88: M2 | G88: 558.05 | H88: 0 | J88: =H88+I88 -> 0 | K88: 30.8 | L88: =G88*K88 -> 17187.94 | M88: =H88*K88 -> 0 | N88: =I88*K88 -> 0 | O88: =J88*K88 -> 0 | P88: =IF(O88<>L88,O88/L88,"") -> 0
A89: 2.8 REVESTIMENTO E FORRO | L89: =SUM(L90:L97) -> 88519.737 | M89: =SUM(M90:M97) -> 0 | N89: =SUM(N90:N97) -> 32107.028 | O89: =SUM(O90:O97) -> 32107.028 | P89: =IF(O89<>L89,O89/L89,"") -> 0.36271038
A90: 2.8.1 | B90: 160114 | D90: CHAPISCO EM PAREDES VERTICAIS TRACO 1:3 (CIMENTO E AREIA), ESPESSURA 0,5CM, PREPARO MECANICO; | E90: SINAPI | F90: M2 | G90: 1981.51 | H90: 0 | I90: ='MEMORIAL DE CÁLCULOS'!J101 -> 1668.56 | J90: =H90+I90 -> 1668.56 | K90: 2.9714 | L90: =G90*K90 -> 5887.8588 | M90: =H90*K90 -> 0 | N90: =I90*K90 -> 4957.9592 | O90: =J90*K90 -> 4957.9592 | P90: =IF(O90<>L90,O90/L90,"") -> 0.84206489 | V90: 3.58 | W90: =V90-V90*$R$5 -> 2.9714
A91: 2.8.2 | B91: 161080 | C91: S77005 | D91: REBOCO VERTICAL, EM ARGAMASSA TRACO 1:2:8 - PREPARO MECANICO COM BETONEIRA 400L, ESPESSURA DE 20MM | E91: SINAPI | F91: M2 | G91: 1162.37 | H91: 0 | I91: ='MEMORIAL DE CÁLCULOS'!J104 -> 849.42 | J91: =H91+I91 -> 849.42 | K91: 18.0027 | L91: =G91*K91 -> 20925.798 | M91: =H91*K91 -> 0 | N91: =I91*K91 -> 15291.853 | O91: =J91*K91 -> 15291.853 | P91: =IF(O91<>L91,O91/L91,"") -> 0.73076559 | V91: 21.69 | W91: =V91-V91*$R$5 -> 18.0027
A92: 2.8.3 | B92: 160138 | D92: EMBOCO, PARA RECEBIMENTO DE CERAMICA, EM ARGAMASSA TRAO 1:2:8, PREPARO MECANICO COM BETONEIRA 400L, APLICADO MANUALMENTE, ESPESSURA DE | E92: SINAPI | F92: M2 | G92: 819.14 | H92: 0 | I92: ='MEMORIAL DE CÁLCULOS'!J107 -> 819.14 | J92: =H92+I92 -> 819.14 | K92: 14.4752 | L92: =G92*K92 -> 11857.215 | M92: =H92*K92 -> 0 | N92: =I92*K92 -> 11857.215 | O92: =J92*K92 -> 11857.215 | P92: =IF(O92<>L92,O92/L92,"") | V92: 17.44 | W92: =V92-V92*$R$5 -> 14.4752
A93: 2.8.4 | B93: 160279 | D93: REVESTIMENTO PARA MOSAICO MONDRIAN EM CERAMICA 10 X 10 CM, ELIZABETH, DIVERSAS CORES, PEI -5, OU SIMILAR, ASSENTADA COM ARGAMASSA COLANTE AC II E REJUNTAMENTO INDUSTRIALIZADO | E93: SINAPI | F93: M2 | G93: 82.55 | H93: 0 | J93: =H93+I93 -> 0 | K93: 87.7476 | L93: =G93*K93 -> 7243.5644 | M93: =H93*K93 -> 0 | N93: =I93*K93 -> 0 | O93: =J93*K93 -> 0 | P93: =IF(O93<>L93,O93/L93,"") -> 0 | V93: 105.72 | W93: =V93-V93*$R$5 -> 87.7476
A94: 2.8.5 | B94: 161082 | C94: S77022 | D94: REVESTIMENTO EM CERAMICA 10 X 10 CM, ELIZABETH, PEI -5, OU SIMILAR, ASSENTADA COM ARGAMASSA COLANTE AC II, REJUNTAMENTO. INDUSTRIALIZADO | E94: SINAPI | F94: M2 | G94: 505.69 | H94: 0 | J94: =H94+I94 -> 0 | K94: 53.1947 | L94: =G94*K94 -> 26900.028 | M94: =H94*K94 -> 0 | N94: =I94*K94 -> 0 | O94: =J94*K94 -> 0 | P94: =IF(O94<>L94,O94/L94,"") -> 0 | V94: 64.09 | W94: =V94-V94*$R$5 -> 53.1947
A95: 2.8.6 | B95: 161922 | D95: CHAPISCO TETO/HORIZONTAL APLICADO COM COLHER DE PEDREIRO. ARGAMASSA TRACO 1:3 COM PREPARO EM BETONEIRA 400L | E95: SINAPI | F95: M2 | G95: 14.18 | H95: 0 | J95: =H95+I95 -> 0 | K95: 4.2579 | L95: =G95*K95 -> 60.377022 | M95: =H95*K95 -> 0 | N95: =I95*K95 -> 0 | O95: =J95*K95 -> 0 | P95: =IF(O95<>L95,O95/L95,"") -> 0 | V95: 5.13 | W95: =V95-V95*$R$5 -> 4.2579
A96: 2.8.7 | B96: 161923 | C96: 87532 | D96: REBOCO TETO/HORIZONTAL, EM ARGAMASSA TRACO 1:2:8, ESPESSURA DE 20MM, COM EXECUCAO DE TALISCAS. | E96: SINAPI | F96: M2 | G96: 14.18 | H96: 0 | J96: =H96+I96 -> 0 | K96: 30.876 | L96: =G96*K96 -> 437.82168 | M96: =H96*K96 -> 0 | N96: =I96*K96 -> 0 | O96: =J96*K96 -> 0 | P96: =IF(O96<>L96,O96/L96,"") -> 0 | V96: 37.2 | W96: =V96-V96*$R$5 -> 30.876
A97: 2.8.8 | C97: 87272 | D97: REVESTIMENTO CERÂMICO PARA PAREDES INTERNAS COM PLACAS TIPO ESMALTADA EXTRA DE DIMENSÕES 33X45 CM APLICADAS EM AMBIENTES DE ÁREA MENOR QUE 5 M² NA ALTURA INTEIRA DAS PAREDES. AF_06/2014 | E97: SINAPI | F97: M2 | G97: 230.9 | H97: 0 | J97: =H97+I97 -> 0 | K97: 65.86 | L97: =G97*K97 -> 15207.074 | M97: =H97*K97 -> 0 | N97: =I97*K97 -> 0 | O97: =J97*K97 -> 0 | P97: =IF(O97<>L97,O97/L97,"") -> 0
A98: 2.9 PINTURA | L98: =SUM(L99:L110) -> 64264.518 | M98: =SUM(M99:M110) -> 0 | N98: =SUM(N99:N110) -> 0 | O98: =SUM(O99:O110) -> 0 | P98: =IF(O98<>L98,O98/L98,"") -> 0
A99: 2.9.1 | B99: 162595 | D99: EMASSAMENTO COM MASSA ACRILICA, DUAS D E M A O S , E M P A R E D E S INTERNAS/EXTERNAS/TETO, INCLUSIVE LIXAMENTO | E99: SINAPI | F99: M2 | G99: 407.76 | H99: 0 | J99: =H99+I99 -> 0 | K99: 27.8548 | L99: =G99*K99 -> 11358.073 | M99: =H99*K99 -> 0 | N99: =I99*K99 -> 0 | O99: =J99*K99 -> 0 | P99: =IF(O99<>L99,O99/L99,"") -> 0 | V99: 33.56 | W99: =V99-V99*$R$5 -> 27.8548
A100: 2.9.2 | B100: 136253 | C100: 88485 | D100: APLICACAO DE FUNDO SELADOR ACRILICO EM PAREDES, UMA DEMAO. AF_06/2014 | E100: SINAPI | F100: M2 | G100: 1162.37 | H100: 0 | J100: =H100+I100 -> 0 | K100: 2.158 | L100: =G100*K100 -> 2508.3945 | M100: =H100*K100 -> 0 | N100: =I100*K100 -> 0 | O100: =J100*K100 -> 0 | P100: =IF(O100<>L100,O100/L100,"") -> 0 | V100: 2.6 | W100: =V100-V100*$R$5 -> 2.158
...

Sheet MEMORIAL DE CÁLCULOS
A1: =[14]ORÇAMENTO!A1:J1 -> ESTADO DA PARAÍBA
A2: ESTADO DA PARAÍBA
A3: PREFEITURA MUNICIPAL DE COREMAS
A4: ='BM-03'!A3 -> CONTRATO Nº 10004/2023
A5: ='BM-03'!A4 -> OBRA: CONSTRUÇÃO DE UMA UNIDADE ESCOLAR DE 06 (SEIS) SALAS DE AULA PARA O MUNICÍPIO DE COREMAS-PB
A6: MEMORIAL DE CÁLCULOS - BM-03
A7: ITEM | B7: DESCRIÇÃO | C7: DADOS | G7: Descontos | I7: RESULTADO | K7: UN.
C8: Quantid. | D8: Comprim. (m) | E8: Largura (m) | F8: Altura (m) | G8: Descrição | H8: Valor | I8: PARCIAL | J8: GERAL
A9: 1 | B9: ETAPA 01: GERAL
A10: 1.1 | B10: ADMINISTRAÇÃO LOCAL
A11: ='BM-03'!A11 -> 1.1.1 | B11: ='BM-03'!D11 -> ADMINSTRACAO LOCAL - PESSOAL | J11: =ROUND(SUM(J12:J12),2) -> 1.36 | K11: ='BM-03'!F11 -> UN
B12: Proporcional ao valor da medição | C12: 1.36 | J12: =C12 -> 1.36
A14: ='BM-03'!A12 -> 1.1.2 | B14: ='BM-03'!D12 -> ADMINISTRACAO LOCAL - DESPESAS GERAIS MENSAIS | J14: =ROUND(SUM(J15:J15),2) -> 1.36 | K14: ='BM-03'!F12 -> UN
B15: Proporcional ao valor da medição | C15: 1.36 | J15: =C15 -> 1.36
A17: ='BM-03'!A13 -> 1.1.3 | B17: ='BM-03'!D13 -> ADMINISTRACAO LOCAL - DESPESAS GERAIS FIXAS | J17: =ROUND(SUM(J18:J18),2) -> 0.17 | K17: ='BM-03'!F13 -> UN
B18: Proporcional ao valor da medição | C18: 0.17 | J18: =C18 -> 0.17
A20: ='BM-03'!A14 -> 1.1.4 | B20: ='BM-03'!D14 -> ADMINISTRACAO LOCAL - VECULOS E EQUIPAMENTOS | J20: =ROUND(SUM(J21:J21),2) -> 1.36 | K20: ='BM-03'!F14 -> UN
B21: Proporcional ao valor da medição | C21: 1.36 | J21: =C21 -> 1.36
A23: ='BM-03'!A15 -> 1.1.5 | B23: ='BM-03'!D15 -> ADMINISTRACAO LOCAL - MOVEIS E UTENSILIOS | J23: =ROUND(SUM(J24:J24),2) -> 0.17 | K23: ='BM-03'!F15 -> UN
B24: Proporcional ao valor da medição | C24: 0.17 | J24: =C24 -> 0.17
A26: 2 | B26: ETAPA 02: CONSTRUÇÃO DA ESCOLA
A27: 2.2 | B27: MOVIMENTO DE TERRA
A28: ='BM-03'!A32 -> 2.2.3 | B28: ='BM-03'!D32 -> ATERRO DO CAIXAO COM AQUISICAO DO MATERIAL/AREIA, APILOADO EM CAMADAS DE 0,20M | J28: =ROUND(SUM(J29:J29),2) -> 55.31 | K28: ='BM-03'!F32 -> M3
B29: Aterro da área entre murada e escola, considerando uma média de 0,60m abaixo das calçadas de contorno, sendo medido em torno de 10% restantes: | J29: =0.1*(SUM(J30:J33)) -> 55.306612
B30: Lateral esquerda | C30: 1 | D30: 53.3 | E30: 8 | F30: 0.3 | I30: =D30*E30*F30 -> 127.92 | J30: =C30*I30 -> 127.92
B31: Lateral direita | C31: 1 | D31: 19.81 | E31: 1.8 | F31: 0.4 | I31: =D31*E31*F31 -> 14.2632 | J31: =C31*I31 -> 14.2632
B32: Fundos bloco pedagógico | C32: 1 | D32: 12.35 | E32: 5 | F32: 0.8 | I32: =D32*E32*F32 -> 49.4 | J32: =C32*I32 -> 49.4
B33: Área de recreação + fundos | C33: 1 | D33: 29.65 | E33: =8.3+5 -> 13.3 | F33: 0.91666667 | I33: =D33*E33*F33 -> 361.48292 | J33: =C33*I33 -> 361.48292
A35: 2.3 | B35: INFRAESTRUTURA
A36: ='BM-03'!A35 -> 2.3.2 | B36: ='BM-03'!D35 -> ALVENARIA DE 1 VEZ VEDACAO COM BLOCOS CERAMICO FURADOS 9 X 19 X 19 CM FUROS HORIZONTAIS, ESPESSURA DA PAREDE 19 CM, JUNTAS DE 10 MM COM ARGAMASSA TRACO 1:2:8 (CIMENTO, CAL E AREIA MEDIA) | J36: =ROUND(SUM(J37:J39),2) -> 97.73 | K36: ='BM-03'!F35 -> M2
B37: Embasamento recreio | C37: 2 | D37: 12 | F37: 0.91666667 | I37: =D37*F37 -> 11 | J37: =C37*I37 -> 22
C38: 5 | D38: 6 | F38: 0.91666667 | I38: =D38*F38 -> 5.5 | J38: =C38*I38 -> 27.5
B39: Embasamento adicional da murada na parte dos fundos para compensar o desnível do terreno | C39: 1 | D39: =31+24.29+5 -> 60.29 | F39: 0.8 | I39: =D39*F39 -> 48.232 | J39: =C39*I39 -> 48.232
A41: 2.4 | B41: SUPER-ESTRUTURA
A42: ='BM-03'!A41 -> 2.4.1 | B42: ='BM-03'!D41 -> CONCRETO ARMADO (PREPARO E LANCAMENTO) PARA VIGA COM FCK>=30MPA, COM FORMA EM CHAPA DE MADEIRA COM- P E N S A D A R E S I N A D A , C O M APROVEITAMENTO DE 3 VEZES COM BETONEIRA - | J42: =ROUND(SUM(J43:J43),2) -> 24.23 | K42: ='BM-03'!F41 -> M3
B43: Vigas térreo, conforme projeto estrutural (24,23 m³) | C43: =24.23 -> 24.23 | J43: =C43 -> 24.23
A45: ='BM-03'!A49 -> 2.4.9 | B45: ='BM-03'!D49 -> MONTAGEM E DESMONTAGEM DE FÔRMA DE LAJE MACIÇA COM ÁREA MÉDIA MAIOR QUE 20 M², PÉ-DIREITO SIMPLES, EM CHAPA DE MADEIRA COMPENSADA RESINADA, 2 UTILIZAÇÕES | J45: =ROUND(SUM(J46:J46),2) -> 560.03 | K45: ='BM-03'!F49 -> M2
B46: Conforme projeto estrutural | C46: 560.03 | J46: =C46 -> 560.03
A48: ='BM-03'!A50 -> 2.4.10 | B48: ='BM-03'!D50 -> ARMAÇÃO DE LAJE DE UMA ESTRUTURA CONVENCIONAL DE CONCRETO ARMADO EM UMA EDIFICAÇÃO TÉRREA OU SOBRADO UTILIZANDO AÇO CA-60 DE 5,0 MM - MONTAGEM. AF_12/2015 | J48: =ROUND(SUM(J49:J49),2) -> 8.8 | K48: ='BM-03'!F50 -> KG
B49: Conforme projeto estrutural | C49: 8.8 | J49: =C49 -> 8.8
A51: ='BM-03'!A51 -> 2.4.11 | B51: ='BM-03'!D51 -> ARMAÇÃO DE LAJE DE UMA ESTRUTURA CONVENCIONAL DE CONCRETO ARMADO EM UMA EDIFICAÇÃO TÉRREA OU SOBRADO UTILIZANDO AÇO CA-50 DE 6,3 MM - MONTAGEM. AF_12/2015 | J51: =ROUND(SUM(J52:J52),2) -> 1103.2 | K51: ='BM-03'!F51 -> KG
B52: Conforme projeto estrutural | C52: 1103.2 | J52: =C52 -> 1103.2
A54: ='BM-03'!A52 -> 2.4.12 | B54: ='BM-03'!D52 -> ARMAÇÃO DE LAJE DE UMA ESTRUTURA CONVENCIONAL DE CONCRETO ARMADO EM UMA EDIFICAÇÃO TÉRREA OU SOBRADO UTILIZANDO AÇO CA-50 DE 8,0 MM - MONTAGEM. AF_12/2015 | J54: =ROUND(SUM(J55:J55),2) -> 740 | K54: ='BM-03'!F52 -> KG
B55: Conforme projeto estrutural | C55: 740 | J55: =C55 -> 740
A57: ='BM-03'!A53 -> 2.4.13 | B57: ='BM-03'!D53 -> ARMAÇÃO DE LAJE DE UMA ESTRUTURA CONVENCIONAL DE CONCRETO ARMADO EM UMA EDIFICAÇÃO TÉRREA OU SOBRADO UTILIZANDO AÇO CA-50 DE 10,0 MM - MONTAGEM. AF_12/2015 | J57: =ROUND(SUM(J58:J58),2) -> 227.6 | K57: ='BM-03'!F53 -> KG
B58: Conforme projeto estrutural | C58: 227.6 | J58: =C58 -> 227.6
A60: ='BM-03'!A54 -> 2.4.14 | B60: ='BM-03'!D54 -> CONCRETAGEM DE VIGAS E LAJES, FCK=20 MPA, PARA LAJES MACIÇAS OU NERVURADAS COM USO DE BOMBA EM EDIFICAÇÃO COM ÁREA MÉDIA DE LAJES MAIOR QUE 20 M² - LANÇAMENTO, ADENSAMENTO E ACABAMENTO. AF_12/2015 | J60: =ROUND(SUM(J61:J61),2) -> 50.36 | K60: ='BM-03'!F54 -> M3
B61: Conforme projeto estrutural | C61: 50.36 | J61: =C61 -> 50.36
A63: 2.5 | B63: PAREDES E PAINEIS
A64: ='BM-03'!A56 -> 2.5.1 | B64: ='BM-03'!D56 -> ALVENARIA DE 1/2 VEZ VEDACAO COM BLOCOS CERAMICO FURADOS 9 X 19 X 19 CM FUROS HORIZONTAIS, ESPESSURA DA PAREDE 9 CM, JUNTAS DE 10 MM COM ARGAMASSA TRACO 1:2:8 (CIMENTO, CAL E | J64: =ROUND(SUM(J65:J65),2) -> 83.43 | K64: ='BM-03'!F56 -> M2
B65: 10% restantes da alvenaria de vedação calculada abaixo: | J65: =ROUND(0.1*(SUM(J66:J95)),2) -> 83.43
B66: Bloco Pedagógico - Salas de Aula | C66: 6 | D66: 7.2 | F66: 3.2 | I66: =D66*F66 -> 23.04 | J66: =C66*I66 -> 138.24
C67: 6 | D67: 7.53 | F67: 3.2 | I67: =D67*F67 -> 24.096 | J67: =C67*I67 -> 144.576
C68: 5 | D68: 7.35 | F68: 3.2 | I68: =D68*F68 -> 23.52 | J68: =C68*I68 -> 117.6
C69: 1 | D69: 9.5 | F69: 3.2 | I69: =D69*F69 -> 30.4 | J69: =C69*I69 -> 30.4
C70: 1 | D70: 12.05 | F70: 3.2 | I70: =D70*F70 -> 38.56 | J70: =C70*I70 -> 38.56
C71: 1 | D71: 24.29 | F71: 2.6 | I71: =D71*F71 -> 63.154 | J71: =C71*I71 -> 63.154
B72: Bloco Administrativo - ENTRADA | C72: 1 | D72: 2.25 | F72: 2.6 | I72: =D72*F72 -> 5.85 | J72: =C72*I72 -> 5.85
C73: 2 | D73: 2.95 | F73: 2.6 | I73: =D73*F73 -> 7.67 | J73: =C73*I73 -> 15.34
C74: 1 | D74: 1.25 | F74: 2.6 | I74: =D74*F74 -> 3.25 | J74: =C74*I74 -> 3.25
B75: Bloco Administrativo | C75: 1 | D75: 8.45 | F75: 3.2 | I75: =D75*F75 -> 27.04 | J75: =C75*I75 -> 27.04
C76: 2 | D76: 3.5 | F76: 3.2 | I76: =D76*F76 -> 11.2 | J76: =C76*I76 -> 22.4
C77: 2 | D77: 5.4 | F77: 3.2 | I77: =D77*F77 -> 17.28 | J77: =C77*I77 -> 34.56
C78: 2 | D78: 2.55 | F78: 3.2 | I78: =D78*F78 -> 8.16 | J78: =C78*I78 -> 16.32
C79: 1 | D79: 10.88 | F79: 3.2 | I79: =D79*F79 -> 34.816 | J79: =C79*I79 -> 34.816
C80: 1 | D80: 6.26 | F80: 3.2 | I80: =D80*F80 -> 20.032 | J80: =C80*I80 -> 20.032
C81: 3 | D81: 2.48 | F81: 3.2 | I81: =D81*F81 -> 7.936 | J81: =C81*I81 -> 23.808
C82: 2 | D82: 2.7 | F82: 3.2 | I82: =D82*F82 -> 8.64 | J82: =C82*I82 -> 17.28
C83: 1 | D83: 2.65 | F83: 3.2 | I83: =D83*F83 -> 8.48 | J83: =C83*I83 -> 8.48
C84: 2 | D84: 1.2 | F84: 3.2 | I84: =D84*F84 -> 3.84 | J84: =C84*I84 -> 7.68
C85: 1 | D85: 2.38 | F85: 3.2 | I85: =D85*F85 -> 7.616 | J85: =C85*I85 -> 7.616
C86: 3 | D86: 2 | F86: 3.2 | I86: =D86*F86 -> 6.4 | J86: =C86*I86 -> 19.2
C87: 1 | D87: 4.4 | F87: 3.2 | I87: =D87*F87 -> 14.08 | J87: =C87*I87 -> 14.08
C88: 1 | D88: 1.12 | F88: 3.2 | I88: =D88*F88 -> 3.584 | J88: =C88*I88 -> 3.584
B89: Bloco Administrativo - cozinha | C89: 2 | D89: 8.78 | F89: 3.2 | I89: =D89*F89 -> 28.096 | J89: =C89*I89 -> 56.192
C90: 3 | D90: 4.03 | F90: 3.2 | I90: =D90*F90 -> 12.896 | J90: =C90*I90 -> 38.688
C91: 1 | D91: 1.95 | F91: 3.2 | I91: =D91*F91 -> 6.24 | J91: =C91*I91 -> 6.24
C92: 1 | D92: 3.15 | F92: 3.2 | I92: =D92*F92 -> 10.08 | J92: =C92*I92 -> 10.08
C93: 1 | D93: 1.8 | F93: 3.2 | I93: =D93*F93 -> 5.76 | J93: =C93*I93 -> 5.76
B94: Desconto esquadrias | C94: =-'BM-03'!G68 -> -59.11 | J94: =C94 -> -59.11
B95: Desconto cobogós | C95: =-'BM-03'!G57 -> -37.44 | J95: =C95 -> -37.44
A97: ='BM-03'!A58 -> 2.5.3 | B97: ='BM-03'!D58 -> MURO EM ALVENARIA DE 1/2 VEZ COM TIJOLOS DE 8 FUROS COM LOCACAO E I N C L U S I V E E X E C U C A O D E GABARITO,ESCAVACAO MANUAL DE VALAS, ALVENARIA DE PEDRA ARGAMASSADA, EMBASAMENTO EM ALVENARIA DE 1 VEZ, CONCRETO ARMADOPARA RADIER E CINTA SUPERIOR, COLUNAS DE CONCRETO ARMADO A CADA 3,0M, CHAPISCADO, REBOCADO, SELADOR ACRILICO EPINTADO, | J97: =ROUND(SUM(J98:J98),2) -> 120 | K97: ='BM-03'!F58 -> M
B98: */- 80% do perímetro de murada (0,80*(60,0*2+30,0)) | C98: =(0.8*(60*2+30)) -> 120 | J98: =C98 -> 120
A100: 2.8 | B100: REVESTIMENTO E FORRO
A101: ='BM-03'!A90 -> 2.8.1 | B101: ='BM-03'!D90 -> CHAPISCO EM PAREDES VERTICAIS TRACO 1:3 (CIMENTO E AREIA), ESPESSURA 0,5CM, PREPARO MECANICO; | J101: =ROUND(SUM(J102:J102),2) -> 1668.56 | K101: ='BM-03'!F90 -> M2
B102: 2x Alvenarias medidas no acumulado | C102: =2*'BM-03'!J56 -> 1668.56 | J102: =C102 -> 1668.56
A104: ='BM-03'!A91 -> 2.8.2 | B104: ='BM-03'!D91 -> REBOCO VERTICAL, EM ARGAMASSA TRACO 1:2:8 - PREPARO MECANICO COM BETONEIRA 400L, ESPESSURA DE 20MM | J104: =ROUND(SUM(J105:J105),2) -> 849.42 | K104: ='BM-03'!F91 -> M2
B105: Igual ao chapisco menos emboço medidos | C105: =J101-J107 -> 849.42 | J105: =C105 -> 849.42
A107: ='BM-03'!A92 -> 2.8.3 | B107: ='BM-03'!D92 -> EMBOCO, PARA RECEBIMENTO DE CERAMICA, EM ARGAMASSA TRAO 1:2:8, PREPARO MECANICO COM BETONEIRA 400L, APLICADO MANUALMENTE, ESPESSURA DE | J107: =ROUND(SUM(J108:J108),2) -> 819.14 | K107: ='BM-03'!F92 -> M2
B108: Igual ao somatório de revestimentos cerâmicos | C108: ='BM-03'!G93+'BM-03'!G94+'BM-03'!G97 -> 819.14 | J108: =C108 -> 819.14
A110: 3 | B110: ETAPA 03: RECREIO COBERTO
A111: 3.1 | B111: SERVICOS PRELIMINARES
A112: ='BM-03'!A202 -> 3.1.1 | B112: ='BM-03'!D202 -> LOCACAO CONVENCIONAL DE OBRA, ATRAVES DE GABARITO DE TABUAS CORRIDAS PONTALETADAS, COM REAPROVEITAMENTO DE 3 VEZES - | J112: =ROUND(SUM(J113:J113),2) -> 72 | K112: ='BM-03'!F202 -> M2
B113: Área do recreio | C113: 1 | D113: 12 | E113: 6 | I113: =D113*E113 -> 72 | J113: =C113*I113 -> 72
A115: 3.2 | B115: MOVIMENTO DE TERRA
A116: ='BM-03'!A204 -> 3.2.1 | B116: ='BM-03'!D204 -> ESCAVACAO MANUAL DE VALA EM MATERIAL DE QUALQUER CATEGORIA, EXCETO ROCHA COM PROFUNDIDADE ATE 2M. | J116: =ROUND(SUM(J117:J118),2) -> 18.24 | K116: ='BM-03'!F204 -> M3
B117: Sapatas | C117: 11 | D117: 0.8 | E117: 0.8 | F117: 1.204 | I117: =D117*E117*F117 -> 0.77056 | J117: =C117*I117 -> 8.47616
B118: Valas | C118: 1 | D118: =(3*5.8 + 2*11.6) -> 40.6 | E118: 0.4 | F118: 0.601 | I118: =D118*E118*F118 -> 9.76024 | J118: =C118*I118 -> 9.76024
A120: ='BM-03'!A205 -> 3.2.2 | B120: ='BM-03'!D205 -> EMBASAMENTO C/PEDRA ARGAMASSADA UTILIZANDO ARG.CIM/AREIA 1:4 | J120: =ROUND(SUM(J121:J121),2) -> 8.64 | K120: ='BM-03'!F205 -> M3
B121: Preenchimento de valas | C121: 1 | D121: =(3*5.8 + 2*11.6) -> 40.6 | E121: 0.4 | F121: 0.532 | I121: =D121*E121*F121 -> 8.63968 | J121: =C121*I121 -> 8.63968
...
