Workbook
Name JR_PAGE_ANCHOR_0_1: ORCAMENTO!$A$1
Name JR_PAGE_ANCHOR_1_1: RESUMO!$A$1
Name JR_PAGE_ANCHOR_2_1: COMPOSICOES!$A$1
Name JR_PAGE_ANCHOR_3_1: 'COMPOSICOES AUXILIARES'!$A$1
Name JR_PAGE_ANCHOR_4_1: CRONOGRAMA!$A$1
Name JR_PAGE_ANCHOR_5_1: BDI!$A$1
Name JR_PAGE_ANCHOR_6_1: 'ENCARGOS SOCIAIS'!$A$1

Sheet ORCAMENTO
A3: ITEM | B3: CÓDIGO | C3: DESCRIÇÃO | D3: FONTE | E3: UND | F3: QUANTIDADE | G3: PREÇO UNIT. S/BDI | H3: PREÇO TOTAL R$
A4: 1 | B4: SERVIÇOS PRELIMINARES | H4: =SUM(H5:H8) -> 7244.08
A5: 1.1 | B5: 97634 | C5: DEMOLIÇÃO DE REVESTIMENTO CERÂMICO, DE FORMA MECANIZADA COM MARTELETE, SEM REAPROVEITAMENTO. AF_12/2017 | D5: SINAPI | E5: M2 | F5: 565.78 | G5: 7.45 | H5: 4215.06
A6: 1.2 | B6: 97644 | C6: REMOÇÃO DE PORTAS, DE FORMA MANUAL, SEM REAPROVEITAMENTO. AF_12/2017 | D6: SINAPI | E6: M2 | F6: 30.66 | G6: 5.45 | H6: 167.1
A7: 1.3 | B7: 97663 | C7: REMOÇÃO DE LOUÇAS, DE FORMA MANUAL, SEM REAPROVEITAMENTO. AF_12/2017 | D7: SINAPI | E7: UN | F7: 7 | G7: 7.2 | H7: 50.4
A8: 1.4 | B8: 74209/001 | C8: PLACA DE OBRA EM CHAPA DE ACO GALVANIZADO | D8: SINAPI | E8: M2 | F8: 8 | G8: 351.44 | H8: 2811.52
B9: ESCOLA | H9: =H10+H14+H22+H28+H32+H39+H42+H61 -> 241463.99
A10: 2.0 | B10: PISO | H10: =SUM(H11:H13) -> 40404.21
A11: 2.1 | B11: 94439 | C11: (COMPOSIÇÃO REPRESENTATIVA) DO SERVIÇO DE CONTRAPISO EM ARGAMASSA TRAÇO 1:4 (CIM E AREIA), EM BETONEIRA 400 L, ESPESSURA 4 CM ÁREAS SECAS E AREAS MOLHADAS SOBRE LAJE E 3 CM ÁREAS MOLHADAS SOBRE IMPERMEABILIZAÇÃO, PARA EDIFICAÇÃO HABITACIONAL UNIFAMILIAR(CASA) E EDIFICAÇÃO PÚBLICA PADRÃO. AF_11/2014 | D11: SINAPI | E11: M2 | F11: 565.78 | G11: 31.73 | H11: 17952.2
A12: 2.2 | B12: 89171 | C12: (COMPOSIÇÃO REPRESENTATIVA) DO SERVIÇO DE REVESTIMENTO CERÂMICO PARA PISO COM PLACAS TIPO GRÉS DE DIMENSÕES 35X35 CM, PARA EDIFICAÇÃO HABITACIONAL UNIFAMILIAR (CASA) E EDIFICAÇÃO PÚBLICA PADRÃO. AF_11/2014 | D12: SINAPI | E12: M2 | F12: 565.78 | G12: 35.43 | H12: 20045.59
A13: 2.3 | B13: 96467 | C13: RODAPÉ CERÂMICO DE 7CM DE ALTURA COM PLACAS TIPO ESMALTADA COMERCIAL DE DIMENSÕES 35X35CM (PADRAO POPULAR). AF_06/2017 | D13: SINAPI | E13: M | F13: 522 | G13: 4.61 | H13: 2406.42
A14: 3.0 | B14: PAREDES | H14: =SUM(H15:H21) -> 114689.92
A15: 3.1 | B15: 87879 | C15: CHAPISCO APLICADO EM ALVENARIAS E ESTRUTURAS DE CONCRETO INTERNAS, COM COLHER DE PEDREIRO. ARGAMASSA TRAÇO 1:3 COM PREPARO EM BETONEIRA 400L. AF_06/2014 | D15: SINAPI | E15: M2 | F15: 1344.7 | G15: 2.44 | H15: 3281.07
A16: 3.2 | B16: 87547 | C16: MASSA ÚNICA, PARA RECEBIMENTO DE PINTURA, EM ARGAMASSA TRAÇO 1:2:8, PREPARO MECÂNICO COM BETONEIRA 400L, APLICADA MANUALMENTE EM FACES INTERNAS DE PAREDES, ESPESSURA DE 10MM, COM EXECUÇÃO DE TALISCAS. AF_06/2014 | D16: SINAPI | E16: M2 | F16: 1344.7 | G16: 13.7 | H16: 18422.39
A17: 3.3 | B17: 89170 | C17: (COMPOSIÇÃO REPRESENTATIVA) DO SERVIÇO DE REVESTIMENTO CERÂMICO PARA PAREDES INTERNAS, MEIA PAREDE, OU PAREDE INTEIRA, PLACAS GRÊS OU SEMI-GRÊS DE 20X20 CM, PARA EDIFICAÇÕES HABITACIONAIS UNIFAMILIAR (CASAS) E EDIFICAÇÕES PÚBLICAS PADRÃO. AF_11/2014 | D17: SINAPI | E17: M2 | F17: 1344.7 | G17: 44.41 | H17: 59718.13
A18: 3.4 | B18: 88485 | C18: APLICAÇÃO DE FUNDO SELADOR ACRÍLICO EM PAREDES, UMA DEMÃO. AF_06/2014 | D18: SINAPI | E18: M2 | F18: 1344.7 | G18: 1.69 | H18: 2272.54
A19: 3.5 | B19: 88497 | C19: APLICAÇÃO E LIXAMENTO DE MASSA LÁTEX EM PAREDES, DUAS DEMÃOS. AF_06/2014 | D19: SINAPI | E19: M2 | F19: 1344.7 | G19: 9.51 | H19: 12788.1
A20: 3.6 | B20: 88489 | C20: APLICAÇÃO MANUAL DE PINTURA COM TINTA LÁTEX ACRÍLICA EM PAREDES, DUAS DEMÃOS. AF_06/2014 | D20: SINAPI | E20: M2 | F20: 1344.7 | G20: 11.08 | H20: 14899.28
A21: 3.7 | B21: 89168 | C21: (COMPOSIÇÃO REPRESENTATIVA) DO SERVIÇO DE ALVENARIA DE VEDAÇÃO DE BLOCOS VAZADOS DE CERÂMICA DE 9X19X19CM (ESPESSURA 9CM), PARA EDIFICAÇÃO HABITACIONAL UNIFAMILIAR (CASA) E EDIFICAÇÃO PÚBLICA PADRÃO. AF_11/2014 | D21: SINAPI | E21: M2 | F21: 63.98 | G21: 51.71 | H21: 3308.41
A22: 4.0 | B22: ESQUADRIAS | H22: =SUM(H23:H27) -> 15053.203
A23: 4.1 | B23: 90844 | C23: KIT DE PORTA DE MADEIRA PARA PINTURA, SEMI-OCA (LEVE OU MÉDIA), PADRÃO MÉDIO, 90X210CM, ESPESSURA DE 3,5CM, ITENS INCLUSOS: DOBRADIÇAS, MONTAGEM E INSTALAÇÃO DO BATENTE, FECHADURA COM EXECUÇÃO DO FURO - FORNECIMENTO E INSTALAÇÃO. AF_08/2015 | D23: SINAPI | E23: UN | F23: 1 | G23: 663.57 | H23: 663.57
A24: 4.2 | B24: 90843 | C24: KIT DE PORTA DE MADEIRA PARA PINTURA, SEMI-OCA (LEVE OU MÉDIA), PADRÃO MÉDIO, 80X210CM, ESPESSURA DE 3,5CM, ITENS INCLUSOS: DOBRADIÇAS, MONTAGEM E INSTALAÇÃO DO BATENTE, FECHADURA COM EXECUÇÃO DO FURO - FORNECIMENTO E INSTALAÇÃO. AF_08/2015 | D24: SINAPI | E24: UN | F24: 13 | G24: 659.711 | H24: =F24*G24 -> 8576.243
A25: 4.3 | B25: 90841 | C25: KIT DE PORTA DE MADEIRA PARA PINTURA, SEMI-OCA (LEVE OU MÉDIA), PADRÃO MÉDIO, 60X210CM, ESPESSURA DE 3,5CM, ITENS INCLUSOS: DOBRADIÇAS, MONTAGEM E INSTALAÇÃO DO BATENTE, FECHADURA COM EXECUÇÃO DO FURO - FORNECIMENTO E INSTALAÇÃO. AF_08/2015 | D25: SINAPI | E25: UN | F25: 7 | G25: 603.73 | H25: 4226.11
A26: 4.4 | B26: 94581 | C26: JANELA DE ALUMÍNIO MAXIM-AR, FIXAÇÃO COM ARGAMASSA, COM VIDROS, PADRONIZADA. AF_07/2016 | D26: SINAPI | E26: M2 | F26: 1.28 | G26: 499.62 | H26: 639.51
A27: 4.5 | B27: 73739/001 | C27: PINTURA ESMALTE ACETINADO EM MADEIRA, DUAS DEMAOS | D27: SINAPI | E27: M2 | F27: 71.91 | G27: 13.18 | H27: 947.77
A28: 5.0 | B28: WC | H28: =SUM(H29:H31) -> 3634.21
A29: 5.1 | B29: 86931 | C29: VASO SANITÁRIO SIFONADO COM CAIXA ACOPLADA LOUÇA BRANCA, INCLUSO ENGATE FLEXÍVEL EM PLÁSTICO BRANCO, 1/2 X 40CM - FORNECIMENTO E INSTALAÇÃO. AF_12/2013 | D29: SINAPI | E29: UN | F29: 7 | G29: 347.44 | H29: 2432.08
A30: 5.2 | B30: 86943 | C30: LAVATÓRIO LOUÇA BRANCA SUSPENSO, 29,5 X 39CM OU EQUIVALENTE, PADRÃO POPULAR, INCLUSO SIFÃO FLEXÍVEL EM PVC, VÁLVULA E ENGATE FLEXÍVEL 30CM EM PLÁSTICO E TORNEIRA CROMADA DE MESA, PADRÃO POPULAR - FORNECIMENTO E INSTALAÇÃO. AF_12/2013 | D30: SINAPI | E30: UN | F30: 7 | G30: 158.01 | H30: 1106.07
A31: 5.3 | B31: 92364 | C31: TUBO DE AÇO GALVANIZADO COM COSTURA, CLASSE MÉDIA, DN 32 (1 1/4"), CONEXÃO ROSQUEADA, INSTALADO EM REDE DE ALIMENTAÇÃO PARA HIDRANTE - FORNECIMENTO E INSTALAÇÃO. AF_12/2015 | D31: SINAPI | E31: M | F31: 3.2 | G31: 30.02 | H31: 96.06
A32: 6.0 | B32: FORRO E COBERTA | H32: =SUM(H33:H38) -> 52529.48
A33: 6.1 | B33: 96113 | C33: FORRO EM PLACAS DE GESSO, PARA AMBIENTES COMERCIAIS. AF_05/2017_P | D33: SINAPI | E33: M2 | F33: 218.86 | G33: 24.3 | H33: 5318.3
A34: 6.2 | B34: 88482 | C34: APLICAÇÃO DE FUNDO SELADOR LÁTEX PVA EM TETO, UMA DEMÃO. AF_06/2014 | D34: SINAPI | E34: M2 | F34: 218.86 | G34: 2.39 | H34: 523.08
A35: 6.3 | B35: 88486 | C35: APLICAÇÃO MANUAL DE PINTURA COM TINTA LÁTEX PVA EM TETO, DUAS DEMÃOS. AF_06/2014 | D35: SINAPI | E35: M2 | F35: 218.86 | G35: 9.76 | H35: 2136.07
A36: 6.4 | B36: 94446 | C36: TELHAMENTO COM TELHA CERÂMICA CAPA-CANAL, TIPO PLAN, COM MAIS DE 2 ÁGUAS, INCLUSO TRANSPORTE VERTICAL. AF_07/2019 | D36: SINAPI | E36: M2 | F36: 473.56 | G36: 26.84 | H36: 12710.35
A37: 6.5 | B37: 92542 | C37: TRAMA DE MADEIRA COMPOSTA POR RIPAS, CAIBROS E TERÇAS PARA TELHADOS DE MAIS QUE 2 ÁGUAS PARA TELHA CERÂMICA CAPA-CANAL, INCLUSO TRANSPORTE VERTICAL. AF_07/2019 | D37: SINAPI | E37: M2 | F37: 473.56 | G37: 57.2 | H37: 27087.63
A38: 6.6 | B38: CPU C001 | C38: Rufo em fibrocimento para telha ondulada e = 6 mm, aba de 26 cm, incluso transporte vertical | D38: PRÓPRIA | E38: m | F38: 100.7 | G38: 47.21 | H38: 4754.05
A39: 7.0 | B39: INSTALAÇÃO HIDRÁULICA | H39: =SUM(H40:H41) -> 441.36
A40: 7.1 | B40: 89957 | C40: PONTO DE CONSUMO TERMINAL DE ÁGUA FRIA (SUBRAMAL) COM TUBULAÇÃO DE PVC, DN 25 MM, INSTALADO EM RAMAL DE ÁGUA, INCLUSOS RASGO E CHUMBAMENTO EM ALVENARIA. AF_12/2014 | D40: SINAPI | E40: UN | F40: 5 | G40: 83.42 | H40: 417.1
A41: 7.2 | B41: 94489 | C41: REGISTRO DE ESFERA, PVC, SOLDÁVEL, DN 25 MM, INSTALADO EM RESERVAÇÃO DE ÁGUA DE EDIFICAÇÃO QUE POSSUA RESERVATÓRIO DE FIBRA/FIBROCIMENTO FORNECIMENTO E INSTALAÇÃO. AF_06/2016 | D41: SINAPI | E41: UN | F41: 2 | G41: 12.13 | H41: 24.26
A42: 8.0 | B42: INSTALAÇÕES SANITÁRIAS | H42: =SUM(H43:H60) -> 5541.11
A43: 8.1 | B43: 89714 | C43: TUBO PVC, SERIE NORMAL, ESGOTO PREDIAL, DN 100 MM, FORNECIDO E INSTALADO EM RAMAL DE DESCARGA OU RAMAL DE ESGOTO SANITÁRIO. AF_12/2014 | D43: SINAPI | E43: M | F43: 100 | G43: 31.89 | H43: 3189
A44: 8.2 | B44: 89712 | C44: TUBO PVC, SERIE NORMAL, ESGOTO PREDIAL, DN 50 MM, FORNECIDO E INSTALADO EM RAMAL DE DESCARGA OU RAMAL DE ESGOTO SANITÁRIO. AF_12/2014 | D44: SINAPI | E44: M | F44: 50 | G44: 16.49 | H44: 824.5
A45: 8.3 | B45: 89711 | C45: TUBO PVC, SERIE NORMAL, ESGOTO PREDIAL, DN 40 MM, FORNECIDO E INSTALADO EM RAMAL DE DESCARGA OU RAMAL DE ESGOTO SANITÁRIO. AF_12/2014 | D45: SINAPI | E45: M | F45: 50 | G45: 11.36 | H45: 568
A46: 8.4 | B46: 89707 | C46: CAIXA SIFONADA, PVC, DN 100 X 100 X 50 MM, JUNTA ELÁSTICA, FORNECIDA E INSTALADA EM RAMAL DE DESCARGA OU EM RAMAL DE ESGOTO SANITÁRIO. AF_12/2014 | D46: SINAPI | E46: UN | F46: 4 | G46: 17.16 | H46: 68.64
A47: 8.5 | B47: 89778 | C47: LUVA SIMPLES, PVC, SERIE NORMAL, ESGOTO PREDIAL, DN 100 MM, JUNTA ELÁSTICA, FORNECIDO E INSTALADO EM RAMAL DE DESCARGA OU RAMAL DE ESGOTO SANITÁRIO. AF_12/2014 | D47: SINAPI | E47: UN | F47: 2 | G47: 10.49 | H47: 20.98
A48: 8.6 | B48: 89813 | C48: LUVA SIMPLES, PVC, SERIE NORMAL, ESGOTO PREDIAL, DN 50 MM, JUNTA ELÁSTICA, FORNECIDO E INSTALADO EM PRUMADA DE ESGOTO SANITÁRIO OU VENTILAÇÃO. AF_12/2014 | D48: SINAPI | E48: UN | F48: 2 | G48: 3.65 | H48: 7.3
A49: 8.7 | B49: 89809 | C49: JOELHO 90 GRAUS, PVC, SERIE NORMAL, ESGOTO PREDIAL, DN 100 MM, JUNTA ELÁSTICA, FORNECIDO E INSTALADO EM PRUMADA DE ESGOTO SANITÁRIO OU VENTILAÇÃO. AF_12/2014 | D49: SINAPI | E49: UN | F49: 5 | G49: 10.15 | H49: 50.75
A50: 8.8 | B50: 89801 | C50: JOELHO 90 GRAUS, PVC, SERIE NORMAL, ESGOTO PREDIAL, DN 50 MM, JUNTA ELÁSTICA, FORNECIDO E INSTALADO EM PRUMADA DE ESGOTO SANITÁRIO OU VENTILAÇÃO. AF_12/2014 | D50: SINAPI | E50: UN | F50: 5 | G50: 3.74 | H50: 18.7
A51: 8.9 | B51: CPU C002 | C51: Joelho 90 graus, pvc, serie normal, esgoto predial, dn 40 mm, junta elástica, fornecido e instalado em prumada de esgoto sanitário ou ventilação | D51: PRÓPRIA | E51: UN | F51: 1 | G51: 3.23 | H51: 3.23
A52: 8.10 | B52: 89810 | C52: JOELHO 45 GRAUS, PVC, SERIE NORMAL, ESGOTO PREDIAL, DN 100 MM, JUNTA ELÁSTICA, FORNECIDO E INSTALADO EM PRUMADA DE ESGOTO SANITÁRIO OU VENTILAÇÃO. AF_12/2014 | D52: SINAPI | E52: UN | F52: 5 | G52: 10.12 | H52: 50.6
A53: 8.11 | B53: 89802 | C53: JOELHO 45 GRAUS, PVC, SERIE NORMAL, ESGOTO PREDIAL, DN 50 MM, JUNTA ELÁSTICA, FORNECIDO E INSTALADO EM PRUMADA DE ESGOTO SANITÁRIO OU VENTILAÇÃO. AF_12/2014 | D53: SINAPI | E53: UN | F53: 5 | G53: 4.06 | H53: 20.3
A54: 8.12 | B54: CPU C1005 | C54: JOELHO, PVC SERIE R, 45 GRAUS, DN 40 MM, PARA ESGOTO PREDIAL | D54: PROPRIA | E54: UN | F54: 5 | G54: 2.42 | H54: 12.1
... A60: 8.18 | B60: 74166/001 | C60: CAIXA DE INSPEÇÃO EM CONCRETO PRÉ-MOLDADO DN 60CM COM TAMPA H= 60CM - FORNECIMENTO E INSTALACAO | D60: SINAPI | E60: UN | F60: 2 | G60: 160.79 | H60: 321.58
A61: 9.0 | B61: INSTALAÇÃO ELÉTRICA | H61: =SUM(H62:H71) -> 9170.5
A62: 9.1 | B62: 72315 | C62: TERMINAL AEREO EM ACO GALVANIZADO COM BASE DE FIXACAO H = 30CM | D62: SINAPI | E62: UN | F62: 1 | G62: 20.66 | H62: 20.66
A63: 9.2 | B63: 93128 | C63: PONTO DE ILUMINAÇÃO RESIDENCIAL INCLUINDO INTERRUPTOR SIMPLES, CAIXA ELÉTRICA, ELETRODUTO, CABO, RASGO, QUEBRA E CHUMBAMENTO (EXCLUINDO LUMINÁRIA E LÂMPADA). AF_01/2016 | D63: SINAPI | E63: UN | F63: 15 | G63: 85.98 | H63: 1289.7
A64: 9.3 | B64: 93137 | C64: PONTO DE ILUMINAÇÃO RESIDENCIAL INCLUINDO INTERRUPTOR SIMPLES (2 MÓDULOS), CAIXA ELÉTRICA, ELETRODUTO, CABO, RASGO, QUEBRA E CHUMBAMENTO (EXCLUINDO LUMINÁRIA E LÂMPADA). AF_01/2016 | D64: SINAPI | E64: UN | F64: 5 | G64: 101.6 | H64: 508
A65: 9.4 | B65: 93141 | C65: PONTO DE TOMADA RESIDENCIAL INCLUINDO TOMADA 10A/250V, CAIXA ELÉTRICA, ELETRODUTO, CABO, RASGO, QUEBRA E CHUMBAMENTO. AF_01/2016 | D65: SINAPI | E65: UN | F65: 30 | G65: 104.53 | H65: 3135.9
A66: 9.5 | B66: 93142 | C66: PONTO DE TOMADA RESIDENCIAL INCLUINDO TOMADA (2 MÓDULOS) 10A/250V, CAIXA ELÉTRICA, ELETRODUTO, CABO, RASGO, QUEBRA E CHUMBAMENTO. AF_01/2016 | D66: SINAPI | E66: UN | F66: 5 | G66: 116.31 | H66: 581.55
A67: 9.6 | B67: 93143 | C67: PONTO DE TOMADA RESIDENCIAL INCLUINDO TOMADA 20A/250V, CAIXA ELÉTRICA, ELETRODUTO, CABO, RASGO, QUEBRA E CHUMBAMENTO. AF_01/2016 | D67: SINAPI | E67: UN | F67: 2 | G67: 105.82 | H67: 211.64
A68: 9.7 | B68: 73953/008 | C68: LUMINÁRIAS TIPO CALHA, DE SOBREPOR, COM REATORES DE PARTIDA RÁPIDA E LÂMPADAS FLUORESCENTES 2X2X36W, COMPLETAS, FORNECIMENTO E INSTALAÇÃO | D68: SINAPI | E68: UN | F68: 15 | G68: 194.6 | H68: 2919
A69: 9.8 | B69: 68066 | C69: CAIXA DE PROTECAO PARA MEDIDOR MONOFASICO, FORNECIMENTO E INSTALACAO | D69: SINAPI | E69: UN | F69: 1 | G69: 121.53 | H69: 121.53
A70: 9.9 | B70: 83463 | C70: QUADRO DE DISTRIBUICAO DE ENERGIA EM CHAPA DE ACO GALVANIZADO, PARA 12 DISJUNTORES TERMOMAGNETICOS MONOPOLARES, COM BARRAMENTO TRIFASICO E NEUTRO - FORNECIMENTO E INSTALACAO | D70: SINAPI | E70: UN | F70: 1 | G70: 285.06 | H70: 285.06
A71: 9.10 | B71: 74130/003 | C71: DISJUNTOR TERMOMAGNETICO BIPOLAR PADRAO NEMA (AMERICANO) 10 A 50A 240V, FORNECIMENTO E INSTALACAO | D71: SINAPI | E71: UN | F71: 2 | G71: 48.73 | H71: 97.46
A72: 10.0 | B72: DIVERSOS | H72: =SUM(H73:H74) -> 1332.29
A73: 10.1 | B73: CPU C006 | C73: Limpeza final da obra | D73: PRÓPRIA | E73: m² | F73: 597.48 | G73: 2.04 | H73: 1218.86
A74: 10.2 | B74: PRÓP. C006 | C74: Lixeira com capacidade de 60 litros, com suporte | D74: PRÓPRIA | E74: UN | F74: 1 | G74: 113.43 | H74: 113.43
F75: VALOR ORÇAMENTO: | H75: =H4+H9+H72 -> 250040.36
F76: VALOR BDI TOTAL: | H76: =H75*0.2009 -> 50233.109
F77: VALOR TOTAL: | H77: =H75+H76 -> 300273.47

Sheet RESUMO
A4: 1 | B4: SERVIÇOS PRELIMINARES | D4: =ORCAMENTO!H4*1.2009 -> 8699.4157 | E4: =D4/D7*100 -> 2.8971642
A5: 2 | B5: ESCOLA | D5: =ORCAMENTO!H9*1.2009 -> 289974.11 | E5: =D5/D7*100 -> 96.570006
A6: 3 | B6: DIVERSOS | D6: =ORCAMENTO!H72*1.2009 -> 1599.9471 | E6: =D6/D7*100 -> 0.53282997
C7: VALOR TOTAL: | D7: =SUM(D4:D6) -> 300273.47 | E7: =SUM(E4:E6) -> 100

Sheet COMPOSICOES
A3: 1.1. 97634 - DEMOLIÇÃO DE REVESTIMENTO CERÂMICO, DE FORMA MECANIZADA COM MARTELETE, SEM REAPROVEITAMENTO. AF_12/2017 (M2)
A4: SERVICO | C4: FONTE | D4: UNID | E4: COEFICIENTE | F4: PREÇO UNITÁRIO | G4: TOTAL
A5: 5795 | B5: MARTELETE OU ROMPEDOR PNEUMÁTICO MANUAL, 28 KG, COM SILENCIADOR - CHP DIURNO. AF_07/2016 | C5: SINAPI | D5: CHP | E5: 0.0699 | F5: 8.77 | G5: 0.61
A6: 5952 | B6: MARTELETE OU ROMPEDOR PNEUMÁTICO MANUAL, 28 KG, COM SILENCIADOR - CHI DIURNO. AF_07/2016 | C6: SINAPI | D6: CHI | E6: 0.0482 | F6: 7.63 | G6: 0.37
A7: 88256 | B7: AZULEJISTA OU LADRILHISTA COM ENCARGOS COMPLEMENTARES | C7: SINAPI | D7: H | E7: 0.1055 | F7: 10.69 | G7: 1.13
A8: 88316 | B8: SERVENTE COM ENCARGOS COMPLEMENTARES | C8: SINAPI | D8: H | E8: 0.2972 | F8: 7.57 | G8: 2.25
E9: TOTAL SERVICO: | G9: 4.36
E10: VALOR SEM ENCARGOS: | G10: 4.36
E11: VALOR ENCARGOS (117.54%): | G11: 3.09
E12: VALOR COM ENCARGOS: | G12: 7.45
E13: VALOR BDI (20.09%): | G13: 1.4967
E14: VALOR COM BDI: | G14: 8.95
A16: 1.2. 97644 - REMOÇÃO DE PORTAS, DE FORMA MANUAL, SEM REAPROVEITAMENTO. AF_12/2017 (M2)
A17: SERVICO | C17: FONTE | D17: UNID | E17: COEFICIENTE | F17: PREÇO UNITÁRIO | G17: TOTAL
A18: 88309 | B18: PEDREIRO COM ENCARGOS COMPLEMENTARES | C18: SINAPI | D18: H | E18: 0.1315 | F18: 9.11 | G18: 1.2
A19: 88316 | B19: SERVENTE COM ENCARGOS COMPLEMENTARES | C19: SINAPI | D19: H | E19: 0.2582 | F19: 7.57 | G19: 1.95
E20: TOTAL SERVICO: | G20: 3.15
E21: VALOR SEM ENCARGOS: | G21: 3.15
E22: VALOR ENCARGOS (117.54%): | G22: 2.3
E23: VALOR COM ENCARGOS: | G23: 5.45
E24: VALOR BDI (20.09%): | G24: 1.0949
E25: VALOR COM BDI: | G25: 6.54
A27: 1.3. 97663 - REMOÇÃO DE LOUÇAS, DE FORMA MANUAL, SEM REAPROVEITAMENTO. AF_12/2017 (UN)
A28: SERVICO | C28: FONTE | D28: UNID | E28: COEFICIENTE | F28: PREÇO UNITÁRIO | G28: TOTAL
A29: 88267 | B29: ENCANADOR OU BOMBEIRO HIDRÁULICO COM ENCARGOS COMPLEMENTARES | C29: SINAPI | D29: H | E29: 0.1755 | F29: 8.71 | G29: 1.53
A30: 88316 | B30: SERVENTE COM ENCARGOS COMPLEMENTARES | C30: SINAPI | D30: H | E30: 0.3448 | F30: 7.57 | G30: 2.61
E31: TOTAL SERVICO: | G31: 4.14
E32: VALOR SEM ENCARGOS: | G32: 4.14
E33: VALOR ENCARGOS (117.54%): | G33: 3.06
E34: VALOR COM ENCARGOS: | G34: 7.2
E35: VALOR BDI (20.09%): | G35: 1.4465
E36: VALOR COM BDI: | G36: 8.65
A38: 1.4. 74209/001 - PLACA DE OBRA EM CHAPA DE ACO GALVANIZADO (M2)
A39: MATERIAL | C39: FONTE | D39: UNID | E39: COEFICIENTE | F39: PREÇO UNITÁRIO | G39: TOTAL
A40: 00004491 | B40: PONTALETE DE MADEIRA NAO APARELHADA *7,5 X 7,5* CM (3 X 3 ") PINUS, MISTA OU EQUIVALENTE DA REGIAO | C40: SINAPI | D40: M | E40: 4 | F40: 5.52 | G40: 22.08
A41: 00004417 | B41: SARRAFO DE MADEIRA NAO APARELHADA *2,5 X 7* CM, MACARANDUBA, ANGELIM OU EQUIVALENTE DA REGIAO | C41: SINAPI | D41: M | E41: 1 | F41: 3.93 | G41: 3.93
A42: 00004813 | B42: PLACA DE OBRA (PARA CONSTRUCAO CIVIL) EM CHAPA GALVANIZADA *N. 22*, ADESIVADA, DE *2,0 X 1,125* M | C42: SINAPI | D42: M2 | E42: 1 | F42: 280.05 | G42: 280.05
A43: 00005075 | B43: PREGO DE ACO POLIDO COM CABECA 18 X 30 (2 3/4 X 10) | C43: SINAPI | D43: KG | E43: 0.11 | F43: 12.25 | G43: 1.35
E44: TOTAL MATERIAL: | G44: 307.41
A45: SERVICO | C45: FONTE | D45: UNID | E45: COEFICIENTE | F45: PREÇO UNITÁRIO | G45: TOTAL
A46: 88316 | B46: SERVENTE COM ENCARGOS COMPLEMENTARES | C46: SINAPI | D46: H | E46: 2.0001134 | F46: 7.57 | G46: 15.14
A47: 88262 | B47: CARPINTEIRO DE FORMAS COM ENCARGOS COMPLEMENTARES | C47: SINAPI | D47: H | E47: 1.0000567 | F47: 9.03 | G47: 9.03
A48: 94962 | B48: CONCRETO MAGRO PARA LASTRO, TRAÇO 1:4,5:4,5 (CIMENTO/ AREIA MÉDIA/ BRITA 1) - PREPARO MECÂNICO COM BETONEIRA 400 L. AF_07/2016 | C48: SINAPI | D48: M3 | E48: 0.01000057 | F48: 207.05 | G48: 2.07
E49: TOTAL SERVICO: | G49: 26.24
E50: VALOR SEM ENCARGOS: | G50: 333.65
E51: VALOR ENCARGOS (117.54%): | G51: 17.79
E52: VALOR COM ENCARGOS: | G52: 351.44
E53: VALOR BDI (20.09%): | G53: 70.6043
E54: VALOR COM BDI: | G54: 422.04
A56: 2.2. 94439 - (COMPOSIÇÃO REPRESENTATIVA) DO SERVIÇO DE CONTRAPISO EM ARGAMASSA TRAÇO 1:4 (CIM E AREIA), EM BETONEIRA 400 L, ESPESSURA 4 CM ÁREAS SECAS E AREAS MOLHADAS SOBRE LAJE E 3 CM ÁREAS MOLHADAS SOBRE IMPERMEABILIZAÇÃO, PARA EDIFICAÇÃO HABITACIONAL UNIFAMILIAR(CASA) E EDIFICAÇÃO PÚBLICA PADRÃO. AF_11/2014 (M2)
A57: SERVICO | C57: FONTE | D57: UNID | E57: COEFICIENTE | F57: PREÇO UNITÁRIO | G57: TOTAL
A58: 87640 | B58: CONTRAPISO EM ARGAMASSA TRAÇO 1:4 (CIMENTO E AREIA), PREPARO MECÂNICO COM BETONEIRA 400 L, APLICADO EM ÁREAS SECAS SOBRE LAJE, ADERIDO, ESPESSURA 4CM. AF_06/2014 | C58: SINAPI | D58: M2 | E58: 0.6381 | F58: 25.86 | G58: 16.5
A59: 87745 | B59: CONTRAPISO EM ARGAMASSA TRAÇO 1:4 (CIMENTO E AREIA), PREPARO MECÂNICO COM BETONEIRA 400 L, APLICADO EM ÁREAS MOLHADAS SOBRE LAJE, ADERIDO, ESPESSURA 3CM. AF_06/2014 | C59: SINAPI | D59: M2 | E59: 0.1996 | F59: 26.26 | G59: 5.24
A60: 87765 | B60: CONTRAPISO EM ARGAMASSA TRAÇO 1:4 (CIMENTO E AREIA), PREPARO MECÂNICO COM BETONEIRA 400 L, APLICADO EM ÁREAS MOLHADAS SOBRE IMPERMEABILIZAÇÃO, ESPESSURA 4CM. AF_06/2014 | C60: SINAPI | D60: M2 | E60: 0.1623 | F60: 25.64 | G60: 4.16
E61: TOTAL SERVICO: | G61: 25.9
E62: VALOR SEM ENCARGOS: | G62: 25.9
E63: VALOR ENCARGOS (117.54%): | G63: 5.83
E64: VALOR COM ENCARGOS: | G64: 31.73
E65: VALOR BDI (20.09%): | G65: 6.3746
E66: VALOR COM BDI: | G66: 38.1
A68: 2.3. 89171 - (COMPOSIÇÃO REPRESENTATIVA) DO SERVIÇO DE REVESTIMENTO CERÂMICO PARA PISO COM PLACAS TIPO GRÉS DE DIMENSÕES 35X35 CM, PARA EDIFICAÇÃO HABITACIONAL UNIFAMILIAR (CASA) E EDIFICAÇÃO PÚBLICA PADRÃO. AF_11/2014 (M2)
A69: SERVICO | C69: FONTE | D69: UNID | E69: COEFICIENTE | F69: PREÇO UNITÁRIO | G69: TOTAL
A70: 87246 | B70: REVESTIMENTO CERÂMICO PARA PISO COM PLACAS TIPO ESMALTADA EXTRA DE DIMENSÕES 35X35 CM APLICADA EM AMBIENTES DE ÁREA MENOR QUE 5 M2. AF_06/2014 | C70: SINAPI | D70: M2 | E70: 0.0548 | F70: 36.05 | G70: 1.98
A71: 87247 | B71: REVESTIMENTO CERÂMICO PARA PISO COM PLACAS TIPO ESMALTADA EXTRA DE DIMENSÕES 35X35 CM APLICADA EM AMBIENTES DE ÁREA ENTRE 5 M2 E 10 M2. AF_06/2014 | C71: SINAPI | D71: M2 | E71: 0.3365 | F71: 32.91 | G71: 11.07
A72: 87248 | B72: REVESTIMENTO CERÂMICO PARA PISO COM PLACAS TIPO ESMALTADA EXTRA DE DIMENSÕES 35X35 CM APLICADA EM AMBIENTES DE ÁREA MAIOR QUE 10 M2. AF_06/2014 | C72: SINAPI | D72: M2 | E72: 0.6087 | F72: 30.51 | G72: 18.57
E73: TOTAL SERVICO: | G73: 31.62
E74: VALOR SEM ENCARGOS: | G74: 31.62
E75: VALOR ENCARGOS (117.54%): | G75: 3.81
E76: VALOR COM ENCARGOS: | G76: 35.43
E77: VALOR BDI (20.09%): | G77: 7.1179
E78: VALOR COM BDI: | G78: 42.55
A80: 2.4. 96467 - RODAPÉ CERÂMICO DE 7CM DE ALTURA COM PLACAS TIPO ESMALTADA COMERCIAL DE DIMENSÕES 35X35CM (PADRAO POPULAR). AF_06/2017 (M)
A81: MATERIAL | C81: FONTE | D81: UNID | E81: COEFICIENTE | F81: PREÇO UNITÁRIO | G81: TOTAL
A82: 00001297 | B82: PISO EM CERAMICA ESMALTADA, COMERCIAL (PADRAO POPULAR), PEI MAIOR OU IGUAL A 3, FORMATO MENOR OU IGUAL A 2025 CM2 | C82: SINAPI | D82: M2 | E82: 0.123 | F82: 18.46 | G82: 2.27
A83: 00001381 | B83: ARGAMASSA COLANTE AC I PARA CERAMICAS | C83: SINAPI | D83: KG | E83: 0.603 | F83: 0.5 | G83: 0.3
A84: 00034357 | B84: REJUNTE COLORIDO, CIMENTICIO | C84: SINAPI | D84: KG | E84: 0.085 | F84: 3.2 | G84: 0.27
E85: TOTAL MATERIAL: | G85: 2.84
A86: SERVICO | C86: FONTE | D86: UNID | E86: COEFICIENTE | F86: PREÇO UNITÁRIO | G86: TOTAL
A87: 88256 | B87: AZULEJISTA OU LADRILHISTA COM ENCARGOS COMPLEMENTARES | C87: SINAPI | D87: H | E87: 0.07 | F87: 10.69 | G87: 0.75
A88: 88316 | B88: SERVENTE COM ENCARGOS COMPLEMENTARES | C88: SINAPI | D88: H | E88: 0.031 | F88: 7.57 | G88: 0.23
E89: TOTAL SERVICO: | G89: 0.98
E90: VALOR SEM ENCARGOS: | G90: 3.82
E91: VALOR ENCARGOS (117.54%): | G91: 0.79
E92: VALOR COM ENCARGOS: | G92: 4.61
E93: VALOR BDI (20.09%): | G93: 0.9261
E94: VALOR COM BDI: | G94: 5.54
A96: 2.6. 87879 - CHAPISCO APLICADO EM ALVENARIAS E ESTRUTURAS DE CONCRETO INTERNAS, COM COLHER DE PEDREIRO. ARGAMASSA TRAÇO 1:3 COM PREPARO EM BETONEIRA 400L. AF_06/2014 (M2)
A97: SERVICO | C97: FONTE | D97: UNID | E97: COEFICIENTE | F97: PREÇO UNITÁRIO | G97: TOTAL
A98: 87313 | B98: ARGAMASSA TRAÇO 1:3 (EM VOLUME DE CIMENTO E AREIA GROSSA ÚMIDA) PARA CHAPISCO CONVENCIONAL, PREPARO MECÂNICO COM BETONEIRA 400 L. AF_08/2019 | C98: SINAPI | D98: M3 | E98: 0.0042 | F98: 267.97 | G98: 1.13
A99: 88309 | B99: PEDREIRO COM ENCARGOS COMPLEMENTARES | C99: SINAPI | D99: H | E99: 0.07 | F99: 9.11 | G99: 0.64
A100: 88316 | B100: SERVENTE COM ENCARGOS COMPLEMENTARES | C100: SINAPI | D100: H | E100: 0.007 | F100: 7.57 | G100: 0.05
E101: TOTAL SERVICO: | G101: 1.82
E102: VALOR SEM ENCARGOS: | G102: 1.82
E103: VALOR ENCARGOS (117.54%): | G103: 0.62
E104: VALOR COM ENCARGOS: | G104: 2.44
E105: VALOR BDI (20.09%): | G105: 0.4902
E106: VALOR COM BDI: | G106: 2.93
A108: 2.7. 87547 - MASSA ÚNICA, PARA RECEBIMENTO DE PINTURA, EM ARGAMASSA TRAÇO 1:2:8, PREPARO MECÂNICO COM BETONEIRA 400L, APLICADA MANUALMENTE EM FACES INTERNAS DE PAREDES, ESPESSURA DE 10MM, COM EXECUÇÃO DE TALISCAS. AF_06/2014 (M2)
A109: SERVICO | C109: FONTE | D109: UNID | E109: COEFICIENTE | F109: PREÇO UNITÁRIO | G109: TOTAL
A110: 87292 | B110: ARGAMASSA TRAÇO 1:2:8 (EM VOLUME DE CIMENTO, CAL E AREIA MÉDIA ÚMIDA) PARA EMBOÇO/MASSA ÚNICA/ASSENTAMENTO DE ALVENARIA DE VEDAÇÃO, PREPARO MECÂNICO COM BETONEIRA 400 L. AF_08/2019 | C110: SINAPI | D110: M3 | E110: 0.0213 | F110: 277.06 | G110: 5.9
...

Sheet COMPOSICOES AUXILIARES
A3: 5795 - MARTELETE OU ROMPEDOR PNEUMÁTICO MANUAL, 28 KG, COM SILENCIADOR - CHP DIURNO. AF_07/2016 (CHP)
A4: SERVICO | C4: FONTE | D4: UNID | E4: COEFICIENTE | F4: PREÇO UNITÁRIO | G4: TOTAL
A5: 53863 | B5: MARTELETE OU ROMPEDOR PNEUMÁTICO MANUAL, 28 KG, COM SILENCIADOR - MANUTENÇÃO. AF_07/2016 | C5: SINAPI | D5: H | E5: 1 | F5: 1.14 | G5: 1.14
A6: 88298 | B6: OPERADOR DE MARTELETE OU MARTELETEIRO COM ENCARGOS COMPLEMENTARES | C6: SINAPI | D6: H | E6: 1 | F6: 6.52 | G6: 6.52
A7: 95114 | B7: MARTELETE OU ROMPEDOR PNEUMÁTICO MANUAL, 28 KG, COM SILENCIADOR - DEPRECIAÇÃO. AF_07/2016 | C7: SINAPI | D7: H | E7: 1 | F7: 0.91 | G7: 0.91
A8: 95115 | B8: MARTELETE OU ROMPEDOR PNEUMÁTICO MANUAL, 28 KG, COM SILENCIADOR - JUROS. AF_07/2016 | C8: SINAPI | D8: H | E8: 1 | F8: 0.2 | G8: 0.2
E9: TOTAL SERVICO: | G9: 8.77
E10: VALOR SEM ENCARGOS: | G10: 8.77
E11: VALOR ENCARGOS (117.54%): | G11: 4.85
E12: VALOR COM ENCARGOS: | G12: 13.62
E13: VALOR BDI (20.09%): | G13: 2.7363
E14: VALOR COM BDI: | G14: 16.36
A16: 53863 - MARTELETE OU ROMPEDOR PNEUMÁTICO MANUAL, 28 KG, COM SILENCIADOR - MANUTENÇÃO. AF_07/2016 (H)
A17: EQUIPAMENTO | C17: FONTE | D17: UNID | E17: COEFICIENTE | F17: PREÇO UNITÁRIO | G17: TOTAL
A18: 00041898 | B18: MARTELO DEMOLIDOR PNEUMATICO MANUAL, PESO DE 28 KG, COM SILENCIADOR | C18: SINAPI | D18: UN | E18: 8e-05 | F18: 14363.27 | G18: 1.15
E19: TOTAL EQUIPAMENTO: | G19: 1.15
E20: VALOR SEM ENCARGOS: | G20: 1.14
E21: VALOR ENCARGOS: | G21: 0
E22: VALOR COM ENCARGOS: | G22: 1.14
E23: VALOR BDI (20.09%): | G23: 0.229
E24: VALOR COM BDI: | G24: 1.37
A26: 88298 - OPERADOR DE MARTELETE OU MARTELETEIRO COM ENCARGOS COMPLEMENTARES (H)
A27: GERAL | C27: FONTE | D27: UNID | E27: COEFICIENTE | F27: PREÇO UNITÁRIO | G27: TOTAL
A28: 00037370 | B28: ALIMENTACAO - HORISTA (COLETADO CAIXA) | C28: SINAPI | D28: H | E28: 1 | F28: 0.7 | G28: 0.7
A29: 00037371 | B29: TRANSPORTE - HORISTA (COLETADO CAIXA) | C29: SINAPI | D29: H | E29: 1 | F29: 0.7 | G29: 0.7
A30: 00037372 | B30: EXAMES - HORISTA (COLETADO CAIXA) | C30: SINAPI | D30: H | E30: 1 | F30: 0.35 | G30: 0.35
A31: 00037373 | B31: SEGURO - HORISTA (COLETADO CAIXA) | C31: SINAPI | D31: H | E31: 1 | F31: 0.01 | G31: 0.01
E32: TOTAL GERAL: | G32: 1.76
A33: MAO DE OBRA | C33: FONTE | D33: UNID | E33: COEFICIENTE | F33: PREÇO UNITÁRIO | G33: TOTAL
A34: 00004257 | B34: OPERADOR DE MARTELETE OU MARTELETEIRO | C34: SINAPI | D34: H | E34: 0.9335 | F34: 4.3992 | G34: 4.11
E35: TOTAL MAO DE OBRA: | G35: 4.11
A36: MATERIAL | C36: FONTE | D36: UNID | E36: COEFICIENTE | F36: PREÇO UNITÁRIO | G36: TOTAL
A37: 00043464 | B37: FERRAMENTAS - FAMILIA OPERADOR ESCAVADEIRA - HORISTA (ENCARGOS COMPLEMENTARES - COLETADO CAIXA) | C37: SINAPI | D37: H | E37: 1 | F37: 0.01 | G37: 0.01
A38: 00043488 | B38: EPI - FAMILIA OPERADOR ESCAVADEIRA - HORISTA (ENCARGOS COMPLEMENTARES - COLETADO CAIXA) | C38: SINAPI | D38: H | E38: 1 | F38: 0.62 | G38: 0.62
E39: TOTAL MATERIAL: | G39: 0.63
A40: SERVICO | C40: FONTE | D40: UNID | E40: COEFICIENTE | F40: PREÇO UNITÁRIO | G40: TOTAL
A41: 95361 | B41: CURSO DE CAPACITAÇÃO PARA OPERADOR DE MARTELETE OU MARTELETEIRO (ENCARGOS COMPLEMENTARES) - HORISTA | C41: SINAPI | D41: H | E41: 1 | F41: 0.02 | G41: 0.02
E42: TOTAL SERVICO: | G42: 0.02
E43: VALOR SEM ENCARGOS: | G43: 6.52
E44: VALOR ENCARGOS (117.54%): | G44: 4.85
E45: VALOR COM ENCARGOS: | G45: 11.37
E46: VALOR BDI (20.09%): | G46: 2.2842
E47: VALOR COM BDI: | G47: 13.65
A49: 95361 - CURSO DE CAPACITAÇÃO PARA OPERADOR DE MARTELETE OU MARTELETEIRO (ENCARGOS COMPLEMENTARES) - HORISTA (H)
A50: MAO DE OBRA | C50: FONTE | D50: UNID | E50: COEFICIENTE | F50: PREÇO UNITÁRIO | G50: TOTAL
A51: 00004257 | B51: OPERADOR DE MARTELETE OU MARTELETEIRO | C51: SINAPI | D51: H | E51: 0.00532095 | F51: 4.3992 | G51: 0.02
E52: TOTAL MAO DE OBRA: | G52: 0.02
E53: VALOR SEM ENCARGOS: | G53: 0.02
E54: VALOR ENCARGOS (117.54%): | G54: 0.03
E55: VALOR COM ENCARGOS: | G55: 0.05
E56: VALOR BDI (20.09%): | G56: 0.01
E57: VALOR COM BDI: | G57: 0.06
A59: 95114 - MARTELETE OU ROMPEDOR PNEUMÁTICO MANUAL, 28 KG, COM SILENCIADOR - DEPRECIAÇÃO. AF_07/2016 (H)
A60: EQUIPAMENTO | C60: FONTE | D60: UNID | E60: COEFICIENTE | F60: PREÇO UNITÁRIO | G60: TOTAL
A61: 00041898 | B61: MARTELO DEMOLIDOR PNEUMATICO MANUAL, PESO DE 28 KG, COM SILENCIADOR | C61: SINAPI | D61: UN | E61: 6.4e-05 | F61: 14363.27 | G61: 0.92
E62: TOTAL EQUIPAMENTO: | G62: 0.92
E63: VALOR SEM ENCARGOS: | G63: 0.91
E64: VALOR ENCARGOS: | G64: 0
E65: VALOR COM ENCARGOS: | G65: 0.91
E66: VALOR BDI (20.09%): | G66: 0.1828
E67: VALOR COM BDI: | G67: 1.09
A69: 95115 - MARTELETE OU ROMPEDOR PNEUMÁTICO MANUAL, 28 KG, COM SILENCIADOR - JUROS. AF_07/2016 (H)
A70: EQUIPAMENTO | C70: FONTE | D70: UNID | E70: COEFICIENTE | F70: PREÇO UNITÁRIO | G70: TOTAL
A71: 00041898 | B71: MARTELO DEMOLIDOR PNEUMATICO MANUAL, PESO DE 28 KG, COM SILENCIADOR | C71: SINAPI | D71: UN | E71: 1.44e-05 | F71: 14363.27 | G71: 0.21
E72: TOTAL EQUIPAMENTO: | G72: 0.21
E73: VALOR SEM ENCARGOS: | G73: 0.2
E74: VALOR ENCARGOS: | G74: 0
E75: VALOR COM ENCARGOS: | G75: 0.2
E76: VALOR BDI (20.09%): | G76: 0.0402
E77: VALOR COM BDI: | G77: 0.24
A79: 5952 - MARTELETE OU ROMPEDOR PNEUMÁTICO MANUAL, 28 KG, COM SILENCIADOR - CHI DIURNO. AF_07/2016 (CHI)
A80: SERVICO | C80: FONTE | D80: UNID | E80: COEFICIENTE | F80: PREÇO UNITÁRIO | G80: TOTAL
A81: 88298 | B81: OPERADOR DE MARTELETE OU MARTELETEIRO COM ENCARGOS COMPLEMENTARES | C81: SINAPI | D81: H | E81: 1 | F81: 6.52 | G81: 6.52
A82: 95114 | B82: MARTELETE OU ROMPEDOR PNEUMÁTICO MANUAL, 28 KG, COM SILENCIADOR - DEPRECIAÇÃO. AF_07/2016 | C82: SINAPI | D82: H | E82: 1 | F82: 0.91 | G82: 0.91
A83: 95115 | B83: MARTELETE OU ROMPEDOR PNEUMÁTICO MANUAL, 28 KG, COM SILENCIADOR - JUROS. AF_07/2016 | C83: SINAPI | D83: H | E83: 1 | F83: 0.2 | G83: 0.2
E84: TOTAL SERVICO: | G84: 7.63
E85: VALOR SEM ENCARGOS: | G85: 7.63
E86: VALOR ENCARGOS (117.54%): | G86: 4.85
E87: VALOR COM ENCARGOS: | G87: 12.48
E88: VALOR BDI (20.09%): | G88: 2.5072
E89: VALOR COM BDI: | G89: 14.99
A91: 88256 - AZULEJISTA OU LADRILHISTA COM ENCARGOS COMPLEMENTARES (H)
A92: GERAL | C92: FONTE | D92: UNID | E92: COEFICIENTE | F92: PREÇO UNITÁRIO | G92: TOTAL
A93: 00037370 | B93: ALIMENTACAO - HORISTA (COLETADO CAIXA) | C93: SINAPI | D93: H | E93: 1 | F93: 0.7 | G93: 0.7
A94: 00037371 | B94: TRANSPORTE - HORISTA (COLETADO CAIXA) | C94: SINAPI | D94: H | E94: 1 | F94: 0.7 | G94: 0.7
A95: 00037372 | B95: EXAMES - HORISTA (COLETADO CAIXA) | C95: SINAPI | D95: H | E95: 1 | F95: 0.35 | G95: 0.35
A96: 00037373 | B96: SEGURO - HORISTA (COLETADO CAIXA) | C96: SINAPI | D96: H | E96: 1 | F96: 0.01 | G96: 0.01
E97: TOTAL GERAL: | G97: 1.76
A98: MAO DE OBRA | C98: FONTE | D98: UNID | E98: COEFICIENTE | F98: PREÇO UNITÁRIO | G98: TOTAL
A99: 00004760 | B99: AZULEJISTA OU LADRILHISTA | C99: SINAPI | D99: H | E99: 0.9335 | F99: 8.0169 | G99: 7.48
E100: TOTAL MAO DE OBRA: | G100: 7.48
A101: MATERIAL | C101: FONTE | D101: UNID | E101: COEFICIENTE | F101: PREÇO UNITÁRIO | G101: TOTAL
A102: 00043465 | B102: FERRAMENTAS - FAMILIA PEDREIRO - HORISTA (ENCARGOS COMPLEMENTARES - COLETADO CAIXA) | C102: SINAPI | D102: H | E102: 1 | F102: 0.47 | G102: 0.47
A103: 00043489 | B103: EPI - FAMILIA PEDREIRO - HORISTA (ENCARGOS COMPLEMENTARES - COLETADO CAIXA) | C103: SINAPI | D103: H | E103: 1 | F103: 0.9 | G103: 0.9
E104: TOTAL MATERIAL: | G104: 1.37
A105: SERVICO | C105: FONTE | D105: UNID | E105: COEFICIENTE | F105: PREÇO UNITÁRIO | G105: TOTAL
A106: 95324 | B106: CURSO DE CAPACITAÇÃO PARA AZULEJISTA OU LADRILHISTA (ENCARGOS COMPLEMENTARES) - HORISTA | C106: SINAPI | D106: H | E106: 1 | F106: 0.08 | G106: 0.08
E107: TOTAL SERVICO: | G107: 0.08
E108: VALOR SEM ENCARGOS: | G108: 10.69
E109: VALOR ENCARGOS (117.54%): | G109: 8.89
...

Sheet CRONOGRAMA
A2: ITEM | B2: DESCRIÇÃO | C2: VALOR (R$) | D2: MÊS 1 | E2: MÊS 2 | F2: MÊS 3 | G2: MÊS 4
A3: 1 | B3: SERVIÇOS PRELIMINARES | C3: =ORCAMENTO!H4*1.2009 -> 8699.4157 | D3: 100
D4: =C3 -> 8699.4157
A5: 2 | B5: PISO | C5: =ORCAMENTO!H10*1.2009 -> 48521.416 | D5: 30 | E5: 40 | F5: 30
D6: =C5*0.3 -> 14556.425 | E6: =C5*0.4 -> 19408.566 | F6: =D6 -> 14556.425
A7: 3 | B7: PAREDES | C7: =ORCAMENTO!H14*1.2009 -> 137731.12 | D7: 20 | E7: 30 | F7: 50
D8: =C7*0.2 -> 27546.225 | E8: =C7*0.3 -> 41319.337 | F8: =C7*0.5 -> 68865.562
A9: 4 | B9: ESQUADRIAS | C9: =ORCAMENTO!H22*1.2009 -> 18077.391 | F9: 100
F10: =C9 -> 18077.391
A11: 5 | B11: WC | C11: =ORCAMENTO!H28*1.2009 -> 4364.3228 | G11: 100
G12: =C11 -> 4364.3228
A13: 6 | B13: FÔRRO E COBERTA | C13: =ORCAMENTO!H32*1.2009 -> 63082.653 | E13: 50 | F13: 30 | G13: 20
E14: =C13*0.5 -> 31541.326 | F14: =C13*0.3 -> 18924.796 | G14: =C13*0.2 -> 12616.531
A15: 7 | B15: INSTALAÇÃO HIDRÁULICA | C15: =ORCAMENTO!H39*1.2009 -> 530.02922 | F15: 100
F16: =C15 -> 530.02922
A17: 8 | B17: INSTALAÇÃO SANITÁRIA | C17: =ORCAMENTO!H42*1.2009 -> 6654.319 | E17: 30 | F17: 35 | G17: 35
E18: =C17*0.3 -> 1996.2957 | F18: =C17*0.35 -> 2329.0116 | G18: =C17*0.35 -> 2329.0116
A19: 9 | B19: ELÉTRICA | C19: =ORCAMENTO!H61*1.2009 -> 11012.853 | E19: 40 | F19: 40 | G19: 20
E20: =C19*0.4 -> 4405.1414 | F20: =C19*0.4 -> 4405.1414 | G20: =C19*0.2 -> 2202.5707
A21: 10 | B21: DIVERSOS | C21: =ORCAMENTO!H72*1.2009 -> 1599.9471 | G21: 100
G22: =C21 -> 1599.9471
B23: TOTAL(R$) | D23: =D4+D6+D8 -> 50802.065 | E23: =E6+E8+E14+E18+E20 -> 98670.667 | F23: =F6+F8+F10+F14+F16+F18+F20 -> 127688.36 | G23: =G12+G14+G18+G20+G22 -> 23112.383
B24: TOTAL ACUMULADO(R$) | D24: =D23 -> 50802.065 | E24: =D24+E23 -> 149472.73 | F24: =E24+F23 -> 277161.09 | G24: =F24+G23 -> 300273.47
B25: PERCENTUAL SIMPLES(%) | D25: =D23/G24*100 -> 16.918599 | E25: =E23/G24*100 -> 32.860268 | F25: =F23/G24*100 -> 42.524022 | G25: =G23/G24*100 -> 7.6971111
B26: PERCENTUAL ACUMULADO(%) | D26: =D25 -> 16.918599 | E26: =D26+E25 -> 49.778867 | F26: =E26+F25 -> 92.302889 | G26: =F26+G25 -> 100

Sheet BDI
A3: COD | B3: DESCRIÇÃO | C3: %
B5: Benefício
A6: S + G | B6: Garantia/seguros | C6: 0.32
A7: L | B7: Lucro | C7: 6.64
B8: TOTAL | C8: 6.96
B11: Despesas Indiretas
A12: AC | B12: Administração central | C12: 3.8
A13: DF | B13: Despesas financeiras | C13: 1.02
A14: R | B14: Riscos | C14: 0.5
B15: TOTAL | C15: 5.32
A18: I | B18: Impostos
B19: COFINS | C19: 3
B20: ISS | C20: 2.5
B21: PIS | C21: 0.65
B22: TOTAL | C22: 6.15
B24: BDI = 20,09%
B25: (1+AC+S+R+G)*(1+DF)*(1+L)/(1-I)-1

Sheet ENCARGOS SOCIAIS
A3: COD | B3: DESCRIÇÃO | C3: HORA % | D3: MES %
A5: A | B5: GRUPO A
A6: A1 | B6: INSS | C6: 20 | D6: 20
A7: A2 | B7: SESI | C7: 1.5 | D7: 1.5
A8: A3 | B8: SENAI | C8: 1 | D8: 1
A9: A4 | B9: INCRA | C9: 0.2 | D9: 0.2
A10: A5 | B10: SEBRAE | C10: 0.6 | D10: 0.6
A11: A6 | B11: Salário Educação | C11: 2.5 | D11: 2.5
A12: A7 | B12: Seguro Contra Acidentes de Trabalho | C12: 3 | D12: 3
A13: A8 | B13: FGTS | C13: 8 | D13: 8
A14: A9 | B14: SECONCI | C14: 0 | D14: 0
B15: TOTAL | C15: 36.8 | D15: 36.8
A17: B | B17: GRUPO B
A18: B1 | B18: Repouso Semanal Remunerado | C18: 18.03 | D18: 0
A19: B2 | B19: Feriados | C19: 4.31 | D19: 0
A20: B3 | B20: Auxílio - Enfermidade | C20: 0.92 | D20: 0.71
A21: B4 | B21: 13º Salário | C21: 10.8 | D21: 8.33
A22: B5 | B22: Licença PaternidadE | C22: 0.07 | D22: 0.06
A23: B6 | B23: Faltas Justificadas | C23: 0.72 | D23: 0.56
A24: B7 | B24: Dias de Chuvas | C24: 1.99 | D24: 0
A25: B8 | B25: Auxílio Acidente de Trabalho | C25: 0.11 | D25: 0.09
A26: B9 | B26: Férias Gozadas | C26: 14.2 | D26: 10.95
A27: B10 | B27: Salário Maternidade | C27: 0.03 | D27: 0.02
B28: TOTAL | C28: 51.18 | D28: 20.72
A30: C | B30: GRUPO C
A31: C1 | B31: Aviso Prévio Indenizado | C31: 4.66 | D31: 3.6
A32: C2 | B32: Aviso Prévio Trabalhado | C32: 0.11 | D32: 0.08
A33: C3 | B33: Férias Indenizadas | C33: 0 | D33: 0
A34: C4 | B34: Depósito Rescisão Sem Justa Causa | C34: 5.16 | D34: 3.99
A35: C5 | B35: Indenização Adicional | C35: 0.39 | D35: 0.3
B36: TOTAL | C36: 10.32 | D36: 7.97
A38: D | B38: GRUPO D
A39: D1 | B39: Reincidência de Grupo A sobre Grupo B | C39: 18.83 | D39: 7.62
A40: D2 | B40: Reincidência de Grupo A sobre Aviso Prévio Trabalhado e Reincidência do FGTS sobre Aviso Prévio Indenizado | C40: 0.41 | D40: 0.32
B41: TOTAL | C41: 19.24 | D41: 7.94
B43: Horista = 117,54% Mensalista = 73,43%
B44: A + B + C + D
