Workbook
Name \C: #REF!
Name \C: #REF!
Name \D: #REF!
Name \D: #REF!
Name \G: #REF!
Name \G: #REF!
Name \I: #REF!
Name \I: #REF!
Name \l: #REF!
Name \l: #REF!
Name \M: #REF!
Name \M: #REF!
Name \P: #REF!
Name \P: #REF!
Name \q: #REF!
Name \q: #REF!
Name \R: #REF!
Name \R: #REF!
Name \s: #REF!
Name \s: #REF!
Name \t: #REF!
Name \t: #REF!
Name \Y: #REF!
Name \Y: #REF!
Name _: #REF!
Name _: #REF!
Name _________sub1: #REF!
Name _________sub1: #REF!
Name _________sub3: #REF!
Name _________sub3: #REF!
Name ________R: #REF!
Name ________sub1: #REF!
Name ________sub1: #REF!
Name ________sub2: #REF!
Name ________sub3: #REF!
Name ________sub3: #REF!
Name ________sub4: #REF!
Name _______MDO1: #REF!
Name _______MDO2: #REF!
Name _______R: #REF!
Name _______R: #REF!
Name _______sub1: #REF!
Name _______sub1: #REF!
Name _______sub2: #REF!
Name _______sub2: #REF!
Name _______sub3: #REF!
Name _______sub3: #REF!
Name _______sub4: #REF!
Name _______sub4: #REF!
Name ______MDO1: #REF!
Name ______MDO1: #REF!
Name ______MDO2: #REF!
Name ______MDO2: #REF!
Name ______R: #REF!
Name ______R: #REF!
Name ______sub1: #REF!
Name ______sub1: #REF!
Name ______sub2: #REF!
Name ______sub2: #REF!
Name ______sub3: #REF!

Sheet capa
M3: (*) COLAR TIMBRE DA PREFEITURA
B7: ESTADO DA PARAÍBA
B8: PREFEITURA MUNICIPAL DE COREMAS
B21: PLANILHA ORÇAMENTÁRIA
C23: CONSTRUÇÃO DE QUADRA POLIESPORTIVA COM VESTIÁRIOS E BANHEIROS, NO MUNICÍPIO DE COREMAS/PB | M23: (*) PREENCHER OBJETO
C26: RECURSOS GOVERNO DO ESTADO | M26: (*) PREENCHER NÚMERO DE CONTRATO
C27: Prefeitura Municipal de Coremas - PB | M27: (*) PREENCHER MINISTÉRIO
G33: LCL PROJETOS DE ENGENHARIA
G34: Av. Flávio R. Coutinho, 500, Sala 601, Jd. Oceania
G35: João Pessoa - PB
G36: CEP: 58038-320
G37: Tel: 83 99924-4447
G38: Eng. Responsável: Lincoln Cartaxo de Lira Júnior
G39: CPF 068.978.614-05
G40: CREA 160 814 689 - 8

Sheet Dados_Intesidade
A1: Nome | B1: Latitude | C1: Longitude | D1: N* | E1: Período | F1: B | G1: n | H1: m | I1: K
A2: Antenor Navarro | B2: 6°44’ | C2: 38°27’ | D2: 30 | E2: (65-94) | F2: 15 | G2: 0.693 | H2: 0.161 | I2: 936
A3: Barra de Santa Rosa | B3: 6°43’ | C3: 36°04’ | D3: 17 | E3: (65-89) | F3: 16 | G3: 0.786 | H3: 0.277 | I3: 765
A4: Bonito de Santa Fé | B4: 7°19’ | C4: 38°31’ | D4: 15 | E4: (67-94) | F4: 10 | G4: 0.729 | H4: 0.181 | I4: 813
A5: Campina Grande | B5: 7°14’ | C5: 35°52’ | D5: 11 | E5: (66-89) | F5: 5 | G5: 0.596 | H5: 0.227 | I5: 334
A6: Catolé do Rocha | B6: 6°21’ | C6: 37°45’ | D6: 27 | E6: (63-92) | F6: 13 | G6: 0.566 | H6: 0.095 | I6: 708
A7: Guarabira | B7: 6°50’ | C7: 35°29’ | D7: 12 | E7: (65-81) | F7: 5 | G7: 0.536 | H7: 0.239 | I7: 246
A8: Taperoá | B8: 7°12’ | C8: 36°50’ | D8: 15 | E8: (63-93) | F8: 7 | G8: 0.497 | H8: 0.074 | I8: 342
A9: Teixeira | B9: 7°13’ | C9: 37°15’ | D9: 17 | E9: (63-85) | F9: 18 | G9: 0.604 | H9: 0.16 | I9: 877
A10: Seridó | B10: 6°51’ | C10: 36°25’ | D10: 16 | E10: (79-94) | F10: 8 | G10: 0.543 | H10: 0.168 | I10: 492
A11: Itaporanga | B11: 7°19’ | C11: 38°09’ | D11: 12 | E11: (65-83) | F11: 15 | G11: 0.58 | H11: 0.083 | I11: 527
A12: João Pessoa | B12: 7°08’ | C12: 34°53’ | D12: 6 | E12: (81-86) | F12: 10 | G12: 0.398 | H12: 0.087 | I12: 290
A13: Monteiro | B13: 7°52’ | C13: 37°07’ | D13: 9 | E13: (67-86) | F13: 15 | G13: 0.724 | H13: 0.295 | I13: 302
... A16: São Gonçalo | B16: 6°50’ | C16: 38°19’ | D16: 7 | E16: (81-87) | F16: 7 | G16: 0.651 | H16: 0.301 | I16: 352

Sheet Encargos
A1: ENCARGOS SOCIAIS
A3: Item | B3: Discriminação | C3: Horista | D3: Mensalista
A4: A | B4: ENCARGOS SOCIAIS BÁSICOS | C4: =SUM(C5:C13) -> 36.8 | D4: =SUM(D5:D13) -> 36.8
A5: A-1 | B5: INSS | C5: 20 | D5: 20
A6: A-2 | B6: SESI | C6: 1.5 | D6: 1.5
A7: A-3 | B7: SENAI | C7: 1 | D7: 1
A8: A-4 | B8: INCRA | C8: 0.2 | D8: 0.2
A9: A-5 | B9: SEBRAE | C9: 0.6 | D9: 0.6
A10: A-6 | B10: SALÁRIO EDUCAÇÃO | C10: 2.5 | D10: 2.5
A11: A-7 | B11: SEGURO CONTRA ACIDENTES DE TRABALHO | C11: 3 | D11: 3
A12: A-8 | B12: FGTS | C12: 8 | D12: 8
A13: A-9 | B13: SECONCI | C13: 0 | D13: 0
A14: B | B14: ENCARGOS SOCIAIS QUE RECEBEM AS INCIDÊNCIAS DE "A" | C14: =SUM(C15:C25) -> 50.51 | D14: =SUM(D15:D25) -> 20.28
A15: B-1 | B15: REPOUSO SEMANAL REMUNERADO | C15: 18.01 | D15: 0
A16: B-2 | B16: FERIADOS | C16: 4.3 | D16: 0
A17: B-3 | B17: AUXILIO - ENFERMIDADE | C17: 0.87 | D17: 0.67
A18: B-4 | B18: 13º SALARIO | C18: 10.78 | D18: 8.33
A19: B-5 | B19: LICENÇA PATERNIDADE | C19: 0.07 | D19: 0.06
A20: B-6 | B20: FALTAS JUSTIFICADAS | C20: 0.72 | D20: 0.56
A21: B-7 | B21: DIAS DE CHUVAS | C21: 1.98 | D21: -
A22: B-8 | B22: AUXILIO ACIDENTE DE TRABALHO | C22: 0.11 | D22: 0.08
A23: B-9 | B23: FÉRIAS GOZADAS | C23: 13.64 | D23: 10.55
A24: B-10 | B24: SALÁRIO MATERNIDADE | C24: 0.03 | D24: 0.03
A26: C | B26: ENCARGOS SOCIAIS QUE NÃO RECEBEM AS INCIDÊNCIAS DE "A" | C26: =SUM(C27:C32) -> 9.52 | D26: =SUM(D27:D32) -> 7.38
A27: C-1 | B27: AVISO PRÉVIO INDENIZADO | C27: 4.45 | D27: 3.45
A28: C-2 | B28: AVISO PRÉVIO TRABALHADO | C28: 0.1 | D28: 0.08
A29: C-3 | B29: FÉRIAS INDENIZADAS | C29: 0.5 | D29: 0.39
A30: C-4 | B30: DEPÓSITO RECISÃO SEM JUSTA CAUSA | C30: 4.1 | D30: 3.17
A31: C-5 | B31: INDENIZAÇÃO ADICIONAL | C31: 0.37 | D31: 0.29
A33: D | B33: TAXAS DE REINCIDÊNCIAS DE UM GRUPO SOBRE O OUTRO | C33: =SUM(C34:C37) -> 18.98 | D33: =SUM(D34:D37) -> 7.77
A34: D-1 | B34: REINCIDENCIA DE GRUPO A SOBRE GRUPO B | C34: 18.59 | D34: 7.46
A35: D-2 | B35: REINCIDENCIA DE GRUPO A SOBRE AVISO PRÉVIO TRABALHADO E REINCIDENCIA DO FGTS SOBRE AVISO PRÉVIO INDENIZADO | C35: 0.39 | D35: 0.31
B38: TOTAL GERAL | C38: =C33+C26+C14+C4 -> 115.81 | D38: =D33+D26+D14+D4 -> 72.23
A42: ENCARGOS SOCIAIS
A44: Item | B44: Discriminação | C44: Horista | D44: Mensalista
A45: A | B45: ENCARGOS SOCIAIS BÁSICOS | C45: =SUM(C46:C54) -> 16.8 | D45: =SUM(D46:D54) -> 16.8
A46: A-1 | B46: INSS | C46: 0 | D46: 0
A47: A-2 | B47: SESI | C47: 1.5 | D47: 1.5
A48: A-3 | B48: SENAI | C48: 1 | D48: 1
A49: A-4 | B49: INCRA | C49: 0.2 | D49: 0.2
A50: A-5 | B50: SEBRAE | C50: 0.6 | D50: 0.6
A51: A-6 | B51: SALÁRIO EDUCAÇÃO | C51: 2.5 | D51: 2.5
A52: A-7 | B52: SEGURO CONTRA ACIDENTES DE TRABALHO | C52: 3 | D52: 3
A53: A-8 | B53: FGTS | C53: 8 | D53: 8
A54: A-9 | B54: SECONCI | C54: 0 | D54: 0
A55: B | B55: ENCARGOS SOCIAIS QUE RECEBEM AS INCIDÊNCIAS DE "A" | C55: =SUM(C56:C66) -> 50.51 | D55: =SUM(D56:D66) -> 20.28
A56: B-1 | B56: REPOUSO SEMANAL REMUNERADO | C56: 18.01 | D56: 0
A57: B-2 | B57: FERIADOS | C57: 4.3 | D57: 0
A58: B-3 | B58: AUXILIO - ENFERMIDADE | C58: 0.87 | D58: 0.67
A59: B-4 | B59: 13º SALARIO | C59: 10.78 | D59: 8.33
A60: B-5 | B60: LICENÇA PATERNIDADE | C60: 0.07 | D60: 0.06
A61: B-6 | B61: FALTAS JUSTIFICADAS | C61: 0.72 | D61: 0.56
A62: B-7 | B62: DIAS DE CHUVAS | C62: 1.98 | D62: -
A63: B-8 | B63: AUXILIO ACIDENTE DE TRABALHO | C63: 0.11 | D63: 0.08
A64: B-9 | B64: FÉRIAS GOZADAS | C64: 13.64 | D64: 10.55
A65: B-10 | B65: SALÁRIO MATERNIDADE | C65: 0.03 | D65: 0.03
A67: C | B67: ENCARGOS SOCIAIS QUE NÃO RECEBEM AS INCIDÊNCIAS DE "A" | C67: =SUM(C68:C73) -> 9.52 | D67: =SUM(D68:D73) -> 7.38
A68: C-1 | B68: AVISO PRÉVIO INDENIZADO | C68: 4.45 | D68: 3.45
A69: C-2 | B69: AVISO PRÉVIO TRABALHADO | C69: 0.1 | D69: 0.08
A70: C-3 | B70: FÉRIAS INDENIZADAS | C70: 0.5 | D70: 0.39
A71: C-4 | B71: DEPÓSITO RECISÃO SEM JUSTA CAUSA | C71: 4.1 | D71: 3.17
A72: C-5 | B72: INDENIZAÇÃO ADICIONAL | C72: 0.37 | D72: 0.29
A74: D | B74: TAXAS DE REINCIDÊNCIAS DE UM GRUPO SOBRE O OUTRO | C74: =SUM(C75:C78) -> 8.86 | D74: =SUM(D75:D78) -> 3.7
A75: D-1 | B75: REINCIDENCIA DE GRUPO A SOBRE GRUPO B | C75: 8.49 | D75: 3.41
A76: D-2 | B76: REINCIDENCIA DE GRUPO A SOBRE AVISO PRÉVIO TRABALHADO E REINCIDENCIA DO FGTS SOBRE AVISO PRÉVIO INDENIZADO | C76: 0.37 | D76: 0.29
B79: TOTAL GERAL | C79: =C74+C67+C55+C45 -> 85.69 | D79: =D74+D67+D55+D45 -> 48.16

Sheet BDI
H1: ESPORTE, CIDADANIA E DESENVOLVIMENTO
A3: (*) | B3: PROGRAMA: | C3: Esporte, Cidadania e Desenvolvimento
A4: (*) | B4: CONCEDENTE: | C4: =capa!C27 -> Prefeitura Municipal de Coremas - PB
A5: (*) | B5: CONVENENTE: | C5: Município de Coremas- PB
B6: CONTRATO: | C6: =capa!C26 -> RECURSOS GOVERNO DO ESTADO
B7: OBRA: | C7: =capa!C23 -> CONSTRUÇÃO DE QUADRA POLIESPORTIVA COM VESTIÁRIOS E BANHEIROS, NO MUNICÍPIO DE COREMAS/PB
A8: (*) | B8: REF. PREÇOS: | C8: SINAPI PB - 06/2025
B10: CÁLCULO DA BONIFICAÇÃO E DESPESAS INDIRETAS
B12: CÁLCULO DE BDI | D12: 1 - Edificações | G12: 2 - Rodovias, Ferrovias, Pistas de Aeroportos, Infra Viária Urbana | J12: 3 - Abastecimento de Água, Coleta de Esgoto | M12: 4 - Estações e Redes de Distribuição de Energia Elétrica | P12: 5 - Portuárias, Marítimas e Fluviais | S12: 6 - Fornecimento de Materiais e Equipamentos
B13: Item componente do BDI | C13: % Info | D13: 1ºQ | E13: Médio | F13: 3º Q | G13: 1ºQ | H13: Médio | I13: 3º Q | J13: 1ºQ | K13: Médio | L13: 3º Q | M13: 1ºQ | N13: Médio | O13: 3º Q | P13: 1ºQ | Q13: Médio | R13: 3º Q | S13: 1ºQ | T13: Médio | U13: 3º Q
B14: Administração Central ( AC ) | C14: 3 | D14: 3 | E14: 4 | F14: 5.5 | G14: 3.8 | H14: 4.01 | I14: 4.67 | J14: 3.43 | K14: 4.93 | L14: 6.71 | M14: 5.29 | N14: 5.92 | O14: 7.93 | P14: 4 | Q14: 5.52 | R14: 7.85 | S14: 1.5 | T14: 3.45 | U14: 4.49
B15: Seguro e Garantia (G) | C15: 0.8 | D15: 0.8 | E15: 0.8 | F15: 1 | G15: 0.32 | H15: 0.4 | I15: 0.74 | J15: 0.28 | K15: 0.49 | L15: 0.75 | M15: 0.25 | N15: 0.51 | O15: 0.56 | P15: 0.81 | Q15: 1.22 | R15: 1.99 | S15: 0.3 | T15: 0.48 | U15: 0.82
B16: Risco (R) | C16: 0.97 | D16: 0.97 | E16: 1.27 | F16: 1.27 | G16: 0.5 | H16: 0.56 | I16: 0.97 | J16: 1 | K16: 1.39 | L16: 1.74 | M16: 1 | N16: 1.48 | O16: 1.97 | P16: 1.46 | Q16: 2.32 | R16: 3.16 | S16: 0.56 | T16: 0.85 | U16: 0.89
B17: Despesas Financeiras (DF) | C17: 0.59 | D17: 0.59 | E17: 1.23 | F17: 1.39 | G17: 1.02 | H17: 1.11 | I17: 1.21 | J17: 0.94 | K17: 0.99 | L17: 1.17 | M17: 1.01 | N17: 1.07 | O17: 1.11 | P17: 0.94 | Q17: 1.02 | R17: 1.33 | S17: 0.85 | T17: 0.85 | U17: 1.11
B18: Lucro (L) | C18: 6.16 | D18: 6.16 | E18: 7.4 | F18: 8.96 | G18: 6.64 | H18: 7.3 | I18: 8.69 | J18: 6.74 | K18: 8.04 | L18: 9.4 | M18: 8 | N18: 8.31 | O18: 9.51 | P18: 7.14 | Q18: 8.4 | R18: 10.43 | S18: 3.5 | T18: 5.11 | U18: 6.22
B19: Impostos (I) - PIS, COFINS, CPRB, ISSQN | C19: =6.15+4.5 -> 10.65 | D19: Conforme Legislação Específica
B20: Observações | G20: VALORES DE BDI POR TIPO DE OBRA
B21: 1) Preencher apenas a coluna % Informado (Coluna C) | G21: Tipo de Obra | M21: 1ºQ | N21: Médio | O21: 3º Q
B22: 2) Os impostos (I) normalmente aplicáveis são: PIS (0,65%), COFINS (3,00%), ISS (2,50% município Coremas-PB). | G22: 1 - Edificações | M22: 20.34 | N22: 22.12 | O22: 25
G23: 2 - Rodovias, Ferrovias, Pistas de Aeroportos, Infra Viária Urbana | M23: 19.6 | N23: 20.97 | O23: 24.23
B24: 3) O cálculo do BDI se baseia na fórmula abaixo utilizada pelo Acórdão 2622/13 do TCU, conforme CE GEPAD 354/2013 de 17/10/2013. | G24: 3 - Abastecimento de Água, Coleta de Esgotos | M24: 20.76 | N24: 24.18 | O24: 26.44
G25: 4 - Estações e Redes de Distribuição de Energia Elétrica | M25: 24 | N25: 25.84 | O25: 27.86
G26: 5 - Portuárias, Marítimas e Fluviais | M26: 22.8 | N26: 27.48 | O26: 30.95
B27: Fórmula Utilizada: | G27: 6 - Fornecimento de Materiais e Equipamentos | M27: 11.1 | N27: 14.02 | O27: 16.8
B31: B.D.I = | C31: =ROUND(((1+(C14+C15+C16)/100)*((1+C17/100)*(1+C18/100))/(1-C19/100))-1,4) -> 0.2522
B32: Observações sobre os % informados no cálculo do BDI, neste caso:
B33: =C7 -> CONSTRUÇÃO DE QUADRA POLIESPORTIVA COM VESTIÁRIOS E BANHEIROS, NO MUNICÍPIO DE COREMAS/PB
B34: Os valores % informados se enquadram nos limites do Acordão 2622/2013-TCU-Plenário | U34: PROJETO: Lincoln Cartaxo de Lira Júnior – Eng° Civil CREA 160 814 689 - 8 – Tel. (83) 9 9924 4447
F36: ='Plan.Orçam.'!#REF! -> #REF! | I36: 99346.74 | K36: =F36-I36 -> #REF!

Sheet BDI-Fornecimento
H1: ESPORTE, CIDADANIA E DESENVOLVIMENTO
A3: (*) | B3: PROGRAMA: | C3: =BDI!C3 -> Esporte, Cidadania e Desenvolvimento
A4: (*) | B4: CONCEDENTE: | C4: =BDI!C4 -> Prefeitura Municipal de Coremas - PB
A5: (*) | B5: CONVENENTE: | C5: =BDI!C5 -> Município de Coremas- PB
B6: CONTRATO: | C6: =BDI!C6 -> RECURSOS GOVERNO DO ESTADO
B7: OBRA: | C7: =BDI!C7 -> CONSTRUÇÃO DE QUADRA POLIESPORTIVA COM VESTIÁRIOS E BANHEIROS, NO MUNICÍPIO DE COREMAS/PB
A8: (*) | B8: REF. PREÇOS: | C8: =BDI!C8 -> SINAPI PB - 06/2025
B10: CÁLCULO DA BONIFICAÇÃO E DESPESAS INDIRETAS - FORNECIMENTO
B12: CÁLCULO DE BDI | D12: 1 - Edificações | G12: 2 - Rodovias, Ferrovias, Pistas de Aeroportos, Infra Viária Urbana | J12: 3 - Abastecimento de Água, Coleta de Esgoto | M12: 4 - Estações e Redes de Distribuição de Energia Elétrica | P12: 5 - Portuárias, Marítimas e Fluviais | S12: 6 - Fornecimento de Materiais e Equipamentos
B13: Item componente do BDI | C13: % Info | D13: 1ºQ | E13: Médio | F13: 3º Q | G13: 1ºQ | H13: Médio | I13: 3º Q | J13: 1ºQ | K13: Médio | L13: 3º Q | M13: 1ºQ | N13: Médio | O13: 3º Q | P13: 1ºQ | Q13: Médio | R13: 3º Q | S13: 1ºQ | T13: Médio | U13: 3º Q
B14: Administração Central ( AC ) | C14: 4 | D14: 3 | E14: 4 | F14: 5.5 | G14: 3.8 | H14: 4.01 | I14: 4.67 | J14: 3.43 | K14: 4.93 | L14: 6.71 | M14: 5.29 | N14: 5.92 | O14: 7.93 | P14: 4 | Q14: 5.52 | R14: 7.85 | S14: 1.5 | T14: 3.45 | U14: 4.49
B15: Seguro e Garantia (G) | C15: =T15 -> 0.48 | D15: 0.8 | E15: 0.8 | F15: 1 | G15: 0.32 | H15: 0.4 | I15: 0.74 | J15: 0.28 | K15: 0.49 | L15: 0.75 | M15: 0.25 | N15: 0.51 | O15: 0.56 | P15: 0.81 | Q15: 1.22 | R15: 1.99 | S15: 0.3 | T15: 0.48 | U15: 0.82
B16: Risco (R) | C16: =T16 -> 0.85 | D16: 0.97 | E16: 1.27 | F16: 1.27 | G16: 0.5 | H16: 0.56 | I16: 0.97 | J16: 1 | K16: 1.39 | L16: 1.74 | M16: 1 | N16: 1.48 | O16: 1.97 | P16: 1.46 | Q16: 2.32 | R16: 3.16 | S16: 0.56 | T16: 0.85 | U16: 0.89
B17: Despesas Financeiras (DF) | C17: =T17 -> 0.85 | D17: 0.59 | E17: 1.23 | F17: 1.39 | G17: 1.02 | H17: 1.11 | I17: 1.21 | J17: 0.94 | K17: 0.99 | L17: 1.17 | M17: 1.01 | N17: 1.07 | O17: 1.11 | P17: 0.94 | Q17: 1.02 | R17: 1.33 | S17: 0.85 | T17: 0.85 | U17: 1.11
B18: Lucro (L) | C18: 5.9 | D18: 6.16 | E18: 7.4 | F18: 8.96 | G18: 6.64 | H18: 7.3 | I18: 8.69 | J18: 6.74 | K18: 8.04 | L18: 9.4 | M18: 8 | N18: 8.31 | O18: 9.51 | P18: 7.14 | Q18: 8.4 | R18: 10.43 | S18: 3.5 | T18: 5.11 | U18: 6.22
B19: Impostos (I) - PIS, COFINS | C19: =0.65+3 -> 3.65 | D19: Conforme Legislação Específica
B20: Observações | G20: VALORES DE BDI POR TIPO DE OBRA
B21: 1) Preencher apenas a coluna % Informado (Coluna C) | G21: Tipo de Obra | M21: 1ºQ | N21: Médio | O21: 3º Q
B22: 2) Os impostos (I) normalmente aplicáveis são: PIS (0,65%), COFINS (3,00%). | G22: 1 - Edificações | M22: 20.34 | N22: 22.12 | O22: 25
G23: 2 - Rodovias, Ferrovias, Pistas de Aeroportos, Infra Viária Urbana | M23: 19.6 | N23: 20.97 | O23: 24.23
B24: 3) O cálculo do BDI se baseia na fórmula abaixo utilizada pelo Acórdão 2622/13 do TCU, conforme CE GEPAD 354/2013 de 17/10/2013. | G24: 3 - Abastecimento de Água, Coleta de Esgotos | M24: 20.76 | N24: 24.18 | O24: 26.44
G25: 4 - Estações e Redes de Distribuição de Energia Elétrica | M25: 24 | N25: 25.84 | O25: 27.86
G26: 5 - Portuárias, Marítimas e Fluviais | M26: 22.8 | N26: 27.48 | O26: 30.95
B27: Fórmula Utilizada: | G27: 6 - Fornecimento de Materiais e Equipamentos | M27: 11.1 | N27: 14.02 | O27: 16.8
B31: B.D.I = | C31: =ROUND(((1+(C14+C15+C16)/100)*((1+C17/100)*(1+C18/100))/(1-C19/100))-1,4) -> 0.1675
B32: Observações sobre os % informados no cálculo do BDI, neste caso:
B33: =C7 -> CONSTRUÇÃO DE QUADRA POLIESPORTIVA COM VESTIÁRIOS E BANHEIROS, NO MUNICÍPIO DE COREMAS/PB
B34: Os valores % informados se enquadram nos limites do Acordão 2622/2013-TCU-Plenário (CPRB desconsiderado) | U34: PROJETO: Lincoln Cartaxo de Lira Júnior – Eng° Civil CREA 160 814 689 - 8 – Tel. (83) 9 9924 4447
F36: ='Plan.Orçam.'!#REF! -> #REF! | I36: 99346.74 | K36: =F36-I36 -> #REF!

Sheet Cotação
B2: PROGRAMA: | C2: =Composição!D2 -> Esporte, Cidadania e Desenvolvimento
B3: CONCEDENTE: | C3: =Composição!D3 -> Prefeitura Municipal de Coremas - PB
B4: CONVENENTE: | C4: =Composição!D4 -> Município de Coremas- PB
B5: CONTRATO: | C5: =Composição!D5 -> RECURSOS GOVERNO DO ESTADO
B6: OBRA: | C6: =Composição!D6 -> CONSTRUÇÃO DE QUADRA POLIESPORTIVA COM VESTIÁRIOS E BANHEIROS, NO MUNICÍPIO DE COREMAS/PB
B7: REF. PREÇOS: | C7: =Composição!D7 -> SINAPI PB - 06/2025
B9: COTAÇÃO DE INSUMOS (MEDIANA)
B11: ITEM | C11: DESCRIÇÃO/FONTE | D11: TIPO | E11: UND | F11: CUSTO
B12: 1 | C12: PISO PODOTATIL DE CONCRETO - DIRECIONAL E ALERTA, 30 X 30 CM [MEDIANA] | E12: M2 | F12: =MEDIAN(F13:F15) -> 48
B13: =CONCATENATE(B12,".1") -> 1.1 | C13: IAC BLOCOS E PISOS (CNPJ: 15.170.465/0001-68) | E13: M2 | F13: 44
B14: =CONCATENATE(B12,".2") -> 1.2 | C14: CONSTRUFACIL COMERCIO DE MATERIAIS DE CONSTRUCAO EIRELI - ME (CNPJ 04.376.116/0001-80) | E14: M2 | F14: 64
B15: =CONCATENATE(B12,".3") -> 1.3 | C15: INTERBLOCK (CNPJ: 11.803.338/0001-06) | E15: M2 | F15: 48

Sheet Composição
B2: PROGRAMA: | D2: =BDI!C3 -> Esporte, Cidadania e Desenvolvimento
B3: CONCEDENTE: | D3: =BDI!C4 -> Prefeitura Municipal de Coremas - PB
B4: CONVENENTE: | D4: =BDI!C5 -> Município de Coremas- PB
B5: CONTRATO: | D5: =BDI!C6 -> RECURSOS GOVERNO DO ESTADO
B6: OBRA: | D6: =BDI!C7 -> CONSTRUÇÃO DE QUADRA POLIESPORTIVA COM VESTIÁRIOS E BANHEIROS, NO MUNICÍPIO DE COREMAS/PB
B7: REF. PREÇOS: | D7: =BDI!C8 -> SINAPI PB - 06/2025
B9: COMPOSIÇÃO DE CUSTOS
B11: ITEM | C11: FONTE | D11: TIPO | E11: CÓD | F11: Descrição da Composição | G11: Unid | H11: Quant | I11: Custo Unit, | J11: Custo Total
A12: =COUNTIF('Plan.Orçam.'!E:E,Composição!B12) -> 1 | B12: 1 | C12: PLACA DE OBRA EM CHAPA DE ACO GALVANIZADO [ADAPTADO SINAPI 74209/01] | G12: M2 | I12: =SUM(J13:J19) -> 497.93
B13: =CONCATENATE(B12,".1") -> 1.1 | C13: SINAPI PB | D13: COMPOSIÇÃO | E13: 88262 | F13: =IF(C13="COMPOSIÇÃO",VLOOKUP(E13,B:J,2,FALSE),IF($D13="COMPOSIÇÃO",VLOOKUP(Composição!$E13,'Sinapi_Comp-06.2023'!$G:$L,2,FALSE),VLOOKUP($E13,'Sinapi_Insum-06.2023'!$A:$E,2,FALSE))) -> CARPINTEIRO DE FORMAS COM ENCARGOS COMPLEMENTARES | G13: =IF(C13="COMPOSIÇÃO",VLOOKUP(E13,B:J,6,FALSE),IF($D13="COMPOSIÇÃO",VLOOKUP(Composição!$E13,'Sinapi_Comp-06.2023'!$G:$L,3,FALSE),VLOOKUP($E13,'Sinapi_Insum-06.2023'!$A:$E,3,FALSE))) -> H | H13: 1 | I13: =IF(C13="COMPOSIÇÃO",VLOOKUP(E13,B:J,8,FALSE),IF(C13="COTAÇÃO",VLOOKUP(E13,Cotação!B:F,7,FALSE),IF($D13="COMPOSIÇÃO",VLOOKUP(Composição!$E13,'Sinapi_Comp-06.2023'!$G:$L,5,FALSE),VLOOKUP($E13,'Sinapi_Insum-06.2023'!$A:$E,5,FALSE)))) -> 22.51 | J13: =ROUND(I13*H13,2) -> 22.51
B14: =CONCATENATE(B12,".2") -> 1.2 | C14: SINAPI PB | D14: COMPOSIÇÃO | E14: 88316 | F14: =IF(C14="COMPOSIÇÃO",VLOOKUP(E14,B:J,2,FALSE),IF($D14="COMPOSIÇÃO",VLOOKUP(Composição!$E14,'Sinapi_Comp-06.2023'!$G:$L,2,FALSE),VLOOKUP($E14,'Sinapi_Insum-06.2023'!$A:$E,2,FALSE))) -> SERVENTE COM ENCARGOS COMPLEMENTARES | G14: =IF(C14="COMPOSIÇÃO",VLOOKUP(E14,B:J,6,FALSE),IF($D14="COMPOSIÇÃO",VLOOKUP(Composição!$E14,'Sinapi_Comp-06.2023'!$G:$L,3,FALSE),VLOOKUP($E14,'Sinapi_Insum-06.2023'!$A:$E,3,FALSE))) -> H | H14: 2 | I14: =IF(C14="COMPOSIÇÃO",VLOOKUP(E14,B:J,8,FALSE),IF(C14="COTAÇÃO",VLOOKUP(E14,Cotação!B:F,7,FALSE),IF($D14="COMPOSIÇÃO",VLOOKUP(Composição!$E14,'Sinapi_Comp-06.2023'!$G:$L,5,FALSE),VLOOKUP($E14,'Sinapi_Insum-06.2023'!$A:$E,5,FALSE)))) -> 18.67 | J14: =ROUND(I14*H14,2) -> 37.34
B15: =CONCATENATE(B12,".3") -> 1.3 | C15: SINAPI PB | D15: COMPOSIÇÃO | E15: 94962 | F15: =IF(C15="COMPOSIÇÃO",VLOOKUP(E15,B:J,2,FALSE),IF($D15="COMPOSIÇÃO",VLOOKUP(Composição!$E15,'Sinapi_Comp-06.2023'!$G:$L,2,FALSE),VLOOKUP($E15,'Sinapi_Insum-06.2023'!$A:$E,2,FALSE))) -> CONCRETO MAGRO PARA LASTRO, TRAÇO 1:4,5:4,5 (EM MASSA SECA DE CIMENTO/ AREIA MÉDIA/ BRITA 1) - PREPARO MECÂNICO COM BETONEIRA 400 L. AF_05/2021 | G15: =IF(C15="COMPOSIÇÃO",VLOOKUP(E15,B:J,6,FALSE),IF($D15="COMPOSIÇÃO",VLOOKUP(Composição!$E15,'Sinapi_Comp-06.2023'!$G:$L,3,FALSE),VLOOKUP($E15,'Sinapi_Insum-06.2023'!$A:$E,3,FALSE))) -> M3 | H15: 0.01 | I15: =IF(C15="COMPOSIÇÃO",VLOOKUP(E15,B:J,8,FALSE),IF(C15="COTAÇÃO",VLOOKUP(E15,Cotação!B:F,7,FALSE),IF($D15="COMPOSIÇÃO",VLOOKUP(Composição!$E15,'Sinapi_Comp-06.2023'!$G:$L,5,FALSE),VLOOKUP($E15,'Sinapi_Insum-06.2023'!$A:$E,5,FALSE)))) -> 389.61 | J15: =ROUND(I15*H15,2) -> 3.9
B16: =CONCATENATE(B12,".4") -> 1.4 | C16: SINAPI PB | D16: INSUMO | E16: 4417 | F16: =IF(C16="COMPOSIÇÃO",VLOOKUP(E16,B:J,2,FALSE),IF($D16="COMPOSIÇÃO",VLOOKUP(Composição!$E16,'Sinapi_Comp-06.2023'!$G:$L,2,FALSE),VLOOKUP($E16,'Sinapi_Insum-06.2023'!$A:$E,2,FALSE))) -> SARRAFO NAO APARELHADO *2,5 X 7* CM, EM MACARANDUBA/MASSARANDUBA, ANGELIM, PEROBA-ROSA OU EQUIVALENTE DA REGIAO - BRUTA | G16: =IF(C16="COMPOSIÇÃO",VLOOKUP(E16,B:J,6,FALSE),IF($D16="COMPOSIÇÃO",VLOOKUP(Composição!$E16,'Sinapi_Comp-06.2023'!$G:$L,3,FALSE),VLOOKUP($E16,'Sinapi_Insum-06.2023'!$A:$E,3,FALSE))) -> M | H16: 1 | I16: =IF(C16="COMPOSIÇÃO",VLOOKUP(E16,B:J,8,FALSE),IF(C16="COTAÇÃO",VLOOKUP(E16,Cotação!B:F,7,FALSE),IF($D16="COMPOSIÇÃO",VLOOKUP(Composição!$E16,'Sinapi_Comp-06.2023'!$G:$L,5,FALSE),VLOOKUP($E16,'Sinapi_Insum-06.2023'!$A:$E,5,FALSE)))) -> 6.21 | J16: =ROUND(I16*H16,2) -> 6.21
B17: =CONCATENATE(B12,".5") -> 1.5 | C17: SINAPI PB | D17: INSUMO | E17: 4491 | F17: =IF(C17="COMPOSIÇÃO",VLOOKUP(E17,B:J,2,FALSE),IF($D17="COMPOSIÇÃO",VLOOKUP(Composição!$E17,'Sinapi_Comp-06.2023'!$G:$L,2,FALSE),VLOOKUP($E17,'Sinapi_Insum-06.2023'!$A:$E,2,FALSE))) -> PONTALETE *7,5 X 7,5* CM EM PINUS, MISTA OU EQUIVALENTE DA REGIAO - BRUTA | G17: =IF(C17="COMPOSIÇÃO",VLOOKUP(E17,B:J,6,FALSE),IF($D17="COMPOSIÇÃO",VLOOKUP(Composição!$E17,'Sinapi_Comp-06.2023'!$G:$L,3,FALSE),VLOOKUP($E17,'Sinapi_Insum-06.2023'!$A:$E,3,FALSE))) -> M | H17: 4 | I17: =IF(C17="COMPOSIÇÃO",VLOOKUP(E17,B:J,8,FALSE),IF(C17="COTAÇÃO",VLOOKUP(E17,Cotação!B:F,7,FALSE),IF($D17="COMPOSIÇÃO",VLOOKUP(Composição!$E17,'Sinapi_Comp-06.2023'!$G:$L,5,FALSE),VLOOKUP($E17,'Sinapi_Insum-06.2023'!$A:$E,5,FALSE)))) -> 12.03 | J17: =ROUND(I17*H17,2) -> 48.12
B18: =CONCATENATE(B12,".6") -> 1.6 | C18: SINAPI PB | D18: INSUMO | E18: 4813 | F18: =IF(C18="COMPOSIÇÃO",VLOOKUP(E18,B:J,2,FALSE),IF($D18="COMPOSIÇÃO",VLOOKUP(Composição!$E18,'Sinapi_Comp-06.2023'!$G:$L,2,FALSE),VLOOKUP($E18,'Sinapi_Insum-06.2023'!$A:$E,2,FALSE))) -> PLACA DE OBRA (PARA CONSTRUCAO CIVIL) EM CHAPA GALVANIZADA *N. 22*, ADESIVADA, DE *2,4 X 1,2* M (SEM POSTES PARA FIXACAO) | G18: =IF(C18="COMPOSIÇÃO",VLOOKUP(E18,B:J,6,FALSE),IF($D18="COMPOSIÇÃO",VLOOKUP(Composição!$E18,'Sinapi_Comp-06.2023'!$G:$L,3,FALSE),VLOOKUP($E18,'Sinapi_Insum-06.2023'!$A:$E,3,FALSE))) -> M2 | H18: 1 | I18: =IF(C18="COMPOSIÇÃO",VLOOKUP(E18,B:J,8,FALSE),IF(C18="COTAÇÃO",VLOOKUP(E18,Cotação!B:F,7,FALSE),IF($D18="COMPOSIÇÃO",VLOOKUP(Composição!$E18,'Sinapi_Comp-06.2023'!$G:$L,5,FALSE),VLOOKUP($E18,'Sinapi_Insum-06.2023'!$A:$E,5,FALSE)))) -> 377.5 | J18: =ROUND(I18*H18,2) -> 377.5
B19: =CONCATENATE(B12,".7") -> 1.7 | C19: SINAPI PB | D19: INSUMO | E19: 5075 | F19: =IF(C19="COMPOSIÇÃO",VLOOKUP(E19,B:J,2,FALSE),IF($D19="COMPOSIÇÃO",VLOOKUP(Composição!$E19,'Sinapi_Comp-06.2023'!$G:$L,2,FALSE),VLOOKUP($E19,'Sinapi_Insum-06.2023'!$A:$E,2,FALSE))) -> PREGO DE ACO POLIDO COM CABECA 18 X 30 (2 3/4 X 10) | G19: =IF(C19="COMPOSIÇÃO",VLOOKUP(E19,B:J,6,FALSE),IF($D19="COMPOSIÇÃO",VLOOKUP(Composição!$E19,'Sinapi_Comp-06.2023'!$G:$L,3,FALSE),VLOOKUP($E19,'Sinapi_Insum-06.2023'!$A:$E,3,FALSE))) -> KG | H19: 0.11 | I19: =IF(C19="COMPOSIÇÃO",VLOOKUP(E19,B:J,8,FALSE),IF(C19="COTAÇÃO",VLOOKUP(E19,Cotação!B:F,7,FALSE),IF($D19="COMPOSIÇÃO",VLOOKUP(Composição!$E19,'Sinapi_Comp-06.2023'!$G:$L,5,FALSE),VLOOKUP($E19,'Sinapi_Insum-06.2023'!$A:$E,5,FALSE)))) -> 21.36 | J19: =ROUND(I19*H19,2) -> 2.35
A20: =COUNTIF('Plan.Orçam.'!E:E,Composição!B20) -> 1 | B20: 2 | C20: =UPPER("Piso tátil direcional e/ou alerta, de concreto, na cor natural, p/deficientes visuais, dimensões 25x25cm, aplicado com argamassa industrializada ac-ii, rejuntado, exclusive regularização de base (ADAPTADO DE 09418/ORSE)") -> PISO TÁTIL DIRECIONAL E/OU ALERTA, DE CONCRETO, NA COR NATURAL, P/DEFICIENTES VISUAIS, DIMENSÕES 25X25CM, APLICADO COM ARGAMASSA INDUSTRIALIZADA AC-II, REJUNTADO, EXCLUSIVE REGULARIZAÇÃO DE BASE (ADAPTADO DE 09418/ORSE) | G20: M2 | I20: =SUM(J21:J25) -> 90.74
B21: =CONCATENATE(B20,".1") -> 2.1 | C21: SINAPI PB | D21: INSUMO | E21: 34357 | F21: =IF(C21="COMPOSIÇÃO",VLOOKUP(E21,B:J,2,FALSE),IF($D21="COMPOSIÇÃO",VLOOKUP(Composição!$E21,'Sinapi_Comp-06.2023'!$G:$L,2,FALSE),VLOOKUP($E21,'Sinapi_Insum-06.2023'!$A:$E,2,FALSE))) -> REJUNTE CIMENTICIO, QUALQUER COR | G21: =IF(C21="COMPOSIÇÃO",VLOOKUP(E21,B:J,6,FALSE),IF($D21="COMPOSIÇÃO",VLOOKUP(Composição!$E21,'Sinapi_Comp-06.2023'!$G:$L,3,FALSE),VLOOKUP($E21,'Sinapi_Insum-06.2023'!$A:$E,3,FALSE))) -> KG | H21: 0.52 | I21: =IF(C21="COMPOSIÇÃO",VLOOKUP(E21,B:J,8,FALSE),IF(C21="COTAÇÃO",VLOOKUP(E21,Cotação!B:F,7,FALSE),IF($D21="COMPOSIÇÃO",VLOOKUP(Composição!$E21,'Sinapi_Comp-06.2023'!$G:$L,5,FALSE),VLOOKUP($E21,'Sinapi_Insum-06.2023'!$A:$E,5,FALSE)))) -> 5.05 | J21: =ROUND(I21*H21,2) -> 2.63
B22: =CONCATENATE(B20,".2") -> 2.2 | C22: SINAPI PB | D22: INSUMO | E22: 371 | F22: =IF(C22="COMPOSIÇÃO",VLOOKUP(E22,B:J,2,FALSE),IF($D22="COMPOSIÇÃO",VLOOKUP(Composição!$E22,'Sinapi_Comp-06.2023'!$G:$L,2,FALSE),VLOOKUP($E22,'Sinapi_Insum-06.2023'!$A:$E,2,FALSE))) -> ARGAMASSA INDUSTRIALIZADA MULTIUSO, PARA REVESTIMENTO INTERNO E EXTERNO E ASSENTAMENTO DE BLOCOS DIVERSOS | G22: =IF(C22="COMPOSIÇÃO",VLOOKUP(E22,B:J,6,FALSE),IF($D22="COMPOSIÇÃO",VLOOKUP(Composição!$E22,'Sinapi_Comp-06.2023'!$G:$L,3,FALSE),VLOOKUP($E22,'Sinapi_Insum-06.2023'!$A:$E,3,FALSE))) -> KG | H22: 4 | I22: =IF(C22="COMPOSIÇÃO",VLOOKUP(E22,B:J,8,FALSE),IF(C22="COTAÇÃO",VLOOKUP(E22,Cotação!B:F,7,FALSE),IF($D22="COMPOSIÇÃO",VLOOKUP(Composição!$E22,'Sinapi_Comp-06.2023'!$G:$L,5,FALSE),VLOOKUP($E22,'Sinapi_Insum-06.2023'!$A:$E,5,FALSE)))) -> 0.94 | J22: =ROUND(I22*H22,2) -> 3.76
B23: =CONCATENATE(B20,".3") -> 2.3 | C23: MERCADO | D23: COTAÇÃO | E23: =Cotação!B12 -> 1 | F23: =Cotação!C12 -> PISO PODOTATIL DE CONCRETO - DIRECIONAL E ALERTA, 30 X 30 CM [MEDIANA] | G23: =Cotação!E12 -> M2 | H23: 1.05 | I23: =Cotação!F12 -> 48 | J23: =ROUND(I23*H23,2) -> 50.4
B24: =CONCATENATE(B20,".4") -> 2.4 | C24: SINAPI PB | D24: COMPOSIÇÃO | E24: 88309 | F24: =IF(C24="COMPOSIÇÃO",VLOOKUP(E24,B:J,2,FALSE),IF($D24="COMPOSIÇÃO",VLOOKUP(Composição!$E24,'Sinapi_Comp-06.2023'!$G:$L,2,FALSE),VLOOKUP($E24,'Sinapi_Insum-06.2023'!$A:$E,2,FALSE))) -> PEDREIRO COM ENCARGOS COMPLEMENTARES | G24: =IF(C24="COMPOSIÇÃO",VLOOKUP(E24,B:J,6,FALSE),IF($D24="COMPOSIÇÃO",VLOOKUP(Composição!$E24,'Sinapi_Comp-06.2023'!$G:$L,3,FALSE),VLOOKUP($E24,'Sinapi_Insum-06.2023'!$A:$E,3,FALSE))) -> H | H24: 0.5 | I24: =IF(C24="COMPOSIÇÃO",VLOOKUP(E24,B:J,8,FALSE),IF(C24="COTAÇÃO",VLOOKUP(E24,Cotação!B:F,7,FALSE),IF($D24="COMPOSIÇÃO",VLOOKUP(Composição!$E24,'Sinapi_Comp-06.2023'!$G:$L,5,FALSE),VLOOKUP($E24,'Sinapi_Insum-06.2023'!$A:$E,5,FALSE)))) -> 23.1 | J24: =ROUND(I24*H24,2) -> 11.55
B25: =CONCATENATE(B20,".5") -> 2.5 | C25: SINAPI PB | D25: COMPOSIÇÃO | E25: 88316 | F25: =Cotação!C12 -> PISO PODOTATIL DE CONCRETO - DIRECIONAL E ALERTA, 30 X 30 CM [MEDIANA] | G25: =IF(C25="COMPOSIÇÃO",VLOOKUP(E25,B:J,6,FALSE),IF($D25="COMPOSIÇÃO",VLOOKUP(Composição!$E25,'Sinapi_Comp-06.2023'!$G:$L,3,FALSE),VLOOKUP($E25,'Sinapi_Insum-06.2023'!$A:$E,3,FALSE))) -> H | H25: 1.2 | I25: =IF(C25="COMPOSIÇÃO",VLOOKUP(E25,B:J,8,FALSE),IF(C25="COTAÇÃO",VLOOKUP(E25,Cotação!B:F,7,FALSE),IF($D25="COMPOSIÇÃO",VLOOKUP(Composição!$E25,'Sinapi_Comp-06.2023'!$G:$L,5,FALSE),VLOOKUP($E25,'Sinapi_Insum-06.2023'!$A:$E,5,FALSE)))) -> 18.67 | J25: =ROUND(I25*H25,2) -> 22.4
A26: =COUNTIF('Plan.Orçam.'!E:E,Composição!B26) -> 1 | B26: 3 | C26: ESTRUTURA METÁLICA MÓVEL PARA TABELA EM AÇO COM ARO PARA BASQUETE, PADRÃO OFICIAL, EM TUBO GALVANIZADO D=5" - INSTALADA (ADAPTADO DE ORSE 2419)") | G26: UN | I26: =SUM(J27:J30) -> 6887.88
B27: =CONCATENATE(B26,".1") -> 3.1 | C27: ORSE | D27: INSUMO | E27: 206 | F27: ARO PARA CESTA BASQUETE STANDART D=45 CM (COD. 4001) | G27: PAR | H27: 1 | I27: 488.82 | J27: =ROUND(I27*H27,2) -> 488.82
B28: =CONCATENATE(B26,".2") -> 3.2 | C28: ORSE | D28: INSUMO | E28: 932 | F28: ESTRUTURA / SUPORTE OFICIAL P/ TABELA DE BASQUETE EM TUBO AÇO GALVANIZADO D=5" H=3,05M PISO ARO, PINTURA SINTÉTICA, FORNECIMENTO E INSTALAÇÃO | G28: PAR | H28: 1 | I28: 3432.32 | J28: =ROUND(I28*H28,2) -> 3432.32
B29: =CONCATENATE(B26,".3") -> 3.3 | C29: ORSE | D29: INSUMO | E29: 1929 | F29: REDE PARA CESTA BASQUETE SEDA FIO 3 MM, MEDINDO 45X45 CM (COD. 2019) | G29: PAR | H29: 1 | I29: 46.65 | J29: =ROUND(I29*H29,2) -> 46.65
B30: =CONCATENATE(B26,".4") -> 3.4 | C30: ORSE | D30: INSUMO | E30: 4811 | F30: TABELA PARA BASQUETE OFICIAL EM CHAPA METÁLICA MEDINDO 1,80X1,05 (COD. 4006) | G30: PAR | H30: 1 | I30: 2920.09 | J30: =ROUND(I30*H30,2) -> 2920.09
A31: =COUNTIF('Plan.Orçam.'!E:E,Composição!B31) -> 1 | B31: 4 | C31: FUNDO PREPARADOR PRIMER A BASE DE EPOXI, PARA ESTRUTURA METALICA, UMA DEMAO, ESPESSURA DE 25 MICRA (ADAPTADO DE SINAPI 73865/1) | G31: M2 | I31: =SUM(J32:J36) -> 16.95
B32: =CONCATENATE(B31,".1") -> 4.1 | C32: SINAPI PB | D32: INSUMO | E32: 3768 | F32: =IF(C32="COMPOSIÇÃO",VLOOKUP(E32,B:J,2,FALSE),IF($D32="COMPOSIÇÃO",VLOOKUP(Composição!$E32,'Sinapi_Comp-06.2023'!$G:$L,2,FALSE),VLOOKUP($E32,'Sinapi_Insum-06.2023'!$A:$E,2,FALSE))) -> LIXA EM FOLHA PARA FERRO, NUMERO 150 | G32: =IF(C32="COMPOSIÇÃO",VLOOKUP(E32,B:J,6,FALSE),IF($D32="COMPOSIÇÃO",VLOOKUP(Composição!$E32,'Sinapi_Comp-06.2023'!$G:$L,3,FALSE),VLOOKUP($E32,'Sinapi_Insum-06.2023'!$A:$E,3,FALSE))) -> UN | H32: 0.25 | I32: =IF(C32="COMPOSIÇÃO",VLOOKUP(E32,B:J,8,FALSE),IF(C32="COTAÇÃO",VLOOKUP(E32,Cotação!B:F,7,FALSE),IF($D32="COMPOSIÇÃO",VLOOKUP(Composição!$E32,'Sinapi_Comp-06.2023'!$G:$L,5,FALSE),VLOOKUP($E32,'Sinapi_Insum-06.2023'!$A:$E,5,FALSE)))) -> 2.54 | J32: =ROUND(I32*H32,2) -> 0.64
B33: =CONCATENATE(B31,".2") -> 4.2 | C33: SINAPI PB | D33: INSUMO | E33: 5318 | F33: =IF(C33="COMPOSIÇÃO",VLOOKUP(E33,B:J,2,FALSE),IF($D33="COMPOSIÇÃO",VLOOKUP(Composição!$E33,'Sinapi_Comp-06.2023'!$G:$L,2,FALSE),VLOOKUP($E33,'Sinapi_Insum-06.2023'!$A:$E,2,FALSE))) -> DILUENTE AGUARRAS | G33: =IF(C33="COMPOSIÇÃO",VLOOKUP(E33,B:J,6,FALSE),IF($D33="COMPOSIÇÃO",VLOOKUP(Composição!$E33,'Sinapi_Comp-06.2023'!$G:$L,3,FALSE),VLOOKUP($E33,'Sinapi_Insum-06.2023'!$A:$E,3,FALSE))) -> L | H33: 0.03 | I33: =IF(C33="COMPOSIÇÃO",VLOOKUP(E33,B:J,8,FALSE),IF(C33="COTAÇÃO",VLOOKUP(E33,Cotação!B:F,7,FALSE),IF($D33="COMPOSIÇÃO",VLOOKUP(Composição!$E33,'Sinapi_Comp-06.2023'!$G:$L,5,FALSE),VLOOKUP($E33,'Sinapi_Insum-06.2023'!$A:$E,5,FALSE)))) -> 19.39 | J33: =ROUND(I33*H33,2) -> 0.58
B34: =CONCATENATE(B31,".3") -> 4.3 | C34: SINAPI PB | D34: INSUMO | E34: 44072 | F34: =IF(C34="COMPOSIÇÃO",VLOOKUP(E34,B:J,2,FALSE),IF($D34="COMPOSIÇÃO",VLOOKUP(Composição!$E34,'Sinapi_Comp-06.2023'!$G:$L,2,FALSE),VLOOKUP($E34,'Sinapi_Insum-06.2023'!$A:$E,2,FALSE))) -> PRIMER EPOXI / EPOXIDICO | G34: =IF(C34="COMPOSIÇÃO",VLOOKUP(E34,B:J,6,FALSE),IF($D34="COMPOSIÇÃO",VLOOKUP(Composição!$E34,'Sinapi_Comp-06.2023'!$G:$L,3,FALSE),VLOOKUP($E34,'Sinapi_Insum-06.2023'!$A:$E,3,FALSE))) -> L | H34: =0.033*3.6 -> 0.1188 | I34: =IF(C34="COMPOSIÇÃO",VLOOKUP(E34,B:J,8,FALSE),IF(C34="COTAÇÃO",VLOOKUP(E34,Cotação!B:F,7,FALSE),IF($D34="COMPOSIÇÃO",VLOOKUP(Composição!$E34,'Sinapi_Comp-06.2023'!$G:$L,5,FALSE),VLOOKUP($E34,'Sinapi_Insum-06.2023'!$A:$E,5,FALSE)))) -> 109.62 | J34: =ROUND(I34*H34,2) -> 13.02
B35: =CONCATENATE(B31,".4") -> 4.4 | C35: SINAPI PB | D35: COMPOSIÇÃO | E35: 88310 | F35: =IF(C35="COMPOSIÇÃO",VLOOKUP(E35,B:J,2,FALSE),IF($D35="COMPOSIÇÃO",VLOOKUP(Composição!$E35,'Sinapi_Comp-06.2023'!$G:$L,2,FALSE),VLOOKUP($E35,'Sinapi_Insum-06.2023'!$A:$E,2,FALSE))) -> PINTOR COM ENCARGOS COMPLEMENTARES | G35: =IF(C35="COMPOSIÇÃO",VLOOKUP(E35,B:J,6,FALSE),IF($D35="COMPOSIÇÃO",VLOOKUP(Composição!$E35,'Sinapi_Comp-06.2023'!$G:$L,3,FALSE),VLOOKUP($E35,'Sinapi_Insum-06.2023'!$A:$E,3,FALSE))) -> H | H35: 0.08 | I35: =IF(C35="COMPOSIÇÃO",VLOOKUP(E35,B:J,8,FALSE),IF(C35="COTAÇÃO",VLOOKUP(E35,Cotação!B:F,7,FALSE),IF($D35="COMPOSIÇÃO",VLOOKUP(Composição!$E35,'Sinapi_Comp-06.2023'!$G:$L,5,FALSE),VLOOKUP($E35,'Sinapi_Insum-06.2023'!$A:$E,5,FALSE)))) -> 24.53 | J35: =ROUND(I35*H35,2) -> 1.96
B36: =CONCATENATE(B31,".5") -> 4.5 | C36: SINAPI PB | D36: COMPOSIÇÃO | E36: 88316 | F36: =IF(C36="COMPOSIÇÃO",VLOOKUP(E36,B:J,2,FALSE),IF($D36="COMPOSIÇÃO",VLOOKUP(Composição!$E36,'Sinapi_Comp-06.2023'!$G:$L,2,FALSE),VLOOKUP($E36,'Sinapi_Insum-06.2023'!$A:$E,2,FALSE))) -> SERVENTE COM ENCARGOS COMPLEMENTARES | G36: =IF(C36="COMPOSIÇÃO",VLOOKUP(E36,B:J,6,FALSE),IF($D36="COMPOSIÇÃO",VLOOKUP(Composição!$E36,'Sinapi_Comp-06.2023'!$G:$L,3,FALSE),VLOOKUP($E36,'Sinapi_Insum-06.2023'!$A:$E,3,FALSE))) -> H | H36: 0.04 | I36: =IF(C36="COMPOSIÇÃO",VLOOKUP(E36,B:J,8,FALSE),IF(C36="COTAÇÃO",VLOOKUP(E36,Cotação!B:F,7,FALSE),IF($D36="COMPOSIÇÃO",VLOOKUP(Composição!$E36,'Sinapi_Comp-06.2023'!$G:$L,5,FALSE),VLOOKUP($E36,'Sinapi_Insum-06.2023'!$A:$E,5,FALSE)))) -> 18.67 | J36: =ROUND(I36*H36,2) -> 0.75
A37: =COUNTIF('Plan.Orçam.'!E:E,Composição!B37) -> 1 | B37: 5 | C37: PINTURA ESMALTE FOSCO, DUAS DEMAOS, SOBRE SUPERFICIE METALICA, INCLUSO UMA DEMAO DE FUNDO ANTICORROSIVO. UTILIZACAO DE REVOLVER ( AR-COMPRIMIDO) (ADAPTADO DE SINAPI 74145/1) | G37: M2 | I37: =SUM(J38:J43) -> 20.77
B38: =CONCATENATE(B37,".1") -> 5.1 | C38: SINAPI PB | D38: INSUMO | E38: 3768 | F38: =IF(C38="COMPOSIÇÃO",VLOOKUP(E38,B:J,2,FALSE),IF($D38="COMPOSIÇÃO",VLOOKUP(Composição!$E38,'Sinapi_Comp-06.2023'!$G:$L,2,FALSE),VLOOKUP($E38,'Sinapi_Insum-06.2023'!$A:$E,2,FALSE))) -> LIXA EM FOLHA PARA FERRO, NUMERO 150 | G38: =IF(C38="COMPOSIÇÃO",VLOOKUP(E38,B:J,6,FALSE),IF($D38="COMPOSIÇÃO",VLOOKUP(Composição!$E38,'Sinapi_Comp-06.2023'!$G:$L,3,FALSE),VLOOKUP($E38,'Sinapi_Insum-06.2023'!$A:$E,3,FALSE))) -> UN | H38: 0.55 | I38: =IF(C38="COMPOSIÇÃO",VLOOKUP(E38,B:J,8,FALSE),IF(C38="COTAÇÃO",VLOOKUP(E38,Cotação!B:F,7,FALSE),IF($D38="COMPOSIÇÃO",VLOOKUP(Composição!$E38,'Sinapi_Comp-06.2023'!$G:$L,5,FALSE),VLOOKUP($E38,'Sinapi_Insum-06.2023'!$A:$E,5,FALSE)))) -> 2.54 | J38: =ROUND(I38*H38,2) -> 1.4
B39: =CONCATENATE(B37,".2") -> 5.2 | C39: SINAPI PB | D39: INSUMO | E39: 5318 | F39: =IF(C39="COMPOSIÇÃO",VLOOKUP(E39,B:J,2,FALSE),IF($D39="COMPOSIÇÃO",VLOOKUP(Composição!$E39,'Sinapi_Comp-06.2023'!$G:$L,2,FALSE),VLOOKUP($E39,'Sinapi_Insum-06.2023'!$A:$E,2,FALSE))) -> DILUENTE AGUARRAS | G39: =IF(C39="COMPOSIÇÃO",VLOOKUP(E39,B:J,6,FALSE),IF($D39="COMPOSIÇÃO",VLOOKUP(Composição!$E39,'Sinapi_Comp-06.2023'!$G:$L,3,FALSE),VLOOKUP($E39,'Sinapi_Insum-06.2023'!$A:$E,3,FALSE))) -> L | H39: 0.044 | I39: =IF(C39="COMPOSIÇÃO",VLOOKUP(E39,B:J,8,FALSE),IF(C39="COTAÇÃO",VLOOKUP(E39,Cotação!B:F,7,FALSE),IF($D39="COMPOSIÇÃO",VLOOKUP(Composição!$E39,'Sinapi_Comp-06.2023'!$G:$L,5,FALSE),VLOOKUP($E39,'Sinapi_Insum-06.2023'!$A:$E,5,FALSE)))) -> 19.39 | J39: =ROUND(I39*H39,2) -> 0.85
B40: =CONCATENATE(B37,".3") -> 5.3 | C40: SINAPI PB | D40: INSUMO | E40: 7288 | F40: =IF(C40="COMPOSIÇÃO",VLOOKUP(E40,B:J,2,FALSE),IF($D40="COMPOSIÇÃO",VLOOKUP(Composição!$E40,'Sinapi_Comp-06.2023'!$G:$L,2,FALSE),VLOOKUP($E40,'Sinapi_Insum-06.2023'!$A:$E,2,FALSE))) -> TINTA ESMALTE SINTETICO PREMIUM FOSCO | G40: =IF(C40="COMPOSIÇÃO",VLOOKUP(E40,B:J,6,FALSE),IF($D40="COMPOSIÇÃO",VLOOKUP(Composição!$E40,'Sinapi_Comp-06.2023'!$G:$L,3,FALSE),VLOOKUP($E40,'Sinapi_Insum-06.2023'!$A:$E,3,FALSE))) -> L | H40: 0.176 | I40: =IF(C40="COMPOSIÇÃO",VLOOKUP(E40,B:J,8,FALSE),IF(C40="COTAÇÃO",VLOOKUP(E40,Cotação!B:F,7,FALSE),IF($D40="COMPOSIÇÃO",VLOOKUP(Composição!$E40,'Sinapi_Comp-06.2023'!$G:$L,5,FALSE),VLOOKUP($E40,'Sinapi_Insum-06.2023'!$A:$E,5,FALSE)))) -> 35.77 | J40: =ROUND(I40*H40,2) -> 6.3
B41: =CONCATENATE(B37,".4") -> 5.4 | C41: SINAPI PB | D41: INSUMO | E41: 7307 | F41: =IF(C41="COMPOSIÇÃO",VLOOKUP(E41,B:J,2,FALSE),IF($D41="COMPOSIÇÃO",VLOOKUP(Composição!$E41,'Sinapi_Comp-06.2023'!$G:$L,2,FALSE),VLOOKUP($E41,'Sinapi_Insum-06.2023'!$A:$E,2,FALSE))) -> FUNDO ANTICORROSIVO PARA METAIS FERROSOS (ZARCAO) | G41: =IF(C41="COMPOSIÇÃO",VLOOKUP(E41,B:J,6,FALSE),IF($D41="COMPOSIÇÃO",VLOOKUP(Composição!$E41,'Sinapi_Comp-06.2023'!$G:$L,3,FALSE),VLOOKUP($E41,'Sinapi_Insum-06.2023'!$A:$E,3,FALSE))) -> L | H41: 0.132 | I41: =IF(C41="COMPOSIÇÃO",VLOOKUP(E41,B:J,8,FALSE),IF(C41="COTAÇÃO",VLOOKUP(E41,Cotação!B:F,7,FALSE),IF($D41="COMPOSIÇÃO",VLOOKUP(Composição!$E41,'Sinapi_Comp-06.2023'!$G:$L,5,FALSE),VLOOKUP($E41,'Sinapi_Insum-06.2023'!$A:$E,5,FALSE)))) -> 38.06 | J41: =ROUND(I41*H41,2) -> 5.02
B42: =CONCATENATE(B37,".5") -> 5.5 | C42: SINAPI PB | D42: COMPOSIÇÃO | E42: 88310 | F42: =IF(C42="COMPOSIÇÃO",VLOOKUP(E42,B:J,2,FALSE),IF($D42="COMPOSIÇÃO",VLOOKUP(Composição!$E42,'Sinapi_Comp-06.2023'!$G:$L,2,FALSE),VLOOKUP($E42,'Sinapi_Insum-06.2023'!$A:$E,2,FALSE))) -> PINTOR COM ENCARGOS COMPLEMENTARES | G42: =IF(C42="COMPOSIÇÃO",VLOOKUP(E42,B:J,6,FALSE),IF($D42="COMPOSIÇÃO",VLOOKUP(Composição!$E42,'Sinapi_Comp-06.2023'!$G:$L,3,FALSE),VLOOKUP($E42,'Sinapi_Insum-06.2023'!$A:$E,3,FALSE))) -> H | H42: 0.21 | I42: =IF(C42="COMPOSIÇÃO",VLOOKUP(E42,B:J,8,FALSE),IF(C42="COTAÇÃO",VLOOKUP(E42,Cotação!B:F,7,FALSE),IF($D42="COMPOSIÇÃO",VLOOKUP(Composição!$E42,'Sinapi_Comp-06.2023'!$G:$L,5,FALSE),VLOOKUP($E42,'Sinapi_Insum-06.2023'!$A:$E,5,FALSE)))) -> 24.53 | J42: =ROUND(I42*H42,2) -> 5.15
B43: =CONCATENATE(B37,".6") -> 5.6 | C43: SINAPI PB | D43: COMPOSIÇÃO | E43: 88316 | F43: =IF(C43="COMPOSIÇÃO",VLOOKUP(E43,B:J,2,FALSE),IF($D43="COMPOSIÇÃO",VLOOKUP(Composição!$E43,'Sinapi_Comp-06.2023'!$G:$L,2,FALSE),VLOOKUP($E43,'Sinapi_Insum-06.2023'!$A:$E,2,FALSE))) -> SERVENTE COM ENCARGOS COMPLEMENTARES | G43: =IF(C43="COMPOSIÇÃO",VLOOKUP(E43,B:J,6,FALSE),IF($D43="COMPOSIÇÃO",VLOOKUP(Composição!$E43,'Sinapi_Comp-06.2023'!$G:$L,3,FALSE),VLOOKUP($E43,'Sinapi_Insum-06.2023'!$A:$E,3,FALSE))) -> H | H43: 0.11 | I43: =IF(C43="COMPOSIÇÃO",VLOOKUP(E43,B:J,8,FALSE),IF(C43="COTAÇÃO",VLOOKUP(E43,Cotação!B:F,7,FALSE),IF($D43="COMPOSIÇÃO",VLOOKUP(Composição!$E43,'Sinapi_Comp-06.2023'!$G:$L,5,FALSE),VLOOKUP($E43,'Sinapi_Insum-06.2023'!$A:$E,5,FALSE)))) -> 18.67 | J43: =ROUND(I43*H43,2) -> 2.05
A44: =COUNTIF('Plan.Orçam.'!E:E,Composição!B44) -> 1 | B44: 6 | C44: LIMPEZA FINAL DA OBRA (ADAPTADO DE SINAPI 9537) | G44: M2 | I44: =SUM(J45:J46) -> 3.35
B45: =CONCATENATE(B44,".1") -> 6.1 | C45: SINAPI PB | D45: COMPOSIÇÃO | E45: 88316 | F45: =IF(C45="COMPOSIÇÃO",VLOOKUP(E45,B:J,2,FALSE),IF($D45="COMPOSIÇÃO",VLOOKUP(Composição!$E45,'Sinapi_Comp-06.2023'!$G:$L,2,FALSE),VLOOKUP($E45,'Sinapi_Insum-06.2023'!$A:$E,2,FALSE))) -> SERVENTE COM ENCARGOS COMPLEMENTARES | G45: =IF(C45="COMPOSIÇÃO",VLOOKUP(E45,B:J,6,FALSE),IF($D45="COMPOSIÇÃO",VLOOKUP(Composição!$E45,'Sinapi_Comp-06.2023'!$G:$L,3,FALSE),VLOOKUP($E45,'Sinapi_Insum-06.2023'!$A:$E,3,FALSE))) -> H | H45: 0.14 | I45: =IF(C45="COMPOSIÇÃO",VLOOKUP(E45,B:J,8,FALSE),IF(C45="COTAÇÃO",VLOOKUP(E45,Cotação!B:F,7,FALSE),IF($D45="COMPOSIÇÃO",VLOOKUP(Composição!$E45,'Sinapi_Comp-06.2023'!$G:$L,5,FALSE),VLOOKUP($E45,'Sinapi_Insum-06.2023'!$A:$E,5,FALSE)))) -> 18.67 | J45: =ROUND(I45*H45,2) -> 2.61
B46: =CONCATENATE(B44,".2") -> 6.2 | C46: SINAPI PB | D46: INSUMO | E46: 3 | F46: =IF(C46="COMPOSIÇÃO",VLOOKUP(E46,B:J,2,FALSE),IF($D46="COMPOSIÇÃO",VLOOKUP(Composição!$E46,'Sinapi_Comp-06.2023'!$G:$L,2,FALSE),VLOOKUP($E46,'Sinapi_Insum-06.2023'!$A:$E,2,FALSE))) -> ACIDO CLORIDRICO / ACIDO MURIATICO, DILUICAO 10% A 12% PARA USO EM LIMPEZA | G46: =IF(C46="COMPOSIÇÃO",VLOOKUP(E46,B:J,6,FALSE),IF($D46="COMPOSIÇÃO",VLOOKUP(Composição!$E46,'Sinapi_Comp-06.2023'!$G:$L,3,FALSE),VLOOKUP($E46,'Sinapi_Insum-06.2023'!$A:$E,3,FALSE))) -> L | H46: 0.05 | I46: =IF(C46="COMPOSIÇÃO",VLOOKUP(E46,B:J,8,FALSE),IF(C46="COTAÇÃO",VLOOKUP(E46,Cotação!B:F,7,FALSE),IF($D46="COMPOSIÇÃO",VLOOKUP(Composição!$E46,'Sinapi_Comp-06.2023'!$G:$L,5,FALSE),VLOOKUP($E46,'Sinapi_Insum-06.2023'!$A:$E,5,FALSE)))) -> 14.72 | J46: =ROUND(I46*H46,2) -> 0.74
A47: 1 | B47: 7 | C47: CAMADA DRENANTE COM BRITA NUM 3 (ADAPTADO DE SINAPI 73902/1) | G47: M3 | I47: =SUM(J48:J49) -> 150.04
B48: =CONCATENATE(B47,".1") -> 7.1 | C48: SINAPI PB | D48: INSUMO | E48: 4722 | F48: =IF(C48="COMPOSIÇÃO",VLOOKUP(E48,B:J,2,FALSE),IF($D48="COMPOSIÇÃO",VLOOKUP(Composição!$E48,'Sinapi_Comp-06.2023'!$G:$L,2,FALSE),VLOOKUP($E48,'Sinapi_Insum-06.2023'!$A:$E,2,FALSE))) -> PEDRA BRITADA N. 3 (38 A 50 MM) POSTO PEDREIRA/FORNECEDOR, SEM FRETE | G48: =IF(C48="COMPOSIÇÃO",VLOOKUP(E48,B:J,6,FALSE),IF($D48="COMPOSIÇÃO",VLOOKUP(Composição!$E48,'Sinapi_Comp-06.2023'!$G:$L,3,FALSE),VLOOKUP($E48,'Sinapi_Insum-06.2023'!$A:$E,3,FALSE))) -> M3 | H48: 1.1 | I48: =IF(C48="COMPOSIÇÃO",VLOOKUP(E48,B:J,8,FALSE),IF(C48="COTAÇÃO",VLOOKUP(E48,Cotação!B:F,7,FALSE),IF($D48="COMPOSIÇÃO",VLOOKUP(Composição!$E48,'Sinapi_Comp-06.2023'!$G:$L,5,FALSE),VLOOKUP($E48,'Sinapi_Insum-06.2023'!$A:$E,5,FALSE)))) -> 93.96 | J48: =ROUND(I48*H48,2) -> 103.36
B49: =CONCATENATE(B47,".2") -> 7.2 | C49: SINAPI PB | D49: COMPOSIÇÃO | E49: 88316 | F49: =IF(C49="COMPOSIÇÃO",VLOOKUP(E49,B:J,2,FALSE),IF($D49="COMPOSIÇÃO",VLOOKUP(Composição!$E49,'Sinapi_Comp-06.2023'!$G:$L,2,FALSE),VLOOKUP($E49,'Sinapi_Insum-06.2023'!$A:$E,2,FALSE))) -> SERVENTE COM ENCARGOS COMPLEMENTARES | G49: =IF(C49="COMPOSIÇÃO",VLOOKUP(E49,B:J,6,FALSE),IF($D49="COMPOSIÇÃO",VLOOKUP(Composição!$E49,'Sinapi_Comp-06.2023'!$G:$L,3,FALSE),VLOOKUP($E49,'Sinapi_Insum-06.2023'!$A:$E,3,FALSE))) -> H | H49: 2.5 | I49: =IF(C49="COMPOSIÇÃO",VLOOKUP(E49,B:J,8,FALSE),IF(C49="COTAÇÃO",VLOOKUP(E49,Cotação!B:F,7,FALSE),IF($D49="COMPOSIÇÃO",VLOOKUP(Composição!$E49,'Sinapi_Comp-06.2023'!$G:$L,5,FALSE),VLOOKUP($E49,'Sinapi_Insum-06.2023'!$A:$E,5,FALSE)))) -> 18.67 | J49: =ROUND(I49*H49,2) -> 46.68
A50: =COUNTIF('Plan.Orçam.'!E:E,Composição!B50) -> 2 | B50: 8 | C50: ESCAVACAO MANUAL EM SOLO-PROF. ATE 1,50 M [ADAPTADO SINAPI 79561/001] | G50: M3 | I50: =SUM(J51) -> 37.34
B51: =CONCATENATE(B50,".1") -> 8.1 | C51: SINAPI PB | D51: COMPOSIÇÃO | E51: 88316 | F51: =IF(C51="COMPOSIÇÃO",VLOOKUP(E51,B:J,2,FALSE),IF($D51="COMPOSIÇÃO",VLOOKUP(Composição!$E51,'Sinapi_Comp-06.2023'!$G:$L,2,FALSE),VLOOKUP($E51,'Sinapi_Insum-06.2023'!$A:$E,2,FALSE))) -> SERVENTE COM ENCARGOS COMPLEMENTARES | G51: =IF(C51="COMPOSIÇÃO",VLOOKUP(E51,B:J,6,FALSE),IF($D51="COMPOSIÇÃO",VLOOKUP(Composição!$E51,'Sinapi_Comp-06.2023'!$G:$L,3,FALSE),VLOOKUP($E51,'Sinapi_Insum-06.2023'!$A:$E,3,FALSE))) -> H | H51: 2 | I51: =IF(C51="COMPOSIÇÃO",VLOOKUP(E51,B:J,8,FALSE),IF(C51="COTAÇÃO",VLOOKUP(E51,Cotação!B:F,7,FALSE),IF($D51="COMPOSIÇÃO",VLOOKUP(Composição!$E51,'Sinapi_Comp-06.2023'!$G:$L,5,FALSE),VLOOKUP($E51,'Sinapi_Insum-06.2023'!$A:$E,5,FALSE)))) -> 18.67 | J51: =ROUND(I51*H51,2) -> 37.34
A52: =COUNTIF('Plan.Orçam.'!E:E,Composição!B52) -> 0 | B52: 9 | C52: EMBASAMENTO C/PEDRA ARGAMASSADA UTILIZANDO ARG.CIM/AREIA 1:4 [ADAPTADO SINAPI 75467/001] | G52: M3 | I52: =SUM(J53:J56) -> 491.25
B53: =CONCATENATE(B52,".1") -> 9.1 | C53: SINAPI PB | D53: COMPOSIÇÃO | E53: 87316 | F53: =IF(C53="COMPOSIÇÃO",VLOOKUP(E53,B:J,2,FALSE),IF($D53="COMPOSIÇÃO",VLOOKUP(Composição!$E53,'Sinapi_Comp-06.2023'!$G:$L,2,FALSE),VLOOKUP($E53,'Sinapi_Insum-06.2023'!$A:$E,2,FALSE))) -> ARGAMASSA TRAÇO 1:4 (EM VOLUME DE CIMENTO E AREIA GROSSA ÚMIDA) PARA CHAPISCO CONVENCIONAL, PREPARO MECÂNICO COM BETONEIRA 400 L. AF_08/2019 | G53: =IF(C53="COMPOSIÇÃO",VLOOKUP(E53,B:J,6,FALSE),IF($D53="COMPOSIÇÃO",VLOOKUP(Composição!$E53,'Sinapi_Comp-06.2023'!$G:$L,3,FALSE),VLOOKUP($E53,'Sinapi_Insum-06.2023'!$A:$E,3,FALSE))) -> M3 | H53: 0.3 | I53: =IF(C53="COMPOSIÇÃO",VLOOKUP(E53,B:J,8,FALSE),IF(C53="COTAÇÃO",VLOOKUP(E53,Cotação!B:F,7,FALSE),IF($D53="COMPOSIÇÃO",VLOOKUP(Composição!$E53,'Sinapi_Comp-06.2023'!$G:$L,5,FALSE),VLOOKUP($E53,'Sinapi_Insum-06.2023'!$A:$E,5,FALSE)))) -> 459.28 | J53: =ROUND(I53*H53,2) -> 137.78
B54: =CONCATENATE(B52,".2") -> 9.2 | C54: SINAPI PB | D54: COMPOSIÇÃO | E54: 88309 | F54: =IF(C54="COMPOSIÇÃO",VLOOKUP(E54,B:J,2,FALSE),IF($D54="COMPOSIÇÃO",VLOOKUP(Composição!$E54,'Sinapi_Comp-06.2023'!$G:$L,2,FALSE),VLOOKUP($E54,'Sinapi_Insum-06.2023'!$A:$E,2,FALSE))) -> PEDREIRO COM ENCARGOS COMPLEMENTARES | G54: =IF(C54="COMPOSIÇÃO",VLOOKUP(E54,B:J,6,FALSE),IF($D54="COMPOSIÇÃO",VLOOKUP(Composição!$E54,'Sinapi_Comp-06.2023'!$G:$L,3,FALSE),VLOOKUP($E54,'Sinapi_Insum-06.2023'!$A:$E,3,FALSE))) -> H | H54: 6 | I54: =IF(C54="COMPOSIÇÃO",VLOOKUP(E54,B:J,8,FALSE),IF(C54="COTAÇÃO",VLOOKUP(E54,Cotação!B:F,7,FALSE),IF($D54="COMPOSIÇÃO",VLOOKUP(Composição!$E54,'Sinapi_Comp-06.2023'!$G:$L,5,FALSE),VLOOKUP($E54,'Sinapi_Insum-06.2023'!$A:$E,5,FALSE)))) -> 23.1 | J54: =ROUND(I54*H54,2) -> 138.6
B55: =CONCATENATE(B52,".3") -> 9.3 | C55: SINAPI PB | D55: COMPOSIÇÃO | E55: 88316 | F55: =IF(C55="COMPOSIÇÃO",VLOOKUP(E55,B:J,2,FALSE),IF($D55="COMPOSIÇÃO",VLOOKUP(Composição!$E55,'Sinapi_Comp-06.2023'!$G:$L,2,FALSE),VLOOKUP($E55,'Sinapi_Insum-06.2023'!$A:$E,2,FALSE))) -> SERVENTE COM ENCARGOS COMPLEMENTARES | G55: =IF(C55="COMPOSIÇÃO",VLOOKUP(E55,B:J,6,FALSE),IF($D55="COMPOSIÇÃO",VLOOKUP(Composição!$E55,'Sinapi_Comp-06.2023'!$G:$L,3,FALSE),VLOOKUP($E55,'Sinapi_Insum-06.2023'!$A:$E,3,FALSE))) -> H | H55: 6 | I55: =IF(C55="COMPOSIÇÃO",VLOOKUP(E55,B:J,8,FALSE),IF(C55="COTAÇÃO",VLOOKUP(E55,Cotação!B:F,7,FALSE),IF($D55="COMPOSIÇÃO",VLOOKUP(Composição!$E55,'Sinapi_Comp-06.2023'!$G:$L,5,FALSE),VLOOKUP($E55,'Sinapi_Insum-06.2023'!$A:$E,5,FALSE)))) -> 18.67 | J55: =ROUND(I55*H55,2) -> 112.02
B56: =CONCATENATE(B52,".4") -> 9.4 | C56: SINAPI PB | D56: INSUMO | E56: 4730 | F56: =IF(C56="COMPOSIÇÃO",VLOOKUP(E56,B:J,2,FALSE),IF($D56="COMPOSIÇÃO",VLOOKUP(Composição!$E56,'Sinapi_Comp-06.2023'!$G:$L,2,FALSE),VLOOKUP($E56,'Sinapi_Insum-06.2023'!$A:$E,2,FALSE))) -> PEDRA DE MAO OU PEDRA RACHAO PARA ARRIMO/FUNDACAO (POSTO PEDREIRA/FORNECEDOR, SEM FRETE) | G56: =IF(C56="COMPOSIÇÃO",VLOOKUP(E56,B:J,6,FALSE),IF($D56="COMPOSIÇÃO",VLOOKUP(Composição!$E56,'Sinapi_Comp-06.2023'!$G:$L,3,FALSE),VLOOKUP($E56,'Sinapi_Insum-06.2023'!$A:$E,3,FALSE))) -> M3 | H56: 1.1 | I56: =IF(C56="COMPOSIÇÃO",VLOOKUP(E56,B:J,8,FALSE),IF(C56="COTAÇÃO",VLOOKUP(E56,Cotação!B:F,7,FALSE),IF($D56="COMPOSIÇÃO",VLOOKUP(Composição!$E56,'Sinapi_Comp-06.2023'!$G:$L,5,FALSE),VLOOKUP($E56,'Sinapi_Insum-06.2023'!$A:$E,5,FALSE)))) -> 93.5 | J56: =ROUND(I56*H56,2) -> 102.85
A57: =COUNTIF('Plan.Orçam.'!E:E,Composição!B57) -> 1 | B57: 10 | C57: ALVENARIA EM TIJOLO CERAMICO FURADO 9X19X19CM, 1 VEZ (ESPESSURA 19 CM), ASSENTADO EM ARGAMASSA TRACO 1:4 (CIMENTO E AREIA MEDIA NAO PENEIRADA), PREPARO MANUAL, JUNTA1 CM [ADAPTADO SINAPI 73935/002] | G57: M2 | I57: =SUM(J58:J61) -> 97.96
B58: =CONCATENATE(B57,".1") -> 10.1 | C58: SINAPI PB | D58: COMPOSIÇÃO | E58: 87373 | F58: =IF(C58="COMPOSIÇÃO",VLOOKUP(E58,B:J,2,FALSE),IF($D58="COMPOSIÇÃO",VLOOKUP(Composição!$E58,'Sinapi_Comp-06.2023'!$G:$L,2,FALSE),VLOOKUP($E58,'Sinapi_Insum-06.2023'!$A:$E,2,FALSE))) -> ARGAMASSA TRAÇO 1:4 (EM VOLUME DE CIMENTO E AREIA MÉDIA ÚMIDA) PARA CONTRAPISO, PREPARO MANUAL. AF_08/2019 | G58: =IF(C58="COMPOSIÇÃO",VLOOKUP(E58,B:J,6,FALSE),IF($D58="COMPOSIÇÃO",VLOOKUP(Composição!$E58,'Sinapi_Comp-06.2023'!$G:$L,3,FALSE),VLOOKUP($E58,'Sinapi_Insum-06.2023'!$A:$E,3,FALSE))) -> M3 | H58: 0.0138 | I58: =IF(C58="COMPOSIÇÃO",VLOOKUP(E58,B:J,8,FALSE),IF(C58="COTAÇÃO",VLOOKUP(E58,Cotação!B:F,7,FALSE),IF($D58="COMPOSIÇÃO",VLOOKUP(Composição!$E58,'Sinapi_Comp-06.2023'!$G:$L,5,FALSE),VLOOKUP($E58,'Sinapi_Insum-06.2023'!$A:$E,5,FALSE)))) -> 712.94 | J58: =ROUND(I58*H58,2) -> 9.84
B59: =CONCATENATE(B57,".2") -> 10.2 | C59: SINAPI PB | D59: COMPOSIÇÃO | E59: 88309 | F59: =IF(C59="COMPOSIÇÃO",VLOOKUP(E59,B:J,2,FALSE),IF($D59="COMPOSIÇÃO",VLOOKUP(Composição!$E59,'Sinapi_Comp-06.2023'!$G:$L,2,FALSE),VLOOKUP($E59,'Sinapi_Insum-06.2023'!$A:$E,2,FALSE))) -> PEDREIRO COM ENCARGOS COMPLEMENTARES | G59: =IF(C59="COMPOSIÇÃO",VLOOKUP(E59,B:J,6,FALSE),IF($D59="COMPOSIÇÃO",VLOOKUP(Composição!$E59,'Sinapi_Comp-06.2023'!$G:$L,3,FALSE),VLOOKUP($E59,'Sinapi_Insum-06.2023'!$A:$E,3,FALSE))) -> H | H59: 1.14 | I59: =IF(C59="COMPOSIÇÃO",VLOOKUP(E59,B:J,8,FALSE),IF(C59="COTAÇÃO",VLOOKUP(E59,Cotação!B:F,7,FALSE),IF($D59="COMPOSIÇÃO",VLOOKUP(Composição!$E59,'Sinapi_Comp-06.2023'!$G:$L,5,FALSE),VLOOKUP($E59,'Sinapi_Insum-06.2023'!$A:$E,5,FALSE)))) -> 23.1 | J59: =ROUND(I59*H59,2) -> 26.33
B60: =CONCATENATE(B57,".3") -> 10.3 | C60: SINAPI PB | D60: COMPOSIÇÃO | E60: 88316 | F60: =IF(C60="COMPOSIÇÃO",VLOOKUP(E60,B:J,2,FALSE),IF($D60="COMPOSIÇÃO",VLOOKUP(Composição!$E60,'Sinapi_Comp-06.2023'!$G:$L,2,FALSE),VLOOKUP($E60,'Sinapi_Insum-06.2023'!$A:$E,2,FALSE))) -> SERVENTE COM ENCARGOS COMPLEMENTARES | G60: =IF(C60="COMPOSIÇÃO",VLOOKUP(E60,B:J,6,FALSE),IF($D60="COMPOSIÇÃO",VLOOKUP(Composição!$E60,'Sinapi_Comp-06.2023'!$G:$L,3,FALSE),VLOOKUP($E60,'Sinapi_Insum-06.2023'!$A:$E,3,FALSE))) -> H | H60: 0.88 | I60: =IF(C60="COMPOSIÇÃO",VLOOKUP(E60,B:J,8,FALSE),IF(C60="COTAÇÃO",VLOOKUP(E60,Cotação!B:F,7,FALSE),IF($D60="COMPOSIÇÃO",VLOOKUP(Composição!$E60,'Sinapi_Comp-06.2023'!$G:$L,5,FALSE),VLOOKUP($E60,'Sinapi_Insum-06.2023'!$A:$E,5,FALSE)))) -> 18.67 | J60: =ROUND(I60*H60,2) -> 16.43
B61: =CONCATENATE(B57,".4") -> 10.4 | C61: SINAPI PB | D61: INSUMO | E61: 7271 | F61: =IF(C61="COMPOSIÇÃO",VLOOKUP(E61,B:J,2,FALSE),IF($D61="COMPOSIÇÃO",VLOOKUP(Composição!$E61,'Sinapi_Comp-06.2023'!$G:$L,2,FALSE),VLOOKUP($E61,'Sinapi_Insum-06.2023'!$A:$E,2,FALSE))) -> BLOCO CERAMICO / TIJOLO VAZADO PARA ALVENARIA DE VEDACAO, 8 FUROS NA HORIZONTAL DE 9 X 19 X 19 CM (L X A X C) | G61: =IF(C61="COMPOSIÇÃO",VLOOKUP(E61,B:J,6,FALSE),IF($D61="COMPOSIÇÃO",VLOOKUP(Composição!$E61,'Sinapi_Comp-06.2023'!$G:$L,3,FALSE),VLOOKUP($E61,'Sinapi_Insum-06.2023'!$A:$E,3,FALSE))) -> UN | H61: 54 | I61: =IF(C61="COMPOSIÇÃO",VLOOKUP(E61,B:J,8,FALSE),IF(C61="COTAÇÃO",VLOOKUP(E61,Cotação!B:F,7,FALSE),IF($D61="COMPOSIÇÃO",VLOOKUP(Composição!$E61,'Sinapi_Comp-06.2023'!$G:$L,5,FALSE),VLOOKUP($E61,'Sinapi_Insum-06.2023'!$A:$E,5,FALSE)))) -> 0.84 | J61: =ROUND(I61*H61,2) -> 45.36
A62: =COUNTIF('Plan.Orçam.'!E:E,Composição!B62) -> 1 | B62: 11 | C62: IMPERMEABILIZACAO DE ESTRUTURAS ENTERRADAS, COM TINTA ASFALTICA, DUAS DEMAOS. [ADAPTADO SINAPI 74106/001] | G62: M2 | I62: =SUM(J63:J64) -> 14.07
B63: =CONCATENATE(B62,".1") -> 11.1 | C63: SINAPI PB | D63: COMPOSIÇÃO | E63: 88316 | F63: =IF(C63="COMPOSIÇÃO",VLOOKUP(E63,B:J,2,FALSE),IF($D63="COMPOSIÇÃO",VLOOKUP(Composição!$E63,'Sinapi_Comp-06.2023'!$G:$L,2,FALSE),VLOOKUP($E63,'Sinapi_Insum-06.2023'!$A:$E,2,FALSE))) -> SERVENTE COM ENCARGOS COMPLEMENTARES | G63: =IF(C63="COMPOSIÇÃO",VLOOKUP(E63,B:J,6,FALSE),IF($D63="COMPOSIÇÃO",VLOOKUP(Composição!$E63,'Sinapi_Comp-06.2023'!$G:$L,3,FALSE),VLOOKUP($E63,'Sinapi_Insum-06.2023'!$A:$E,3,FALSE))) -> H | H63: 0.4 | I63: =IF(C63="COMPOSIÇÃO",VLOOKUP(E63,B:J,8,FALSE),IF(C63="COTAÇÃO",VLOOKUP(E63,Cotação!B:F,7,FALSE),IF($D63="COMPOSIÇÃO",VLOOKUP(Composição!$E63,'Sinapi_Comp-06.2023'!$G:$L,5,FALSE),VLOOKUP($E63,'Sinapi_Insum-06.2023'!$A:$E,5,FALSE)))) -> 18.67 | J63: =ROUND(I63*H63,2) -> 7.47
B64: =CONCATENATE(B62,".2") -> 11.2 | C64: SINAPI PB | D64: INSUMO | E64: 7319 | F64: =IF(C64="COMPOSIÇÃO",VLOOKUP(E64,B:J,2,FALSE),IF($D64="COMPOSIÇÃO",VLOOKUP(Composição!$E64,'Sinapi_Comp-06.2023'!$G:$L,2,FALSE),VLOOKUP($E64,'Sinapi_Insum-06.2023'!$A:$E,2,FALSE))) -> TINTA ASFALTICA IMPERMEABILIZANTE DISPERSA EM AGUA, PARA MATERIAIS CIMENTICIOS | G64: =IF(C64="COMPOSIÇÃO",VLOOKUP(E64,B:J,6,FALSE),IF($D64="COMPOSIÇÃO",VLOOKUP(Composição!$E64,'Sinapi_Comp-06.2023'!$G:$L,3,FALSE),VLOOKUP($E64,'Sinapi_Insum-06.2023'!$A:$E,3,FALSE))) -> L | H64: 0.4 | I64: =IF(C64="COMPOSIÇÃO",VLOOKUP(E64,B:J,8,FALSE),IF(C64="COTAÇÃO",VLOOKUP(E64,Cotação!B:F,7,FALSE),IF($D64="COMPOSIÇÃO",VLOOKUP(Composição!$E64,'Sinapi_Comp-06.2023'!$G:$L,5,FALSE),VLOOKUP($E64,'Sinapi_Insum-06.2023'!$A:$E,5,FALSE)))) -> 16.5 | J64: =ROUND(I64*H64,2) -> 6.6
A65: =COUNTIF('Plan.Orçam.'!E:E,Composição!B65) -> 1 | B65: 12 | C65: COBOGO DE CONCRETO (ELEMENTO VAZADO), 7X50X50CM, ASSENTADO COM ARGAMASSA TRACO 1:3 (CIMENTO E AREIA) [ADAPTADO SINAPI 73937/003] | G65: M2 | I65: =SUM(J66:J69) -> 179.42
B66: =CONCATENATE(B65,".1") -> 12.1 | C66: SINAPI PB | D66: COMPOSIÇÃO | E66: 88309 | F66: =IF(C66="COMPOSIÇÃO",VLOOKUP(E66,B:J,2,FALSE),IF($D66="COMPOSIÇÃO",VLOOKUP(Composição!$E66,'Sinapi_Comp-06.2023'!$G:$L,2,FALSE),VLOOKUP($E66,'Sinapi_Insum-06.2023'!$A:$E,2,FALSE))) -> PEDREIRO COM ENCARGOS COMPLEMENTARES | G66: =IF(C66="COMPOSIÇÃO",VLOOKUP(E66,B:J,6,FALSE),IF($D66="COMPOSIÇÃO",VLOOKUP(Composição!$E66,'Sinapi_Comp-06.2023'!$G:$L,3,FALSE),VLOOKUP($E66,'Sinapi_Insum-06.2023'!$A:$E,3,FALSE))) -> H | H66: 0.85 | I66: =IF(C66="COMPOSIÇÃO",VLOOKUP(E66,B:J,8,FALSE),IF(C66="COTAÇÃO",VLOOKUP(E66,Cotação!B:F,7,FALSE),IF($D66="COMPOSIÇÃO",VLOOKUP(Composição!$E66,'Sinapi_Comp-06.2023'!$G:$L,5,FALSE),VLOOKUP($E66,'Sinapi_Insum-06.2023'!$A:$E,5,FALSE)))) -> 23.1 | J66: =ROUND(I66*H66,2) -> 19.64
B67: =CONCATENATE(B65,".2") -> 12.2 | C67: SINAPI PB | D67: COMPOSIÇÃO | E67: 88316 | F67: =IF(C67="COMPOSIÇÃO",VLOOKUP(E67,B:J,2,FALSE),IF($D67="COMPOSIÇÃO",VLOOKUP(Composição!$E67,'Sinapi_Comp-06.2023'!$G:$L,2,FALSE),VLOOKUP($E67,'Sinapi_Insum-06.2023'!$A:$E,2,FALSE))) -> SERVENTE COM ENCARGOS COMPLEMENTARES | G67: =IF(C67="COMPOSIÇÃO",VLOOKUP(E67,B:J,6,FALSE),IF($D67="COMPOSIÇÃO",VLOOKUP(Composição!$E67,'Sinapi_Comp-06.2023'!$G:$L,3,FALSE),VLOOKUP($E67,'Sinapi_Insum-06.2023'!$A:$E,3,FALSE))) -> H | H67: 0.85 | I67: =IF(C67="COMPOSIÇÃO",VLOOKUP(E67,B:J,8,FALSE),IF(C67="COTAÇÃO",VLOOKUP(E67,Cotação!B:F,7,FALSE),IF($D67="COMPOSIÇÃO",VLOOKUP(Composição!$E67,'Sinapi_Comp-06.2023'!$G:$L,5,FALSE),VLOOKUP($E67,'Sinapi_Insum-06.2023'!$A:$E,5,FALSE)))) -> 18.67 | J67: =ROUND(I67*H67,2) -> 15.87
B68: =CONCATENATE(B65,".3") -> 12.3 | C68: SINAPI PB | D68: COMPOSIÇÃO | E68: 88629 | F68: =IF(C68="COMPOSIÇÃO",VLOOKUP(E68,B:J,2,FALSE),IF($D68="COMPOSIÇÃO",VLOOKUP(Composição!$E68,'Sinapi_Comp-06.2023'!$G:$L,2,FALSE),VLOOKUP($E68,'Sinapi_Insum-06.2023'!$A:$E,2,FALSE))) -> ARGAMASSA TRAÇO 1:3 (EM VOLUME DE CIMENTO E AREIA MÉDIA ÚMIDA), PREPARO MANUAL. AF_08/2019 | G68: =IF(C68="COMPOSIÇÃO",VLOOKUP(E68,B:J,6,FALSE),IF($D68="COMPOSIÇÃO",VLOOKUP(Composição!$E68,'Sinapi_Comp-06.2023'!$G:$L,3,FALSE),VLOOKUP($E68,'Sinapi_Insum-06.2023'!$A:$E,3,FALSE))) -> M3 | H68: 0.0048 | I68: =IF(C68="COMPOSIÇÃO",VLOOKUP(E68,B:J,8,FALSE),IF(C68="COTAÇÃO",VLOOKUP(E68,Cotação!B:F,7,FALSE),IF($D68="COMPOSIÇÃO",VLOOKUP(Composição!$E68,'Sinapi_Comp-06.2023'!$G:$L,5,FALSE),VLOOKUP($E68,'Sinapi_Insum-06.2023'!$A:$E,5,FALSE)))) -> 647.87 | J68: =ROUND(I68*H68,2) -> 3.11
B69: =CONCATENATE(B65,".4") -> 12.4 | C69: SINAPI PB | D69: INSUMO | E69: 665 | F69: =IF(C69="COMPOSIÇÃO",VLOOKUP(E69,B:J,2,FALSE),IF($D69="COMPOSIÇÃO",VLOOKUP(Composição!$E69,'Sinapi_Comp-06.2023'!$G:$L,2,FALSE),VLOOKUP($E69,'Sinapi_Insum-06.2023'!$A:$E,2,FALSE))) -> ELEMENTO VAZADO DE CONCRETO, QUADRICULADO, 16 FUROS *50 X 50 X 7* CM | G69: =IF(C69="COMPOSIÇÃO",VLOOKUP(E69,B:J,6,FALSE),IF($D69="COMPOSIÇÃO",VLOOKUP(Composição!$E69,'Sinapi_Comp-06.2023'!$G:$L,3,FALSE),VLOOKUP($E69,'Sinapi_Insum-06.2023'!$A:$E,3,FALSE))) -> UN | H69: 4 | I69: =IF(C69="COMPOSIÇÃO",VLOOKUP(E69,B:J,8,FALSE),IF(C69="COTAÇÃO",VLOOKUP(E69,Cotação!B:F,7,FALSE),IF($D69="COMPOSIÇÃO",VLOOKUP(Composição!$E69,'Sinapi_Comp-06.2023'!$G:$L,5,FALSE),VLOOKUP($E69,'Sinapi_Insum-06.2023'!$A:$E,5,FALSE)))) -> 35.2 | J69: =ROUND(I69*H69,2) -> 140.8
A70: =COUNTIF('Plan.Orçam.'!E:E,Composição!B70) -> 1 | B70: 13 | C70: PORTAO DE FERRO EM CHAPA GALVANIZADA PLANA 14 GSG [ADAPTADO SINAPI 68054] | G70: M2 | I70: =SUM(J71:J78) -> 237.96
B71: =CONCATENATE(B70,".1") -> 13.1 | C71: SINAPI PB | D71: COMPOSIÇÃO | E71: 88309 | F71: =IF(C71="COMPOSIÇÃO",VLOOKUP(E71,B:J,2,FALSE),IF($D71="COMPOSIÇÃO",VLOOKUP(Composição!$E71,'Sinapi_Comp-06.2023'!$G:$L,2,FALSE),VLOOKUP($E71,'Sinapi_Insum-06.2023'!$A:$E,2,FALSE))) -> PEDREIRO COM ENCARGOS COMPLEMENTARES | G71: =IF(C71="COMPOSIÇÃO",VLOOKUP(E71,B:J,6,FALSE),IF($D71="COMPOSIÇÃO",VLOOKUP(Composição!$E71,'Sinapi_Comp-06.2023'!$G:$L,3,FALSE),VLOOKUP($E71,'Sinapi_Insum-06.2023'!$A:$E,3,FALSE))) -> H | H71: 1.5 | I71: =IF(C71="COMPOSIÇÃO",VLOOKUP(E71,B:J,8,FALSE),IF(C71="COTAÇÃO",VLOOKUP(E71,Cotação!B:F,7,FALSE),IF($D71="COMPOSIÇÃO",VLOOKUP(Composição!$E71,'Sinapi_Comp-06.2023'!$G:$L,5,FALSE),VLOOKUP($E71,'Sinapi_Insum-06.2023'!$A:$E,5,FALSE)))) -> 23.1 | J71: =ROUND(I71*H71,2) -> 34.65
B72: =CONCATENATE(B70,".2") -> 13.2 | C72: SINAPI PB | D72: COMPOSIÇÃO | E72: 88316 | F72: =IF(C72="COMPOSIÇÃO",VLOOKUP(E72,B:J,2,FALSE),IF($D72="COMPOSIÇÃO",VLOOKUP(Composição!$E72,'Sinapi_Comp-06.2023'!$G:$L,2,FALSE),VLOOKUP($E72,'Sinapi_Insum-06.2023'!$A:$E,2,FALSE))) -> SERVENTE COM ENCARGOS COMPLEMENTARES | G72: =IF(C72="COMPOSIÇÃO",VLOOKUP(E72,B:J,6,FALSE),IF($D72="COMPOSIÇÃO",VLOOKUP(Composição!$E72,'Sinapi_Comp-06.2023'!$G:$L,3,FALSE),VLOOKUP($E72,'Sinapi_Insum-06.2023'!$A:$E,3,FALSE))) -> H | H72: 1.5 | I72: =IF(C72="COMPOSIÇÃO",VLOOKUP(E72,B:J,8,FALSE),IF(C72="COTAÇÃO",VLOOKUP(E72,Cotação!B:F,7,FALSE),IF($D72="COMPOSIÇÃO",VLOOKUP(Composição!$E72,'Sinapi_Comp-06.2023'!$G:$L,5,FALSE),VLOOKUP($E72,'Sinapi_Insum-06.2023'!$A:$E,5,FALSE)))) -> 18.67 | J72: =ROUND(I72*H72,2) -> 28.01
B73: =CONCATENATE(B70,".3") -> 13.3 | C73: SINAPI PB | D73: INSUMO | E73: 370 | F73: =IF(C73="COMPOSIÇÃO",VLOOKUP(E73,B:J,2,FALSE),IF($D73="COMPOSIÇÃO",VLOOKUP(Composição!$E73,'Sinapi_Comp-06.2023'!$G:$L,2,FALSE),VLOOKUP($E73,'Sinapi_Insum-06.2023'!$A:$E,2,FALSE))) -> AREIA MEDIA - POSTO JAZIDA/FORNECEDOR (RETIRADO NA JAZIDA, SEM TRANSPORTE) | G73: =IF(C73="COMPOSIÇÃO",VLOOKUP(E73,B:J,6,FALSE),IF($D73="COMPOSIÇÃO",VLOOKUP(Composição!$E73,'Sinapi_Comp-06.2023'!$G:$L,3,FALSE),VLOOKUP($E73,'Sinapi_Insum-06.2023'!$A:$E,3,FALSE))) -> M3 | H73: 0.025 | I73: =IF(C73="COMPOSIÇÃO",VLOOKUP(E73,B:J,8,FALSE),IF(C73="COTAÇÃO",VLOOKUP(E73,Cotação!B:F,7,FALSE),IF($D73="COMPOSIÇÃO",VLOOKUP(Composição!$E73,'Sinapi_Comp-06.2023'!$G:$L,5,FALSE),VLOOKUP($E73,'Sinapi_Insum-06.2023'!$A:$E,5,FALSE)))) -> 140 | J73: =ROUND(I73*H73,2) -> 3.5
B74: =CONCATENATE(B70,".4") -> 13.4 | C74: SINAPI PB | D74: INSUMO | E74: 1106 | F74: =IF(C74="COMPOSIÇÃO",VLOOKUP(E74,B:J,2,FALSE),IF($D74="COMPOSIÇÃO",VLOOKUP(Composição!$E74,'Sinapi_Comp-06.2023'!$G:$L,2,FALSE),VLOOKUP($E74,'Sinapi_Insum-06.2023'!$A:$E,2,FALSE))) -> CAL HIDRATADA CH-I PARA ARGAMASSAS | G74: =IF(C74="COMPOSIÇÃO",VLOOKUP(E74,B:J,6,FALSE),IF($D74="COMPOSIÇÃO",VLOOKUP(Composição!$E74,'Sinapi_Comp-06.2023'!$G:$L,3,FALSE),VLOOKUP($E74,'Sinapi_Insum-06.2023'!$A:$E,3,FALSE))) -> KG | H74: 1 | I74: =IF(C74="COMPOSIÇÃO",VLOOKUP(E74,B:J,8,FALSE),IF(C74="COTAÇÃO",VLOOKUP(E74,Cotação!B:F,7,FALSE),IF($D74="COMPOSIÇÃO",VLOOKUP(Composição!$E74,'Sinapi_Comp-06.2023'!$G:$L,5,FALSE),VLOOKUP($E74,'Sinapi_Insum-06.2023'!$A:$E,5,FALSE)))) -> 1.1 | J74: =ROUND(I74*H74,2) -> 1.1
B75: =CONCATENATE(B70,".5") -> 13.5 | C75: SINAPI PB | D75: INSUMO | E75: 1379 | F75: =IF(C75="COMPOSIÇÃO",VLOOKUP(E75,B:J,2,FALSE),IF($D75="COMPOSIÇÃO",VLOOKUP(Composição!$E75,'Sinapi_Comp-06.2023'!$G:$L,2,FALSE),VLOOKUP($E75,'Sinapi_Insum-06.2023'!$A:$E,2,FALSE))) -> CIMENTO PORTLAND COMPOSTO CP II-32 | G75: =IF(C75="COMPOSIÇÃO",VLOOKUP(E75,B:J,6,FALSE),IF($D75="COMPOSIÇÃO",VLOOKUP(Composição!$E75,'Sinapi_Comp-06.2023'!$G:$L,3,FALSE),VLOOKUP($E75,'Sinapi_Insum-06.2023'!$A:$E,3,FALSE))) -> KG | H75: 0.0048 | I75: =IF(C75="COMPOSIÇÃO",VLOOKUP(E75,B:J,8,FALSE),IF(C75="COTAÇÃO",VLOOKUP(E75,Cotação!B:F,7,FALSE),IF($D75="COMPOSIÇÃO",VLOOKUP(Composição!$E75,'Sinapi_Comp-06.2023'!$G:$L,5,FALSE),VLOOKUP($E75,'Sinapi_Insum-06.2023'!$A:$E,5,FALSE)))) -> 0.7 | J75: =ROUND(I75*H75,2) -> 0
B76: =CONCATENATE(B70,".6") -> 13.6 | C76: SINAPI PB | D76: INSUMO | E76: 4777 | F76: =IF(C76="COMPOSIÇÃO",VLOOKUP(E76,B:J,2,FALSE),IF($D76="COMPOSIÇÃO",VLOOKUP(Composição!$E76,'Sinapi_Comp-06.2023'!$G:$L,2,FALSE),VLOOKUP($E76,'Sinapi_Insum-06.2023'!$A:$E,2,FALSE))) -> CANTONEIRA ACO ABAS IGUAIS (QUALQUER BITOLA), ESPESSURA ENTRE 1/8" E 1/4" | G76: =IF(C76="COMPOSIÇÃO",VLOOKUP(E76,B:J,6,FALSE),IF($D76="COMPOSIÇÃO",VLOOKUP(Composição!$E76,'Sinapi_Comp-06.2023'!$G:$L,3,FALSE),VLOOKUP($E76,'Sinapi_Insum-06.2023'!$A:$E,3,FALSE))) -> KG | H76: 4.6 | I76: =IF(C76="COMPOSIÇÃO",VLOOKUP(E76,B:J,8,FALSE),IF(C76="COTAÇÃO",VLOOKUP(E76,Cotação!B:F,7,FALSE),IF($D76="COMPOSIÇÃO",VLOOKUP(Composição!$E76,'Sinapi_Comp-06.2023'!$G:$L,5,FALSE),VLOOKUP($E76,'Sinapi_Insum-06.2023'!$A:$E,5,FALSE)))) -> 10.43 | J76: =ROUND(I76*H76,2) -> 47.98
B77: =CONCATENATE(B70,".7") -> 13.7 | C77: SINAPI PB | D77: INSUMO | E77: 11026 | F77: =IF(C77="COMPOSIÇÃO",VLOOKUP(E77,B:J,2,FALSE),IF($D77="COMPOSIÇÃO",VLOOKUP(Composição!$E77,'Sinapi_Comp-06.2023'!$G:$L,2,FALSE),VLOOKUP($E77,'Sinapi_Insum-06.2023'!$A:$E,2,FALSE))) -> CHAPA DE ACO GALVANIZADA BITOLA GSG 14, E = 1,95 MM (15,60 KG/M2) | G77: =IF(C77="COMPOSIÇÃO",VLOOKUP(E77,B:J,6,FALSE),IF($D77="COMPOSIÇÃO",VLOOKUP(Composição!$E77,'Sinapi_Comp-06.2023'!$G:$L,3,FALSE),VLOOKUP($E77,'Sinapi_Insum-06.2023'!$A:$E,3,FALSE))) -> KG | H77: 8.26 | I77: =IF(C77="COMPOSIÇÃO",VLOOKUP(E77,B:J,8,FALSE),IF(C77="COTAÇÃO",VLOOKUP(E77,Cotação!B:F,7,FALSE),IF($D77="COMPOSIÇÃO",VLOOKUP(Composição!$E77,'Sinapi_Comp-06.2023'!$G:$L,5,FALSE),VLOOKUP($E77,'Sinapi_Insum-06.2023'!$A:$E,5,FALSE)))) -> 9.85 | J77: =ROUND(I77*H77,2) -> 81.36
B78: =CONCATENATE(B70,".8") -> 13.8 | C78: SINAPI PB | D78: INSUMO | E78: 43054 | F78: =IF(C78="COMPOSIÇÃO",VLOOKUP(E78,B:J,2,FALSE),IF($D78="COMPOSIÇÃO",VLOOKUP(Composição!$E78,'Sinapi_Comp-06.2023'!$G:$L,2,FALSE),VLOOKUP($E78,'Sinapi_Insum-06.2023'!$A:$E,2,FALSE))) -> ACO CA-25, 10,0 MM, OU 12,5 MM, OU 16,0 MM, OU 20,0 MM, OU 25,0 MM, VERGALHAO | G78: =IF(C78="COMPOSIÇÃO",VLOOKUP(E78,B:J,6,FALSE),IF($D78="COMPOSIÇÃO",VLOOKUP(Composição!$E78,'Sinapi_Comp-06.2023'!$G:$L,3,FALSE),VLOOKUP($E78,'Sinapi_Insum-06.2023'!$A:$E,3,FALSE))) -> KG | H78: 5.1 | I78: =IF(C78="COMPOSIÇÃO",VLOOKUP(E78,B:J,8,FALSE),IF(C78="COTAÇÃO",VLOOKUP(E78,Cotação!B:F,7,FALSE),IF($D78="COMPOSIÇÃO",VLOOKUP(Composição!$E78,'Sinapi_Comp-06.2023'!$G:$L,5,FALSE),VLOOKUP($E78,'Sinapi_Insum-06.2023'!$A:$E,5,FALSE)))) -> 8.11 | J78: =ROUND(I78*H78,2) -> 41.36
A79: =COUNTIF('Plan.Orçam.'!E:E,Composição!B79) -> 1 | B79: 14 | C79: COMPACTACAO MECANICA, SEM CONTROLE DO GC (C/COMPACTADOR PLACA 400 KG) [ADAPTADO 74005/001] | G79: M2 | I79: =SUM(J80:J81) -> 22.17
B80: =CONCATENATE(B79,".1") -> 14.1 | C80: SINAPI PB | D80: COMPOSIÇÃO | E80: 88316 | F80: =IF(C80="COMPOSIÇÃO",VLOOKUP(E80,B:J,2,FALSE),IF($D80="COMPOSIÇÃO",VLOOKUP(Composição!$E80,'Sinapi_Comp-06.2023'!$G:$L,2,FALSE),VLOOKUP($E80,'Sinapi_Insum-06.2023'!$A:$E,2,FALSE))) -> SERVENTE COM ENCARGOS COMPLEMENTARES | G80: =IF(C80="COMPOSIÇÃO",VLOOKUP(E80,B:J,6,FALSE),IF($D80="COMPOSIÇÃO",VLOOKUP(Composição!$E80,'Sinapi_Comp-06.2023'!$G:$L,3,FALSE),VLOOKUP($E80,'Sinapi_Insum-06.2023'!$A:$E,3,FALSE))) -> H | H80: 0.25 | I80: =IF(C80="COMPOSIÇÃO",VLOOKUP(E80,B:J,8,FALSE),IF(C80="COTAÇÃO",VLOOKUP(E80,Cotação!B:F,7,FALSE),IF($D80="COMPOSIÇÃO",VLOOKUP(Composição!$E80,'Sinapi_Comp-06.2023'!$G:$L,5,FALSE),VLOOKUP($E80,'Sinapi_Insum-06.2023'!$A:$E,5,FALSE)))) -> 18.67 | J80: =ROUND(I80*H80,2) -> 4.67
B81: =CONCATENATE(B79,".2") -> 14.2 | C81: SINAPI PB | D81: INSUMO | E81: 370 | F81: =IF(C81="COMPOSIÇÃO",VLOOKUP(E81,B:J,2,FALSE),IF($D81="COMPOSIÇÃO",VLOOKUP(Composição!$E81,'Sinapi_Comp-06.2023'!$G:$L,2,FALSE),VLOOKUP($E81,'Sinapi_Insum-06.2023'!$A:$E,2,FALSE))) -> AREIA MEDIA - POSTO JAZIDA/FORNECEDOR (RETIRADO NA JAZIDA, SEM TRANSPORTE) | G81: =IF(C81="COMPOSIÇÃO",VLOOKUP(E81,B:J,6,FALSE),IF($D81="COMPOSIÇÃO",VLOOKUP(Composição!$E81,'Sinapi_Comp-06.2023'!$G:$L,3,FALSE),VLOOKUP($E81,'Sinapi_Insum-06.2023'!$A:$E,3,FALSE))) -> M3 | H81: 0.125 | I81: =IF(C81="COMPOSIÇÃO",VLOOKUP(E81,B:J,8,FALSE),IF(C81="COTAÇÃO",VLOOKUP(E81,Cotação!B:F,7,FALSE),IF($D81="COMPOSIÇÃO",VLOOKUP(Composição!$E81,'Sinapi_Comp-06.2023'!$G:$L,5,FALSE),VLOOKUP($E81,'Sinapi_Insum-06.2023'!$A:$E,5,FALSE)))) -> 140 | J81: =ROUND(I81*H81,2) -> 17.5
A82: =COUNTIF('Plan.Orçam.'!E:E,Composição!B82) -> 1 | B82: 15 | C82: PISO EM CONCRETO 20MPA PREPARO MECANICO, ESPESSURA 7 CM, COM ARMACAO EM TELA SOLDADA E ESPAÇADORES[ADAPTADO 72183] | G82: M2 | I82: =SUM(J83:J88) -> 102.94
B83: =CONCATENATE(B82,".1") -> 15.1 | C83: SINAPI PB | D83: COMPOSIÇÃO | E83: 88245 | F83: =IF(C83="COMPOSIÇÃO",VLOOKUP(E83,B:J,2,FALSE),IF($D83="COMPOSIÇÃO",VLOOKUP(Composição!$E83,'Sinapi_Comp-06.2023'!$G:$L,2,FALSE),VLOOKUP($E83,'Sinapi_Insum-06.2023'!$A:$E,2,FALSE))) -> ARMADOR COM ENCARGOS COMPLEMENTARES | G83: =IF(C83="COMPOSIÇÃO",VLOOKUP(E83,B:J,6,FALSE),IF($D83="COMPOSIÇÃO",VLOOKUP(Composição!$E83,'Sinapi_Comp-06.2023'!$G:$L,3,FALSE),VLOOKUP($E83,'Sinapi_Insum-06.2023'!$A:$E,3,FALSE))) -> H | H83: 0.02 | I83: =IF(C83="COMPOSIÇÃO",VLOOKUP(E83,B:J,8,FALSE),IF(C83="COTAÇÃO",VLOOKUP(E83,Cotação!B:F,7,FALSE),IF($D83="COMPOSIÇÃO",VLOOKUP(Composição!$E83,'Sinapi_Comp-06.2023'!$G:$L,5,FALSE),VLOOKUP($E83,'Sinapi_Insum-06.2023'!$A:$E,5,FALSE)))) -> 22.94 | J83: =ROUND(I83*H83,2) -> 0.46
B84: =CONCATENATE(B82,".2") -> 15.2 | C84: SINAPI PB | D84: COMPOSIÇÃO | E84: 88309 | F84: =IF(C84="COMPOSIÇÃO",VLOOKUP(E84,B:J,2,FALSE),IF($D84="COMPOSIÇÃO",VLOOKUP(Composição!$E84,'Sinapi_Comp-06.2023'!$G:$L,2,FALSE),VLOOKUP($E84,'Sinapi_Insum-06.2023'!$A:$E,2,FALSE))) -> PEDREIRO COM ENCARGOS COMPLEMENTARES | G84: =IF(C84="COMPOSIÇÃO",VLOOKUP(E84,B:J,6,FALSE),IF($D84="COMPOSIÇÃO",VLOOKUP(Composição!$E84,'Sinapi_Comp-06.2023'!$G:$L,3,FALSE),VLOOKUP($E84,'Sinapi_Insum-06.2023'!$A:$E,3,FALSE))) -> H | H84: 0.26 | I84: =IF(C84="COMPOSIÇÃO",VLOOKUP(E84,B:J,8,FALSE),IF(C84="COTAÇÃO",VLOOKUP(E84,Cotação!B:F,7,FALSE),IF($D84="COMPOSIÇÃO",VLOOKUP(Composição!$E84,'Sinapi_Comp-06.2023'!$G:$L,5,FALSE),VLOOKUP($E84,'Sinapi_Insum-06.2023'!$A:$E,5,FALSE)))) -> 23.1 | J84: =ROUND(I84*H84,2) -> 6.01
B85: =CONCATENATE(B82,".3") -> 15.3 | C85: SINAPI PB | D85: COMPOSIÇÃO | E85: 88316 | F85: =IF(C85="COMPOSIÇÃO",VLOOKUP(E85,B:J,2,FALSE),IF($D85="COMPOSIÇÃO",VLOOKUP(Composição!$E85,'Sinapi_Comp-06.2023'!$G:$L,2,FALSE),VLOOKUP($E85,'Sinapi_Insum-06.2023'!$A:$E,2,FALSE))) -> SERVENTE COM ENCARGOS COMPLEMENTARES | G85: =IF(C85="COMPOSIÇÃO",VLOOKUP(E85,B:J,6,FALSE),IF($D85="COMPOSIÇÃO",VLOOKUP(Composição!$E85,'Sinapi_Comp-06.2023'!$G:$L,3,FALSE),VLOOKUP($E85,'Sinapi_Insum-06.2023'!$A:$E,3,FALSE))) -> H | H85: 1.94 | I85: =IF(C85="COMPOSIÇÃO",VLOOKUP(E85,B:J,8,FALSE),IF(C85="COTAÇÃO",VLOOKUP(E85,Cotação!B:F,7,FALSE),IF($D85="COMPOSIÇÃO",VLOOKUP(Composição!$E85,'Sinapi_Comp-06.2023'!$G:$L,5,FALSE),VLOOKUP($E85,'Sinapi_Insum-06.2023'!$A:$E,5,FALSE)))) -> 18.67 | J85: =ROUND(I85*H85,2) -> 36.22
B86: =CONCATENATE(B82,".4") -> 15.4 | C86: SINAPI PB | D86: COMPOSIÇÃO | E86: 94970 | F86: =IF(C86="COMPOSIÇÃO",VLOOKUP(E86,B:J,2,FALSE),IF($D86="COMPOSIÇÃO",VLOOKUP(Composição!$E86,'Sinapi_Comp-06.2023'!$G:$L,2,FALSE),VLOOKUP($E86,'Sinapi_Insum-06.2023'!$A:$E,2,FALSE))) -> CONCRETO FCK = 20MPA, TRAÇO 1:2,7:3 (EM MASSA SECA DE CIMENTO/ AREIA MÉDIA/ BRITA 1) - PREPARO MECÂNICO COM BETONEIRA 600 L. AF_05/2021 | G86: =IF(C86="COMPOSIÇÃO",VLOOKUP(E86,B:J,6,FALSE),IF($D86="COMPOSIÇÃO",VLOOKUP(Composição!$E86,'Sinapi_Comp-06.2023'!$G:$L,3,FALSE),VLOOKUP($E86,'Sinapi_Insum-06.2023'!$A:$E,3,FALSE))) -> M3 | H86: 0.07 | I86: =IF(C86="COMPOSIÇÃO",VLOOKUP(E86,B:J,8,FALSE),IF(C86="COTAÇÃO",VLOOKUP(E86,Cotação!B:F,7,FALSE),IF($D86="COMPOSIÇÃO",VLOOKUP(Composição!$E86,'Sinapi_Comp-06.2023'!$G:$L,5,FALSE),VLOOKUP($E86,'Sinapi_Insum-06.2023'!$A:$E,5,FALSE)))) -> 454.46 | J86: =ROUND(I86*H86,2) -> 31.81
B87: =CONCATENATE(B82,".5") -> 15.5 | C87: SINAPI PB | D87: INSUMO | E87: 7156 | F87: =IF(C87="COMPOSIÇÃO",VLOOKUP(E87,B:J,2,FALSE),IF($D87="COMPOSIÇÃO",VLOOKUP(Composição!$E87,'Sinapi_Comp-06.2023'!$G:$L,2,FALSE),VLOOKUP($E87,'Sinapi_Insum-06.2023'!$A:$E,2,FALSE))) -> TELA DE ACO SOLDADA NERVURADA, CA-60, Q-196, (3,11 KG/M2), DIAMETRO DO FIO = 5,0 MM, LARGURA = 2,45 M, ESPACAMENTO DA MALHA = 10 X 10 CM | G87: =IF(C87="COMPOSIÇÃO",VLOOKUP(E87,B:J,6,FALSE),IF($D87="COMPOSIÇÃO",VLOOKUP(Composição!$E87,'Sinapi_Comp-06.2023'!$G:$L,3,FALSE),VLOOKUP($E87,'Sinapi_Insum-06.2023'!$A:$E,3,FALSE))) -> M2 | H87: 1.05 | I87: =IF(C87="COMPOSIÇÃO",VLOOKUP(E87,B:J,8,FALSE),IF(C87="COTAÇÃO",VLOOKUP(E87,Cotação!B:F,7,FALSE),IF($D87="COMPOSIÇÃO",VLOOKUP(Composição!$E87,'Sinapi_Comp-06.2023'!$G:$L,5,FALSE),VLOOKUP($E87,'Sinapi_Insum-06.2023'!$A:$E,5,FALSE)))) -> 26.25 | J87: =ROUND(I87*H87,2) -> 27.56
B88: =CONCATENATE(B82,".6") -> 15.6 | C88: SINAPI PB | D88: INSUMO | E88: 39017 | F88: =IF(C88="COMPOSIÇÃO",VLOOKUP(E88,B:J,2,FALSE),IF($D88="COMPOSIÇÃO",VLOOKUP(Composição!$E88,'Sinapi_Comp-06.2023'!$G:$L,2,FALSE),VLOOKUP($E88,'Sinapi_Insum-06.2023'!$A:$E,2,FALSE))) -> ESPACADOR / DISTANCIADOR CIRCULAR COM ENTRADA LATERAL, EM PLASTICO, PARA VERGALHAO *4,2 A 12,5* MM, COBRIMENTO 20 MM | G88: =IF(C88="COMPOSIÇÃO",VLOOKUP(E88,B:J,6,FALSE),IF($D88="COMPOSIÇÃO",VLOOKUP(Composição!$E88,'Sinapi_Comp-06.2023'!$G:$L,3,FALSE),VLOOKUP($E88,'Sinapi_Insum-06.2023'!$A:$E,3,FALSE))) -> UN | H88: 4 | I88: =IF(C88="COMPOSIÇÃO",VLOOKUP(E88,B:J,8,FALSE),IF(C88="COTAÇÃO",VLOOKUP(E88,Cotação!B:F,7,FALSE),IF($D88="COMPOSIÇÃO",VLOOKUP(Composição!$E88,'Sinapi_Comp-06.2023'!$G:$L,5,FALSE),VLOOKUP($E88,'Sinapi_Insum-06.2023'!$A:$E,5,FALSE)))) -> 0.22 | J88: =ROUND(I88*H88,2) -> 0.88
A89: =COUNTIF('Plan.Orçam.'!E:E,Composição!B89) -> 1 | B89: 16 | C89: APLICAÇÃO DE FUNDO SELADOR LÁTEX PVA EM TETO, UMA DEMÃO. AF_06/2014 [ADAPTADO 88482] | G89: M2 | I89: =SUM(J90:J92) -> 23.05
B90: =CONCATENATE(B89,".1") -> 16.1 | C90: SINAPI PB | D90: COMPOSIÇÃO | E90: 88310 | F90: =IF(C90="COMPOSIÇÃO",VLOOKUP(E90,B:J,2,FALSE),IF($D90="COMPOSIÇÃO",VLOOKUP(Composição!$E90,'Sinapi_Comp-06.2023'!$G:$L,2,FALSE),VLOOKUP($E90,'Sinapi_Insum-06.2023'!$A:$E,2,FALSE))) -> PINTOR COM ENCARGOS COMPLEMENTARES | G90: =IF(C90="COMPOSIÇÃO",VLOOKUP(E90,B:J,6,FALSE),IF($D90="COMPOSIÇÃO",VLOOKUP(Composição!$E90,'Sinapi_Comp-06.2023'!$G:$L,3,FALSE),VLOOKUP($E90,'Sinapi_Insum-06.2023'!$A:$E,3,FALSE))) -> H | H90: 0.02 | I90: =IF(C90="COMPOSIÇÃO",VLOOKUP(E90,B:J,8,FALSE),IF(C90="COTAÇÃO",VLOOKUP(E90,Cotação!B:F,7,FALSE),IF($D90="COMPOSIÇÃO",VLOOKUP(Composição!$E90,'Sinapi_Comp-06.2023'!$G:$L,5,FALSE),VLOOKUP($E90,'Sinapi_Insum-06.2023'!$A:$E,5,FALSE)))) -> 24.53 | J90: =ROUND(I90*H90,2) -> 0.49
B91: =CONCATENATE(B89,".2") -> 16.2 | C91: SINAPI PB | D91: COMPOSIÇÃO | E91: 88316 | F91: =IF(C91="COMPOSIÇÃO",VLOOKUP(E91,B:J,2,FALSE),IF($D91="COMPOSIÇÃO",VLOOKUP(Composição!$E91,'Sinapi_Comp-06.2023'!$G:$L,2,FALSE),VLOOKUP($E91,'Sinapi_Insum-06.2023'!$A:$E,2,FALSE))) -> SERVENTE COM ENCARGOS COMPLEMENTARES | G91: =IF(C91="COMPOSIÇÃO",VLOOKUP(E91,B:J,6,FALSE),IF($D91="COMPOSIÇÃO",VLOOKUP(Composição!$E91,'Sinapi_Comp-06.2023'!$G:$L,3,FALSE),VLOOKUP($E91,'Sinapi_Insum-06.2023'!$A:$E,3,FALSE))) -> H | H91: 0.26 | I91: =IF(C91="COMPOSIÇÃO",VLOOKUP(E91,B:J,8,FALSE),IF(C91="COTAÇÃO",VLOOKUP(E91,Cotação!B:F,7,FALSE),IF($D91="COMPOSIÇÃO",VLOOKUP(Composição!$E91,'Sinapi_Comp-06.2023'!$G:$L,5,FALSE),VLOOKUP($E91,'Sinapi_Insum-06.2023'!$A:$E,5,FALSE)))) -> 18.67 | J91: =ROUND(I91*H91,2) -> 4.85
B92: =CONCATENATE(B89,".3") -> 16.3 | C92: SINAPI PB | D92: INSUMO | E92: 6085 | F92: =IF(C92="COMPOSIÇÃO",VLOOKUP(E92,B:J,2,FALSE),IF($D92="COMPOSIÇÃO",VLOOKUP(Composição!$E92,'Sinapi_Comp-06.2023'!$G:$L,2,FALSE),VLOOKUP($E92,'Sinapi_Insum-06.2023'!$A:$E,2,FALSE))) -> SELADOR ACRILICO OPACO PREMIUM INTERIOR/EXTERIOR | G92: =IF(C92="COMPOSIÇÃO",VLOOKUP(E92,B:J,6,FALSE),IF($D92="COMPOSIÇÃO",VLOOKUP(Composição!$E92,'Sinapi_Comp-06.2023'!$G:$L,3,FALSE),VLOOKUP($E92,'Sinapi_Insum-06.2023'!$A:$E,3,FALSE))) -> L | H92: 1.94 | I92: =IF(C92="COMPOSIÇÃO",VLOOKUP(E92,B:J,8,FALSE),IF(C92="COTAÇÃO",VLOOKUP(E92,Cotação!B:F,7,FALSE),IF($D92="COMPOSIÇÃO",VLOOKUP(Composição!$E92,'Sinapi_Comp-06.2023'!$G:$L,5,FALSE),VLOOKUP($E92,'Sinapi_Insum-06.2023'!$A:$E,5,FALSE)))) -> 9.13 | J92: =ROUND(I92*H92,2) -> 17.71
A93: =COUNTIF('Plan.Orçam.'!E:E,Composição!B93) -> 1 | B93: 17 | C93: CAIXA DE INSPEÇÃO 80X80X80CM EM ALVENARIA - EXECUÇÃO [ADAPTADO 72289] | G93: UN | I93: =SUM(J94:J100) -> 419.12
B94: =CONCATENATE(B93,".1") -> 17.1 | C94: SINAPI PB | D94: COMPOSIÇÃO | E94: 88309 | F94: =IF(C94="COMPOSIÇÃO",VLOOKUP(E94,B:J,2,FALSE),IF($D94="COMPOSIÇÃO",VLOOKUP(Composição!$E94,'Sinapi_Comp-06.2023'!$G:$L,2,FALSE),VLOOKUP($E94,'Sinapi_Insum-06.2023'!$A:$E,2,FALSE))) -> PEDREIRO COM ENCARGOS COMPLEMENTARES | G94: =IF(C94="COMPOSIÇÃO",VLOOKUP(E94,B:J,6,FALSE),IF($D94="COMPOSIÇÃO",VLOOKUP(Composição!$E94,'Sinapi_Comp-06.2023'!$G:$L,3,FALSE),VLOOKUP($E94,'Sinapi_Insum-06.2023'!$A:$E,3,FALSE))) -> H | H94: 3.63 | I94: =IF(C94="COMPOSIÇÃO",VLOOKUP(E94,B:J,8,FALSE),IF(C94="COTAÇÃO",VLOOKUP(E94,Cotação!B:F,7,FALSE),IF($D94="COMPOSIÇÃO",VLOOKUP(Composição!$E94,'Sinapi_Comp-06.2023'!$G:$L,5,FALSE),VLOOKUP($E94,'Sinapi_Insum-06.2023'!$A:$E,5,FALSE)))) -> 23.1 | J94: =ROUND(I94*H94,2) -> 83.85
B95: =CONCATENATE(B93,".2") -> 17.2 | C95: SINAPI PB | D95: COMPOSIÇÃO | E95: 88316 | F95: =IF(C95="COMPOSIÇÃO",VLOOKUP(E95,B:J,2,FALSE),IF($D95="COMPOSIÇÃO",VLOOKUP(Composição!$E95,'Sinapi_Comp-06.2023'!$G:$L,2,FALSE),VLOOKUP($E95,'Sinapi_Insum-06.2023'!$A:$E,2,FALSE))) -> SERVENTE COM ENCARGOS COMPLEMENTARES | G95: =IF(C95="COMPOSIÇÃO",VLOOKUP(E95,B:J,6,FALSE),IF($D95="COMPOSIÇÃO",VLOOKUP(Composição!$E95,'Sinapi_Comp-06.2023'!$G:$L,3,FALSE),VLOOKUP($E95,'Sinapi_Insum-06.2023'!$A:$E,3,FALSE))) -> H | H95: 11 | I95: =IF(C95="COMPOSIÇÃO",VLOOKUP(E95,B:J,8,FALSE),IF(C95="COTAÇÃO",VLOOKUP(E95,Cotação!B:F,7,FALSE),IF($D95="COMPOSIÇÃO",VLOOKUP(Composição!$E95,'Sinapi_Comp-06.2023'!$G:$L,5,FALSE),VLOOKUP($E95,'Sinapi_Insum-06.2023'!$A:$E,5,FALSE)))) -> 18.67 | J95: =ROUND(I95*H95,2) -> 205.37
B96: =CONCATENATE(B93,".3") -> 17.3 | C96: SINAPI PB | D96: INSUMO | E96: 43054 | F96: =IF(C96="COMPOSIÇÃO",VLOOKUP(E96,B:J,2,FALSE),IF($D96="COMPOSIÇÃO",VLOOKUP(Composição!$E96,'Sinapi_Comp-06.2023'!$G:$L,2,FALSE),VLOOKUP($E96,'Sinapi_Insum-06.2023'!$A:$E,2,FALSE))) -> ACO CA-25, 10,0 MM, OU 12,5 MM, OU 16,0 MM, OU 20,0 MM, OU 25,0 MM, VERGALHAO | G96: =IF(C96="COMPOSIÇÃO",VLOOKUP(E96,B:J,6,FALSE),IF($D96="COMPOSIÇÃO",VLOOKUP(Composição!$E96,'Sinapi_Comp-06.2023'!$G:$L,3,FALSE),VLOOKUP($E96,'Sinapi_Insum-06.2023'!$A:$E,3,FALSE))) -> KG | H96: 2.5 | I96: =IF(C96="COMPOSIÇÃO",VLOOKUP(E96,B:J,8,FALSE),IF(C96="COTAÇÃO",VLOOKUP(E96,Cotação!B:F,7,FALSE),IF($D96="COMPOSIÇÃO",VLOOKUP(Composição!$E96,'Sinapi_Comp-06.2023'!$G:$L,5,FALSE),VLOOKUP($E96,'Sinapi_Insum-06.2023'!$A:$E,5,FALSE)))) -> 8.11 | J96: =ROUND(I96*H96,2) -> 20.28
B97: =CONCATENATE(B93,".4") -> 17.4 | C97: SINAPI PB | D97: INSUMO | E97: 370 | F97: =IF(C97="COMPOSIÇÃO",VLOOKUP(E97,B:J,2,FALSE),IF($D97="COMPOSIÇÃO",VLOOKUP(Composição!$E97,'Sinapi_Comp-06.2023'!$G:$L,2,FALSE),VLOOKUP($E97,'Sinapi_Insum-06.2023'!$A:$E,2,FALSE))) -> AREIA MEDIA - POSTO JAZIDA/FORNECEDOR (RETIRADO NA JAZIDA, SEM TRANSPORTE) | G97: =IF(C97="COMPOSIÇÃO",VLOOKUP(E97,B:J,6,FALSE),IF($D97="COMPOSIÇÃO",VLOOKUP(Composição!$E97,'Sinapi_Comp-06.2023'!$G:$L,3,FALSE),VLOOKUP($E97,'Sinapi_Insum-06.2023'!$A:$E,3,FALSE))) -> M3 | H97: 0.25 | I97: =IF(C97="COMPOSIÇÃO",VLOOKUP(E97,B:J,8,FALSE),IF(C97="COTAÇÃO",VLOOKUP(E97,Cotação!B:F,7,FALSE),IF($D97="COMPOSIÇÃO",VLOOKUP(Composição!$E97,'Sinapi_Comp-06.2023'!$G:$L,5,FALSE),VLOOKUP($E97,'Sinapi_Insum-06.2023'!$A:$E,5,FALSE)))) -> 140 | J97: =ROUND(I97*H97,2) -> 35
B98: =CONCATENATE(B93,".5") -> 17.5 | C98: SINAPI PB | D98: INSUMO | E98: 34753 | F98: =IF(C98="COMPOSIÇÃO",VLOOKUP(E98,B:J,2,FALSE),IF($D98="COMPOSIÇÃO",VLOOKUP(Composição!$E98,'Sinapi_Comp-06.2023'!$G:$L,2,FALSE),VLOOKUP($E98,'Sinapi_Insum-06.2023'!$A:$E,2,FALSE))) -> CIMENTO PORTLAND POZOLANICO CP IV-32 | G98: =IF(C98="COMPOSIÇÃO",VLOOKUP(E98,B:J,6,FALSE),IF($D98="COMPOSIÇÃO",VLOOKUP(Composição!$E98,'Sinapi_Comp-06.2023'!$G:$L,3,FALSE),VLOOKUP($E98,'Sinapi_Insum-06.2023'!$A:$E,3,FALSE))) -> KG | H98: 1.78 | I98: =IF(C98="COMPOSIÇÃO",VLOOKUP(E98,B:J,8,FALSE),IF(C98="COTAÇÃO",VLOOKUP(E98,Cotação!B:F,7,FALSE),IF($D98="COMPOSIÇÃO",VLOOKUP(Composição!$E98,'Sinapi_Comp-06.2023'!$G:$L,5,FALSE),VLOOKUP($E98,'Sinapi_Insum-06.2023'!$A:$E,5,FALSE)))) -> 0.68 | J98: =ROUND(I98*H98,2) -> 1.21
B99: =CONCATENATE(B93,".6") -> 17.6 | C99: SINAPI PB | D99: INSUMO | E99: 4721 | F99: =IF(C99="COMPOSIÇÃO",VLOOKUP(E99,B:J,2,FALSE),IF($D99="COMPOSIÇÃO",VLOOKUP(Composição!$E99,'Sinapi_Comp-06.2023'!$G:$L,2,FALSE),VLOOKUP($E99,'Sinapi_Insum-06.2023'!$A:$E,2,FALSE))) -> PEDRA BRITADA N. 1 (9,5 A 19 MM) POSTO PEDREIRA/FORNECEDOR, SEM FRETE | G99: =IF(C99="COMPOSIÇÃO",VLOOKUP(E99,B:J,6,FALSE),IF($D99="COMPOSIÇÃO",VLOOKUP(Composição!$E99,'Sinapi_Comp-06.2023'!$G:$L,3,FALSE),VLOOKUP($E99,'Sinapi_Insum-06.2023'!$A:$E,3,FALSE))) -> M3 | H99: 0.13 | I99: =IF(C99="COMPOSIÇÃO",VLOOKUP(E99,B:J,8,FALSE),IF(C99="COTAÇÃO",VLOOKUP(E99,Cotação!B:F,7,FALSE),IF($D99="COMPOSIÇÃO",VLOOKUP(Composição!$E99,'Sinapi_Comp-06.2023'!$G:$L,5,FALSE),VLOOKUP($E99,'Sinapi_Insum-06.2023'!$A:$E,5,FALSE)))) -> 99.47 | J99: =ROUND(I99*H99,2) -> 12.93
B100: =CONCATENATE(B93,".7") -> 17.7 | C100: SINAPI PB | D100: INSUMO | E100: 7271 | F100: =IF(C100="COMPOSIÇÃO",VLOOKUP(E100,B:J,2,FALSE),IF($D100="COMPOSIÇÃO",VLOOKUP(Composição!$E100,'Sinapi_Comp-06.2023'!$G:$L,2,FALSE),VLOOKUP($E100,'Sinapi_Insum-06.2023'!$A:$E,2,FALSE))) -> BLOCO CERAMICO / TIJOLO VAZADO PARA ALVENARIA DE VEDACAO, 8 FUROS NA HORIZONTAL DE 9 X 19 X 19 CM (L X A X C) | G100: =IF(C100="COMPOSIÇÃO",VLOOKUP(E100,B:J,6,FALSE),IF($D100="COMPOSIÇÃO",VLOOKUP(Composição!$E100,'Sinapi_Comp-06.2023'!$G:$L,3,FALSE),VLOOKUP($E100,'Sinapi_Insum-06.2023'!$A:$E,3,FALSE))) -> UN | H100: 72 | I100: =IF(C100="COMPOSIÇÃO",VLOOKUP(E100,B:J,8,FALSE),IF(C100="COTAÇÃO",VLOOKUP(E100,Cotação!B:F,7,FALSE),IF($D100="COMPOSIÇÃO",VLOOKUP(Composição!$E100,'Sinapi_Comp-06.2023'!$G:$L,5,FALSE),VLOOKUP($E100,'Sinapi_Insum-06.2023'!$A:$E,5,FALSE)))) -> 0.84 | J100: =ROUND(I100*H100,2) -> 60.48
A101: =COUNTIF('Plan.Orçam.'!E:E,Composição!B101) -> 1 | B101: 18 | C101: EXTINTOR DE PQS 4KG - FORNECIMENTO E INSTALACAO [ADAPTADO 72553] | G101: UN | I101: =SUM(J102:J105) -> 271.02
B102: =CONCATENATE(B101,".1") -> 18.1 | C102: SINAPI PB | D102: COMPOSIÇÃO | E102: 88267 | F102: =IF(C102="COMPOSIÇÃO",VLOOKUP(E102,B:J,2,FALSE),IF($D102="COMPOSIÇÃO",VLOOKUP(Composição!$E102,'Sinapi_Comp-06.2023'!$G:$L,2,FALSE),VLOOKUP($E102,'Sinapi_Insum-06.2023'!$A:$E,2,FALSE))) -> ENCANADOR OU BOMBEIRO HIDRÁULICO COM ENCARGOS COMPLEMENTARES | G102: =IF(C102="COMPOSIÇÃO",VLOOKUP(E102,B:J,6,FALSE),IF($D102="COMPOSIÇÃO",VLOOKUP(Composição!$E102,'Sinapi_Comp-06.2023'!$G:$L,3,FALSE),VLOOKUP($E102,'Sinapi_Insum-06.2023'!$A:$E,3,FALSE))) -> H | H102: 0.3 | I102: =IF(C102="COMPOSIÇÃO",VLOOKUP(E102,B:J,8,FALSE),IF(C102="COTAÇÃO",VLOOKUP(E102,Cotação!B:F,7,FALSE),IF($D102="COMPOSIÇÃO",VLOOKUP(Composição!$E102,'Sinapi_Comp-06.2023'!$G:$L,5,FALSE),VLOOKUP($E102,'Sinapi_Insum-06.2023'!$A:$E,5,FALSE)))) -> 22.12 | J102: =ROUND(I102*H102,2) -> 6.64
B103: =CONCATENATE(B101,".2") -> 18.2 | C103: SINAPI PB | D103: COMPOSIÇÃO | E103: 88316 | F103: =IF(C103="COMPOSIÇÃO",VLOOKUP(E103,B:J,2,FALSE),IF($D103="COMPOSIÇÃO",VLOOKUP(Composição!$E103,'Sinapi_Comp-06.2023'!$G:$L,2,FALSE),VLOOKUP($E103,'Sinapi_Insum-06.2023'!$A:$E,2,FALSE))) -> SERVENTE COM ENCARGOS COMPLEMENTARES | G103: =IF(C103="COMPOSIÇÃO",VLOOKUP(E103,B:J,6,FALSE),IF($D103="COMPOSIÇÃO",VLOOKUP(Composição!$E103,'Sinapi_Comp-06.2023'!$G:$L,3,FALSE),VLOOKUP($E103,'Sinapi_Insum-06.2023'!$A:$E,3,FALSE))) -> H | H103: 0.3 | I103: =IF(C103="COMPOSIÇÃO",VLOOKUP(E103,B:J,8,FALSE),IF(C103="COTAÇÃO",VLOOKUP(E103,Cotação!B:F,7,FALSE),IF($D103="COMPOSIÇÃO",VLOOKUP(Composição!$E103,'Sinapi_Comp-06.2023'!$G:$L,5,FALSE),VLOOKUP($E103,'Sinapi_Insum-06.2023'!$A:$E,5,FALSE)))) -> 18.67 | J103: =ROUND(I103*H103,2) -> 5.6
...

Sheet M.Cálc.Quant.
G2: PROGRAMA: | I2: =BDI!C3 -> Esporte, Cidadania e Desenvolvimento
G3: CONCEDENTE: | I3: =BDI!C4 -> Prefeitura Municipal de Coremas - PB
G4: CONVENENTE: | I4: =BDI!C5 -> Município de Coremas- PB
G5: CONTRATO: | I5: =BDI!C6 -> RECURSOS GOVERNO DO ESTADO
G6: OBRA: | I6: =BDI!C7 -> CONSTRUÇÃO DE QUADRA POLIESPORTIVA COM VESTIÁRIOS E BANHEIROS, NO MUNICÍPIO DE COREMAS/PB
G7: REF. PREÇOS: | I7: =BDI!C8 -> SINAPI PB - 06/2025
G8: DESONERADO | I8: SIM
C10: ITEM | D10: SINAPI | G10: MEMÓRIA DE CÁLCULO DE QUANTIDADES
A12: NÍVEL | C12: FONTE | D12: CÓDIGO | E12: TIPO | F12: ITEM | G12: ITEM | H12: SERVIÇO | I12: DESCRIÇÃO | J12: VEZ | K12: DADOS | Q12: RESULTADO | T12: UNID
K13: X1 | L13: X2 | M13: Y1 | N13: Y2 | O13: Z1 | P13: Z2 | Q13: PARCIAL | R13: TOTAL | S13: GERAL
F14: 1.0 | G14: =F14 -> 1.0 | H14: =I6 -> CONSTRUÇÃO DE QUADRA POLIESPORTIVA COM VESTIÁRIOS E BANHEIROS, NO MUNICÍPIO DE COREMAS/PB
A15: 3 | B15: =G15 -> 1.1 | C15: COMPOSIÇÃO | D15: =Composição!B11 -> ITEM | F15: 1.1 | G15: =F15 -> 1.1 | H15: SERVIÇOS PRELIMINARES
A16: 3 | B16: =G16 -> 1.1.1 | C16: COMPOSIÇÃO | D16: =Composição!B12 -> 1 | E16: COMPOSIÇÃO | F16: 1.1.1 | G16: =F16 -> 1.1.1 | H16: =IF(C16="GIDUR JP",VLOOKUP(D16,GIDUR!A:D,2,FALSE),IF(C16="DER PB",VLOOKUP('M.Cálc.Quant.'!D16,DER!A:D,2,FALSE),IF(C16="COMPOSIÇÃO",VLOOKUP(D16,Composição!B:J,2,FALSE),IF(E16="COMPOSIÇÃO",VLOOKUP(D16,'Sinapi_Comp-06.2023'!G:H,2,FALSE),VLOOKUP(D16,'Sinapi_Insum-06.2023'!A:B,2,FALSE))))) -> PLACA DE OBRA EM CHAPA DE ACO GALVANIZADO [ADAPTADO SINAPI 74209/01] | I16: A placa terá 2,0m de largura por 4,0m de comprimento, conforme modelo de placas de obras da Secretaria. | S16: =SUM(R17) -> 8 | T16: =IF(C16="GIDUR JP",VLOOKUP(D16,GIDUR!A:D,3,FALSE),IF(C16="DER PB",VLOOKUP('M.Cálc.Quant.'!D16,DER!A:D,3,FALSE),IF(C16="COMPOSIÇÃO",VLOOKUP(D16,Composição!B:J,6,FALSE),IF(E16="COMPOSIÇÃO",VLOOKUP(D16,'Sinapi_Comp-06.2023'!G:I,3,FALSE),VLOOKUP(D16,'Sinapi_Insum-06.2023'!A:C,3,FALSE))))) -> M2 | V16: 10
A17: 4 | B17: =G17 -> 1.1.1.1 | F17: =CONCATENATE(F16,".1") -> 1.1.1.1 | G17: =F17 -> 1.1.1.1 | H17: =LEFT(H16,SEARCH(" ",H16)-1) -> PLACA | J17: 1 | K17: 2 | M17: 4 | Q17: =IF(SUM(K17:L17)=0,1,IF(L17<>0,SUM(K17:L17)/2,K17))*IF(SUM(M17:N17)=0,1,IF(N17<>0,SUM(M17:N17)/2,M17))*IF(SUM(O17:P17)=0,1,IF(P17<>0,SUM(O17:P17)/2,O17)) -> 8 | R17: =ROUND(J17*Q17,2) -> 8
A18: 3 | B18: =G18 -> 1.1.2 | C18: SINAPI | D18: 99059 | E18: COMPOSIÇÃO | F18: 1.1.2 | G18: =F18 -> 1.1.2 | H18: =IF(C18="GIDUR JP",VLOOKUP(D18,GIDUR!A:D,2,FALSE),IF(C18="DER PB",VLOOKUP('M.Cálc.Quant.'!D18,DER!A:D,2,FALSE),IF(C18="COMPOSIÇÃO",VLOOKUP(D18,Composição!B:J,2,FALSE),IF(E18="COMPOSIÇÃO",VLOOKUP(D18,'Sinapi_Comp-06.2023'!G:H,2,FALSE),VLOOKUP(D18,'Sinapi_Insum-06.2023'!A:B,2,FALSE))))) -> LOCAÇÃO CONVENCIONAL DE OBRA, UTILIZANDO GABARITO DE TÁBUAS CORRIDAS PONTALETADAS A CADA 2,00M - 2 UTILIZAÇÕES. AF_03/2024 | I18: locação geral | S18: =SUM(R19) -> 106.5 | T18: =IF(C18="GIDUR JP",VLOOKUP(D18,GIDUR!A:D,3,FALSE),IF(C18="DER PB",VLOOKUP('M.Cálc.Quant.'!D18,DER!A:D,3,FALSE),IF(C18="COMPOSIÇÃO",VLOOKUP(D18,Composição!B:J,6,FALSE),IF(E18="COMPOSIÇÃO",VLOOKUP(D18,'Sinapi_Comp-06.2023'!G:I,3,FALSE),VLOOKUP(D18,'Sinapi_Insum-06.2023'!A:C,3,FALSE))))) -> M | U18: =(24+37)*2 -> 122 | V18: 122
A19: 4 | B19: =G19 -> 1.1.2.1 | F19: =CONCATENATE(F18,".1") -> 1.1.2.1 | G19: =F19 -> 1.1.2.1 | H19: =LEFT(H18,SEARCH(" ",H18)-1) -> LOCAÇÃO | I19: (24+37)*2 | J19: 1 | K19: 2 | M19: 53.25 | Q19: =IF(SUM(K19:L19)=0,1,IF(L19<>0,SUM(K19:L19)/2,K19))*IF(SUM(M19:N19)=0,1,IF(N19<>0,SUM(M19:N19)/2,M19))*IF(SUM(O19:P19)=0,1,IF(P19<>0,SUM(O19:P19)/2,O19)) -> 106.5 | R19: =ROUND(J19*Q19,2) -> 106.5
A20: 2 | B20: =G20 -> 1.2 | E20: 0 | F20: 1.2 | G20: =F20 -> 1.2 | H20: MOVIMENTO DE TERRA
A21: 3 | B21: =G21 -> 1.2.1 | C21: COMPOSIÇÃO | D21: =Composição!B50 -> 8 | E21: COMPOSIÇÃO | F21: 1.2.1 | G21: =F21 -> 1.2.1 | H21: =IF(C21="GIDUR JP",VLOOKUP(D21,GIDUR!A:D,2,FALSE),IF(C21="DER PB",VLOOKUP('M.Cálc.Quant.'!D21,DER!A:D,2,FALSE),IF(C21="COMPOSIÇÃO",VLOOKUP(D21,Composição!B:J,2,FALSE),IF(E21="COMPOSIÇÃO",VLOOKUP(D21,'Sinapi_Comp-06.2023'!G:H,2,FALSE),VLOOKUP(D21,'Sinapi_Insum-06.2023'!A:B,2,FALSE))))) -> ESCAVACAO MANUAL EM SOLO-PROF. ATE 1,50 M [ADAPTADO SINAPI 79561/001] | S21: =SUM(R22:R32) -> 74.74 | T21: =IF(C21="GIDUR JP",VLOOKUP(D21,GIDUR!A:D,3,FALSE),IF(C21="DER PB",VLOOKUP('M.Cálc.Quant.'!D21,DER!A:D,3,FALSE),IF(C21="COMPOSIÇÃO",VLOOKUP(D21,Composição!B:J,6,FALSE),IF(E21="COMPOSIÇÃO",VLOOKUP(D21,'Sinapi_Comp-06.2023'!G:I,3,FALSE),VLOOKUP(D21,'Sinapi_Insum-06.2023'!A:C,3,FALSE))))) -> M3 | U21: =27*44*0.8 -> 950.4 | V21: 0
A22: 4 | B22: =G22 -> 1.2.1.1 | F22: =CONCATENATE(F21,".1") -> 1.2.1.1 | G22: =F22 -> 1.2.1.1 | H22: S11=S12 | J22: 2 | K22: 0.75 | M22: 0.75 | O22: 1.65 | Q22: =IF(SUM(K22:L22)=0,1,IF(L22<>0,SUM(K22:L22)/2,K22))*IF(SUM(M22:N22)=0,1,IF(N22<>0,SUM(M22:N22)/2,M22))*IF(SUM(O22:P22)=0,1,IF(P22<>0,SUM(O22:P22)/2,O22)) -> 0.93 | R22: =ROUND(J22*Q22,2) -> 1.86
A23: 4 | B23: =G23 -> 1.2.1.2 | F23: =CONCATENATE(F21,".2") -> 1.2.1.2 | G23: =F23 -> 1.2.1.2 | H23: S21=S22 | J23: 2 | K23: 0.85 | M23: 0.85 | O23: 1.65 | Q23: =IF(SUM(K23:L23)=0,1,IF(L23<>0,SUM(K23:L23)/2,K23))*IF(SUM(M23:N23)=0,1,IF(N23<>0,SUM(M23:N23)/2,M23))*IF(SUM(O23:P23)=0,1,IF(P23<>0,SUM(O23:P23)/2,O23)) -> 1.19 | R23: =ROUND(J23*Q23,2) -> 2.38
A24: 4 | B24: =G24 -> 1.2.1.3 | F24: =CONCATENATE(F21,".3") -> 1.2.1.3 | G24: =F24 -> 1.2.1.3 | H24: S14 | J24: 1 | K24: 1 | M24: 1.2 | O24: 1.65 | Q24: =IF(SUM(K24:L24)=0,1,IF(L24<>0,SUM(K24:L24)/2,K24))*IF(SUM(M24:N24)=0,1,IF(N24<>0,SUM(M24:N24)/2,M24))*IF(SUM(O24:P24)=0,1,IF(P24<>0,SUM(O24:P24)/2,O24)) -> 1.98 | R24: =ROUND(J24*Q24,2) -> 1.98
A25: 5 | B25: =G25 -> 1.2.1.4 | F25: 1.2.1.4 | G25: =F25 -> 1.2.1.4 | H25: S19 | J25: 1 | K25: 1.1 | M25: 1.3 | O25: 1.65 | Q25: =IF(SUM(K25:L25)=0,1,IF(L25<>0,SUM(K25:L25)/2,K25))*IF(SUM(M25:N25)=0,1,IF(N25<>0,SUM(M25:N25)/2,M25))*IF(SUM(O25:P25)=0,1,IF(P25<>0,SUM(O25:P25)/2,O25)) -> 2.36 | R25: =ROUND(J25*Q25,2) -> 2.36
A26: 6 | B26: =G26 -> 1.2.1.5 | F26: 1.2.1.5 | G26: =F26 -> 1.2.1.5 | H26: S18 | J26: 1 | K26: 1.05 | M26: 1.4 | O26: 1.65 | Q26: =IF(SUM(K26:L26)=0,1,IF(L26<>0,SUM(K26:L26)/2,K26))*IF(SUM(M26:N26)=0,1,IF(N26<>0,SUM(M26:N26)/2,M26))*IF(SUM(O26:P26)=0,1,IF(P26<>0,SUM(O26:P26)/2,O26)) -> 2.43 | R26: =ROUND(J26*Q26,2) -> 2.43
A27: 7 | B27: =G27 -> 1.2.1.6 | F27: 1.2.1.6 | G27: =F27 -> 1.2.1.6 | H27: S16=S17 | J27: 2 | K27: 1.15 | M27: 1.35 | O27: 1.65 | Q27: =IF(SUM(K27:L27)=0,1,IF(L27<>0,SUM(K27:L27)/2,K27))*IF(SUM(M27:N27)=0,1,IF(N27<>0,SUM(M27:N27)/2,M27))*IF(SUM(O27:P27)=0,1,IF(P27<>0,SUM(O27:P27)/2,O27)) -> 2.56 | R27: =ROUND(J27*Q27,2) -> 5.12
A28: 8 | B28: =G28 -> 1.2.1.7 | F28: 1.2.1.7 | G28: =F28 -> 1.2.1.7 | H28: S15 | J28: 1 | K28: 1.1 | M28: 1.45 | O28: 1.65 | Q28: =IF(SUM(K28:L28)=0,1,IF(L28<>0,SUM(K28:L28)/2,K28))*IF(SUM(M28:N28)=0,1,IF(N28<>0,SUM(M28:N28)/2,M28))*IF(SUM(O28:P28)=0,1,IF(P28<>0,SUM(O28:P28)/2,O28)) -> 2.63 | R28: =ROUND(J28*Q28,2) -> 2.63
A29: 9 | B29: =G29 -> 1.2.1.8 | F29: 1.2.1.8 | G29: =F29 -> 1.2.1.8 | H29: S1=S2=S6=S13=S20 | J29: 5 | K29: 1.25 | M29: 1.45 | O29: 1.65 | Q29: =IF(SUM(K29:L29)=0,1,IF(L29<>0,SUM(K29:L29)/2,K29))*IF(SUM(M29:N29)=0,1,IF(N29<>0,SUM(M29:N29)/2,M29))*IF(SUM(O29:P29)=0,1,IF(P29<>0,SUM(O29:P29)/2,O29)) -> 2.99 | R29: =ROUND(J29*Q29,2) -> 14.95
A30: 10 | B30: =G30 -> 1.2.1.9 | F30: 1.2.1.9 | G30: =F30 -> 1.2.1.9 | H30: S3=S4=S5 | J30: 3 | K30: 1.3 | M30: 1.5 | O30: 1.65 | Q30: =IF(SUM(K30:L30)=0,1,IF(L30<>0,SUM(K30:L30)/2,K30))*IF(SUM(M30:N30)=0,1,IF(N30<>0,SUM(M30:N30)/2,M30))*IF(SUM(O30:P30)=0,1,IF(P30<>0,SUM(O30:P30)/2,O30)) -> 3.22 | R30: =ROUND(J30*Q30,2) -> 9.66
A31: 11 | B31: =G31 -> 1.2.1.10 | F31: 1.2.1.10 | G31: =F31 -> 1.2.1.10 | H31: S7=S8=S9=S10 | J31: 4 | K31: 1.75 | M31: 1.85 | O31: 1.65 | Q31: =IF(SUM(K31:L31)=0,1,IF(L31<>0,SUM(K31:L31)/2,K31))*IF(SUM(M31:N31)=0,1,IF(N31<>0,SUM(M31:N31)/2,M31))*IF(SUM(O31:P31)=0,1,IF(P31<>0,SUM(O31:P31)/2,O31)) -> 5.34 | R31: =ROUND(J31*Q31,2) -> 21.36
A32: 12 | B32: =G32 -> 1.2.1.11 | F32: 1.2.1.11 | G32: =F32 -> 1.2.1.11 | H32: baldrames | J32: 1 | K32: =13+8+10+94.1 -> 125.1 | M32: 0.2 | O32: 0.4 | Q32: =IF(SUM(K32:L32)=0,1,IF(L32<>0,SUM(K32:L32)/2,K32))*IF(SUM(M32:N32)=0,1,IF(N32<>0,SUM(M32:N32)/2,M32))*IF(SUM(O32:P32)=0,1,IF(P32<>0,SUM(O32:P32)/2,O32)) -> 10.01 | R32: =ROUND(J32*Q32,2) -> 10.01
A33: 3 | B33: =G33 -> 1.2.2 | C33: SINAPI | D33: 93382 | E33: COMPOSIÇÃO | F33: 1.2.2 | G33: =F33 -> 1.2.2 | H33: =IF(C33="GIDUR JP",VLOOKUP(D33,GIDUR!A:D,2,FALSE),IF(C33="DER PB",VLOOKUP('M.Cálc.Quant.'!D33,DER!A:D,2,FALSE),IF(C33="COMPOSIÇÃO",VLOOKUP(D33,Composição!B:J,2,FALSE),IF(E33="COMPOSIÇÃO",VLOOKUP(D33,'Sinapi_Comp-06.2023'!G:H,2,FALSE),VLOOKUP(D33,'Sinapi_Insum-06.2023'!A:B,2,FALSE))))) -> REATERRO MANUAL DE VALAS, COM COMPACTADOR DE SOLOS DE PERCUSSÃO. AF_08/2023 | S33: =SUM(R34:R34) -> 63.7 | T33: =IF(C33="GIDUR JP",VLOOKUP(D33,GIDUR!A:D,3,FALSE),IF(C33="DER PB",VLOOKUP('M.Cálc.Quant.'!D33,DER!A:D,3,FALSE),IF(C33="COMPOSIÇÃO",VLOOKUP(D33,Composição!B:J,6,FALSE),IF(E33="COMPOSIÇÃO",VLOOKUP(D33,'Sinapi_Comp-06.2023'!G:I,3,FALSE),VLOOKUP(D33,'Sinapi_Insum-06.2023'!A:C,3,FALSE))))) -> M3 | U33: =27*44 -> 1188 | V33: 1188
A34: 4 | B34: =G34 -> 1.2.2.1 | F34: =CONCATENATE(F33,".1") -> 1.2.2.1 | G34: =F34 -> 1.2.2.1 | H34: Volume de escavação-volume de concreto | J34: 1 | K34: =S21-S81 -> 63.7 | Q34: =IF(SUM(K34:L34)=0,1,IF(L34<>0,SUM(K34:L34)/2,K34))*IF(SUM(M34:N34)=0,1,IF(N34<>0,SUM(M34:N34)/2,M34))*IF(SUM(O34:P34)=0,1,IF(P34<>0,SUM(O34:P34)/2,O34)) -> 63.7 | R34: =ROUND(J34*Q34,2) -> 63.7
B35: =G35 -> 1.3 | E35: #N/A | F35: 1.3 | G35: =F35 -> 1.3 | H35: INFRA-ESTRUTURA: FUNDAÇÕES (TODA A QUADRA)
B36: =G36 -> 1.3.1 | E36: #N/A | F36: 1.3.1 | G36: =F36 -> 1.3.1 | H36: SAPATAS ISOLADAS/ARRANQUE DOS PILARES
B37: =G37 -> 1.3.1.1 | C37: SINAPI | D37: 101616 | E37: COMPOSIÇÃO | F37: 1.3.1.1 | G37: =F37 -> 1.3.1.1 | H37: =IF(C37="GIDUR JP",VLOOKUP(D37,GIDUR!A:D,2,FALSE),IF(C37="DER PB",VLOOKUP('M.Cálc.Quant.'!D37,DER!A:D,2,FALSE),IF(C37="COMPOSIÇÃO",VLOOKUP(D37,Composição!B:J,2,FALSE),IF(E37="COMPOSIÇÃO",VLOOKUP(D37,'Sinapi_Comp-06.2023'!G:H,2,FALSE),VLOOKUP(D37,'Sinapi_Insum-06.2023'!A:B,2,FALSE))))) -> PREPARO DE FUNDO DE VALA COM LARGURA MENOR QUE 1,5 M (ACERTO DO SOLO NATURAL). AF_08/2020 | S37: =SUM(R38:R48) -> 64.24 | T37: =IF(C37="GIDUR JP",VLOOKUP(D37,GIDUR!A:D,3,FALSE),IF(C37="DER PB",VLOOKUP('M.Cálc.Quant.'!D37,DER!A:D,3,FALSE),IF(C37="COMPOSIÇÃO",VLOOKUP(D37,Composição!B:J,6,FALSE),IF(E37="COMPOSIÇÃO",VLOOKUP(D37,'Sinapi_Comp-06.2023'!G:I,3,FALSE),VLOOKUP(D37,'Sinapi_Insum-06.2023'!A:C,3,FALSE))))) -> M2 | V37: 38.6
A38: 4 | B38: =G38 -> 1.3.1.1.1 | F38: 1.3.1.1.1 | G38: =F38 -> 1.3.1.1.1 | H38: S11=S12 | J38: 2 | K38: 0.75 | M38: 0.75 | Q38: =IF(SUM(K38:L38)=0,1,IF(L38<>0,SUM(K38:L38)/2,K38))*IF(SUM(M38:N38)=0,1,IF(N38<>0,SUM(M38:N38)/2,M38))*IF(SUM(O38:P38)=0,1,IF(P38<>0,SUM(O38:P38)/2,O38)) -> 0.56 | R38: =ROUND(J38*Q38,2) -> 1.12
A39: 4 | B39: =G39 -> 1.3.1.1.2 | F39: 1.3.1.1.2 | G39: =F39 -> 1.3.1.1.2 | H39: S21=S22 | J39: 2 | K39: 0.85 | M39: 0.85 | Q39: =IF(SUM(K39:L39)=0,1,IF(L39<>0,SUM(K39:L39)/2,K39))*IF(SUM(M39:N39)=0,1,IF(N39<>0,SUM(M39:N39)/2,M39))*IF(SUM(O39:P39)=0,1,IF(P39<>0,SUM(O39:P39)/2,O39)) -> 0.72 | R39: =ROUND(J39*Q39,2) -> 1.44
A40: 4 | B40: =G40 -> 1.3.1.1.3 | F40: 1.3.1.1.3 | G40: =F40 -> 1.3.1.1.3 | H40: S14 | J40: 1 | K40: 1 | M40: 1.2 | Q40: =IF(SUM(K40:L40)=0,1,IF(L40<>0,SUM(K40:L40)/2,K40))*IF(SUM(M40:N40)=0,1,IF(N40<>0,SUM(M40:N40)/2,M40))*IF(SUM(O40:P40)=0,1,IF(P40<>0,SUM(O40:P40)/2,O40)) -> 1.2 | R40: =ROUND(J40*Q40,2) -> 1.2
A41: 4 | B41: =G41 -> 1.3.1.1.4 | F41: 1.3.1.1.4 | G41: =F41 -> 1.3.1.1.4 | H41: S19 | J41: 1 | K41: 1.1 | M41: 1.3 | Q41: =IF(SUM(K41:L41)=0,1,IF(L41<>0,SUM(K41:L41)/2,K41))*IF(SUM(M41:N41)=0,1,IF(N41<>0,SUM(M41:N41)/2,M41))*IF(SUM(O41:P41)=0,1,IF(P41<>0,SUM(O41:P41)/2,O41)) -> 1.43 | R41: =ROUND(J41*Q41,2) -> 1.43
A42: 4 | B42: =G42 -> 1.3.1.1.5 | F42: 1.3.1.1.5 | G42: =F42 -> 1.3.1.1.5 | H42: S18 | J42: 1 | K42: 1.05 | M42: 1.4 | Q42: =IF(SUM(K42:L42)=0,1,IF(L42<>0,SUM(K42:L42)/2,K42))*IF(SUM(M42:N42)=0,1,IF(N42<>0,SUM(M42:N42)/2,M42))*IF(SUM(O42:P42)=0,1,IF(P42<>0,SUM(O42:P42)/2,O42)) -> 1.47 | R42: =ROUND(J42*Q42,2) -> 1.47
A43: 4 | B43: =G43 -> 1.3.1.1.6 | F43: 1.3.1.1.6 | G43: =F43 -> 1.3.1.1.6 | H43: S16=S17 | J43: 2 | K43: 1.15 | M43: 1.35 | Q43: =IF(SUM(K43:L43)=0,1,IF(L43<>0,SUM(K43:L43)/2,K43))*IF(SUM(M43:N43)=0,1,IF(N43<>0,SUM(M43:N43)/2,M43))*IF(SUM(O43:P43)=0,1,IF(P43<>0,SUM(O43:P43)/2,O43)) -> 1.55 | R43: =ROUND(J43*Q43,2) -> 3.1
A44: 4 | B44: =G44 -> 1.3.1.1.7 | F44: 1.3.1.1.7 | G44: =F44 -> 1.3.1.1.7 | H44: S15 | J44: 1 | K44: 1.1 | M44: 1.45 | Q44: =IF(SUM(K44:L44)=0,1,IF(L44<>0,SUM(K44:L44)/2,K44))*IF(SUM(M44:N44)=0,1,IF(N44<>0,SUM(M44:N44)/2,M44))*IF(SUM(O44:P44)=0,1,IF(P44<>0,SUM(O44:P44)/2,O44)) -> 1.6 | R44: =ROUND(J44*Q44,2) -> 1.6
A45: 4 | B45: =G45 -> 1.3.1.1.8 | F45: 1.3.1.1.8 | G45: =F45 -> 1.3.1.1.8 | H45: S1=S2=S6=S13=S20 | J45: 5 | K45: 1.25 | M45: 1.45 | Q45: =IF(SUM(K45:L45)=0,1,IF(L45<>0,SUM(K45:L45)/2,K45))*IF(SUM(M45:N45)=0,1,IF(N45<>0,SUM(M45:N45)/2,M45))*IF(SUM(O45:P45)=0,1,IF(P45<>0,SUM(O45:P45)/2,O45)) -> 1.81 | R45: =ROUND(J45*Q45,2) -> 9.05
A46: 4 | B46: =G46 -> 1.3.1.1.9 | F46: 1.3.1.1.9 | G46: =F46 -> 1.3.1.1.9 | H46: S3=S4=S5 | J46: 3 | K46: 1.3 | M46: 1.5 | Q46: =IF(SUM(K46:L46)=0,1,IF(L46<>0,SUM(K46:L46)/2,K46))*IF(SUM(M46:N46)=0,1,IF(N46<>0,SUM(M46:N46)/2,M46))*IF(SUM(O46:P46)=0,1,IF(P46<>0,SUM(O46:P46)/2,O46)) -> 1.95 | R46: =ROUND(J46*Q46,2) -> 5.85
A47: 4 | B47: =G47 -> 1.3.1.1.10 | F47: 1.3.1.1.10 | G47: =F47 -> 1.3.1.1.10 | H47: S7=S8=S9=S10 | J47: 4 | K47: 1.75 | M47: 1.85 | Q47: =IF(SUM(K47:L47)=0,1,IF(L47<>0,SUM(K47:L47)/2,K47))*IF(SUM(M47:N47)=0,1,IF(N47<>0,SUM(M47:N47)/2,M47))*IF(SUM(O47:P47)=0,1,IF(P47<>0,SUM(O47:P47)/2,O47)) -> 3.24 | R47: =ROUND(J47*Q47,2) -> 12.96
A48: 4 | B48: =G48 -> 1.3.1.1.11 | F48: 1.3.1.1.11 | G48: =F48 -> 1.3.1.1.11 | H48: baldrames | J48: 1 | K48: =13+8+10+94.1 -> 125.1 | M48: 0.2 | Q48: =IF(SUM(K48:L48)=0,1,IF(L48<>0,SUM(K48:L48)/2,K48))*IF(SUM(M48:N48)=0,1,IF(N48<>0,SUM(M48:N48)/2,M48))*IF(SUM(O48:P48)=0,1,IF(P48<>0,SUM(O48:P48)/2,O48)) -> 25.02 | R48: =ROUND(J48*Q48,2) -> 25.02
B49: =G49 -> 1.3.1.2 | C49: COMPOSIÇÃO | D49: =Composição!B57 -> 10 | E49: COMPOSIÇÃO | F49: 1.3.1.2 | G49: =F49 -> 1.3.1.2 | H49: =IF(C49="GIDUR JP",VLOOKUP(D49,GIDUR!A:D,2,FALSE),IF(C49="DER PB",VLOOKUP('M.Cálc.Quant.'!D49,DER!A:D,2,FALSE),IF(C49="COMPOSIÇÃO",VLOOKUP(D49,Composição!B:J,2,FALSE),IF(E49="COMPOSIÇÃO",VLOOKUP(D49,'Sinapi_Comp-06.2023'!G:H,2,FALSE),VLOOKUP(D49,'Sinapi_Insum-06.2023'!A:B,2,FALSE))))) -> ALVENARIA EM TIJOLO CERAMICO FURADO 9X19X19CM, 1 VEZ (ESPESSURA 19 CM), ASSENTADO EM ARGAMASSA TRACO 1:4 (CIMENTO E AREIA MEDIA NAO PENEIRADA), PREPARO MANUAL, JUNTA1 CM [ADAPTADO SINAPI 73935/002] | S49: =SUM(R50) -> 50.04 | T49: =IF(C49="GIDUR JP",VLOOKUP(D49,GIDUR!A:D,3,FALSE),IF(C49="DER PB",VLOOKUP('M.Cálc.Quant.'!D49,DER!A:D,3,FALSE),IF(C49="COMPOSIÇÃO",VLOOKUP(D49,Composição!B:J,6,FALSE),IF(E49="COMPOSIÇÃO",VLOOKUP(D49,'Sinapi_Comp-06.2023'!G:I,3,FALSE),VLOOKUP(D49,'Sinapi_Insum-06.2023'!A:C,3,FALSE))))) -> M2 | V49: 24.9
B50: =G50 -> 1.3.1.2.1 | F50: =CONCATENATE(F49,".1") -> 1.3.1.2.1 | G50: =F50 -> 1.3.1.2.1 | H50: =LEFT(H49,SEARCH(" ",H49)-1) -> ALVENARIA | I50: Área de regularização das sapatas: P=27,3+27,3+19,75+19,75 | J50: 1 | K50: =K48 -> 125.1 | M50: 0.4 | Q50: =IF(SUM(K50:L50)=0,1,IF(L50<>0,SUM(K50:L50)/2,K50))*IF(SUM(M50:N50)=0,1,IF(N50<>0,SUM(M50:N50)/2,M50))*IF(SUM(O50:P50)=0,1,IF(P50<>0,SUM(O50:P50)/2,O50)) -> 50.04 | R50: =ROUND(J50*Q50,2) -> 50.04
B51: =G51 -> 1.3.1.3 | C51: SINAPI | D51: 96620 | E51: COMPOSIÇÃO | F51: 1.3.1.3 | G51: =F51 -> 1.3.1.3 | H51: =IF(C51="GIDUR JP",VLOOKUP(D51,GIDUR!A:D,2,FALSE),IF(C51="DER PB",VLOOKUP('M.Cálc.Quant.'!D51,DER!A:D,2,FALSE),IF(C51="COMPOSIÇÃO",VLOOKUP(D51,Composição!B:J,2,FALSE),IF(E51="COMPOSIÇÃO",VLOOKUP(D51,'Sinapi_Comp-06.2023'!G:H,2,FALSE),VLOOKUP(D51,'Sinapi_Insum-06.2023'!A:B,2,FALSE))))) -> LASTRO DE CONCRETO MAGRO, APLICADO EM PISOS, LAJES SOBRE SOLO OU RADIERS. AF_01/2024 | S51: =SUM(R52:R62) -> 3.22 | T51: =IF(C51="GIDUR JP",VLOOKUP(D51,GIDUR!A:D,3,FALSE),IF(C51="DER PB",VLOOKUP('M.Cálc.Quant.'!D51,DER!A:D,3,FALSE),IF(C51="COMPOSIÇÃO",VLOOKUP(D51,Composição!B:J,6,FALSE),IF(E51="COMPOSIÇÃO",VLOOKUP(D51,'Sinapi_Comp-06.2023'!G:I,3,FALSE),VLOOKUP(D51,'Sinapi_Insum-06.2023'!A:C,3,FALSE))))) -> M3 | V51: 1.25
A52: 4 | B52: =G52 -> 1.3.1.3.1 | F52: =CONCATENATE(F51,".1") -> 1.3.1.3.1 | G52: =F52 -> 1.3.1.3.1 | H52: S11=S12 | J52: 2 | K52: 0.75 | M52: 0.75 | O52: 0.05 | Q52: =IF(SUM(K52:L52)=0,1,IF(L52<>0,SUM(K52:L52)/2,K52))*IF(SUM(M52:N52)=0,1,IF(N52<>0,SUM(M52:N52)/2,M52))*IF(SUM(O52:P52)=0,1,IF(P52<>0,SUM(O52:P52)/2,O52)) -> 0.03 | R52: =ROUND(J52*Q52,2) -> 0.06
A53: 4 | B53: =G53 -> 1.3.1.3.2 | F53: 1.3.1.3.2 | G53: =F53 -> 1.3.1.3.2 | H53: S21=S22 | J53: 2 | K53: 0.85 | M53: 0.85 | O53: 0.05 | Q53: =IF(SUM(K53:L53)=0,1,IF(L53<>0,SUM(K53:L53)/2,K53))*IF(SUM(M53:N53)=0,1,IF(N53<>0,SUM(M53:N53)/2,M53))*IF(SUM(O53:P53)=0,1,IF(P53<>0,SUM(O53:P53)/2,O53)) -> 0.04 | R53: =ROUND(J53*Q53,2) -> 0.08
A54: 4 | B54: =G54 -> 1.3.1.3.3 | F54: 1.3.1.3.3 | G54: =F54 -> 1.3.1.3.3 | H54: S14 | J54: 1 | K54: 1 | M54: 1.2 | O54: 0.05 | Q54: =IF(SUM(K54:L54)=0,1,IF(L54<>0,SUM(K54:L54)/2,K54))*IF(SUM(M54:N54)=0,1,IF(N54<>0,SUM(M54:N54)/2,M54))*IF(SUM(O54:P54)=0,1,IF(P54<>0,SUM(O54:P54)/2,O54)) -> 0.06 | R54: =ROUND(J54*Q54,2) -> 0.06
A55: 4 | B55: =G55 -> 1.3.1.3.4 | F55: 1.3.1.3.4 | G55: =F55 -> 1.3.1.3.4 | H55: S19 | J55: 1 | K55: 1.1 | M55: 1.3 | O55: 0.05 | Q55: =IF(SUM(K55:L55)=0,1,IF(L55<>0,SUM(K55:L55)/2,K55))*IF(SUM(M55:N55)=0,1,IF(N55<>0,SUM(M55:N55)/2,M55))*IF(SUM(O55:P55)=0,1,IF(P55<>0,SUM(O55:P55)/2,O55)) -> 0.07 | R55: =ROUND(J55*Q55,2) -> 0.07
A56: 4 | B56: =G56 -> 1.3.1.3.5 | F56: 1.3.1.3.5 | G56: =F56 -> 1.3.1.3.5 | H56: S18 | J56: 1 | K56: 1.05 | M56: 1.4 | O56: 0.05 | Q56: =IF(SUM(K56:L56)=0,1,IF(L56<>0,SUM(K56:L56)/2,K56))*IF(SUM(M56:N56)=0,1,IF(N56<>0,SUM(M56:N56)/2,M56))*IF(SUM(O56:P56)=0,1,IF(P56<>0,SUM(O56:P56)/2,O56)) -> 0.07 | R56: =ROUND(J56*Q56,2) -> 0.07
A57: 4 | B57: =G57 -> 1.3.1.3.6 | F57: 1.3.1.3.6 | G57: =F57 -> 1.3.1.3.6 | H57: S16=S17 | J57: 2 | K57: 1.15 | M57: 1.35 | O57: 0.05 | Q57: =IF(SUM(K57:L57)=0,1,IF(L57<>0,SUM(K57:L57)/2,K57))*IF(SUM(M57:N57)=0,1,IF(N57<>0,SUM(M57:N57)/2,M57))*IF(SUM(O57:P57)=0,1,IF(P57<>0,SUM(O57:P57)/2,O57)) -> 0.08 | R57: =ROUND(J57*Q57,2) -> 0.16
A58: 4 | B58: =G58 -> 1.3.1.3.7 | F58: 1.3.1.3.7 | G58: =F58 -> 1.3.1.3.7 | H58: S15 | J58: 1 | K58: 1.1 | M58: 1.45 | O58: 0.05 | Q58: =IF(SUM(K58:L58)=0,1,IF(L58<>0,SUM(K58:L58)/2,K58))*IF(SUM(M58:N58)=0,1,IF(N58<>0,SUM(M58:N58)/2,M58))*IF(SUM(O58:P58)=0,1,IF(P58<>0,SUM(O58:P58)/2,O58)) -> 0.08 | R58: =ROUND(J58*Q58,2) -> 0.08
A59: 4 | B59: =G59 -> 1.3.1.3.8 | F59: 1.3.1.3.8 | G59: =F59 -> 1.3.1.3.8 | H59: S1=S2=S6=S13=S20 | J59: 5 | K59: 1.25 | M59: 1.45 | O59: 0.05 | Q59: =IF(SUM(K59:L59)=0,1,IF(L59<>0,SUM(K59:L59)/2,K59))*IF(SUM(M59:N59)=0,1,IF(N59<>0,SUM(M59:N59)/2,M59))*IF(SUM(O59:P59)=0,1,IF(P59<>0,SUM(O59:P59)/2,O59)) -> 0.09 | R59: =ROUND(J59*Q59,2) -> 0.45
A60: 4 | B60: =G60 -> 1.3.1.3.9 | F60: 1.3.1.3.9 | G60: =F60 -> 1.3.1.3.9 | H60: S3=S4=S5 | J60: 3 | K60: 1.3 | M60: 1.5 | O60: 0.05 | Q60: =IF(SUM(K60:L60)=0,1,IF(L60<>0,SUM(K60:L60)/2,K60))*IF(SUM(M60:N60)=0,1,IF(N60<>0,SUM(M60:N60)/2,M60))*IF(SUM(O60:P60)=0,1,IF(P60<>0,SUM(O60:P60)/2,O60)) -> 0.1 | R60: =ROUND(J60*Q60,2) -> 0.3
A61: 4 | B61: =G61 -> 1.3.1.3.10 | F61: 1.3.1.3.10 | G61: =F61 -> 1.3.1.3.10 | H61: S7=S8=S9=S10 | J61: 4 | K61: 1.75 | M61: 1.85 | O61: 0.05 | Q61: =IF(SUM(K61:L61)=0,1,IF(L61<>0,SUM(K61:L61)/2,K61))*IF(SUM(M61:N61)=0,1,IF(N61<>0,SUM(M61:N61)/2,M61))*IF(SUM(O61:P61)=0,1,IF(P61<>0,SUM(O61:P61)/2,O61)) -> 0.16 | R61: =ROUND(J61*Q61,2) -> 0.64
A62: 4 | B62: =G62 -> 1.3.1.3.11 | F62: 1.3.1.3.11 | G62: =F62 -> 1.3.1.3.11 | H62: baldrames | J62: 1 | K62: =13+8+10+94.1 -> 125.1 | M62: 0.2 | O62: 0.05 | Q62: =IF(SUM(K62:L62)=0,1,IF(L62<>0,SUM(K62:L62)/2,K62))*IF(SUM(M62:N62)=0,1,IF(N62<>0,SUM(M62:N62)/2,M62))*IF(SUM(O62:P62)=0,1,IF(P62<>0,SUM(O62:P62)/2,O62)) -> 1.25 | R62: =ROUND(J62*Q62,2) -> 1.25
B63: =G63 -> 1.3.1.4 | C63: SINAPI | D63: 96535 | E63: COMPOSIÇÃO | F63: 1.3.1.4 | G63: =F63 -> 1.3.1.4 | H63: =IF(C63="GIDUR JP",VLOOKUP(D63,GIDUR!A:D,2,FALSE),IF(C63="DER PB",VLOOKUP('M.Cálc.Quant.'!D63,DER!A:D,2,FALSE),IF(C63="COMPOSIÇÃO",VLOOKUP(D63,Composição!B:J,2,FALSE),IF(E63="COMPOSIÇÃO",VLOOKUP(D63,'Sinapi_Comp-06.2023'!G:H,2,FALSE),VLOOKUP(D63,'Sinapi_Insum-06.2023'!A:B,2,FALSE))))) -> FABRICAÇÃO, MONTAGEM E DESMONTAGEM DE FÔRMA PARA SAPATA, EM MADEIRA SERRADA, E=25 MM, 4 UTILIZAÇÕES. AF_01/2024 | S63: =SUM(R64) -> 57.41 | T63: =IF(C63="GIDUR JP",VLOOKUP(D63,GIDUR!A:D,3,FALSE),IF(C63="DER PB",VLOOKUP('M.Cálc.Quant.'!D63,DER!A:D,3,FALSE),IF(C63="COMPOSIÇÃO",VLOOKUP(D63,Composição!B:J,6,FALSE),IF(E63="COMPOSIÇÃO",VLOOKUP(D63,'Sinapi_Comp-06.2023'!G:I,3,FALSE),VLOOKUP(D63,'Sinapi_Insum-06.2023'!A:C,3,FALSE))))) -> M2 | V63: 86.05
B64: =G64 -> 1.3.1.4.1 | F64: =CONCATENATE(F63,".1") -> 1.3.1.4.1 | G64: =F64 -> 1.3.1.4.1 | H64: sapatas | I64: Área de forma das sapatas da edificação (Conforme quadro resumo do projetos estrutural) | J64: 1 | K64: 57.41 | Q64: =IF(SUM(K64:L64)=0,1,IF(L64<>0,SUM(K64:L64)/2,K64))*IF(SUM(M64:N64)=0,1,IF(N64<>0,SUM(M64:N64)/2,M64))*IF(SUM(O64:P64)=0,1,IF(P64<>0,SUM(O64:P64)/2,O64)) -> 57.41 | R64: =ROUND(J64*Q64,2) -> 57.41
B65: =G65 -> 1.3.1.5 | C65: SINAPI | D65: 96536 | E65: COMPOSIÇÃO | F65: 1.3.1.5 | G65: =F65 -> 1.3.1.5 | H65: =IF(C65="GIDUR JP",VLOOKUP(D65,GIDUR!A:D,2,FALSE),IF(C65="DER PB",VLOOKUP('M.Cálc.Quant.'!D65,DER!A:D,2,FALSE),IF(C65="COMPOSIÇÃO",VLOOKUP(D65,Composição!B:J,2,FALSE),IF(E65="COMPOSIÇÃO",VLOOKUP(D65,'Sinapi_Comp-06.2023'!G:H,2,FALSE),VLOOKUP(D65,'Sinapi_Insum-06.2023'!A:B,2,FALSE))))) -> FABRICAÇÃO, MONTAGEM E DESMONTAGEM DE FÔRMA PARA VIGA BALDRAME, EM MADEIRA SERRADA, E=25 MM, 4 UTILIZAÇÕES. AF_01/2024 | S65: =SUM(R66:R66) -> 111.16 | T65: =IF(C65="GIDUR JP",VLOOKUP(D65,GIDUR!A:D,3,FALSE),IF(C65="DER PB",VLOOKUP('M.Cálc.Quant.'!D65,DER!A:D,3,FALSE),IF(C65="COMPOSIÇÃO",VLOOKUP(D65,Composição!B:J,6,FALSE),IF(E65="COMPOSIÇÃO",VLOOKUP(D65,'Sinapi_Comp-06.2023'!G:I,3,FALSE),VLOOKUP(D65,'Sinapi_Insum-06.2023'!A:C,3,FALSE))))) -> M2 | V65: 172.3
B66: =G66 -> 1.3.1.5.1 | F66: =CONCATENATE(F65,".1") -> 1.3.1.5.1 | G66: =F66 -> 1.3.1.5.1 | H66: Vigas baldrames | I66: Conforme quadro resumo do projetos estrutural | J66: 1 | K66: 111.16 | Q66: =IF(SUM(K66:L66)=0,1,IF(L66<>0,SUM(K66:L66)/2,K66))*IF(SUM(M66:N66)=0,1,IF(N66<>0,SUM(M66:N66)/2,M66))*IF(SUM(O66:P66)=0,1,IF(P66<>0,SUM(O66:P66)/2,O66)) -> 111.16 | R66: =ROUND(J66*Q66,2) -> 111.16
B67: =G67 -> 1.3.1.6 | C67: SINAPI | D67: 96544 | E67: COMPOSIÇÃO | F67: 1.3.1.6 | G67: =F67 -> 1.3.1.6 | H67: =IF(C67="GIDUR JP",VLOOKUP(D67,GIDUR!A:D,2,FALSE),IF(C67="DER PB",VLOOKUP('M.Cálc.Quant.'!D67,DER!A:D,2,FALSE),IF(C67="COMPOSIÇÃO",VLOOKUP(D67,Composição!B:J,2,FALSE),IF(E67="COMPOSIÇÃO",VLOOKUP(D67,'Sinapi_Comp-06.2023'!G:H,2,FALSE),VLOOKUP(D67,'Sinapi_Insum-06.2023'!A:B,2,FALSE))))) -> ARMAÇÃO DE BLOCO UTILIZANDO AÇO CA-50 DE 6,3 MM - MONTAGEM. AF_01/2024 | S67: =SUM(R68) -> 97.5 | T67: =IF(C67="GIDUR JP",VLOOKUP(D67,GIDUR!A:D,3,FALSE),IF(C67="DER PB",VLOOKUP('M.Cálc.Quant.'!D67,DER!A:D,3,FALSE),IF(C67="COMPOSIÇÃO",VLOOKUP(D67,Composição!B:J,6,FALSE),IF(E67="COMPOSIÇÃO",VLOOKUP(D67,'Sinapi_Comp-06.2023'!G:I,3,FALSE),VLOOKUP(D67,'Sinapi_Insum-06.2023'!A:C,3,FALSE))))) -> KG | V67: 495.5
B68: =G68 -> 1.3.1.6.1 | F68: =CONCATENATE(F67,".1") -> 1.3.1.6.1 | G68: =F68 -> 1.3.1.6.1 | H68: Sapatas | I68: Conforme quadro resumo do projetos estrutural | J68: 1 | K68: 97.5 | Q68: =IF(SUM(K68:L68)=0,1,IF(L68<>0,SUM(K68:L68)/2,K68))*IF(SUM(M68:N68)=0,1,IF(N68<>0,SUM(M68:N68)/2,M68))*IF(SUM(O68:P68)=0,1,IF(P68<>0,SUM(O68:P68)/2,O68)) -> 97.5 | R68: =ROUND(J68*Q68,2) -> 97.5
B69: =G69 -> 1.3.1.7 | C69: SINAPI | D69: 96545 | E69: COMPOSIÇÃO | F69: 1.3.1.7 | G69: =F69 -> 1.3.1.7 | H69: =IF(C69="GIDUR JP",VLOOKUP(D69,GIDUR!A:D,2,FALSE),IF(C69="DER PB",VLOOKUP('M.Cálc.Quant.'!D69,DER!A:D,2,FALSE),IF(C69="COMPOSIÇÃO",VLOOKUP(D69,Composição!B:J,2,FALSE),IF(E69="COMPOSIÇÃO",VLOOKUP(D69,'Sinapi_Comp-06.2023'!G:H,2,FALSE),VLOOKUP(D69,'Sinapi_Insum-06.2023'!A:B,2,FALSE))))) -> ARMAÇÃO DE BLOCO UTILIZANDO AÇO CA-50 DE 8 MM - MONTAGEM. AF_01/2024 | S69: =SUM(R70:R71) -> 394.6 | T69: =IF(C69="GIDUR JP",VLOOKUP(D69,GIDUR!A:D,3,FALSE),IF(C69="DER PB",VLOOKUP('M.Cálc.Quant.'!D69,DER!A:D,3,FALSE),IF(C69="COMPOSIÇÃO",VLOOKUP(D69,Composição!B:J,6,FALSE),IF(E69="COMPOSIÇÃO",VLOOKUP(D69,'Sinapi_Comp-06.2023'!G:I,3,FALSE),VLOOKUP(D69,'Sinapi_Insum-06.2023'!A:C,3,FALSE))))) -> KG | V69: 41.2
B70: =G70 -> 1.3.1.7.1 | F70: =CONCATENATE(F69,".1") -> 1.3.1.7.1 | G70: =F70 -> 1.3.1.7.1 | H70: Sapatas | I70: Conforme quadro resumo do projetos estrutural | J70: 1 | K70: 275.5 | Q70: =IF(SUM(K70:L70)=0,1,IF(L70<>0,SUM(K70:L70)/2,K70))*IF(SUM(M70:N70)=0,1,IF(N70<>0,SUM(M70:N70)/2,M70))*IF(SUM(O70:P70)=0,1,IF(P70<>0,SUM(O70:P70)/2,O70)) -> 275.5 | R70: =ROUND(J70*Q70,2) -> 275.5
B71: =G71 -> 1.3.1.7.2 | F71: =CONCATENATE(F69,".2") -> 1.3.1.7.2 | G71: =F71 -> 1.3.1.7.2 | H71: Vigas baldrames | I71: Conforme quadro resumo do projetos estrutural | J71: 1 | K71: 119.1 | Q71: =IF(SUM(K71:L71)=0,1,IF(L71<>0,SUM(K71:L71)/2,K71))*IF(SUM(M71:N71)=0,1,IF(N71<>0,SUM(M71:N71)/2,M71))*IF(SUM(O71:P71)=0,1,IF(P71<>0,SUM(O71:P71)/2,O71)) -> 119.1 | R71: =ROUND(J71*Q71,2) -> 119.1
B72: =G72 -> 1.3.1.8 | C72: SINAPI | D72: 96546 | E72: COMPOSIÇÃO | F72: 1.3.1.8 | G72: =F72 -> 1.3.1.8 | H72: =IF(C72="GIDUR JP",VLOOKUP(D72,GIDUR!A:D,2,FALSE),IF(C72="DER PB",VLOOKUP('M.Cálc.Quant.'!D72,DER!A:D,2,FALSE),IF(C72="COMPOSIÇÃO",VLOOKUP(D72,Composição!B:J,2,FALSE),IF(E72="COMPOSIÇÃO",VLOOKUP(D72,'Sinapi_Comp-06.2023'!G:H,2,FALSE),VLOOKUP(D72,'Sinapi_Insum-06.2023'!A:B,2,FALSE))))) -> ARMAÇÃO DE BLOCO UTILIZANDO AÇO CA-50 DE 10 MM - MONTAGEM. AF_01/2024 | S72: =SUM(R73:R74) -> 335.6 | T72: =IF(C72="GIDUR JP",VLOOKUP(D72,GIDUR!A:D,3,FALSE),IF(C72="DER PB",VLOOKUP('M.Cálc.Quant.'!D72,DER!A:D,3,FALSE),IF(C72="COMPOSIÇÃO",VLOOKUP(D72,Composição!B:J,6,FALSE),IF(E72="COMPOSIÇÃO",VLOOKUP(D72,'Sinapi_Comp-06.2023'!G:I,3,FALSE),VLOOKUP(D72,'Sinapi_Insum-06.2023'!A:C,3,FALSE))))) -> KG | V72: 66
B73: =G73 -> 1.3.1.8.1 | F73: =CONCATENATE(F72,".1") -> 1.3.1.8.1 | G73: =F73 -> 1.3.1.8.1 | H73: Sapatas | I73: Conforme quadro resumo do projetos estrutural | J73: 1 | K73: 123.2 | Q73: =IF(SUM(K73:L73)=0,1,IF(L73<>0,SUM(K73:L73)/2,K73))*IF(SUM(M73:N73)=0,1,IF(N73<>0,SUM(M73:N73)/2,M73))*IF(SUM(O73:P73)=0,1,IF(P73<>0,SUM(O73:P73)/2,O73)) -> 123.2 | R73: =ROUND(J73*Q73,2) -> 123.2
B74: =G74 -> 1.3.1.8.2 | F74: =CONCATENATE(F72,".2") -> 1.3.1.8.2 | G74: =F74 -> 1.3.1.8.2 | H74: Vigas baldrames | J74: 1 | K74: 212.4 | Q74: =IF(SUM(K74:L74)=0,1,IF(L74<>0,SUM(K74:L74)/2,K74))*IF(SUM(M74:N74)=0,1,IF(N74<>0,SUM(M74:N74)/2,M74))*IF(SUM(O74:P74)=0,1,IF(P74<>0,SUM(O74:P74)/2,O74)) -> 212.4 | R74: =ROUND(J74*Q74,2) -> 212.4
B75: =G75 -> 1.3.1.9 | C75: SINAPI | D75: 104920 | E75: COMPOSIÇÃO | F75: 1.3.1.9 | G75: =F75 -> 1.3.1.9 | H75: =IF(C75="GIDUR JP",VLOOKUP(D75,GIDUR!A:D,2,FALSE),IF(C75="DER PB",VLOOKUP('M.Cálc.Quant.'!D75,DER!A:D,2,FALSE),IF(C75="COMPOSIÇÃO",VLOOKUP(D75,Composição!B:J,2,FALSE),IF(E75="COMPOSIÇÃO",VLOOKUP(D75,'Sinapi_Comp-06.2023'!G:H,2,FALSE),VLOOKUP(D75,'Sinapi_Insum-06.2023'!A:B,2,FALSE))))) -> ARMAÇÃO DE BLOCO, SAPATA ISOLADA, VIGA BALDRAME E SAPATA CORRIDA UTILIZANDO AÇO CA-50 DE 12,5 MM - MONTAGEM. AF_01/2024 | S75: =SUM(R76) -> 169.9 | T75: =IF(C75="GIDUR JP",VLOOKUP(D75,GIDUR!A:D,3,FALSE),IF(C75="DER PB",VLOOKUP('M.Cálc.Quant.'!D75,DER!A:D,3,FALSE),IF(C75="COMPOSIÇÃO",VLOOKUP(D75,Composição!B:J,6,FALSE),IF(E75="COMPOSIÇÃO",VLOOKUP(D75,'Sinapi_Comp-06.2023'!G:I,3,FALSE),VLOOKUP(D75,'Sinapi_Insum-06.2023'!A:C,3,FALSE))))) -> KG
B76: =G76 -> 1.3.1.9.1 | F76: =CONCATENATE(F75,".1") -> 1.3.1.9.1 | G76: =F76 -> 1.3.1.9.1 | H76: Sapatas | I76: Conforme quadro resumo do projetos estrutural | J76: 1 | K76: 169.9 | Q76: =IF(SUM(K76:L76)=0,1,IF(L76<>0,SUM(K76:L76)/2,K76))*IF(SUM(M76:N76)=0,1,IF(N76<>0,SUM(M76:N76)/2,M76))*IF(SUM(O76:P76)=0,1,IF(P76<>0,SUM(O76:P76)/2,O76)) -> 169.9 | R76: =ROUND(J76*Q76,2) -> 169.9
B77: =G77 -> 1.3.1.9.2 | F77: =CONCATENATE(F75,".2") -> 1.3.1.9.2 | G77: =F77 -> 1.3.1.9.2 | H77: Vigas baldrames
B78: =G78 -> 1.3.1.10 | C78: SINAPI | D78: 96543 | E78: COMPOSIÇÃO | F78: 1.3.1.10 | G78: =F78 -> 1.3.1.10 | H78: =IF(C78="GIDUR JP",VLOOKUP(D78,GIDUR!A:D,2,FALSE),IF(C78="DER PB",VLOOKUP('M.Cálc.Quant.'!D78,DER!A:D,2,FALSE),IF(C78="COMPOSIÇÃO",VLOOKUP(D78,Composição!B:J,2,FALSE),IF(E78="COMPOSIÇÃO",VLOOKUP(D78,'Sinapi_Comp-06.2023'!G:H,2,FALSE),VLOOKUP(D78,'Sinapi_Insum-06.2023'!A:B,2,FALSE))))) -> ARMAÇÃO DE BLOCO UTILIZANDO AÇO CA-60 DE 5 MM - MONTAGEM. AF_01/2024 | S78: =SUM(R79:R80) -> 182.3 | T78: =IF(C78="GIDUR JP",VLOOKUP(D78,GIDUR!A:D,3,FALSE),IF(C78="DER PB",VLOOKUP('M.Cálc.Quant.'!D78,DER!A:D,3,FALSE),IF(C78="COMPOSIÇÃO",VLOOKUP(D78,Composição!B:J,6,FALSE),IF(E78="COMPOSIÇÃO",VLOOKUP(D78,'Sinapi_Comp-06.2023'!G:I,3,FALSE),VLOOKUP(D78,'Sinapi_Insum-06.2023'!A:C,3,FALSE))))) -> KG | V78: 78
B79: =G79 -> 1.3.1.10.1 | F79: =CONCATENATE(F78,".1") -> 1.3.1.10.1 | G79: =F79 -> 1.3.1.10.1 | H79: Sapatas | I79: Conforme quadro resumo do projetos estrutural | J79: 1 | K79: 61.7 | Q79: =IF(SUM(K79:L79)=0,1,IF(L79<>0,SUM(K79:L79)/2,K79))*IF(SUM(M79:N79)=0,1,IF(N79<>0,SUM(M79:N79)/2,M79))*IF(SUM(O79:P79)=0,1,IF(P79<>0,SUM(O79:P79)/2,O79)) -> 61.7 | R79: =ROUND(J79*Q79,2) -> 61.7
B80: =G80 -> 1.3.1.10.2 | F80: =CONCATENATE(F78,".2") -> 1.3.1.10.2 | G80: =F80 -> 1.3.1.10.2 | H80: Viga baldrame | J80: 1 | K80: 120.6 | Q80: =IF(SUM(K80:L80)=0,1,IF(L80<>0,SUM(K80:L80)/2,K80))*IF(SUM(M80:N80)=0,1,IF(N80<>0,SUM(M80:N80)/2,M80))*IF(SUM(O80:P80)=0,1,IF(P80<>0,SUM(O80:P80)/2,O80)) -> 120.6 | R80: =ROUND(J80*Q80,2) -> 120.6
B81: =G81 -> 1.3.1.11 | C81: SINAPI | D81: 94965 | E81: COMPOSIÇÃO | F81: 1.3.1.11 | G81: =F81 -> 1.3.1.11 | H81: =IF(C81="GIDUR JP",VLOOKUP(D81,GIDUR!A:D,2,FALSE),IF(C81="DER PB",VLOOKUP('M.Cálc.Quant.'!D81,DER!A:D,2,FALSE),IF(C81="COMPOSIÇÃO",VLOOKUP(D81,Composição!B:J,2,FALSE),IF(E81="COMPOSIÇÃO",VLOOKUP(D81,'Sinapi_Comp-06.2023'!G:H,2,FALSE),VLOOKUP(D81,'Sinapi_Insum-06.2023'!A:B,2,FALSE))))) -> CONCRETO FCK = 25MPA, TRAÇO 1:2,3:2,7 (EM MASSA SECA DE CIMENTO/ AREIA MÉDIA/ BRITA 1) - PREPARO MECÂNICO COM BETONEIRA 400 L. AF_05/2021 | S81: =SUM(R82:R83) -> 11.04 | T81: =IF(C81="GIDUR JP",VLOOKUP(D81,GIDUR!A:D,3,FALSE),IF(C81="DER PB",VLOOKUP('M.Cálc.Quant.'!D81,DER!A:D,3,FALSE),IF(C81="COMPOSIÇÃO",VLOOKUP(D81,Composição!B:J,6,FALSE),IF(E81="COMPOSIÇÃO",VLOOKUP(D81,'Sinapi_Comp-06.2023'!G:I,3,FALSE),VLOOKUP(D81,'Sinapi_Insum-06.2023'!A:C,3,FALSE))))) -> M3 | V81: 12.74
A82: 4 | B82: =G82 -> 1.3.1.11.1 | F82: =CONCATENATE(F81,".1") -> 1.3.1.11.1 | G82: =F82 -> 1.3.1.11.1 | H82: sapatas | J82: 1 | K82: 2.38 | Q82: =IF(SUM(K82:L82)=0,1,IF(L82<>0,SUM(K82:L82)/2,K82))*IF(SUM(M82:N82)=0,1,IF(N82<>0,SUM(M82:N82)/2,M82))*IF(SUM(O82:P82)=0,1,IF(P82<>0,SUM(O82:P82)/2,O82)) -> 2.38 | R82: =ROUND(J82*Q82,2) -> 2.38
A83: 4 | B83: =G83 -> 1.3.1.11.2 | F83: =CONCATENATE(F81,".2") -> 1.3.1.11.2 | G83: =F83 -> 1.3.1.11.2 | H83: Vigas baldrames | J83: 1 | K83: 8.66 | Q83: =IF(SUM(K83:L83)=0,1,IF(L83<>0,SUM(K83:L83)/2,K83))*IF(SUM(M83:N83)=0,1,IF(N83<>0,SUM(M83:N83)/2,M83))*IF(SUM(O83:P83)=0,1,IF(P83<>0,SUM(O83:P83)/2,O83)) -> 8.66 | R83: =ROUND(J83*Q83,2) -> 8.66
A84: 4 | B84: =G84 -> 1.3.1.12 | C84: SINAPI | D84: 103670 | E84: COMPOSIÇÃO | F84: 1.3.1.12 | G84: =F84 -> 1.3.1.12 | H84: =IF(C84="GIDUR JP",VLOOKUP(D84,GIDUR!A:D,2,FALSE),IF(C84="DER PB",VLOOKUP('M.Cálc.Quant.'!D84,DER!A:D,2,FALSE),IF(C84="COMPOSIÇÃO",VLOOKUP(D84,Composição!B:J,2,FALSE),IF(E84="COMPOSIÇÃO",VLOOKUP(D84,'Sinapi_Comp-06.2023'!G:H,2,FALSE),VLOOKUP(D84,'Sinapi_Insum-06.2023'!A:B,2,FALSE))))) -> LANÇAMENTO COM USO DE BALDES, ADENSAMENTO E ACABAMENTO DE CONCRETO EM ESTRUTURAS. AF_02/2022 | S84: =SUM(R85) -> 21.64 | T84: =IF(C84="GIDUR JP",VLOOKUP(D84,GIDUR!A:D,3,FALSE),IF(C84="DER PB",VLOOKUP('M.Cálc.Quant.'!D84,DER!A:D,3,FALSE),IF(C84="COMPOSIÇÃO",VLOOKUP(D84,Composição!B:J,6,FALSE),IF(E84="COMPOSIÇÃO",VLOOKUP(D84,'Sinapi_Comp-06.2023'!G:I,3,FALSE),VLOOKUP(D84,'Sinapi_Insum-06.2023'!A:C,3,FALSE))))) -> M3 | V84: 12.74
A85: 4 | B85: =G85 -> 1.3.1.12.1 | F85: =CONCATENATE(F84,".1") -> 1.3.1.12.1 | G85: =F85 -> 1.3.1.12.1 | H85: =LEFT(H84,SEARCH(" ",H84)-1) -> LANÇAMENTO | I85: Conforme quadro resumo do projetos estrutural | J85: 1 | K85: =S81+K89 -> 21.64 | Q85: =IF(SUM(K85:L85)=0,1,IF(L85<>0,SUM(K85:L85)/2,K85))*IF(SUM(M85:N85)=0,1,IF(N85<>0,SUM(M85:N85)/2,M85))*IF(SUM(O85:P85)=0,1,IF(P85<>0,SUM(O85:P85)/2,O85)) -> 21.64 | R85: =ROUND(J85*Q85,2) -> 21.64
A86: 4 | B86: =G86 -> 1.3.1.13 | C86: COMPOSIÇÃO | D86: =Composição!B62 -> 11 | E86: COMPOSIÇÃO | F86: 1.3.1.13 | G86: =F86 -> 1.3.1.13 | H86: =IF(C86="GIDUR JP",VLOOKUP(D86,GIDUR!A:D,2,FALSE),IF(C86="DER PB",VLOOKUP('M.Cálc.Quant.'!D86,DER!A:D,2,FALSE),IF(C86="COMPOSIÇÃO",VLOOKUP(D86,Composição!B:J,2,FALSE),IF(E86="COMPOSIÇÃO",VLOOKUP(D86,'Sinapi_Comp-06.2023'!G:H,2,FALSE),VLOOKUP(D86,'Sinapi_Insum-06.2023'!A:B,2,FALSE))))) -> IMPERMEABILIZACAO DE ESTRUTURAS ENTERRADAS, COM TINTA ASFALTICA, DUAS DEMAOS. [ADAPTADO SINAPI 74106/001] | S86: =SUM(R87) -> 112.92 | T86: =IF(C86="GIDUR JP",VLOOKUP(D86,GIDUR!A:D,3,FALSE),IF(C86="DER PB",VLOOKUP('M.Cálc.Quant.'!D86,DER!A:D,3,FALSE),IF(C86="COMPOSIÇÃO",VLOOKUP(D86,Composição!B:J,6,FALSE),IF(E86="COMPOSIÇÃO",VLOOKUP(D86,'Sinapi_Comp-06.2023'!G:I,3,FALSE),VLOOKUP(D86,'Sinapi_Insum-06.2023'!A:C,3,FALSE))))) -> M2
A87: 4 | B87: =G87 -> 1.3.1.13.1 | F87: =CONCATENATE(F86,".1") -> 1.3.1.13.1 | G87: =F87 -> 1.3.1.13.1 | H87: =LEFT(H86,SEARCH(" ",H86)-1) -> IMPERMEABILIZACAO | J87: 1 | K87: =27.3+27.3+19.75+19.75 -> 94.1 | M87: 1.2 | Q87: =IF(SUM(K87:L87)=0,1,IF(L87<>0,SUM(K87:L87)/2,K87))*IF(SUM(M87:N87)=0,1,IF(N87<>0,SUM(M87:N87)/2,M87))*IF(SUM(O87:P87)=0,1,IF(P87<>0,SUM(O87:P87)/2,O87)) -> 112.92 | R87: =ROUND(J87*Q87,2) -> 112.92
A88: 4 | B88: =G88 -> 1.3.1.14 | C88: SINAPI | D88: 94966 | E88: COMPOSIÇÃO | F88: 1.3.1.14 | G88: =F88 -> 1.3.1.14 | H88: =IF(C88="GIDUR JP",VLOOKUP(D88,GIDUR!A:D,2,FALSE),IF(C88="DER PB",VLOOKUP('M.Cálc.Quant.'!D88,DER!A:D,2,FALSE),IF(C88="COMPOSIÇÃO",VLOOKUP(D88,Composição!B:J,2,FALSE),IF(E88="COMPOSIÇÃO",VLOOKUP(D88,'Sinapi_Comp-06.2023'!G:H,2,FALSE),VLOOKUP(D88,'Sinapi_Insum-06.2023'!A:B,2,FALSE))))) -> CONCRETO FCK = 30MPA, TRAÇO 1:2,1:2,5 (EM MASSA SECA DE CIMENTO/ AREIA MÉDIA/ BRITA 1) - PREPARO MECÂNICO COM BETONEIRA 400 L. AF_05/2021 | S88: =SUM(R89) -> 10.6 | T88: =IF(C88="GIDUR JP",VLOOKUP(D88,GIDUR!A:D,3,FALSE),IF(C88="DER PB",VLOOKUP('M.Cálc.Quant.'!D88,DER!A:D,3,FALSE),IF(C88="COMPOSIÇÃO",VLOOKUP(D88,Composição!B:J,6,FALSE),IF(E88="COMPOSIÇÃO",VLOOKUP(D88,'Sinapi_Comp-06.2023'!G:I,3,FALSE),VLOOKUP(D88,'Sinapi_Insum-06.2023'!A:C,3,FALSE))))) -> M3
A89: 4 | B89: =G89 -> 1.3.1.14.1 | F89: =CONCATENATE(F88,".1") -> 1.3.1.14.1 | G89: =F89 -> 1.3.1.14.1 | H89: sapatas | J89: 1 | K89: 10.6 | Q89: =IF(SUM(K89:L89)=0,1,IF(L89<>0,SUM(K89:L89)/2,K89))*IF(SUM(M89:N89)=0,1,IF(N89<>0,SUM(M89:N89)/2,M89))*IF(SUM(O89:P89)=0,1,IF(P89<>0,SUM(O89:P89)/2,O89)) -> 10.6 | R89: =ROUND(J89*Q89,2) -> 10.6
A90: 4 | B90: =G90 -> 1.4 | E90: #N/A | F90: 1.4 | G90: =F90 -> 1.4 | H90: SUPERESTRUTURA (PILARES, VIGAS E LAJES) - TODA A QUADRA
A91: 4 | B91: =G91 -> 1.4.1 | E91: #N/A | F91: 1.4.1 | G91: =F91 -> 1.4.1 | H91: CONCRETO ARMADO PARA PILARES DA EDIFICAÇÃO
A92: 4 | B92: =G92 -> 1.4.1.1 | C92: SINAPI | D92: 92443 | E92: COMPOSIÇÃO | F92: 1.4.1.1 | G92: =F92 -> 1.4.1.1 | H92: =IF(C92="GIDUR JP",VLOOKUP(D92,GIDUR!A:D,2,FALSE),IF(C92="DER PB",VLOOKUP('M.Cálc.Quant.'!D92,DER!A:D,2,FALSE),IF(C92="COMPOSIÇÃO",VLOOKUP(D92,Composição!B:J,2,FALSE),IF(E92="COMPOSIÇÃO",VLOOKUP(D92,'Sinapi_Comp-06.2023'!G:H,2,FALSE),VLOOKUP(D92,'Sinapi_Insum-06.2023'!A:B,2,FALSE))))) -> MONTAGEM E DESMONTAGEM DE FÔRMA DE PILARES RETANGULARES E ESTRUTURAS SIMILARES, PÉ-DIREITO SIMPLES, EM CHAPA DE MADEIRA COMPENSADA PLASTIFICADA, 18 UTILIZAÇÕES. AF_09/2020 | S92: =SUM(R93:R96) -> 90.78 | T92: =IF(C92="GIDUR JP",VLOOKUP(D92,GIDUR!A:D,3,FALSE),IF(C92="DER PB",VLOOKUP('M.Cálc.Quant.'!D92,DER!A:D,3,FALSE),IF(C92="COMPOSIÇÃO",VLOOKUP(D92,Composição!B:J,6,FALSE),IF(E92="COMPOSIÇÃO",VLOOKUP(D92,'Sinapi_Comp-06.2023'!G:I,3,FALSE),VLOOKUP(D92,'Sinapi_Insum-06.2023'!A:C,3,FALSE))))) -> M2 | V92: 311.32
A93: 4 | B93: =G93 -> 1.4.1.1.1 | F93: 1.4.1.1.1 | G93: =F93 -> 1.4.1.1.1 | H93: pilares baldrames | I93: Conforme quadro resumo do projetos estrutural | J93: 1 | K93: 8.56 | Q93: =IF(SUM(K93:L93)=0,1,IF(L93<>0,SUM(K93:L93)/2,K93))*IF(SUM(M93:N93)=0,1,IF(N93<>0,SUM(M93:N93)/2,M93))*IF(SUM(O93:P93)=0,1,IF(P93<>0,SUM(O93:P93)/2,O93)) -> 8.56 | R93: =ROUND(J93*Q93,2) -> 8.56
A94: 4 | B94: =G94 -> 1.4.1.1.2 | F94: 1.4.1.1.2 | G94: =F94 -> 1.4.1.1.2 | H94: pilares terreo | J94: 1 | K94: 54.16 | Q94: =IF(SUM(K94:L94)=0,1,IF(L94<>0,SUM(K94:L94)/2,K94))*IF(SUM(M94:N94)=0,1,IF(N94<>0,SUM(M94:N94)/2,M94))*IF(SUM(O94:P94)=0,1,IF(P94<>0,SUM(O94:P94)/2,O94)) -> 54.16 | R94: =ROUND(J94*Q94,2) -> 54.16
A95: 5 | B95: =G95 -> 1.4.1.1.3 | F95: 1.4.1.1.3 | G95: =F95 -> 1.4.1.1.3 | H95: pilares terreo 02 | J95: 1 | K95: 4.06 | Q95: =IF(SUM(K95:L95)=0,1,IF(L95<>0,SUM(K95:L95)/2,K95))*IF(SUM(M95:N95)=0,1,IF(N95<>0,SUM(M95:N95)/2,M95))*IF(SUM(O95:P95)=0,1,IF(P95<>0,SUM(O95:P95)/2,O95)) -> 4.06 | R95: =ROUND(J95*Q95,2) -> 4.06
A96: 6 | B96: =G96 -> 1.4.1.1.4 | F96: 1.4.1.1.4 | G96: =F96 -> 1.4.1.1.4 | H96: pilares terreo 03 | J96: 1 | K96: 24 | Q96: =IF(SUM(K96:L96)=0,1,IF(L96<>0,SUM(K96:L96)/2,K96))*IF(SUM(M96:N96)=0,1,IF(N96<>0,SUM(M96:N96)/2,M96))*IF(SUM(O96:P96)=0,1,IF(P96<>0,SUM(O96:P96)/2,O96)) -> 24 | R96: =ROUND(J96*Q96,2) -> 24
A97: 4 | B97: =G97 -> 1.4.1.2 | C97: SINAPI | D97: 92759 | E97: COMPOSIÇÃO | F97: 1.4.1.2 | G97: =F97 -> 1.4.1.2 | H97: =IF(C97="GIDUR JP",VLOOKUP(D97,GIDUR!A:D,2,FALSE),IF(C97="DER PB",VLOOKUP('M.Cálc.Quant.'!D97,DER!A:D,2,FALSE),IF(C97="COMPOSIÇÃO",VLOOKUP(D97,Composição!B:J,2,FALSE),IF(E97="COMPOSIÇÃO",VLOOKUP(D97,'Sinapi_Comp-06.2023'!G:H,2,FALSE),VLOOKUP(D97,'Sinapi_Insum-06.2023'!A:B,2,FALSE))))) -> ARMAÇÃO DE PILAR OU VIGA DE ESTRUTURA CONVENCIONAL DE CONCRETO ARMADO UTILIZANDO AÇO CA-60 DE 5,0 MM - MONTAGEM. AF_06/2022 | S97: =SUM(R98:R101) -> 164.5 | T97: =IF(C97="GIDUR JP",VLOOKUP(D97,GIDUR!A:D,3,FALSE),IF(C97="DER PB",VLOOKUP('M.Cálc.Quant.'!D97,DER!A:D,3,FALSE),IF(C97="COMPOSIÇÃO",VLOOKUP(D97,Composição!B:J,6,FALSE),IF(E97="COMPOSIÇÃO",VLOOKUP(D97,'Sinapi_Comp-06.2023'!G:I,3,FALSE),VLOOKUP(D97,'Sinapi_Insum-06.2023'!A:C,3,FALSE))))) -> KG | V97: 363.6
A98: 4 | B98: =G98 -> 1.4.1.2.1 | F98: 1.4.1.2.1 | G98: =F98 -> 1.4.1.2.1 | H98: pilares baldrames | I98: Conforme quadro resumo do projetos estrutural | J98: 1 | K98: 19 | Q98: =IF(SUM(K98:L98)=0,1,IF(L98<>0,SUM(K98:L98)/2,K98))*IF(SUM(M98:N98)=0,1,IF(N98<>0,SUM(M98:N98)/2,M98))*IF(SUM(O98:P98)=0,1,IF(P98<>0,SUM(O98:P98)/2,O98)) -> 19 | R98: =ROUND(J98*Q98,2) -> 19
A99: 5 | B99: =G99 -> 1.4.1.2.2 | F99: 1.4.1.2.2 | G99: =F99 -> 1.4.1.2.2 | H99: pilares terreo | J99: 1 | K99: 109.2 | Q99: =IF(SUM(K99:L99)=0,1,IF(L99<>0,SUM(K99:L99)/2,K99))*IF(SUM(M99:N99)=0,1,IF(N99<>0,SUM(M99:N99)/2,M99))*IF(SUM(O99:P99)=0,1,IF(P99<>0,SUM(O99:P99)/2,O99)) -> 109.2 | R99: =ROUND(J99*Q99,2) -> 109.2
A100: 6 | B100: =G100 -> 1.4.1.2.3 | F100: 1.4.1.2.3 | G100: =F100 -> 1.4.1.2.3 | H100: pilares terreo 02 | J100: 1 | K100: 9.6 | Q100: =IF(SUM(K100:L100)=0,1,IF(L100<>0,SUM(K100:L100)/2,K100))*IF(SUM(M100:N100)=0,1,IF(N100<>0,SUM(M100:N100)/2,M100))*IF(SUM(O100:P100)=0,1,IF(P100<>0,SUM(O100:P100)/2,O100)) -> 9.6 | R100: =ROUND(J100*Q100,2) -> 9.6
A101: 7 | B101: =G101 -> 1.4.1.2.4 | F101: 1.4.1.2.4 | G101: =F101 -> 1.4.1.2.4 | H101: pilares terreo 03 | J101: 1 | K101: 26.7 | Q101: =IF(SUM(K101:L101)=0,1,IF(L101<>0,SUM(K101:L101)/2,K101))*IF(SUM(M101:N101)=0,1,IF(N101<>0,SUM(M101:N101)/2,M101))*IF(SUM(O101:P101)=0,1,IF(P101<>0,SUM(O101:P101)/2,O101)) -> 26.7 | R101: =ROUND(J101*Q101,2) -> 26.7
A102: 4 | B102: =G102 -> 1.4.1.3 | C102: SINAPI | D102: 92762 | E102: COMPOSIÇÃO | F102: 1.4.1.3 | G102: =F102 -> 1.4.1.3 | H102: =IF(C102="GIDUR JP",VLOOKUP(D102,GIDUR!A:D,2,FALSE),IF(C102="DER PB",VLOOKUP('M.Cálc.Quant.'!D102,DER!A:D,2,FALSE),IF(C102="COMPOSIÇÃO",VLOOKUP(D102,Composição!B:J,2,FALSE),IF(E102="COMPOSIÇÃO",VLOOKUP(D102,'Sinapi_Comp-06.2023'!G:H,2,FALSE),VLOOKUP(D102,'Sinapi_Insum-06.2023'!A:B,2,FALSE))))) -> ARMAÇÃO DE PILAR OU VIGA DE ESTRUTURA CONVENCIONAL DE CONCRETO ARMADO UTILIZANDO AÇO CA-50 DE 10,0 MM - MONTAGEM. AF_06/2022 | S102: =SUM(R103:R105) -> 356.5 | T102: =IF(C102="GIDUR JP",VLOOKUP(D102,GIDUR!A:D,3,FALSE),IF(C102="DER PB",VLOOKUP('M.Cálc.Quant.'!D102,DER!A:D,3,FALSE),IF(C102="COMPOSIÇÃO",VLOOKUP(D102,Composição!B:J,6,FALSE),IF(E102="COMPOSIÇÃO",VLOOKUP(D102,'Sinapi_Comp-06.2023'!G:I,3,FALSE),VLOOKUP(D102,'Sinapi_Insum-06.2023'!A:C,3,FALSE))))) -> KG | V102: 224.3
A103: 4 | B103: =G103 -> 1.4.1.3.1 | F103: 1.4.1.3.1 | G103: =F103 -> 1.4.1.3.1 | H103: pilares baldrames | I103: Conforme quadro resumo do projetos estrutural | J103: 1 | K103: 85.3 | Q103: =IF(SUM(K103:L103)=0,1,IF(L103<>0,SUM(K103:L103)/2,K103))*IF(SUM(M103:N103)=0,1,IF(N103<>0,SUM(M103:N103)/2,M103))*IF(SUM(O103:P103)=0,1,IF(P103<>0,SUM(O103:P103)/2,O103)) -> 85.3 | R103: =ROUND(J103*Q103,2) -> 85.3
...

Sheet Planilha2
C4: DATA BASE 08/2020
G5: composições | L5: Qtd | M5: Valor Total
C6: 1 | D6: ATERRO APILOADO(MANUAL) EM CAMADAS DE 20 CM COM EMPRÉSTIMO DE MATERIAL [ADAPTADO SINAPI 73904/001] | H6: M3 | J6: =SUM(K7:K8) -> 63.99 | L6: 58.37 | M6: =L6*J6 -> 3735.1
C7: =CONCATENATE(C6,".1") -> 1.1 | D7: SINAPI PB | E7: INSUMO | F7: 6079 | G7: ARGILA, ARGILA VERMELHA OU ARGILA ARENOSA (RETIRADA NA JAZIDA, SEM TRANSPORTE) | H7: M³ | I7: 1.1 | J7: =9.43*1.3024 -> 12.281632 | K7: =ROUND(J7*I7,2) -> 13.51
C8: =CONCATENATE(C6,".2") -> 1.2 | D8: SINAPI PB | E8: COMPOSIÇÃO | F8: 88316 | G8: SERVENTE COM ENCARGOS COMPLEMENTARES | H8: H | I8: 3 | J8: =12.92*1.3024 -> 16.827008 | K8: =ROUND(J8*I8,2) -> 50.48
C10: 2 | D10: ALVENARIA EM TIJOLO CERAMICO FURADO 9X19X19CM, 1 VEZ (ESPESSURA 19 CM) , ASSENTADO ARGAMASSA TRACO 1:4 (CIMENTO E AREIA MEDIA NAO PENEIRADA), PREPARO MANUAL, JUNTA1 CM [ADAPTADO DE SINAPI 73935/002] | H10: M2 | J10: =SUM(K11:K14) -> 79.61 | L10: 253.76 | M10: =J10*L10 -> 20201.83
C11: =CONCATENATE(C10,".1") -> 2.1 | D11: SINAPI PB | E11: COMPOSIÇÃO | F11: 87373 | G11: ARGAMASSA TRAÇO 1:4 (EM VOLUME DE CIMENTO E AREIA MÉDIA ÚMIDA) PARA CONTRAPISO, PREPARO MANUAL. AF_08/2019 | H11: M3 | I11: 0.0138 | J11: =445.97*1.3024 -> 580.83133 | K11: =ROUND(J11*I11,2) -> 8.02
C12: =CONCATENATE(C10,".2") -> 2.2 | D12: SINAPI PB | E12: COMPOSIÇÃO | F12: 88309 | G12: PEDREIRO COM ENCARGOS COMPLEMENTARES | H12: H | I12: 1.14 | J12: =16.35*1.3024 -> 21.29424 | K12: =ROUND(J12*I12,2) -> 24.28
C13: =CONCATENATE(C10,".3") -> 2.3 | D13: SINAPI PB | E13: COMPOSIÇÃO | F13: 88316 | G13: SERVENTE COM ENCARGOS COMPLEMENTARES | H13: H | I13: 0.88 | J13: =12.92*1.3024 -> 17 | K13: =ROUND(J13*I13,2) -> 14.96
C14: =CONCATENATE(C10,".4") -> 2.4 | D14: SINAPI PB | E14: INSUMO | F14: 7271 | G14: BLOCO CERAMICO / TIJOLO VAZADO PARA ALVENARIA DE VEDACAO, 8 FUROS NA HORIZONTAL, DE 9 X 19 X 19 CM (L XA X C) | H14: UN | I14: 54 | J14: =0.46*1.3024 -> 0.599104 | K14: =ROUND(J14*I14,2) -> 32.35
C15: 3 | D15: DEMOLIÇÃO DE PILARES E VIGAS EM CONCRETO ARMADO, DE FORMA MANUAL, SEM REAPROVEITAMENTO. AF_12/2017 97627 | H15: M3 | J15: =1.3024*163.5 -> 212.94 | L15: 380.64 | M15: =J15*L15 -> 81053.48
L17: total | M17: =SUM(M6:M15) -> 104990.41

Sheet Plan.Orçam.
D2: PROGRAMA: | G2: ='M.Cálc.Quant.'!I2 -> Esporte, Cidadania e Desenvolvimento
D3: CONCEDENTE: | G3: ='M.Cálc.Quant.'!I3 -> Prefeitura Municipal de Coremas - PB
D4: CONVENENTE: | G4: ='M.Cálc.Quant.'!I4 -> Município de Coremas- PB
D5: CONTRATO: | G5: ='M.Cálc.Quant.'!I5 -> RECURSOS GOVERNO DO ESTADO
D6: OBRA: | G6: ='M.Cálc.Quant.'!I6 -> CONSTRUÇÃO DE QUADRA POLIESPORTIVA COM VESTIÁRIOS E BANHEIROS, NO MUNICÍPIO DE COREMAS/PB | J6: Encargos: | K6: =Encargos!C79 -> 85.69
D7: REF. PREÇOS: | G7: ='M.Cálc.Quant.'!I7 -> SINAPI PB - 06/2025 | J7: B.D.I.: | K7: =BDI!$C$31 -> 0.2522
J8: B.D.I fornecimento: | K8: ='BDI-Fornecimento'!C31 -> 0.1675
D9: PLANILHA ORÇAMENTÁRIA
C11: ITEM BASE | D11: FONTE | E11: CÓDIGO | F11: ITEM | G11: DESCRIÇÃO DOS SERVIÇOS | H11: UNID. | I11: QUANT. | J11: VALORES (R$)
J12: UNIT. | K12: TOTAL
F13: 0.0 | G13: CONSTRUÇÃO DE QUADRA POLIESPORTIVA | K13: =K14+K156 -> 845804.73
F14: 1.0 | G14: QUADRA | K14: =K15+K18+K22+K38+K62+K68+K72+K79+K82+K90+K100+K106+K114+K117+K123+K127+K133+K152+K138 -> 716912.86
C15: 1 | F15: 1.1 | G15: =VLOOKUP(F15,'M.Cálc.Quant.'!G:T,2,FALSE) -> SERVIÇOS PRELIMINARES | K15: =SUM(K16:K17) -> 12614.55
A16: =VLOOKUP(F16,'M.Cálc.Quant.'!B:T,4,FALSE) -> COMPOSIÇÃO | C16: 1.1 | D16: =VLOOKUP(F16,'M.Cálc.Quant.'!B:T,2,FALSE) -> COMPOSIÇÃO | E16: =VLOOKUP(F16,'M.Cálc.Quant.'!B:T,3,FALSE) -> 1 | F16: 1.1.1 | G16: =VLOOKUP(F16,'M.Cálc.Quant.'!G:T,2,FALSE) -> PLACA DE OBRA EM CHAPA DE ACO GALVANIZADO [ADAPTADO SINAPI 74209/01] | H16: =VLOOKUP(F16,'M.Cálc.Quant.'!G:T,14,FALSE) -> M2 | I16: =VLOOKUP(F16,'M.Cálc.Quant.'!G:T,13,FALSE) -> 8 | J16: =(1+$K$7)*IF(D16="GIDUR JP",VLOOKUP(E16,GIDUR!A:D,4,FALSE),IF(D16="DER PB",VLOOKUP(E16,DER!A:D,4,FALSE)/(1+DER!$E$2),IF(D16="COMPOSIÇÃO",VLOOKUP(E16,Composição!B:J,8,FALSE),IF(A16="COMPOSIÇÃO",VLOOKUP(E16,'Sinapi_Comp-06.2023'!G:K,5,FALSE),VLOOKUP(E16,'Sinapi_Insum-06.2023'!A:E,5,FALSE))))) -> 623.51 | K16: =IFERROR(ROUND(I16*J16,2),0) -> 4988.08 | M16: =ROUND(I16*J16,2) -> 4988.08
A17: =VLOOKUP(F17,'M.Cálc.Quant.'!B:T,4,FALSE) -> COMPOSIÇÃO | C17: 1.1 | D17: =VLOOKUP(F17,'M.Cálc.Quant.'!B:T,2,FALSE) -> SINAPI | E17: =VLOOKUP(F17,'M.Cálc.Quant.'!B:T,3,FALSE) -> 99059 | F17: 1.1.2 | G17: =VLOOKUP(F17,'M.Cálc.Quant.'!G:T,2,FALSE) -> LOCAÇÃO CONVENCIONAL DE OBRA, UTILIZANDO GABARITO DE TÁBUAS CORRIDAS PONTALETADAS A CADA 2,00M - 2 UTILIZAÇÕES. AF_03/2024 | H17: =VLOOKUP(F17,'M.Cálc.Quant.'!G:T,14,FALSE) -> M | I17: =VLOOKUP(F17,'M.Cálc.Quant.'!G:T,13,FALSE) -> 106.5 | J17: =(1+$K$7)*IF(D17="GIDUR JP",VLOOKUP(E17,GIDUR!A:D,4,FALSE),IF(D17="DER PB",VLOOKUP(E17,DER!A:D,4,FALSE)/(1+DER!$E$2),IF(D17="COMPOSIÇÃO",VLOOKUP(E17,Composição!B:J,8,FALSE),IF(A17="COMPOSIÇÃO",VLOOKUP(E17,'Sinapi_Comp-06.2023'!G:K,5,FALSE),VLOOKUP(E17,'Sinapi_Insum-06.2023'!A:E,5,FALSE))))) -> 71.61 | K17: =IFERROR(ROUND(I17*J17,2),0) -> 7626.47 | L17: =(24+37)*2 -> 122 | M17: =ROUND(I17*J17,2) -> 7626.47
C18: 2 | F18: 1.2 | G18: =VLOOKUP(F18,'M.Cálc.Quant.'!G:T,2,FALSE) -> MOVIMENTO DE TERRA | K18: =K19 -> 5269.52 | M18: =ROUND(I18*J18,2) -> 0
A19: =VLOOKUP(F19,'M.Cálc.Quant.'!B:E,4,FALSE) -> 0 | C19: 3.2 | F19: ='M.Cálc.Quant.'!G20 -> 1.2 | G19: =VLOOKUP(F19,'M.Cálc.Quant.'!G:T,2,FALSE) -> MOVIMENTO DE TERRA | K19: =SUM(K20:K21) -> 5269.52 | M19: =ROUND(I19*J19,2) -> 0
A20: =VLOOKUP(F20,'M.Cálc.Quant.'!B:T,4,FALSE) -> COMPOSIÇÃO | C20: 2.1 | D20: =VLOOKUP(F20,'M.Cálc.Quant.'!B:T,2,FALSE) -> COMPOSIÇÃO | E20: =VLOOKUP(F20,'M.Cálc.Quant.'!B:T,3,FALSE) -> 8 | F20: ='M.Cálc.Quant.'!$G$21 -> 1.2.1 | G20: =VLOOKUP(F20,'M.Cálc.Quant.'!G:T,2,FALSE) -> ESCAVACAO MANUAL EM SOLO-PROF. ATE 1,50 M [ADAPTADO SINAPI 79561/001] | H20: =VLOOKUP(F20,'M.Cálc.Quant.'!G:T,14,FALSE) -> M3 | I20: =VLOOKUP(F20,'M.Cálc.Quant.'!G:T,13,FALSE) -> 74.74 | J20: =(1+$K$7)*IF(D20="GIDUR JP",VLOOKUP(E20,GIDUR!A:D,4,FALSE),IF(D20="DER PB",VLOOKUP(E20,DER!A:D,4,FALSE)/(1+DER!$E$2),IF(D20="COMPOSIÇÃO",VLOOKUP(E20,Composição!B:J,8,FALSE),IF(A20="COMPOSIÇÃO",VLOOKUP(E20,'Sinapi_Comp-06.2023'!G:K,5,FALSE),VLOOKUP(E20,'Sinapi_Insum-06.2023'!A:E,5,FALSE))))) -> 46.76 | K20: =IFERROR(ROUND(I20*J20,2),0) -> 3494.84 | L20: =27*44*0.8 -> 950.4 | M20: =ROUND(I20*J20,2) -> 3494.84
A21: =VLOOKUP(F21,'M.Cálc.Quant.'!B:T,4,FALSE) -> COMPOSIÇÃO | C21: 2.2 | D21: =VLOOKUP(F21,'M.Cálc.Quant.'!B:T,2,FALSE) -> SINAPI | E21: =VLOOKUP(F21,'M.Cálc.Quant.'!B:T,3,FALSE) -> 93382 | F21: ='M.Cálc.Quant.'!$G$33 -> 1.2.2 | G21: =VLOOKUP(F21,'M.Cálc.Quant.'!G:T,2,FALSE) -> REATERRO MANUAL DE VALAS, COM COMPACTADOR DE SOLOS DE PERCUSSÃO. AF_08/2023 | H21: =VLOOKUP(F21,'M.Cálc.Quant.'!G:T,14,FALSE) -> M3 | I21: =VLOOKUP(F21,'M.Cálc.Quant.'!G:T,13,FALSE) -> 63.7 | J21: =(1+$K$7)*IF(D21="GIDUR JP",VLOOKUP(E21,GIDUR!A:D,4,FALSE),IF(D21="DER PB",VLOOKUP(E21,DER!A:D,4,FALSE)/(1+DER!$E$2),IF(D21="COMPOSIÇÃO",VLOOKUP(E21,Composição!B:J,8,FALSE),IF(A21="COMPOSIÇÃO",VLOOKUP(E21,'Sinapi_Comp-06.2023'!G:K,5,FALSE),VLOOKUP(E21,'Sinapi_Insum-06.2023'!A:E,5,FALSE))))) -> 27.86 | K21: =IFERROR(ROUND(I21*J21,2),0) -> 1774.68 | L21: =27*44 -> 1188 | M21: =ROUND(I21*J21,2) -> 1774.68
C22: 3 | F22: 1.3 | G22: =VLOOKUP(F22,'M.Cálc.Quant.'!G:T,2,FALSE) -> INFRA-ESTRUTURA: FUNDAÇÕES (TODA A QUADRA) | K22: =K23 -> 70701.3 | M22: =ROUND(I22*J22,2) -> 0 | S22: =CONCATENATE(#REF!,".1") -> #REF! | T22: SINAPI PB | U22: INSUMO | V22: 6079 | W22: #N/A | X22: #N/A | Y22: 1.1 | Z22: =9.43*1.3024 -> 12.281632 | AA22: =ROUND(Z22*Y22,2) -> 13.51
C23: 3.2 | F23: 1.3.1 | G23: =VLOOKUP(F23,'M.Cálc.Quant.'!G:T,2,FALSE) -> SAPATAS ISOLADAS/ARRANQUE DOS PILARES | K23: =SUM(K24:K37) -> 70701.3 | M23: =ROUND(I23*J23,2) -> 0 | S23: =CONCATENATE(#REF!,".2") -> #REF! | T23: SINAPI PB | U23: COMPOSIÇÃO | V23: 88316 | W23: #N/A | X23: #N/A | Y23: 3 | Z23: =12.92*1.3024 -> 16.827008 | AA23: =ROUND(Z23*Y23,2) -> 50.48
A24: =VLOOKUP(F24,'M.Cálc.Quant.'!B:T,4,FALSE) -> COMPOSIÇÃO | C24: 3.3 | D24: =VLOOKUP(F24,'M.Cálc.Quant.'!B:T,2,FALSE) -> SINAPI | E24: =VLOOKUP(F24,'M.Cálc.Quant.'!B:T,3,FALSE) -> 101616 | F24: 1.3.1.1 | G24: =VLOOKUP(F24,'M.Cálc.Quant.'!G:T,2,FALSE) -> PREPARO DE FUNDO DE VALA COM LARGURA MENOR QUE 1,5 M (ACERTO DO SOLO NATURAL). AF_08/2020 | H24: =VLOOKUP(F24,'M.Cálc.Quant.'!G:T,14,FALSE) -> M2 | I24: =VLOOKUP(F24,'M.Cálc.Quant.'!G:T,13,FALSE) -> 64.24 | J24: =(1+$K$7)*IF(D24="GIDUR JP",VLOOKUP(E24,GIDUR!A:D,4,FALSE),IF(D24="DER PB",VLOOKUP(E24,DER!A:D,4,FALSE)/(1+DER!$E$2),IF(D24="COMPOSIÇÃO",VLOOKUP(E24,Composição!B:J,8,FALSE),IF(A24="COMPOSIÇÃO",VLOOKUP(E24,'Sinapi_Comp-06.2023'!G:K,5,FALSE),VLOOKUP(E24,'Sinapi_Insum-06.2023'!A:E,5,FALSE))))) -> 6.74 | K24: =IFERROR(ROUND(I24*J24,2),0) -> 432.98 | M24: =ROUND(I24*J24,2) -> 432.98
A25: =VLOOKUP(F25,'M.Cálc.Quant.'!B:T,4,FALSE) -> COMPOSIÇÃO | C25: 3.4 | D25: =VLOOKUP(F25,'M.Cálc.Quant.'!B:T,2,FALSE) -> COMPOSIÇÃO | E25: =VLOOKUP(F25,'M.Cálc.Quant.'!B:T,3,FALSE) -> 10 | F25: 1.3.1.2 | G25: =VLOOKUP(F25,'M.Cálc.Quant.'!G:T,2,FALSE) -> ALVENARIA EM TIJOLO CERAMICO FURADO 9X19X19CM, 1 VEZ (ESPESSURA 19 CM), ASSENTADO EM ARGAMASSA TRACO 1:4 (CIMENTO E AREIA MEDIA NAO PENEIRADA), PREPARO MANUAL, JUNTA1 CM [ADAPTADO SINAPI 73935/002] | H25: =VLOOKUP(F25,'M.Cálc.Quant.'!G:T,14,FALSE) -> M2 | I25: =VLOOKUP(F25,'M.Cálc.Quant.'!G:T,13,FALSE) -> 50.04 | J25: =(1+$K$7)*IF(D25="GIDUR JP",VLOOKUP(E25,GIDUR!A:D,4,FALSE),IF(D25="DER PB",VLOOKUP(E25,DER!A:D,4,FALSE)/(1+DER!$E$2),IF(D25="COMPOSIÇÃO",VLOOKUP(E25,Composição!B:J,8,FALSE),IF(A25="COMPOSIÇÃO",VLOOKUP(E25,'Sinapi_Comp-06.2023'!G:K,5,FALSE),VLOOKUP(E25,'Sinapi_Insum-06.2023'!A:E,5,FALSE))))) -> 122.67 | K25: =IFERROR(ROUND(I25*J25,2),0) -> 6138.41 | M25: =ROUND(I25*J25,2) -> 6138.41 | S25: 6 | T25: ALVENARIA EM TIJOLO CERAMICO FURADO 9X19X19CM, 1 VEZ (ESPESSURA 19 CM) , ASSENTADO ARGAMASSA TRACO 1:4 (CIMENTO E AREIA MEDIA NAO PENEIRADA), PREPARO MANUAL, JUNTA1 CM [ADAPTADO DE SINAPI 73935/002] | X25: M2 | Z25: =SUM(AA26:AA29) -> 79.61 | AB25: =Z25*253.76 -> 20201.834
A26: =VLOOKUP(F26,'M.Cálc.Quant.'!B:T,4,FALSE) -> COMPOSIÇÃO | C26: 3.5 | D26: =VLOOKUP(F26,'M.Cálc.Quant.'!B:T,2,FALSE) -> SINAPI | E26: =VLOOKUP(F26,'M.Cálc.Quant.'!B:T,3,FALSE) -> 96620 | F26: 1.3.1.3 | G26: =VLOOKUP(F26,'M.Cálc.Quant.'!G:T,2,FALSE) -> LASTRO DE CONCRETO MAGRO, APLICADO EM PISOS, LAJES SOBRE SOLO OU RADIERS. AF_01/2024 | H26: =VLOOKUP(F26,'M.Cálc.Quant.'!G:T,14,FALSE) -> M3 | I26: =VLOOKUP(F26,'M.Cálc.Quant.'!G:T,13,FALSE) -> 3.22 | J26: =(1+$K$7)*IF(D26="GIDUR JP",VLOOKUP(E26,GIDUR!A:D,4,FALSE),IF(D26="DER PB",VLOOKUP(E26,DER!A:D,4,FALSE)/(1+DER!$E$2),IF(D26="COMPOSIÇÃO",VLOOKUP(E26,Composição!B:J,8,FALSE),IF(A26="COMPOSIÇÃO",VLOOKUP(E26,'Sinapi_Comp-06.2023'!G:K,5,FALSE),VLOOKUP(E26,'Sinapi_Insum-06.2023'!A:E,5,FALSE))))) -> 860.29 | K26: =IFERROR(ROUND(I26*J26,2),0) -> 2770.13 | M26: =ROUND(I26*J26,2) -> 2770.13 | S26: =CONCATENATE(S25,".1") -> 6.1 | T26: SINAPI PB | U26: COMPOSIÇÃO | V26: 87373 | W26: #N/A | X26: #N/A | Y26: 0.0138 | Z26: =445.97*1.3024 -> 580.83133 | AA26: =ROUND(Z26*Y26,2) -> 8.02
A27: =VLOOKUP(F27,'M.Cálc.Quant.'!B:T,4,FALSE) -> COMPOSIÇÃO | C27: 3.6 | D27: =VLOOKUP(F27,'M.Cálc.Quant.'!B:T,2,FALSE) -> SINAPI | E27: =VLOOKUP(F27,'M.Cálc.Quant.'!B:T,3,FALSE) -> 96535 | F27: 1.3.1.4 | G27: =VLOOKUP(F27,'M.Cálc.Quant.'!G:T,2,FALSE) -> FABRICAÇÃO, MONTAGEM E DESMONTAGEM DE FÔRMA PARA SAPATA, EM MADEIRA SERRADA, E=25 MM, 4 UTILIZAÇÕES. AF_01/2024 | H27: =VLOOKUP(F27,'M.Cálc.Quant.'!G:T,14,FALSE) -> M2 | I27: =VLOOKUP(F27,'M.Cálc.Quant.'!G:T,13,FALSE) -> 57.41 | J27: =(1+$K$7)*IF(D27="GIDUR JP",VLOOKUP(E27,GIDUR!A:D,4,FALSE),IF(D27="DER PB",VLOOKUP(E27,DER!A:D,4,FALSE)/(1+DER!$E$2),IF(D27="COMPOSIÇÃO",VLOOKUP(E27,Composição!B:J,8,FALSE),IF(A27="COMPOSIÇÃO",VLOOKUP(E27,'Sinapi_Comp-06.2023'!G:K,5,FALSE),VLOOKUP(E27,'Sinapi_Insum-06.2023'!A:E,5,FALSE))))) -> 155.67 | K27: =IFERROR(ROUND(I27*J27,2),0) -> 8937.01 | M27: =ROUND(I27*J27,2) -> 8937.01 | S27: =CONCATENATE(S25,".2") -> 6.2 | T27: SINAPI PB | U27: COMPOSIÇÃO | V27: 88309 | W27: #N/A | X27: #N/A | Y27: 1.14 | Z27: =16.35*1.3024 -> 21.29424 | AA27: =ROUND(Z27*Y27,2) -> 24.28
A28: =VLOOKUP(F28,'M.Cálc.Quant.'!B:T,4,FALSE) -> COMPOSIÇÃO | C28: 3.7 | D28: =VLOOKUP(F28,'M.Cálc.Quant.'!B:T,2,FALSE) -> SINAPI | E28: =VLOOKUP(F28,'M.Cálc.Quant.'!B:T,3,FALSE) -> 96536 | F28: 1.3.1.5 | G28: =VLOOKUP(F28,'M.Cálc.Quant.'!G:T,2,FALSE) -> FABRICAÇÃO, MONTAGEM E DESMONTAGEM DE FÔRMA PARA VIGA BALDRAME, EM MADEIRA SERRADA, E=25 MM, 4 UTILIZAÇÕES. AF_01/2024 | H28: =VLOOKUP(F28,'M.Cálc.Quant.'!G:T,14,FALSE) -> M2 | I28: =VLOOKUP(F28,'M.Cálc.Quant.'!G:T,13,FALSE) -> 111.16 | J28: =(1+$K$7)*IF(D28="GIDUR JP",VLOOKUP(E28,GIDUR!A:D,4,FALSE),IF(D28="DER PB",VLOOKUP(E28,DER!A:D,4,FALSE)/(1+DER!$E$2),IF(D28="COMPOSIÇÃO",VLOOKUP(E28,Composição!B:J,8,FALSE),IF(A28="COMPOSIÇÃO",VLOOKUP(E28,'Sinapi_Comp-06.2023'!G:K,5,FALSE),VLOOKUP(E28,'Sinapi_Insum-06.2023'!A:E,5,FALSE))))) -> 86.87 | K28: =IFERROR(ROUND(I28*J28,2),0) -> 9656.47 | M28: =ROUND(I28*J28,2) -> 9656.47 | S28: =CONCATENATE(S25,".3") -> 6.3 | T28: SINAPI PB | U28: COMPOSIÇÃO | V28: 88316 | W28: #N/A | X28: #N/A | Y28: 0.88 | Z28: =12.92*1.3024 -> 17 | AA28: =ROUND(Z28*Y28,2) -> 14.96
A29: =VLOOKUP(F29,'M.Cálc.Quant.'!B:T,4,FALSE) -> COMPOSIÇÃO | C29: 3.7 | D29: =VLOOKUP(F29,'M.Cálc.Quant.'!B:T,2,FALSE) -> SINAPI | E29: =VLOOKUP(F29,'M.Cálc.Quant.'!B:T,3,FALSE) -> 96544 | F29: 1.3.1.6 | G29: =VLOOKUP(F29,'M.Cálc.Quant.'!G:T,2,FALSE) -> ARMAÇÃO DE BLOCO UTILIZANDO AÇO CA-50 DE 6,3 MM - MONTAGEM. AF_01/2024 | H29: =VLOOKUP(F29,'M.Cálc.Quant.'!G:T,14,FALSE) -> KG | I29: =VLOOKUP(F29,'M.Cálc.Quant.'!G:T,13,FALSE) -> 97.5 | J29: =(1+$K$7)*IF(D29="GIDUR JP",VLOOKUP(E29,GIDUR!A:D,4,FALSE),IF(D29="DER PB",VLOOKUP(E29,DER!A:D,4,FALSE)/(1+DER!$E$2),IF(D29="COMPOSIÇÃO",VLOOKUP(E29,Composição!B:J,8,FALSE),IF(A29="COMPOSIÇÃO",VLOOKUP(E29,'Sinapi_Comp-06.2023'!G:K,5,FALSE),VLOOKUP(E29,'Sinapi_Insum-06.2023'!A:E,5,FALSE))))) -> 20.09 | K29: =IFERROR(ROUND(I29*J29,2),0) -> 1958.78 | M29: =ROUND(I29*J29,2) -> 1958.78 | S29: =CONCATENATE(S25,".4") -> 6.4 | T29: SINAPI PB | U29: INSUMO | V29: 7271 | W29: #N/A | X29: #N/A | Y29: 54 | Z29: =0.46*1.3024 -> 0.599104 | AA29: =ROUND(Z29*Y29,2) -> 32.35
A30: =VLOOKUP(F30,'M.Cálc.Quant.'!B:T,4,FALSE) -> COMPOSIÇÃO | C30: 3.7 | D30: =VLOOKUP(F30,'M.Cálc.Quant.'!B:T,2,FALSE) -> SINAPI | E30: =VLOOKUP(F30,'M.Cálc.Quant.'!B:T,3,FALSE) -> 96545 | F30: 1.3.1.7 | G30: =VLOOKUP(F30,'M.Cálc.Quant.'!G:T,2,FALSE) -> ARMAÇÃO DE BLOCO UTILIZANDO AÇO CA-50 DE 8 MM - MONTAGEM. AF_01/2024 | H30: =VLOOKUP(F30,'M.Cálc.Quant.'!G:T,14,FALSE) -> KG | I30: =VLOOKUP(F30,'M.Cálc.Quant.'!G:T,13,FALSE) -> 394.6 | J30: =(1+$K$7)*IF(D30="GIDUR JP",VLOOKUP(E30,GIDUR!A:D,4,FALSE),IF(D30="DER PB",VLOOKUP(E30,DER!A:D,4,FALSE)/(1+DER!$E$2),IF(D30="COMPOSIÇÃO",VLOOKUP(E30,Composição!B:J,8,FALSE),IF(A30="COMPOSIÇÃO",VLOOKUP(E30,'Sinapi_Comp-06.2023'!G:K,5,FALSE),VLOOKUP(E30,'Sinapi_Insum-06.2023'!A:E,5,FALSE))))) -> 18.27 | K30: =IFERROR(ROUND(I30*J30,2),0) -> 7209.34 | M30: =ROUND(I30*J30,2) -> 7209.34
A31: =VLOOKUP(F31,'M.Cálc.Quant.'!B:T,4,FALSE) -> COMPOSIÇÃO | C31: 4.1 | D31: =VLOOKUP(F31,'M.Cálc.Quant.'!B:T,2,FALSE) -> SINAPI | E31: =VLOOKUP(F31,'M.Cálc.Quant.'!B:T,3,FALSE) -> 96546 | F31: 1.3.1.8 | G31: =VLOOKUP(F31,'M.Cálc.Quant.'!G:T,2,FALSE) -> ARMAÇÃO DE BLOCO UTILIZANDO AÇO CA-50 DE 10 MM - MONTAGEM. AF_01/2024 | H31: =VLOOKUP(F31,'M.Cálc.Quant.'!G:T,14,FALSE) -> KG | I31: =VLOOKUP(F31,'M.Cálc.Quant.'!G:T,13,FALSE) -> 335.6 | J31: =(1+$K$7)*IF(D31="GIDUR JP",VLOOKUP(E31,GIDUR!A:D,4,FALSE),IF(D31="DER PB",VLOOKUP(E31,DER!A:D,4,FALSE)/(1+DER!$E$2),IF(D31="COMPOSIÇÃO",VLOOKUP(E31,Composição!B:J,8,FALSE),IF(A31="COMPOSIÇÃO",VLOOKUP(E31,'Sinapi_Comp-06.2023'!G:K,5,FALSE),VLOOKUP(E31,'Sinapi_Insum-06.2023'!A:E,5,FALSE))))) -> 16.05 | K31: =IFERROR(ROUND(I31*J31,2),0) -> 5386.38 | M31: =ROUND(I31*J31,2) -> 5386.38
A32: =VLOOKUP(F32,'M.Cálc.Quant.'!B:T,4,FALSE) -> COMPOSIÇÃO | C32: 3.13 | D32: =VLOOKUP(F32,'M.Cálc.Quant.'!B:T,2,FALSE) -> SINAPI | E32: =VLOOKUP(F32,'M.Cálc.Quant.'!B:T,3,FALSE) -> 104920 | F32: 1.3.1.9 | G32: =VLOOKUP(F32,'M.Cálc.Quant.'!G:T,2,FALSE) -> ARMAÇÃO DE BLOCO, SAPATA ISOLADA, VIGA BALDRAME E SAPATA CORRIDA UTILIZANDO AÇO CA-50 DE 12,5 MM - MONTAGEM. AF_01/2024 | H32: =VLOOKUP(F32,'M.Cálc.Quant.'!G:T,14,FALSE) -> KG | I32: =VLOOKUP(F32,'M.Cálc.Quant.'!G:T,13,FALSE) -> 169.9 | J32: =(1+$K$7)*IF(D32="GIDUR JP",VLOOKUP(E32,GIDUR!A:D,4,FALSE),IF(D32="DER PB",VLOOKUP(E32,DER!A:D,4,FALSE)/(1+DER!$E$2),IF(D32="COMPOSIÇÃO",VLOOKUP(E32,Composição!B:J,8,FALSE),IF(A32="COMPOSIÇÃO",VLOOKUP(E32,'Sinapi_Comp-06.2023'!G:K,5,FALSE),VLOOKUP(E32,'Sinapi_Insum-06.2023'!A:E,5,FALSE))))) -> 12.5 | K32: =IFERROR(ROUND(I32*J32,2),0) -> 2123.75 | M32: =ROUND(I32*J32,2) -> 2123.75 | N32: =K32/K31 -> 0.39
A33: =VLOOKUP(F33,'M.Cálc.Quant.'!B:T,4,FALSE) -> COMPOSIÇÃO | C33: 3.14 | D33: =VLOOKUP(F33,'M.Cálc.Quant.'!B:T,2,FALSE) -> SINAPI | E33: =VLOOKUP(F33,'M.Cálc.Quant.'!B:T,3,FALSE) -> 96543 | F33: 1.3.1.10 | G33: =VLOOKUP(F33,'M.Cálc.Quant.'!G:T,2,FALSE) -> ARMAÇÃO DE BLOCO UTILIZANDO AÇO CA-60 DE 5 MM - MONTAGEM. AF_01/2024 | H33: =VLOOKUP(F33,'M.Cálc.Quant.'!G:T,14,FALSE) -> KG | I33: =VLOOKUP(F33,'M.Cálc.Quant.'!G:T,13,FALSE) -> 182.3 | J33: =(1+$K$7)*IF(D33="GIDUR JP",VLOOKUP(E33,GIDUR!A:D,4,FALSE),IF(D33="DER PB",VLOOKUP(E33,DER!A:D,4,FALSE)/(1+DER!$E$2),IF(D33="COMPOSIÇÃO",VLOOKUP(E33,Composição!B:J,8,FALSE),IF(A33="COMPOSIÇÃO",VLOOKUP(E33,'Sinapi_Comp-06.2023'!G:K,5,FALSE),VLOOKUP(E33,'Sinapi_Insum-06.2023'!A:E,5,FALSE))))) -> 22.11 | K33: =IFERROR(ROUND(I33*J33,2),0) -> 4030.65 | M33: =ROUND(I33*J33,2) -> 4030.65 | N33: =SUM(K33:K36)/K31 -> 3.62
A34: =VLOOKUP(F34,'M.Cálc.Quant.'!B:T,4,FALSE) -> COMPOSIÇÃO | C34: 3.15 | D34: =VLOOKUP(F34,'M.Cálc.Quant.'!B:T,2,FALSE) -> SINAPI | E34: =VLOOKUP(F34,'M.Cálc.Quant.'!B:T,3,FALSE) -> 94965 | F34: 1.3.1.11 | G34: =VLOOKUP(F34,'M.Cálc.Quant.'!G:T,2,FALSE) -> CONCRETO FCK = 25MPA, TRAÇO 1:2,3:2,7 (EM MASSA SECA DE CIMENTO/ AREIA MÉDIA/ BRITA 1) - PREPARO MECÂNICO COM BETONEIRA 400 L. AF_05/2021 | H34: =VLOOKUP(F34,'M.Cálc.Quant.'!G:T,14,FALSE) -> M3 | I34: =VLOOKUP(F34,'M.Cálc.Quant.'!G:T,13,FALSE) -> 11.04 | J34: =(1+$K$7)*IF(D34="GIDUR JP",VLOOKUP(E34,GIDUR!A:D,4,FALSE),IF(D34="DER PB",VLOOKUP(E34,DER!A:D,4,FALSE)/(1+DER!$E$2),IF(D34="COMPOSIÇÃO",VLOOKUP(E34,Composição!B:J,8,FALSE),IF(A34="COMPOSIÇÃO",VLOOKUP(E34,'Sinapi_Comp-06.2023'!G:K,5,FALSE),VLOOKUP(E34,'Sinapi_Insum-06.2023'!A:E,5,FALSE))))) -> 602.47 | K34: =IFERROR(ROUND(I34*J34,2),0) -> 6651.27 | M34: =ROUND(I34*J34,2) -> 6651.27
A35: =VLOOKUP(F35,'M.Cálc.Quant.'!B:T,4,FALSE) -> COMPOSIÇÃO | C35: 3.16 | D35: =VLOOKUP(F35,'M.Cálc.Quant.'!B:T,2,FALSE) -> SINAPI | E35: =VLOOKUP(F35,'M.Cálc.Quant.'!B:T,3,FALSE) -> 103670 | F35: 1.3.1.12 | G35: =VLOOKUP(F35,'M.Cálc.Quant.'!G:T,2,FALSE) -> LANÇAMENTO COM USO DE BALDES, ADENSAMENTO E ACABAMENTO DE CONCRETO EM ESTRUTURAS. AF_02/2022 | H35: =VLOOKUP(F35,'M.Cálc.Quant.'!G:T,14,FALSE) -> M3 | I35: =VLOOKUP(F35,'M.Cálc.Quant.'!G:T,13,FALSE) -> 21.64 | J35: =(1+$K$7)*IF(D35="GIDUR JP",VLOOKUP(E35,GIDUR!A:D,4,FALSE),IF(D35="DER PB",VLOOKUP(E35,DER!A:D,4,FALSE)/(1+DER!$E$2),IF(D35="COMPOSIÇÃO",VLOOKUP(E35,Composição!B:J,8,FALSE),IF(A35="COMPOSIÇÃO",VLOOKUP(E35,'Sinapi_Comp-06.2023'!G:K,5,FALSE),VLOOKUP(E35,'Sinapi_Insum-06.2023'!A:E,5,FALSE))))) -> 315.49 | K35: =IFERROR(ROUND(I35*J35,2),0) -> 6827.2 | M35: =ROUND(I35*J35,2) -> 6827.2
A36: =VLOOKUP(F36,'M.Cálc.Quant.'!B:T,4,FALSE) -> COMPOSIÇÃO | C36: 3.16 | D36: =VLOOKUP(F36,'M.Cálc.Quant.'!B:T,2,FALSE) -> COMPOSIÇÃO | E36: =VLOOKUP(F36,'M.Cálc.Quant.'!B:T,3,FALSE) -> 11 | F36: ='M.Cálc.Quant.'!G86 -> 1.3.1.13 | G36: =VLOOKUP(F36,'M.Cálc.Quant.'!G:T,2,FALSE) -> IMPERMEABILIZACAO DE ESTRUTURAS ENTERRADAS, COM TINTA ASFALTICA, DUAS DEMAOS. [ADAPTADO SINAPI 74106/001] | H36: =VLOOKUP(F36,'M.Cálc.Quant.'!G:T,14,FALSE) -> M2 | I36: =VLOOKUP(F36,'M.Cálc.Quant.'!G:T,13,FALSE) -> 112.92 | J36: =(1+$K$7)*IF(D36="GIDUR JP",VLOOKUP(E36,GIDUR!A:D,4,FALSE),IF(D36="DER PB",VLOOKUP(E36,DER!A:D,4,FALSE)/(1+DER!$E$2),IF(D36="COMPOSIÇÃO",VLOOKUP(E36,Composição!B:J,8,FALSE),IF(A36="COMPOSIÇÃO",VLOOKUP(E36,'Sinapi_Comp-06.2023'!G:K,5,FALSE),VLOOKUP(E36,'Sinapi_Insum-06.2023'!A:E,5,FALSE))))) -> 17.62 | K36: =IFERROR(ROUND(I36*J36,2),0) -> 1989.65 | M36: =ROUND(I36*J36,2) -> 1989.65
A37: =VLOOKUP(F37,'M.Cálc.Quant.'!B:T,4,FALSE) -> COMPOSIÇÃO | C37: 3.16 | D37: =VLOOKUP(F37,'M.Cálc.Quant.'!B:T,2,FALSE) -> SINAPI | E37: =VLOOKUP(F37,'M.Cálc.Quant.'!B:T,3,FALSE) -> 94966 | F37: ='M.Cálc.Quant.'!G88 -> 1.3.1.14 | G37: =VLOOKUP(F37,'M.Cálc.Quant.'!G:T,2,FALSE) -> CONCRETO FCK = 30MPA, TRAÇO 1:2,1:2,5 (EM MASSA SECA DE CIMENTO/ AREIA MÉDIA/ BRITA 1) - PREPARO MECÂNICO COM BETONEIRA 400 L. AF_05/2021 | H37: =VLOOKUP(F37,'M.Cálc.Quant.'!G:T,14,FALSE) -> M3 | I37: =VLOOKUP(F37,'M.Cálc.Quant.'!G:T,13,FALSE) -> 10.6 | J37: =(1+$K$7)*IF(D37="GIDUR JP",VLOOKUP(E37,GIDUR!A:D,4,FALSE),IF(D37="DER PB",VLOOKUP(E37,DER!A:D,4,FALSE)/(1+DER!$E$2),IF(D37="COMPOSIÇÃO",VLOOKUP(E37,Composição!B:J,8,FALSE),IF(A37="COMPOSIÇÃO",VLOOKUP(E37,'Sinapi_Comp-06.2023'!G:K,5,FALSE),VLOOKUP(E37,'Sinapi_Insum-06.2023'!A:E,5,FALSE))))) -> 621.63 | K37: =IFERROR(ROUND(I37*J37,2),0) -> 6589.28
C38: 3.20 | F38: 1.4 | G38: =VLOOKUP(F38,'M.Cálc.Quant.'!G:T,2,FALSE) -> SUPERESTRUTURA (PILARES, VIGAS E LAJES) - TODA A QUADRA | K38: =K39+K47+K55 -> 55355.09 | M38: =ROUND(I38*J38,2) -> 0
C39: 3.21 | F39: 1.4.1 | G39: =VLOOKUP(F39,'M.Cálc.Quant.'!G:T,2,FALSE) -> CONCRETO ARMADO PARA PILARES DA EDIFICAÇÃO | K39: =SUM(K40:K46) -> 22313.5 | M39: =ROUND(I39*J39,2) -> 0
A40: =VLOOKUP(F40,'M.Cálc.Quant.'!B:T,4,FALSE) -> COMPOSIÇÃO | C40: 3.22 | D40: =VLOOKUP(F40,'M.Cálc.Quant.'!B:T,2,FALSE) -> SINAPI | E40: =VLOOKUP(F40,'M.Cálc.Quant.'!B:T,3,FALSE) -> 92443 | F40: 1.4.1.1 | G40: =VLOOKUP(F40,'M.Cálc.Quant.'!G:T,2,FALSE) -> MONTAGEM E DESMONTAGEM DE FÔRMA DE PILARES RETANGULARES E ESTRUTURAS SIMILARES, PÉ-DIREITO SIMPLES, EM CHAPA DE MADEIRA COMPENSADA PLASTIFICADA, 18 UTILIZAÇÕES. AF_09/2020 | H40: =VLOOKUP(F40,'M.Cálc.Quant.'!G:T,14,FALSE) -> M2 | I40: =VLOOKUP(F40,'M.Cálc.Quant.'!G:T,13,FALSE) -> 90.78 | J40: =(1+$K$7)*IF(D40="GIDUR JP",VLOOKUP(E40,GIDUR!A:D,4,FALSE),IF(D40="DER PB",VLOOKUP(E40,DER!A:D,4,FALSE)/(1+DER!$E$2),IF(D40="COMPOSIÇÃO",VLOOKUP(E40,Composição!B:J,8,FALSE),IF(A40="COMPOSIÇÃO",VLOOKUP(E40,'Sinapi_Comp-06.2023'!G:K,5,FALSE),VLOOKUP(E40,'Sinapi_Insum-06.2023'!A:E,5,FALSE))))) -> 51.83 | K40: =IFERROR(ROUND(I40*J40,2),0) -> 4705.13 | M40: =ROUND(I40*J40,2) -> 4705.13
A41: =VLOOKUP(F41,'M.Cálc.Quant.'!B:T,4,FALSE) -> COMPOSIÇÃO | C41: 10 | D41: =VLOOKUP(F41,'M.Cálc.Quant.'!B:T,2,FALSE) -> SINAPI | E41: =VLOOKUP(F41,'M.Cálc.Quant.'!B:T,3,FALSE) -> 92759 | F41: 1.4.1.2 | G41: =VLOOKUP(F41,'M.Cálc.Quant.'!G:T,2,FALSE) -> ARMAÇÃO DE PILAR OU VIGA DE ESTRUTURA CONVENCIONAL DE CONCRETO ARMADO UTILIZANDO AÇO CA-60 DE 5,0 MM - MONTAGEM. AF_06/2022 | H41: =VLOOKUP(F41,'M.Cálc.Quant.'!G:T,14,FALSE) -> KG | I41: =VLOOKUP(F41,'M.Cálc.Quant.'!G:T,13,FALSE) -> 164.5 | J41: =(1+$K$7)*IF(D41="GIDUR JP",VLOOKUP(E41,GIDUR!A:D,4,FALSE),IF(D41="DER PB",VLOOKUP(E41,DER!A:D,4,FALSE)/(1+DER!$E$2),IF(D41="COMPOSIÇÃO",VLOOKUP(E41,Composição!B:J,8,FALSE),IF(A41="COMPOSIÇÃO",VLOOKUP(E41,'Sinapi_Comp-06.2023'!G:K,5,FALSE),VLOOKUP(E41,'Sinapi_Insum-06.2023'!A:E,5,FALSE))))) -> 16.02 | K41: =IFERROR(ROUND(I41*J41,2),0) -> 2635.29 | M41: =ROUND(I41*J41,2) -> 2635.29
A42: =VLOOKUP(F42,'M.Cálc.Quant.'!B:T,4,FALSE) -> COMPOSIÇÃO | C42: 3.5 | D42: =VLOOKUP(F42,'M.Cálc.Quant.'!B:T,2,FALSE) -> SINAPI | E42: =VLOOKUP(F42,'M.Cálc.Quant.'!B:T,3,FALSE) -> 92762 | F42: 1.4.1.3 | G42: =VLOOKUP(F42,'M.Cálc.Quant.'!G:T,2,FALSE) -> ARMAÇÃO DE PILAR OU VIGA DE ESTRUTURA CONVENCIONAL DE CONCRETO ARMADO UTILIZANDO AÇO CA-50 DE 10,0 MM - MONTAGEM. AF_06/2022 | H42: =VLOOKUP(F42,'M.Cálc.Quant.'!G:T,14,FALSE) -> KG | I42: =VLOOKUP(F42,'M.Cálc.Quant.'!G:T,13,FALSE) -> 356.5 | J42: =(1+$K$7)*IF(D42="GIDUR JP",VLOOKUP(E42,GIDUR!A:D,4,FALSE),IF(D42="DER PB",VLOOKUP(E42,DER!A:D,4,FALSE)/(1+DER!$E$2),IF(D42="COMPOSIÇÃO",VLOOKUP(E42,Composição!B:J,8,FALSE),IF(A42="COMPOSIÇÃO",VLOOKUP(E42,'Sinapi_Comp-06.2023'!G:K,5,FALSE),VLOOKUP(E42,'Sinapi_Insum-06.2023'!A:E,5,FALSE))))) -> 12.94 | K42: =IFERROR(ROUND(I42*J42,2),0) -> 4613.11 | M42: =ROUND(I42*J42,2) -> 4613.11
A43: =VLOOKUP(F43,'M.Cálc.Quant.'!B:T,4,FALSE) -> COMPOSIÇÃO | C43: 3.7 | D43: =VLOOKUP(F43,'M.Cálc.Quant.'!B:T,2,FALSE) -> SINAPI | E43: =VLOOKUP(F43,'M.Cálc.Quant.'!B:T,3,FALSE) -> 92763 | F43: 1.4.1.4 | G43: =VLOOKUP(F43,'M.Cálc.Quant.'!G:T,2,FALSE) -> ARMAÇÃO DE PILAR OU VIGA DE ESTRUTURA CONVENCIONAL DE CONCRETO ARMADO UTILIZANDO AÇO CA-50 DE 12,5 MM - MONTAGEM. AF_06/2022 | H43: =VLOOKUP(F43,'M.Cálc.Quant.'!G:T,14,FALSE) -> KG | I43: =VLOOKUP(F43,'M.Cálc.Quant.'!G:T,13,FALSE) -> 54.1 | J43: =(1+$K$7)*IF(D43="GIDUR JP",VLOOKUP(E43,GIDUR!A:D,4,FALSE),IF(D43="DER PB",VLOOKUP(E43,DER!A:D,4,FALSE)/(1+DER!$E$2),IF(D43="COMPOSIÇÃO",VLOOKUP(E43,Composição!B:J,8,FALSE),IF(A43="COMPOSIÇÃO",VLOOKUP(E43,'Sinapi_Comp-06.2023'!G:K,5,FALSE),VLOOKUP(E43,'Sinapi_Insum-06.2023'!A:E,5,FALSE))))) -> 10.92 | K43: =IFERROR(ROUND(I43*J43,2),0) -> 590.77 | M43: =ROUND(I43*J43,2) -> 590.77
A44: =VLOOKUP(F44,'M.Cálc.Quant.'!B:T,4,FALSE) -> COMPOSIÇÃO | C44: 10 | D44: =VLOOKUP(F44,'M.Cálc.Quant.'!B:T,2,FALSE) -> SINAPI | E44: =VLOOKUP(F44,'M.Cálc.Quant.'!B:T,3,FALSE) -> 92764 | F44: 1.4.1.5 | G44: =VLOOKUP(F44,'M.Cálc.Quant.'!G:T,2,FALSE) -> ARMAÇÃO DE PILAR OU VIGA DE ESTRUTURA CONVENCIONAL DE CONCRETO ARMADO UTILIZANDO AÇO CA-50 DE 16,0 MM - MONTAGEM. AF_06/2022 | H44: =VLOOKUP(F44,'M.Cálc.Quant.'!G:T,14,FALSE) -> KG | I44: =VLOOKUP(F44,'M.Cálc.Quant.'!G:T,13,FALSE) -> 418.4 | J44: =(1+$K$7)*IF(D44="GIDUR JP",VLOOKUP(E44,GIDUR!A:D,4,FALSE),IF(D44="DER PB",VLOOKUP(E44,DER!A:D,4,FALSE)/(1+DER!$E$2),IF(D44="COMPOSIÇÃO",VLOOKUP(E44,Composição!B:J,8,FALSE),IF(A44="COMPOSIÇÃO",VLOOKUP(E44,'Sinapi_Comp-06.2023'!G:K,5,FALSE),VLOOKUP(E44,'Sinapi_Insum-06.2023'!A:E,5,FALSE))))) -> 10.58 | K44: =IFERROR(ROUND(I44*J44,2),0) -> 4426.67 | M44: =ROUND(I44*J44,2) -> 4426.67
A45: =VLOOKUP(F45,'M.Cálc.Quant.'!B:T,4,FALSE) -> COMPOSIÇÃO | C45: 10 | D45: =VLOOKUP(F45,'M.Cálc.Quant.'!B:T,2,FALSE) -> SINAPI | E45: =VLOOKUP(F45,'M.Cálc.Quant.'!B:T,3,FALSE) -> 94965 | F45: ='M.Cálc.Quant.'!G113 -> 1.4.1.6 | G45: =VLOOKUP(F45,'M.Cálc.Quant.'!G:T,2,FALSE) -> CONCRETO FCK = 25MPA, TRAÇO 1:2,3:2,7 (EM MASSA SECA DE CIMENTO/ AREIA MÉDIA/ BRITA 1) - PREPARO MECÂNICO COM BETONEIRA 400 L. AF_05/2021 | H45: =VLOOKUP(F45,'M.Cálc.Quant.'!G:T,14,FALSE) -> M3 | I45: =VLOOKUP(F45,'M.Cálc.Quant.'!G:T,13,FALSE) -> 5.82 | J45: =(1+$K$7)*IF(D45="GIDUR JP",VLOOKUP(E45,GIDUR!A:D,4,FALSE),IF(D45="DER PB",VLOOKUP(E45,DER!A:D,4,FALSE)/(1+DER!$E$2),IF(D45="COMPOSIÇÃO",VLOOKUP(E45,Composição!B:J,8,FALSE),IF(A45="COMPOSIÇÃO",VLOOKUP(E45,'Sinapi_Comp-06.2023'!G:K,5,FALSE),VLOOKUP(E45,'Sinapi_Insum-06.2023'!A:E,5,FALSE))))) -> 602.47 | K45: =IFERROR(ROUND(I45*J45,2),0) -> 3506.38
A46: =VLOOKUP(F46,'M.Cálc.Quant.'!B:T,4,FALSE) -> COMPOSIÇÃO | C46: 10 | D46: =VLOOKUP(F46,'M.Cálc.Quant.'!B:T,2,FALSE) -> SINAPI | E46: =VLOOKUP(F46,'M.Cálc.Quant.'!B:T,3,FALSE) -> 103670 | F46: ='M.Cálc.Quant.'!G118 -> 1.4.1.7 | G46: =VLOOKUP(F46,'M.Cálc.Quant.'!G:T,2,FALSE) -> LANÇAMENTO COM USO DE BALDES, ADENSAMENTO E ACABAMENTO DE CONCRETO EM ESTRUTURAS. AF_02/2022 | H46: =VLOOKUP(F46,'M.Cálc.Quant.'!G:T,14,FALSE) -> M3 | I46: =VLOOKUP(F46,'M.Cálc.Quant.'!G:T,13,FALSE) -> 5.82 | J46: =(1+$K$7)*IF(D46="GIDUR JP",VLOOKUP(E46,GIDUR!A:D,4,FALSE),IF(D46="DER PB",VLOOKUP(E46,DER!A:D,4,FALSE)/(1+DER!$E$2),IF(D46="COMPOSIÇÃO",VLOOKUP(E46,Composição!B:J,8,FALSE),IF(A46="COMPOSIÇÃO",VLOOKUP(E46,'Sinapi_Comp-06.2023'!G:K,5,FALSE),VLOOKUP(E46,'Sinapi_Insum-06.2023'!A:E,5,FALSE))))) -> 315.49 | K46: =IFERROR(ROUND(I46*J46,2),0) -> 1836.15
A47: =VLOOKUP(F47,'M.Cálc.Quant.'!B:E,4,FALSE) -> #N/A | C47: 4 | F47: 1.4.2 | G47: =VLOOKUP(F47,'M.Cálc.Quant.'!G:T,2,FALSE) -> CONCRETO ARMADO PARA VIGAS DA EDIFICAÇÃO | K47: =SUM(K48:K54) -> 26789.65 | M47: =ROUND(I47*J47,2) -> 0
A48: =VLOOKUP(F48,'M.Cálc.Quant.'!B:T,4,FALSE) -> COMPOSIÇÃO | C48: 4.1 | D48: =VLOOKUP(F48,'M.Cálc.Quant.'!B:T,2,FALSE) -> SINAPI | E48: =VLOOKUP(F48,'M.Cálc.Quant.'!B:T,3,FALSE) -> 92480 | F48: 1.4.2.1 | G48: =VLOOKUP(F48,'M.Cálc.Quant.'!G:T,2,FALSE) -> MONTAGEM E DESMONTAGEM DE FÔRMA DE VIGA, ESCORAMENTO METÁLICO, PÉ-DIREITO SIMPLES, EM CHAPA DE MADEIRA PLASTIFICADA, 18 UTILIZAÇÕES. AF_09/2020 | H48: =VLOOKUP(F48,'M.Cálc.Quant.'!G:T,14,FALSE) -> M2 | I48: =VLOOKUP(F48,'M.Cálc.Quant.'!G:T,13,FALSE) -> 115.05 | J48: =(1+$K$7)*IF(D48="GIDUR JP",VLOOKUP(E48,GIDUR!A:D,4,FALSE),IF(D48="DER PB",VLOOKUP(E48,DER!A:D,4,FALSE)/(1+DER!$E$2),IF(D48="COMPOSIÇÃO",VLOOKUP(E48,Composição!B:J,8,FALSE),IF(A48="COMPOSIÇÃO",VLOOKUP(E48,'Sinapi_Comp-06.2023'!G:K,5,FALSE),VLOOKUP(E48,'Sinapi_Insum-06.2023'!A:E,5,FALSE))))) -> 93.88 | K48: =IFERROR(ROUND(I48*J48,2),0) -> 10800.89 | M48: =ROUND(I48*J48,2) -> 10800.89
A49: =VLOOKUP(F49,'M.Cálc.Quant.'!B:T,4,FALSE) -> COMPOSIÇÃO | C49: 4.3 | D49: =VLOOKUP(F49,'M.Cálc.Quant.'!B:T,2,FALSE) -> SINAPI | E49: =VLOOKUP(F49,'M.Cálc.Quant.'!B:T,3,FALSE) -> 92759 | F49: 1.4.2.2 | G49: =VLOOKUP(F49,'M.Cálc.Quant.'!G:T,2,FALSE) -> ARMAÇÃO DE PILAR OU VIGA DE ESTRUTURA CONVENCIONAL DE CONCRETO ARMADO UTILIZANDO AÇO CA-60 DE 5,0 MM - MONTAGEM. AF_06/2022 | H49: =VLOOKUP(F49,'M.Cálc.Quant.'!G:T,14,FALSE) -> KG | I49: =VLOOKUP(F49,'M.Cálc.Quant.'!G:T,13,FALSE) -> 123.5 | J49: =(1+$K$7)*IF(D49="GIDUR JP",VLOOKUP(E49,GIDUR!A:D,4,FALSE),IF(D49="DER PB",VLOOKUP(E49,DER!A:D,4,FALSE)/(1+DER!$E$2),IF(D49="COMPOSIÇÃO",VLOOKUP(E49,Composição!B:J,8,FALSE),IF(A49="COMPOSIÇÃO",VLOOKUP(E49,'Sinapi_Comp-06.2023'!G:K,5,FALSE),VLOOKUP(E49,'Sinapi_Insum-06.2023'!A:E,5,FALSE))))) -> 16.02 | K49: =IFERROR(ROUND(I49*J49,2),0) -> 1978.47 | M49: =ROUND(I49*J49,2) -> 1978.47
A50: =VLOOKUP(F50,'M.Cálc.Quant.'!B:T,4,FALSE) -> COMPOSIÇÃO | C50: 4.4 | D50: =VLOOKUP(F50,'M.Cálc.Quant.'!B:T,2,FALSE) -> SINAPI | E50: =VLOOKUP(F50,'M.Cálc.Quant.'!B:T,3,FALSE) -> 92760 | F50: 1.4.2.3 | G50: =VLOOKUP(F50,'M.Cálc.Quant.'!G:T,2,FALSE) -> ARMAÇÃO DE PILAR OU VIGA DE ESTRUTURA CONVENCIONAL DE CONCRETO ARMADO UTILIZANDO AÇO CA-50 DE 6,3 MM - MONTAGEM. AF_06/2022 | H50: =VLOOKUP(F50,'M.Cálc.Quant.'!G:T,14,FALSE) -> KG | I50: =VLOOKUP(F50,'M.Cálc.Quant.'!G:T,13,FALSE) -> 0.4 | J50: =(1+$K$7)*IF(D50="GIDUR JP",VLOOKUP(E50,GIDUR!A:D,4,FALSE),IF(D50="DER PB",VLOOKUP(E50,DER!A:D,4,FALSE)/(1+DER!$E$2),IF(D50="COMPOSIÇÃO",VLOOKUP(E50,Composição!B:J,8,FALSE),IF(A50="COMPOSIÇÃO",VLOOKUP(E50,'Sinapi_Comp-06.2023'!G:K,5,FALSE),VLOOKUP(E50,'Sinapi_Insum-06.2023'!A:E,5,FALSE))))) -> 15.26 | K50: =IFERROR(ROUND(I50*J50,2),0) -> 6.1 | M50: =ROUND(I50*J50,2) -> 6.1
A51: =VLOOKUP(F51,'M.Cálc.Quant.'!B:T,4,FALSE) -> COMPOSIÇÃO | C51: 4.4 | D51: =VLOOKUP(F51,'M.Cálc.Quant.'!B:T,2,FALSE) -> SINAPI | E51: =VLOOKUP(F51,'M.Cálc.Quant.'!B:T,3,FALSE) -> 92761 | F51: 1.4.2.4 | G51: =VLOOKUP(F51,'M.Cálc.Quant.'!G:T,2,FALSE) -> ARMAÇÃO DE PILAR OU VIGA DE ESTRUTURA CONVENCIONAL DE CONCRETO ARMADO UTILIZANDO AÇO CA-50 DE 8,0 MM - MONTAGEM. AF_06/2022 | H51: =VLOOKUP(F51,'M.Cálc.Quant.'!G:T,14,FALSE) -> KG | I51: =VLOOKUP(F51,'M.Cálc.Quant.'!G:T,13,FALSE) -> 94.7 | J51: =(1+$K$7)*IF(D51="GIDUR JP",VLOOKUP(E51,GIDUR!A:D,4,FALSE),IF(D51="DER PB",VLOOKUP(E51,DER!A:D,4,FALSE)/(1+DER!$E$2),IF(D51="COMPOSIÇÃO",VLOOKUP(E51,Composição!B:J,8,FALSE),IF(A51="COMPOSIÇÃO",VLOOKUP(E51,'Sinapi_Comp-06.2023'!G:K,5,FALSE),VLOOKUP(E51,'Sinapi_Insum-06.2023'!A:E,5,FALSE))))) -> 14.44 | K51: =IFERROR(ROUND(I51*J51,2),0) -> 1367.47 | M51: =ROUND(I51*J51,2) -> 1367.47
A52: =VLOOKUP(F52,'M.Cálc.Quant.'!B:T,4,FALSE) -> COMPOSIÇÃO | C52: 4.4 | D52: =VLOOKUP(F52,'M.Cálc.Quant.'!B:T,2,FALSE) -> SINAPI | E52: =VLOOKUP(F52,'M.Cálc.Quant.'!B:T,3,FALSE) -> 92762 | F52: 1.4.2.5 | G52: =VLOOKUP(F52,'M.Cálc.Quant.'!G:T,2,FALSE) -> ARMAÇÃO DE PILAR OU VIGA DE ESTRUTURA CONVENCIONAL DE CONCRETO ARMADO UTILIZANDO AÇO CA-50 DE 10,0 MM - MONTAGEM. AF_06/2022 | H52: =VLOOKUP(F52,'M.Cálc.Quant.'!G:T,14,FALSE) -> KG | I52: =VLOOKUP(F52,'M.Cálc.Quant.'!G:T,13,FALSE) -> 367.9 | J52: =(1+$K$7)*IF(D52="GIDUR JP",VLOOKUP(E52,GIDUR!A:D,4,FALSE),IF(D52="DER PB",VLOOKUP(E52,DER!A:D,4,FALSE)/(1+DER!$E$2),IF(D52="COMPOSIÇÃO",VLOOKUP(E52,Composição!B:J,8,FALSE),IF(A52="COMPOSIÇÃO",VLOOKUP(E52,'Sinapi_Comp-06.2023'!G:K,5,FALSE),VLOOKUP(E52,'Sinapi_Insum-06.2023'!A:E,5,FALSE))))) -> 12.94 | K52: =IFERROR(ROUND(I52*J52,2),0) -> 4760.63 | M52: =ROUND(I52*J52,2) -> 4760.63
A53: =VLOOKUP(F53,'M.Cálc.Quant.'!B:T,4,FALSE) -> COMPOSIÇÃO | D53: =VLOOKUP(F53,'M.Cálc.Quant.'!B:T,2,FALSE) -> SINAPI | E53: =VLOOKUP(F53,'M.Cálc.Quant.'!B:T,3,FALSE) -> 94965 | F53: 1.4.2.6 | G53: =VLOOKUP(F53,'M.Cálc.Quant.'!G:T,2,FALSE) -> CONCRETO FCK = 25MPA, TRAÇO 1:2,3:2,7 (EM MASSA SECA DE CIMENTO/ AREIA MÉDIA/ BRITA 1) - PREPARO MECÂNICO COM BETONEIRA 400 L. AF_05/2021 | H53: =VLOOKUP(F53,'M.Cálc.Quant.'!G:T,14,FALSE) -> M3 | I53: =VLOOKUP(F53,'M.Cálc.Quant.'!G:T,13,FALSE) -> 8.58 | J53: =(1+$K$7)*IF(D53="GIDUR JP",VLOOKUP(E53,GIDUR!A:D,4,FALSE),IF(D53="DER PB",VLOOKUP(E53,DER!A:D,4,FALSE)/(1+DER!$E$2),IF(D53="COMPOSIÇÃO",VLOOKUP(E53,Composição!B:J,8,FALSE),IF(A53="COMPOSIÇÃO",VLOOKUP(E53,'Sinapi_Comp-06.2023'!G:K,5,FALSE),VLOOKUP(E53,'Sinapi_Insum-06.2023'!A:E,5,FALSE))))) -> 602.47 | K53: =IFERROR(ROUND(I53*J53,2),0) -> 5169.19 | M53: =ROUND(I53*J53,2) -> 5169.19
A54: =VLOOKUP(F54,'M.Cálc.Quant.'!B:T,4,FALSE) -> COMPOSIÇÃO | C54: 1 | D54: =VLOOKUP(F54,'M.Cálc.Quant.'!B:T,2,FALSE) -> SINAPI | E54: =VLOOKUP(F54,'M.Cálc.Quant.'!B:T,3,FALSE) -> 103670 | F54: 1.4.2.7 | G54: =VLOOKUP(F54,'M.Cálc.Quant.'!G:T,2,FALSE) -> LANÇAMENTO COM USO DE BALDES, ADENSAMENTO E ACABAMENTO DE CONCRETO EM ESTRUTURAS. AF_02/2022 | H54: =VLOOKUP(F54,'M.Cálc.Quant.'!G:T,14,FALSE) -> M3 | I54: =VLOOKUP(F54,'M.Cálc.Quant.'!G:T,13,FALSE) -> 8.58 | J54: =(1+$K$7)*IF(D54="GIDUR JP",VLOOKUP(E54,GIDUR!A:D,4,FALSE),IF(D54="DER PB",VLOOKUP(E54,DER!A:D,4,FALSE)/(1+DER!$E$2),IF(D54="COMPOSIÇÃO",VLOOKUP(E54,Composição!B:J,8,FALSE),IF(A54="COMPOSIÇÃO",VLOOKUP(E54,'Sinapi_Comp-06.2023'!G:K,5,FALSE),VLOOKUP(E54,'Sinapi_Insum-06.2023'!A:E,5,FALSE))))) -> 315.49 | K54: =IFERROR(ROUND(I54*J54,2),0) -> 2706.9 | M54: =ROUND(I54*J54,2) -> 2706.9
A55: =VLOOKUP(F55,'M.Cálc.Quant.'!B:E,4,FALSE) -> 0 | C55: 3 | F55: 1.4.3 | G55: =VLOOKUP(F55,'M.Cálc.Quant.'!G:T,2,FALSE) -> CONCRETO ARMADO PARA LAJES DA EDIFICAÇÃO | K55: =SUM(K56:K61) -> 6251.94 | M55: =ROUND(I55*J55,2) -> 0
A56: =VLOOKUP(F56,'M.Cálc.Quant.'!B:T,4,FALSE) -> COMPOSIÇÃO | C56: 5 | D56: =VLOOKUP(F56,'M.Cálc.Quant.'!B:T,2,FALSE) -> SINAPI | E56: =VLOOKUP(F56,'M.Cálc.Quant.'!B:T,3,FALSE) -> 92522 | F56: 1.4.3.1 | G56: =VLOOKUP(F56,'M.Cálc.Quant.'!G:T,2,FALSE) -> MONTAGEM E DESMONTAGEM DE FÔRMA DE LAJE MACIÇA, PÉ-DIREITO SIMPLES, EM CHAPA DE MADEIRA COMPENSADA RESINADA, 8 UTILIZAÇÕES. AF_09/2020 | H56: =VLOOKUP(F56,'M.Cálc.Quant.'!G:T,14,FALSE) -> M2 | I56: =VLOOKUP(F56,'M.Cálc.Quant.'!G:T,13,FALSE) -> 22.69 | J56: =(1+$K$7)*IF(D56="GIDUR JP",VLOOKUP(E56,GIDUR!A:D,4,FALSE),IF(D56="DER PB",VLOOKUP(E56,DER!A:D,4,FALSE)/(1+DER!$E$2),IF(D56="COMPOSIÇÃO",VLOOKUP(E56,Composição!B:J,8,FALSE),IF(A56="COMPOSIÇÃO",VLOOKUP(E56,'Sinapi_Comp-06.2023'!G:K,5,FALSE),VLOOKUP(E56,'Sinapi_Insum-06.2023'!A:E,5,FALSE))))) -> 40.05 | K56: =IFERROR(ROUND(I56*J56,2),0) -> 908.73 | M56: =ROUND(I56*J56,2) -> 908.73 | O56: =(K54+K55+K56+K62)/K53 -> 12.31
A57: =VLOOKUP(F57,'M.Cálc.Quant.'!B:T,4,FALSE) -> COMPOSIÇÃO | C57: 5 | D57: =VLOOKUP(F57,'M.Cálc.Quant.'!B:T,2,FALSE) -> SINAPI | E57: =VLOOKUP(F57,'M.Cálc.Quant.'!B:T,3,FALSE) -> 94971 | F57: ='M.Cálc.Quant.'!G138 -> 1.4.3.2 | G57: =VLOOKUP(F57,'M.Cálc.Quant.'!G:T,2,FALSE) -> CONCRETO FCK = 25MPA, TRAÇO 1:2,3:2,7 (EM MASSA SECA DE CIMENTO/ AREIA MÉDIA/ BRITA 1) - PREPARO MECÂNICO COM BETONEIRA 600 L. AF_05/2021 | H57: =VLOOKUP(F57,'M.Cálc.Quant.'!G:T,14,FALSE) -> M3 | I57: =VLOOKUP(F57,'M.Cálc.Quant.'!G:T,13,FALSE) -> 3.8 | J57: =(1+$K$7)*IF(D57="GIDUR JP",VLOOKUP(E57,GIDUR!A:D,4,FALSE),IF(D57="DER PB",VLOOKUP(E57,DER!A:D,4,FALSE)/(1+DER!$E$2),IF(D57="COMPOSIÇÃO",VLOOKUP(E57,Composição!B:J,8,FALSE),IF(A57="COMPOSIÇÃO",VLOOKUP(E57,'Sinapi_Comp-06.2023'!G:K,5,FALSE),VLOOKUP(E57,'Sinapi_Insum-06.2023'!A:E,5,FALSE))))) -> 597.12 | K57: =IFERROR(ROUND(I57*J57,2),0) -> 2269.06 | M57: =ROUND(I57*J57,2) -> 2269.06
A58: =VLOOKUP(F58,'M.Cálc.Quant.'!B:T,4,FALSE) -> COMPOSIÇÃO | C58: 5 | D58: =VLOOKUP(F58,'M.Cálc.Quant.'!B:T,2,FALSE) -> SINAPI | E58: =VLOOKUP(F58,'M.Cálc.Quant.'!B:T,3,FALSE) -> 103670 | F58: ='M.Cálc.Quant.'!G140 -> 1.4.3.3 | G58: =VLOOKUP(F58,'M.Cálc.Quant.'!G:T,2,FALSE) -> LANÇAMENTO COM USO DE BALDES, ADENSAMENTO E ACABAMENTO DE CONCRETO EM ESTRUTURAS. AF_02/2022 | H58: =VLOOKUP(F58,'M.Cálc.Quant.'!G:T,14,FALSE) -> M3 | I58: =VLOOKUP(F58,'M.Cálc.Quant.'!G:T,13,FALSE) -> 3.8 | J58: =(1+$K$7)*IF(D58="GIDUR JP",VLOOKUP(E58,GIDUR!A:D,4,FALSE),IF(D58="DER PB",VLOOKUP(E58,DER!A:D,4,FALSE)/(1+DER!$E$2),IF(D58="COMPOSIÇÃO",VLOOKUP(E58,Composição!B:J,8,FALSE),IF(A58="COMPOSIÇÃO",VLOOKUP(E58,'Sinapi_Comp-06.2023'!G:K,5,FALSE),VLOOKUP(E58,'Sinapi_Insum-06.2023'!A:E,5,FALSE))))) -> 315.49 | K58: =IFERROR(ROUND(I58*J58,2),0) -> 1198.86 | M58: =ROUND(I58*J58,2) -> 1198.86
A59: =VLOOKUP(F59,'M.Cálc.Quant.'!B:T,4,FALSE) -> COMPOSIÇÃO | C59: 5 | D59: =VLOOKUP(F59,'M.Cálc.Quant.'!B:T,2,FALSE) -> SINAPI | E59: =VLOOKUP(F59,'M.Cálc.Quant.'!B:T,3,FALSE) -> 92760 | F59: ='M.Cálc.Quant.'!G142 -> 1.4.3.4 | G59: =VLOOKUP(F59,'M.Cálc.Quant.'!G:T,2,FALSE) -> ARMAÇÃO DE PILAR OU VIGA DE ESTRUTURA CONVENCIONAL DE CONCRETO ARMADO UTILIZANDO AÇO CA-50 DE 6,3 MM - MONTAGEM. AF_06/2022 | H59: =VLOOKUP(F59,'M.Cálc.Quant.'!G:T,14,FALSE) -> KG | I59: =VLOOKUP(F59,'M.Cálc.Quant.'!G:T,13,FALSE) -> 52.3 | J59: =(1+$K$7)*IF(D59="GIDUR JP",VLOOKUP(E59,GIDUR!A:D,4,FALSE),IF(D59="DER PB",VLOOKUP(E59,DER!A:D,4,FALSE)/(1+DER!$E$2),IF(D59="COMPOSIÇÃO",VLOOKUP(E59,Composição!B:J,8,FALSE),IF(A59="COMPOSIÇÃO",VLOOKUP(E59,'Sinapi_Comp-06.2023'!G:K,5,FALSE),VLOOKUP(E59,'Sinapi_Insum-06.2023'!A:E,5,FALSE))))) -> 15.26 | K59: =IFERROR(ROUND(I59*J59,2),0) -> 798.1 | M59: =ROUND(I59*J59,2) -> 798.1
A60: =VLOOKUP(F60,'M.Cálc.Quant.'!B:T,4,FALSE) -> COMPOSIÇÃO | C60: 5 | D60: =VLOOKUP(F60,'M.Cálc.Quant.'!B:T,2,FALSE) -> SINAPI | E60: =VLOOKUP(F60,'M.Cálc.Quant.'!B:T,3,FALSE) -> 92761 | F60: ='M.Cálc.Quant.'!G144 -> 1.4.3.5 | G60: =VLOOKUP(F60,'M.Cálc.Quant.'!G:T,2,FALSE) -> ARMAÇÃO DE PILAR OU VIGA DE ESTRUTURA CONVENCIONAL DE CONCRETO ARMADO UTILIZANDO AÇO CA-50 DE 8,0 MM - MONTAGEM. AF_06/2022 | H60: =VLOOKUP(F60,'M.Cálc.Quant.'!G:T,14,FALSE) -> KG | I60: =VLOOKUP(F60,'M.Cálc.Quant.'!G:T,13,FALSE) -> 51.3 | J60: =(1+$K$7)*IF(D60="GIDUR JP",VLOOKUP(E60,GIDUR!A:D,4,FALSE),IF(D60="DER PB",VLOOKUP(E60,DER!A:D,4,FALSE)/(1+DER!$E$2),IF(D60="COMPOSIÇÃO",VLOOKUP(E60,Composição!B:J,8,FALSE),IF(A60="COMPOSIÇÃO",VLOOKUP(E60,'Sinapi_Comp-06.2023'!G:K,5,FALSE),VLOOKUP(E60,'Sinapi_Insum-06.2023'!A:E,5,FALSE))))) -> 14.44 | K60: =IFERROR(ROUND(I60*J60,2),0) -> 740.77 | M60: =ROUND(I60*J60,2) -> 740.77
A61: =VLOOKUP(F61,'M.Cálc.Quant.'!B:T,4,FALSE) -> COMPOSIÇÃO | C61: 5 | D61: =VLOOKUP(F61,'M.Cálc.Quant.'!B:T,2,FALSE) -> SINAPI | E61: =VLOOKUP(F61,'M.Cálc.Quant.'!B:T,3,FALSE) -> 92759 | F61: ='M.Cálc.Quant.'!G146 -> 1.4.3.6 | G61: =VLOOKUP(F61,'M.Cálc.Quant.'!G:T,2,FALSE) -> ARMAÇÃO DE PILAR OU VIGA DE ESTRUTURA CONVENCIONAL DE CONCRETO ARMADO UTILIZANDO AÇO CA-60 DE 5,0 MM - MONTAGEM. AF_06/2022 | H61: =VLOOKUP(F61,'M.Cálc.Quant.'!G:T,14,FALSE) -> KG | I61: =VLOOKUP(F61,'M.Cálc.Quant.'!G:T,13,FALSE) -> 21 | J61: =(1+$K$7)*IF(D61="GIDUR JP",VLOOKUP(E61,GIDUR!A:D,4,FALSE),IF(D61="DER PB",VLOOKUP(E61,DER!A:D,4,FALSE)/(1+DER!$E$2),IF(D61="COMPOSIÇÃO",VLOOKUP(E61,Composição!B:J,8,FALSE),IF(A61="COMPOSIÇÃO",VLOOKUP(E61,'Sinapi_Comp-06.2023'!G:K,5,FALSE),VLOOKUP(E61,'Sinapi_Insum-06.2023'!A:E,5,FALSE))))) -> 16.02 | K61: =IFERROR(ROUND(I61*J61,2),0) -> 336.42 | M61: =ROUND(I61*J61,2) -> 336.42
A62: =VLOOKUP(F62,'M.Cálc.Quant.'!B:E,4,FALSE) -> #N/A | C62: 7 | F62: 1.5 | G62: =VLOOKUP(F62,'M.Cálc.Quant.'!G:T,2,FALSE) -> ELEVAÇÃO (murada) | K62: =SUM(K63:K67) -> 53748.44 | M62: =ROUND(I62*J62,2) -> 0
A63: =VLOOKUP(F63,'M.Cálc.Quant.'!B:T,4,FALSE) -> COMPOSIÇÃO | C63: 5 | D63: =VLOOKUP(F63,'M.Cálc.Quant.'!B:T,2,FALSE) -> SINAPI | E63: =VLOOKUP(F63,'M.Cálc.Quant.'!B:T,3,FALSE) -> 103322 | F63: 1.5.1 | G63: =VLOOKUP(F63,'M.Cálc.Quant.'!G:T,2,FALSE) -> ALVENARIA DE VEDAÇÃO DE BLOCOS CERÂMICOS FURADOS NA VERTICAL DE 9X19X39 CM (ESPESSURA 9 CM) E ARGAMASSA DE ASSENTAMENTO COM PREPARO EM BETONEIRA. AF_12/2021 | H63: =VLOOKUP(F63,'M.Cálc.Quant.'!G:T,14,FALSE) -> M2 | I63: =VLOOKUP(F63,'M.Cálc.Quant.'!G:T,13,FALSE) -> 148.45 | J63: =(1+$K$7)*IF(D63="GIDUR JP",VLOOKUP(E63,GIDUR!A:D,4,FALSE),IF(D63="DER PB",VLOOKUP(E63,DER!A:D,4,FALSE)/(1+DER!$E$2),IF(D63="COMPOSIÇÃO",VLOOKUP(E63,Composição!B:J,8,FALSE),IF(A63="COMPOSIÇÃO",VLOOKUP(E63,'Sinapi_Comp-06.2023'!G:K,5,FALSE),VLOOKUP(E63,'Sinapi_Insum-06.2023'!A:E,5,FALSE))))) -> 67.82 | K63: =IFERROR(ROUND(I63*J63,2),0) -> 10067.88 | M63: =ROUND(I63*J63,2) -> 10067.88
A64: =VLOOKUP(F64,'M.Cálc.Quant.'!B:T,4,FALSE) -> COMPOSIÇÃO | C64: 5 | D64: =VLOOKUP(F64,'M.Cálc.Quant.'!B:T,2,FALSE) -> COMPOSIÇÃO | E64: =VLOOKUP(F64,'M.Cálc.Quant.'!B:T,3,FALSE) -> 12 | F64: ='M.Cálc.Quant.'!G154 -> 1.5.2 | G64: =VLOOKUP(F64,'M.Cálc.Quant.'!G:T,2,FALSE) -> COBOGO DE CONCRETO (ELEMENTO VAZADO), 7X50X50CM, ASSENTADO COM ARGAMASSA TRACO 1:3 (CIMENTO E AREIA) [ADAPTADO SINAPI 73937/003] | H64: =VLOOKUP(F64,'M.Cálc.Quant.'!G:T,14,FALSE) -> M2 | I64: =VLOOKUP(F64,'M.Cálc.Quant.'!G:T,13,FALSE) -> 191.54 | J64: =(1+$K$7)*IF(D64="GIDUR JP",VLOOKUP(E64,GIDUR!A:D,4,FALSE),IF(D64="DER PB",VLOOKUP(E64,DER!A:D,4,FALSE)/(1+DER!$E$2),IF(D64="COMPOSIÇÃO",VLOOKUP(E64,Composição!B:J,8,FALSE),IF(A64="COMPOSIÇÃO",VLOOKUP(E64,'Sinapi_Comp-06.2023'!G:K,5,FALSE),VLOOKUP(E64,'Sinapi_Insum-06.2023'!A:E,5,FALSE))))) -> 224.67 | K64: =IFERROR(ROUND(I64*J64,2),0) -> 43033.29 | M64: =ROUND(I64*J64,2) -> 43033.29
A65: =VLOOKUP(F65,'M.Cálc.Quant.'!B:T,4,FALSE) -> COMPOSIÇÃO | C65: 5 | D65: =VLOOKUP(F65,'M.Cálc.Quant.'!B:T,2,FALSE) -> SINAPI | E65: =VLOOKUP(F65,'M.Cálc.Quant.'!B:T,3,FALSE) -> 105021 | F65: ='M.Cálc.Quant.'!G157 -> 1.5.3 | G65: =VLOOKUP(F65,'M.Cálc.Quant.'!G:T,2,FALSE) -> VERGA PRÉ-MOLDADA COM ATÉ 1,5 M DE VÃO, ESPESSURA DE *15* CM. AF_03/2024 | H65: =VLOOKUP(F65,'M.Cálc.Quant.'!G:T,14,FALSE) -> M | I65: =VLOOKUP(F65,'M.Cálc.Quant.'!G:T,13,FALSE) -> 2.12 | J65: =(1+$K$7)*IF(D65="GIDUR JP",VLOOKUP(E65,GIDUR!A:D,4,FALSE),IF(D65="DER PB",VLOOKUP(E65,DER!A:D,4,FALSE)/(1+DER!$E$2),IF(D65="COMPOSIÇÃO",VLOOKUP(E65,Composição!B:J,8,FALSE),IF(A65="COMPOSIÇÃO",VLOOKUP(E65,'Sinapi_Comp-06.2023'!G:K,5,FALSE),VLOOKUP(E65,'Sinapi_Insum-06.2023'!A:E,5,FALSE))))) -> 28.16 | K65: =IFERROR(ROUND(I65*J65,2),0) -> 59.7 | M65: =ROUND(I65*J65,2) -> 59.7
A66: =VLOOKUP(F66,'M.Cálc.Quant.'!B:T,4,FALSE) -> COMPOSIÇÃO | C66: 5 | D66: =VLOOKUP(F66,'M.Cálc.Quant.'!B:T,2,FALSE) -> SINAPI | E66: =VLOOKUP(F66,'M.Cálc.Quant.'!B:T,3,FALSE) -> 93184 | F66: ='M.Cálc.Quant.'!G159 -> 1.5.4 | G66: =VLOOKUP(F66,'M.Cálc.Quant.'!G:T,2,FALSE) -> VERGA PRÉ-MOLDADA COM ATÉ 1,5 M DE VÃO, ESPESSURA DE *20* CM. AF_03/2024 | H66: =VLOOKUP(F66,'M.Cálc.Quant.'!G:T,14,FALSE) -> M | I66: =VLOOKUP(F66,'M.Cálc.Quant.'!G:T,13,FALSE) -> 15.95 | J66: =(1+$K$7)*IF(D66="GIDUR JP",VLOOKUP(E66,GIDUR!A:D,4,FALSE),IF(D66="DER PB",VLOOKUP(E66,DER!A:D,4,FALSE)/(1+DER!$E$2),IF(D66="COMPOSIÇÃO",VLOOKUP(E66,Composição!B:J,8,FALSE),IF(A66="COMPOSIÇÃO",VLOOKUP(E66,'Sinapi_Comp-06.2023'!G:K,5,FALSE),VLOOKUP(E66,'Sinapi_Insum-06.2023'!A:E,5,FALSE))))) -> 32.61 | K66: =IFERROR(ROUND(I66*J66,2),0) -> 520.13 | M66: =ROUND(I66*J66,2) -> 520.13
A67: =VLOOKUP(F67,'M.Cálc.Quant.'!B:T,4,FALSE) -> COMPOSIÇÃO | C67: 5 | D67: =VLOOKUP(F67,'M.Cálc.Quant.'!B:T,2,FALSE) -> SINAPI | E67: =VLOOKUP(F67,'M.Cálc.Quant.'!B:T,3,FALSE) -> 93194 | F67: ='M.Cálc.Quant.'!G163 -> 1.5.5 | G67: =VLOOKUP(F67,'M.Cálc.Quant.'!G:T,2,FALSE) -> CONTRAVERGA PRÉ-MOLDADA, ESPESSURA DE *20* CM. AF_03/2024 | H67: =VLOOKUP(F67,'M.Cálc.Quant.'!G:T,14,FALSE) -> M | I67: =VLOOKUP(F67,'M.Cálc.Quant.'!G:T,13,FALSE) -> 2.12 | J67: =(1+$K$7)*IF(D67="GIDUR JP",VLOOKUP(E67,GIDUR!A:D,4,FALSE),IF(D67="DER PB",VLOOKUP(E67,DER!A:D,4,FALSE)/(1+DER!$E$2),IF(D67="COMPOSIÇÃO",VLOOKUP(E67,Composição!B:J,8,FALSE),IF(A67="COMPOSIÇÃO",VLOOKUP(E67,'Sinapi_Comp-06.2023'!G:K,5,FALSE),VLOOKUP(E67,'Sinapi_Insum-06.2023'!A:E,5,FALSE))))) -> 31.81 | K67: =IFERROR(ROUND(I67*J67,2),0) -> 67.44 | M67: =ROUND(I67*J67,2) -> 67.44
A68: =VLOOKUP(F68,'M.Cálc.Quant.'!B:E,4,FALSE) -> #N/A | C68: 9 | F68: 1.6 | G68: =VLOOKUP(F68,'M.Cálc.Quant.'!G:T,2,FALSE) -> ESQUADRIAS | K68: =SUM(K70:K71) -> 9576.15 | M68: =ROUND(I68*J68,2) -> 0
A69: =VLOOKUP(F69,'M.Cálc.Quant.'!B:E,4,FALSE) -> #N/A | C69: 7 | F69: 1.6.1 | G69: =VLOOKUP(F69,'M.Cálc.Quant.'!G:T,2,FALSE) -> PORTÃO DE FERRO | M69: =ROUND(I69*J69,2) -> 0
A70: =VLOOKUP(F70,'M.Cálc.Quant.'!B:T,4,FALSE) -> COMPOSIÇÃO | C70: 9 | D70: =VLOOKUP(F70,'M.Cálc.Quant.'!B:T,2,FALSE) -> SINAPI | E70: =VLOOKUP(F70,'M.Cálc.Quant.'!B:T,3,FALSE) -> 91341 | F70: 1.6.1.1 | G70: =VLOOKUP(F70,'M.Cálc.Quant.'!G:T,2,FALSE) -> PORTA EM ALUMÍNIO DE ABRIR TIPO VENEZIANA COM GUARNIÇÃO, FIXAÇÃO COM PARAFUSOS - FORNECIMENTO E INSTALAÇÃO. AF_12/2019 | H70: =VLOOKUP(F70,'M.Cálc.Quant.'!G:T,14,FALSE) -> M2 | I70: =VLOOKUP(F70,'M.Cálc.Quant.'!G:T,13,FALSE) -> 1.49 | J70: =(1+$K$7)*IF(D70="GIDUR JP",VLOOKUP(E70,GIDUR!A:D,4,FALSE),IF(D70="DER PB",VLOOKUP(E70,DER!A:D,4,FALSE)/(1+DER!$E$2),IF(D70="COMPOSIÇÃO",VLOOKUP(E70,Composição!B:J,8,FALSE),IF(A70="COMPOSIÇÃO",VLOOKUP(E70,'Sinapi_Comp-06.2023'!G:K,5,FALSE),VLOOKUP(E70,'Sinapi_Insum-06.2023'!A:E,5,FALSE))))) -> 877.5 | K70: =IFERROR(ROUND(I70*J70,2),0) -> 1307.48 | M70: =ROUND(I70*J70,2) -> 1307.48
A71: =VLOOKUP(F71,'M.Cálc.Quant.'!B:T,4,FALSE) -> COMPOSIÇÃO | C71: 9 | D71: =VLOOKUP(F71,'M.Cálc.Quant.'!B:T,2,FALSE) -> COMPOSIÇÃO | E71: =VLOOKUP(F71,'M.Cálc.Quant.'!B:T,3,FALSE) -> 13 | F71: ='M.Cálc.Quant.'!G169 -> 1.6.1.2 | G71: =VLOOKUP(F71,'M.Cálc.Quant.'!G:T,2,FALSE) -> PORTAO DE FERRO EM CHAPA GALVANIZADA PLANA 14 GSG [ADAPTADO SINAPI 68054] | H71: =VLOOKUP(F71,'M.Cálc.Quant.'!G:T,14,FALSE) -> M2 | I71: =VLOOKUP(F71,'M.Cálc.Quant.'!G:T,13,FALSE) -> 27.75 | J71: =(1+$K$7)*IF(D71="GIDUR JP",VLOOKUP(E71,GIDUR!A:D,4,FALSE),IF(D71="DER PB",VLOOKUP(E71,DER!A:D,4,FALSE)/(1+DER!$E$2),IF(D71="COMPOSIÇÃO",VLOOKUP(E71,Composição!B:J,8,FALSE),IF(A71="COMPOSIÇÃO",VLOOKUP(E71,'Sinapi_Comp-06.2023'!G:K,5,FALSE),VLOOKUP(E71,'Sinapi_Insum-06.2023'!A:E,5,FALSE))))) -> 297.97 | K71: =IFERROR(ROUND(I71*J71,2),0) -> 8268.67 | M71: =ROUND(I71*J71,2) -> 8268.67
F72: ='M.Cálc.Quant.'!$F$172 -> 1.7 | G72: =VLOOKUP(F72,'M.Cálc.Quant.'!G:T,2,FALSE) -> COBERTURA | K72: =K73 -> 186119.62 | M72: =ROUND(I72*J72,2) -> 0
F73: ='M.Cálc.Quant.'!$F$173 -> 1.7.1 | G73: =VLOOKUP(F73,'M.Cálc.Quant.'!G:T,2,FALSE) -> ESTRUTRA METÁLICA DE COBERTURA E FECHAMENTO | K73: =SUM(K74:K78) -> 186119.62 | M73: =ROUND(I73*J73,2) -> 0
A74: =VLOOKUP(F74,'M.Cálc.Quant.'!B:T,4,FALSE) -> COMPOSIÇÃO | D74: =VLOOKUP(F74,'M.Cálc.Quant.'!B:T,2,FALSE) -> SINAPI | E74: =VLOOKUP(F74,'M.Cálc.Quant.'!B:T,3,FALSE) -> 100773 | F74: ='M.Cálc.Quant.'!$F$174 -> 1.7.1.1 | G74: =VLOOKUP(F74,'M.Cálc.Quant.'!G:T,2,FALSE) -> ESTRUTURA TRELIÇADA DE COBERTURA, TIPO ARCO, COM LIGAÇÕES SOLDADAS, INCLUSOS PERFIS METÁLICOS, CHAPAS METÁLICAS, MÃO DE OBRA E TRANSPORTE COM GUINDASTE - FORNECIMENTO E INSTALAÇÃO. AF_01/2020_PSA | H74: =VLOOKUP(F74,'M.Cálc.Quant.'!G:T,14,FALSE) -> kg | I74: =VLOOKUP(F74,'M.Cálc.Quant.'!G:T,13,FALSE) -> 4972 | J74: =18.5*1.2522 -> 23.17 | K74: =IFERROR(ROUND(I74*J74,2),0) -> 115201.24 | M74: =ROUND(I74*J74,2) -> 115201.24
A75: =VLOOKUP(F75,'M.Cálc.Quant.'!B:T,4,FALSE) -> COMPOSIÇÃO | D75: =VLOOKUP(F75,'M.Cálc.Quant.'!B:T,2,FALSE) -> SINAPI | E75: =VLOOKUP(F75,'M.Cálc.Quant.'!B:T,3,FALSE) -> 94213 | F75: ='M.Cálc.Quant.'!$F$176 -> 1.7.1.2 | G75: =VLOOKUP(F75,'M.Cálc.Quant.'!G:T,2,FALSE) -> TELHAMENTO COM TELHA DE AÇO/ALUMÍNIO E = 0,5 MM, COM ATÉ 2 ÁGUAS, INCLUSO IÇAMENTO. AF_07/2019 | H75: =VLOOKUP(F75,'M.Cálc.Quant.'!G:T,14,FALSE) -> M2 | I75: =VLOOKUP(F75,'M.Cálc.Quant.'!G:T,13,FALSE) -> 690.98 | J75: =(1+$K$7)*IF(D75="GIDUR JP",VLOOKUP(E75,GIDUR!A:D,4,FALSE),IF(D75="DER PB",VLOOKUP(E75,DER!A:D,4,FALSE)/(1+DER!$E$2),IF(D75="COMPOSIÇÃO",VLOOKUP(E75,Composição!B:J,8,FALSE),IF(A75="COMPOSIÇÃO",VLOOKUP(E75,'Sinapi_Comp-06.2023'!G:K,5,FALSE),VLOOKUP(E75,'Sinapi_Insum-06.2023'!A:E,5,FALSE))))) -> 90.43 | K75: =IFERROR(ROUND(I75*J75,2),0) -> 62485.32 | L75: =23.56*36 -> 848.16 | M75: =ROUND(I75*J75,2) -> 62485.32
A76: =VLOOKUP(F76,'M.Cálc.Quant.'!B:T,4,FALSE) -> COMPOSIÇÃO | D76: =VLOOKUP(F76,'M.Cálc.Quant.'!B:T,2,FALSE) -> SINAPI | E76: =VLOOKUP(F76,'M.Cálc.Quant.'!B:T,3,FALSE) -> 100434 | F76: ='M.Cálc.Quant.'!$F$178 -> 1.7.1.3 | G76: =VLOOKUP(F76,'M.Cálc.Quant.'!G:T,2,FALSE) -> CALHA DE BEIRAL, SEMICIRCULAR DE PVC, DIAMETRO 125 MM, INCLUINDO CABECEIRAS, EMENDAS, BOCAIS, SUPORTES E VEDAÇÕES, EXCLUINDO CONDUTORES, INCLUSO TRANSPORTE VERTICAL. AF_07/2019 | H76: =VLOOKUP(F76,'M.Cálc.Quant.'!G:T,14,FALSE) -> M | I76: =VLOOKUP(F76,'M.Cálc.Quant.'!G:T,13,FALSE) -> 36 | J76: =(1+$K$7)*IF(D76="GIDUR JP",VLOOKUP(E76,GIDUR!A:D,4,FALSE),IF(D76="DER PB",VLOOKUP(E76,DER!A:D,4,FALSE)/(1+DER!$E$2),IF(D76="COMPOSIÇÃO",VLOOKUP(E76,Composição!B:J,8,FALSE),IF(A76="COMPOSIÇÃO",VLOOKUP(E76,'Sinapi_Comp-06.2023'!G:K,5,FALSE),VLOOKUP(E76,'Sinapi_Insum-06.2023'!A:E,5,FALSE))))) -> 180.09 | K76: =IFERROR(ROUND(I76*J76,2),0) -> 6483.24 | M76: =ROUND(I76*J76,2) -> 6483.24
A77: =VLOOKUP(F77,'M.Cálc.Quant.'!B:T,4,FALSE) -> COMPOSIÇÃO | D77: =VLOOKUP(F77,'M.Cálc.Quant.'!B:T,2,FALSE) -> SINAPI | E77: =VLOOKUP(F77,'M.Cálc.Quant.'!B:T,3,FALSE) -> 96113 | F77: ='M.Cálc.Quant.'!$F$180 -> 1.7.1.4 | G77: =VLOOKUP(F77,'M.Cálc.Quant.'!G:T,2,FALSE) -> FORRO EM PLACAS DE GESSO, PARA AMBIENTES COMERCIAIS. AF_08/2023_PS | H77: =VLOOKUP(F77,'M.Cálc.Quant.'!G:T,14,FALSE) -> M2 | I77: =VLOOKUP(F77,'M.Cálc.Quant.'!G:T,13,FALSE) -> 6.48 | J77: =(1+$K$7)*IF(D77="GIDUR JP",VLOOKUP(E77,GIDUR!A:D,4,FALSE),IF(D77="DER PB",VLOOKUP(E77,DER!A:D,4,FALSE)/(1+DER!$E$2),IF(D77="COMPOSIÇÃO",VLOOKUP(E77,Composição!B:J,8,FALSE),IF(A77="COMPOSIÇÃO",VLOOKUP(E77,'Sinapi_Comp-06.2023'!G:K,5,FALSE),VLOOKUP(E77,'Sinapi_Insum-06.2023'!A:E,5,FALSE))))) -> 52.3 | K77: =IFERROR(ROUND(I77*J77,2),0) -> 338.9 | L77: =36*2 -> 72 | M77: =ROUND(I77*J77,2) -> 338.9
A78: =VLOOKUP(F78,'M.Cálc.Quant.'!B:T,4,FALSE) -> COMPOSIÇÃO | D78: =VLOOKUP(F78,'M.Cálc.Quant.'!B:T,2,FALSE) -> SINAPI | E78: =VLOOKUP(F78,'M.Cálc.Quant.'!B:T,3,FALSE) -> 98562 | F78: ='M.Cálc.Quant.'!$F$182 -> 1.7.1.5 | G78: =VLOOKUP(F78,'M.Cálc.Quant.'!G:T,2,FALSE) -> IMPERMEABILIZAÇÃO DE SUPERFÍCIE COM ARGAMASSA DE CIMENTO E AREIA, COM ADITIVO IMPERMEABILIZANTE, E = 1,5CM. AF_09/2023 | H78: =VLOOKUP(F78,'M.Cálc.Quant.'!G:T,14,FALSE) -> M2 | I78: =VLOOKUP(F78,'M.Cálc.Quant.'!G:T,13,FALSE) -> 29.12 | J78: =(1+$K$7)*IF(D78="GIDUR JP",VLOOKUP(E78,GIDUR!A:D,4,FALSE),IF(D78="DER PB",VLOOKUP(E78,DER!A:D,4,FALSE)/(1+DER!$E$2),IF(D78="COMPOSIÇÃO",VLOOKUP(E78,Composição!B:J,8,FALSE),IF(A78="COMPOSIÇÃO",VLOOKUP(E78,'Sinapi_Comp-06.2023'!G:K,5,FALSE),VLOOKUP(E78,'Sinapi_Insum-06.2023'!A:E,5,FALSE))))) -> 55.32 | K78: =IFERROR(ROUND(I78*J78,2),0) -> 1610.92 | L78: =(36*2*0.6)+(23.56*0.8) -> 62.048 | M78: =ROUND(I78*J78,2) -> 1610.92
F79: 1.8 | G79: =VLOOKUP(F79,'M.Cálc.Quant.'!G:T,2,FALSE) -> REVESTIMENTO DE PAREDES | K79: =SUM(K80:K81) -> 21057.62 | M79: =ROUND(I79*J79,2) -> 0
A80: =VLOOKUP(F80,'M.Cálc.Quant.'!B:T,4,FALSE) -> COMPOSIÇÃO | D80: =VLOOKUP(F80,'M.Cálc.Quant.'!B:T,2,FALSE) -> SINAPI | E80: =VLOOKUP(F80,'M.Cálc.Quant.'!B:T,3,FALSE) -> 87879 | F80: 1.8.1 | G80: =VLOOKUP(F80,'M.Cálc.Quant.'!G:T,2,FALSE) -> CHAPISCO APLICADO EM ALVENARIAS E ESTRUTURAS DE CONCRETO INTERNAS, COM COLHER DE PEDREIRO. ARGAMASSA TRAÇO 1:3 COM PREPARO EM BETONEIRA 400L. AF_10/2022 | H80: =VLOOKUP(F80,'M.Cálc.Quant.'!G:T,14,FALSE) -> M2 | I80: =VLOOKUP(F80,'M.Cálc.Quant.'!G:T,13,FALSE) -> 463.11 | J80: =(1+$K$7)*IF(D80="GIDUR JP",VLOOKUP(E80,GIDUR!A:D,4,FALSE),IF(D80="DER PB",VLOOKUP(E80,DER!A:D,4,FALSE)/(1+DER!$E$2),IF(D80="COMPOSIÇÃO",VLOOKUP(E80,Composição!B:J,8,FALSE),IF(A80="COMPOSIÇÃO",VLOOKUP(E80,'Sinapi_Comp-06.2023'!G:K,5,FALSE),VLOOKUP(E80,'Sinapi_Insum-06.2023'!A:E,5,FALSE))))) -> 4.87 | K80: =IFERROR(ROUND(I80*J80,2),0) -> 2255.35 | M80: =ROUND(I80*J80,2) -> 2255.35
A81: =VLOOKUP(F81,'M.Cálc.Quant.'!B:T,4,FALSE) -> COMPOSIÇÃO | D81: =VLOOKUP(F81,'M.Cálc.Quant.'!B:T,2,FALSE) -> SINAPI | E81: =VLOOKUP(F81,'M.Cálc.Quant.'!B:T,3,FALSE) -> 87529 | F81: ='M.Cálc.Quant.'!G192 -> 1.8.2 | G81: =VLOOKUP(F81,'M.Cálc.Quant.'!G:T,2,FALSE) -> MASSA ÚNICA, EM ARGAMASSA TRAÇO 1:2:8, PREPARO MECÂNICO, APLICADA MANUALMENTE EM PAREDES INTERNAS DE AMBIENTES COM ÁREA ENTRE 5M² E 10M², E = 17,5MM, COM TALISCAS. AF_03/2024 | H81: =VLOOKUP(F81,'M.Cálc.Quant.'!G:T,14,FALSE) -> M2 | I81: =VLOOKUP(F81,'M.Cálc.Quant.'!G:T,13,FALSE) -> 463.11 | J81: =(1+$K$7)*IF(D81="GIDUR JP",VLOOKUP(E81,GIDUR!A:D,4,FALSE),IF(D81="DER PB",VLOOKUP(E81,DER!A:D,4,FALSE)/(1+DER!$E$2),IF(D81="COMPOSIÇÃO",VLOOKUP(E81,Composição!B:J,8,FALSE),IF(A81="COMPOSIÇÃO",VLOOKUP(E81,'Sinapi_Comp-06.2023'!G:K,5,FALSE),VLOOKUP(E81,'Sinapi_Insum-06.2023'!A:E,5,FALSE))))) -> 40.6 | K81: =IFERROR(ROUND(I81*J81,2),0) -> 18802.27 | M81: =ROUND(I81*J81,2) -> 18802.27
F82: 1.9 | G82: =VLOOKUP(F82,'M.Cálc.Quant.'!G:T,2,FALSE) -> PAVIMENTAÇÃO | K82: =SUM(K83:K89) -> 164641.62 | M82: =ROUND(I82*J82,2) -> 0
A83: =VLOOKUP(F83,'M.Cálc.Quant.'!B:T,4,FALSE) -> COMPOSIÇÃO | D83: =VLOOKUP(F83,'M.Cálc.Quant.'!B:T,2,FALSE) -> COMPOSIÇÃO | E83: =VLOOKUP(F83,'M.Cálc.Quant.'!B:T,3,FALSE) -> 14 | F83: 1.9.1 | G83: =VLOOKUP(F83,'M.Cálc.Quant.'!G:T,2,FALSE) -> COMPACTACAO MECANICA, SEM CONTROLE DO GC (C/COMPACTADOR PLACA 400 KG) [ADAPTADO 74005/001] | H83: =VLOOKUP(F83,'M.Cálc.Quant.'!G:T,14,FALSE) -> M2 | I83: =VLOOKUP(F83,'M.Cálc.Quant.'!G:T,13,FALSE) -> 450.65 | J83: =(1+$K$7)*IF(D83="GIDUR JP",VLOOKUP(E83,GIDUR!A:D,4,FALSE),IF(D83="DER PB",VLOOKUP(E83,DER!A:D,4,FALSE)/(1+DER!$E$2),IF(D83="COMPOSIÇÃO",VLOOKUP(E83,Composição!B:J,8,FALSE),IF(A83="COMPOSIÇÃO",VLOOKUP(E83,'Sinapi_Comp-06.2023'!G:K,5,FALSE),VLOOKUP(E83,'Sinapi_Insum-06.2023'!A:E,5,FALSE))))) -> 27.76 | K83: =IFERROR(ROUND(I83*J83,2),0) -> 12510.04 | M83: =ROUND(I83*J83,2) -> 12510.04
A84: =VLOOKUP(F84,'M.Cálc.Quant.'!B:T,4,FALSE) -> COMPOSIÇÃO | D84: =VLOOKUP(F84,'M.Cálc.Quant.'!B:T,2,FALSE) -> SINAPI | E84: =VLOOKUP(F84,'M.Cálc.Quant.'!B:T,3,FALSE) -> 96620 | F84: 1.9.2 | G84: =VLOOKUP(F84,'M.Cálc.Quant.'!G:T,2,FALSE) -> LASTRO DE CONCRETO MAGRO, APLICADO EM PISOS, LAJES SOBRE SOLO OU RADIERS. AF_01/2024 | H84: =VLOOKUP(F84,'M.Cálc.Quant.'!G:T,14,FALSE) -> M3 | I84: =VLOOKUP(F84,'M.Cálc.Quant.'!G:T,13,FALSE) -> 22.53 | J84: =(1+$K$7)*IF(D84="GIDUR JP",VLOOKUP(E84,GIDUR!A:D,4,FALSE),IF(D84="DER PB",VLOOKUP(E84,DER!A:D,4,FALSE)/(1+DER!$E$2),IF(D84="COMPOSIÇÃO",VLOOKUP(E84,Composição!B:J,8,FALSE),IF(A84="COMPOSIÇÃO",VLOOKUP(E84,'Sinapi_Comp-06.2023'!G:K,5,FALSE),VLOOKUP(E84,'Sinapi_Insum-06.2023'!A:E,5,FALSE))))) -> 860.29 | K84: =IFERROR(ROUND(I84*J84,2),0) -> 19382.33 | M84: =ROUND(I84*J84,2) -> 19382.33
A85: =VLOOKUP(F85,'M.Cálc.Quant.'!B:T,4,FALSE) -> COMPOSIÇÃO | D85: =VLOOKUP(F85,'M.Cálc.Quant.'!B:T,2,FALSE) -> SINAPI | E85: =VLOOKUP(F85,'M.Cálc.Quant.'!B:T,3,FALSE) -> 87256 | F85: ='M.Cálc.Quant.'!G199 -> 1.9.3 | G85: =VLOOKUP(F85,'M.Cálc.Quant.'!G:T,2,FALSE) -> REVESTIMENTO CERÂMICO PARA PISO COM PLACAS TIPO ESMALTADA DE DIMENSÕES 60X60 CM APLICADA EM AMBIENTES DE ÁREA ENTRE 5 M2 E 10 M2. AF_02/2023_PE | H85: =VLOOKUP(F85,'M.Cálc.Quant.'!G:T,14,FALSE) -> M2 | I85: =VLOOKUP(F85,'M.Cálc.Quant.'!G:T,13,FALSE) -> 6.48 | J85: =(1+$K$7)*IF(D85="GIDUR JP",VLOOKUP(E85,GIDUR!A:D,4,FALSE),IF(D85="DER PB",VLOOKUP(E85,DER!A:D,4,FALSE)/(1+DER!$E$2),IF(D85="COMPOSIÇÃO",VLOOKUP(E85,Composição!B:J,8,FALSE),IF(A85="COMPOSIÇÃO",VLOOKUP(E85,'Sinapi_Comp-06.2023'!G:K,5,FALSE),VLOOKUP(E85,'Sinapi_Insum-06.2023'!A:E,5,FALSE))))) -> 97.1 | K85: =IFERROR(ROUND(I85*J85,2),0) -> 629.21 | M85: =ROUND(I85*J85,2) -> 629.21
A86: =VLOOKUP(F86,'M.Cálc.Quant.'!B:T,4,FALSE) -> COMPOSIÇÃO | D86: =VLOOKUP(F86,'M.Cálc.Quant.'!B:T,2,FALSE) -> COMPOSIÇÃO | E86: =VLOOKUP(F86,'M.Cálc.Quant.'!B:T,3,FALSE) -> 15 | F86: ='M.Cálc.Quant.'!G201 -> 1.9.4 | G86: =VLOOKUP(F86,'M.Cálc.Quant.'!G:T,2,FALSE) -> PISO EM CONCRETO 20MPA PREPARO MECANICO, ESPESSURA 7 CM, COM ARMACAO EM TELA SOLDADA E ESPAÇADORES[ADAPTADO 72183] | H86: =VLOOKUP(F86,'M.Cálc.Quant.'!G:T,14,FALSE) -> M2 | I86: =VLOOKUP(F86,'M.Cálc.Quant.'!G:T,13,FALSE) -> 450.65 | J86: =(1+$K$7)*IF(D86="GIDUR JP",VLOOKUP(E86,GIDUR!A:D,4,FALSE),IF(D86="DER PB",VLOOKUP(E86,DER!A:D,4,FALSE)/(1+DER!$E$2),IF(D86="COMPOSIÇÃO",VLOOKUP(E86,Composição!B:J,8,FALSE),IF(A86="COMPOSIÇÃO",VLOOKUP(E86,'Sinapi_Comp-06.2023'!G:K,5,FALSE),VLOOKUP(E86,'Sinapi_Insum-06.2023'!A:E,5,FALSE))))) -> 128.9 | K86: =IFERROR(ROUND(I86*J86,2),0) -> 58088.79 | M86: =ROUND(I86*J86,2) -> 58088.79
A87: =VLOOKUP(F87,'M.Cálc.Quant.'!B:T,4,FALSE) -> COMPOSIÇÃO | D87: =VLOOKUP(F87,'M.Cálc.Quant.'!B:T,2,FALSE) -> COMPOSIÇÃO | E87: =VLOOKUP(F87,'M.Cálc.Quant.'!B:T,3,FALSE) -> 21 | F87: ='M.Cálc.Quant.'!G203 -> 1.9.5 | G87: =VLOOKUP(F87,'M.Cálc.Quant.'!G:T,2,FALSE) -> PISO INDUSTRIAL ALTA RESISTENCIA, ESPESSURA 12MM, INCLUSO JUNTAS DE DILATACAO PLASTICAS E POLIMENTO MECANIZADO [ADAPTADO 72137] | H87: =VLOOKUP(F87,'M.Cálc.Quant.'!G:T,14,FALSE) -> m2 | I87: =VLOOKUP(F87,'M.Cálc.Quant.'!G:T,13,FALSE) -> 450.65 | J87: =(1+$K$7)*IF(D87="GIDUR JP",VLOOKUP(E87,GIDUR!A:D,4,FALSE),IF(D87="DER PB",VLOOKUP(E87,DER!A:D,4,FALSE)/(1+DER!$E$2),IF(D87="COMPOSIÇÃO",VLOOKUP(E87,Composição!B:J,8,FALSE),IF(A87="COMPOSIÇÃO",VLOOKUP(E87,'Sinapi_Comp-06.2023'!G:K,5,FALSE),VLOOKUP(E87,'Sinapi_Insum-06.2023'!A:E,5,FALSE))))) -> 145.17 | K87: =IFERROR(ROUND(I87*J87,2),0) -> 65420.86 | M87: =ROUND(I87*J87,2) -> 65420.86
A88: =VLOOKUP(F88,'M.Cálc.Quant.'!B:T,4,FALSE) -> COMPOSIÇÃO | D88: =VLOOKUP(F88,'M.Cálc.Quant.'!B:T,2,FALSE) -> COMPOSIÇÃO | E88: =VLOOKUP(F88,'M.Cálc.Quant.'!B:T,3,FALSE) -> 2 | F88: ='M.Cálc.Quant.'!G205 -> 1.9.6 | G88: =VLOOKUP(F88,'M.Cálc.Quant.'!G:T,2,FALSE) -> PISO TÁTIL DIRECIONAL E/OU ALERTA, DE CONCRETO, NA COR NATURAL, P/DEFICIENTES VISUAIS, DIMENSÕES 25X25CM, APLICADO COM ARGAMASSA INDUSTRIALIZADA AC-II, REJUNTADO, EXCLUSIVE REGULARIZAÇÃO DE BASE (ADAPTADO DE 09418/ORSE) | H88: =VLOOKUP(F88,'M.Cálc.Quant.'!G:T,14,FALSE) -> M2 | I88: =VLOOKUP(F88,'M.Cálc.Quant.'!G:T,13,FALSE) -> 19.1 | J88: =(1+$K$7)*IF(D88="GIDUR JP",VLOOKUP(E88,GIDUR!A:D,4,FALSE),IF(D88="DER PB",VLOOKUP(E88,DER!A:D,4,FALSE)/(1+DER!$E$2),IF(D88="COMPOSIÇÃO",VLOOKUP(E88,Composição!B:J,8,FALSE),IF(A88="COMPOSIÇÃO",VLOOKUP(E88,'Sinapi_Comp-06.2023'!G:K,5,FALSE),VLOOKUP(E88,'Sinapi_Insum-06.2023'!A:E,5,FALSE))))) -> 113.62 | K88: =IFERROR(ROUND(I88*J88,2),0) -> 2170.14 | M88: =ROUND(I88*J88,2) -> 2170.14
A89: =VLOOKUP(F89,'M.Cálc.Quant.'!B:T,4,FALSE) -> COMPOSIÇÃO | D89: =VLOOKUP(F89,'M.Cálc.Quant.'!B:T,2,FALSE) -> SINAPI | E89: =VLOOKUP(F89,'M.Cálc.Quant.'!B:T,3,FALSE) -> 94319 | F89: ='M.Cálc.Quant.'!G207 -> 1.9.7 | G89: =VLOOKUP(F89,'M.Cálc.Quant.'!G:T,2,FALSE) -> ATERRO MANUAL DE VALAS COM SOLO ARGILO-ARENOSO. AF_08/2023 | H89: =VLOOKUP(F89,'M.Cálc.Quant.'!G:T,14,FALSE) -> M3 | I89: =VLOOKUP(F89,'M.Cálc.Quant.'!G:T,13,FALSE) -> 67.6 | J89: =(1+$K$7)*IF(D89="GIDUR JP",VLOOKUP(E89,GIDUR!A:D,4,FALSE),IF(D89="DER PB",VLOOKUP(E89,DER!A:D,4,FALSE)/(1+DER!$E$2),IF(D89="COMPOSIÇÃO",VLOOKUP(E89,Composição!B:J,8,FALSE),IF(A89="COMPOSIÇÃO",VLOOKUP(E89,'Sinapi_Comp-06.2023'!G:K,5,FALSE),VLOOKUP(E89,'Sinapi_Insum-06.2023'!A:E,5,FALSE))))) -> 95.27 | K89: =IFERROR(ROUND(I89*J89,2),0) -> 6440.25
F90: 1.10 | G90: =VLOOKUP(F90,'M.Cálc.Quant.'!G:T,2,FALSE) -> PINTURA | K90: =SUM(K91:K99) -> 55238.83 | M90: =ROUND(I90*J90,2) -> 0
A91: =VLOOKUP(F91,'M.Cálc.Quant.'!B:T,4,FALSE) -> COMPOSIÇÃO | D91: =VLOOKUP(F91,'M.Cálc.Quant.'!B:T,2,FALSE) -> SINAPI | E91: =VLOOKUP(F91,'M.Cálc.Quant.'!B:T,3,FALSE) -> 88485 | F91: 1.10.1 | G91: =VLOOKUP(F91,'M.Cálc.Quant.'!G:T,2,FALSE) -> FUNDO SELADOR ACRÍLICO, APLICAÇÃO MANUAL EM PAREDE, UMA DEMÃO. AF_04/2023 | H91: =VLOOKUP(F91,'M.Cálc.Quant.'!G:T,14,FALSE) -> M2 | I91: =VLOOKUP(F91,'M.Cálc.Quant.'!G:T,13,FALSE) -> 463.11 | J91: =(1+$K$7)*IF(D91="GIDUR JP",VLOOKUP(E91,GIDUR!A:D,4,FALSE),IF(D91="DER PB",VLOOKUP(E91,DER!A:D,4,FALSE)/(1+DER!$E$2),IF(D91="COMPOSIÇÃO",VLOOKUP(E91,Composição!B:J,8,FALSE),IF(A91="COMPOSIÇÃO",VLOOKUP(E91,'Sinapi_Comp-06.2023'!G:K,5,FALSE),VLOOKUP(E91,'Sinapi_Insum-06.2023'!A:E,5,FALSE))))) -> 4.46 | K91: =IFERROR(ROUND(I91*J91,2),0) -> 2065.47 | M91: =ROUND(I91*J91,2) -> 2065.47
A92: =VLOOKUP(F92,'M.Cálc.Quant.'!B:T,4,FALSE) -> COMPOSIÇÃO | D92: =VLOOKUP(F92,'M.Cálc.Quant.'!B:T,2,FALSE) -> SINAPI | E92: =VLOOKUP(F92,'M.Cálc.Quant.'!B:T,3,FALSE) -> 88495 | F92: 1.10.2 | G92: =VLOOKUP(F92,'M.Cálc.Quant.'!G:T,2,FALSE) -> EMASSAMENTO COM MASSA LÁTEX, APLICAÇÃO EM PAREDE, UMA DEMÃO, LIXAMENTO MANUAL. AF_04/2023 | H92: =VLOOKUP(F92,'M.Cálc.Quant.'!G:T,14,FALSE) -> M2 | I92: =VLOOKUP(F92,'M.Cálc.Quant.'!G:T,13,FALSE) -> 463.11 | J92: =(1+$K$7)*IF(D92="GIDUR JP",VLOOKUP(E92,GIDUR!A:D,4,FALSE),IF(D92="DER PB",VLOOKUP(E92,DER!A:D,4,FALSE)/(1+DER!$E$2),IF(D92="COMPOSIÇÃO",VLOOKUP(E92,Composição!B:J,8,FALSE),IF(A92="COMPOSIÇÃO",VLOOKUP(E92,'Sinapi_Comp-06.2023'!G:K,5,FALSE),VLOOKUP(E92,'Sinapi_Insum-06.2023'!A:E,5,FALSE))))) -> 11.8 | K92: =IFERROR(ROUND(I92*J92,2),0) -> 5464.7 | M92: =ROUND(I92*J92,2) -> 5464.7
A93: =VLOOKUP(F93,'M.Cálc.Quant.'!B:T,4,FALSE) -> COMPOSIÇÃO | D93: =VLOOKUP(F93,'M.Cálc.Quant.'!B:T,2,FALSE) -> SINAPI | E93: =VLOOKUP(F93,'M.Cálc.Quant.'!B:T,3,FALSE) -> 88489 | F93: 1.10.3 | G93: =VLOOKUP(F93,'M.Cálc.Quant.'!G:T,2,FALSE) -> PINTURA LÁTEX ACRÍLICA PREMIUM, APLICAÇÃO MANUAL EM PAREDES, DUAS DEMÃOS. AF_04/2023 | H93: =VLOOKUP(F93,'M.Cálc.Quant.'!G:T,14,FALSE) -> M2 | I93: =VLOOKUP(F93,'M.Cálc.Quant.'!G:T,13,FALSE) -> 463.11 | J93: =(1+$K$7)*IF(D93="GIDUR JP",VLOOKUP(E93,GIDUR!A:D,4,FALSE),IF(D93="DER PB",VLOOKUP(E93,DER!A:D,4,FALSE)/(1+DER!$E$2),IF(D93="COMPOSIÇÃO",VLOOKUP(E93,Composição!B:J,8,FALSE),IF(A93="COMPOSIÇÃO",VLOOKUP(E93,'Sinapi_Comp-06.2023'!G:K,5,FALSE),VLOOKUP(E93,'Sinapi_Insum-06.2023'!A:E,5,FALSE))))) -> 14.44 | K93: =IFERROR(ROUND(I93*J93,2),0) -> 6687.31 | M93: =ROUND(I93*J93,2) -> 6687.31
A94: =VLOOKUP(F94,'M.Cálc.Quant.'!B:T,4,FALSE) -> COMPOSIÇÃO | D94: =VLOOKUP(F94,'M.Cálc.Quant.'!B:T,2,FALSE) -> COMPOSIÇÃO | E94: =VLOOKUP(F94,'M.Cálc.Quant.'!B:T,3,FALSE) -> 16 | F94: 1.10.4 | G94: =VLOOKUP(F94,'M.Cálc.Quant.'!G:T,2,FALSE) -> APLICAÇÃO DE FUNDO SELADOR LÁTEX PVA EM TETO, UMA DEMÃO. AF_06/2014 [ADAPTADO 88482] | H94: =VLOOKUP(F94,'M.Cálc.Quant.'!G:T,14,FALSE) -> M2 | I94: =VLOOKUP(F94,'M.Cálc.Quant.'!G:T,13,FALSE) -> 6.48 | J94: =(1+$K$7)*IF(D94="GIDUR JP",VLOOKUP(E94,GIDUR!A:D,4,FALSE),IF(D94="DER PB",VLOOKUP(E94,DER!A:D,4,FALSE)/(1+DER!$E$2),IF(D94="COMPOSIÇÃO",VLOOKUP(E94,Composição!B:J,8,FALSE),IF(A94="COMPOSIÇÃO",VLOOKUP(E94,'Sinapi_Comp-06.2023'!G:K,5,FALSE),VLOOKUP(E94,'Sinapi_Insum-06.2023'!A:E,5,FALSE))))) -> 28.86 | K94: =IFERROR(ROUND(I94*J94,2),0) -> 187.01 | M94: =ROUND(I94*J94,2) -> 187.01
A95: =VLOOKUP(F95,'M.Cálc.Quant.'!B:T,4,FALSE) -> COMPOSIÇÃO | D95: =VLOOKUP(F95,'M.Cálc.Quant.'!B:T,2,FALSE) -> SINAPI | E95: =VLOOKUP(F95,'M.Cálc.Quant.'!B:T,3,FALSE) -> 88496 | F95: ='M.Cálc.Quant.'!G218 -> 1.10.5 | G95: =VLOOKUP(F95,'M.Cálc.Quant.'!G:T,2,FALSE) -> EMASSAMENTO COM MASSA LÁTEX, APLICAÇÃO EM TETO, DUAS DEMÃOS, LIXAMENTO MANUAL. AF_04/2023 | H95: =VLOOKUP(F95,'M.Cálc.Quant.'!G:T,14,FALSE) -> M2 | I95: =VLOOKUP(F95,'M.Cálc.Quant.'!G:T,13,FALSE) -> 6.48 | J95: =(1+$K$7)*IF(D95="GIDUR JP",VLOOKUP(E95,GIDUR!A:D,4,FALSE),IF(D95="DER PB",VLOOKUP(E95,DER!A:D,4,FALSE)/(1+DER!$E$2),IF(D95="COMPOSIÇÃO",VLOOKUP(E95,Composição!B:J,8,FALSE),IF(A95="COMPOSIÇÃO",VLOOKUP(E95,'Sinapi_Comp-06.2023'!G:K,5,FALSE),VLOOKUP(E95,'Sinapi_Insum-06.2023'!A:E,5,FALSE))))) -> 32.85 | K95: =IFERROR(ROUND(I95*J95,2),0) -> 212.87 | M95: =ROUND(I95*J95,2) -> 212.87
A96: =VLOOKUP(F96,'M.Cálc.Quant.'!B:T,4,FALSE) -> COMPOSIÇÃO | D96: =VLOOKUP(F96,'M.Cálc.Quant.'!B:T,2,FALSE) -> SINAPI | E96: =VLOOKUP(F96,'M.Cálc.Quant.'!B:T,3,FALSE) -> 88488 | F96: ='M.Cálc.Quant.'!G220 -> 1.10.6 | G96: =VLOOKUP(F96,'M.Cálc.Quant.'!G:T,2,FALSE) -> PINTURA LÁTEX ACRÍLICA PREMIUM, APLICAÇÃO MANUAL EM TETO, DUAS DEMÃOS. AF_04/2023 | H96: =VLOOKUP(F96,'M.Cálc.Quant.'!G:T,14,FALSE) -> M2 | I96: =VLOOKUP(F96,'M.Cálc.Quant.'!G:T,13,FALSE) -> 6.48 | J96: =(1+$K$7)*IF(D96="GIDUR JP",VLOOKUP(E96,GIDUR!A:D,4,FALSE),IF(D96="DER PB",VLOOKUP(E96,DER!A:D,4,FALSE)/(1+DER!$E$2),IF(D96="COMPOSIÇÃO",VLOOKUP(E96,Composição!B:J,8,FALSE),IF(A96="COMPOSIÇÃO",VLOOKUP(E96,'Sinapi_Comp-06.2023'!G:K,5,FALSE),VLOOKUP(E96,'Sinapi_Insum-06.2023'!A:E,5,FALSE))))) -> 16.89 | K96: =IFERROR(ROUND(I96*J96,2),0) -> 109.45 | M96: =ROUND(I96*J96,2) -> 109.45
A97: =VLOOKUP(F97,'M.Cálc.Quant.'!B:T,4,FALSE) -> COMPOSIÇÃO | D97: =VLOOKUP(F97,'M.Cálc.Quant.'!B:T,2,FALSE) -> SINAPI | E97: =VLOOKUP(F97,'M.Cálc.Quant.'!B:T,3,FALSE) -> 102494 | F97: ='M.Cálc.Quant.'!G222 -> 1.10.7 | G97: =VLOOKUP(F97,'M.Cálc.Quant.'!G:T,2,FALSE) -> PINTURA DE PISO COM TINTA EPÓXI, APLICAÇÃO MANUAL, 2 DEMÃOS, INCLUSO PRIMER EPÓXI. AF_05/2021 | H97: =VLOOKUP(F97,'M.Cálc.Quant.'!G:T,14,FALSE) -> M2 | I97: =VLOOKUP(F97,'M.Cálc.Quant.'!G:T,13,FALSE) -> 340.38 | J97: =(1+$K$7)*IF(D97="GIDUR JP",VLOOKUP(E97,GIDUR!A:D,4,FALSE),IF(D97="DER PB",VLOOKUP(E97,DER!A:D,4,FALSE)/(1+DER!$E$2),IF(D97="COMPOSIÇÃO",VLOOKUP(E97,Composição!B:J,8,FALSE),IF(A97="COMPOSIÇÃO",VLOOKUP(E97,'Sinapi_Comp-06.2023'!G:K,5,FALSE),VLOOKUP(E97,'Sinapi_Insum-06.2023'!A:E,5,FALSE))))) -> 71.79 | K97: =IFERROR(ROUND(I97*J97,2),0) -> 24435.88 | M97: =ROUND(I97*J97,2) -> 24435.88
A98: =VLOOKUP(F98,'M.Cálc.Quant.'!B:T,4,FALSE) -> COMPOSIÇÃO | D98: =VLOOKUP(F98,'M.Cálc.Quant.'!B:T,2,FALSE) -> COMPOSIÇÃO | E98: =VLOOKUP(F98,'M.Cálc.Quant.'!B:T,3,FALSE) -> 4 | F98: ='M.Cálc.Quant.'!G224 -> 1.10.8 | G98: =VLOOKUP(F98,'M.Cálc.Quant.'!G:T,2,FALSE) -> FUNDO PREPARADOR PRIMER A BASE DE EPOXI, PARA ESTRUTURA METALICA, UMA DEMAO, ESPESSURA DE 25 MICRA (ADAPTADO DE SINAPI 73865/1) | H98: =VLOOKUP(F98,'M.Cálc.Quant.'!G:T,14,FALSE) -> M2 | I98: =VLOOKUP(F98,'M.Cálc.Quant.'!G:T,13,FALSE) -> 340.38 | J98: =(1+$K$7)*IF(D98="GIDUR JP",VLOOKUP(E98,GIDUR!A:D,4,FALSE),IF(D98="DER PB",VLOOKUP(E98,DER!A:D,4,FALSE)/(1+DER!$E$2),IF(D98="COMPOSIÇÃO",VLOOKUP(E98,Composição!B:J,8,FALSE),IF(A98="COMPOSIÇÃO",VLOOKUP(E98,'Sinapi_Comp-06.2023'!G:K,5,FALSE),VLOOKUP(E98,'Sinapi_Insum-06.2023'!A:E,5,FALSE))))) -> 21.22 | K98: =IFERROR(ROUND(I98*J98,2),0) -> 7222.86 | M98: =ROUND(I98*J98,2) -> 7222.86
A99: =VLOOKUP(F99,'M.Cálc.Quant.'!B:T,4,FALSE) -> COMPOSIÇÃO | D99: =VLOOKUP(F99,'M.Cálc.Quant.'!B:T,2,FALSE) -> COMPOSIÇÃO | E99: =VLOOKUP(F99,'M.Cálc.Quant.'!B:T,3,FALSE) -> 5 | F99: ='M.Cálc.Quant.'!G226 -> 1.10.9 | G99: =VLOOKUP(F99,'M.Cálc.Quant.'!G:T,2,FALSE) -> PINTURA ESMALTE FOSCO, DUAS DEMAOS, SOBRE SUPERFICIE METALICA, INCLUSO UMA DEMAO DE FUNDO ANTICORROSIVO. UTILIZACAO DE REVOLVER ( AR-COMPRIMIDO) (ADAPTADO DE SINAPI 74145/1) | H99: =VLOOKUP(F99,'M.Cálc.Quant.'!G:T,14,FALSE) -> M2 | I99: =VLOOKUP(F99,'M.Cálc.Quant.'!G:T,13,FALSE) -> 340.38 | J99: =(1+$K$7)*IF(D99="GIDUR JP",VLOOKUP(E99,GIDUR!A:D,4,FALSE),IF(D99="DER PB",VLOOKUP(E99,DER!A:D,4,FALSE)/(1+DER!$E$2),IF(D99="COMPOSIÇÃO",VLOOKUP(E99,Composição!B:J,8,FALSE),IF(A99="COMPOSIÇÃO",VLOOKUP(E99,'Sinapi_Comp-06.2023'!G:K,5,FALSE),VLOOKUP(E99,'Sinapi_Insum-06.2023'!A:E,5,FALSE))))) -> 26.01 | K99: =IFERROR(ROUND(I99*J99,2),0) -> 8853.28 | M99: =ROUND(I99*J99,2) -> 8853.28
F100: 1.11 | G100: =VLOOKUP(F100,'M.Cálc.Quant.'!G:T,2,FALSE) -> INSTALAÇÃO ELÉTRICA (REFERENTE À TODA QUADRA) | K100: =SUM(K101:K105) -> 616.71 | M100: =ROUND(I100*J100,2) -> 0
A101: =VLOOKUP(F101,'M.Cálc.Quant.'!B:T,4,FALSE) -> INSUMO | D101: =VLOOKUP(F101,'M.Cálc.Quant.'!B:T,2,FALSE) -> SINAPI | E101: =VLOOKUP(F101,'M.Cálc.Quant.'!B:T,3,FALSE) -> 2392 | F101: 1.11.1 | G101: =VLOOKUP(F101,'M.Cálc.Quant.'!G:T,2,FALSE) -> DISJUNTOR TIPO NEMA, TRIPOLAR 10 ATE 50A, TENSAO MAXIMA DE 415 V | H101: =VLOOKUP(F101,'M.Cálc.Quant.'!G:T,14,FALSE) -> UN | I101: =VLOOKUP(F101,'M.Cálc.Quant.'!G:T,13,FALSE) -> 1 | J101: =(1+$K$7)*IF(D101="GIDUR JP",VLOOKUP(E101,GIDUR!A:D,4,FALSE),IF(D101="DER PB",VLOOKUP(E101,DER!A:D,4,FALSE)/(1+DER!$E$2),IF(D101="COMPOSIÇÃO",VLOOKUP(E101,Composição!B:J,8,FALSE),IF(A101="COMPOSIÇÃO",VLOOKUP(E101,'Sinapi_Comp-06.2023'!G:K,5,FALSE),VLOOKUP(E101,'Sinapi_Insum-06.2023'!A:E,5,FALSE))))) -> 81.44 | K101: =IFERROR(ROUND(I101*J101,2),0) -> 81.44 | M101: =ROUND(I101*J101,2) -> 81.44
A102: =VLOOKUP(F102,'M.Cálc.Quant.'!B:T,4,FALSE) -> COMPOSIÇÃO | D102: =VLOOKUP(F102,'M.Cálc.Quant.'!B:T,2,FALSE) -> SINAPI | E102: =VLOOKUP(F102,'M.Cálc.Quant.'!B:T,3,FALSE) -> 93656 | F102: 1.11.2 | G102: =VLOOKUP(F102,'M.Cálc.Quant.'!G:T,2,FALSE) -> DISJUNTOR MONOPOLAR TIPO DIN, CORRENTE NOMINAL DE 25A - FORNECIMENTO E INSTALAÇÃO. AF_10/2020 | H102: =VLOOKUP(F102,'M.Cálc.Quant.'!G:T,14,FALSE) -> UN | I102: =VLOOKUP(F102,'M.Cálc.Quant.'!G:T,13,FALSE) -> 1 | J102: =(1+$K$7)*IF(D102="GIDUR JP",VLOOKUP(E102,GIDUR!A:D,4,FALSE),IF(D102="DER PB",VLOOKUP(E102,DER!A:D,4,FALSE)/(1+DER!$E$2),IF(D102="COMPOSIÇÃO",VLOOKUP(E102,Composição!B:J,8,FALSE),IF(A102="COMPOSIÇÃO",VLOOKUP(E102,'Sinapi_Comp-06.2023'!G:K,5,FALSE),VLOOKUP(E102,'Sinapi_Insum-06.2023'!A:E,5,FALSE))))) -> 14.4 | K102: =IFERROR(ROUND(I102*J102,2),0) -> 14.4 | M102: =ROUND(I102*J102,2) -> 14.4
...

Sheet Plan. Orçam. Resumo
C2: PROGRAMA: | D2: =Composição!D2 -> Esporte, Cidadania e Desenvolvimento | H2: Preencher com o(s) valore(s) do(s) convênio(s)
C3: CONCEDENTE: | D3: =Composição!D3 -> Prefeitura Municipal de Coremas - PB | L3: =I7+L7 -> 1385244.2
C4: CONTRATO: | D4: =Composição!D4 -> Município de Coremas- PB | E4: Encargos
C5: OBRA: | D5: =Composição!D5 -> RECURSOS GOVERNO DO ESTADO | E5: ='Plan.Orçam.'!$K$6/100 -> 0.8569 | H5: ↓
C6: CONVENENTE: | D6: =Composição!D6 -> CONSTRUÇÃO DE QUADRA POLIESPORTIVA COM VESTIÁRIOS E BANHEIROS, NO MUNICÍPIO DE COREMAS/PB | E6: B.D.I. | F6: Item | G6: Convênio | H6: Previsto | I6: Orçado | J6: Diferença | L6: Valor Projeto | M6: Percentual Projeto | N6: Valor Residual do Convênio
C7: REF. PREF. DE PREÇOS: | D7: =BDI!$C$8 -> SINAPI PB - 06/2025 | E7: =BDI!$C$31 -> 0.2522 | F7: 1 | G7: =D5 -> RECURSOS GOVERNO DO ESTADO | H7: =250000 -> 250000 | I7: =SUMIF($B$13:$B$30,F7,$E$13:$E$30) -> 1380244.2 | J7: =H7-I7 -> -1130244.2 | L7: =L9 -> 5000 | M7: =H7/$H$9 -> 1 | N7: =J7-L7 -> -1135244.2 | O7: =IF(N7>=0,"OK!","CORRIGIR") -> CORRIGIR
M8: =H8/$H$9 -> 0 | N8: =J8-L8 -> 0 | O8: =IF(N8>=0,"OK!","CORRIGIR") -> OK!
C9: PLANILHA ORÇAMENTÁRIA RESUMO | H9: =SUM(H7:H8) -> 250000 | I9: =SUM(I7:I8) -> 1380244.2 | J9: =H9-I9 -> -1130244.2 | L9: 5000 | M9: =L9/H9 -> 0.02 | N9: =SUM(N7:N8) -> -1135244.2
C11: ITEM | D11: DESCRIÇÃO DOS SERVIÇOS | E11: VALORES (R$) | L11: Valor unitário do Projeto
A13: 1 | B13: 1 | C13: =CONCATENATE(A13,".0") -> 1.0 | D13: =IFERROR(VLOOKUP(C13,'Plan.Orçam.'!F:G,2,FALSE),"") -> QUADRA | E13: =IFERROR(VLOOKUP(C13,'Plan.Orçam.'!F:K,6,FALSE),"") -> 716912.86 | L13: =L9/#REF! -> #REF! | M13: R$/m2
A14: 1 | B14: 1 | C14: 1.1 | D14: =IFERROR(VLOOKUP(C14,'Plan.Orçam.'!F:G,2,FALSE),"") -> SERVIÇOS PRELIMINARES | E14: =IFERROR(VLOOKUP(C14,'Plan.Orçam.'!F:K,6,FALSE),"") -> 12614.55
A15: 1 | B15: 1 | C15: 1.2 | D15: =IFERROR(VLOOKUP(C15,'Plan.Orçam.'!F:G,2,FALSE),"") -> MOVIMENTO DE TERRA | E15: =IFERROR(VLOOKUP(C15,'Plan.Orçam.'!F:K,6,FALSE),"") -> 5269.52
A16: 1 | B16: 1 | C16: 1.3 | D16: =IFERROR(VLOOKUP(C16,'Plan.Orçam.'!F:G,2,FALSE),"") -> INFRA-ESTRUTURA: FUNDAÇÕES (TODA A QUADRA) | E16: =IFERROR(VLOOKUP(C16,'Plan.Orçam.'!F:K,6,FALSE),"") -> 70701.3
A17: 1 | B17: 1 | C17: 1.4 | D17: =IFERROR(VLOOKUP(C17,'Plan.Orçam.'!F:G,2,FALSE),"") -> SUPERESTRUTURA (PILARES, VIGAS E LAJES) - TODA A QUADRA | E17: =IFERROR(VLOOKUP(C17,'Plan.Orçam.'!F:K,6,FALSE),"") -> 55355.09
A18: 1 | B18: 1 | C18: 1.5 | D18: =IFERROR(VLOOKUP(C18,'Plan.Orçam.'!F:G,2,FALSE),"") -> ELEVAÇÃO (murada) | E18: =IFERROR(VLOOKUP(C18,'Plan.Orçam.'!F:K,6,FALSE),"") -> 53748.44
A19: 1 | B19: 1 | C19: 1.6 | D19: =IFERROR(VLOOKUP(C19,'Plan.Orçam.'!F:G,2,FALSE),"") -> ESQUADRIAS | E19: =IFERROR(VLOOKUP(C19,'Plan.Orçam.'!F:K,6,FALSE),"") -> 9576.15
A20: 1 | B20: 1 | C20: 1.7 | D20: =IFERROR(VLOOKUP(C20,'Plan.Orçam.'!F:G,2,FALSE),"") -> COBERTURA | E20: =IFERROR(VLOOKUP(C20,'Plan.Orçam.'!F:K,6,FALSE),"") -> 186119.62
A21: 1 | B21: 1 | C21: 1.8 | D21: =IFERROR(VLOOKUP(C21,'Plan.Orçam.'!F:G,2,FALSE),"") -> REVESTIMENTO DE PAREDES | E21: =IFERROR(VLOOKUP(C21,'Plan.Orçam.'!F:K,6,FALSE),"") -> 21057.62
A22: 1 | B22: 1 | C22: 1.9 | D22: =IFERROR(VLOOKUP(C22,'Plan.Orçam.'!F:G,2,FALSE),"") -> PAVIMENTAÇÃO | E22: =IFERROR(VLOOKUP(C22,'Plan.Orçam.'!F:K,6,FALSE),"") -> 164641.62
A23: 1 | B23: 1 | C23: 1.10 | D23: =IFERROR(VLOOKUP(C23,'Plan.Orçam.'!F:G,2,FALSE),"") -> PINTURA | E23: =IFERROR(VLOOKUP(C23,'Plan.Orçam.'!F:K,6,FALSE),"") -> 55238.83
A24: 1 | B24: 1 | C24: 1.11 | D24: =IFERROR(VLOOKUP(C24,'Plan.Orçam.'!F:G,2,FALSE),"") -> INSTALAÇÃO ELÉTRICA (REFERENTE À TODA QUADRA) | E24: =IFERROR(VLOOKUP(C24,'Plan.Orçam.'!F:K,6,FALSE),"") -> 616.71
A25: 1 | B25: 1 | C25: 1.12 | D25: =IFERROR(VLOOKUP(C25,'Plan.Orçam.'!F:G,2,FALSE),"") -> ELETRODUTOS E ACESSORIOS | E25: =IFERROR(VLOOKUP(C25,'Plan.Orçam.'!F:K,6,FALSE),"") -> 3997.45
... A32: 1 | B32: 1 | C32: 1.19 | D32: =IFERROR(VLOOKUP(C32,'Plan.Orçam.'!F:G,2,FALSE),"") -> SERVIÇOS FINAIS | E32: =IFERROR(VLOOKUP(C32,'Plan.Orçam.'!F:K,6,FALSE),"") -> 35664.47
C33: ='Plan.Orçam.'!F156 -> 2.0 | D33: =IFERROR(VLOOKUP(C33,'Plan.Orçam.'!F:G,2,FALSE),"") -> BANHEIROS E VESTIÁRIOS | E33: =IFERROR(VLOOKUP(C33,'Plan.Orçam.'!F:K,6,FALSE),"") -> 128891.87
C34: 2.1 | D34: =IFERROR(VLOOKUP(C34,'Plan.Orçam.'!F:G,2,FALSE),"") -> MOVIMENTO DE TERRA | E34: =IFERROR(VLOOKUP(C34,'Plan.Orçam.'!F:K,6,FALSE),"") -> 2063.85
C35: 2.2 | D35: =IFERROR(VLOOKUP(C35,'Plan.Orçam.'!F:G,2,FALSE),"") -> INFRA-ESTRUTURA: FUNDAÇÕES | E35: =IFERROR(VLOOKUP(C35,'Plan.Orçam.'!F:K,6,FALSE),"") -> 14715.68
C36: 2.3 | D36: =IFERROR(VLOOKUP(C36,'Plan.Orçam.'!F:G,2,FALSE),"") -> ESTRUTURA | E36: =IFERROR(VLOOKUP(C36,'Plan.Orçam.'!F:K,6,FALSE),"") -> 24642.66
C37: 2.4 | D37: =IFERROR(VLOOKUP(C37,'Plan.Orçam.'!F:G,2,FALSE),"") -> PAREDES E PAINÉIS | E37: =IFERROR(VLOOKUP(C37,'Plan.Orçam.'!F:K,6,FALSE),"") -> 10667.14
C38: 2.5 | D38: =IFERROR(VLOOKUP(C38,'Plan.Orçam.'!F:G,2,FALSE),"") -> REVESTIMENTOS | E38: =IFERROR(VLOOKUP(C38,'Plan.Orçam.'!F:K,6,FALSE),"") -> 33437.27
C39: 2.6 | D39: =IFERROR(VLOOKUP(C39,'Plan.Orçam.'!F:G,2,FALSE),"") -> PISO | E39: =IFERROR(VLOOKUP(C39,'Plan.Orçam.'!F:K,6,FALSE),"") -> 8087.42
C40: 2.7 | D40: =IFERROR(VLOOKUP(C40,'Plan.Orçam.'!F:G,2,FALSE),"") -> ESQUADRIAS | E40: =IFERROR(VLOOKUP(C40,'Plan.Orçam.'!F:K,6,FALSE),"") -> 12472.01
C41: 2.8 | D41: =IFERROR(VLOOKUP(C41,'Plan.Orçam.'!F:G,2,FALSE),"") -> COBERTA | E41: =IFERROR(VLOOKUP(C41,'Plan.Orçam.'!F:K,6,FALSE),"") -> 5137.36
C42: 2.9 | D42: =IFERROR(VLOOKUP(C42,'Plan.Orçam.'!F:G,2,FALSE),"") -> LOUÇAS E METAIS | E42: =IFERROR(VLOOKUP(C42,'Plan.Orçam.'!F:K,6,FALSE),"") -> 10131.68
C43: 2.10 | D43: =IFERROR(VLOOKUP(C43,'Plan.Orçam.'!F:G,2,FALSE),"") -> INSTALAÇÕES HIDRÁULICAS | E43: =IFERROR(VLOOKUP(C43,'Plan.Orçam.'!F:K,6,FALSE),"") -> 3049.76
C44: 2.11 | D44: =IFERROR(VLOOKUP(C44,'Plan.Orçam.'!F:G,2,FALSE),"") -> INSTALAÇÕES SANITÁRIAS | E44: =IFERROR(VLOOKUP(C44,'Plan.Orçam.'!F:K,6,FALSE),"") -> 2596.93
C45: 2.12 | D45: =IFERROR(VLOOKUP(C45,'Plan.Orçam.'!F:G,2,FALSE),"") -> INSTALAÇÕES ELÉTRICAS | E45: =IFERROR(VLOOKUP(C45,'Plan.Orçam.'!F:K,6,FALSE),"") -> 1890.11

Sheet QCI
L2: Quadro de Composição do Investimento - QCI - OGU -
L3: Setor Público
B6: Empreendimento
B8: =BDI!C7 -> CONSTRUÇÃO DE QUADRA POLIESPORTIVA COM VESTIÁRIOS E BANHEIROS, NO MUNICÍPIO DE COREMAS/PB | AK8: Valor do Repasse | AL8: =AD54 -> 845804.73 | AN8: =AL8*1.04 -> 879636.92
B10: Agente executor | AK10: Valor da Contrapartida
B12: =BDI!C5 -> Município de Coremas- PB | AK12: Valor do Investimento | AL12: =AL10+AL8 -> 845804.73
B14: Programa | R14: Modalidade | AK14: Percentual de contrapartida: | AL14: =AK54 -> 0
B16: =BDI!C3 -> Esporte, Cidadania e Desenvolvimento | AK16: Percentual União | AL16: =AL8/AL12 -> 1
B18: Item | D18: Discriminação | O18: Investimento total (R$) | AK18: 1- SEPARAR POR RUAS, QUANDO HOUVER MAIS DE UMA; 2- NÃO NECESSITA DISCRMINAR OS SERVIÇOS.
O19: Recursos Estado | T19: Prefeitura | Y19: Outras fontes | AD19: Total
B20: 1.0 | D20: ='Plan. Orçam. Resumo'!D13 -> QUADRA
A21: 1 | B21: 1.1 | D21: =IFERROR(VLOOKUP(B21,'Plan.Orçam.'!F:K,2,FALSE),"") -> SERVIÇOS PRELIMINARES | O21: =IFERROR(AD21-T21,"") -> 12614.55 | T21: =IFERROR($AL$14*AD21,"") -> 0 | AD21: =IFERROR(VLOOKUP(B21,'Plan.Orçam.'!F:K,6,FALSE),"") -> 12614.55
A22: 2 | B22: 1.2 | D22: =IFERROR(VLOOKUP(B22,'Plan.Orçam.'!F:K,2,FALSE),"") -> MOVIMENTO DE TERRA | O22: =IFERROR(AD22-T22,"") -> 5269.52 | T22: =IFERROR($AL$14*AD22,"") -> 0 | AD22: =IFERROR(VLOOKUP(B22,'Plan.Orçam.'!F:K,6,FALSE),"") -> 5269.52
A23: 3 | B23: 1.3 | D23: =IFERROR(VLOOKUP(B23,'Plan.Orçam.'!F:K,2,FALSE),"") -> INFRA-ESTRUTURA: FUNDAÇÕES (TODA A QUADRA) | O23: =IFERROR(AD23-T23,"") -> 70701.3 | T23: =IFERROR($AL$14*AD23,"") -> 0 | AD23: =IFERROR(VLOOKUP(B23,'Plan.Orçam.'!F:K,6,FALSE),"") -> 70701.3
A24: 4 | B24: 1.4 | D24: =IFERROR(VLOOKUP(B24,'Plan.Orçam.'!F:K,2,FALSE),"") -> SUPERESTRUTURA (PILARES, VIGAS E LAJES) - TODA A QUADRA | O24: =IFERROR(AD24-T24,"") -> 55355.09 | T24: =IFERROR($AL$14*AD24,"") -> 0 | AD24: =IFERROR(VLOOKUP(B24,'Plan.Orçam.'!F:K,6,FALSE),"") -> 55355.09
A25: 5 | B25: 1.5 | D25: =IFERROR(VLOOKUP(B25,'Plan.Orçam.'!F:K,2,FALSE),"") -> ELEVAÇÃO (murada) | O25: =IFERROR(AD25-T25,"") -> 53748.44 | T25: =IFERROR($AL$14*AD25,"") -> 0 | AD25: =IFERROR(VLOOKUP(B25,'Plan.Orçam.'!F:K,6,FALSE),"") -> 53748.44
A26: 6 | B26: 1.6 | D26: =IFERROR(VLOOKUP(B26,'Plan.Orçam.'!F:K,2,FALSE),"") -> ESQUADRIAS | O26: =IFERROR(AD26-T26,"") -> 9576.15 | T26: =IFERROR($AL$14*AD26,"") -> 0 | AD26: =IFERROR(VLOOKUP(B26,'Plan.Orçam.'!F:K,6,FALSE),"") -> 9576.15
A27: 7 | B27: 1.7 | D27: =IFERROR(VLOOKUP(B27,'Plan.Orçam.'!F:K,2,FALSE),"") -> COBERTURA | O27: =IFERROR(AD27-T27,"") -> 186119.62 | T27: =IFERROR($AL$14*AD27,"") -> 0 | AD27: =IFERROR(VLOOKUP(B27,'Plan.Orçam.'!F:K,6,FALSE),"") -> 186119.62
A28: 8 | B28: 1.8 | D28: =IFERROR(VLOOKUP(B28,'Plan.Orçam.'!F:K,2,FALSE),"") -> REVESTIMENTO DE PAREDES | O28: =IFERROR(AD28-T28,"") -> 21057.62 | T28: =IFERROR($AL$14*AD28,"") -> 0 | AD28: =IFERROR(VLOOKUP(B28,'Plan.Orçam.'!F:K,6,FALSE),"") -> 21057.62
A29: 9 | B29: 1.9 | D29: =IFERROR(VLOOKUP(B29,'Plan.Orçam.'!F:K,2,FALSE),"") -> PAVIMENTAÇÃO | O29: =IFERROR(AD29-T29,"") -> 164641.62 | T29: =IFERROR($AL$14*AD29,"") -> 0 | AD29: =IFERROR(VLOOKUP(B29,'Plan.Orçam.'!F:K,6,FALSE),"") -> 164641.62
A30: 10 | B30: 1.10 | D30: =IFERROR(VLOOKUP(B30,'Plan.Orçam.'!F:K,2,FALSE),"") -> PINTURA | O30: =IFERROR(AD30-T30,"") -> 55238.83 | T30: =IFERROR($AL$14*AD30,"") -> 0 | AD30: =IFERROR(VLOOKUP(B30,'Plan.Orçam.'!F:K,6,FALSE),"") -> 55238.83
A31: 11 | B31: 1.11 | D31: =IFERROR(VLOOKUP(B31,'Plan.Orçam.'!F:K,2,FALSE),"") -> INSTALAÇÃO ELÉTRICA (REFERENTE À TODA QUADRA) | O31: =IFERROR(AD31-T31,"") -> 616.71 | T31: =IFERROR($AL$14*AD31,"") -> 0 | AD31: =IFERROR(VLOOKUP(B31,'Plan.Orçam.'!F:K,6,FALSE),"") -> 616.71
