Workbook
Name activatedados.form2: IF(ISNUMBER(Eventograma_e_Quantitativos!$K1),Eventograma_e_Quantitativos!$K1&"-"&INDEX(Eventos,Eventograma_e_Quantitativos!$K1,2),"")
Name artExec: DADOS!$D$26
Name artFiscal: DADOS!$D$23
Name cargoTomador: DADOS!$C$30
Name creaExec: DADOS!$C$26
Name creaFiscal: DADOS!$C$23
Name creaPLE: DADOS!$C$20
Name Cronograma: Cronograma!$B$38:$BB$43
Name Cronograma.LinhaPadrão: Cronograma!$19:$19
Name Cronograma.MesesQuadro: COUNTA(OFFSET(Cronograma,0,0,,1))*4
Name Cronograma.NumPeríodos: MAX(Cronograma.Períodos)
Name Cronograma.Padrão: Cronograma!$B$38:$BB$43
Name Cronograma.Períodos: OFFSET(Cronograma!$E$33,1,0):OFFSET(Cronograma!$BB$38,-1,0)
Name Cronograma.Períodos.LinhaPadrão: Cronograma!$B$19:$BB$19
Name CronoPrev: OFFSET(CronoPrev!$B$13,1,0):OFFSET(CronoPrev!$G$26,-1,0)
Name CronoPrev.LinhaPadrão: CronoPrev!$B$8:$G$8
Name DADOS.LinhaPadrão: DADOS!$A$1:$C$1
Name dataInicioObra: DADOS!$H$13
Name deactivatedados.form1: IF(Eventograma_e_Quantitativos!B1="","",VALUE(LEFT(Eventograma_e_Quantitativos!B1,(FIND("-",Eventograma_e_Quantitativos!B1,1))-1)))
Name Detalhamento: OFFSET(Detalhamento!$A$16,1,0):OFFSET(Detalhamento!$A$40,-1,0)
Name Detalhamento.Filtro: Detalhamento!$A$16:$J$16
Name Detalhamento.Imprimir: Detalhamento!$E$2:OFFSET(Detalhamento!$K$43,0,MAX(TRUNC(numFrentes/6,0)+IF(MOD(numFrentes,6)<>0,1,0),1)*6)
Name Detalhamento.LinhaPadrão: Detalhamento!$1:$1
Name Detalhamento.OpçãoServiços: Detalhamento!$B$12
Name Detalhamento.OpçõesExibição: Detalhamento!$B$6:$B$7
Name Detalhamento.OpçõesServiços: Detalhamento!$B$9:$B$11
Name Eventograma_e_Quantitativos.Imprimir: Eventograma_e_Quantitativos!$C$4:OFFSET(Eventograma_e_Quantitativos!$M$44,0,MAX(TRUNC(numFrentes/6,0)+IF(MOD(numFrentes,6)<>0,1,0),1)*6)
Name Eventograma_e_Quantitativos.LinhaPadrão: Eventograma_e_Quantitativos!$1:$1
Name Eventos: OFFSET(DADOS!$A$33,1,0):OFFSET(DADOS!$C$38,-1,0)
Name EventosVariaveis: OFFSET(DADOS!$A$34,1,0):OFFSET(DADOS!$C$38,-1,0)
Name FaltaEvento: Eventograma_e_Quantitativos!$B$16
Name hoje: TODAY()
Name Import.Ação: DADOS!$F$7
Name Import.CNPJ: DADOS!$D$13
Name Import.Convênio: DADOS!$B$7
Name Import.CR: DADOS!$A$7
Name Import.CTEF: DADOS!$A$13
Name Import.DataAssinaturaCR: DADOS!$H$7
Name Import.DataInícioObra: DADOS!$H$13
Name Import.Descrição: Eventograma_e_Quantitativos!$E$18:$E$35
Name Import.Empresa: DADOS!$B$13
Name Import.FrenteDeObra: Eventograma_e_Quantitativos!$N$15:$BK$15
Name Import.Gestor: DADOS!$D$7
Name Import.Gigov: DADOS!$C$7
Name Import.Item: OFFSET(Eventograma_e_Quantitativos!$D$17,1,0):OFFSET(Eventograma_e_Quantitativos!$D$37,-1,0)
Name Import.Localidade: DADOS!$E$10
Name Import.Município: DADOS!$D$10
Name Import.numEventos: OFFSET(Eventograma_e_Quantitativos!$K$17,1,0):OFFSET(Eventograma_e_Quantitativos!$K$37,-1,0)
Name Import.ObjetoCR: DADOS!$F$10
Name Import.ObjetoCTEF: DADOS!$E$13
Name Import.PLE: OFFSET(PLE!$E$33,1,0):OFFSET(PLE!$BB$38,-1,0)
Name Import.PLQ: OFFSET(Eventograma_e_Quantitativos!$N$17,1,0):OFFSET(Eventograma_e_Quantitativos!$BK$37,-1,0)
Name Import.PreçoTotal: OFFSET(Eventograma_e_Quantitativos!$I$17,1,0):OFFSET(Eventograma_e_Quantitativos!$I$37,-1,0)
Name Import.Programa: DADOS!$E$7
Name Import.Proponente: DADOS!$A$10
Name Import.Unidade: OFFSET(Eventograma_e_Quantitativos!$F$17,1,0):OFFSET(Eventograma_e_Quantitativos!$F$37,-1,0)
Name Item: Eventograma_e_Quantitativos!$D1
Name LForçamento: OFFSET(Eventograma_e_Quantitativos!$37:$37,-1,0)
Name LIorçamento: OFFSET(Eventograma_e_Quantitativos!$17:$17,1,0)
Name mais_um: OFFSET(Detalhamento!A1,-1,0)+1

Sheet DADOS
A1: =OFFSET(A1,-1,0)+1 -> #REF! | J1: =CONCATENATE(A1,"-",B1) -> #REF!
A2: 27477 | B2: PLE - Planilha de Levantamento de Eventos
A3: v006
A6: Nº OPERAÇÃO | B6: Nº SICONV | C6: GIGOV | D6: GESTOR | E6: PROGRAMA | F6: AÇÃO / MODALIDADE | H6: DATA ASSINATURA
A7: 1080659-09 | B7: 923417/2021 | C7: JOÃO PESSOA | D7: MDR | E7: DESENVOLVIMENTO REGIONAL, TERRITORIAL E URBANO | F7: APOIO À POLITICA NACIONAL DE DESENVOLVIMENTO URBANO | H7: 44498
A9: PROPONENTE / TOMADOR | D9: MUNICÍPIO / UF | E9: LOCALIDADE / ENDEREÇO | F9: OBJETO
A10: PREFEITURA MUNICIPAL DE COREMAS | D10: COREMAS/PB | E10: ZONA URBANO | F10: PAVIMENTAÇÃO EM PARALELEPÍPEDO
A12: Nº CTEF | B12: EMPRESA EXECUTORA | D12: CNPJ | E12: OBJETO DO CTEF | H12: INÍCIO DA OBRA
A18: RESPONSÁVEIS TÉCNICOS:
A19: Elaboração do documento | C19: CREA/CAU
A22: Fiscalização | C22: CREA/CAU | D22: ART/RRT
A23: FERNANDO
A25: Execução | C25: CREA/CAU | D25: ART/RRT
A28: REPRESENTANTE TOMADOR / AG. PROMOTOR / TOMADOR
A29: Nome | C29: Cargo
A32: EVENTOS
A33: Núm do Evento | B33: Título do Evento
A34: 1 | B34: Administração Local | J34: =CONCATENATE(A34,"-",B34) -> 1-Administração Local
A35: =OFFSET(A35,-1,0)+1 -> 2 | B35: PAVIMENTAÇÃO | J35: =CONCATENATE(A35,"-",B35) -> 2-PAVIMENTAÇÃO
A36: =OFFSET(A36,-1,0)+1 -> 3 | B36: CALÇADAS E RAMPAS | J36: =CONCATENATE(A36,"-",B36) -> 3-CALÇADAS E RAMPAS
A37: =OFFSET(A37,-1,0)+1 -> 4 | B37: SINALIZAÇÃO E SERVIÇOS FINAIS | J37: =CONCATENATE(A37,"-",B37) -> 4-SINALIZAÇÃO E SERVIÇOS FINAIS
A40: INSTRUÇÕES DE USO E PREENCHIMENTO
A42: Informações gerais:
A44: 1. Este documento somente pode ser utilizado nas versões do Excel 2003 ou superior. Não devem ser utilizadas versões do BROffice.
A46: 2. Para funcionamento pleno desse arquivo, a Segurança de Macros do Excel deve ser habilitada.
A48: a. Na Versão Excel 2003, selecione na Faixa de Opções: Ferramentas --> Macro --> Segurança --> Na aba Nível de Segurança selecione a Opção "Baixo" --> Clique em OK --> Feche e abra o Excel novamente para utilizar a Planilha.
A49: b. Na Versão Excel 2007 ou superior, selecione na Faixa de Opções: Arquivo --> Opções --> Central de Confiabilidade --> Configurações da Central de Confiabilidade --> Configurações de Macro --> Habilitar todas as Macros --> Clique em OK --> Feche e abra o excel novamente para utilizar a Planilha.
A51: 3. O Preenchimento deve ser feito somente nas células em amarelo. As demais células são de preenchimento Automático e estão bloqueadas para edição.
A53: Instruções de preenchimento:
A55: Aba DADOS
A57: 1º passo: Na aba Dados, preencher os dados do contrato e identificação dos responsáveis;
A59: 2º passo: Incluir e nomear os eventos (pode ser alterado posteriormente também);
A61: Aba EVENTOGRAMA E QUANTITATIVOS
... A125: VT - VITORIA

Sheet Eventograma_e_Quantitativos
B1: =ROW(Nível)-ROW(LIorçamento)+1 -> -16 | C1: =IF(D1="","",IF(ISNUMBER(VALUE(D1)),"Meta",IF(AND(F1<>"",I1<>""),"Serviço","Nível"))) | G1: =IF(Nível="Serviço",SUMIF($N$15:$BK$15,"<>"&"",N1:BK1),"") | H1: =IF(AND(ISNUMBER(G1),G1<>0),I1/G1,IF(G1=0,0,"")) | K1: =IF(L1="","",VALUE(LEFT(L1,(FIND("-",L1,1))-1))) | BM1: =IF(N$15="",0,IF(ISNUMBER(PreçoUnit),PreçoUnit*INDEX(Import.PLQ,$B1,BM$16),0)) -> 0 | BN1: =IF(O$15="",0,IF(ISNUMBER(PreçoUnit),PreçoUnit*INDEX(Import.PLQ,$B1,BN$16),0)) -> 0 | BO1: =IF(P$15="",0,IF(ISNUMBER(PreçoUnit),PreçoUnit*INDEX(Import.PLQ,$B1,BO$16),0)) -> 0 | BP1: =IF(Q$15="",0,IF(ISNUMBER(PreçoUnit),PreçoUnit*INDEX(Import.PLQ,$B1,BP$16),0)) -> 0 | BQ1: =IF(R$15="",0,IF(ISNUMBER(PreçoUnit),PreçoUnit*INDEX(Import.PLQ,$B1,BQ$16),0)) -> 0 | BR1: =IF(S$15="",0,IF(ISNUMBER(PreçoUnit),PreçoUnit*INDEX(Import.PLQ,$B1,BR$16),0)) -> 0 | BS1: =IF(T$15="",0,IF(ISNUMBER(PreçoUnit),PreçoUnit*INDEX(Import.PLQ,$B1,BS$16),0)) -> 0 | BT1: =IF(U$15="",0,IF(ISNUMBER(PreçoUnit),PreçoUnit*INDEX(Import.PLQ,$B1,BT$16),0)) -> 0 | ... DJ1: =IF(BK$15="",0,IF(ISNUMBER(PreçoUnit),PreçoUnit*INDEX(Import.PLQ,$B1,DJ$16),0)) -> 0 | DK1: =IF(D1="",0,IF(ISNUMBER(VALUE(D1)),VALUE(D1),LEFT(D1,FIND(".",D1)-1))) -> 0 | DL1: =SUM(DM1:FJ1) -> 0 | DM1: =IF($K1<>1,IF(ISNUMBER(INDEX(Import.PLE,$K1,DM$16)),IF(INDEX(Import.PLE,$K1,DM$16)<=mediçao,BM1,0),0),PLE!$AA$28*BM1) -> 0 | DN1: =IF($K1<>1,IF(ISNUMBER(INDEX(Import.PLE,$K1,DN$16)),IF(INDEX(Import.PLE,$K1,DN$16)<=mediçao,BN1,0),0),PLE!$AA$28*BN1) -> 0 | DO1: =IF($K1<>1,IF(ISNUMBER(INDEX(Import.PLE,$K1,DO$16)),IF(INDEX(Import.PLE,$K1,DO$16)<=mediçao,BO1,0),0),PLE!$AA$28*BO1) -> 0 | DP1: =IF($K1<>1,IF(ISNUMBER(INDEX(Import.PLE,$K1,DP$16)),IF(INDEX(Import.PLE,$K1,DP$16)<=mediçao,BP1,0),0),PLE!$AA$28*BP1) -> 0 | DQ1: =IF($K1<>1,IF(ISNUMBER(INDEX(Import.PLE,$K1,DQ$16)),IF(INDEX(Import.PLE,$K1,DQ$16)<=mediçao,BQ1,0),0),PLE!$AA$28*BQ1) -> 0 | DR1: =IF($K1<>1,IF(ISNUMBER(INDEX(Import.PLE,$K1,DR$16)),IF(INDEX(Import.PLE,$K1,DR$16)<=mediçao,BR1,0),0),PLE!$AA$28*BR1) -> 0 | DS1: =IF($K1<>1,IF(ISNUMBER(INDEX(Import.PLE,$K1,DS$16)),IF(INDEX(Import.PLE,$K1,DS$16)<=mediçao,BS1,0),0),PLE!$AA$28*BS1) -> 0 | DT1: =IF($K1<>1,IF(ISNUMBER(INDEX(Import.PLE,$K1,DT$16)),IF(INDEX(Import.PLE,$K1,DT$16)<=mediçao,BT1,0),0),PLE!$AA$28*BT1) -> 0 | ... FJ1: =IF($K1<>1,IF(ISNUMBER(INDEX(Import.PLE,$K1,FJ$16)),IF(INDEX(Import.PLE,$K1,FJ$16)<=mediçao,DJ1,0),0),PLE!$AA$28*DJ1) -> 0
B3: =ROW(Nível)-ROW(LIorçamento)+1 -> -14 | C3: Evento | D3: Evento | E3: =INDEX(Eventos,K3,2) -> #VALUE! | F3: R$ | G3: =IF(Nível="Serviço",SUMIF($N$15:$BK$15,"<>"&"",N3:BK3),"") | H3: =IF(AND(ISNUMBER(G3),G3<>0),I3/G3,IF(G3=0,0,"")) | I3: =SUM(N3:BK3) -> 0 | K3: =INDEX(Eventos,ROW(Nível)-ROW(LForçamento),1) -> #VALUE! | L3: =IF(AND(NumEvento<>"",Nível="Serviço"),INDEX(Eventos,NumEvento,2),"") -> #VALUE! | N3: =IF(N$15="",0,SUMIF(Import.numEventos,$K3,OFFSET(PreçoServiçoPorFrente,0,N$16-1,,1))) -> 0 | O3: =IF(O$15="",0,SUMIF(Import.numEventos,$K3,OFFSET(PreçoServiçoPorFrente,0,O$16-1,,1))) -> 0 | P3: =IF(P$15="",0,SUMIF(Import.numEventos,$K3,OFFSET(PreçoServiçoPorFrente,0,P$16-1,,1))) -> 0 | Q3: =IF(Q$15="",0,SUMIF(Import.numEventos,$K3,OFFSET(PreçoServiçoPorFrente,0,Q$16-1,,1))) -> 0 | R3: =IF(R$15="",0,SUMIF(Import.numEventos,$K3,OFFSET(PreçoServiçoPorFrente,0,R$16-1,,1))) -> 0 | S3: =IF(S$15="",0,SUMIF(Import.numEventos,$K3,OFFSET(PreçoServiçoPorFrente,0,S$16-1,,1))) -> 0 | T3: =IF(T$15="",0,SUMIF(Import.numEventos,$K3,OFFSET(PreçoServiçoPorFrente,0,T$16-1,,1))) -> 0 | U3: =IF(U$15="",0,SUMIF(Import.numEventos,$K3,OFFSET(PreçoServiçoPorFrente,0,U$16-1,,1))) -> 0 | ... BK3: =IF(BK$15="",0,SUMIF(Import.numEventos,$K3,OFFSET(PreçoServiçoPorFrente,0,BK$16-1,,1))) -> 0
E4: PLE - Planilha de Levantamento de Eventos Eventograma e Quantitativos | R4: Grau de Sigilo #PUBLICO | X4: Grau de Sigilo #PUBLICO | AD4: Grau de Sigilo #PUBLICO | AJ4: Grau de Sigilo #PUBLICO | AP4: Grau de Sigilo #PUBLICO | AV4: Grau de Sigilo #PUBLICO | BB4: Grau de Sigilo #PUBLICO | BH4: Grau de Sigilo #PUBLICO
BM14: Preço do Serviço por frente | DM14: Preço dos Serviços executados
C15: ="Valor Total do Orçamento: R$ "&TEXT(SUMIF(C18:C40,"Serviço",I18:I40),"#.#0,00") -> Valor Total do Orçamento: R$ 797.972,21 | L15: Frentes de Obra: | N15: Rua Oficial de Justiça Vicente Gregório Antão | O15: Rua Francisca Garrido de Sousa | P15: Rua Francisco Batista Silva | Q15: Rua Bartolomeu Buriti | R15: Rua Maria Farias de Assis | S15: Rua Roberto Wilson Moura | T15: Rua Cícero Eufrásio da Silva | U15: Rua Firmino da Silva Lacerda
B16: =COUNTA(OFFSET(Eventograma_e_Quantitativos!$K$17,1,0):OFFSET(Eventograma_e_Quantitativos!$K$37,-1,0))-COUNTBLANK(OFFSET(Eventograma_e_Quantitativos!$L$17,1,0):OFFSET(Eventograma_e_Quantitativos!$L$37,-1,0))<COUNTIF(OFFSET(Eventograma_e_Quantitativos!$C$17,1,0):OFFSET(Eventograma_e_Quantitativos!$C$37,-1,0),"Serviço") -> FALSE | C16: Nível | D16: Item | E16: Descrição | F16: Unid. | G16: Qtde. | H16: Preço Unit. (R$) | I16: Preço Total (R$) | K16: Núm. Evento | L16: Agrupador de Eventos | N16: 1 | O16: 2 | P16: 3 | Q16: 4 | R16: 5 | S16: 6 | T16: 7 | U16: 8 | V16: 9 | W16: 10 | X16: 11 | Y16: 12 | Z16: 13 | AA16: 14 | AB16: 15 | AC16: 16 | AD16: 17 | AE16: 18 | AF16: 19 | AG16: 20 | AH16: 21 | AI16: 22 | AJ16: 23 | AK16: 24 | AL16: 25 | AM16: 26 | AN16: 27 | AO16: 28 | AP16: 29 | AQ16: 30 | AR16: 31 | AS16: 32 | AT16: 33 | AU16: 34 | AV16: 35 | AW16: 36 | AX16: 37 | AY16: 38 | AZ16: 39 | BA16: 40 | BB16: 41 | BC16: 42 | BD16: 43 | BE16: 44 | BF16: 45 | BG16: 46 | BH16: 47 | BI16: 48 | BJ16: 49 | BK16: 50 | BM16: 1 | BN16: 2 | BO16: 3 | BP16: 4 | BQ16: 5 | BR16: 6 | BS16: 7 | BT16: 8 | BU16: 9 | BV16: 10 | BW16: 11 | BX16: 12 | BY16: 13 | BZ16: 14 | CA16: 15 | CB16: 16 | CC16: 17 | CD16: 18 | CE16: 19 | CF16: 20 | CG16: 21 | CH16: 22 | CI16: 23 | CJ16: 24 | CK16: 25 | CL16: 26 | CM16: 27 | CN16: 28 | CO16: 29 | CP16: 30 | CQ16: 31 | CR16: 32 | CS16: 33 | CT16: 34 | CU16: 35 | CV16: 36 | CW16: 37 | CX16: 38 | CY16: 39 | CZ16: 40 | DA16: 41 | DB16: 42 | DC16: 43 | DD16: 44 | DE16: 45 | DF16: 46 | DG16: 47 | DH16: 48 | DI16: 49 | DJ16: 50 | DK16: meta | DM16: 1 | DN16: 2 | DO16: 3 | DP16: 4 | DQ16: 5 | DR16: 6 | DS16: 7 | DT16: 8 | DU16: 9 | DV16: 10 | DW16: 11 | DX16: 12 | DY16: 13 | DZ16: 14 | EA16: 15 | EB16: 16 | EC16: 17 | ED16: 18 | EE16: 19 | EF16: 20 | EG16: 21 | EH16: 22 | EI16: 23 | EJ16: 24 | EK16: 25 | EL16: 26 | EM16: 27 | EN16: 28 | EO16: 29 | EP16: 30 | EQ16: 31 | ER16: 32 | ES16: 33 | ET16: 34 | EU16: 35 | EV16: 36 | EW16: 37 | EX16: 38 | EY16: 39 | EZ16: 40 | FA16: 41 | FB16: 42 | FC16: 43 | FD16: 44 | FE16: 45 | FF16: 46 | FG16: 47 | FH16: 48 | FI16: 49 | FJ16: 50
B18: =ROW(Nível)-ROW(LIorçamento)+1 -> 1 | C18: =IF(D18="","",IF(ISNUMBER(VALUE(D18)),"Meta",IF(AND(F18<>"",I18<>""),"Serviço","Nível"))) -> Nível | D18: I | E18: PAVIMENTAÇÃO DE RUAS | G18: =IF(Nível="Serviço",SUMIF($N$15:$BK$15,"<>"&"",N18:BK18),"") | H18: =IF(AND(ISNUMBER(G18),G18<>0),I18/G18,IF(G18=0,0,"")) | K18: =deactivatedados.form1 | BM18: =IF(N$15="",0,IF(ISNUMBER(PreçoUnit),PreçoUnit*INDEX(Import.PLQ,$B18,BM$16),0)) -> 0 | BN18: =IF(O$15="",0,IF(ISNUMBER(PreçoUnit),PreçoUnit*INDEX(Import.PLQ,$B18,BN$16),0)) -> 0 | BO18: =IF(P$15="",0,IF(ISNUMBER(PreçoUnit),PreçoUnit*INDEX(Import.PLQ,$B18,BO$16),0)) -> 0 | BP18: =IF(Q$15="",0,IF(ISNUMBER(PreçoUnit),PreçoUnit*INDEX(Import.PLQ,$B18,BP$16),0)) -> 0 | BQ18: =IF(R$15="",0,IF(ISNUMBER(PreçoUnit),PreçoUnit*INDEX(Import.PLQ,$B18,BQ$16),0)) -> 0 | BR18: =IF(S$15="",0,IF(ISNUMBER(PreçoUnit),PreçoUnit*INDEX(Import.PLQ,$B18,BR$16),0)) -> 0 | BS18: =IF(T$15="",0,IF(ISNUMBER(PreçoUnit),PreçoUnit*INDEX(Import.PLQ,$B18,BS$16),0)) -> 0 | BT18: =IF(U$15="",0,IF(ISNUMBER(PreçoUnit),PreçoUnit*INDEX(Import.PLQ,$B18,BT$16),0)) -> 0 | ... DJ18: =IF(BK$15="",0,IF(ISNUMBER(PreçoUnit),PreçoUnit*INDEX(Import.PLQ,$B18,DJ$16),0)) -> 0 | DK18: =IF(D18="",0,IF(ISNUMBER(VALUE(D18)),VALUE(D18),LEFT(D18,FIND(".",D18)-1))) -> #VALUE! | DL18: =SUM(DM18:FJ18) -> 0 | DM18: =IF($K18<>1,IF(ISNUMBER(INDEX(Import.PLE,$K18,DM$16)),IF(INDEX(Import.PLE,$K18,DM$16)<=mediçao,BM18,0),0),PLE!$AA$28*BM18) -> 0 | DN18: =IF($K18<>1,IF(ISNUMBER(INDEX(Import.PLE,$K18,DN$16)),IF(INDEX(Import.PLE,$K18,DN$16)<=mediçao,BN18,0),0),PLE!$AA$28*BN18) -> 0 | DO18: =IF($K18<>1,IF(ISNUMBER(INDEX(Import.PLE,$K18,DO$16)),IF(INDEX(Import.PLE,$K18,DO$16)<=mediçao,BO18,0),0),PLE!$AA$28*BO18) -> 0 | DP18: =IF($K18<>1,IF(ISNUMBER(INDEX(Import.PLE,$K18,DP$16)),IF(INDEX(Import.PLE,$K18,DP$16)<=mediçao,BP18,0),0),PLE!$AA$28*BP18) -> 0 | DQ18: =IF($K18<>1,IF(ISNUMBER(INDEX(Import.PLE,$K18,DQ$16)),IF(INDEX(Import.PLE,$K18,DQ$16)<=mediçao,BQ18,0),0),PLE!$AA$28*BQ18) -> 0 | DR18: =IF($K18<>1,IF(ISNUMBER(INDEX(Import.PLE,$K18,DR$16)),IF(INDEX(Import.PLE,$K18,DR$16)<=mediçao,BR18,0),0),PLE!$AA$28*BR18) -> 0 | DS18: =IF($K18<>1,IF(ISNUMBER(INDEX(Import.PLE,$K18,DS$16)),IF(INDEX(Import.PLE,$K18,DS$16)<=mediçao,BS18,0),0),PLE!$AA$28*BS18) -> 0 | DT18: =IF($K18<>1,IF(ISNUMBER(INDEX(Import.PLE,$K18,DT$16)),IF(INDEX(Import.PLE,$K18,DT$16)<=mediçao,BT18,0),0),PLE!$AA$28*BT18) -> 0 | ... FJ18: =IF($K18<>1,IF(ISNUMBER(INDEX(Import.PLE,$K18,FJ$16)),IF(INDEX(Import.PLE,$K18,FJ$16)<=mediçao,DJ18,0),0),PLE!$AA$28*DJ18) -> 0
B19: =ROW(Nível)-ROW(LIorçamento)+1 -> 2 | C19: =IF(D19="","",IF(ISNUMBER(VALUE(D19)),"Meta",IF(AND(F19<>"",I19<>""),"Serviço","Nível"))) -> Meta | D19: 1 | E19: SERVIÇOS PRELIMINARES | G19: =IF(Nível="Serviço",SUMIF($N$15:$BK$15,"<>"&"",N19:BK19),"") | H19: =IF(AND(ISNUMBER(G19),G19<>0),I19/G19,IF(G19=0,0,"")) | K19: =deactivatedados.form1 | BM19: =IF(N$15="",0,IF(ISNUMBER(PreçoUnit),PreçoUnit*INDEX(Import.PLQ,$B19,BM$16),0)) -> 0 | BN19: =IF(O$15="",0,IF(ISNUMBER(PreçoUnit),PreçoUnit*INDEX(Import.PLQ,$B19,BN$16),0)) -> 0 | BO19: =IF(P$15="",0,IF(ISNUMBER(PreçoUnit),PreçoUnit*INDEX(Import.PLQ,$B19,BO$16),0)) -> 0 | BP19: =IF(Q$15="",0,IF(ISNUMBER(PreçoUnit),PreçoUnit*INDEX(Import.PLQ,$B19,BP$16),0)) -> 0 | BQ19: =IF(R$15="",0,IF(ISNUMBER(PreçoUnit),PreçoUnit*INDEX(Import.PLQ,$B19,BQ$16),0)) -> 0 | BR19: =IF(S$15="",0,IF(ISNUMBER(PreçoUnit),PreçoUnit*INDEX(Import.PLQ,$B19,BR$16),0)) -> 0 | BS19: =IF(T$15="",0,IF(ISNUMBER(PreçoUnit),PreçoUnit*INDEX(Import.PLQ,$B19,BS$16),0)) -> 0 | BT19: =IF(U$15="",0,IF(ISNUMBER(PreçoUnit),PreçoUnit*INDEX(Import.PLQ,$B19,BT$16),0)) -> 0 | ... DJ19: =IF(BK$15="",0,IF(ISNUMBER(PreçoUnit),PreçoUnit*INDEX(Import.PLQ,$B19,DJ$16),0)) -> 0 | DK19: =IF(D19="",0,IF(ISNUMBER(VALUE(D19)),VALUE(D19),LEFT(D19,FIND(".",D19)-1))) -> 1 | DL19: =SUM(DM19:FJ19) -> 0 | DM19: =IF($K19<>1,IF(ISNUMBER(INDEX(Import.PLE,$K19,DM$16)),IF(INDEX(Import.PLE,$K19,DM$16)<=mediçao,BM19,0),0),PLE!$AA$28*BM19) -> 0 | DN19: =IF($K19<>1,IF(ISNUMBER(INDEX(Import.PLE,$K19,DN$16)),IF(INDEX(Import.PLE,$K19,DN$16)<=mediçao,BN19,0),0),PLE!$AA$28*BN19) -> 0 | DO19: =IF($K19<>1,IF(ISNUMBER(INDEX(Import.PLE,$K19,DO$16)),IF(INDEX(Import.PLE,$K19,DO$16)<=mediçao,BO19,0),0),PLE!$AA$28*BO19) -> 0 | DP19: =IF($K19<>1,IF(ISNUMBER(INDEX(Import.PLE,$K19,DP$16)),IF(INDEX(Import.PLE,$K19,DP$16)<=mediçao,BP19,0),0),PLE!$AA$28*BP19) -> 0 | DQ19: =IF($K19<>1,IF(ISNUMBER(INDEX(Import.PLE,$K19,DQ$16)),IF(INDEX(Import.PLE,$K19,DQ$16)<=mediçao,BQ19,0),0),PLE!$AA$28*BQ19) -> 0 | DR19: =IF($K19<>1,IF(ISNUMBER(INDEX(Import.PLE,$K19,DR$16)),IF(INDEX(Import.PLE,$K19,DR$16)<=mediçao,BR19,0),0),PLE!$AA$28*BR19) -> 0 | DS19: =IF($K19<>1,IF(ISNUMBER(INDEX(Import.PLE,$K19,DS$16)),IF(INDEX(Import.PLE,$K19,DS$16)<=mediçao,BS19,0),0),PLE!$AA$28*BS19) -> 0 | DT19: =IF($K19<>1,IF(ISNUMBER(INDEX(Import.PLE,$K19,DT$16)),IF(INDEX(Import.PLE,$K19,DT$16)<=mediçao,BT19,0),0),PLE!$AA$28*BT19) -> 0 | ... FJ19: =IF($K19<>1,IF(ISNUMBER(INDEX(Import.PLE,$K19,FJ$16)),IF(INDEX(Import.PLE,$K19,FJ$16)<=mediçao,DJ19,0),0),PLE!$AA$28*DJ19) -> 0
B20: =ROW(Nível)-ROW(LIorçamento)+1 -> 3 | C20: =IF(D20="","",IF(ISNUMBER(VALUE(D20)),"Meta",IF(AND(F20<>"",I20<>""),"Serviço","Nível"))) -> Serviço | D20: 1.1 | E20: Placa indicativa da obra em chapa de aço galvanizado (4,0m x 2,0m) | F20: m² | G20: =IF(Nível="Serviço",SUMIF($N$15:$BK$15,"<>"&"",N20:BK20),"") -> 8 | H20: =IF(AND(ISNUMBER(G20),G20<>0),I20/G20,IF(G20=0,0,"")) -> 170.69 | I20: 1365.52 | K20: =deactivatedados.form1 -> 2 | L20: 2-PAVIMENTAÇÃO | N20: 8 | O20: 0 | P20: 0 | Q20: 0 | R20: 0 | S20: 0 | T20: 0 | U20: 0 | BM20: =IF(N$15="",0,IF(ISNUMBER(PreçoUnit),PreçoUnit*INDEX(Import.PLQ,$B20,BM$16),0)) -> 1365.52 | BN20: =IF(O$15="",0,IF(ISNUMBER(PreçoUnit),PreçoUnit*INDEX(Import.PLQ,$B20,BN$16),0)) -> 0 | BO20: =IF(P$15="",0,IF(ISNUMBER(PreçoUnit),PreçoUnit*INDEX(Import.PLQ,$B20,BO$16),0)) -> 0 | BP20: =IF(Q$15="",0,IF(ISNUMBER(PreçoUnit),PreçoUnit*INDEX(Import.PLQ,$B20,BP$16),0)) -> 0 | BQ20: =IF(R$15="",0,IF(ISNUMBER(PreçoUnit),PreçoUnit*INDEX(Import.PLQ,$B20,BQ$16),0)) -> 0 | BR20: =IF(S$15="",0,IF(ISNUMBER(PreçoUnit),PreçoUnit*INDEX(Import.PLQ,$B20,BR$16),0)) -> 0 | BS20: =IF(T$15="",0,IF(ISNUMBER(PreçoUnit),PreçoUnit*INDEX(Import.PLQ,$B20,BS$16),0)) -> 0 | BT20: =IF(U$15="",0,IF(ISNUMBER(PreçoUnit),PreçoUnit*INDEX(Import.PLQ,$B20,BT$16),0)) -> 0 | ... DJ20: =IF(BK$15="",0,IF(ISNUMBER(PreçoUnit),PreçoUnit*INDEX(Import.PLQ,$B20,DJ$16),0)) -> 0 | DK20: =IF(D20="",0,IF(ISNUMBER(VALUE(D20)),VALUE(D20),LEFT(D20,FIND(".",D20)-1))) -> 1 | DL20: =SUM(DM20:FJ20) -> 0 | DM20: =IF($K20<>1,IF(ISNUMBER(INDEX(Import.PLE,$K20,DM$16)),IF(INDEX(Import.PLE,$K20,DM$16)<=mediçao,BM20,0),0),PLE!$AA$28*BM20) -> 0 | DN20: =IF($K20<>1,IF(ISNUMBER(INDEX(Import.PLE,$K20,DN$16)),IF(INDEX(Import.PLE,$K20,DN$16)<=mediçao,BN20,0),0),PLE!$AA$28*BN20) -> 0 | DO20: =IF($K20<>1,IF(ISNUMBER(INDEX(Import.PLE,$K20,DO$16)),IF(INDEX(Import.PLE,$K20,DO$16)<=mediçao,BO20,0),0),PLE!$AA$28*BO20) -> 0 | DP20: =IF($K20<>1,IF(ISNUMBER(INDEX(Import.PLE,$K20,DP$16)),IF(INDEX(Import.PLE,$K20,DP$16)<=mediçao,BP20,0),0),PLE!$AA$28*BP20) -> 0 | DQ20: =IF($K20<>1,IF(ISNUMBER(INDEX(Import.PLE,$K20,DQ$16)),IF(INDEX(Import.PLE,$K20,DQ$16)<=mediçao,BQ20,0),0),PLE!$AA$28*BQ20) -> 0 | DR20: =IF($K20<>1,IF(ISNUMBER(INDEX(Import.PLE,$K20,DR$16)),IF(INDEX(Import.PLE,$K20,DR$16)<=mediçao,BR20,0),0),PLE!$AA$28*BR20) -> 0 | DS20: =IF($K20<>1,IF(ISNUMBER(INDEX(Import.PLE,$K20,DS$16)),IF(INDEX(Import.PLE,$K20,DS$16)<=mediçao,BS20,0),0),PLE!$AA$28*BS20) -> 0 | DT20: =IF($K20<>1,IF(ISNUMBER(INDEX(Import.PLE,$K20,DT$16)),IF(INDEX(Import.PLE,$K20,DT$16)<=mediçao,BT20,0),0),PLE!$AA$28*BT20) -> 0 | ... FJ20: =IF($K20<>1,IF(ISNUMBER(INDEX(Import.PLE,$K20,FJ$16)),IF(INDEX(Import.PLE,$K20,FJ$16)<=mediçao,DJ20,0),0),PLE!$AA$28*DJ20) -> 0
B21: =ROW(Nível)-ROW(LIorçamento)+1 -> 4 | C21: =IF(D21="","",IF(ISNUMBER(VALUE(D21)),"Meta",IF(AND(F21<>"",I21<>""),"Serviço","Nível"))) -> Meta | D21: 2 | E21: SERVIÇOS DE TERRAPLENAGEM | G21: =IF(Nível="Serviço",SUMIF($N$15:$BK$15,"<>"&"",N21:BK21),"") | H21: =IF(AND(ISNUMBER(G21),G21<>0),I21/G21,IF(G21=0,0,"")) | K21: =deactivatedados.form1 | BM21: =IF(N$15="",0,IF(ISNUMBER(PreçoUnit),PreçoUnit*INDEX(Import.PLQ,$B21,BM$16),0)) -> 0 | BN21: =IF(O$15="",0,IF(ISNUMBER(PreçoUnit),PreçoUnit*INDEX(Import.PLQ,$B21,BN$16),0)) -> 0 | BO21: =IF(P$15="",0,IF(ISNUMBER(PreçoUnit),PreçoUnit*INDEX(Import.PLQ,$B21,BO$16),0)) -> 0 | BP21: =IF(Q$15="",0,IF(ISNUMBER(PreçoUnit),PreçoUnit*INDEX(Import.PLQ,$B21,BP$16),0)) -> 0 | BQ21: =IF(R$15="",0,IF(ISNUMBER(PreçoUnit),PreçoUnit*INDEX(Import.PLQ,$B21,BQ$16),0)) -> 0 | BR21: =IF(S$15="",0,IF(ISNUMBER(PreçoUnit),PreçoUnit*INDEX(Import.PLQ,$B21,BR$16),0)) -> 0 | BS21: =IF(T$15="",0,IF(ISNUMBER(PreçoUnit),PreçoUnit*INDEX(Import.PLQ,$B21,BS$16),0)) -> 0 | BT21: =IF(U$15="",0,IF(ISNUMBER(PreçoUnit),PreçoUnit*INDEX(Import.PLQ,$B21,BT$16),0)) -> 0 | ... DJ21: =IF(BK$15="",0,IF(ISNUMBER(PreçoUnit),PreçoUnit*INDEX(Import.PLQ,$B21,DJ$16),0)) -> 0 | DK21: =IF(D21="",0,IF(ISNUMBER(VALUE(D21)),VALUE(D21),LEFT(D21,FIND(".",D21)-1))) -> 2 | DL21: =SUM(DM21:FJ21) -> 0 | DM21: =IF($K21<>1,IF(ISNUMBER(INDEX(Import.PLE,$K21,DM$16)),IF(INDEX(Import.PLE,$K21,DM$16)<=mediçao,BM21,0),0),PLE!$AA$28*BM21) -> 0 | DN21: =IF($K21<>1,IF(ISNUMBER(INDEX(Import.PLE,$K21,DN$16)),IF(INDEX(Import.PLE,$K21,DN$16)<=mediçao,BN21,0),0),PLE!$AA$28*BN21) -> 0 | DO21: =IF($K21<>1,IF(ISNUMBER(INDEX(Import.PLE,$K21,DO$16)),IF(INDEX(Import.PLE,$K21,DO$16)<=mediçao,BO21,0),0),PLE!$AA$28*BO21) -> 0 | DP21: =IF($K21<>1,IF(ISNUMBER(INDEX(Import.PLE,$K21,DP$16)),IF(INDEX(Import.PLE,$K21,DP$16)<=mediçao,BP21,0),0),PLE!$AA$28*BP21) -> 0 | DQ21: =IF($K21<>1,IF(ISNUMBER(INDEX(Import.PLE,$K21,DQ$16)),IF(INDEX(Import.PLE,$K21,DQ$16)<=mediçao,BQ21,0),0),PLE!$AA$28*BQ21) -> 0 | DR21: =IF($K21<>1,IF(ISNUMBER(INDEX(Import.PLE,$K21,DR$16)),IF(INDEX(Import.PLE,$K21,DR$16)<=mediçao,BR21,0),0),PLE!$AA$28*BR21) -> 0 | DS21: =IF($K21<>1,IF(ISNUMBER(INDEX(Import.PLE,$K21,DS$16)),IF(INDEX(Import.PLE,$K21,DS$16)<=mediçao,BS21,0),0),PLE!$AA$28*BS21) -> 0 | DT21: =IF($K21<>1,IF(ISNUMBER(INDEX(Import.PLE,$K21,DT$16)),IF(INDEX(Import.PLE,$K21,DT$16)<=mediçao,BT21,0),0),PLE!$AA$28*BT21) -> 0 | ... FJ21: =IF($K21<>1,IF(ISNUMBER(INDEX(Import.PLE,$K21,FJ$16)),IF(INDEX(Import.PLE,$K21,FJ$16)<=mediçao,DJ21,0),0),PLE!$AA$28*DJ21) -> 0
B22: =ROW(Nível)-ROW(LIorçamento)+1 -> 5 | C22: =IF(D22="","",IF(ISNUMBER(VALUE(D22)),"Meta",IF(AND(F22<>"",I22<>""),"Serviço","Nível"))) -> Serviço | D22: 2.1 | E22: Regularização e compactação de sub-leito até 20cm de espessura | F22: m² | G22: =IF(Nível="Serviço",SUMIF($N$15:$BK$15,"<>"&"",N22:BK22),"") -> 5349.12 | H22: =IF(AND(ISNUMBER(G22),G22<>0),I22/G22,IF(G22=0,0,"")) -> 2.5999996 | I22: 13907.71 | K22: =deactivatedados.form1 -> 2 | L22: 2-PAVIMENTAÇÃO | N22: 1102.85 | O22: 452.76 | P22: 727.62 | Q22: 1032.9 | R22: 390.01 | S22: 733.74 | T22: 523.8 | U22: 385.44 | BM22: =IF(N$15="",0,IF(ISNUMBER(PreçoUnit),PreçoUnit*INDEX(Import.PLQ,$B22,BM$16),0)) -> 2867.4096 | BN22: =IF(O$15="",0,IF(ISNUMBER(PreçoUnit),PreçoUnit*INDEX(Import.PLQ,$B22,BN$16),0)) -> 1177.1758 | BO22: =IF(P$15="",0,IF(ISNUMBER(PreçoUnit),PreçoUnit*INDEX(Import.PLQ,$B22,BO$16),0)) -> 1891.8117 | BP22: =IF(Q$15="",0,IF(ISNUMBER(PreçoUnit),PreçoUnit*INDEX(Import.PLQ,$B22,BP$16),0)) -> 2685.5396 | BQ22: =IF(R$15="",0,IF(ISNUMBER(PreçoUnit),PreçoUnit*INDEX(Import.PLQ,$B22,BQ$16),0)) -> 1014.0259 | BR22: =IF(S$15="",0,IF(ISNUMBER(PreçoUnit),PreçoUnit*INDEX(Import.PLQ,$B22,BR$16),0)) -> 1907.7237 | BS22: =IF(T$15="",0,IF(ISNUMBER(PreçoUnit),PreçoUnit*INDEX(Import.PLQ,$B22,BS$16),0)) -> 1361.8798 | BT22: =IF(U$15="",0,IF(ISNUMBER(PreçoUnit),PreçoUnit*INDEX(Import.PLQ,$B22,BT$16),0)) -> 1002.1439 | ... DJ22: =IF(BK$15="",0,IF(ISNUMBER(PreçoUnit),PreçoUnit*INDEX(Import.PLQ,$B22,DJ$16),0)) -> 0 | DK22: =IF(D22="",0,IF(ISNUMBER(VALUE(D22)),VALUE(D22),LEFT(D22,FIND(".",D22)-1))) -> 2 | DL22: =SUM(DM22:FJ22) -> 0 | DM22: =IF($K22<>1,IF(ISNUMBER(INDEX(Import.PLE,$K22,DM$16)),IF(INDEX(Import.PLE,$K22,DM$16)<=mediçao,BM22,0),0),PLE!$AA$28*BM22) -> 0 | DN22: =IF($K22<>1,IF(ISNUMBER(INDEX(Import.PLE,$K22,DN$16)),IF(INDEX(Import.PLE,$K22,DN$16)<=mediçao,BN22,0),0),PLE!$AA$28*BN22) -> 0 | DO22: =IF($K22<>1,IF(ISNUMBER(INDEX(Import.PLE,$K22,DO$16)),IF(INDEX(Import.PLE,$K22,DO$16)<=mediçao,BO22,0),0),PLE!$AA$28*BO22) -> 0 | DP22: =IF($K22<>1,IF(ISNUMBER(INDEX(Import.PLE,$K22,DP$16)),IF(INDEX(Import.PLE,$K22,DP$16)<=mediçao,BP22,0),0),PLE!$AA$28*BP22) -> 0 | DQ22: =IF($K22<>1,IF(ISNUMBER(INDEX(Import.PLE,$K22,DQ$16)),IF(INDEX(Import.PLE,$K22,DQ$16)<=mediçao,BQ22,0),0),PLE!$AA$28*BQ22) -> 0 | DR22: =IF($K22<>1,IF(ISNUMBER(INDEX(Import.PLE,$K22,DR$16)),IF(INDEX(Import.PLE,$K22,DR$16)<=mediçao,BR22,0),0),PLE!$AA$28*BR22) -> 0 | DS22: =IF($K22<>1,IF(ISNUMBER(INDEX(Import.PLE,$K22,DS$16)),IF(INDEX(Import.PLE,$K22,DS$16)<=mediçao,BS22,0),0),PLE!$AA$28*BS22) -> 0 | DT22: =IF($K22<>1,IF(ISNUMBER(INDEX(Import.PLE,$K22,DT$16)),IF(INDEX(Import.PLE,$K22,DT$16)<=mediçao,BT22,0),0),PLE!$AA$28*BT22) -> 0 | ... FJ22: =IF($K22<>1,IF(ISNUMBER(INDEX(Import.PLE,$K22,FJ$16)),IF(INDEX(Import.PLE,$K22,FJ$16)<=mediçao,DJ22,0),0),PLE!$AA$28*DJ22) -> 0
B23: =ROW(Nível)-ROW(LIorçamento)+1 -> 6 | C23: =IF(D23="","",IF(ISNUMBER(VALUE(D23)),"Meta",IF(AND(F23<>"",I23<>""),"Serviço","Nível"))) -> Meta | D23: 3 | E23: PAVIMENTAÇÃO | G23: =IF(Nível="Serviço",SUMIF($N$15:$BK$15,"<>"&"",N23:BK23),"") | H23: =IF(AND(ISNUMBER(G23),G23<>0),I23/G23,IF(G23=0,0,"")) | K23: =deactivatedados.form1 | BM23: =IF(N$15="",0,IF(ISNUMBER(PreçoUnit),PreçoUnit*INDEX(Import.PLQ,$B23,BM$16),0)) -> 0 | BN23: =IF(O$15="",0,IF(ISNUMBER(PreçoUnit),PreçoUnit*INDEX(Import.PLQ,$B23,BN$16),0)) -> 0 | BO23: =IF(P$15="",0,IF(ISNUMBER(PreçoUnit),PreçoUnit*INDEX(Import.PLQ,$B23,BO$16),0)) -> 0 | BP23: =IF(Q$15="",0,IF(ISNUMBER(PreçoUnit),PreçoUnit*INDEX(Import.PLQ,$B23,BP$16),0)) -> 0 | BQ23: =IF(R$15="",0,IF(ISNUMBER(PreçoUnit),PreçoUnit*INDEX(Import.PLQ,$B23,BQ$16),0)) -> 0 | BR23: =IF(S$15="",0,IF(ISNUMBER(PreçoUnit),PreçoUnit*INDEX(Import.PLQ,$B23,BR$16),0)) -> 0 | BS23: =IF(T$15="",0,IF(ISNUMBER(PreçoUnit),PreçoUnit*INDEX(Import.PLQ,$B23,BS$16),0)) -> 0 | BT23: =IF(U$15="",0,IF(ISNUMBER(PreçoUnit),PreçoUnit*INDEX(Import.PLQ,$B23,BT$16),0)) -> 0 | ... DJ23: =IF(BK$15="",0,IF(ISNUMBER(PreçoUnit),PreçoUnit*INDEX(Import.PLQ,$B23,DJ$16),0)) -> 0 | DK23: =IF(D23="",0,IF(ISNUMBER(VALUE(D23)),VALUE(D23),LEFT(D23,FIND(".",D23)-1))) -> 3 | DL23: =SUM(DM23:FJ23) -> 0 | DM23: =IF($K23<>1,IF(ISNUMBER(INDEX(Import.PLE,$K23,DM$16)),IF(INDEX(Import.PLE,$K23,DM$16)<=mediçao,BM23,0),0),PLE!$AA$28*BM23) -> 0 | DN23: =IF($K23<>1,IF(ISNUMBER(INDEX(Import.PLE,$K23,DN$16)),IF(INDEX(Import.PLE,$K23,DN$16)<=mediçao,BN23,0),0),PLE!$AA$28*BN23) -> 0 | DO23: =IF($K23<>1,IF(ISNUMBER(INDEX(Import.PLE,$K23,DO$16)),IF(INDEX(Import.PLE,$K23,DO$16)<=mediçao,BO23,0),0),PLE!$AA$28*BO23) -> 0 | DP23: =IF($K23<>1,IF(ISNUMBER(INDEX(Import.PLE,$K23,DP$16)),IF(INDEX(Import.PLE,$K23,DP$16)<=mediçao,BP23,0),0),PLE!$AA$28*BP23) -> 0 | DQ23: =IF($K23<>1,IF(ISNUMBER(INDEX(Import.PLE,$K23,DQ$16)),IF(INDEX(Import.PLE,$K23,DQ$16)<=mediçao,BQ23,0),0),PLE!$AA$28*BQ23) -> 0 | DR23: =IF($K23<>1,IF(ISNUMBER(INDEX(Import.PLE,$K23,DR$16)),IF(INDEX(Import.PLE,$K23,DR$16)<=mediçao,BR23,0),0),PLE!$AA$28*BR23) -> 0 | DS23: =IF($K23<>1,IF(ISNUMBER(INDEX(Import.PLE,$K23,DS$16)),IF(INDEX(Import.PLE,$K23,DS$16)<=mediçao,BS23,0),0),PLE!$AA$28*BS23) -> 0 | DT23: =IF($K23<>1,IF(ISNUMBER(INDEX(Import.PLE,$K23,DT$16)),IF(INDEX(Import.PLE,$K23,DT$16)<=mediçao,BT23,0),0),PLE!$AA$28*BT23) -> 0 | ... FJ23: =IF($K23<>1,IF(ISNUMBER(INDEX(Import.PLE,$K23,FJ$16)),IF(INDEX(Import.PLE,$K23,FJ$16)<=mediçao,DJ23,0),0),PLE!$AA$28*DJ23) -> 0
B24: =ROW(Nível)-ROW(LIorçamento)+1 -> 7 | C24: =IF(D24="","",IF(ISNUMBER(VALUE(D24)),"Meta",IF(AND(F24<>"",I24<>""),"Serviço","Nível"))) -> Serviço | D24: 3.1 | E24: Serviços topográficos para pavimentação (locação e nivelamento), inclusive nota de serviços, acompanhamento e greide | F24: m² | G24: =IF(Nível="Serviço",SUMIF($N$15:$BK$15,"<>"&"",N24:BK24),"") -> 5349.12 | H24: =IF(AND(ISNUMBER(G24),G24<>0),I24/G24,IF(G24=0,0,"")) -> 0.47999858 | I24: 2567.57 | K24: =deactivatedados.form1 -> 2 | L24: 2-PAVIMENTAÇÃO | N24: 1102.85 | O24: 452.76 | P24: 727.62 | Q24: 1032.9 | R24: 390.01 | S24: 733.74 | T24: 523.8 | U24: 385.44 | BM24: =IF(N$15="",0,IF(ISNUMBER(PreçoUnit),PreçoUnit*INDEX(Import.PLQ,$B24,BM$16),0)) -> 529.36643 | BN24: =IF(O$15="",0,IF(ISNUMBER(PreçoUnit),PreçoUnit*INDEX(Import.PLQ,$B24,BN$16),0)) -> 217.32416 | BO24: =IF(P$15="",0,IF(ISNUMBER(PreçoUnit),PreçoUnit*INDEX(Import.PLQ,$B24,BO$16),0)) -> 349.25657 | BP24: =IF(Q$15="",0,IF(ISNUMBER(PreçoUnit),PreçoUnit*INDEX(Import.PLQ,$B24,BP$16),0)) -> 495.79053 | BQ24: =IF(R$15="",0,IF(ISNUMBER(PreçoUnit),PreçoUnit*INDEX(Import.PLQ,$B24,BQ$16),0)) -> 187.20425 | BR24: =IF(S$15="",0,IF(ISNUMBER(PreçoUnit),PreçoUnit*INDEX(Import.PLQ,$B24,BR$16),0)) -> 352.19416 | BS24: =IF(T$15="",0,IF(ISNUMBER(PreçoUnit),PreçoUnit*INDEX(Import.PLQ,$B24,BS$16),0)) -> 251.42326 | BT24: =IF(U$15="",0,IF(ISNUMBER(PreçoUnit),PreçoUnit*INDEX(Import.PLQ,$B24,BT$16),0)) -> 185.01065 | ... DJ24: =IF(BK$15="",0,IF(ISNUMBER(PreçoUnit),PreçoUnit*INDEX(Import.PLQ,$B24,DJ$16),0)) -> 0 | DK24: =IF(D24="",0,IF(ISNUMBER(VALUE(D24)),VALUE(D24),LEFT(D24,FIND(".",D24)-1))) -> 3 | DL24: =SUM(DM24:FJ24) -> 0 | DM24: =IF($K24<>1,IF(ISNUMBER(INDEX(Import.PLE,$K24,DM$16)),IF(INDEX(Import.PLE,$K24,DM$16)<=mediçao,BM24,0),0),PLE!$AA$28*BM24) -> 0 | DN24: =IF($K24<>1,IF(ISNUMBER(INDEX(Import.PLE,$K24,DN$16)),IF(INDEX(Import.PLE,$K24,DN$16)<=mediçao,BN24,0),0),PLE!$AA$28*BN24) -> 0 | DO24: =IF($K24<>1,IF(ISNUMBER(INDEX(Import.PLE,$K24,DO$16)),IF(INDEX(Import.PLE,$K24,DO$16)<=mediçao,BO24,0),0),PLE!$AA$28*BO24) -> 0 | DP24: =IF($K24<>1,IF(ISNUMBER(INDEX(Import.PLE,$K24,DP$16)),IF(INDEX(Import.PLE,$K24,DP$16)<=mediçao,BP24,0),0),PLE!$AA$28*BP24) -> 0 | DQ24: =IF($K24<>1,IF(ISNUMBER(INDEX(Import.PLE,$K24,DQ$16)),IF(INDEX(Import.PLE,$K24,DQ$16)<=mediçao,BQ24,0),0),PLE!$AA$28*BQ24) -> 0 | DR24: =IF($K24<>1,IF(ISNUMBER(INDEX(Import.PLE,$K24,DR$16)),IF(INDEX(Import.PLE,$K24,DR$16)<=mediçao,BR24,0),0),PLE!$AA$28*BR24) -> 0 | DS24: =IF($K24<>1,IF(ISNUMBER(INDEX(Import.PLE,$K24,DS$16)),IF(INDEX(Import.PLE,$K24,DS$16)<=mediçao,BS24,0),0),PLE!$AA$28*BS24) -> 0 | DT24: =IF($K24<>1,IF(ISNUMBER(INDEX(Import.PLE,$K24,DT$16)),IF(INDEX(Import.PLE,$K24,DT$16)<=mediçao,BT24,0),0),PLE!$AA$28*BT24) -> 0 | ... FJ24: =IF($K24<>1,IF(ISNUMBER(INDEX(Import.PLE,$K24,FJ$16)),IF(INDEX(Import.PLE,$K24,FJ$16)<=mediçao,DJ24,0),0),PLE!$AA$28*DJ24) -> 0
B25: =ROW(Nível)-ROW(LIorçamento)+1 -> 8 | C25: =IF(D25="","",IF(ISNUMBER(VALUE(D25)),"Meta",IF(AND(F25<>"",I25<>""),"Serviço","Nível"))) -> Serviço | D25: 3.2 | E25: Assentamento de guia (meio-fio) em trecho reto, confeccionada em concreto pré-fabricado, dimensões 100x15x13x30 cm (comprimento x base inferior x base superior x altura), para vias urbanas (uso viário) | F25: m | G25: =IF(Nível="Serviço",SUMIF($N$15:$BK$15,"<>"&"",N25:BK25),"") -> 1740.41 | H25: =IF(AND(ISNUMBER(G25),G25<>0),I25/G25,IF(G25=0,0,"")) -> 54.370005 | I25: 94626.1 | K25: =deactivatedados.form1 -> 2 | L25: 2-PAVIMENTAÇÃO | N25: 353.89 | O25: 154.35 | P25: 215.58 | Q25: 348.78 | R25: 130.15 | S25: 241.91 | T25: 167.27 | U25: 128.48 | BM25: =IF(N$15="",0,IF(ISNUMBER(PreçoUnit),PreçoUnit*INDEX(Import.PLQ,$B25,BM$16),0)) -> 19241.001 | BN25: =IF(O$15="",0,IF(ISNUMBER(PreçoUnit),PreçoUnit*INDEX(Import.PLQ,$B25,BN$16),0)) -> 8392.0102 | BO25: =IF(P$15="",0,IF(ISNUMBER(PreçoUnit),PreçoUnit*INDEX(Import.PLQ,$B25,BO$16),0)) -> 11721.086 | BP25: =IF(Q$15="",0,IF(ISNUMBER(PreçoUnit),PreçoUnit*INDEX(Import.PLQ,$B25,BP$16),0)) -> 18963.17 | BQ25: =IF(R$15="",0,IF(ISNUMBER(PreçoUnit),PreçoUnit*INDEX(Import.PLQ,$B25,BQ$16),0)) -> 7076.2561 | BR25: =IF(S$15="",0,IF(ISNUMBER(PreçoUnit),PreçoUnit*INDEX(Import.PLQ,$B25,BR$16),0)) -> 13152.648 | BS25: =IF(T$15="",0,IF(ISNUMBER(PreçoUnit),PreçoUnit*INDEX(Import.PLQ,$B25,BS$16),0)) -> 9094.4707 | BT25: =IF(U$15="",0,IF(ISNUMBER(PreçoUnit),PreçoUnit*INDEX(Import.PLQ,$B25,BT$16),0)) -> 6985.4582 | ... DJ25: =IF(BK$15="",0,IF(ISNUMBER(PreçoUnit),PreçoUnit*INDEX(Import.PLQ,$B25,DJ$16),0)) -> 0 | DK25: =IF(D25="",0,IF(ISNUMBER(VALUE(D25)),VALUE(D25),LEFT(D25,FIND(".",D25)-1))) -> 3 | DL25: =SUM(DM25:FJ25) -> 0 | DM25: =IF($K25<>1,IF(ISNUMBER(INDEX(Import.PLE,$K25,DM$16)),IF(INDEX(Import.PLE,$K25,DM$16)<=mediçao,BM25,0),0),PLE!$AA$28*BM25) -> 0 | DN25: =IF($K25<>1,IF(ISNUMBER(INDEX(Import.PLE,$K25,DN$16)),IF(INDEX(Import.PLE,$K25,DN$16)<=mediçao,BN25,0),0),PLE!$AA$28*BN25) -> 0 | DO25: =IF($K25<>1,IF(ISNUMBER(INDEX(Import.PLE,$K25,DO$16)),IF(INDEX(Import.PLE,$K25,DO$16)<=mediçao,BO25,0),0),PLE!$AA$28*BO25) -> 0 | DP25: =IF($K25<>1,IF(ISNUMBER(INDEX(Import.PLE,$K25,DP$16)),IF(INDEX(Import.PLE,$K25,DP$16)<=mediçao,BP25,0),0),PLE!$AA$28*BP25) -> 0 | DQ25: =IF($K25<>1,IF(ISNUMBER(INDEX(Import.PLE,$K25,DQ$16)),IF(INDEX(Import.PLE,$K25,DQ$16)<=mediçao,BQ25,0),0),PLE!$AA$28*BQ25) -> 0 | DR25: =IF($K25<>1,IF(ISNUMBER(INDEX(Import.PLE,$K25,DR$16)),IF(INDEX(Import.PLE,$K25,DR$16)<=mediçao,BR25,0),0),PLE!$AA$28*BR25) -> 0 | DS25: =IF($K25<>1,IF(ISNUMBER(INDEX(Import.PLE,$K25,DS$16)),IF(INDEX(Import.PLE,$K25,DS$16)<=mediçao,BS25,0),0),PLE!$AA$28*BS25) -> 0 | DT25: =IF($K25<>1,IF(ISNUMBER(INDEX(Import.PLE,$K25,DT$16)),IF(INDEX(Import.PLE,$K25,DT$16)<=mediçao,BT25,0),0),PLE!$AA$28*BT25) -> 0 | ... FJ25: =IF($K25<>1,IF(ISNUMBER(INDEX(Import.PLE,$K25,FJ$16)),IF(INDEX(Import.PLE,$K25,FJ$16)<=mediçao,DJ25,0),0),PLE!$AA$28*DJ25) -> 0
B26: =ROW(Nível)-ROW(LIorçamento)+1 -> 9 | C26: =IF(D26="","",IF(ISNUMBER(VALUE(D26)),"Meta",IF(AND(F26<>"",I26<>""),"Serviço","Nível"))) -> Serviço | D26: 3.3 | E26: Revestimento em paralelepipedo inclusive colchão de areia rejuntado no traço 1:3 (Cimento e areia) | F26: m² | G26: =IF(Nível="Serviço",SUMIF($N$15:$BK$15,"<>"&"",N26:BK26),"") -> 5349.12 | H26: =IF(AND(ISNUMBER(G26),G26<>0),I26/G26,IF(G26=0,0,"")) -> 93.65 | I26: 500945.09 | K26: =deactivatedados.form1 -> 2 | L26: 2-PAVIMENTAÇÃO | N26: 1102.85 | O26: 452.76 | P26: 727.62 | Q26: 1032.9 | R26: 390.01 | S26: 733.74 | T26: 523.8 | U26: 385.44 | BM26: =IF(N$15="",0,IF(ISNUMBER(PreçoUnit),PreçoUnit*INDEX(Import.PLQ,$B26,BM$16),0)) -> 103281.9 | BN26: =IF(O$15="",0,IF(ISNUMBER(PreçoUnit),PreçoUnit*INDEX(Import.PLQ,$B26,BN$16),0)) -> 42400.974 | BO26: =IF(P$15="",0,IF(ISNUMBER(PreçoUnit),PreçoUnit*INDEX(Import.PLQ,$B26,BO$16),0)) -> 68141.613 | BP26: =IF(Q$15="",0,IF(ISNUMBER(PreçoUnit),PreçoUnit*INDEX(Import.PLQ,$B26,BP$16),0)) -> 96731.085 | BQ26: =IF(R$15="",0,IF(ISNUMBER(PreçoUnit),PreçoUnit*INDEX(Import.PLQ,$B26,BQ$16),0)) -> 36524.437 | BR26: =IF(S$15="",0,IF(ISNUMBER(PreçoUnit),PreçoUnit*INDEX(Import.PLQ,$B26,BR$16),0)) -> 68714.751 | BS26: =IF(T$15="",0,IF(ISNUMBER(PreçoUnit),PreçoUnit*INDEX(Import.PLQ,$B26,BS$16),0)) -> 49053.87 | BT26: =IF(U$15="",0,IF(ISNUMBER(PreçoUnit),PreçoUnit*INDEX(Import.PLQ,$B26,BT$16),0)) -> 36096.456 | ... DJ26: =IF(BK$15="",0,IF(ISNUMBER(PreçoUnit),PreçoUnit*INDEX(Import.PLQ,$B26,DJ$16),0)) -> 0 | DK26: =IF(D26="",0,IF(ISNUMBER(VALUE(D26)),VALUE(D26),LEFT(D26,FIND(".",D26)-1))) -> 3 | DL26: =SUM(DM26:FJ26) -> 0 | DM26: =IF($K26<>1,IF(ISNUMBER(INDEX(Import.PLE,$K26,DM$16)),IF(INDEX(Import.PLE,$K26,DM$16)<=mediçao,BM26,0),0),PLE!$AA$28*BM26) -> 0 | DN26: =IF($K26<>1,IF(ISNUMBER(INDEX(Import.PLE,$K26,DN$16)),IF(INDEX(Import.PLE,$K26,DN$16)<=mediçao,BN26,0),0),PLE!$AA$28*BN26) -> 0 | DO26: =IF($K26<>1,IF(ISNUMBER(INDEX(Import.PLE,$K26,DO$16)),IF(INDEX(Import.PLE,$K26,DO$16)<=mediçao,BO26,0),0),PLE!$AA$28*BO26) -> 0 | DP26: =IF($K26<>1,IF(ISNUMBER(INDEX(Import.PLE,$K26,DP$16)),IF(INDEX(Import.PLE,$K26,DP$16)<=mediçao,BP26,0),0),PLE!$AA$28*BP26) -> 0 | DQ26: =IF($K26<>1,IF(ISNUMBER(INDEX(Import.PLE,$K26,DQ$16)),IF(INDEX(Import.PLE,$K26,DQ$16)<=mediçao,BQ26,0),0),PLE!$AA$28*BQ26) -> 0 | DR26: =IF($K26<>1,IF(ISNUMBER(INDEX(Import.PLE,$K26,DR$16)),IF(INDEX(Import.PLE,$K26,DR$16)<=mediçao,BR26,0),0),PLE!$AA$28*BR26) -> 0 | DS26: =IF($K26<>1,IF(ISNUMBER(INDEX(Import.PLE,$K26,DS$16)),IF(INDEX(Import.PLE,$K26,DS$16)<=mediçao,BS26,0),0),PLE!$AA$28*BS26) -> 0 | DT26: =IF($K26<>1,IF(ISNUMBER(INDEX(Import.PLE,$K26,DT$16)),IF(INDEX(Import.PLE,$K26,DT$16)<=mediçao,BT26,0),0),PLE!$AA$28*BT26) -> 0 | ... FJ26: =IF($K26<>1,IF(ISNUMBER(INDEX(Import.PLE,$K26,FJ$16)),IF(INDEX(Import.PLE,$K26,FJ$16)<=mediçao,DJ26,0),0),PLE!$AA$28*DJ26) -> 0
B27: =ROW(Nível)-ROW(LIorçamento)+1 -> 10 | C27: =IF(D27="","",IF(ISNUMBER(VALUE(D27)),"Meta",IF(AND(F27<>"",I27<>""),"Serviço","Nível"))) -> Serviço | D27: 3.4 | E27: Fornecimento e aplicação de meio fio em pedra granitica.(Cordão) | F27: m | G27: =IF(Nível="Serviço",SUMIF($N$15:$BK$15,"<>"&"",N27:BK27),"") -> 50.8 | H27: =IF(AND(ISNUMBER(G27),G27<>0),I27/G27,IF(G27=0,0,"")) -> 36.560039 | I27: 1857.25 | K27: =deactivatedados.form1 -> 2 | L27: 2-PAVIMENTAÇÃO | N27: 8.8 | O27: 0 | P27: 12 | Q27: 6 | R27: 0 | S27: 6 | T27: 6 | U27: 12 | BM27: =IF(N$15="",0,IF(ISNUMBER(PreçoUnit),PreçoUnit*INDEX(Import.PLQ,$B27,BM$16),0)) -> 321.72835 | BN27: =IF(O$15="",0,IF(ISNUMBER(PreçoUnit),PreçoUnit*INDEX(Import.PLQ,$B27,BN$16),0)) -> 0 | BO27: =IF(P$15="",0,IF(ISNUMBER(PreçoUnit),PreçoUnit*INDEX(Import.PLQ,$B27,BO$16),0)) -> 438.72047 | BP27: =IF(Q$15="",0,IF(ISNUMBER(PreçoUnit),PreçoUnit*INDEX(Import.PLQ,$B27,BP$16),0)) -> 219.36024 | BQ27: =IF(R$15="",0,IF(ISNUMBER(PreçoUnit),PreçoUnit*INDEX(Import.PLQ,$B27,BQ$16),0)) -> 0 | BR27: =IF(S$15="",0,IF(ISNUMBER(PreçoUnit),PreçoUnit*INDEX(Import.PLQ,$B27,BR$16),0)) -> 219.36024 | BS27: =IF(T$15="",0,IF(ISNUMBER(PreçoUnit),PreçoUnit*INDEX(Import.PLQ,$B27,BS$16),0)) -> 219.36024 | BT27: =IF(U$15="",0,IF(ISNUMBER(PreçoUnit),PreçoUnit*INDEX(Import.PLQ,$B27,BT$16),0)) -> 438.72047 | ... DJ27: =IF(BK$15="",0,IF(ISNUMBER(PreçoUnit),PreçoUnit*INDEX(Import.PLQ,$B27,DJ$16),0)) -> 0 | DK27: =IF(D27="",0,IF(ISNUMBER(VALUE(D27)),VALUE(D27),LEFT(D27,FIND(".",D27)-1))) -> 3 | DL27: =SUM(DM27:FJ27) -> 0 | DM27: =IF($K27<>1,IF(ISNUMBER(INDEX(Import.PLE,$K27,DM$16)),IF(INDEX(Import.PLE,$K27,DM$16)<=mediçao,BM27,0),0),PLE!$AA$28*BM27) -> 0 | DN27: =IF($K27<>1,IF(ISNUMBER(INDEX(Import.PLE,$K27,DN$16)),IF(INDEX(Import.PLE,$K27,DN$16)<=mediçao,BN27,0),0),PLE!$AA$28*BN27) -> 0 | DO27: =IF($K27<>1,IF(ISNUMBER(INDEX(Import.PLE,$K27,DO$16)),IF(INDEX(Import.PLE,$K27,DO$16)<=mediçao,BO27,0),0),PLE!$AA$28*BO27) -> 0 | DP27: =IF($K27<>1,IF(ISNUMBER(INDEX(Import.PLE,$K27,DP$16)),IF(INDEX(Import.PLE,$K27,DP$16)<=mediçao,BP27,0),0),PLE!$AA$28*BP27) -> 0 | DQ27: =IF($K27<>1,IF(ISNUMBER(INDEX(Import.PLE,$K27,DQ$16)),IF(INDEX(Import.PLE,$K27,DQ$16)<=mediçao,BQ27,0),0),PLE!$AA$28*BQ27) -> 0 | DR27: =IF($K27<>1,IF(ISNUMBER(INDEX(Import.PLE,$K27,DR$16)),IF(INDEX(Import.PLE,$K27,DR$16)<=mediçao,BR27,0),0),PLE!$AA$28*BR27) -> 0 | DS27: =IF($K27<>1,IF(ISNUMBER(INDEX(Import.PLE,$K27,DS$16)),IF(INDEX(Import.PLE,$K27,DS$16)<=mediçao,BS27,0),0),PLE!$AA$28*BS27) -> 0 | DT27: =IF($K27<>1,IF(ISNUMBER(INDEX(Import.PLE,$K27,DT$16)),IF(INDEX(Import.PLE,$K27,DT$16)<=mediçao,BT27,0),0),PLE!$AA$28*BT27) -> 0 | ... FJ27: =IF($K27<>1,IF(ISNUMBER(INDEX(Import.PLE,$K27,FJ$16)),IF(INDEX(Import.PLE,$K27,FJ$16)<=mediçao,DJ27,0),0),PLE!$AA$28*DJ27) -> 0
B28: =ROW(Nível)-ROW(LIorçamento)+1 -> 11 | C28: =IF(D28="","",IF(ISNUMBER(VALUE(D28)),"Meta",IF(AND(F28<>"",I28<>""),"Serviço","Nível"))) -> Meta | D28: 4 | E28: SERVIÇOS COMPLEMENTARES | G28: =IF(Nível="Serviço",SUMIF($N$15:$BK$15,"<>"&"",N28:BK28),"") | H28: =IF(AND(ISNUMBER(G28),G28<>0),I28/G28,IF(G28=0,0,"")) | K28: =deactivatedados.form1 | BM28: =IF(N$15="",0,IF(ISNUMBER(PreçoUnit),PreçoUnit*INDEX(Import.PLQ,$B28,BM$16),0)) -> 0 | BN28: =IF(O$15="",0,IF(ISNUMBER(PreçoUnit),PreçoUnit*INDEX(Import.PLQ,$B28,BN$16),0)) -> 0 | BO28: =IF(P$15="",0,IF(ISNUMBER(PreçoUnit),PreçoUnit*INDEX(Import.PLQ,$B28,BO$16),0)) -> 0 | BP28: =IF(Q$15="",0,IF(ISNUMBER(PreçoUnit),PreçoUnit*INDEX(Import.PLQ,$B28,BP$16),0)) -> 0 | BQ28: =IF(R$15="",0,IF(ISNUMBER(PreçoUnit),PreçoUnit*INDEX(Import.PLQ,$B28,BQ$16),0)) -> 0 | BR28: =IF(S$15="",0,IF(ISNUMBER(PreçoUnit),PreçoUnit*INDEX(Import.PLQ,$B28,BR$16),0)) -> 0 | BS28: =IF(T$15="",0,IF(ISNUMBER(PreçoUnit),PreçoUnit*INDEX(Import.PLQ,$B28,BS$16),0)) -> 0 | BT28: =IF(U$15="",0,IF(ISNUMBER(PreçoUnit),PreçoUnit*INDEX(Import.PLQ,$B28,BT$16),0)) -> 0 | ... DJ28: =IF(BK$15="",0,IF(ISNUMBER(PreçoUnit),PreçoUnit*INDEX(Import.PLQ,$B28,DJ$16),0)) -> 0 | DK28: =IF(D28="",0,IF(ISNUMBER(VALUE(D28)),VALUE(D28),LEFT(D28,FIND(".",D28)-1))) -> 4 | DL28: =SUM(DM28:FJ28) -> 0 | DM28: =IF($K28<>1,IF(ISNUMBER(INDEX(Import.PLE,$K28,DM$16)),IF(INDEX(Import.PLE,$K28,DM$16)<=mediçao,BM28,0),0),PLE!$AA$28*BM28) -> 0 | DN28: =IF($K28<>1,IF(ISNUMBER(INDEX(Import.PLE,$K28,DN$16)),IF(INDEX(Import.PLE,$K28,DN$16)<=mediçao,BN28,0),0),PLE!$AA$28*BN28) -> 0 | DO28: =IF($K28<>1,IF(ISNUMBER(INDEX(Import.PLE,$K28,DO$16)),IF(INDEX(Import.PLE,$K28,DO$16)<=mediçao,BO28,0),0),PLE!$AA$28*BO28) -> 0 | DP28: =IF($K28<>1,IF(ISNUMBER(INDEX(Import.PLE,$K28,DP$16)),IF(INDEX(Import.PLE,$K28,DP$16)<=mediçao,BP28,0),0),PLE!$AA$28*BP28) -> 0 | DQ28: =IF($K28<>1,IF(ISNUMBER(INDEX(Import.PLE,$K28,DQ$16)),IF(INDEX(Import.PLE,$K28,DQ$16)<=mediçao,BQ28,0),0),PLE!$AA$28*BQ28) -> 0 | DR28: =IF($K28<>1,IF(ISNUMBER(INDEX(Import.PLE,$K28,DR$16)),IF(INDEX(Import.PLE,$K28,DR$16)<=mediçao,BR28,0),0),PLE!$AA$28*BR28) -> 0 | DS28: =IF($K28<>1,IF(ISNUMBER(INDEX(Import.PLE,$K28,DS$16)),IF(INDEX(Import.PLE,$K28,DS$16)<=mediçao,BS28,0),0),PLE!$AA$28*BS28) -> 0 | DT28: =IF($K28<>1,IF(ISNUMBER(INDEX(Import.PLE,$K28,DT$16)),IF(INDEX(Import.PLE,$K28,DT$16)<=mediçao,BT28,0),0),PLE!$AA$28*BT28) -> 0 | ... FJ28: =IF($K28<>1,IF(ISNUMBER(INDEX(Import.PLE,$K28,FJ$16)),IF(INDEX(Import.PLE,$K28,FJ$16)<=mediçao,DJ28,0),0),PLE!$AA$28*DJ28) -> 0
B29: =ROW(Nível)-ROW(LIorçamento)+1 -> 12 | C29: =IF(D29="","",IF(ISNUMBER(VALUE(D29)),"Meta",IF(AND(F29<>"",I29<>""),"Serviço","Nível"))) -> Serviço | D29: 4.1 | E29: Execução de passeio (calçada) em concreto moldado in loco, feito em obra, acabamento convencional, não armado, espessura 6 cm | F29: m³ | G29: =IF(Nível="Serviço",SUMIF($N$15:$BK$15,"<>"&"",N29:BK29),"") -> 100.67 | H29: =IF(AND(ISNUMBER(G29),G29<>0),I29/G29,IF(G29=0,0,"")) -> 864.34996 | I29: 87014.11 | K29: =deactivatedados.form1 -> 3 | L29: 3-CALÇADAS E RAMPAS | N29: 18.23 | O29: 8.89 | P29: 12.29 | Q29: 20.81 | R29: 7.84 | S29: 15.19 | T29: 10.1 | U29: 7.32 | BM29: =IF(N$15="",0,IF(ISNUMBER(PreçoUnit),PreçoUnit*INDEX(Import.PLQ,$B29,BM$16),0)) -> 15757.1 | BN29: =IF(O$15="",0,IF(ISNUMBER(PreçoUnit),PreçoUnit*INDEX(Import.PLQ,$B29,BN$16),0)) -> 7684.0711 | BO29: =IF(P$15="",0,IF(ISNUMBER(PreçoUnit),PreçoUnit*INDEX(Import.PLQ,$B29,BO$16),0)) -> 10622.861 | BP29: =IF(Q$15="",0,IF(ISNUMBER(PreçoUnit),PreçoUnit*INDEX(Import.PLQ,$B29,BP$16),0)) -> 17987.123 | BQ29: =IF(R$15="",0,IF(ISNUMBER(PreçoUnit),PreçoUnit*INDEX(Import.PLQ,$B29,BQ$16),0)) -> 6776.5036 | BR29: =IF(S$15="",0,IF(ISNUMBER(PreçoUnit),PreçoUnit*INDEX(Import.PLQ,$B29,BR$16),0)) -> 13129.476 | BS29: =IF(T$15="",0,IF(ISNUMBER(PreçoUnit),PreçoUnit*INDEX(Import.PLQ,$B29,BS$16),0)) -> 8729.9345 | BT29: =IF(U$15="",0,IF(ISNUMBER(PreçoUnit),PreçoUnit*INDEX(Import.PLQ,$B29,BT$16),0)) -> 6327.0417 | ... DJ29: =IF(BK$15="",0,IF(ISNUMBER(PreçoUnit),PreçoUnit*INDEX(Import.PLQ,$B29,DJ$16),0)) -> 0 | DK29: =IF(D29="",0,IF(ISNUMBER(VALUE(D29)),VALUE(D29),LEFT(D29,FIND(".",D29)-1))) -> 4 | DL29: =SUM(DM29:FJ29) -> 0 | DM29: =IF($K29<>1,IF(ISNUMBER(INDEX(Import.PLE,$K29,DM$16)),IF(INDEX(Import.PLE,$K29,DM$16)<=mediçao,BM29,0),0),PLE!$AA$28*BM29) -> 0 | DN29: =IF($K29<>1,IF(ISNUMBER(INDEX(Import.PLE,$K29,DN$16)),IF(INDEX(Import.PLE,$K29,DN$16)<=mediçao,BN29,0),0),PLE!$AA$28*BN29) -> 0 | DO29: =IF($K29<>1,IF(ISNUMBER(INDEX(Import.PLE,$K29,DO$16)),IF(INDEX(Import.PLE,$K29,DO$16)<=mediçao,BO29,0),0),PLE!$AA$28*BO29) -> 0 | DP29: =IF($K29<>1,IF(ISNUMBER(INDEX(Import.PLE,$K29,DP$16)),IF(INDEX(Import.PLE,$K29,DP$16)<=mediçao,BP29,0),0),PLE!$AA$28*BP29) -> 0 | DQ29: =IF($K29<>1,IF(ISNUMBER(INDEX(Import.PLE,$K29,DQ$16)),IF(INDEX(Import.PLE,$K29,DQ$16)<=mediçao,BQ29,0),0),PLE!$AA$28*BQ29) -> 0 | DR29: =IF($K29<>1,IF(ISNUMBER(INDEX(Import.PLE,$K29,DR$16)),IF(INDEX(Import.PLE,$K29,DR$16)<=mediçao,BR29,0),0),PLE!$AA$28*BR29) -> 0 | DS29: =IF($K29<>1,IF(ISNUMBER(INDEX(Import.PLE,$K29,DS$16)),IF(INDEX(Import.PLE,$K29,DS$16)<=mediçao,BS29,0),0),PLE!$AA$28*BS29) -> 0 | DT29: =IF($K29<>1,IF(ISNUMBER(INDEX(Import.PLE,$K29,DT$16)),IF(INDEX(Import.PLE,$K29,DT$16)<=mediçao,BT29,0),0),PLE!$AA$28*BT29) -> 0 | ... FJ29: =IF($K29<>1,IF(ISNUMBER(INDEX(Import.PLE,$K29,FJ$16)),IF(INDEX(Import.PLE,$K29,FJ$16)<=mediçao,DJ29,0),0),PLE!$AA$28*DJ29) -> 0
B30: =ROW(Nível)-ROW(LIorçamento)+1 -> 13 | C30: =IF(D30="","",IF(ISNUMBER(VALUE(D30)),"Meta",IF(AND(F30<>"",I30<>""),"Serviço","Nível"))) -> Serviço | D30: 4.2 | E30: Alvenaria de vedação de blocos cerâmicos furados na horizontal de 9x19x19cm (espessura 9cm)para execução de passeio e argamassa de assentamento com preparo em betoneira | F30: m² | G30: =IF(Nível="Serviço",SUMIF($N$15:$BK$15,"<>"&"",N30:BK30),"") -> 314.73 | H30: =IF(AND(ISNUMBER(G30),G30<>0),I30/G30,IF(G30=0,0,"")) -> 53.080005 | I30: 16705.87 | K30: =deactivatedados.form1 -> 3 | L30: 3-CALÇADAS E RAMPAS | N30: 54.52 | O30: 29.01 | P30: 42.33 | Q30: 67.53 | R30: 21.62 | S30: 39.7 | T30: 33.12 | U30: 26.9 | BM30: =IF(N$15="",0,IF(ISNUMBER(PreçoUnit),PreçoUnit*INDEX(Import.PLQ,$B30,BM$16),0)) -> 2893.9219 | BN30: =IF(O$15="",0,IF(ISNUMBER(PreçoUnit),PreçoUnit*INDEX(Import.PLQ,$B30,BN$16),0)) -> 1539.8509 | BO30: =IF(P$15="",0,IF(ISNUMBER(PreçoUnit),PreçoUnit*INDEX(Import.PLQ,$B30,BO$16),0)) -> 2246.8766 | BP30: =IF(Q$15="",0,IF(ISNUMBER(PreçoUnit),PreçoUnit*INDEX(Import.PLQ,$B30,BP$16),0)) -> 3584.4927 | BQ30: =IF(R$15="",0,IF(ISNUMBER(PreçoUnit),PreçoUnit*INDEX(Import.PLQ,$B30,BQ$16),0)) -> 1147.5897 | BR30: =IF(S$15="",0,IF(ISNUMBER(PreçoUnit),PreçoUnit*INDEX(Import.PLQ,$B30,BR$16),0)) -> 2107.2762 | BS30: =IF(T$15="",0,IF(ISNUMBER(PreçoUnit),PreçoUnit*INDEX(Import.PLQ,$B30,BS$16),0)) -> 1758.0098 | BT30: =IF(U$15="",0,IF(ISNUMBER(PreçoUnit),PreçoUnit*INDEX(Import.PLQ,$B30,BT$16),0)) -> 1427.8521 | ... DJ30: =IF(BK$15="",0,IF(ISNUMBER(PreçoUnit),PreçoUnit*INDEX(Import.PLQ,$B30,DJ$16),0)) -> 0 | DK30: =IF(D30="",0,IF(ISNUMBER(VALUE(D30)),VALUE(D30),LEFT(D30,FIND(".",D30)-1))) -> 4 | DL30: =SUM(DM30:FJ30) -> 0 | DM30: =IF($K30<>1,IF(ISNUMBER(INDEX(Import.PLE,$K30,DM$16)),IF(INDEX(Import.PLE,$K30,DM$16)<=mediçao,BM30,0),0),PLE!$AA$28*BM30) -> 0 | DN30: =IF($K30<>1,IF(ISNUMBER(INDEX(Import.PLE,$K30,DN$16)),IF(INDEX(Import.PLE,$K30,DN$16)<=mediçao,BN30,0),0),PLE!$AA$28*BN30) -> 0 | DO30: =IF($K30<>1,IF(ISNUMBER(INDEX(Import.PLE,$K30,DO$16)),IF(INDEX(Import.PLE,$K30,DO$16)<=mediçao,BO30,0),0),PLE!$AA$28*BO30) -> 0 | DP30: =IF($K30<>1,IF(ISNUMBER(INDEX(Import.PLE,$K30,DP$16)),IF(INDEX(Import.PLE,$K30,DP$16)<=mediçao,BP30,0),0),PLE!$AA$28*BP30) -> 0 | DQ30: =IF($K30<>1,IF(ISNUMBER(INDEX(Import.PLE,$K30,DQ$16)),IF(INDEX(Import.PLE,$K30,DQ$16)<=mediçao,BQ30,0),0),PLE!$AA$28*BQ30) -> 0 | DR30: =IF($K30<>1,IF(ISNUMBER(INDEX(Import.PLE,$K30,DR$16)),IF(INDEX(Import.PLE,$K30,DR$16)<=mediçao,BR30,0),0),PLE!$AA$28*BR30) -> 0 | DS30: =IF($K30<>1,IF(ISNUMBER(INDEX(Import.PLE,$K30,DS$16)),IF(INDEX(Import.PLE,$K30,DS$16)<=mediçao,BS30,0),0),PLE!$AA$28*BS30) -> 0 | DT30: =IF($K30<>1,IF(ISNUMBER(INDEX(Import.PLE,$K30,DT$16)),IF(INDEX(Import.PLE,$K30,DT$16)<=mediçao,BT30,0),0),PLE!$AA$28*BT30) -> 0 | ... FJ30: =IF($K30<>1,IF(ISNUMBER(INDEX(Import.PLE,$K30,FJ$16)),IF(INDEX(Import.PLE,$K30,FJ$16)<=mediçao,DJ30,0),0),PLE!$AA$28*DJ30) -> 0
B31: =ROW(Nível)-ROW(LIorçamento)+1 -> 14 | C31: =IF(D31="","",IF(ISNUMBER(VALUE(D31)),"Meta",IF(AND(F31<>"",I31<>""),"Serviço","Nível"))) -> Serviço | D31: 4.3 | E31: Execução de rampa em concreto moldado in loco, feito em obra, acabamento convencional, não armado, conforme ABNT NBR 9050/2004 | F31: m³ | G31: =IF(Nível="Serviço",SUMIF($N$15:$BK$15,"<>"&"",N31:BK31),"") -> 25.63 | H31: =IF(AND(ISNUMBER(G31),G31<>0),I31/G31,IF(G31=0,0,"")) -> 864.34998 | I31: 22153.29 | K31: =deactivatedados.form1 -> 3 | L31: 3-CALÇADAS E RAMPAS | N31: 5.26 | O31: 2.63 | P31: 3.94 | Q31: 5.26 | R31: 1.31 | S31: 1.97 | T31: 2.63 | U31: 2.63 | BM31: =IF(N$15="",0,IF(ISNUMBER(PreçoUnit),PreçoUnit*INDEX(Import.PLQ,$B31,BM$16),0)) -> 4546.4809 | BN31: =IF(O$15="",0,IF(ISNUMBER(PreçoUnit),PreçoUnit*INDEX(Import.PLQ,$B31,BN$16),0)) -> 2273.2404 | BO31: =IF(P$15="",0,IF(ISNUMBER(PreçoUnit),PreçoUnit*INDEX(Import.PLQ,$B31,BO$16),0)) -> 3405.5389 | BP31: =IF(Q$15="",0,IF(ISNUMBER(PreçoUnit),PreçoUnit*INDEX(Import.PLQ,$B31,BP$16),0)) -> 4546.4809 | BQ31: =IF(R$15="",0,IF(ISNUMBER(PreçoUnit),PreçoUnit*INDEX(Import.PLQ,$B31,BQ$16),0)) -> 1132.2985 | BR31: =IF(S$15="",0,IF(ISNUMBER(PreçoUnit),PreçoUnit*INDEX(Import.PLQ,$B31,BR$16),0)) -> 1702.7695 | BS31: =IF(T$15="",0,IF(ISNUMBER(PreçoUnit),PreçoUnit*INDEX(Import.PLQ,$B31,BS$16),0)) -> 2273.2404 | BT31: =IF(U$15="",0,IF(ISNUMBER(PreçoUnit),PreçoUnit*INDEX(Import.PLQ,$B31,BT$16),0)) -> 2273.2404 | ... DJ31: =IF(BK$15="",0,IF(ISNUMBER(PreçoUnit),PreçoUnit*INDEX(Import.PLQ,$B31,DJ$16),0)) -> 0 | DK31: =IF(D31="",0,IF(ISNUMBER(VALUE(D31)),VALUE(D31),LEFT(D31,FIND(".",D31)-1))) -> 4 | DL31: =SUM(DM31:FJ31) -> 0 | DM31: =IF($K31<>1,IF(ISNUMBER(INDEX(Import.PLE,$K31,DM$16)),IF(INDEX(Import.PLE,$K31,DM$16)<=mediçao,BM31,0),0),PLE!$AA$28*BM31) -> 0 | DN31: =IF($K31<>1,IF(ISNUMBER(INDEX(Import.PLE,$K31,DN$16)),IF(INDEX(Import.PLE,$K31,DN$16)<=mediçao,BN31,0),0),PLE!$AA$28*BN31) -> 0 | DO31: =IF($K31<>1,IF(ISNUMBER(INDEX(Import.PLE,$K31,DO$16)),IF(INDEX(Import.PLE,$K31,DO$16)<=mediçao,BO31,0),0),PLE!$AA$28*BO31) -> 0 | DP31: =IF($K31<>1,IF(ISNUMBER(INDEX(Import.PLE,$K31,DP$16)),IF(INDEX(Import.PLE,$K31,DP$16)<=mediçao,BP31,0),0),PLE!$AA$28*BP31) -> 0 | DQ31: =IF($K31<>1,IF(ISNUMBER(INDEX(Import.PLE,$K31,DQ$16)),IF(INDEX(Import.PLE,$K31,DQ$16)<=mediçao,BQ31,0),0),PLE!$AA$28*BQ31) -> 0 | DR31: =IF($K31<>1,IF(ISNUMBER(INDEX(Import.PLE,$K31,DR$16)),IF(INDEX(Import.PLE,$K31,DR$16)<=mediçao,BR31,0),0),PLE!$AA$28*BR31) -> 0 | DS31: =IF($K31<>1,IF(ISNUMBER(INDEX(Import.PLE,$K31,DS$16)),IF(INDEX(Import.PLE,$K31,DS$16)<=mediçao,BS31,0),0),PLE!$AA$28*BS31) -> 0 | DT31: =IF($K31<>1,IF(ISNUMBER(INDEX(Import.PLE,$K31,DT$16)),IF(INDEX(Import.PLE,$K31,DT$16)<=mediçao,BT31,0),0),PLE!$AA$28*BT31) -> 0 | ... FJ31: =IF($K31<>1,IF(ISNUMBER(INDEX(Import.PLE,$K31,FJ$16)),IF(INDEX(Import.PLE,$K31,FJ$16)<=mediçao,DJ31,0),0),PLE!$AA$28*DJ31) -> 0
B32: =ROW(Nível)-ROW(LIorçamento)+1 -> 15 | C32: =IF(D32="","",IF(ISNUMBER(VALUE(D32)),"Meta",IF(AND(F32<>"",I32<>""),"Serviço","Nível"))) -> Serviço | D32: 4.4 | E32: Piso tátil em rampas e calçadas para acessibilidade (rota acessível) | F32: m² | G32: =IF(Nível="Serviço",SUMIF($N$15:$BK$15,"<>"&"",N32:BK32),"") -> 307.65 | H32: =IF(AND(ISNUMBER(G32),G32<>0),I32/G32,IF(G32=0,0,"")) -> 121.78001 | I32: 37465.62 | K32: =deactivatedados.form1 -> 3 | L32: 3-CALÇADAS E RAMPAS | N32: 54.67 | O32: 27.88 | P32: 38.13 | Q32: 62.42 | R32: 24.61 | S32: 45.87 | T32: 30.77 | U32: 23.3 | BM32: =IF(N$15="",0,IF(ISNUMBER(PreçoUnit),PreçoUnit*INDEX(Import.PLQ,$B32,BM$16),0)) -> 6657.7131 | BN32: =IF(O$15="",0,IF(ISNUMBER(PreçoUnit),PreçoUnit*INDEX(Import.PLQ,$B32,BN$16),0)) -> 3395.2267 | BO32: =IF(P$15="",0,IF(ISNUMBER(PreçoUnit),PreçoUnit*INDEX(Import.PLQ,$B32,BO$16),0)) -> 4643.4718 | BP32: =IF(Q$15="",0,IF(ISNUMBER(PreçoUnit),PreçoUnit*INDEX(Import.PLQ,$B32,BP$16),0)) -> 7601.5082 | BQ32: =IF(R$15="",0,IF(ISNUMBER(PreçoUnit),PreçoUnit*INDEX(Import.PLQ,$B32,BQ$16),0)) -> 2997.006 | BR32: =IF(S$15="",0,IF(ISNUMBER(PreçoUnit),PreçoUnit*INDEX(Import.PLQ,$B32,BR$16),0)) -> 5586.049 | BS32: =IF(T$15="",0,IF(ISNUMBER(PreçoUnit),PreçoUnit*INDEX(Import.PLQ,$B32,BS$16),0)) -> 3747.1709 | BT32: =IF(U$15="",0,IF(ISNUMBER(PreçoUnit),PreçoUnit*INDEX(Import.PLQ,$B32,BT$16),0)) -> 2837.4742 | ... DJ32: =IF(BK$15="",0,IF(ISNUMBER(PreçoUnit),PreçoUnit*INDEX(Import.PLQ,$B32,DJ$16),0)) -> 0 | DK32: =IF(D32="",0,IF(ISNUMBER(VALUE(D32)),VALUE(D32),LEFT(D32,FIND(".",D32)-1))) -> 4 | DL32: =SUM(DM32:FJ32) -> 0 | DM32: =IF($K32<>1,IF(ISNUMBER(INDEX(Import.PLE,$K32,DM$16)),IF(INDEX(Import.PLE,$K32,DM$16)<=mediçao,BM32,0),0),PLE!$AA$28*BM32) -> 0 | DN32: =IF($K32<>1,IF(ISNUMBER(INDEX(Import.PLE,$K32,DN$16)),IF(INDEX(Import.PLE,$K32,DN$16)<=mediçao,BN32,0),0),PLE!$AA$28*BN32) -> 0 | DO32: =IF($K32<>1,IF(ISNUMBER(INDEX(Import.PLE,$K32,DO$16)),IF(INDEX(Import.PLE,$K32,DO$16)<=mediçao,BO32,0),0),PLE!$AA$28*BO32) -> 0 | DP32: =IF($K32<>1,IF(ISNUMBER(INDEX(Import.PLE,$K32,DP$16)),IF(INDEX(Import.PLE,$K32,DP$16)<=mediçao,BP32,0),0),PLE!$AA$28*BP32) -> 0 | DQ32: =IF($K32<>1,IF(ISNUMBER(INDEX(Import.PLE,$K32,DQ$16)),IF(INDEX(Import.PLE,$K32,DQ$16)<=mediçao,BQ32,0),0),PLE!$AA$28*BQ32) -> 0 | DR32: =IF($K32<>1,IF(ISNUMBER(INDEX(Import.PLE,$K32,DR$16)),IF(INDEX(Import.PLE,$K32,DR$16)<=mediçao,BR32,0),0),PLE!$AA$28*BR32) -> 0 | DS32: =IF($K32<>1,IF(ISNUMBER(INDEX(Import.PLE,$K32,DS$16)),IF(INDEX(Import.PLE,$K32,DS$16)<=mediçao,BS32,0),0),PLE!$AA$28*BS32) -> 0 | DT32: =IF($K32<>1,IF(ISNUMBER(INDEX(Import.PLE,$K32,DT$16)),IF(INDEX(Import.PLE,$K32,DT$16)<=mediçao,BT32,0),0),PLE!$AA$28*BT32) -> 0 | ... FJ32: =IF($K32<>1,IF(ISNUMBER(INDEX(Import.PLE,$K32,FJ$16)),IF(INDEX(Import.PLE,$K32,FJ$16)<=mediçao,DJ32,0),0),PLE!$AA$28*DJ32) -> 0
B33: =ROW(Nível)-ROW(LIorçamento)+1 -> 16 | C33: =IF(D33="","",IF(ISNUMBER(VALUE(D33)),"Meta",IF(AND(F33<>"",I33<>""),"Serviço","Nível"))) -> Serviço | D33: 4.5 | E33: Pintura acrílica em piso cimentado da rampa, 2 demãos | F33: m² | G33: =IF(Nível="Serviço",SUMIF($N$15:$BK$15,"<>"&"",N33:BK33),"") -> 485.94 | H33: =IF(AND(ISNUMBER(G33),G33<>0),I33/G33,IF(G33=0,0,"")) -> 19.189982 | I33: 9325.18 | K33: =deactivatedados.form1 -> 4 | L33: 4-SINALIZAÇÃO E SERVIÇOS FINAIS | N33: 99.68 | O33: 49.84 | P33: 74.76 | Q33: 99.68 | R33: 24.92 | S33: 37.38 | T33: 49.84 | U33: 49.84 | BM33: =IF(N$15="",0,IF(ISNUMBER(PreçoUnit),PreçoUnit*INDEX(Import.PLQ,$B33,BM$16),0)) -> 1912.8574 | BN33: =IF(O$15="",0,IF(ISNUMBER(PreçoUnit),PreçoUnit*INDEX(Import.PLQ,$B33,BN$16),0)) -> 956.42872 | BO33: =IF(P$15="",0,IF(ISNUMBER(PreçoUnit),PreçoUnit*INDEX(Import.PLQ,$B33,BO$16),0)) -> 1434.6431 | BP33: =IF(Q$15="",0,IF(ISNUMBER(PreçoUnit),PreçoUnit*INDEX(Import.PLQ,$B33,BP$16),0)) -> 1912.8574 | BQ33: =IF(R$15="",0,IF(ISNUMBER(PreçoUnit),PreçoUnit*INDEX(Import.PLQ,$B33,BQ$16),0)) -> 478.21436 | BR33: =IF(S$15="",0,IF(ISNUMBER(PreçoUnit),PreçoUnit*INDEX(Import.PLQ,$B33,BR$16),0)) -> 717.32154 | BS33: =IF(T$15="",0,IF(ISNUMBER(PreçoUnit),PreçoUnit*INDEX(Import.PLQ,$B33,BS$16),0)) -> 956.42872 | BT33: =IF(U$15="",0,IF(ISNUMBER(PreçoUnit),PreçoUnit*INDEX(Import.PLQ,$B33,BT$16),0)) -> 956.42872 | ... DJ33: =IF(BK$15="",0,IF(ISNUMBER(PreçoUnit),PreçoUnit*INDEX(Import.PLQ,$B33,DJ$16),0)) -> 0 | DK33: =IF(D33="",0,IF(ISNUMBER(VALUE(D33)),VALUE(D33),LEFT(D33,FIND(".",D33)-1))) -> 4 | DL33: =SUM(DM33:FJ33) -> 0 | DM33: =IF($K33<>1,IF(ISNUMBER(INDEX(Import.PLE,$K33,DM$16)),IF(INDEX(Import.PLE,$K33,DM$16)<=mediçao,BM33,0),0),PLE!$AA$28*BM33) -> 0 | DN33: =IF($K33<>1,IF(ISNUMBER(INDEX(Import.PLE,$K33,DN$16)),IF(INDEX(Import.PLE,$K33,DN$16)<=mediçao,BN33,0),0),PLE!$AA$28*BN33) -> 0 | DO33: =IF($K33<>1,IF(ISNUMBER(INDEX(Import.PLE,$K33,DO$16)),IF(INDEX(Import.PLE,$K33,DO$16)<=mediçao,BO33,0),0),PLE!$AA$28*BO33) -> 0 | DP33: =IF($K33<>1,IF(ISNUMBER(INDEX(Import.PLE,$K33,DP$16)),IF(INDEX(Import.PLE,$K33,DP$16)<=mediçao,BP33,0),0),PLE!$AA$28*BP33) -> 0 | DQ33: =IF($K33<>1,IF(ISNUMBER(INDEX(Import.PLE,$K33,DQ$16)),IF(INDEX(Import.PLE,$K33,DQ$16)<=mediçao,BQ33,0),0),PLE!$AA$28*BQ33) -> 0 | DR33: =IF($K33<>1,IF(ISNUMBER(INDEX(Import.PLE,$K33,DR$16)),IF(INDEX(Import.PLE,$K33,DR$16)<=mediçao,BR33,0),0),PLE!$AA$28*BR33) -> 0 | DS33: =IF($K33<>1,IF(ISNUMBER(INDEX(Import.PLE,$K33,DS$16)),IF(INDEX(Import.PLE,$K33,DS$16)<=mediçao,BS33,0),0),PLE!$AA$28*BS33) -> 0 | DT33: =IF($K33<>1,IF(ISNUMBER(INDEX(Import.PLE,$K33,DT$16)),IF(INDEX(Import.PLE,$K33,DT$16)<=mediçao,BT33,0),0),PLE!$AA$28*BT33) -> 0 | ... FJ33: =IF($K33<>1,IF(ISNUMBER(INDEX(Import.PLE,$K33,FJ$16)),IF(INDEX(Import.PLE,$K33,FJ$16)<=mediçao,DJ33,0),0),PLE!$AA$28*DJ33) -> 0
B34: =ROW(Nível)-ROW(LIorçamento)+1 -> 17 | C34: =IF(D34="","",IF(ISNUMBER(VALUE(D34)),"Meta",IF(AND(F34<>"",I34<>""),"Serviço","Nível"))) -> Serviço | D34: 4.6 | E34: Sinalização permanente, vertical, com placa octogonal de aço, padrão DNER, largura 0,60m, com tubo de aço galvanizado de 2,10m, já sendo descontado a altura que ficará contido na base, fixado com base de concreto 40 x 40 x 50 | F34: unid | G34: =IF(Nível="Serviço",SUMIF($N$15:$BK$15,"<>"&"",N34:BK34),"") -> 8 | H34: =IF(AND(ISNUMBER(G34),G34<>0),I34/G34,IF(G34=0,0,"")) -> 688.67 | I34: 5509.36 | K34: =deactivatedados.form1 -> 4 | L34: 4-SINALIZAÇÃO E SERVIÇOS FINAIS | N34: 1 | O34: 2 | P34: 0 | Q34: 1 | R34: 1 | S34: 1 | T34: 1 | U34: 1 | BM34: =IF(N$15="",0,IF(ISNUMBER(PreçoUnit),PreçoUnit*INDEX(Import.PLQ,$B34,BM$16),0)) -> 688.67 | BN34: =IF(O$15="",0,IF(ISNUMBER(PreçoUnit),PreçoUnit*INDEX(Import.PLQ,$B34,BN$16),0)) -> 1377.34 | BO34: =IF(P$15="",0,IF(ISNUMBER(PreçoUnit),PreçoUnit*INDEX(Import.PLQ,$B34,BO$16),0)) -> 0 | BP34: =IF(Q$15="",0,IF(ISNUMBER(PreçoUnit),PreçoUnit*INDEX(Import.PLQ,$B34,BP$16),0)) -> 688.67 | BQ34: =IF(R$15="",0,IF(ISNUMBER(PreçoUnit),PreçoUnit*INDEX(Import.PLQ,$B34,BQ$16),0)) -> 688.67 | BR34: =IF(S$15="",0,IF(ISNUMBER(PreçoUnit),PreçoUnit*INDEX(Import.PLQ,$B34,BR$16),0)) -> 688.67 | BS34: =IF(T$15="",0,IF(ISNUMBER(PreçoUnit),PreçoUnit*INDEX(Import.PLQ,$B34,BS$16),0)) -> 688.67 | BT34: =IF(U$15="",0,IF(ISNUMBER(PreçoUnit),PreçoUnit*INDEX(Import.PLQ,$B34,BT$16),0)) -> 688.67 | ... DJ34: =IF(BK$15="",0,IF(ISNUMBER(PreçoUnit),PreçoUnit*INDEX(Import.PLQ,$B34,DJ$16),0)) -> 0 | DK34: =IF(D34="",0,IF(ISNUMBER(VALUE(D34)),VALUE(D34),LEFT(D34,FIND(".",D34)-1))) -> 4 | DL34: =SUM(DM34:FJ34) -> 0 | DM34: =IF($K34<>1,IF(ISNUMBER(INDEX(Import.PLE,$K34,DM$16)),IF(INDEX(Import.PLE,$K34,DM$16)<=mediçao,BM34,0),0),PLE!$AA$28*BM34) -> 0 | DN34: =IF($K34<>1,IF(ISNUMBER(INDEX(Import.PLE,$K34,DN$16)),IF(INDEX(Import.PLE,$K34,DN$16)<=mediçao,BN34,0),0),PLE!$AA$28*BN34) -> 0 | DO34: =IF($K34<>1,IF(ISNUMBER(INDEX(Import.PLE,$K34,DO$16)),IF(INDEX(Import.PLE,$K34,DO$16)<=mediçao,BO34,0),0),PLE!$AA$28*BO34) -> 0 | DP34: =IF($K34<>1,IF(ISNUMBER(INDEX(Import.PLE,$K34,DP$16)),IF(INDEX(Import.PLE,$K34,DP$16)<=mediçao,BP34,0),0),PLE!$AA$28*BP34) -> 0 | DQ34: =IF($K34<>1,IF(ISNUMBER(INDEX(Import.PLE,$K34,DQ$16)),IF(INDEX(Import.PLE,$K34,DQ$16)<=mediçao,BQ34,0),0),PLE!$AA$28*BQ34) -> 0 | DR34: =IF($K34<>1,IF(ISNUMBER(INDEX(Import.PLE,$K34,DR$16)),IF(INDEX(Import.PLE,$K34,DR$16)<=mediçao,BR34,0),0),PLE!$AA$28*BR34) -> 0 | DS34: =IF($K34<>1,IF(ISNUMBER(INDEX(Import.PLE,$K34,DS$16)),IF(INDEX(Import.PLE,$K34,DS$16)<=mediçao,BS34,0),0),PLE!$AA$28*BS34) -> 0 | DT34: =IF($K34<>1,IF(ISNUMBER(INDEX(Import.PLE,$K34,DT$16)),IF(INDEX(Import.PLE,$K34,DT$16)<=mediçao,BT34,0),0),PLE!$AA$28*BT34) -> 0 | ... FJ34: =IF($K34<>1,IF(ISNUMBER(INDEX(Import.PLE,$K34,FJ$16)),IF(INDEX(Import.PLE,$K34,FJ$16)<=mediçao,DJ34,0),0),PLE!$AA$28*DJ34) -> 0
B35: =ROW(Nível)-ROW(LIorçamento)+1 -> 18 | C35: =IF(D35="","",IF(ISNUMBER(VALUE(D35)),"Meta",IF(AND(F35<>"",I35<>""),"Serviço","Nível"))) -> Serviço | D35: 4.7 | E35: Caiação em meio-fio | F35: m² | G35: =IF(Nível="Serviço",SUMIF($N$15:$BK$15,"<>"&"",N35:BK35),"") -> 435.12 | H35: =IF(AND(ISNUMBER(G35),G35<>0),I35/G35,IF(G35=0,0,"")) -> 1.4400165 | I35: 626.58 | K35: =deactivatedados.form1 -> 4 | L35: 4-SINALIZAÇÃO E SERVIÇOS FINAIS | N35: 88.47 | O35: 38.59 | P35: 53.9 | Q35: 87.2 | R35: 32.54 | S35: 60.48 | T35: 41.82 | U35: 32.12 | BM35: =IF(N$15="",0,IF(ISNUMBER(PreçoUnit),PreçoUnit*INDEX(Import.PLQ,$B35,BM$16),0)) -> 127.39826 | BN35: =IF(O$15="",0,IF(ISNUMBER(PreçoUnit),PreçoUnit*INDEX(Import.PLQ,$B35,BN$16),0)) -> 55.570239 | BO35: =IF(P$15="",0,IF(ISNUMBER(PreçoUnit),PreçoUnit*INDEX(Import.PLQ,$B35,BO$16),0)) -> 77.616892 | BP35: =IF(Q$15="",0,IF(ISNUMBER(PreçoUnit),PreçoUnit*INDEX(Import.PLQ,$B35,BP$16),0)) -> 125.56944 | BQ35: =IF(R$15="",0,IF(ISNUMBER(PreçoUnit),PreçoUnit*INDEX(Import.PLQ,$B35,BQ$16),0)) -> 46.858138 | BR35: =IF(S$15="",0,IF(ISNUMBER(PreçoUnit),PreçoUnit*INDEX(Import.PLQ,$B35,BR$16),0)) -> 87.092201 | BS35: =IF(T$15="",0,IF(ISNUMBER(PreçoUnit),PreçoUnit*INDEX(Import.PLQ,$B35,BS$16),0)) -> 60.221492 | BT35: =IF(U$15="",0,IF(ISNUMBER(PreçoUnit),PreçoUnit*INDEX(Import.PLQ,$B35,BT$16),0)) -> 46.253331 | ... DJ35: =IF(BK$15="",0,IF(ISNUMBER(PreçoUnit),PreçoUnit*INDEX(Import.PLQ,$B35,DJ$16),0)) -> 0 | DK35: =IF(D35="",0,IF(ISNUMBER(VALUE(D35)),VALUE(D35),LEFT(D35,FIND(".",D35)-1))) -> 4 | DL35: =SUM(DM35:FJ35) -> 0 | DM35: =IF($K35<>1,IF(ISNUMBER(INDEX(Import.PLE,$K35,DM$16)),IF(INDEX(Import.PLE,$K35,DM$16)<=mediçao,BM35,0),0),PLE!$AA$28*BM35) -> 0 | DN35: =IF($K35<>1,IF(ISNUMBER(INDEX(Import.PLE,$K35,DN$16)),IF(INDEX(Import.PLE,$K35,DN$16)<=mediçao,BN35,0),0),PLE!$AA$28*BN35) -> 0 | DO35: =IF($K35<>1,IF(ISNUMBER(INDEX(Import.PLE,$K35,DO$16)),IF(INDEX(Import.PLE,$K35,DO$16)<=mediçao,BO35,0),0),PLE!$AA$28*BO35) -> 0 | DP35: =IF($K35<>1,IF(ISNUMBER(INDEX(Import.PLE,$K35,DP$16)),IF(INDEX(Import.PLE,$K35,DP$16)<=mediçao,BP35,0),0),PLE!$AA$28*BP35) -> 0 | DQ35: =IF($K35<>1,IF(ISNUMBER(INDEX(Import.PLE,$K35,DQ$16)),IF(INDEX(Import.PLE,$K35,DQ$16)<=mediçao,BQ35,0),0),PLE!$AA$28*BQ35) -> 0 | DR35: =IF($K35<>1,IF(ISNUMBER(INDEX(Import.PLE,$K35,DR$16)),IF(INDEX(Import.PLE,$K35,DR$16)<=mediçao,BR35,0),0),PLE!$AA$28*BR35) -> 0 | DS35: =IF($K35<>1,IF(ISNUMBER(INDEX(Import.PLE,$K35,DS$16)),IF(INDEX(Import.PLE,$K35,DS$16)<=mediçao,BS35,0),0),PLE!$AA$28*BS35) -> 0 | DT35: =IF($K35<>1,IF(ISNUMBER(INDEX(Import.PLE,$K35,DT$16)),IF(INDEX(Import.PLE,$K35,DT$16)<=mediçao,BT35,0),0),PLE!$AA$28*BT35) -> 0 | ... FJ35: =IF($K35<>1,IF(ISNUMBER(INDEX(Import.PLE,$K35,FJ$16)),IF(INDEX(Import.PLE,$K35,FJ$16)<=mediçao,DJ35,0),0),PLE!$AA$28*DJ35) -> 0
B36: =ROW(Nível)-ROW(LIorçamento)+1 -> 19 | C36: =IF(D36="","",IF(ISNUMBER(VALUE(D36)),"Meta",IF(AND(F36<>"",I36<>""),"Serviço","Nível"))) -> Serviço | D36: 4.8 | E36: Placa esmaltada para identificação de número de rua, dimensões 45x20cm | F36: unid | G36: =IF(Nível="Serviço",SUMIF($N$15:$BK$15,"<>"&"",N36:BK36),"") -> 8 | H36: =IF(AND(ISNUMBER(G36),G36<>0),I36/G36,IF(G36=0,0,"")) -> 487.87 | I36: 3902.96 | K36: =deactivatedados.form1 -> 4 | L36: 4-SINALIZAÇÃO E SERVIÇOS FINAIS | N36: 1 | O36: 1 | P36: 1 | Q36: 1 | R36: 1 | S36: 1 | T36: 1 | U36: 1 | BM36: =IF(N$15="",0,IF(ISNUMBER(PreçoUnit),PreçoUnit*INDEX(Import.PLQ,$B36,BM$16),0)) -> 487.87 | BN36: =IF(O$15="",0,IF(ISNUMBER(PreçoUnit),PreçoUnit*INDEX(Import.PLQ,$B36,BN$16),0)) -> 487.87 | BO36: =IF(P$15="",0,IF(ISNUMBER(PreçoUnit),PreçoUnit*INDEX(Import.PLQ,$B36,BO$16),0)) -> 487.87 | BP36: =IF(Q$15="",0,IF(ISNUMBER(PreçoUnit),PreçoUnit*INDEX(Import.PLQ,$B36,BP$16),0)) -> 487.87 | BQ36: =IF(R$15="",0,IF(ISNUMBER(PreçoUnit),PreçoUnit*INDEX(Import.PLQ,$B36,BQ$16),0)) -> 487.87 | BR36: =IF(S$15="",0,IF(ISNUMBER(PreçoUnit),PreçoUnit*INDEX(Import.PLQ,$B36,BR$16),0)) -> 487.87 | BS36: =IF(T$15="",0,IF(ISNUMBER(PreçoUnit),PreçoUnit*INDEX(Import.PLQ,$B36,BS$16),0)) -> 487.87 | BT36: =IF(U$15="",0,IF(ISNUMBER(PreçoUnit),PreçoUnit*INDEX(Import.PLQ,$B36,BT$16),0)) -> 487.87 | ... DJ36: =IF(BK$15="",0,IF(ISNUMBER(PreçoUnit),PreçoUnit*INDEX(Import.PLQ,$B36,DJ$16),0)) -> 0 | DK36: =IF(D36="",0,IF(ISNUMBER(VALUE(D36)),VALUE(D36),LEFT(D36,FIND(".",D36)-1))) -> 4 | DL36: =SUM(DM36:FJ36) -> 0 | DM36: =IF($K36<>1,IF(ISNUMBER(INDEX(Import.PLE,$K36,DM$16)),IF(INDEX(Import.PLE,$K36,DM$16)<=mediçao,BM36,0),0),PLE!$AA$28*BM36) -> 0 | DN36: =IF($K36<>1,IF(ISNUMBER(INDEX(Import.PLE,$K36,DN$16)),IF(INDEX(Import.PLE,$K36,DN$16)<=mediçao,BN36,0),0),PLE!$AA$28*BN36) -> 0 | DO36: =IF($K36<>1,IF(ISNUMBER(INDEX(Import.PLE,$K36,DO$16)),IF(INDEX(Import.PLE,$K36,DO$16)<=mediçao,BO36,0),0),PLE!$AA$28*BO36) -> 0 | DP36: =IF($K36<>1,IF(ISNUMBER(INDEX(Import.PLE,$K36,DP$16)),IF(INDEX(Import.PLE,$K36,DP$16)<=mediçao,BP36,0),0),PLE!$AA$28*BP36) -> 0 | DQ36: =IF($K36<>1,IF(ISNUMBER(INDEX(Import.PLE,$K36,DQ$16)),IF(INDEX(Import.PLE,$K36,DQ$16)<=mediçao,BQ36,0),0),PLE!$AA$28*BQ36) -> 0 | DR36: =IF($K36<>1,IF(ISNUMBER(INDEX(Import.PLE,$K36,DR$16)),IF(INDEX(Import.PLE,$K36,DR$16)<=mediçao,BR36,0),0),PLE!$AA$28*BR36) -> 0 | DS36: =IF($K36<>1,IF(ISNUMBER(INDEX(Import.PLE,$K36,DS$16)),IF(INDEX(Import.PLE,$K36,DS$16)<=mediçao,BS36,0),0),PLE!$AA$28*BS36) -> 0 | DT36: =IF($K36<>1,IF(ISNUMBER(INDEX(Import.PLE,$K36,DT$16)),IF(INDEX(Import.PLE,$K36,DT$16)<=mediçao,BT36,0),0),PLE!$AA$28*BT36) -> 0 | ... FJ36: =IF($K36<>1,IF(ISNUMBER(INDEX(Import.PLE,$K36,FJ$16)),IF(INDEX(Import.PLE,$K36,FJ$16)<=mediçao,DJ36,0),0),PLE!$AA$28*DJ36) -> 0
B37: =ROW(Nível)-ROW(LIorçamento)+1 -> 20 | C37: Evento | D37: Evento | E37: =INDEX(Eventos,K37,2) -> Administração Local | F37: R$ | G37: =IF(Nível="Serviço",SUMIF($N$15:$BK$15,"<>"&"",N37:BK37),"") | H37: =IF(AND(ISNUMBER(G37),G37<>0),I37/G37,IF(G37=0,0,"")) | I37: =SUM(N37:BK37) -> 0 | K37: =INDEX(Eventos,ROW(Nível)-ROW(LForçamento),1) -> 1 | L37: =IF(AND(NumEvento<>"",Nível="Serviço"),INDEX(Eventos,NumEvento,2),"") | N37: =IF(N$15="",0,SUMIF(Import.numEventos,$K37,OFFSET(PreçoServiçoPorFrente,0,N$16-1,,1))) -> 0 | O37: =IF(O$15="",0,SUMIF(Import.numEventos,$K37,OFFSET(PreçoServiçoPorFrente,0,O$16-1,,1))) -> 0 | P37: =IF(P$15="",0,SUMIF(Import.numEventos,$K37,OFFSET(PreçoServiçoPorFrente,0,P$16-1,,1))) -> 0 | Q37: =IF(Q$15="",0,SUMIF(Import.numEventos,$K37,OFFSET(PreçoServiçoPorFrente,0,Q$16-1,,1))) -> 0 | R37: =IF(R$15="",0,SUMIF(Import.numEventos,$K37,OFFSET(PreçoServiçoPorFrente,0,R$16-1,,1))) -> 0 | S37: =IF(S$15="",0,SUMIF(Import.numEventos,$K37,OFFSET(PreçoServiçoPorFrente,0,S$16-1,,1))) -> 0 | T37: =IF(T$15="",0,SUMIF(Import.numEventos,$K37,OFFSET(PreçoServiçoPorFrente,0,T$16-1,,1))) -> 0 | U37: =IF(U$15="",0,SUMIF(Import.numEventos,$K37,OFFSET(PreçoServiçoPorFrente,0,U$16-1,,1))) -> 0 | ... BK37: =IF(BK$15="",0,SUMIF(Import.numEventos,$K37,OFFSET(PreçoServiçoPorFrente,0,BK$16-1,,1))) -> 0
B38: =ROW(Nível)-ROW(LIorçamento)+1 -> 21 | C38: Evento | D38: Evento | E38: =INDEX(Eventos,K38,2) -> PAVIMENTAÇÃO | F38: R$ | G38: =IF(Nível="Serviço",SUMIF($N$15:$BK$15,"<>"&"",N38:BK38),"") | H38: =IF(AND(ISNUMBER(G38),G38<>0),I38/G38,IF(G38=0,0,"")) | I38: =SUM(N38:BK38) -> 615269.24 | K38: =INDEX(Eventos,ROW(Nível)-ROW(LForçamento),1) -> 2 | L38: =IF(AND(NumEvento<>"",Nível="Serviço"),INDEX(Eventos,NumEvento,2),"") | N38: =IF(N$15="",0,SUMIF(Import.numEventos,$K38,OFFSET(PreçoServiçoPorFrente,0,N$16-1,,1))) -> 127606.93 | O38: =IF(O$15="",0,SUMIF(Import.numEventos,$K38,OFFSET(PreçoServiçoPorFrente,0,O$16-1,,1))) -> 52187.484 | P38: =IF(P$15="",0,SUMIF(Import.numEventos,$K38,OFFSET(PreçoServiçoPorFrente,0,P$16-1,,1))) -> 82542.488 | Q38: =IF(Q$15="",0,SUMIF(Import.numEventos,$K38,OFFSET(PreçoServiçoPorFrente,0,Q$16-1,,1))) -> 119094.95 | R38: =IF(R$15="",0,SUMIF(Import.numEventos,$K38,OFFSET(PreçoServiçoPorFrente,0,R$16-1,,1))) -> 44801.923 | S38: =IF(S$15="",0,SUMIF(Import.numEventos,$K38,OFFSET(PreçoServiçoPorFrente,0,S$16-1,,1))) -> 84346.677 | T38: =IF(T$15="",0,SUMIF(Import.numEventos,$K38,OFFSET(PreçoServiçoPorFrente,0,T$16-1,,1))) -> 59981.004 | U38: =IF(U$15="",0,SUMIF(Import.numEventos,$K38,OFFSET(PreçoServiçoPorFrente,0,U$16-1,,1))) -> 44707.789 | ... BK38: =IF(BK$15="",0,SUMIF(Import.numEventos,$K38,OFFSET(PreçoServiçoPorFrente,0,BK$16-1,,1))) -> 0
B39: =ROW(Nível)-ROW(LIorçamento)+1 -> 22 | C39: Evento | D39: Evento | E39: =INDEX(Eventos,K39,2) -> CALÇADAS E RAMPAS | F39: R$ | G39: =IF(Nível="Serviço",SUMIF($N$15:$BK$15,"<>"&"",N39:BK39),"") | H39: =IF(AND(ISNUMBER(G39),G39<>0),I39/G39,IF(G39=0,0,"")) | I39: =SUM(N39:BK39) -> 163338.89 | K39: =INDEX(Eventos,ROW(Nível)-ROW(LForçamento),1) -> 3 | L39: =IF(AND(NumEvento<>"",Nível="Serviço"),INDEX(Eventos,NumEvento,2),"") | N39: =IF(N$15="",0,SUMIF(Import.numEventos,$K39,OFFSET(PreçoServiçoPorFrente,0,N$16-1,,1))) -> 29855.216 | O39: =IF(O$15="",0,SUMIF(Import.numEventos,$K39,OFFSET(PreçoServiçoPorFrente,0,O$16-1,,1))) -> 14892.389 | P39: =IF(P$15="",0,SUMIF(Import.numEventos,$K39,OFFSET(PreçoServiçoPorFrente,0,P$16-1,,1))) -> 20918.748 | Q39: =IF(Q$15="",0,SUMIF(Import.numEventos,$K39,OFFSET(PreçoServiçoPorFrente,0,Q$16-1,,1))) -> 33719.604 | R39: =IF(R$15="",0,SUMIF(Import.numEventos,$K39,OFFSET(PreçoServiçoPorFrente,0,R$16-1,,1))) -> 12053.398 | S39: =IF(S$15="",0,SUMIF(Import.numEventos,$K39,OFFSET(PreçoServiçoPorFrente,0,S$16-1,,1))) -> 22525.571 | T39: =IF(T$15="",0,SUMIF(Import.numEventos,$K39,OFFSET(PreçoServiçoPorFrente,0,T$16-1,,1))) -> 16508.356 | U39: =IF(U$15="",0,SUMIF(Import.numEventos,$K39,OFFSET(PreçoServiçoPorFrente,0,U$16-1,,1))) -> 12865.608 | ... BK39: =IF(BK$15="",0,SUMIF(Import.numEventos,$K39,OFFSET(PreçoServiçoPorFrente,0,BK$16-1,,1))) -> 0
B40: =ROW(Nível)-ROW(LIorçamento)+1 -> 23 | C40: Evento | D40: Evento | E40: =INDEX(Eventos,K40,2) -> SINALIZAÇÃO E SERVIÇOS FINAIS | F40: R$ | G40: =IF(Nível="Serviço",SUMIF($N$15:$BK$15,"<>"&"",N40:BK40),"") | H40: =IF(AND(ISNUMBER(G40),G40<>0),I40/G40,IF(G40=0,0,"")) | I40: =SUM(N40:BK40) -> 19364.08 | K40: =INDEX(Eventos,ROW(Nível)-ROW(LForçamento),1) -> 4 | L40: =IF(AND(NumEvento<>"",Nível="Serviço"),INDEX(Eventos,NumEvento,2),"") | N40: =IF(N$15="",0,SUMIF(Import.numEventos,$K40,OFFSET(PreçoServiçoPorFrente,0,N$16-1,,1))) -> 3216.7957 | O40: =IF(O$15="",0,SUMIF(Import.numEventos,$K40,OFFSET(PreçoServiçoPorFrente,0,O$16-1,,1))) -> 2877.209 | P40: =IF(P$15="",0,SUMIF(Import.numEventos,$K40,OFFSET(PreçoServiçoPorFrente,0,P$16-1,,1))) -> 2000.13 | Q40: =IF(Q$15="",0,SUMIF(Import.numEventos,$K40,OFFSET(PreçoServiçoPorFrente,0,Q$16-1,,1))) -> 3214.9669 | R40: =IF(R$15="",0,SUMIF(Import.numEventos,$K40,OFFSET(PreçoServiçoPorFrente,0,R$16-1,,1))) -> 1701.6125 | S40: =IF(S$15="",0,SUMIF(Import.numEventos,$K40,OFFSET(PreçoServiçoPorFrente,0,S$16-1,,1))) -> 1980.9537 | T40: =IF(T$15="",0,SUMIF(Import.numEventos,$K40,OFFSET(PreçoServiçoPorFrente,0,T$16-1,,1))) -> 2193.1902 | U40: =IF(U$15="",0,SUMIF(Import.numEventos,$K40,OFFSET(PreçoServiçoPorFrente,0,U$16-1,,1))) -> 2179.222 | ... BK40: =IF(BK$15="",0,SUMIF(Import.numEventos,$K40,OFFSET(PreçoServiçoPorFrente,0,BK$16-1,,1))) -> 0
C42: =Import.Município&", "&TEXT(hoje,"dd")&" de "&TEXT(hoje,"mmmm")&" de "&TEXT(hoje,"aaaa") -> COREMAS/PB, 31 de julho de 2023
C43: Local e Data | O43: Responsável Técnico: | P43: =respPLE -> 0 | U43: Responsável Técnico: | V43: =respPLE -> 0 | AA43: Responsável Técnico: | AB43: =respPLE -> 0 | AG43: Responsável Técnico: | AH43: =respPLE -> 0 | AM43: Responsável Técnico: | AN43: =respPLE -> 0 | AS43: Responsável Técnico: | AT43: =respPLE -> 0 | AY43: Responsável Técnico: | AZ43: =respPLE -> 0 | BE43: Responsável Técnico: | BF43: =respPLE -> 0
O44: CREA / CAU: | P44: =creaPLE -> 0 | U44: CREA / CAU: | V44: =creaPLE -> 0 | AA44: CREA / CAU: | AB44: =creaPLE -> 0 | AG44: CREA / CAU: | AH44: =creaPLE -> 0 | AM44: CREA / CAU: | AN44: =creaPLE -> 0 | AS44: CREA / CAU: | AT44: =creaPLE -> 0 | AY44: CREA / CAU: | AZ44: =creaPLE -> 0 | BE44: CREA / CAU: | BF44: =creaPLE -> 0

Sheet Detalhamento
A1: =mais_um -> #REF! | B1: =OFFSET(LIorçamento,$A1-1,B$16,1,1) -> #REF! | E1: =OFFSET(LIorçamento,$A1-1,E$16,1,1) -> #REF! | F1: =CHOOSE($B$8,IF(OR(Nível="Serviço",Nível="Evento"),E1*10^4+IF(Nível<>"Evento",A1,0),0),IF(Nível<>"Evento",A1,0)) -> #REF! | G1: =OFFSET(LIorçamento,$A1-1,G$16,1,1) -> #REF! | H1: =OFFSET(LIorçamento,$A1-1,H$16,1,1) -> #REF! | I1: =IF(OR(Nível="Serviço",Nível="evento"),OFFSET(LIorçamento,$A1-1,I$16,1,1),"") -> #REF! | J1: =IF(OR(Nível="Serviço",Nível="evento"),SUM(L1:BI1),"") -> #REF! | L1: =IF(L$13="",0,CHOOSE(Detalhamento.OpçãoServiços,OFFSET(Import.PLQ,$A1-1,L$15-1,1,1),IF($E1<>1,IF(ISNUMBER(INDEX(Import.PLE,Detalhamento!$E1,Detalhamento!L$15)),IF(INDEX(Import.PLE,Detalhamento!$E1,Detalhamento!L$15)<=mediçao,OFFSET(Import.PLQ,$A1-1,L$15-1,1,1),0),0),PLE!$AA$28*OFFSET(Import.PLQ,$A1-1,L$15-1,1,1)),IF($E1<>1,IF(ISNUMBER(INDEX(Import.PLE,Detalhamento!$E1,Detalhamento!L$15)),IF(INDEX(Import.PLE,Detalhamento!$E1,Detalhamento!L$15)<=mediçao,0,OFFSET(Import.PLQ,$A1-1,L$15-1,1,1)),OFFSET(Import.PLQ,$A1-1,L$15-1,1,1)),(1-PLE!$AA$28)*OFFSET(Import.PLQ,$A1-1,L$15-1,1,1)))) -> #REF! | M1: =IF(M$13="",0,CHOOSE(Detalhamento.OpçãoServiços,OFFSET(Import.PLQ,$A1-1,M$15-1,1,1),IF($E1<>1,IF(ISNUMBER(INDEX(Import.PLE,Detalhamento!$E1,Detalhamento!M$15)),IF(INDEX(Import.PLE,Detalhamento!$E1,Detalhamento!M$15)<=mediçao,OFFSET(Import.PLQ,$A1-1,M$15-1,1,1),0),0),PLE!$AA$28*OFFSET(Import.PLQ,$A1-1,M$15-1,1,1)),IF($E1<>1,IF(ISNUMBER(INDEX(Import.PLE,Detalhamento!$E1,Detalhamento!M$15)),IF(INDEX(Import.PLE,Detalhamento!$E1,Detalhamento!M$15)<=mediçao,0,OFFSET(Import.PLQ,$A1-1,M$15-1,1,1)),OFFSET(Import.PLQ,$A1-1,M$15-1,1,1)),(1-PLE!$AA$28)*OFFSET(Import.PLQ,$A1-1,M$15-1,1,1)))) -> #REF! | N1: =IF(N$13="",0,CHOOSE(Detalhamento.OpçãoServiços,OFFSET(Import.PLQ,$A1-1,N$15-1,1,1),IF($E1<>1,IF(ISNUMBER(INDEX(Import.PLE,Detalhamento!$E1,Detalhamento!N$15)),IF(INDEX(Import.PLE,Detalhamento!$E1,Detalhamento!N$15)<=mediçao,OFFSET(Import.PLQ,$A1-1,N$15-1,1,1),0),0),PLE!$AA$28*OFFSET(Import.PLQ,$A1-1,N$15-1,1,1)),IF($E1<>1,IF(ISNUMBER(INDEX(Import.PLE,Detalhamento!$E1,Detalhamento!N$15)),IF(INDEX(Import.PLE,Detalhamento!$E1,Detalhamento!N$15)<=mediçao,0,OFFSET(Import.PLQ,$A1-1,N$15-1,1,1)),OFFSET(Import.PLQ,$A1-1,N$15-1,1,1)),(1-PLE!$AA$28)*OFFSET(Import.PLQ,$A1-1,N$15-1,1,1)))) -> #REF! | O1: =IF(O$13="",0,CHOOSE(Detalhamento.OpçãoServiços,OFFSET(Import.PLQ,$A1-1,O$15-1,1,1),IF($E1<>1,IF(ISNUMBER(INDEX(Import.PLE,Detalhamento!$E1,Detalhamento!O$15)),IF(INDEX(Import.PLE,Detalhamento!$E1,Detalhamento!O$15)<=mediçao,OFFSET(Import.PLQ,$A1-1,O$15-1,1,1),0),0),PLE!$AA$28*OFFSET(Import.PLQ,$A1-1,O$15-1,1,1)),IF($E1<>1,IF(ISNUMBER(INDEX(Import.PLE,Detalhamento!$E1,Detalhamento!O$15)),IF(INDEX(Import.PLE,Detalhamento!$E1,Detalhamento!O$15)<=mediçao,0,OFFSET(Import.PLQ,$A1-1,O$15-1,1,1)),OFFSET(Import.PLQ,$A1-1,O$15-1,1,1)),(1-PLE!$AA$28)*OFFSET(Import.PLQ,$A1-1,O$15-1,1,1)))) -> #REF! | P1: =IF(P$13="",0,CHOOSE(Detalhamento.OpçãoServiços,OFFSET(Import.PLQ,$A1-1,P$15-1,1,1),IF($E1<>1,IF(ISNUMBER(INDEX(Import.PLE,Detalhamento!$E1,Detalhamento!P$15)),IF(INDEX(Import.PLE,Detalhamento!$E1,Detalhamento!P$15)<=mediçao,OFFSET(Import.PLQ,$A1-1,P$15-1,1,1),0),0),PLE!$AA$28*OFFSET(Import.PLQ,$A1-1,P$15-1,1,1)),IF($E1<>1,IF(ISNUMBER(INDEX(Import.PLE,Detalhamento!$E1,Detalhamento!P$15)),IF(INDEX(Import.PLE,Detalhamento!$E1,Detalhamento!P$15)<=mediçao,0,OFFSET(Import.PLQ,$A1-1,P$15-1,1,1)),OFFSET(Import.PLQ,$A1-1,P$15-1,1,1)),(1-PLE!$AA$28)*OFFSET(Import.PLQ,$A1-1,P$15-1,1,1)))) -> #REF! | Q1: =IF(Q$13="",0,CHOOSE(Detalhamento.OpçãoServiços,OFFSET(Import.PLQ,$A1-1,Q$15-1,1,1),IF($E1<>1,IF(ISNUMBER(INDEX(Import.PLE,Detalhamento!$E1,Detalhamento!Q$15)),IF(INDEX(Import.PLE,Detalhamento!$E1,Detalhamento!Q$15)<=mediçao,OFFSET(Import.PLQ,$A1-1,Q$15-1,1,1),0),0),PLE!$AA$28*OFFSET(Import.PLQ,$A1-1,Q$15-1,1,1)),IF($E1<>1,IF(ISNUMBER(INDEX(Import.PLE,Detalhamento!$E1,Detalhamento!Q$15)),IF(INDEX(Import.PLE,Detalhamento!$E1,Detalhamento!Q$15)<=mediçao,0,OFFSET(Import.PLQ,$A1-1,Q$15-1,1,1)),OFFSET(Import.PLQ,$A1-1,Q$15-1,1,1)),(1-PLE!$AA$28)*OFFSET(Import.PLQ,$A1-1,Q$15-1,1,1)))) -> #REF! | R1: =IF(R$13="",0,CHOOSE(Detalhamento.OpçãoServiços,OFFSET(Import.PLQ,$A1-1,R$15-1,1,1),IF($E1<>1,IF(ISNUMBER(INDEX(Import.PLE,Detalhamento!$E1,Detalhamento!R$15)),IF(INDEX(Import.PLE,Detalhamento!$E1,Detalhamento!R$15)<=mediçao,OFFSET(Import.PLQ,$A1-1,R$15-1,1,1),0),0),PLE!$AA$28*OFFSET(Import.PLQ,$A1-1,R$15-1,1,1)),IF($E1<>1,IF(ISNUMBER(INDEX(Import.PLE,Detalhamento!$E1,Detalhamento!R$15)),IF(INDEX(Import.PLE,Detalhamento!$E1,Detalhamento!R$15)<=mediçao,0,OFFSET(Import.PLQ,$A1-1,R$15-1,1,1)),OFFSET(Import.PLQ,$A1-1,R$15-1,1,1)),(1-PLE!$AA$28)*OFFSET(Import.PLQ,$A1-1,R$15-1,1,1)))) -> #REF! | S1: =IF(S$13="",0,CHOOSE(Detalhamento.OpçãoServiços,OFFSET(Import.PLQ,$A1-1,S$15-1,1,1),IF($E1<>1,IF(ISNUMBER(INDEX(Import.PLE,Detalhamento!$E1,Detalhamento!S$15)),IF(INDEX(Import.PLE,Detalhamento!$E1,Detalhamento!S$15)<=mediçao,OFFSET(Import.PLQ,$A1-1,S$15-1,1,1),0),0),PLE!$AA$28*OFFSET(Import.PLQ,$A1-1,S$15-1,1,1)),IF($E1<>1,IF(ISNUMBER(INDEX(Import.PLE,Detalhamento!$E1,Detalhamento!S$15)),IF(INDEX(Import.PLE,Detalhamento!$E1,Detalhamento!S$15)<=mediçao,0,OFFSET(Import.PLQ,$A1-1,S$15-1,1,1)),OFFSET(Import.PLQ,$A1-1,S$15-1,1,1)),(1-PLE!$AA$28)*OFFSET(Import.PLQ,$A1-1,S$15-1,1,1)))) -> #REF! | ... BI1: =IF(BI$13="",0,CHOOSE(Detalhamento.OpçãoServiços,OFFSET(Import.PLQ,$A1-1,BI$15-1,1,1),IF($E1<>1,IF(ISNUMBER(INDEX(Import.PLE,Detalhamento!$E1,Detalhamento!BI$15)),IF(INDEX(Import.PLE,Detalhamento!$E1,Detalhamento!BI$15)<=mediçao,OFFSET(Import.PLQ,$A1-1,BI$15-1,1,1),0),0),PLE!$AA$28*OFFSET(Import.PLQ,$A1-1,BI$15-1,1,1)),IF($E1<>1,IF(ISNUMBER(INDEX(Import.PLE,Detalhamento!$E1,Detalhamento!BI$15)),IF(INDEX(Import.PLE,Detalhamento!$E1,Detalhamento!BI$15)<=mediçao,0,OFFSET(Import.PLQ,$A1-1,BI$15-1,1,1)),OFFSET(Import.PLQ,$A1-1,BI$15-1,1,1)),(1-PLE!$AA$28)*OFFSET(Import.PLQ,$A1-1,BI$15-1,1,1)))) -> 0
H2: PLE - Planilha de Levantamento de Eventos Detalhamento de Eventos | Q2: Grau de Sigilo #PUBLICO | W2: Grau de Sigilo #PUBLICO | AC2: Grau de Sigilo #PUBLICO | AI2: Grau de Sigilo #PUBLICO | AO2: Grau de Sigilo #PUBLICO | AU2: Grau de Sigilo #PUBLICO | BA2: Grau de Sigilo #PUBLICO | BG2: Grau de Sigilo #PUBLICO
B6: Eventos
B7: Orçamento
B8: 1
B9: Todos
B10: Executados
B11: A Executar
B12: 1
J13: Frente de Obra: | L13: =IF(Eventograma_e_Quantitativos!N15<>"",Eventograma_e_Quantitativos!N15,"") -> Rua Oficial de Justiça Vicente Gregório Antão | M13: =IF(Eventograma_e_Quantitativos!O15<>"",Eventograma_e_Quantitativos!O15,"") -> Rua Francisca Garrido de Sousa | N13: =IF(Eventograma_e_Quantitativos!P15<>"",Eventograma_e_Quantitativos!P15,"") -> Rua Francisco Batista Silva | O13: =IF(Eventograma_e_Quantitativos!Q15<>"",Eventograma_e_Quantitativos!Q15,"") -> Rua Bartolomeu Buriti | P13: =IF(Eventograma_e_Quantitativos!R15<>"",Eventograma_e_Quantitativos!R15,"") -> Rua Maria Farias de Assis | Q13: =IF(Eventograma_e_Quantitativos!S15<>"",Eventograma_e_Quantitativos!S15,"") -> Rua Roberto Wilson Moura | R13: =IF(Eventograma_e_Quantitativos!T15<>"",Eventograma_e_Quantitativos!T15,"") -> Rua Cícero Eufrásio da Silva | S13: =IF(Eventograma_e_Quantitativos!U15<>"",Eventograma_e_Quantitativos!U15,"") -> Rua Firmino da Silva Lacerda | ... BI13: =IF(Eventograma_e_Quantitativos!BK15<>"",Eventograma_e_Quantitativos!BK15,"")
E14: ="Valor "&CHOOSE(Detalhamento.OpçãoServiços,"de Investimento","Executado","A Executar")&": R$ "&TEXT(SUMIF(OFFSET(Detalhamento,0,6),"Evento",OFFSET(Detalhamento,0,9)),"#.#0,00") -> Valor de Investimento: R$ 797.972,21 | J14: Total por Frente (R$): | L14: =CHOOSE(Detalhamento.OpçãoServiços,SUM(OFFSET(PreçoServiçoPorFrente,0,L15-1,,1)),SUM(OFFSET(PreçoServiçosPorFrente.Executados,0,L15-1,,1)),SUM(OFFSET(PreçoServiçoPorFrente,0,L15-1,,1))-SUM(OFFSET(PreçoServiçosPorFrente.Executados,0,L15-1,,1))) -> 160678.94 | M14: =CHOOSE(Detalhamento.OpçãoServiços,SUM(OFFSET(PreçoServiçoPorFrente,0,M15-1,,1)),SUM(OFFSET(PreçoServiçosPorFrente.Executados,0,M15-1,,1)),SUM(OFFSET(PreçoServiçoPorFrente,0,M15-1,,1))-SUM(OFFSET(PreçoServiçosPorFrente.Executados,0,M15-1,,1))) -> 69957.083 | N14: =CHOOSE(Detalhamento.OpçãoServiços,SUM(OFFSET(PreçoServiçoPorFrente,0,N15-1,,1)),SUM(OFFSET(PreçoServiçosPorFrente.Executados,0,N15-1,,1)),SUM(OFFSET(PreçoServiçoPorFrente,0,N15-1,,1))-SUM(OFFSET(PreçoServiçosPorFrente.Executados,0,N15-1,,1))) -> 105461.37 | O14: =CHOOSE(Detalhamento.OpçãoServiços,SUM(OFFSET(PreçoServiçoPorFrente,0,O15-1,,1)),SUM(OFFSET(PreçoServiçosPorFrente.Executados,0,O15-1,,1)),SUM(OFFSET(PreçoServiçoPorFrente,0,O15-1,,1))-SUM(OFFSET(PreçoServiçosPorFrente.Executados,0,O15-1,,1))) -> 156029.52 | P14: =CHOOSE(Detalhamento.OpçãoServiços,SUM(OFFSET(PreçoServiçoPorFrente,0,P15-1,,1)),SUM(OFFSET(PreçoServiçosPorFrente.Executados,0,P15-1,,1)),SUM(OFFSET(PreçoServiçoPorFrente,0,P15-1,,1))-SUM(OFFSET(PreçoServiçosPorFrente.Executados,0,P15-1,,1))) -> 58556.933 | Q14: =CHOOSE(Detalhamento.OpçãoServiços,SUM(OFFSET(PreçoServiçoPorFrente,0,Q15-1,,1)),SUM(OFFSET(PreçoServiçosPorFrente.Executados,0,Q15-1,,1)),SUM(OFFSET(PreçoServiçoPorFrente,0,Q15-1,,1))-SUM(OFFSET(PreçoServiçosPorFrente.Executados,0,Q15-1,,1))) -> 108853.2 | R14: =CHOOSE(Detalhamento.OpçãoServiços,SUM(OFFSET(PreçoServiçoPorFrente,0,R15-1,,1)),SUM(OFFSET(PreçoServiçosPorFrente.Executados,0,R15-1,,1)),SUM(OFFSET(PreçoServiçoPorFrente,0,R15-1,,1))-SUM(OFFSET(PreçoServiçosPorFrente.Executados,0,R15-1,,1))) -> 78682.55 | S14: =CHOOSE(Detalhamento.OpçãoServiços,SUM(OFFSET(PreçoServiçoPorFrente,0,S15-1,,1)),SUM(OFFSET(PreçoServiçosPorFrente.Executados,0,S15-1,,1)),SUM(OFFSET(PreçoServiçoPorFrente,0,S15-1,,1))-SUM(OFFSET(PreçoServiçosPorFrente.Executados,0,S15-1,,1))) -> 59752.62 | ... BI14: =CHOOSE(Detalhamento.OpçãoServiços,SUM(OFFSET(PreçoServiçoPorFrente,0,BI15-1,,1)),SUM(OFFSET(PreçoServiçosPorFrente.Executados,0,BI15-1,,1)),SUM(OFFSET(PreçoServiçoPorFrente,0,BI15-1,,1))-SUM(OFFSET(PreçoServiçosPorFrente.Executados,0,BI15-1,,1))) -> 0
E15: Evento | F15: Linha Orç | G15: Item Orç | H15: Título dos Eventos / Descrição Serviço | I15: Unid. | J15: Qtde. | L15: 1 | M15: 2 | N15: 3 | O15: 4 | P15: 5 | Q15: 6 | R15: 7 | S15: 8 | T15: 9 | U15: 10 | V15: 11 | W15: 12 | X15: 13 | Y15: 14 | Z15: 15 | AA15: 16 | AB15: 17 | AC15: 18 | AD15: 19 | AE15: 20 | AF15: 21 | AG15: 22 | AH15: 23 | AI15: 24 | AJ15: 25 | AK15: 26 | AL15: 27 | AM15: 28 | AN15: 29 | AO15: 30 | AP15: 31 | AQ15: 32 | AR15: 33 | AS15: 34 | AT15: 35 | AU15: 36 | AV15: 37 | AW15: 38 | AX15: 39 | AY15: 40 | AZ15: 41 | BA15: 42 | BB15: 43 | BC15: 44 | BD15: 45 | BE15: 46 | BF15: 47 | BG15: 48 | BH15: 49 | BI15: 50
B16: 2 | E16: 10 | G16: 3 | H16: 4 | I16: 5 | J16: 8
A17: 1 | B17: =OFFSET(LIorçamento,$A17-1,B$16,1,1) -> Nível | E17: =OFFSET(LIorçamento,$A17-1,E$16,1,1) | F17: =CHOOSE($B$8,IF(OR(Nível="Serviço",Nível="Evento"),E17*10^4+IF(Nível<>"Evento",A17,0),0),IF(Nível<>"Evento",A17,0)) -> 0 | G17: =OFFSET(LIorçamento,$A17-1,G$16,1,1) -> I | H17: =OFFSET(LIorçamento,$A17-1,H$16,1,1) -> PAVIMENTAÇÃO DE RUAS | I17: =IF(OR(Nível="Serviço",Nível="evento"),OFFSET(LIorçamento,$A17-1,I$16,1,1),"") | J17: =IF(OR(Nível="Serviço",Nível="evento"),SUM(L17:BI17),"") | L17: =IF(L$13="",0,CHOOSE(Detalhamento.OpçãoServiços,OFFSET(Import.PLQ,$A17-1,L$15-1,1,1),IF($E17<>1,IF(ISNUMBER(INDEX(Import.PLE,Detalhamento!$E17,Detalhamento!L$15)),IF(INDEX(Import.PLE,Detalhamento!$E17,Detalhamento!L$15)<=mediçao,OFFSET(Import.PLQ,$A17-1,L$15-1,1,1),0),0),PLE!$AA$28*OFFSET(Import.PLQ,$A17-1,L$15-1,1,1)),IF($E17<>1,IF(ISNUMBER(INDEX(Import.PLE,Detalhamento!$E17,Detalhamento!L$15)),IF(INDEX(Import.PLE,Detalhamento!$E17,Detalhamento!L$15)<=mediçao,0,OFFSET(Import.PLQ,$A17-1,L$15-1,1,1)),OFFSET(Import.PLQ,$A17-1,L$15-1,1,1)),(1-PLE!$AA$28)*OFFSET(Import.PLQ,$A17-1,L$15-1,1,1)))) -> 0 | M17: =IF(M$13="",0,CHOOSE(Detalhamento.OpçãoServiços,OFFSET(Import.PLQ,$A17-1,M$15-1,1,1),IF($E17<>1,IF(ISNUMBER(INDEX(Import.PLE,Detalhamento!$E17,Detalhamento!M$15)),IF(INDEX(Import.PLE,Detalhamento!$E17,Detalhamento!M$15)<=mediçao,OFFSET(Import.PLQ,$A17-1,M$15-1,1,1),0),0),PLE!$AA$28*OFFSET(Import.PLQ,$A17-1,M$15-1,1,1)),IF($E17<>1,IF(ISNUMBER(INDEX(Import.PLE,Detalhamento!$E17,Detalhamento!M$15)),IF(INDEX(Import.PLE,Detalhamento!$E17,Detalhamento!M$15)<=mediçao,0,OFFSET(Import.PLQ,$A17-1,M$15-1,1,1)),OFFSET(Import.PLQ,$A17-1,M$15-1,1,1)),(1-PLE!$AA$28)*OFFSET(Import.PLQ,$A17-1,M$15-1,1,1)))) -> 0 | N17: =IF(N$13="",0,CHOOSE(Detalhamento.OpçãoServiços,OFFSET(Import.PLQ,$A17-1,N$15-1,1,1),IF($E17<>1,IF(ISNUMBER(INDEX(Import.PLE,Detalhamento!$E17,Detalhamento!N$15)),IF(INDEX(Import.PLE,Detalhamento!$E17,Detalhamento!N$15)<=mediçao,OFFSET(Import.PLQ,$A17-1,N$15-1,1,1),0),0),PLE!$AA$28*OFFSET(Import.PLQ,$A17-1,N$15-1,1,1)),IF($E17<>1,IF(ISNUMBER(INDEX(Import.PLE,Detalhamento!$E17,Detalhamento!N$15)),IF(INDEX(Import.PLE,Detalhamento!$E17,Detalhamento!N$15)<=mediçao,0,OFFSET(Import.PLQ,$A17-1,N$15-1,1,1)),OFFSET(Import.PLQ,$A17-1,N$15-1,1,1)),(1-PLE!$AA$28)*OFFSET(Import.PLQ,$A17-1,N$15-1,1,1)))) -> 0 | O17: =IF(O$13="",0,CHOOSE(Detalhamento.OpçãoServiços,OFFSET(Import.PLQ,$A17-1,O$15-1,1,1),IF($E17<>1,IF(ISNUMBER(INDEX(Import.PLE,Detalhamento!$E17,Detalhamento!O$15)),IF(INDEX(Import.PLE,Detalhamento!$E17,Detalhamento!O$15)<=mediçao,OFFSET(Import.PLQ,$A17-1,O$15-1,1,1),0),0),PLE!$AA$28*OFFSET(Import.PLQ,$A17-1,O$15-1,1,1)),IF($E17<>1,IF(ISNUMBER(INDEX(Import.PLE,Detalhamento!$E17,Detalhamento!O$15)),IF(INDEX(Import.PLE,Detalhamento!$E17,Detalhamento!O$15)<=mediçao,0,OFFSET(Import.PLQ,$A17-1,O$15-1,1,1)),OFFSET(Import.PLQ,$A17-1,O$15-1,1,1)),(1-PLE!$AA$28)*OFFSET(Import.PLQ,$A17-1,O$15-1,1,1)))) -> 0 | P17: =IF(P$13="",0,CHOOSE(Detalhamento.OpçãoServiços,OFFSET(Import.PLQ,$A17-1,P$15-1,1,1),IF($E17<>1,IF(ISNUMBER(INDEX(Import.PLE,Detalhamento!$E17,Detalhamento!P$15)),IF(INDEX(Import.PLE,Detalhamento!$E17,Detalhamento!P$15)<=mediçao,OFFSET(Import.PLQ,$A17-1,P$15-1,1,1),0),0),PLE!$AA$28*OFFSET(Import.PLQ,$A17-1,P$15-1,1,1)),IF($E17<>1,IF(ISNUMBER(INDEX(Import.PLE,Detalhamento!$E17,Detalhamento!P$15)),IF(INDEX(Import.PLE,Detalhamento!$E17,Detalhamento!P$15)<=mediçao,0,OFFSET(Import.PLQ,$A17-1,P$15-1,1,1)),OFFSET(Import.PLQ,$A17-1,P$15-1,1,1)),(1-PLE!$AA$28)*OFFSET(Import.PLQ,$A17-1,P$15-1,1,1)))) -> 0 | Q17: =IF(Q$13="",0,CHOOSE(Detalhamento.OpçãoServiços,OFFSET(Import.PLQ,$A17-1,Q$15-1,1,1),IF($E17<>1,IF(ISNUMBER(INDEX(Import.PLE,Detalhamento!$E17,Detalhamento!Q$15)),IF(INDEX(Import.PLE,Detalhamento!$E17,Detalhamento!Q$15)<=mediçao,OFFSET(Import.PLQ,$A17-1,Q$15-1,1,1),0),0),PLE!$AA$28*OFFSET(Import.PLQ,$A17-1,Q$15-1,1,1)),IF($E17<>1,IF(ISNUMBER(INDEX(Import.PLE,Detalhamento!$E17,Detalhamento!Q$15)),IF(INDEX(Import.PLE,Detalhamento!$E17,Detalhamento!Q$15)<=mediçao,0,OFFSET(Import.PLQ,$A17-1,Q$15-1,1,1)),OFFSET(Import.PLQ,$A17-1,Q$15-1,1,1)),(1-PLE!$AA$28)*OFFSET(Import.PLQ,$A17-1,Q$15-1,1,1)))) -> 0 | R17: =IF(R$13="",0,CHOOSE(Detalhamento.OpçãoServiços,OFFSET(Import.PLQ,$A17-1,R$15-1,1,1),IF($E17<>1,IF(ISNUMBER(INDEX(Import.PLE,Detalhamento!$E17,Detalhamento!R$15)),IF(INDEX(Import.PLE,Detalhamento!$E17,Detalhamento!R$15)<=mediçao,OFFSET(Import.PLQ,$A17-1,R$15-1,1,1),0),0),PLE!$AA$28*OFFSET(Import.PLQ,$A17-1,R$15-1,1,1)),IF($E17<>1,IF(ISNUMBER(INDEX(Import.PLE,Detalhamento!$E17,Detalhamento!R$15)),IF(INDEX(Import.PLE,Detalhamento!$E17,Detalhamento!R$15)<=mediçao,0,OFFSET(Import.PLQ,$A17-1,R$15-1,1,1)),OFFSET(Import.PLQ,$A17-1,R$15-1,1,1)),(1-PLE!$AA$28)*OFFSET(Import.PLQ,$A17-1,R$15-1,1,1)))) -> 0 | S17: =IF(S$13="",0,CHOOSE(Detalhamento.OpçãoServiços,OFFSET(Import.PLQ,$A17-1,S$15-1,1,1),IF($E17<>1,IF(ISNUMBER(INDEX(Import.PLE,Detalhamento!$E17,Detalhamento!S$15)),IF(INDEX(Import.PLE,Detalhamento!$E17,Detalhamento!S$15)<=mediçao,OFFSET(Import.PLQ,$A17-1,S$15-1,1,1),0),0),PLE!$AA$28*OFFSET(Import.PLQ,$A17-1,S$15-1,1,1)),IF($E17<>1,IF(ISNUMBER(INDEX(Import.PLE,Detalhamento!$E17,Detalhamento!S$15)),IF(INDEX(Import.PLE,Detalhamento!$E17,Detalhamento!S$15)<=mediçao,0,OFFSET(Import.PLQ,$A17-1,S$15-1,1,1)),OFFSET(Import.PLQ,$A17-1,S$15-1,1,1)),(1-PLE!$AA$28)*OFFSET(Import.PLQ,$A17-1,S$15-1,1,1)))) -> 0 | ... BI17: =IF(BI$13="",0,CHOOSE(Detalhamento.OpçãoServiços,OFFSET(Import.PLQ,$A17-1,BI$15-1,1,1),IF($E17<>1,IF(ISNUMBER(INDEX(Import.PLE,Detalhamento!$E17,Detalhamento!BI$15)),IF(INDEX(Import.PLE,Detalhamento!$E17,Detalhamento!BI$15)<=mediçao,OFFSET(Import.PLQ,$A17-1,BI$15-1,1,1),0),0),PLE!$AA$28*OFFSET(Import.PLQ,$A17-1,BI$15-1,1,1)),IF($E17<>1,IF(ISNUMBER(INDEX(Import.PLE,Detalhamento!$E17,Detalhamento!BI$15)),IF(INDEX(Import.PLE,Detalhamento!$E17,Detalhamento!BI$15)<=mediçao,0,OFFSET(Import.PLQ,$A17-1,BI$15-1,1,1)),OFFSET(Import.PLQ,$A17-1,BI$15-1,1,1)),(1-PLE!$AA$28)*OFFSET(Import.PLQ,$A17-1,BI$15-1,1,1)))) -> 0
A18: 2 | B18: =OFFSET(LIorçamento,$A18-1,B$16,1,1) -> Meta | E18: =OFFSET(LIorçamento,$A18-1,E$16,1,1) | F18: =CHOOSE($B$8,IF(OR(Nível="Serviço",Nível="Evento"),E18*10^4+IF(Nível<>"Evento",A18,0),0),IF(Nível<>"Evento",A18,0)) -> 0 | G18: =OFFSET(LIorçamento,$A18-1,G$16,1,1) -> 1 | H18: =OFFSET(LIorçamento,$A18-1,H$16,1,1) -> SERVIÇOS PRELIMINARES | I18: =IF(OR(Nível="Serviço",Nível="evento"),OFFSET(LIorçamento,$A18-1,I$16,1,1),"") | J18: =IF(OR(Nível="Serviço",Nível="evento"),SUM(L18:BI18),"") | L18: =IF(L$13="",0,CHOOSE(Detalhamento.OpçãoServiços,OFFSET(Import.PLQ,$A18-1,L$15-1,1,1),IF($E18<>1,IF(ISNUMBER(INDEX(Import.PLE,Detalhamento!$E18,Detalhamento!L$15)),IF(INDEX(Import.PLE,Detalhamento!$E18,Detalhamento!L$15)<=mediçao,OFFSET(Import.PLQ,$A18-1,L$15-1,1,1),0),0),PLE!$AA$28*OFFSET(Import.PLQ,$A18-1,L$15-1,1,1)),IF($E18<>1,IF(ISNUMBER(INDEX(Import.PLE,Detalhamento!$E18,Detalhamento!L$15)),IF(INDEX(Import.PLE,Detalhamento!$E18,Detalhamento!L$15)<=mediçao,0,OFFSET(Import.PLQ,$A18-1,L$15-1,1,1)),OFFSET(Import.PLQ,$A18-1,L$15-1,1,1)),(1-PLE!$AA$28)*OFFSET(Import.PLQ,$A18-1,L$15-1,1,1)))) -> 0 | M18: =IF(M$13="",0,CHOOSE(Detalhamento.OpçãoServiços,OFFSET(Import.PLQ,$A18-1,M$15-1,1,1),IF($E18<>1,IF(ISNUMBER(INDEX(Import.PLE,Detalhamento!$E18,Detalhamento!M$15)),IF(INDEX(Import.PLE,Detalhamento!$E18,Detalhamento!M$15)<=mediçao,OFFSET(Import.PLQ,$A18-1,M$15-1,1,1),0),0),PLE!$AA$28*OFFSET(Import.PLQ,$A18-1,M$15-1,1,1)),IF($E18<>1,IF(ISNUMBER(INDEX(Import.PLE,Detalhamento!$E18,Detalhamento!M$15)),IF(INDEX(Import.PLE,Detalhamento!$E18,Detalhamento!M$15)<=mediçao,0,OFFSET(Import.PLQ,$A18-1,M$15-1,1,1)),OFFSET(Import.PLQ,$A18-1,M$15-1,1,1)),(1-PLE!$AA$28)*OFFSET(Import.PLQ,$A18-1,M$15-1,1,1)))) -> 0 | N18: =IF(N$13="",0,CHOOSE(Detalhamento.OpçãoServiços,OFFSET(Import.PLQ,$A18-1,N$15-1,1,1),IF($E18<>1,IF(ISNUMBER(INDEX(Import.PLE,Detalhamento!$E18,Detalhamento!N$15)),IF(INDEX(Import.PLE,Detalhamento!$E18,Detalhamento!N$15)<=mediçao,OFFSET(Import.PLQ,$A18-1,N$15-1,1,1),0),0),PLE!$AA$28*OFFSET(Import.PLQ,$A18-1,N$15-1,1,1)),IF($E18<>1,IF(ISNUMBER(INDEX(Import.PLE,Detalhamento!$E18,Detalhamento!N$15)),IF(INDEX(Import.PLE,Detalhamento!$E18,Detalhamento!N$15)<=mediçao,0,OFFSET(Import.PLQ,$A18-1,N$15-1,1,1)),OFFSET(Import.PLQ,$A18-1,N$15-1,1,1)),(1-PLE!$AA$28)*OFFSET(Import.PLQ,$A18-1,N$15-1,1,1)))) -> 0 | O18: =IF(O$13="",0,CHOOSE(Detalhamento.OpçãoServiços,OFFSET(Import.PLQ,$A18-1,O$15-1,1,1),IF($E18<>1,IF(ISNUMBER(INDEX(Import.PLE,Detalhamento!$E18,Detalhamento!O$15)),IF(INDEX(Import.PLE,Detalhamento!$E18,Detalhamento!O$15)<=mediçao,OFFSET(Import.PLQ,$A18-1,O$15-1,1,1),0),0),PLE!$AA$28*OFFSET(Import.PLQ,$A18-1,O$15-1,1,1)),IF($E18<>1,IF(ISNUMBER(INDEX(Import.PLE,Detalhamento!$E18,Detalhamento!O$15)),IF(INDEX(Import.PLE,Detalhamento!$E18,Detalhamento!O$15)<=mediçao,0,OFFSET(Import.PLQ,$A18-1,O$15-1,1,1)),OFFSET(Import.PLQ,$A18-1,O$15-1,1,1)),(1-PLE!$AA$28)*OFFSET(Import.PLQ,$A18-1,O$15-1,1,1)))) -> 0 | P18: =IF(P$13="",0,CHOOSE(Detalhamento.OpçãoServiços,OFFSET(Import.PLQ,$A18-1,P$15-1,1,1),IF($E18<>1,IF(ISNUMBER(INDEX(Import.PLE,Detalhamento!$E18,Detalhamento!P$15)),IF(INDEX(Import.PLE,Detalhamento!$E18,Detalhamento!P$15)<=mediçao,OFFSET(Import.PLQ,$A18-1,P$15-1,1,1),0),0),PLE!$AA$28*OFFSET(Import.PLQ,$A18-1,P$15-1,1,1)),IF($E18<>1,IF(ISNUMBER(INDEX(Import.PLE,Detalhamento!$E18,Detalhamento!P$15)),IF(INDEX(Import.PLE,Detalhamento!$E18,Detalhamento!P$15)<=mediçao,0,OFFSET(Import.PLQ,$A18-1,P$15-1,1,1)),OFFSET(Import.PLQ,$A18-1,P$15-1,1,1)),(1-PLE!$AA$28)*OFFSET(Import.PLQ,$A18-1,P$15-1,1,1)))) -> 0 | Q18: =IF(Q$13="",0,CHOOSE(Detalhamento.OpçãoServiços,OFFSET(Import.PLQ,$A18-1,Q$15-1,1,1),IF($E18<>1,IF(ISNUMBER(INDEX(Import.PLE,Detalhamento!$E18,Detalhamento!Q$15)),IF(INDEX(Import.PLE,Detalhamento!$E18,Detalhamento!Q$15)<=mediçao,OFFSET(Import.PLQ,$A18-1,Q$15-1,1,1),0),0),PLE!$AA$28*OFFSET(Import.PLQ,$A18-1,Q$15-1,1,1)),IF($E18<>1,IF(ISNUMBER(INDEX(Import.PLE,Detalhamento!$E18,Detalhamento!Q$15)),IF(INDEX(Import.PLE,Detalhamento!$E18,Detalhamento!Q$15)<=mediçao,0,OFFSET(Import.PLQ,$A18-1,Q$15-1,1,1)),OFFSET(Import.PLQ,$A18-1,Q$15-1,1,1)),(1-PLE!$AA$28)*OFFSET(Import.PLQ,$A18-1,Q$15-1,1,1)))) -> 0 | R18: =IF(R$13="",0,CHOOSE(Detalhamento.OpçãoServiços,OFFSET(Import.PLQ,$A18-1,R$15-1,1,1),IF($E18<>1,IF(ISNUMBER(INDEX(Import.PLE,Detalhamento!$E18,Detalhamento!R$15)),IF(INDEX(Import.PLE,Detalhamento!$E18,Detalhamento!R$15)<=mediçao,OFFSET(Import.PLQ,$A18-1,R$15-1,1,1),0),0),PLE!$AA$28*OFFSET(Import.PLQ,$A18-1,R$15-1,1,1)),IF($E18<>1,IF(ISNUMBER(INDEX(Import.PLE,Detalhamento!$E18,Detalhamento!R$15)),IF(INDEX(Import.PLE,Detalhamento!$E18,Detalhamento!R$15)<=mediçao,0,OFFSET(Import.PLQ,$A18-1,R$15-1,1,1)),OFFSET(Import.PLQ,$A18-1,R$15-1,1,1)),(1-PLE!$AA$28)*OFFSET(Import.PLQ,$A18-1,R$15-1,1,1)))) -> 0 | S18: =IF(S$13="",0,CHOOSE(Detalhamento.OpçãoServiços,OFFSET(Import.PLQ,$A18-1,S$15-1,1,1),IF($E18<>1,IF(ISNUMBER(INDEX(Import.PLE,Detalhamento!$E18,Detalhamento!S$15)),IF(INDEX(Import.PLE,Detalhamento!$E18,Detalhamento!S$15)<=mediçao,OFFSET(Import.PLQ,$A18-1,S$15-1,1,1),0),0),PLE!$AA$28*OFFSET(Import.PLQ,$A18-1,S$15-1,1,1)),IF($E18<>1,IF(ISNUMBER(INDEX(Import.PLE,Detalhamento!$E18,Detalhamento!S$15)),IF(INDEX(Import.PLE,Detalhamento!$E18,Detalhamento!S$15)<=mediçao,0,OFFSET(Import.PLQ,$A18-1,S$15-1,1,1)),OFFSET(Import.PLQ,$A18-1,S$15-1,1,1)),(1-PLE!$AA$28)*OFFSET(Import.PLQ,$A18-1,S$15-1,1,1)))) -> 0 | ... BI18: =IF(BI$13="",0,CHOOSE(Detalhamento.OpçãoServiços,OFFSET(Import.PLQ,$A18-1,BI$15-1,1,1),IF($E18<>1,IF(ISNUMBER(INDEX(Import.PLE,Detalhamento!$E18,Detalhamento!BI$15)),IF(INDEX(Import.PLE,Detalhamento!$E18,Detalhamento!BI$15)<=mediçao,OFFSET(Import.PLQ,$A18-1,BI$15-1,1,1),0),0),PLE!$AA$28*OFFSET(Import.PLQ,$A18-1,BI$15-1,1,1)),IF($E18<>1,IF(ISNUMBER(INDEX(Import.PLE,Detalhamento!$E18,Detalhamento!BI$15)),IF(INDEX(Import.PLE,Detalhamento!$E18,Detalhamento!BI$15)<=mediçao,0,OFFSET(Import.PLQ,$A18-1,BI$15-1,1,1)),OFFSET(Import.PLQ,$A18-1,BI$15-1,1,1)),(1-PLE!$AA$28)*OFFSET(Import.PLQ,$A18-1,BI$15-1,1,1)))) -> 0
A19: 20 | B19: =OFFSET(LIorçamento,$A19-1,B$16,1,1) -> Evento | E19: =OFFSET(LIorçamento,$A19-1,E$16,1,1) -> 1 | F19: =CHOOSE($B$8,IF(OR(Nível="Serviço",Nível="Evento"),E19*10^4+IF(Nível<>"Evento",A19,0),0),IF(Nível<>"Evento",A19,0)) -> 10000 | G19: =OFFSET(LIorçamento,$A19-1,G$16,1,1) -> Evento | H19: =OFFSET(LIorçamento,$A19-1,H$16,1,1) -> Administração Local | I19: =IF(OR(Nível="Serviço",Nível="evento"),OFFSET(LIorçamento,$A19-1,I$16,1,1),"") -> R$ | J19: =IF(OR(Nível="Serviço",Nível="evento"),SUM(L19:BI19),"") -> 0 | L19: =IF(L$13="",0,CHOOSE(Detalhamento.OpçãoServiços,OFFSET(Import.PLQ,$A19-1,L$15-1,1,1),IF($E19<>1,IF(ISNUMBER(INDEX(Import.PLE,Detalhamento!$E19,Detalhamento!L$15)),IF(INDEX(Import.PLE,Detalhamento!$E19,Detalhamento!L$15)<=mediçao,OFFSET(Import.PLQ,$A19-1,L$15-1,1,1),0),0),PLE!$AA$28*OFFSET(Import.PLQ,$A19-1,L$15-1,1,1)),IF($E19<>1,IF(ISNUMBER(INDEX(Import.PLE,Detalhamento!$E19,Detalhamento!L$15)),IF(INDEX(Import.PLE,Detalhamento!$E19,Detalhamento!L$15)<=mediçao,0,OFFSET(Import.PLQ,$A19-1,L$15-1,1,1)),OFFSET(Import.PLQ,$A19-1,L$15-1,1,1)),(1-PLE!$AA$28)*OFFSET(Import.PLQ,$A19-1,L$15-1,1,1)))) -> 0 | M19: =IF(M$13="",0,CHOOSE(Detalhamento.OpçãoServiços,OFFSET(Import.PLQ,$A19-1,M$15-1,1,1),IF($E19<>1,IF(ISNUMBER(INDEX(Import.PLE,Detalhamento!$E19,Detalhamento!M$15)),IF(INDEX(Import.PLE,Detalhamento!$E19,Detalhamento!M$15)<=mediçao,OFFSET(Import.PLQ,$A19-1,M$15-1,1,1),0),0),PLE!$AA$28*OFFSET(Import.PLQ,$A19-1,M$15-1,1,1)),IF($E19<>1,IF(ISNUMBER(INDEX(Import.PLE,Detalhamento!$E19,Detalhamento!M$15)),IF(INDEX(Import.PLE,Detalhamento!$E19,Detalhamento!M$15)<=mediçao,0,OFFSET(Import.PLQ,$A19-1,M$15-1,1,1)),OFFSET(Import.PLQ,$A19-1,M$15-1,1,1)),(1-PLE!$AA$28)*OFFSET(Import.PLQ,$A19-1,M$15-1,1,1)))) -> 0 | N19: =IF(N$13="",0,CHOOSE(Detalhamento.OpçãoServiços,OFFSET(Import.PLQ,$A19-1,N$15-1,1,1),IF($E19<>1,IF(ISNUMBER(INDEX(Import.PLE,Detalhamento!$E19,Detalhamento!N$15)),IF(INDEX(Import.PLE,Detalhamento!$E19,Detalhamento!N$15)<=mediçao,OFFSET(Import.PLQ,$A19-1,N$15-1,1,1),0),0),PLE!$AA$28*OFFSET(Import.PLQ,$A19-1,N$15-1,1,1)),IF($E19<>1,IF(ISNUMBER(INDEX(Import.PLE,Detalhamento!$E19,Detalhamento!N$15)),IF(INDEX(Import.PLE,Detalhamento!$E19,Detalhamento!N$15)<=mediçao,0,OFFSET(Import.PLQ,$A19-1,N$15-1,1,1)),OFFSET(Import.PLQ,$A19-1,N$15-1,1,1)),(1-PLE!$AA$28)*OFFSET(Import.PLQ,$A19-1,N$15-1,1,1)))) -> 0 | O19: =IF(O$13="",0,CHOOSE(Detalhamento.OpçãoServiços,OFFSET(Import.PLQ,$A19-1,O$15-1,1,1),IF($E19<>1,IF(ISNUMBER(INDEX(Import.PLE,Detalhamento!$E19,Detalhamento!O$15)),IF(INDEX(Import.PLE,Detalhamento!$E19,Detalhamento!O$15)<=mediçao,OFFSET(Import.PLQ,$A19-1,O$15-1,1,1),0),0),PLE!$AA$28*OFFSET(Import.PLQ,$A19-1,O$15-1,1,1)),IF($E19<>1,IF(ISNUMBER(INDEX(Import.PLE,Detalhamento!$E19,Detalhamento!O$15)),IF(INDEX(Import.PLE,Detalhamento!$E19,Detalhamento!O$15)<=mediçao,0,OFFSET(Import.PLQ,$A19-1,O$15-1,1,1)),OFFSET(Import.PLQ,$A19-1,O$15-1,1,1)),(1-PLE!$AA$28)*OFFSET(Import.PLQ,$A19-1,O$15-1,1,1)))) -> 0 | P19: =IF(P$13="",0,CHOOSE(Detalhamento.OpçãoServiços,OFFSET(Import.PLQ,$A19-1,P$15-1,1,1),IF($E19<>1,IF(ISNUMBER(INDEX(Import.PLE,Detalhamento!$E19,Detalhamento!P$15)),IF(INDEX(Import.PLE,Detalhamento!$E19,Detalhamento!P$15)<=mediçao,OFFSET(Import.PLQ,$A19-1,P$15-1,1,1),0),0),PLE!$AA$28*OFFSET(Import.PLQ,$A19-1,P$15-1,1,1)),IF($E19<>1,IF(ISNUMBER(INDEX(Import.PLE,Detalhamento!$E19,Detalhamento!P$15)),IF(INDEX(Import.PLE,Detalhamento!$E19,Detalhamento!P$15)<=mediçao,0,OFFSET(Import.PLQ,$A19-1,P$15-1,1,1)),OFFSET(Import.PLQ,$A19-1,P$15-1,1,1)),(1-PLE!$AA$28)*OFFSET(Import.PLQ,$A19-1,P$15-1,1,1)))) -> 0 | Q19: =IF(Q$13="",0,CHOOSE(Detalhamento.OpçãoServiços,OFFSET(Import.PLQ,$A19-1,Q$15-1,1,1),IF($E19<>1,IF(ISNUMBER(INDEX(Import.PLE,Detalhamento!$E19,Detalhamento!Q$15)),IF(INDEX(Import.PLE,Detalhamento!$E19,Detalhamento!Q$15)<=mediçao,OFFSET(Import.PLQ,$A19-1,Q$15-1,1,1),0),0),PLE!$AA$28*OFFSET(Import.PLQ,$A19-1,Q$15-1,1,1)),IF($E19<>1,IF(ISNUMBER(INDEX(Import.PLE,Detalhamento!$E19,Detalhamento!Q$15)),IF(INDEX(Import.PLE,Detalhamento!$E19,Detalhamento!Q$15)<=mediçao,0,OFFSET(Import.PLQ,$A19-1,Q$15-1,1,1)),OFFSET(Import.PLQ,$A19-1,Q$15-1,1,1)),(1-PLE!$AA$28)*OFFSET(Import.PLQ,$A19-1,Q$15-1,1,1)))) -> 0 | R19: =IF(R$13="",0,CHOOSE(Detalhamento.OpçãoServiços,OFFSET(Import.PLQ,$A19-1,R$15-1,1,1),IF($E19<>1,IF(ISNUMBER(INDEX(Import.PLE,Detalhamento!$E19,Detalhamento!R$15)),IF(INDEX(Import.PLE,Detalhamento!$E19,Detalhamento!R$15)<=mediçao,OFFSET(Import.PLQ,$A19-1,R$15-1,1,1),0),0),PLE!$AA$28*OFFSET(Import.PLQ,$A19-1,R$15-1,1,1)),IF($E19<>1,IF(ISNUMBER(INDEX(Import.PLE,Detalhamento!$E19,Detalhamento!R$15)),IF(INDEX(Import.PLE,Detalhamento!$E19,Detalhamento!R$15)<=mediçao,0,OFFSET(Import.PLQ,$A19-1,R$15-1,1,1)),OFFSET(Import.PLQ,$A19-1,R$15-1,1,1)),(1-PLE!$AA$28)*OFFSET(Import.PLQ,$A19-1,R$15-1,1,1)))) -> 0 | S19: =IF(S$13="",0,CHOOSE(Detalhamento.OpçãoServiços,OFFSET(Import.PLQ,$A19-1,S$15-1,1,1),IF($E19<>1,IF(ISNUMBER(INDEX(Import.PLE,Detalhamento!$E19,Detalhamento!S$15)),IF(INDEX(Import.PLE,Detalhamento!$E19,Detalhamento!S$15)<=mediçao,OFFSET(Import.PLQ,$A19-1,S$15-1,1,1),0),0),PLE!$AA$28*OFFSET(Import.PLQ,$A19-1,S$15-1,1,1)),IF($E19<>1,IF(ISNUMBER(INDEX(Import.PLE,Detalhamento!$E19,Detalhamento!S$15)),IF(INDEX(Import.PLE,Detalhamento!$E19,Detalhamento!S$15)<=mediçao,0,OFFSET(Import.PLQ,$A19-1,S$15-1,1,1)),OFFSET(Import.PLQ,$A19-1,S$15-1,1,1)),(1-PLE!$AA$28)*OFFSET(Import.PLQ,$A19-1,S$15-1,1,1)))) -> 0 | ... BI19: =IF(BI$13="",0,CHOOSE(Detalhamento.OpçãoServiços,OFFSET(Import.PLQ,$A19-1,BI$15-1,1,1),IF($E19<>1,IF(ISNUMBER(INDEX(Import.PLE,Detalhamento!$E19,Detalhamento!BI$15)),IF(INDEX(Import.PLE,Detalhamento!$E19,Detalhamento!BI$15)<=mediçao,OFFSET(Import.PLQ,$A19-1,BI$15-1,1,1),0),0),PLE!$AA$28*OFFSET(Import.PLQ,$A19-1,BI$15-1,1,1)),IF($E19<>1,IF(ISNUMBER(INDEX(Import.PLE,Detalhamento!$E19,Detalhamento!BI$15)),IF(INDEX(Import.PLE,Detalhamento!$E19,Detalhamento!BI$15)<=mediçao,0,OFFSET(Import.PLQ,$A19-1,BI$15-1,1,1)),OFFSET(Import.PLQ,$A19-1,BI$15-1,1,1)),(1-PLE!$AA$28)*OFFSET(Import.PLQ,$A19-1,BI$15-1,1,1)))) -> 0
A20: 4 | B20: =OFFSET(LIorçamento,$A20-1,B$16,1,1) -> Meta | E20: =OFFSET(LIorçamento,$A20-1,E$16,1,1) | F20: =CHOOSE($B$8,IF(OR(Nível="Serviço",Nível="Evento"),E20*10^4+IF(Nível<>"Evento",A20,0),0),IF(Nível<>"Evento",A20,0)) -> 0 | G20: =OFFSET(LIorçamento,$A20-1,G$16,1,1) -> 2 | H20: =OFFSET(LIorçamento,$A20-1,H$16,1,1) -> SERVIÇOS DE TERRAPLENAGEM | I20: =IF(OR(Nível="Serviço",Nível="evento"),OFFSET(LIorçamento,$A20-1,I$16,1,1),"") | J20: =IF(OR(Nível="Serviço",Nível="evento"),SUM(L20:BI20),"") | L20: =IF(L$13="",0,CHOOSE(Detalhamento.OpçãoServiços,OFFSET(Import.PLQ,$A20-1,L$15-1,1,1),IF($E20<>1,IF(ISNUMBER(INDEX(Import.PLE,Detalhamento!$E20,Detalhamento!L$15)),IF(INDEX(Import.PLE,Detalhamento!$E20,Detalhamento!L$15)<=mediçao,OFFSET(Import.PLQ,$A20-1,L$15-1,1,1),0),0),PLE!$AA$28*OFFSET(Import.PLQ,$A20-1,L$15-1,1,1)),IF($E20<>1,IF(ISNUMBER(INDEX(Import.PLE,Detalhamento!$E20,Detalhamento!L$15)),IF(INDEX(Import.PLE,Detalhamento!$E20,Detalhamento!L$15)<=mediçao,0,OFFSET(Import.PLQ,$A20-1,L$15-1,1,1)),OFFSET(Import.PLQ,$A20-1,L$15-1,1,1)),(1-PLE!$AA$28)*OFFSET(Import.PLQ,$A20-1,L$15-1,1,1)))) -> 0 | M20: =IF(M$13="",0,CHOOSE(Detalhamento.OpçãoServiços,OFFSET(Import.PLQ,$A20-1,M$15-1,1,1),IF($E20<>1,IF(ISNUMBER(INDEX(Import.PLE,Detalhamento!$E20,Detalhamento!M$15)),IF(INDEX(Import.PLE,Detalhamento!$E20,Detalhamento!M$15)<=mediçao,OFFSET(Import.PLQ,$A20-1,M$15-1,1,1),0),0),PLE!$AA$28*OFFSET(Import.PLQ,$A20-1,M$15-1,1,1)),IF($E20<>1,IF(ISNUMBER(INDEX(Import.PLE,Detalhamento!$E20,Detalhamento!M$15)),IF(INDEX(Import.PLE,Detalhamento!$E20,Detalhamento!M$15)<=mediçao,0,OFFSET(Import.PLQ,$A20-1,M$15-1,1,1)),OFFSET(Import.PLQ,$A20-1,M$15-1,1,1)),(1-PLE!$AA$28)*OFFSET(Import.PLQ,$A20-1,M$15-1,1,1)))) -> 0 | N20: =IF(N$13="",0,CHOOSE(Detalhamento.OpçãoServiços,OFFSET(Import.PLQ,$A20-1,N$15-1,1,1),IF($E20<>1,IF(ISNUMBER(INDEX(Import.PLE,Detalhamento!$E20,Detalhamento!N$15)),IF(INDEX(Import.PLE,Detalhamento!$E20,Detalhamento!N$15)<=mediçao,OFFSET(Import.PLQ,$A20-1,N$15-1,1,1),0),0),PLE!$AA$28*OFFSET(Import.PLQ,$A20-1,N$15-1,1,1)),IF($E20<>1,IF(ISNUMBER(INDEX(Import.PLE,Detalhamento!$E20,Detalhamento!N$15)),IF(INDEX(Import.PLE,Detalhamento!$E20,Detalhamento!N$15)<=mediçao,0,OFFSET(Import.PLQ,$A20-1,N$15-1,1,1)),OFFSET(Import.PLQ,$A20-1,N$15-1,1,1)),(1-PLE!$AA$28)*OFFSET(Import.PLQ,$A20-1,N$15-1,1,1)))) -> 0 | O20: =IF(O$13="",0,CHOOSE(Detalhamento.OpçãoServiços,OFFSET(Import.PLQ,$A20-1,O$15-1,1,1),IF($E20<>1,IF(ISNUMBER(INDEX(Import.PLE,Detalhamento!$E20,Detalhamento!O$15)),IF(INDEX(Import.PLE,Detalhamento!$E20,Detalhamento!O$15)<=mediçao,OFFSET(Import.PLQ,$A20-1,O$15-1,1,1),0),0),PLE!$AA$28*OFFSET(Import.PLQ,$A20-1,O$15-1,1,1)),IF($E20<>1,IF(ISNUMBER(INDEX(Import.PLE,Detalhamento!$E20,Detalhamento!O$15)),IF(INDEX(Import.PLE,Detalhamento!$E20,Detalhamento!O$15)<=mediçao,0,OFFSET(Import.PLQ,$A20-1,O$15-1,1,1)),OFFSET(Import.PLQ,$A20-1,O$15-1,1,1)),(1-PLE!$AA$28)*OFFSET(Import.PLQ,$A20-1,O$15-1,1,1)))) -> 0 | P20: =IF(P$13="",0,CHOOSE(Detalhamento.OpçãoServiços,OFFSET(Import.PLQ,$A20-1,P$15-1,1,1),IF($E20<>1,IF(ISNUMBER(INDEX(Import.PLE,Detalhamento!$E20,Detalhamento!P$15)),IF(INDEX(Import.PLE,Detalhamento!$E20,Detalhamento!P$15)<=mediçao,OFFSET(Import.PLQ,$A20-1,P$15-1,1,1),0),0),PLE!$AA$28*OFFSET(Import.PLQ,$A20-1,P$15-1,1,1)),IF($E20<>1,IF(ISNUMBER(INDEX(Import.PLE,Detalhamento!$E20,Detalhamento!P$15)),IF(INDEX(Import.PLE,Detalhamento!$E20,Detalhamento!P$15)<=mediçao,0,OFFSET(Import.PLQ,$A20-1,P$15-1,1,1)),OFFSET(Import.PLQ,$A20-1,P$15-1,1,1)),(1-PLE!$AA$28)*OFFSET(Import.PLQ,$A20-1,P$15-1,1,1)))) -> 0 | Q20: =IF(Q$13="",0,CHOOSE(Detalhamento.OpçãoServiços,OFFSET(Import.PLQ,$A20-1,Q$15-1,1,1),IF($E20<>1,IF(ISNUMBER(INDEX(Import.PLE,Detalhamento!$E20,Detalhamento!Q$15)),IF(INDEX(Import.PLE,Detalhamento!$E20,Detalhamento!Q$15)<=mediçao,OFFSET(Import.PLQ,$A20-1,Q$15-1,1,1),0),0),PLE!$AA$28*OFFSET(Import.PLQ,$A20-1,Q$15-1,1,1)),IF($E20<>1,IF(ISNUMBER(INDEX(Import.PLE,Detalhamento!$E20,Detalhamento!Q$15)),IF(INDEX(Import.PLE,Detalhamento!$E20,Detalhamento!Q$15)<=mediçao,0,OFFSET(Import.PLQ,$A20-1,Q$15-1,1,1)),OFFSET(Import.PLQ,$A20-1,Q$15-1,1,1)),(1-PLE!$AA$28)*OFFSET(Import.PLQ,$A20-1,Q$15-1,1,1)))) -> 0 | R20: =IF(R$13="",0,CHOOSE(Detalhamento.OpçãoServiços,OFFSET(Import.PLQ,$A20-1,R$15-1,1,1),IF($E20<>1,IF(ISNUMBER(INDEX(Import.PLE,Detalhamento!$E20,Detalhamento!R$15)),IF(INDEX(Import.PLE,Detalhamento!$E20,Detalhamento!R$15)<=mediçao,OFFSET(Import.PLQ,$A20-1,R$15-1,1,1),0),0),PLE!$AA$28*OFFSET(Import.PLQ,$A20-1,R$15-1,1,1)),IF($E20<>1,IF(ISNUMBER(INDEX(Import.PLE,Detalhamento!$E20,Detalhamento!R$15)),IF(INDEX(Import.PLE,Detalhamento!$E20,Detalhamento!R$15)<=mediçao,0,OFFSET(Import.PLQ,$A20-1,R$15-1,1,1)),OFFSET(Import.PLQ,$A20-1,R$15-1,1,1)),(1-PLE!$AA$28)*OFFSET(Import.PLQ,$A20-1,R$15-1,1,1)))) -> 0 | S20: =IF(S$13="",0,CHOOSE(Detalhamento.OpçãoServiços,OFFSET(Import.PLQ,$A20-1,S$15-1,1,1),IF($E20<>1,IF(ISNUMBER(INDEX(Import.PLE,Detalhamento!$E20,Detalhamento!S$15)),IF(INDEX(Import.PLE,Detalhamento!$E20,Detalhamento!S$15)<=mediçao,OFFSET(Import.PLQ,$A20-1,S$15-1,1,1),0),0),PLE!$AA$28*OFFSET(Import.PLQ,$A20-1,S$15-1,1,1)),IF($E20<>1,IF(ISNUMBER(INDEX(Import.PLE,Detalhamento!$E20,Detalhamento!S$15)),IF(INDEX(Import.PLE,Detalhamento!$E20,Detalhamento!S$15)<=mediçao,0,OFFSET(Import.PLQ,$A20-1,S$15-1,1,1)),OFFSET(Import.PLQ,$A20-1,S$15-1,1,1)),(1-PLE!$AA$28)*OFFSET(Import.PLQ,$A20-1,S$15-1,1,1)))) -> 0 | ... BI20: =IF(BI$13="",0,CHOOSE(Detalhamento.OpçãoServiços,OFFSET(Import.PLQ,$A20-1,BI$15-1,1,1),IF($E20<>1,IF(ISNUMBER(INDEX(Import.PLE,Detalhamento!$E20,Detalhamento!BI$15)),IF(INDEX(Import.PLE,Detalhamento!$E20,Detalhamento!BI$15)<=mediçao,OFFSET(Import.PLQ,$A20-1,BI$15-1,1,1),0),0),PLE!$AA$28*OFFSET(Import.PLQ,$A20-1,BI$15-1,1,1)),IF($E20<>1,IF(ISNUMBER(INDEX(Import.PLE,Detalhamento!$E20,Detalhamento!BI$15)),IF(INDEX(Import.PLE,Detalhamento!$E20,Detalhamento!BI$15)<=mediçao,0,OFFSET(Import.PLQ,$A20-1,BI$15-1,1,1)),OFFSET(Import.PLQ,$A20-1,BI$15-1,1,1)),(1-PLE!$AA$28)*OFFSET(Import.PLQ,$A20-1,BI$15-1,1,1)))) -> 0
A21: 21 | B21: =OFFSET(LIorçamento,$A21-1,B$16,1,1) -> Evento | E21: =OFFSET(LIorçamento,$A21-1,E$16,1,1) -> 2 | F21: =CHOOSE($B$8,IF(OR(Nível="Serviço",Nível="Evento"),E21*10^4+IF(Nível<>"Evento",A21,0),0),IF(Nível<>"Evento",A21,0)) -> 20000 | G21: =OFFSET(LIorçamento,$A21-1,G$16,1,1) -> Evento | H21: =OFFSET(LIorçamento,$A21-1,H$16,1,1) -> PAVIMENTAÇÃO | I21: =IF(OR(Nível="Serviço",Nível="evento"),OFFSET(LIorçamento,$A21-1,I$16,1,1),"") -> R$ | J21: =IF(OR(Nível="Serviço",Nível="evento"),SUM(L21:BI21),"") -> 615269.24 | L21: =IF(L$13="",0,CHOOSE(Detalhamento.OpçãoServiços,OFFSET(Import.PLQ,$A21-1,L$15-1,1,1),IF($E21<>1,IF(ISNUMBER(INDEX(Import.PLE,Detalhamento!$E21,Detalhamento!L$15)),IF(INDEX(Import.PLE,Detalhamento!$E21,Detalhamento!L$15)<=mediçao,OFFSET(Import.PLQ,$A21-1,L$15-1,1,1),0),0),PLE!$AA$28*OFFSET(Import.PLQ,$A21-1,L$15-1,1,1)),IF($E21<>1,IF(ISNUMBER(INDEX(Import.PLE,Detalhamento!$E21,Detalhamento!L$15)),IF(INDEX(Import.PLE,Detalhamento!$E21,Detalhamento!L$15)<=mediçao,0,OFFSET(Import.PLQ,$A21-1,L$15-1,1,1)),OFFSET(Import.PLQ,$A21-1,L$15-1,1,1)),(1-PLE!$AA$28)*OFFSET(Import.PLQ,$A21-1,L$15-1,1,1)))) -> 127606.93 | M21: =IF(M$13="",0,CHOOSE(Detalhamento.OpçãoServiços,OFFSET(Import.PLQ,$A21-1,M$15-1,1,1),IF($E21<>1,IF(ISNUMBER(INDEX(Import.PLE,Detalhamento!$E21,Detalhamento!M$15)),IF(INDEX(Import.PLE,Detalhamento!$E21,Detalhamento!M$15)<=mediçao,OFFSET(Import.PLQ,$A21-1,M$15-1,1,1),0),0),PLE!$AA$28*OFFSET(Import.PLQ,$A21-1,M$15-1,1,1)),IF($E21<>1,IF(ISNUMBER(INDEX(Import.PLE,Detalhamento!$E21,Detalhamento!M$15)),IF(INDEX(Import.PLE,Detalhamento!$E21,Detalhamento!M$15)<=mediçao,0,OFFSET(Import.PLQ,$A21-1,M$15-1,1,1)),OFFSET(Import.PLQ,$A21-1,M$15-1,1,1)),(1-PLE!$AA$28)*OFFSET(Import.PLQ,$A21-1,M$15-1,1,1)))) -> 52187.484 | N21: =IF(N$13="",0,CHOOSE(Detalhamento.OpçãoServiços,OFFSET(Import.PLQ,$A21-1,N$15-1,1,1),IF($E21<>1,IF(ISNUMBER(INDEX(Import.PLE,Detalhamento!$E21,Detalhamento!N$15)),IF(INDEX(Import.PLE,Detalhamento!$E21,Detalhamento!N$15)<=mediçao,OFFSET(Import.PLQ,$A21-1,N$15-1,1,1),0),0),PLE!$AA$28*OFFSET(Import.PLQ,$A21-1,N$15-1,1,1)),IF($E21<>1,IF(ISNUMBER(INDEX(Import.PLE,Detalhamento!$E21,Detalhamento!N$15)),IF(INDEX(Import.PLE,Detalhamento!$E21,Detalhamento!N$15)<=mediçao,0,OFFSET(Import.PLQ,$A21-1,N$15-1,1,1)),OFFSET(Import.PLQ,$A21-1,N$15-1,1,1)),(1-PLE!$AA$28)*OFFSET(Import.PLQ,$A21-1,N$15-1,1,1)))) -> 82542.488 | O21: =IF(O$13="",0,CHOOSE(Detalhamento.OpçãoServiços,OFFSET(Import.PLQ,$A21-1,O$15-1,1,1),IF($E21<>1,IF(ISNUMBER(INDEX(Import.PLE,Detalhamento!$E21,Detalhamento!O$15)),IF(INDEX(Import.PLE,Detalhamento!$E21,Detalhamento!O$15)<=mediçao,OFFSET(Import.PLQ,$A21-1,O$15-1,1,1),0),0),PLE!$AA$28*OFFSET(Import.PLQ,$A21-1,O$15-1,1,1)),IF($E21<>1,IF(ISNUMBER(INDEX(Import.PLE,Detalhamento!$E21,Detalhamento!O$15)),IF(INDEX(Import.PLE,Detalhamento!$E21,Detalhamento!O$15)<=mediçao,0,OFFSET(Import.PLQ,$A21-1,O$15-1,1,1)),OFFSET(Import.PLQ,$A21-1,O$15-1,1,1)),(1-PLE!$AA$28)*OFFSET(Import.PLQ,$A21-1,O$15-1,1,1)))) -> 119094.95 | P21: =IF(P$13="",0,CHOOSE(Detalhamento.OpçãoServiços,OFFSET(Import.PLQ,$A21-1,P$15-1,1,1),IF($E21<>1,IF(ISNUMBER(INDEX(Import.PLE,Detalhamento!$E21,Detalhamento!P$15)),IF(INDEX(Import.PLE,Detalhamento!$E21,Detalhamento!P$15)<=mediçao,OFFSET(Import.PLQ,$A21-1,P$15-1,1,1),0),0),PLE!$AA$28*OFFSET(Import.PLQ,$A21-1,P$15-1,1,1)),IF($E21<>1,IF(ISNUMBER(INDEX(Import.PLE,Detalhamento!$E21,Detalhamento!P$15)),IF(INDEX(Import.PLE,Detalhamento!$E21,Detalhamento!P$15)<=mediçao,0,OFFSET(Import.PLQ,$A21-1,P$15-1,1,1)),OFFSET(Import.PLQ,$A21-1,P$15-1,1,1)),(1-PLE!$AA$28)*OFFSET(Import.PLQ,$A21-1,P$15-1,1,1)))) -> 44801.923 | Q21: =IF(Q$13="",0,CHOOSE(Detalhamento.OpçãoServiços,OFFSET(Import.PLQ,$A21-1,Q$15-1,1,1),IF($E21<>1,IF(ISNUMBER(INDEX(Import.PLE,Detalhamento!$E21,Detalhamento!Q$15)),IF(INDEX(Import.PLE,Detalhamento!$E21,Detalhamento!Q$15)<=mediçao,OFFSET(Import.PLQ,$A21-1,Q$15-1,1,1),0),0),PLE!$AA$28*OFFSET(Import.PLQ,$A21-1,Q$15-1,1,1)),IF($E21<>1,IF(ISNUMBER(INDEX(Import.PLE,Detalhamento!$E21,Detalhamento!Q$15)),IF(INDEX(Import.PLE,Detalhamento!$E21,Detalhamento!Q$15)<=mediçao,0,OFFSET(Import.PLQ,$A21-1,Q$15-1,1,1)),OFFSET(Import.PLQ,$A21-1,Q$15-1,1,1)),(1-PLE!$AA$28)*OFFSET(Import.PLQ,$A21-1,Q$15-1,1,1)))) -> 84346.677 | R21: =IF(R$13="",0,CHOOSE(Detalhamento.OpçãoServiços,OFFSET(Import.PLQ,$A21-1,R$15-1,1,1),IF($E21<>1,IF(ISNUMBER(INDEX(Import.PLE,Detalhamento!$E21,Detalhamento!R$15)),IF(INDEX(Import.PLE,Detalhamento!$E21,Detalhamento!R$15)<=mediçao,OFFSET(Import.PLQ,$A21-1,R$15-1,1,1),0),0),PLE!$AA$28*OFFSET(Import.PLQ,$A21-1,R$15-1,1,1)),IF($E21<>1,IF(ISNUMBER(INDEX(Import.PLE,Detalhamento!$E21,Detalhamento!R$15)),IF(INDEX(Import.PLE,Detalhamento!$E21,Detalhamento!R$15)<=mediçao,0,OFFSET(Import.PLQ,$A21-1,R$15-1,1,1)),OFFSET(Import.PLQ,$A21-1,R$15-1,1,1)),(1-PLE!$AA$28)*OFFSET(Import.PLQ,$A21-1,R$15-1,1,1)))) -> 59981.004 | S21: =IF(S$13="",0,CHOOSE(Detalhamento.OpçãoServiços,OFFSET(Import.PLQ,$A21-1,S$15-1,1,1),IF($E21<>1,IF(ISNUMBER(INDEX(Import.PLE,Detalhamento!$E21,Detalhamento!S$15)),IF(INDEX(Import.PLE,Detalhamento!$E21,Detalhamento!S$15)<=mediçao,OFFSET(Import.PLQ,$A21-1,S$15-1,1,1),0),0),PLE!$AA$28*OFFSET(Import.PLQ,$A21-1,S$15-1,1,1)),IF($E21<>1,IF(ISNUMBER(INDEX(Import.PLE,Detalhamento!$E21,Detalhamento!S$15)),IF(INDEX(Import.PLE,Detalhamento!$E21,Detalhamento!S$15)<=mediçao,0,OFFSET(Import.PLQ,$A21-1,S$15-1,1,1)),OFFSET(Import.PLQ,$A21-1,S$15-1,1,1)),(1-PLE!$AA$28)*OFFSET(Import.PLQ,$A21-1,S$15-1,1,1)))) -> 44707.789 | ... BI21: =IF(BI$13="",0,CHOOSE(Detalhamento.OpçãoServiços,OFFSET(Import.PLQ,$A21-1,BI$15-1,1,1),IF($E21<>1,IF(ISNUMBER(INDEX(Import.PLE,Detalhamento!$E21,Detalhamento!BI$15)),IF(INDEX(Import.PLE,Detalhamento!$E21,Detalhamento!BI$15)<=mediçao,OFFSET(Import.PLQ,$A21-1,BI$15-1,1,1),0),0),PLE!$AA$28*OFFSET(Import.PLQ,$A21-1,BI$15-1,1,1)),IF($E21<>1,IF(ISNUMBER(INDEX(Import.PLE,Detalhamento!$E21,Detalhamento!BI$15)),IF(INDEX(Import.PLE,Detalhamento!$E21,Detalhamento!BI$15)<=mediçao,0,OFFSET(Import.PLQ,$A21-1,BI$15-1,1,1)),OFFSET(Import.PLQ,$A21-1,BI$15-1,1,1)),(1-PLE!$AA$28)*OFFSET(Import.PLQ,$A21-1,BI$15-1,1,1)))) -> 0
A22: 6 | B22: =OFFSET(LIorçamento,$A22-1,B$16,1,1) -> Meta | E22: =OFFSET(LIorçamento,$A22-1,E$16,1,1) | F22: =CHOOSE($B$8,IF(OR(Nível="Serviço",Nível="Evento"),E22*10^4+IF(Nível<>"Evento",A22,0),0),IF(Nível<>"Evento",A22,0)) -> 0 | G22: =OFFSET(LIorçamento,$A22-1,G$16,1,1) -> 3 | H22: =OFFSET(LIorçamento,$A22-1,H$16,1,1) -> PAVIMENTAÇÃO | I22: =IF(OR(Nível="Serviço",Nível="evento"),OFFSET(LIorçamento,$A22-1,I$16,1,1),"") | J22: =IF(OR(Nível="Serviço",Nível="evento"),SUM(L22:BI22),"") | L22: =IF(L$13="",0,CHOOSE(Detalhamento.OpçãoServiços,OFFSET(Import.PLQ,$A22-1,L$15-1,1,1),IF($E22<>1,IF(ISNUMBER(INDEX(Import.PLE,Detalhamento!$E22,Detalhamento!L$15)),IF(INDEX(Import.PLE,Detalhamento!$E22,Detalhamento!L$15)<=mediçao,OFFSET(Import.PLQ,$A22-1,L$15-1,1,1),0),0),PLE!$AA$28*OFFSET(Import.PLQ,$A22-1,L$15-1,1,1)),IF($E22<>1,IF(ISNUMBER(INDEX(Import.PLE,Detalhamento!$E22,Detalhamento!L$15)),IF(INDEX(Import.PLE,Detalhamento!$E22,Detalhamento!L$15)<=mediçao,0,OFFSET(Import.PLQ,$A22-1,L$15-1,1,1)),OFFSET(Import.PLQ,$A22-1,L$15-1,1,1)),(1-PLE!$AA$28)*OFFSET(Import.PLQ,$A22-1,L$15-1,1,1)))) -> 0 | M22: =IF(M$13="",0,CHOOSE(Detalhamento.OpçãoServiços,OFFSET(Import.PLQ,$A22-1,M$15-1,1,1),IF($E22<>1,IF(ISNUMBER(INDEX(Import.PLE,Detalhamento!$E22,Detalhamento!M$15)),IF(INDEX(Import.PLE,Detalhamento!$E22,Detalhamento!M$15)<=mediçao,OFFSET(Import.PLQ,$A22-1,M$15-1,1,1),0),0),PLE!$AA$28*OFFSET(Import.PLQ,$A22-1,M$15-1,1,1)),IF($E22<>1,IF(ISNUMBER(INDEX(Import.PLE,Detalhamento!$E22,Detalhamento!M$15)),IF(INDEX(Import.PLE,Detalhamento!$E22,Detalhamento!M$15)<=mediçao,0,OFFSET(Import.PLQ,$A22-1,M$15-1,1,1)),OFFSET(Import.PLQ,$A22-1,M$15-1,1,1)),(1-PLE!$AA$28)*OFFSET(Import.PLQ,$A22-1,M$15-1,1,1)))) -> 0 | N22: =IF(N$13="",0,CHOOSE(Detalhamento.OpçãoServiços,OFFSET(Import.PLQ,$A22-1,N$15-1,1,1),IF($E22<>1,IF(ISNUMBER(INDEX(Import.PLE,Detalhamento!$E22,Detalhamento!N$15)),IF(INDEX(Import.PLE,Detalhamento!$E22,Detalhamento!N$15)<=mediçao,OFFSET(Import.PLQ,$A22-1,N$15-1,1,1),0),0),PLE!$AA$28*OFFSET(Import.PLQ,$A22-1,N$15-1,1,1)),IF($E22<>1,IF(ISNUMBER(INDEX(Import.PLE,Detalhamento!$E22,Detalhamento!N$15)),IF(INDEX(Import.PLE,Detalhamento!$E22,Detalhamento!N$15)<=mediçao,0,OFFSET(Import.PLQ,$A22-1,N$15-1,1,1)),OFFSET(Import.PLQ,$A22-1,N$15-1,1,1)),(1-PLE!$AA$28)*OFFSET(Import.PLQ,$A22-1,N$15-1,1,1)))) -> 0 | O22: =IF(O$13="",0,CHOOSE(Detalhamento.OpçãoServiços,OFFSET(Import.PLQ,$A22-1,O$15-1,1,1),IF($E22<>1,IF(ISNUMBER(INDEX(Import.PLE,Detalhamento!$E22,Detalhamento!O$15)),IF(INDEX(Import.PLE,Detalhamento!$E22,Detalhamento!O$15)<=mediçao,OFFSET(Import.PLQ,$A22-1,O$15-1,1,1),0),0),PLE!$AA$28*OFFSET(Import.PLQ,$A22-1,O$15-1,1,1)),IF($E22<>1,IF(ISNUMBER(INDEX(Import.PLE,Detalhamento!$E22,Detalhamento!O$15)),IF(INDEX(Import.PLE,Detalhamento!$E22,Detalhamento!O$15)<=mediçao,0,OFFSET(Import.PLQ,$A22-1,O$15-1,1,1)),OFFSET(Import.PLQ,$A22-1,O$15-1,1,1)),(1-PLE!$AA$28)*OFFSET(Import.PLQ,$A22-1,O$15-1,1,1)))) -> 0 | P22: =IF(P$13="",0,CHOOSE(Detalhamento.OpçãoServiços,OFFSET(Import.PLQ,$A22-1,P$15-1,1,1),IF($E22<>1,IF(ISNUMBER(INDEX(Import.PLE,Detalhamento!$E22,Detalhamento!P$15)),IF(INDEX(Import.PLE,Detalhamento!$E22,Detalhamento!P$15)<=mediçao,OFFSET(Import.PLQ,$A22-1,P$15-1,1,1),0),0),PLE!$AA$28*OFFSET(Import.PLQ,$A22-1,P$15-1,1,1)),IF($E22<>1,IF(ISNUMBER(INDEX(Import.PLE,Detalhamento!$E22,Detalhamento!P$15)),IF(INDEX(Import.PLE,Detalhamento!$E22,Detalhamento!P$15)<=mediçao,0,OFFSET(Import.PLQ,$A22-1,P$15-1,1,1)),OFFSET(Import.PLQ,$A22-1,P$15-1,1,1)),(1-PLE!$AA$28)*OFFSET(Import.PLQ,$A22-1,P$15-1,1,1)))) -> 0 | Q22: =IF(Q$13="",0,CHOOSE(Detalhamento.OpçãoServiços,OFFSET(Import.PLQ,$A22-1,Q$15-1,1,1),IF($E22<>1,IF(ISNUMBER(INDEX(Import.PLE,Detalhamento!$E22,Detalhamento!Q$15)),IF(INDEX(Import.PLE,Detalhamento!$E22,Detalhamento!Q$15)<=mediçao,OFFSET(Import.PLQ,$A22-1,Q$15-1,1,1),0),0),PLE!$AA$28*OFFSET(Import.PLQ,$A22-1,Q$15-1,1,1)),IF($E22<>1,IF(ISNUMBER(INDEX(Import.PLE,Detalhamento!$E22,Detalhamento!Q$15)),IF(INDEX(Import.PLE,Detalhamento!$E22,Detalhamento!Q$15)<=mediçao,0,OFFSET(Import.PLQ,$A22-1,Q$15-1,1,1)),OFFSET(Import.PLQ,$A22-1,Q$15-1,1,1)),(1-PLE!$AA$28)*OFFSET(Import.PLQ,$A22-1,Q$15-1,1,1)))) -> 0 | R22: =IF(R$13="",0,CHOOSE(Detalhamento.OpçãoServiços,OFFSET(Import.PLQ,$A22-1,R$15-1,1,1),IF($E22<>1,IF(ISNUMBER(INDEX(Import.PLE,Detalhamento!$E22,Detalhamento!R$15)),IF(INDEX(Import.PLE,Detalhamento!$E22,Detalhamento!R$15)<=mediçao,OFFSET(Import.PLQ,$A22-1,R$15-1,1,1),0),0),PLE!$AA$28*OFFSET(Import.PLQ,$A22-1,R$15-1,1,1)),IF($E22<>1,IF(ISNUMBER(INDEX(Import.PLE,Detalhamento!$E22,Detalhamento!R$15)),IF(INDEX(Import.PLE,Detalhamento!$E22,Detalhamento!R$15)<=mediçao,0,OFFSET(Import.PLQ,$A22-1,R$15-1,1,1)),OFFSET(Import.PLQ,$A22-1,R$15-1,1,1)),(1-PLE!$AA$28)*OFFSET(Import.PLQ,$A22-1,R$15-1,1,1)))) -> 0 | S22: =IF(S$13="",0,CHOOSE(Detalhamento.OpçãoServiços,OFFSET(Import.PLQ,$A22-1,S$15-1,1,1),IF($E22<>1,IF(ISNUMBER(INDEX(Import.PLE,Detalhamento!$E22,Detalhamento!S$15)),IF(INDEX(Import.PLE,Detalhamento!$E22,Detalhamento!S$15)<=mediçao,OFFSET(Import.PLQ,$A22-1,S$15-1,1,1),0),0),PLE!$AA$28*OFFSET(Import.PLQ,$A22-1,S$15-1,1,1)),IF($E22<>1,IF(ISNUMBER(INDEX(Import.PLE,Detalhamento!$E22,Detalhamento!S$15)),IF(INDEX(Import.PLE,Detalhamento!$E22,Detalhamento!S$15)<=mediçao,0,OFFSET(Import.PLQ,$A22-1,S$15-1,1,1)),OFFSET(Import.PLQ,$A22-1,S$15-1,1,1)),(1-PLE!$AA$28)*OFFSET(Import.PLQ,$A22-1,S$15-1,1,1)))) -> 0 | ... BI22: =IF(BI$13="",0,CHOOSE(Detalhamento.OpçãoServiços,OFFSET(Import.PLQ,$A22-1,BI$15-1,1,1),IF($E22<>1,IF(ISNUMBER(INDEX(Import.PLE,Detalhamento!$E22,Detalhamento!BI$15)),IF(INDEX(Import.PLE,Detalhamento!$E22,Detalhamento!BI$15)<=mediçao,OFFSET(Import.PLQ,$A22-1,BI$15-1,1,1),0),0),PLE!$AA$28*OFFSET(Import.PLQ,$A22-1,BI$15-1,1,1)),IF($E22<>1,IF(ISNUMBER(INDEX(Import.PLE,Detalhamento!$E22,Detalhamento!BI$15)),IF(INDEX(Import.PLE,Detalhamento!$E22,Detalhamento!BI$15)<=mediçao,0,OFFSET(Import.PLQ,$A22-1,BI$15-1,1,1)),OFFSET(Import.PLQ,$A22-1,BI$15-1,1,1)),(1-PLE!$AA$28)*OFFSET(Import.PLQ,$A22-1,BI$15-1,1,1)))) -> 0
A23: 3 | B23: =OFFSET(LIorçamento,$A23-1,B$16,1,1) -> Serviço | E23: =OFFSET(LIorçamento,$A23-1,E$16,1,1) -> 2 | F23: =CHOOSE($B$8,IF(OR(Nível="Serviço",Nível="Evento"),E23*10^4+IF(Nível<>"Evento",A23,0),0),IF(Nível<>"Evento",A23,0)) -> 20003 | G23: =OFFSET(LIorçamento,$A23-1,G$16,1,1) -> 1.1 | H23: =OFFSET(LIorçamento,$A23-1,H$16,1,1) -> Placa indicativa da obra em chapa de aço galvanizado (4,0m x 2,0m) | I23: =IF(OR(Nível="Serviço",Nível="evento"),OFFSET(LIorçamento,$A23-1,I$16,1,1),"") -> m² | J23: =IF(OR(Nível="Serviço",Nível="evento"),SUM(L23:BI23),"") -> 8 | L23: =IF(L$13="",0,CHOOSE(Detalhamento.OpçãoServiços,OFFSET(Import.PLQ,$A23-1,L$15-1,1,1),IF($E23<>1,IF(ISNUMBER(INDEX(Import.PLE,Detalhamento!$E23,Detalhamento!L$15)),IF(INDEX(Import.PLE,Detalhamento!$E23,Detalhamento!L$15)<=mediçao,OFFSET(Import.PLQ,$A23-1,L$15-1,1,1),0),0),PLE!$AA$28*OFFSET(Import.PLQ,$A23-1,L$15-1,1,1)),IF($E23<>1,IF(ISNUMBER(INDEX(Import.PLE,Detalhamento!$E23,Detalhamento!L$15)),IF(INDEX(Import.PLE,Detalhamento!$E23,Detalhamento!L$15)<=mediçao,0,OFFSET(Import.PLQ,$A23-1,L$15-1,1,1)),OFFSET(Import.PLQ,$A23-1,L$15-1,1,1)),(1-PLE!$AA$28)*OFFSET(Import.PLQ,$A23-1,L$15-1,1,1)))) -> 8 | M23: =IF(M$13="",0,CHOOSE(Detalhamento.OpçãoServiços,OFFSET(Import.PLQ,$A23-1,M$15-1,1,1),IF($E23<>1,IF(ISNUMBER(INDEX(Import.PLE,Detalhamento!$E23,Detalhamento!M$15)),IF(INDEX(Import.PLE,Detalhamento!$E23,Detalhamento!M$15)<=mediçao,OFFSET(Import.PLQ,$A23-1,M$15-1,1,1),0),0),PLE!$AA$28*OFFSET(Import.PLQ,$A23-1,M$15-1,1,1)),IF($E23<>1,IF(ISNUMBER(INDEX(Import.PLE,Detalhamento!$E23,Detalhamento!M$15)),IF(INDEX(Import.PLE,Detalhamento!$E23,Detalhamento!M$15)<=mediçao,0,OFFSET(Import.PLQ,$A23-1,M$15-1,1,1)),OFFSET(Import.PLQ,$A23-1,M$15-1,1,1)),(1-PLE!$AA$28)*OFFSET(Import.PLQ,$A23-1,M$15-1,1,1)))) -> 0 | N23: =IF(N$13="",0,CHOOSE(Detalhamento.OpçãoServiços,OFFSET(Import.PLQ,$A23-1,N$15-1,1,1),IF($E23<>1,IF(ISNUMBER(INDEX(Import.PLE,Detalhamento!$E23,Detalhamento!N$15)),IF(INDEX(Import.PLE,Detalhamento!$E23,Detalhamento!N$15)<=mediçao,OFFSET(Import.PLQ,$A23-1,N$15-1,1,1),0),0),PLE!$AA$28*OFFSET(Import.PLQ,$A23-1,N$15-1,1,1)),IF($E23<>1,IF(ISNUMBER(INDEX(Import.PLE,Detalhamento!$E23,Detalhamento!N$15)),IF(INDEX(Import.PLE,Detalhamento!$E23,Detalhamento!N$15)<=mediçao,0,OFFSET(Import.PLQ,$A23-1,N$15-1,1,1)),OFFSET(Import.PLQ,$A23-1,N$15-1,1,1)),(1-PLE!$AA$28)*OFFSET(Import.PLQ,$A23-1,N$15-1,1,1)))) -> 0 | O23: =IF(O$13="",0,CHOOSE(Detalhamento.OpçãoServiços,OFFSET(Import.PLQ,$A23-1,O$15-1,1,1),IF($E23<>1,IF(ISNUMBER(INDEX(Import.PLE,Detalhamento!$E23,Detalhamento!O$15)),IF(INDEX(Import.PLE,Detalhamento!$E23,Detalhamento!O$15)<=mediçao,OFFSET(Import.PLQ,$A23-1,O$15-1,1,1),0),0),PLE!$AA$28*OFFSET(Import.PLQ,$A23-1,O$15-1,1,1)),IF($E23<>1,IF(ISNUMBER(INDEX(Import.PLE,Detalhamento!$E23,Detalhamento!O$15)),IF(INDEX(Import.PLE,Detalhamento!$E23,Detalhamento!O$15)<=mediçao,0,OFFSET(Import.PLQ,$A23-1,O$15-1,1,1)),OFFSET(Import.PLQ,$A23-1,O$15-1,1,1)),(1-PLE!$AA$28)*OFFSET(Import.PLQ,$A23-1,O$15-1,1,1)))) -> 0 | P23: =IF(P$13="",0,CHOOSE(Detalhamento.OpçãoServiços,OFFSET(Import.PLQ,$A23-1,P$15-1,1,1),IF($E23<>1,IF(ISNUMBER(INDEX(Import.PLE,Detalhamento!$E23,Detalhamento!P$15)),IF(INDEX(Import.PLE,Detalhamento!$E23,Detalhamento!P$15)<=mediçao,OFFSET(Import.PLQ,$A23-1,P$15-1,1,1),0),0),PLE!$AA$28*OFFSET(Import.PLQ,$A23-1,P$15-1,1,1)),IF($E23<>1,IF(ISNUMBER(INDEX(Import.PLE,Detalhamento!$E23,Detalhamento!P$15)),IF(INDEX(Import.PLE,Detalhamento!$E23,Detalhamento!P$15)<=mediçao,0,OFFSET(Import.PLQ,$A23-1,P$15-1,1,1)),OFFSET(Import.PLQ,$A23-1,P$15-1,1,1)),(1-PLE!$AA$28)*OFFSET(Import.PLQ,$A23-1,P$15-1,1,1)))) -> 0 | Q23: =IF(Q$13="",0,CHOOSE(Detalhamento.OpçãoServiços,OFFSET(Import.PLQ,$A23-1,Q$15-1,1,1),IF($E23<>1,IF(ISNUMBER(INDEX(Import.PLE,Detalhamento!$E23,Detalhamento!Q$15)),IF(INDEX(Import.PLE,Detalhamento!$E23,Detalhamento!Q$15)<=mediçao,OFFSET(Import.PLQ,$A23-1,Q$15-1,1,1),0),0),PLE!$AA$28*OFFSET(Import.PLQ,$A23-1,Q$15-1,1,1)),IF($E23<>1,IF(ISNUMBER(INDEX(Import.PLE,Detalhamento!$E23,Detalhamento!Q$15)),IF(INDEX(Import.PLE,Detalhamento!$E23,Detalhamento!Q$15)<=mediçao,0,OFFSET(Import.PLQ,$A23-1,Q$15-1,1,1)),OFFSET(Import.PLQ,$A23-1,Q$15-1,1,1)),(1-PLE!$AA$28)*OFFSET(Import.PLQ,$A23-1,Q$15-1,1,1)))) -> 0 | R23: =IF(R$13="",0,CHOOSE(Detalhamento.OpçãoServiços,OFFSET(Import.PLQ,$A23-1,R$15-1,1,1),IF($E23<>1,IF(ISNUMBER(INDEX(Import.PLE,Detalhamento!$E23,Detalhamento!R$15)),IF(INDEX(Import.PLE,Detalhamento!$E23,Detalhamento!R$15)<=mediçao,OFFSET(Import.PLQ,$A23-1,R$15-1,1,1),0),0),PLE!$AA$28*OFFSET(Import.PLQ,$A23-1,R$15-1,1,1)),IF($E23<>1,IF(ISNUMBER(INDEX(Import.PLE,Detalhamento!$E23,Detalhamento!R$15)),IF(INDEX(Import.PLE,Detalhamento!$E23,Detalhamento!R$15)<=mediçao,0,OFFSET(Import.PLQ,$A23-1,R$15-1,1,1)),OFFSET(Import.PLQ,$A23-1,R$15-1,1,1)),(1-PLE!$AA$28)*OFFSET(Import.PLQ,$A23-1,R$15-1,1,1)))) -> 0 | S23: =IF(S$13="",0,CHOOSE(Detalhamento.OpçãoServiços,OFFSET(Import.PLQ,$A23-1,S$15-1,1,1),IF($E23<>1,IF(ISNUMBER(INDEX(Import.PLE,Detalhamento!$E23,Detalhamento!S$15)),IF(INDEX(Import.PLE,Detalhamento!$E23,Detalhamento!S$15)<=mediçao,OFFSET(Import.PLQ,$A23-1,S$15-1,1,1),0),0),PLE!$AA$28*OFFSET(Import.PLQ,$A23-1,S$15-1,1,1)),IF($E23<>1,IF(ISNUMBER(INDEX(Import.PLE,Detalhamento!$E23,Detalhamento!S$15)),IF(INDEX(Import.PLE,Detalhamento!$E23,Detalhamento!S$15)<=mediçao,0,OFFSET(Import.PLQ,$A23-1,S$15-1,1,1)),OFFSET(Import.PLQ,$A23-1,S$15-1,1,1)),(1-PLE!$AA$28)*OFFSET(Import.PLQ,$A23-1,S$15-1,1,1)))) -> 0 | ... BI23: =IF(BI$13="",0,CHOOSE(Detalhamento.OpçãoServiços,OFFSET(Import.PLQ,$A23-1,BI$15-1,1,1),IF($E23<>1,IF(ISNUMBER(INDEX(Import.PLE,Detalhamento!$E23,Detalhamento!BI$15)),IF(INDEX(Import.PLE,Detalhamento!$E23,Detalhamento!BI$15)<=mediçao,OFFSET(Import.PLQ,$A23-1,BI$15-1,1,1),0),0),PLE!$AA$28*OFFSET(Import.PLQ,$A23-1,BI$15-1,1,1)),IF($E23<>1,IF(ISNUMBER(INDEX(Import.PLE,Detalhamento!$E23,Detalhamento!BI$15)),IF(INDEX(Import.PLE,Detalhamento!$E23,Detalhamento!BI$15)<=mediçao,0,OFFSET(Import.PLQ,$A23-1,BI$15-1,1,1)),OFFSET(Import.PLQ,$A23-1,BI$15-1,1,1)),(1-PLE!$AA$28)*OFFSET(Import.PLQ,$A23-1,BI$15-1,1,1)))) -> 0
A24: 5 | B24: =OFFSET(LIorçamento,$A24-1,B$16,1,1) -> Serviço | E24: =OFFSET(LIorçamento,$A24-1,E$16,1,1) -> 2 | F24: =CHOOSE($B$8,IF(OR(Nível="Serviço",Nível="Evento"),E24*10^4+IF(Nível<>"Evento",A24,0),0),IF(Nível<>"Evento",A24,0)) -> 20005 | G24: =OFFSET(LIorçamento,$A24-1,G$16,1,1) -> 2.1 | H24: =OFFSET(LIorçamento,$A24-1,H$16,1,1) -> Regularização e compactação de sub-leito até 20cm de espessura | I24: =IF(OR(Nível="Serviço",Nível="evento"),OFFSET(LIorçamento,$A24-1,I$16,1,1),"") -> m² | J24: =IF(OR(Nível="Serviço",Nível="evento"),SUM(L24:BI24),"") -> 5349.12 | L24: =IF(L$13="",0,CHOOSE(Detalhamento.OpçãoServiços,OFFSET(Import.PLQ,$A24-1,L$15-1,1,1),IF($E24<>1,IF(ISNUMBER(INDEX(Import.PLE,Detalhamento!$E24,Detalhamento!L$15)),IF(INDEX(Import.PLE,Detalhamento!$E24,Detalhamento!L$15)<=mediçao,OFFSET(Import.PLQ,$A24-1,L$15-1,1,1),0),0),PLE!$AA$28*OFFSET(Import.PLQ,$A24-1,L$15-1,1,1)),IF($E24<>1,IF(ISNUMBER(INDEX(Import.PLE,Detalhamento!$E24,Detalhamento!L$15)),IF(INDEX(Import.PLE,Detalhamento!$E24,Detalhamento!L$15)<=mediçao,0,OFFSET(Import.PLQ,$A24-1,L$15-1,1,1)),OFFSET(Import.PLQ,$A24-1,L$15-1,1,1)),(1-PLE!$AA$28)*OFFSET(Import.PLQ,$A24-1,L$15-1,1,1)))) -> 1102.85 | M24: =IF(M$13="",0,CHOOSE(Detalhamento.OpçãoServiços,OFFSET(Import.PLQ,$A24-1,M$15-1,1,1),IF($E24<>1,IF(ISNUMBER(INDEX(Import.PLE,Detalhamento!$E24,Detalhamento!M$15)),IF(INDEX(Import.PLE,Detalhamento!$E24,Detalhamento!M$15)<=mediçao,OFFSET(Import.PLQ,$A24-1,M$15-1,1,1),0),0),PLE!$AA$28*OFFSET(Import.PLQ,$A24-1,M$15-1,1,1)),IF($E24<>1,IF(ISNUMBER(INDEX(Import.PLE,Detalhamento!$E24,Detalhamento!M$15)),IF(INDEX(Import.PLE,Detalhamento!$E24,Detalhamento!M$15)<=mediçao,0,OFFSET(Import.PLQ,$A24-1,M$15-1,1,1)),OFFSET(Import.PLQ,$A24-1,M$15-1,1,1)),(1-PLE!$AA$28)*OFFSET(Import.PLQ,$A24-1,M$15-1,1,1)))) -> 452.76 | N24: =IF(N$13="",0,CHOOSE(Detalhamento.OpçãoServiços,OFFSET(Import.PLQ,$A24-1,N$15-1,1,1),IF($E24<>1,IF(ISNUMBER(INDEX(Import.PLE,Detalhamento!$E24,Detalhamento!N$15)),IF(INDEX(Import.PLE,Detalhamento!$E24,Detalhamento!N$15)<=mediçao,OFFSET(Import.PLQ,$A24-1,N$15-1,1,1),0),0),PLE!$AA$28*OFFSET(Import.PLQ,$A24-1,N$15-1,1,1)),IF($E24<>1,IF(ISNUMBER(INDEX(Import.PLE,Detalhamento!$E24,Detalhamento!N$15)),IF(INDEX(Import.PLE,Detalhamento!$E24,Detalhamento!N$15)<=mediçao,0,OFFSET(Import.PLQ,$A24-1,N$15-1,1,1)),OFFSET(Import.PLQ,$A24-1,N$15-1,1,1)),(1-PLE!$AA$28)*OFFSET(Import.PLQ,$A24-1,N$15-1,1,1)))) -> 727.62 | O24: =IF(O$13="",0,CHOOSE(Detalhamento.OpçãoServiços,OFFSET(Import.PLQ,$A24-1,O$15-1,1,1),IF($E24<>1,IF(ISNUMBER(INDEX(Import.PLE,Detalhamento!$E24,Detalhamento!O$15)),IF(INDEX(Import.PLE,Detalhamento!$E24,Detalhamento!O$15)<=mediçao,OFFSET(Import.PLQ,$A24-1,O$15-1,1,1),0),0),PLE!$AA$28*OFFSET(Import.PLQ,$A24-1,O$15-1,1,1)),IF($E24<>1,IF(ISNUMBER(INDEX(Import.PLE,Detalhamento!$E24,Detalhamento!O$15)),IF(INDEX(Import.PLE,Detalhamento!$E24,Detalhamento!O$15)<=mediçao,0,OFFSET(Import.PLQ,$A24-1,O$15-1,1,1)),OFFSET(Import.PLQ,$A24-1,O$15-1,1,1)),(1-PLE!$AA$28)*OFFSET(Import.PLQ,$A24-1,O$15-1,1,1)))) -> 1032.9 | P24: =IF(P$13="",0,CHOOSE(Detalhamento.OpçãoServiços,OFFSET(Import.PLQ,$A24-1,P$15-1,1,1),IF($E24<>1,IF(ISNUMBER(INDEX(Import.PLE,Detalhamento!$E24,Detalhamento!P$15)),IF(INDEX(Import.PLE,Detalhamento!$E24,Detalhamento!P$15)<=mediçao,OFFSET(Import.PLQ,$A24-1,P$15-1,1,1),0),0),PLE!$AA$28*OFFSET(Import.PLQ,$A24-1,P$15-1,1,1)),IF($E24<>1,IF(ISNUMBER(INDEX(Import.PLE,Detalhamento!$E24,Detalhamento!P$15)),IF(INDEX(Import.PLE,Detalhamento!$E24,Detalhamento!P$15)<=mediçao,0,OFFSET(Import.PLQ,$A24-1,P$15-1,1,1)),OFFSET(Import.PLQ,$A24-1,P$15-1,1,1)),(1-PLE!$AA$28)*OFFSET(Import.PLQ,$A24-1,P$15-1,1,1)))) -> 390.01 | Q24: =IF(Q$13="",0,CHOOSE(Detalhamento.OpçãoServiços,OFFSET(Import.PLQ,$A24-1,Q$15-1,1,1),IF($E24<>1,IF(ISNUMBER(INDEX(Import.PLE,Detalhamento!$E24,Detalhamento!Q$15)),IF(INDEX(Import.PLE,Detalhamento!$E24,Detalhamento!Q$15)<=mediçao,OFFSET(Import.PLQ,$A24-1,Q$15-1,1,1),0),0),PLE!$AA$28*OFFSET(Import.PLQ,$A24-1,Q$15-1,1,1)),IF($E24<>1,IF(ISNUMBER(INDEX(Import.PLE,Detalhamento!$E24,Detalhamento!Q$15)),IF(INDEX(Import.PLE,Detalhamento!$E24,Detalhamento!Q$15)<=mediçao,0,OFFSET(Import.PLQ,$A24-1,Q$15-1,1,1)),OFFSET(Import.PLQ,$A24-1,Q$15-1,1,1)),(1-PLE!$AA$28)*OFFSET(Import.PLQ,$A24-1,Q$15-1,1,1)))) -> 733.74 | R24: =IF(R$13="",0,CHOOSE(Detalhamento.OpçãoServiços,OFFSET(Import.PLQ,$A24-1,R$15-1,1,1),IF($E24<>1,IF(ISNUMBER(INDEX(Import.PLE,Detalhamento!$E24,Detalhamento!R$15)),IF(INDEX(Import.PLE,Detalhamento!$E24,Detalhamento!R$15)<=mediçao,OFFSET(Import.PLQ,$A24-1,R$15-1,1,1),0),0),PLE!$AA$28*OFFSET(Import.PLQ,$A24-1,R$15-1,1,1)),IF($E24<>1,IF(ISNUMBER(INDEX(Import.PLE,Detalhamento!$E24,Detalhamento!R$15)),IF(INDEX(Import.PLE,Detalhamento!$E24,Detalhamento!R$15)<=mediçao,0,OFFSET(Import.PLQ,$A24-1,R$15-1,1,1)),OFFSET(Import.PLQ,$A24-1,R$15-1,1,1)),(1-PLE!$AA$28)*OFFSET(Import.PLQ,$A24-1,R$15-1,1,1)))) -> 523.8 | S24: =IF(S$13="",0,CHOOSE(Detalhamento.OpçãoServiços,OFFSET(Import.PLQ,$A24-1,S$15-1,1,1),IF($E24<>1,IF(ISNUMBER(INDEX(Import.PLE,Detalhamento!$E24,Detalhamento!S$15)),IF(INDEX(Import.PLE,Detalhamento!$E24,Detalhamento!S$15)<=mediçao,OFFSET(Import.PLQ,$A24-1,S$15-1,1,1),0),0),PLE!$AA$28*OFFSET(Import.PLQ,$A24-1,S$15-1,1,1)),IF($E24<>1,IF(ISNUMBER(INDEX(Import.PLE,Detalhamento!$E24,Detalhamento!S$15)),IF(INDEX(Import.PLE,Detalhamento!$E24,Detalhamento!S$15)<=mediçao,0,OFFSET(Import.PLQ,$A24-1,S$15-1,1,1)),OFFSET(Import.PLQ,$A24-1,S$15-1,1,1)),(1-PLE!$AA$28)*OFFSET(Import.PLQ,$A24-1,S$15-1,1,1)))) -> 385.44 | ... BI24: =IF(BI$13="",0,CHOOSE(Detalhamento.OpçãoServiços,OFFSET(Import.PLQ,$A24-1,BI$15-1,1,1),IF($E24<>1,IF(ISNUMBER(INDEX(Import.PLE,Detalhamento!$E24,Detalhamento!BI$15)),IF(INDEX(Import.PLE,Detalhamento!$E24,Detalhamento!BI$15)<=mediçao,OFFSET(Import.PLQ,$A24-1,BI$15-1,1,1),0),0),PLE!$AA$28*OFFSET(Import.PLQ,$A24-1,BI$15-1,1,1)),IF($E24<>1,IF(ISNUMBER(INDEX(Import.PLE,Detalhamento!$E24,Detalhamento!BI$15)),IF(INDEX(Import.PLE,Detalhamento!$E24,Detalhamento!BI$15)<=mediçao,0,OFFSET(Import.PLQ,$A24-1,BI$15-1,1,1)),OFFSET(Import.PLQ,$A24-1,BI$15-1,1,1)),(1-PLE!$AA$28)*OFFSET(Import.PLQ,$A24-1,BI$15-1,1,1)))) -> 0
A25: 7 | B25: =OFFSET(LIorçamento,$A25-1,B$16,1,1) -> Serviço | E25: =OFFSET(LIorçamento,$A25-1,E$16,1,1) -> 2 | F25: =CHOOSE($B$8,IF(OR(Nível="Serviço",Nível="Evento"),E25*10^4+IF(Nível<>"Evento",A25,0),0),IF(Nível<>"Evento",A25,0)) -> 20007 | G25: =OFFSET(LIorçamento,$A25-1,G$16,1,1) -> 3.1 | H25: =OFFSET(LIorçamento,$A25-1,H$16,1,1) -> Serviços topográficos para pavimentação (locação e nivelamento), inclusive nota de serviços, acompanhamento e greide | I25: =IF(OR(Nível="Serviço",Nível="evento"),OFFSET(LIorçamento,$A25-1,I$16,1,1),"") -> m² | J25: =IF(OR(Nível="Serviço",Nível="evento"),SUM(L25:BI25),"") -> 5349.12 | L25: =IF(L$13="",0,CHOOSE(Detalhamento.OpçãoServiços,OFFSET(Import.PLQ,$A25-1,L$15-1,1,1),IF($E25<>1,IF(ISNUMBER(INDEX(Import.PLE,Detalhamento!$E25,Detalhamento!L$15)),IF(INDEX(Import.PLE,Detalhamento!$E25,Detalhamento!L$15)<=mediçao,OFFSET(Import.PLQ,$A25-1,L$15-1,1,1),0),0),PLE!$AA$28*OFFSET(Import.PLQ,$A25-1,L$15-1,1,1)),IF($E25<>1,IF(ISNUMBER(INDEX(Import.PLE,Detalhamento!$E25,Detalhamento!L$15)),IF(INDEX(Import.PLE,Detalhamento!$E25,Detalhamento!L$15)<=mediçao,0,OFFSET(Import.PLQ,$A25-1,L$15-1,1,1)),OFFSET(Import.PLQ,$A25-1,L$15-1,1,1)),(1-PLE!$AA$28)*OFFSET(Import.PLQ,$A25-1,L$15-1,1,1)))) -> 1102.85 | M25: =IF(M$13="",0,CHOOSE(Detalhamento.OpçãoServiços,OFFSET(Import.PLQ,$A25-1,M$15-1,1,1),IF($E25<>1,IF(ISNUMBER(INDEX(Import.PLE,Detalhamento!$E25,Detalhamento!M$15)),IF(INDEX(Import.PLE,Detalhamento!$E25,Detalhamento!M$15)<=mediçao,OFFSET(Import.PLQ,$A25-1,M$15-1,1,1),0),0),PLE!$AA$28*OFFSET(Import.PLQ,$A25-1,M$15-1,1,1)),IF($E25<>1,IF(ISNUMBER(INDEX(Import.PLE,Detalhamento!$E25,Detalhamento!M$15)),IF(INDEX(Import.PLE,Detalhamento!$E25,Detalhamento!M$15)<=mediçao,0,OFFSET(Import.PLQ,$A25-1,M$15-1,1,1)),OFFSET(Import.PLQ,$A25-1,M$15-1,1,1)),(1-PLE!$AA$28)*OFFSET(Import.PLQ,$A25-1,M$15-1,1,1)))) -> 452.76 | N25: =IF(N$13="",0,CHOOSE(Detalhamento.OpçãoServiços,OFFSET(Import.PLQ,$A25-1,N$15-1,1,1),IF($E25<>1,IF(ISNUMBER(INDEX(Import.PLE,Detalhamento!$E25,Detalhamento!N$15)),IF(INDEX(Import.PLE,Detalhamento!$E25,Detalhamento!N$15)<=mediçao,OFFSET(Import.PLQ,$A25-1,N$15-1,1,1),0),0),PLE!$AA$28*OFFSET(Import.PLQ,$A25-1,N$15-1,1,1)),IF($E25<>1,IF(ISNUMBER(INDEX(Import.PLE,Detalhamento!$E25,Detalhamento!N$15)),IF(INDEX(Import.PLE,Detalhamento!$E25,Detalhamento!N$15)<=mediçao,0,OFFSET(Import.PLQ,$A25-1,N$15-1,1,1)),OFFSET(Import.PLQ,$A25-1,N$15-1,1,1)),(1-PLE!$AA$28)*OFFSET(Import.PLQ,$A25-1,N$15-1,1,1)))) -> 727.62 | O25: =IF(O$13="",0,CHOOSE(Detalhamento.OpçãoServiços,OFFSET(Import.PLQ,$A25-1,O$15-1,1,1),IF($E25<>1,IF(ISNUMBER(INDEX(Import.PLE,Detalhamento!$E25,Detalhamento!O$15)),IF(INDEX(Import.PLE,Detalhamento!$E25,Detalhamento!O$15)<=mediçao,OFFSET(Import.PLQ,$A25-1,O$15-1,1,1),0),0),PLE!$AA$28*OFFSET(Import.PLQ,$A25-1,O$15-1,1,1)),IF($E25<>1,IF(ISNUMBER(INDEX(Import.PLE,Detalhamento!$E25,Detalhamento!O$15)),IF(INDEX(Import.PLE,Detalhamento!$E25,Detalhamento!O$15)<=mediçao,0,OFFSET(Import.PLQ,$A25-1,O$15-1,1,1)),OFFSET(Import.PLQ,$A25-1,O$15-1,1,1)),(1-PLE!$AA$28)*OFFSET(Import.PLQ,$A25-1,O$15-1,1,1)))) -> 1032.9 | P25: =IF(P$13="",0,CHOOSE(Detalhamento.OpçãoServiços,OFFSET(Import.PLQ,$A25-1,P$15-1,1,1),IF($E25<>1,IF(ISNUMBER(INDEX(Import.PLE,Detalhamento!$E25,Detalhamento!P$15)),IF(INDEX(Import.PLE,Detalhamento!$E25,Detalhamento!P$15)<=mediçao,OFFSET(Import.PLQ,$A25-1,P$15-1,1,1),0),0),PLE!$AA$28*OFFSET(Import.PLQ,$A25-1,P$15-1,1,1)),IF($E25<>1,IF(ISNUMBER(INDEX(Import.PLE,Detalhamento!$E25,Detalhamento!P$15)),IF(INDEX(Import.PLE,Detalhamento!$E25,Detalhamento!P$15)<=mediçao,0,OFFSET(Import.PLQ,$A25-1,P$15-1,1,1)),OFFSET(Import.PLQ,$A25-1,P$15-1,1,1)),(1-PLE!$AA$28)*OFFSET(Import.PLQ,$A25-1,P$15-1,1,1)))) -> 390.01 | Q25: =IF(Q$13="",0,CHOOSE(Detalhamento.OpçãoServiços,OFFSET(Import.PLQ,$A25-1,Q$15-1,1,1),IF($E25<>1,IF(ISNUMBER(INDEX(Import.PLE,Detalhamento!$E25,Detalhamento!Q$15)),IF(INDEX(Import.PLE,Detalhamento!$E25,Detalhamento!Q$15)<=mediçao,OFFSET(Import.PLQ,$A25-1,Q$15-1,1,1),0),0),PLE!$AA$28*OFFSET(Import.PLQ,$A25-1,Q$15-1,1,1)),IF($E25<>1,IF(ISNUMBER(INDEX(Import.PLE,Detalhamento!$E25,Detalhamento!Q$15)),IF(INDEX(Import.PLE,Detalhamento!$E25,Detalhamento!Q$15)<=mediçao,0,OFFSET(Import.PLQ,$A25-1,Q$15-1,1,1)),OFFSET(Import.PLQ,$A25-1,Q$15-1,1,1)),(1-PLE!$AA$28)*OFFSET(Import.PLQ,$A25-1,Q$15-1,1,1)))) -> 733.74 | R25: =IF(R$13="",0,CHOOSE(Detalhamento.OpçãoServiços,OFFSET(Import.PLQ,$A25-1,R$15-1,1,1),IF($E25<>1,IF(ISNUMBER(INDEX(Import.PLE,Detalhamento!$E25,Detalhamento!R$15)),IF(INDEX(Import.PLE,Detalhamento!$E25,Detalhamento!R$15)<=mediçao,OFFSET(Import.PLQ,$A25-1,R$15-1,1,1),0),0),PLE!$AA$28*OFFSET(Import.PLQ,$A25-1,R$15-1,1,1)),IF($E25<>1,IF(ISNUMBER(INDEX(Import.PLE,Detalhamento!$E25,Detalhamento!R$15)),IF(INDEX(Import.PLE,Detalhamento!$E25,Detalhamento!R$15)<=mediçao,0,OFFSET(Import.PLQ,$A25-1,R$15-1,1,1)),OFFSET(Import.PLQ,$A25-1,R$15-1,1,1)),(1-PLE!$AA$28)*OFFSET(Import.PLQ,$A25-1,R$15-1,1,1)))) -> 523.8 | S25: =IF(S$13="",0,CHOOSE(Detalhamento.OpçãoServiços,OFFSET(Import.PLQ,$A25-1,S$15-1,1,1),IF($E25<>1,IF(ISNUMBER(INDEX(Import.PLE,Detalhamento!$E25,Detalhamento!S$15)),IF(INDEX(Import.PLE,Detalhamento!$E25,Detalhamento!S$15)<=mediçao,OFFSET(Import.PLQ,$A25-1,S$15-1,1,1),0),0),PLE!$AA$28*OFFSET(Import.PLQ,$A25-1,S$15-1,1,1)),IF($E25<>1,IF(ISNUMBER(INDEX(Import.PLE,Detalhamento!$E25,Detalhamento!S$15)),IF(INDEX(Import.PLE,Detalhamento!$E25,Detalhamento!S$15)<=mediçao,0,OFFSET(Import.PLQ,$A25-1,S$15-1,1,1)),OFFSET(Import.PLQ,$A25-1,S$15-1,1,1)),(1-PLE!$AA$28)*OFFSET(Import.PLQ,$A25-1,S$15-1,1,1)))) -> 385.44 | ... BI25: =IF(BI$13="",0,CHOOSE(Detalhamento.OpçãoServiços,OFFSET(Import.PLQ,$A25-1,BI$15-1,1,1),IF($E25<>1,IF(ISNUMBER(INDEX(Import.PLE,Detalhamento!$E25,Detalhamento!BI$15)),IF(INDEX(Import.PLE,Detalhamento!$E25,Detalhamento!BI$15)<=mediçao,OFFSET(Import.PLQ,$A25-1,BI$15-1,1,1),0),0),PLE!$AA$28*OFFSET(Import.PLQ,$A25-1,BI$15-1,1,1)),IF($E25<>1,IF(ISNUMBER(INDEX(Import.PLE,Detalhamento!$E25,Detalhamento!BI$15)),IF(INDEX(Import.PLE,Detalhamento!$E25,Detalhamento!BI$15)<=mediçao,0,OFFSET(Import.PLQ,$A25-1,BI$15-1,1,1)),OFFSET(Import.PLQ,$A25-1,BI$15-1,1,1)),(1-PLE!$AA$28)*OFFSET(Import.PLQ,$A25-1,BI$15-1,1,1)))) -> 0
A26: 8 | B26: =OFFSET(LIorçamento,$A26-1,B$16,1,1) -> Serviço | E26: =OFFSET(LIorçamento,$A26-1,E$16,1,1) -> 2 | F26: =CHOOSE($B$8,IF(OR(Nível="Serviço",Nível="Evento"),E26*10^4+IF(Nível<>"Evento",A26,0),0),IF(Nível<>"Evento",A26,0)) -> 20008 | G26: =OFFSET(LIorçamento,$A26-1,G$16,1,1) -> 3.2 | H26: =OFFSET(LIorçamento,$A26-1,H$16,1,1) -> Assentamento de guia (meio-fio) em trecho reto, confeccionada em concreto pré-fabricado, dimensões 100x15x13x30 cm (comprimento x base inferior x base superior x altura), para vias urbanas (uso viário) | I26: =IF(OR(Nível="Serviço",Nível="evento"),OFFSET(LIorçamento,$A26-1,I$16,1,1),"") -> m | J26: =IF(OR(Nível="Serviço",Nível="evento"),SUM(L26:BI26),"") -> 1740.41 | L26: =IF(L$13="",0,CHOOSE(Detalhamento.OpçãoServiços,OFFSET(Import.PLQ,$A26-1,L$15-1,1,1),IF($E26<>1,IF(ISNUMBER(INDEX(Import.PLE,Detalhamento!$E26,Detalhamento!L$15)),IF(INDEX(Import.PLE,Detalhamento!$E26,Detalhamento!L$15)<=mediçao,OFFSET(Import.PLQ,$A26-1,L$15-1,1,1),0),0),PLE!$AA$28*OFFSET(Import.PLQ,$A26-1,L$15-1,1,1)),IF($E26<>1,IF(ISNUMBER(INDEX(Import.PLE,Detalhamento!$E26,Detalhamento!L$15)),IF(INDEX(Import.PLE,Detalhamento!$E26,Detalhamento!L$15)<=mediçao,0,OFFSET(Import.PLQ,$A26-1,L$15-1,1,1)),OFFSET(Import.PLQ,$A26-1,L$15-1,1,1)),(1-PLE!$AA$28)*OFFSET(Import.PLQ,$A26-1,L$15-1,1,1)))) -> 353.89 | M26: =IF(M$13="",0,CHOOSE(Detalhamento.OpçãoServiços,OFFSET(Import.PLQ,$A26-1,M$15-1,1,1),IF($E26<>1,IF(ISNUMBER(INDEX(Import.PLE,Detalhamento!$E26,Detalhamento!M$15)),IF(INDEX(Import.PLE,Detalhamento!$E26,Detalhamento!M$15)<=mediçao,OFFSET(Import.PLQ,$A26-1,M$15-1,1,1),0),0),PLE!$AA$28*OFFSET(Import.PLQ,$A26-1,M$15-1,1,1)),IF($E26<>1,IF(ISNUMBER(INDEX(Import.PLE,Detalhamento!$E26,Detalhamento!M$15)),IF(INDEX(Import.PLE,Detalhamento!$E26,Detalhamento!M$15)<=mediçao,0,OFFSET(Import.PLQ,$A26-1,M$15-1,1,1)),OFFSET(Import.PLQ,$A26-1,M$15-1,1,1)),(1-PLE!$AA$28)*OFFSET(Import.PLQ,$A26-1,M$15-1,1,1)))) -> 154.35 | N26: =IF(N$13="",0,CHOOSE(Detalhamento.OpçãoServiços,OFFSET(Import.PLQ,$A26-1,N$15-1,1,1),IF($E26<>1,IF(ISNUMBER(INDEX(Import.PLE,Detalhamento!$E26,Detalhamento!N$15)),IF(INDEX(Import.PLE,Detalhamento!$E26,Detalhamento!N$15)<=mediçao,OFFSET(Import.PLQ,$A26-1,N$15-1,1,1),0),0),PLE!$AA$28*OFFSET(Import.PLQ,$A26-1,N$15-1,1,1)),IF($E26<>1,IF(ISNUMBER(INDEX(Import.PLE,Detalhamento!$E26,Detalhamento!N$15)),IF(INDEX(Import.PLE,Detalhamento!$E26,Detalhamento!N$15)<=mediçao,0,OFFSET(Import.PLQ,$A26-1,N$15-1,1,1)),OFFSET(Import.PLQ,$A26-1,N$15-1,1,1)),(1-PLE!$AA$28)*OFFSET(Import.PLQ,$A26-1,N$15-1,1,1)))) -> 215.58 | O26: =IF(O$13="",0,CHOOSE(Detalhamento.OpçãoServiços,OFFSET(Import.PLQ,$A26-1,O$15-1,1,1),IF($E26<>1,IF(ISNUMBER(INDEX(Import.PLE,Detalhamento!$E26,Detalhamento!O$15)),IF(INDEX(Import.PLE,Detalhamento!$E26,Detalhamento!O$15)<=mediçao,OFFSET(Import.PLQ,$A26-1,O$15-1,1,1),0),0),PLE!$AA$28*OFFSET(Import.PLQ,$A26-1,O$15-1,1,1)),IF($E26<>1,IF(ISNUMBER(INDEX(Import.PLE,Detalhamento!$E26,Detalhamento!O$15)),IF(INDEX(Import.PLE,Detalhamento!$E26,Detalhamento!O$15)<=mediçao,0,OFFSET(Import.PLQ,$A26-1,O$15-1,1,1)),OFFSET(Import.PLQ,$A26-1,O$15-1,1,1)),(1-PLE!$AA$28)*OFFSET(Import.PLQ,$A26-1,O$15-1,1,1)))) -> 348.78 | P26: =IF(P$13="",0,CHOOSE(Detalhamento.OpçãoServiços,OFFSET(Import.PLQ,$A26-1,P$15-1,1,1),IF($E26<>1,IF(ISNUMBER(INDEX(Import.PLE,Detalhamento!$E26,Detalhamento!P$15)),IF(INDEX(Import.PLE,Detalhamento!$E26,Detalhamento!P$15)<=mediçao,OFFSET(Import.PLQ,$A26-1,P$15-1,1,1),0),0),PLE!$AA$28*OFFSET(Import.PLQ,$A26-1,P$15-1,1,1)),IF($E26<>1,IF(ISNUMBER(INDEX(Import.PLE,Detalhamento!$E26,Detalhamento!P$15)),IF(INDEX(Import.PLE,Detalhamento!$E26,Detalhamento!P$15)<=mediçao,0,OFFSET(Import.PLQ,$A26-1,P$15-1,1,1)),OFFSET(Import.PLQ,$A26-1,P$15-1,1,1)),(1-PLE!$AA$28)*OFFSET(Import.PLQ,$A26-1,P$15-1,1,1)))) -> 130.15 | Q26: =IF(Q$13="",0,CHOOSE(Detalhamento.OpçãoServiços,OFFSET(Import.PLQ,$A26-1,Q$15-1,1,1),IF($E26<>1,IF(ISNUMBER(INDEX(Import.PLE,Detalhamento!$E26,Detalhamento!Q$15)),IF(INDEX(Import.PLE,Detalhamento!$E26,Detalhamento!Q$15)<=mediçao,OFFSET(Import.PLQ,$A26-1,Q$15-1,1,1),0),0),PLE!$AA$28*OFFSET(Import.PLQ,$A26-1,Q$15-1,1,1)),IF($E26<>1,IF(ISNUMBER(INDEX(Import.PLE,Detalhamento!$E26,Detalhamento!Q$15)),IF(INDEX(Import.PLE,Detalhamento!$E26,Detalhamento!Q$15)<=mediçao,0,OFFSET(Import.PLQ,$A26-1,Q$15-1,1,1)),OFFSET(Import.PLQ,$A26-1,Q$15-1,1,1)),(1-PLE!$AA$28)*OFFSET(Import.PLQ,$A26-1,Q$15-1,1,1)))) -> 241.91 | R26: =IF(R$13="",0,CHOOSE(Detalhamento.OpçãoServiços,OFFSET(Import.PLQ,$A26-1,R$15-1,1,1),IF($E26<>1,IF(ISNUMBER(INDEX(Import.PLE,Detalhamento!$E26,Detalhamento!R$15)),IF(INDEX(Import.PLE,Detalhamento!$E26,Detalhamento!R$15)<=mediçao,OFFSET(Import.PLQ,$A26-1,R$15-1,1,1),0),0),PLE!$AA$28*OFFSET(Import.PLQ,$A26-1,R$15-1,1,1)),IF($E26<>1,IF(ISNUMBER(INDEX(Import.PLE,Detalhamento!$E26,Detalhamento!R$15)),IF(INDEX(Import.PLE,Detalhamento!$E26,Detalhamento!R$15)<=mediçao,0,OFFSET(Import.PLQ,$A26-1,R$15-1,1,1)),OFFSET(Import.PLQ,$A26-1,R$15-1,1,1)),(1-PLE!$AA$28)*OFFSET(Import.PLQ,$A26-1,R$15-1,1,1)))) -> 167.27 | S26: =IF(S$13="",0,CHOOSE(Detalhamento.OpçãoServiços,OFFSET(Import.PLQ,$A26-1,S$15-1,1,1),IF($E26<>1,IF(ISNUMBER(INDEX(Import.PLE,Detalhamento!$E26,Detalhamento!S$15)),IF(INDEX(Import.PLE,Detalhamento!$E26,Detalhamento!S$15)<=mediçao,OFFSET(Import.PLQ,$A26-1,S$15-1,1,1),0),0),PLE!$AA$28*OFFSET(Import.PLQ,$A26-1,S$15-1,1,1)),IF($E26<>1,IF(ISNUMBER(INDEX(Import.PLE,Detalhamento!$E26,Detalhamento!S$15)),IF(INDEX(Import.PLE,Detalhamento!$E26,Detalhamento!S$15)<=mediçao,0,OFFSET(Import.PLQ,$A26-1,S$15-1,1,1)),OFFSET(Import.PLQ,$A26-1,S$15-1,1,1)),(1-PLE!$AA$28)*OFFSET(Import.PLQ,$A26-1,S$15-1,1,1)))) -> 128.48 | ... BI26: =IF(BI$13="",0,CHOOSE(Detalhamento.OpçãoServiços,OFFSET(Import.PLQ,$A26-1,BI$15-1,1,1),IF($E26<>1,IF(ISNUMBER(INDEX(Import.PLE,Detalhamento!$E26,Detalhamento!BI$15)),IF(INDEX(Import.PLE,Detalhamento!$E26,Detalhamento!BI$15)<=mediçao,OFFSET(Import.PLQ,$A26-1,BI$15-1,1,1),0),0),PLE!$AA$28*OFFSET(Import.PLQ,$A26-1,BI$15-1,1,1)),IF($E26<>1,IF(ISNUMBER(INDEX(Import.PLE,Detalhamento!$E26,Detalhamento!BI$15)),IF(INDEX(Import.PLE,Detalhamento!$E26,Detalhamento!BI$15)<=mediçao,0,OFFSET(Import.PLQ,$A26-1,BI$15-1,1,1)),OFFSET(Import.PLQ,$A26-1,BI$15-1,1,1)),(1-PLE!$AA$28)*OFFSET(Import.PLQ,$A26-1,BI$15-1,1,1)))) -> 0
A27: 11 | B27: =OFFSET(LIorçamento,$A27-1,B$16,1,1) -> Meta | E27: =OFFSET(LIorçamento,$A27-1,E$16,1,1) | F27: =CHOOSE($B$8,IF(OR(Nível="Serviço",Nível="Evento"),E27*10^4+IF(Nível<>"Evento",A27,0),0),IF(Nível<>"Evento",A27,0)) -> 0 | G27: =OFFSET(LIorçamento,$A27-1,G$16,1,1) -> 4 | H27: =OFFSET(LIorçamento,$A27-1,H$16,1,1) -> SERVIÇOS COMPLEMENTARES | I27: =IF(OR(Nível="Serviço",Nível="evento"),OFFSET(LIorçamento,$A27-1,I$16,1,1),"") | J27: =IF(OR(Nível="Serviço",Nível="evento"),SUM(L27:BI27),"") | L27: =IF(L$13="",0,CHOOSE(Detalhamento.OpçãoServiços,OFFSET(Import.PLQ,$A27-1,L$15-1,1,1),IF($E27<>1,IF(ISNUMBER(INDEX(Import.PLE,Detalhamento!$E27,Detalhamento!L$15)),IF(INDEX(Import.PLE,Detalhamento!$E27,Detalhamento!L$15)<=mediçao,OFFSET(Import.PLQ,$A27-1,L$15-1,1,1),0),0),PLE!$AA$28*OFFSET(Import.PLQ,$A27-1,L$15-1,1,1)),IF($E27<>1,IF(ISNUMBER(INDEX(Import.PLE,Detalhamento!$E27,Detalhamento!L$15)),IF(INDEX(Import.PLE,Detalhamento!$E27,Detalhamento!L$15)<=mediçao,0,OFFSET(Import.PLQ,$A27-1,L$15-1,1,1)),OFFSET(Import.PLQ,$A27-1,L$15-1,1,1)),(1-PLE!$AA$28)*OFFSET(Import.PLQ,$A27-1,L$15-1,1,1)))) -> 0 | M27: =IF(M$13="",0,CHOOSE(Detalhamento.OpçãoServiços,OFFSET(Import.PLQ,$A27-1,M$15-1,1,1),IF($E27<>1,IF(ISNUMBER(INDEX(Import.PLE,Detalhamento!$E27,Detalhamento!M$15)),IF(INDEX(Import.PLE,Detalhamento!$E27,Detalhamento!M$15)<=mediçao,OFFSET(Import.PLQ,$A27-1,M$15-1,1,1),0),0),PLE!$AA$28*OFFSET(Import.PLQ,$A27-1,M$15-1,1,1)),IF($E27<>1,IF(ISNUMBER(INDEX(Import.PLE,Detalhamento!$E27,Detalhamento!M$15)),IF(INDEX(Import.PLE,Detalhamento!$E27,Detalhamento!M$15)<=mediçao,0,OFFSET(Import.PLQ,$A27-1,M$15-1,1,1)),OFFSET(Import.PLQ,$A27-1,M$15-1,1,1)),(1-PLE!$AA$28)*OFFSET(Import.PLQ,$A27-1,M$15-1,1,1)))) -> 0 | N27: =IF(N$13="",0,CHOOSE(Detalhamento.OpçãoServiços,OFFSET(Import.PLQ,$A27-1,N$15-1,1,1),IF($E27<>1,IF(ISNUMBER(INDEX(Import.PLE,Detalhamento!$E27,Detalhamento!N$15)),IF(INDEX(Import.PLE,Detalhamento!$E27,Detalhamento!N$15)<=mediçao,OFFSET(Import.PLQ,$A27-1,N$15-1,1,1),0),0),PLE!$AA$28*OFFSET(Import.PLQ,$A27-1,N$15-1,1,1)),IF($E27<>1,IF(ISNUMBER(INDEX(Import.PLE,Detalhamento!$E27,Detalhamento!N$15)),IF(INDEX(Import.PLE,Detalhamento!$E27,Detalhamento!N$15)<=mediçao,0,OFFSET(Import.PLQ,$A27-1,N$15-1,1,1)),OFFSET(Import.PLQ,$A27-1,N$15-1,1,1)),(1-PLE!$AA$28)*OFFSET(Import.PLQ,$A27-1,N$15-1,1,1)))) -> 0 | O27: =IF(O$13="",0,CHOOSE(Detalhamento.OpçãoServiços,OFFSET(Import.PLQ,$A27-1,O$15-1,1,1),IF($E27<>1,IF(ISNUMBER(INDEX(Import.PLE,Detalhamento!$E27,Detalhamento!O$15)),IF(INDEX(Import.PLE,Detalhamento!$E27,Detalhamento!O$15)<=mediçao,OFFSET(Import.PLQ,$A27-1,O$15-1,1,1),0),0),PLE!$AA$28*OFFSET(Import.PLQ,$A27-1,O$15-1,1,1)),IF($E27<>1,IF(ISNUMBER(INDEX(Import.PLE,Detalhamento!$E27,Detalhamento!O$15)),IF(INDEX(Import.PLE,Detalhamento!$E27,Detalhamento!O$15)<=mediçao,0,OFFSET(Import.PLQ,$A27-1,O$15-1,1,1)),OFFSET(Import.PLQ,$A27-1,O$15-1,1,1)),(1-PLE!$AA$28)*OFFSET(Import.PLQ,$A27-1,O$15-1,1,1)))) -> 0 | P27: =IF(P$13="",0,CHOOSE(Detalhamento.OpçãoServiços,OFFSET(Import.PLQ,$A27-1,P$15-1,1,1),IF($E27<>1,IF(ISNUMBER(INDEX(Import.PLE,Detalhamento!$E27,Detalhamento!P$15)),IF(INDEX(Import.PLE,Detalhamento!$E27,Detalhamento!P$15)<=mediçao,OFFSET(Import.PLQ,$A27-1,P$15-1,1,1),0),0),PLE!$AA$28*OFFSET(Import.PLQ,$A27-1,P$15-1,1,1)),IF($E27<>1,IF(ISNUMBER(INDEX(Import.PLE,Detalhamento!$E27,Detalhamento!P$15)),IF(INDEX(Import.PLE,Detalhamento!$E27,Detalhamento!P$15)<=mediçao,0,OFFSET(Import.PLQ,$A27-1,P$15-1,1,1)),OFFSET(Import.PLQ,$A27-1,P$15-1,1,1)),(1-PLE!$AA$28)*OFFSET(Import.PLQ,$A27-1,P$15-1,1,1)))) -> 0 | Q27: =IF(Q$13="",0,CHOOSE(Detalhamento.OpçãoServiços,OFFSET(Import.PLQ,$A27-1,Q$15-1,1,1),IF($E27<>1,IF(ISNUMBER(INDEX(Import.PLE,Detalhamento!$E27,Detalhamento!Q$15)),IF(INDEX(Import.PLE,Detalhamento!$E27,Detalhamento!Q$15)<=mediçao,OFFSET(Import.PLQ,$A27-1,Q$15-1,1,1),0),0),PLE!$AA$28*OFFSET(Import.PLQ,$A27-1,Q$15-1,1,1)),IF($E27<>1,IF(ISNUMBER(INDEX(Import.PLE,Detalhamento!$E27,Detalhamento!Q$15)),IF(INDEX(Import.PLE,Detalhamento!$E27,Detalhamento!Q$15)<=mediçao,0,OFFSET(Import.PLQ,$A27-1,Q$15-1,1,1)),OFFSET(Import.PLQ,$A27-1,Q$15-1,1,1)),(1-PLE!$AA$28)*OFFSET(Import.PLQ,$A27-1,Q$15-1,1,1)))) -> 0 | R27: =IF(R$13="",0,CHOOSE(Detalhamento.OpçãoServiços,OFFSET(Import.PLQ,$A27-1,R$15-1,1,1),IF($E27<>1,IF(ISNUMBER(INDEX(Import.PLE,Detalhamento!$E27,Detalhamento!R$15)),IF(INDEX(Import.PLE,Detalhamento!$E27,Detalhamento!R$15)<=mediçao,OFFSET(Import.PLQ,$A27-1,R$15-1,1,1),0),0),PLE!$AA$28*OFFSET(Import.PLQ,$A27-1,R$15-1,1,1)),IF($E27<>1,IF(ISNUMBER(INDEX(Import.PLE,Detalhamento!$E27,Detalhamento!R$15)),IF(INDEX(Import.PLE,Detalhamento!$E27,Detalhamento!R$15)<=mediçao,0,OFFSET(Import.PLQ,$A27-1,R$15-1,1,1)),OFFSET(Import.PLQ,$A27-1,R$15-1,1,1)),(1-PLE!$AA$28)*OFFSET(Import.PLQ,$A27-1,R$15-1,1,1)))) -> 0 | S27: =IF(S$13="",0,CHOOSE(Detalhamento.OpçãoServiços,OFFSET(Import.PLQ,$A27-1,S$15-1,1,1),IF($E27<>1,IF(ISNUMBER(INDEX(Import.PLE,Detalhamento!$E27,Detalhamento!S$15)),IF(INDEX(Import.PLE,Detalhamento!$E27,Detalhamento!S$15)<=mediçao,OFFSET(Import.PLQ,$A27-1,S$15-1,1,1),0),0),PLE!$AA$28*OFFSET(Import.PLQ,$A27-1,S$15-1,1,1)),IF($E27<>1,IF(ISNUMBER(INDEX(Import.PLE,Detalhamento!$E27,Detalhamento!S$15)),IF(INDEX(Import.PLE,Detalhamento!$E27,Detalhamento!S$15)<=mediçao,0,OFFSET(Import.PLQ,$A27-1,S$15-1,1,1)),OFFSET(Import.PLQ,$A27-1,S$15-1,1,1)),(1-PLE!$AA$28)*OFFSET(Import.PLQ,$A27-1,S$15-1,1,1)))) -> 0 | ... BI27: =IF(BI$13="",0,CHOOSE(Detalhamento.OpçãoServiços,OFFSET(Import.PLQ,$A27-1,BI$15-1,1,1),IF($E27<>1,IF(ISNUMBER(INDEX(Import.PLE,Detalhamento!$E27,Detalhamento!BI$15)),IF(INDEX(Import.PLE,Detalhamento!$E27,Detalhamento!BI$15)<=mediçao,OFFSET(Import.PLQ,$A27-1,BI$15-1,1,1),0),0),PLE!$AA$28*OFFSET(Import.PLQ,$A27-1,BI$15-1,1,1)),IF($E27<>1,IF(ISNUMBER(INDEX(Import.PLE,Detalhamento!$E27,Detalhamento!BI$15)),IF(INDEX(Import.PLE,Detalhamento!$E27,Detalhamento!BI$15)<=mediçao,0,OFFSET(Import.PLQ,$A27-1,BI$15-1,1,1)),OFFSET(Import.PLQ,$A27-1,BI$15-1,1,1)),(1-PLE!$AA$28)*OFFSET(Import.PLQ,$A27-1,BI$15-1,1,1)))) -> 0
A28: 9 | B28: =OFFSET(LIorçamento,$A28-1,B$16,1,1) -> Serviço | E28: =OFFSET(LIorçamento,$A28-1,E$16,1,1) -> 2 | F28: =CHOOSE($B$8,IF(OR(Nível="Serviço",Nível="Evento"),E28*10^4+IF(Nível<>"Evento",A28,0),0),IF(Nível<>"Evento",A28,0)) -> 20009 | G28: =OFFSET(LIorçamento,$A28-1,G$16,1,1) -> 3.3 | H28: =OFFSET(LIorçamento,$A28-1,H$16,1,1) -> Revestimento em paralelepipedo inclusive colchão de areia rejuntado no traço 1:3 (Cimento e areia) | I28: =IF(OR(Nível="Serviço",Nível="evento"),OFFSET(LIorçamento,$A28-1,I$16,1,1),"") -> m² | J28: =IF(OR(Nível="Serviço",Nível="evento"),SUM(L28:BI28),"") -> 5349.12 | L28: =IF(L$13="",0,CHOOSE(Detalhamento.OpçãoServiços,OFFSET(Import.PLQ,$A28-1,L$15-1,1,1),IF($E28<>1,IF(ISNUMBER(INDEX(Import.PLE,Detalhamento!$E28,Detalhamento!L$15)),IF(INDEX(Import.PLE,Detalhamento!$E28,Detalhamento!L$15)<=mediçao,OFFSET(Import.PLQ,$A28-1,L$15-1,1,1),0),0),PLE!$AA$28*OFFSET(Import.PLQ,$A28-1,L$15-1,1,1)),IF($E28<>1,IF(ISNUMBER(INDEX(Import.PLE,Detalhamento!$E28,Detalhamento!L$15)),IF(INDEX(Import.PLE,Detalhamento!$E28,Detalhamento!L$15)<=mediçao,0,OFFSET(Import.PLQ,$A28-1,L$15-1,1,1)),OFFSET(Import.PLQ,$A28-1,L$15-1,1,1)),(1-PLE!$AA$28)*OFFSET(Import.PLQ,$A28-1,L$15-1,1,1)))) -> 1102.85 | M28: =IF(M$13="",0,CHOOSE(Detalhamento.OpçãoServiços,OFFSET(Import.PLQ,$A28-1,M$15-1,1,1),IF($E28<>1,IF(ISNUMBER(INDEX(Import.PLE,Detalhamento!$E28,Detalhamento!M$15)),IF(INDEX(Import.PLE,Detalhamento!$E28,Detalhamento!M$15)<=mediçao,OFFSET(Import.PLQ,$A28-1,M$15-1,1,1),0),0),PLE!$AA$28*OFFSET(Import.PLQ,$A28-1,M$15-1,1,1)),IF($E28<>1,IF(ISNUMBER(INDEX(Import.PLE,Detalhamento!$E28,Detalhamento!M$15)),IF(INDEX(Import.PLE,Detalhamento!$E28,Detalhamento!M$15)<=mediçao,0,OFFSET(Import.PLQ,$A28-1,M$15-1,1,1)),OFFSET(Import.PLQ,$A28-1,M$15-1,1,1)),(1-PLE!$AA$28)*OFFSET(Import.PLQ,$A28-1,M$15-1,1,1)))) -> 452.76 | N28: =IF(N$13="",0,CHOOSE(Detalhamento.OpçãoServiços,OFFSET(Import.PLQ,$A28-1,N$15-1,1,1),IF($E28<>1,IF(ISNUMBER(INDEX(Import.PLE,Detalhamento!$E28,Detalhamento!N$15)),IF(INDEX(Import.PLE,Detalhamento!$E28,Detalhamento!N$15)<=mediçao,OFFSET(Import.PLQ,$A28-1,N$15-1,1,1),0),0),PLE!$AA$28*OFFSET(Import.PLQ,$A28-1,N$15-1,1,1)),IF($E28<>1,IF(ISNUMBER(INDEX(Import.PLE,Detalhamento!$E28,Detalhamento!N$15)),IF(INDEX(Import.PLE,Detalhamento!$E28,Detalhamento!N$15)<=mediçao,0,OFFSET(Import.PLQ,$A28-1,N$15-1,1,1)),OFFSET(Import.PLQ,$A28-1,N$15-1,1,1)),(1-PLE!$AA$28)*OFFSET(Import.PLQ,$A28-1,N$15-1,1,1)))) -> 727.62 | O28: =IF(O$13="",0,CHOOSE(Detalhamento.OpçãoServiços,OFFSET(Import.PLQ,$A28-1,O$15-1,1,1),IF($E28<>1,IF(ISNUMBER(INDEX(Import.PLE,Detalhamento!$E28,Detalhamento!O$15)),IF(INDEX(Import.PLE,Detalhamento!$E28,Detalhamento!O$15)<=mediçao,OFFSET(Import.PLQ,$A28-1,O$15-1,1,1),0),0),PLE!$AA$28*OFFSET(Import.PLQ,$A28-1,O$15-1,1,1)),IF($E28<>1,IF(ISNUMBER(INDEX(Import.PLE,Detalhamento!$E28,Detalhamento!O$15)),IF(INDEX(Import.PLE,Detalhamento!$E28,Detalhamento!O$15)<=mediçao,0,OFFSET(Import.PLQ,$A28-1,O$15-1,1,1)),OFFSET(Import.PLQ,$A28-1,O$15-1,1,1)),(1-PLE!$AA$28)*OFFSET(Import.PLQ,$A28-1,O$15-1,1,1)))) -> 1032.9 | P28: =IF(P$13="",0,CHOOSE(Detalhamento.OpçãoServiços,OFFSET(Import.PLQ,$A28-1,P$15-1,1,1),IF($E28<>1,IF(ISNUMBER(INDEX(Import.PLE,Detalhamento!$E28,Detalhamento!P$15)),IF(INDEX(Import.PLE,Detalhamento!$E28,Detalhamento!P$15)<=mediçao,OFFSET(Import.PLQ,$A28-1,P$15-1,1,1),0),0),PLE!$AA$28*OFFSET(Import.PLQ,$A28-1,P$15-1,1,1)),IF($E28<>1,IF(ISNUMBER(INDEX(Import.PLE,Detalhamento!$E28,Detalhamento!P$15)),IF(INDEX(Import.PLE,Detalhamento!$E28,Detalhamento!P$15)<=mediçao,0,OFFSET(Import.PLQ,$A28-1,P$15-1,1,1)),OFFSET(Import.PLQ,$A28-1,P$15-1,1,1)),(1-PLE!$AA$28)*OFFSET(Import.PLQ,$A28-1,P$15-1,1,1)))) -> 390.01 | Q28: =IF(Q$13="",0,CHOOSE(Detalhamento.OpçãoServiços,OFFSET(Import.PLQ,$A28-1,Q$15-1,1,1),IF($E28<>1,IF(ISNUMBER(INDEX(Import.PLE,Detalhamento!$E28,Detalhamento!Q$15)),IF(INDEX(Import.PLE,Detalhamento!$E28,Detalhamento!Q$15)<=mediçao,OFFSET(Import.PLQ,$A28-1,Q$15-1,1,1),0),0),PLE!$AA$28*OFFSET(Import.PLQ,$A28-1,Q$15-1,1,1)),IF($E28<>1,IF(ISNUMBER(INDEX(Import.PLE,Detalhamento!$E28,Detalhamento!Q$15)),IF(INDEX(Import.PLE,Detalhamento!$E28,Detalhamento!Q$15)<=mediçao,0,OFFSET(Import.PLQ,$A28-1,Q$15-1,1,1)),OFFSET(Import.PLQ,$A28-1,Q$15-1,1,1)),(1-PLE!$AA$28)*OFFSET(Import.PLQ,$A28-1,Q$15-1,1,1)))) -> 733.74 | R28: =IF(R$13="",0,CHOOSE(Detalhamento.OpçãoServiços,OFFSET(Import.PLQ,$A28-1,R$15-1,1,1),IF($E28<>1,IF(ISNUMBER(INDEX(Import.PLE,Detalhamento!$E28,Detalhamento!R$15)),IF(INDEX(Import.PLE,Detalhamento!$E28,Detalhamento!R$15)<=mediçao,OFFSET(Import.PLQ,$A28-1,R$15-1,1,1),0),0),PLE!$AA$28*OFFSET(Import.PLQ,$A28-1,R$15-1,1,1)),IF($E28<>1,IF(ISNUMBER(INDEX(Import.PLE,Detalhamento!$E28,Detalhamento!R$15)),IF(INDEX(Import.PLE,Detalhamento!$E28,Detalhamento!R$15)<=mediçao,0,OFFSET(Import.PLQ,$A28-1,R$15-1,1,1)),OFFSET(Import.PLQ,$A28-1,R$15-1,1,1)),(1-PLE!$AA$28)*OFFSET(Import.PLQ,$A28-1,R$15-1,1,1)))) -> 523.8 | S28: =IF(S$13="",0,CHOOSE(Detalhamento.OpçãoServiços,OFFSET(Import.PLQ,$A28-1,S$15-1,1,1),IF($E28<>1,IF(ISNUMBER(INDEX(Import.PLE,Detalhamento!$E28,Detalhamento!S$15)),IF(INDEX(Import.PLE,Detalhamento!$E28,Detalhamento!S$15)<=mediçao,OFFSET(Import.PLQ,$A28-1,S$15-1,1,1),0),0),PLE!$AA$28*OFFSET(Import.PLQ,$A28-1,S$15-1,1,1)),IF($E28<>1,IF(ISNUMBER(INDEX(Import.PLE,Detalhamento!$E28,Detalhamento!S$15)),IF(INDEX(Import.PLE,Detalhamento!$E28,Detalhamento!S$15)<=mediçao,0,OFFSET(Import.PLQ,$A28-1,S$15-1,1,1)),OFFSET(Import.PLQ,$A28-1,S$15-1,1,1)),(1-PLE!$AA$28)*OFFSET(Import.PLQ,$A28-1,S$15-1,1,1)))) -> 385.44 | ... BI28: =IF(BI$13="",0,CHOOSE(Detalhamento.OpçãoServiços,OFFSET(Import.PLQ,$A28-1,BI$15-1,1,1),IF($E28<>1,IF(ISNUMBER(INDEX(Import.PLE,Detalhamento!$E28,Detalhamento!BI$15)),IF(INDEX(Import.PLE,Detalhamento!$E28,Detalhamento!BI$15)<=mediçao,OFFSET(Import.PLQ,$A28-1,BI$15-1,1,1),0),0),PLE!$AA$28*OFFSET(Import.PLQ,$A28-1,BI$15-1,1,1)),IF($E28<>1,IF(ISNUMBER(INDEX(Import.PLE,Detalhamento!$E28,Detalhamento!BI$15)),IF(INDEX(Import.PLE,Detalhamento!$E28,Detalhamento!BI$15)<=mediçao,0,OFFSET(Import.PLQ,$A28-1,BI$15-1,1,1)),OFFSET(Import.PLQ,$A28-1,BI$15-1,1,1)),(1-PLE!$AA$28)*OFFSET(Import.PLQ,$A28-1,BI$15-1,1,1)))) -> 0
... A39: 19 | B39: =OFFSET(LIorçamento,$A39-1,B$16,1,1) -> Serviço | E39: =OFFSET(LIorçamento,$A39-1,E$16,1,1) -> 4 | F39: =CHOOSE($B$8,IF(OR(Nível="Serviço",Nível="Evento"),E39*10^4+IF(Nível<>"Evento",A39,0),0),IF(Nível<>"Evento",A39,0)) -> 40019 | G39: =OFFSET(LIorçamento,$A39-1,G$16,1,1) -> 4.8 | H39: =OFFSET(LIorçamento,$A39-1,H$16,1,1) -> Placa esmaltada para identificação de número de rua, dimensões 45x20cm | I39: =IF(OR(Nível="Serviço",Nível="evento"),OFFSET(LIorçamento,$A39-1,I$16,1,1),"") -> unid | J39: =IF(OR(Nível="Serviço",Nível="evento"),SUM(L39:BI39),"") -> 8 | L39: =IF(L$13="",0,CHOOSE(Detalhamento.OpçãoServiços,OFFSET(Import.PLQ,$A39-1,L$15-1,1,1),IF($E39<>1,IF(ISNUMBER(INDEX(Import.PLE,Detalhamento!$E39,Detalhamento!L$15)),IF(INDEX(Import.PLE,Detalhamento!$E39,Detalhamento!L$15)<=mediçao,OFFSET(Import.PLQ,$A39-1,L$15-1,1,1),0),0),PLE!$AA$28*OFFSET(Import.PLQ,$A39-1,L$15-1,1,1)),IF($E39<>1,IF(ISNUMBER(INDEX(Import.PLE,Detalhamento!$E39,Detalhamento!L$15)),IF(INDEX(Import.PLE,Detalhamento!$E39,Detalhamento!L$15)<=mediçao,0,OFFSET(Import.PLQ,$A39-1,L$15-1,1,1)),OFFSET(Import.PLQ,$A39-1,L$15-1,1,1)),(1-PLE!$AA$28)*OFFSET(Import.PLQ,$A39-1,L$15-1,1,1)))) -> 1 | M39: =IF(M$13="",0,CHOOSE(Detalhamento.OpçãoServiços,OFFSET(Import.PLQ,$A39-1,M$15-1,1,1),IF($E39<>1,IF(ISNUMBER(INDEX(Import.PLE,Detalhamento!$E39,Detalhamento!M$15)),IF(INDEX(Import.PLE,Detalhamento!$E39,Detalhamento!M$15)<=mediçao,OFFSET(Import.PLQ,$A39-1,M$15-1,1,1),0),0),PLE!$AA$28*OFFSET(Import.PLQ,$A39-1,M$15-1,1,1)),IF($E39<>1,IF(ISNUMBER(INDEX(Import.PLE,Detalhamento!$E39,Detalhamento!M$15)),IF(INDEX(Import.PLE,Detalhamento!$E39,Detalhamento!M$15)<=mediçao,0,OFFSET(Import.PLQ,$A39-1,M$15-1,1,1)),OFFSET(Import.PLQ,$A39-1,M$15-1,1,1)),(1-PLE!$AA$28)*OFFSET(Import.PLQ,$A39-1,M$15-1,1,1)))) -> 1 | N39: =IF(N$13="",0,CHOOSE(Detalhamento.OpçãoServiços,OFFSET(Import.PLQ,$A39-1,N$15-1,1,1),IF($E39<>1,IF(ISNUMBER(INDEX(Import.PLE,Detalhamento!$E39,Detalhamento!N$15)),IF(INDEX(Import.PLE,Detalhamento!$E39,Detalhamento!N$15)<=mediçao,OFFSET(Import.PLQ,$A39-1,N$15-1,1,1),0),0),PLE!$AA$28*OFFSET(Import.PLQ,$A39-1,N$15-1,1,1)),IF($E39<>1,IF(ISNUMBER(INDEX(Import.PLE,Detalhamento!$E39,Detalhamento!N$15)),IF(INDEX(Import.PLE,Detalhamento!$E39,Detalhamento!N$15)<=mediçao,0,OFFSET(Import.PLQ,$A39-1,N$15-1,1,1)),OFFSET(Import.PLQ,$A39-1,N$15-1,1,1)),(1-PLE!$AA$28)*OFFSET(Import.PLQ,$A39-1,N$15-1,1,1)))) -> 1 | O39: =IF(O$13="",0,CHOOSE(Detalhamento.OpçãoServiços,OFFSET(Import.PLQ,$A39-1,O$15-1,1,1),IF($E39<>1,IF(ISNUMBER(INDEX(Import.PLE,Detalhamento!$E39,Detalhamento!O$15)),IF(INDEX(Import.PLE,Detalhamento!$E39,Detalhamento!O$15)<=mediçao,OFFSET(Import.PLQ,$A39-1,O$15-1,1,1),0),0),PLE!$AA$28*OFFSET(Import.PLQ,$A39-1,O$15-1,1,1)),IF($E39<>1,IF(ISNUMBER(INDEX(Import.PLE,Detalhamento!$E39,Detalhamento!O$15)),IF(INDEX(Import.PLE,Detalhamento!$E39,Detalhamento!O$15)<=mediçao,0,OFFSET(Import.PLQ,$A39-1,O$15-1,1,1)),OFFSET(Import.PLQ,$A39-1,O$15-1,1,1)),(1-PLE!$AA$28)*OFFSET(Import.PLQ,$A39-1,O$15-1,1,1)))) -> 1 | P39: =IF(P$13="",0,CHOOSE(Detalhamento.OpçãoServiços,OFFSET(Import.PLQ,$A39-1,P$15-1,1,1),IF($E39<>1,IF(ISNUMBER(INDEX(Import.PLE,Detalhamento!$E39,Detalhamento!P$15)),IF(INDEX(Import.PLE,Detalhamento!$E39,Detalhamento!P$15)<=mediçao,OFFSET(Import.PLQ,$A39-1,P$15-1,1,1),0),0),PLE!$AA$28*OFFSET(Import.PLQ,$A39-1,P$15-1,1,1)),IF($E39<>1,IF(ISNUMBER(INDEX(Import.PLE,Detalhamento!$E39,Detalhamento!P$15)),IF(INDEX(Import.PLE,Detalhamento!$E39,Detalhamento!P$15)<=mediçao,0,OFFSET(Import.PLQ,$A39-1,P$15-1,1,1)),OFFSET(Import.PLQ,$A39-1,P$15-1,1,1)),(1-PLE!$AA$28)*OFFSET(Import.PLQ,$A39-1,P$15-1,1,1)))) -> 1 | Q39: =IF(Q$13="",0,CHOOSE(Detalhamento.OpçãoServiços,OFFSET(Import.PLQ,$A39-1,Q$15-1,1,1),IF($E39<>1,IF(ISNUMBER(INDEX(Import.PLE,Detalhamento!$E39,Detalhamento!Q$15)),IF(INDEX(Import.PLE,Detalhamento!$E39,Detalhamento!Q$15)<=mediçao,OFFSET(Import.PLQ,$A39-1,Q$15-1,1,1),0),0),PLE!$AA$28*OFFSET(Import.PLQ,$A39-1,Q$15-1,1,1)),IF($E39<>1,IF(ISNUMBER(INDEX(Import.PLE,Detalhamento!$E39,Detalhamento!Q$15)),IF(INDEX(Import.PLE,Detalhamento!$E39,Detalhamento!Q$15)<=mediçao,0,OFFSET(Import.PLQ,$A39-1,Q$15-1,1,1)),OFFSET(Import.PLQ,$A39-1,Q$15-1,1,1)),(1-PLE!$AA$28)*OFFSET(Import.PLQ,$A39-1,Q$15-1,1,1)))) -> 1 | R39: =IF(R$13="",0,CHOOSE(Detalhamento.OpçãoServiços,OFFSET(Import.PLQ,$A39-1,R$15-1,1,1),IF($E39<>1,IF(ISNUMBER(INDEX(Import.PLE,Detalhamento!$E39,Detalhamento!R$15)),IF(INDEX(Import.PLE,Detalhamento!$E39,Detalhamento!R$15)<=mediçao,OFFSET(Import.PLQ,$A39-1,R$15-1,1,1),0),0),PLE!$AA$28*OFFSET(Import.PLQ,$A39-1,R$15-1,1,1)),IF($E39<>1,IF(ISNUMBER(INDEX(Import.PLE,Detalhamento!$E39,Detalhamento!R$15)),IF(INDEX(Import.PLE,Detalhamento!$E39,Detalhamento!R$15)<=mediçao,0,OFFSET(Import.PLQ,$A39-1,R$15-1,1,1)),OFFSET(Import.PLQ,$A39-1,R$15-1,1,1)),(1-PLE!$AA$28)*OFFSET(Import.PLQ,$A39-1,R$15-1,1,1)))) -> 1 | S39: =IF(S$13="",0,CHOOSE(Detalhamento.OpçãoServiços,OFFSET(Import.PLQ,$A39-1,S$15-1,1,1),IF($E39<>1,IF(ISNUMBER(INDEX(Import.PLE,Detalhamento!$E39,Detalhamento!S$15)),IF(INDEX(Import.PLE,Detalhamento!$E39,Detalhamento!S$15)<=mediçao,OFFSET(Import.PLQ,$A39-1,S$15-1,1,1),0),0),PLE!$AA$28*OFFSET(Import.PLQ,$A39-1,S$15-1,1,1)),IF($E39<>1,IF(ISNUMBER(INDEX(Import.PLE,Detalhamento!$E39,Detalhamento!S$15)),IF(INDEX(Import.PLE,Detalhamento!$E39,Detalhamento!S$15)<=mediçao,0,OFFSET(Import.PLQ,$A39-1,S$15-1,1,1)),OFFSET(Import.PLQ,$A39-1,S$15-1,1,1)),(1-PLE!$AA$28)*OFFSET(Import.PLQ,$A39-1,S$15-1,1,1)))) -> 1 | ... BI39: =IF(BI$13="",0,CHOOSE(Detalhamento.OpçãoServiços,OFFSET(Import.PLQ,$A39-1,BI$15-1,1,1),IF($E39<>1,IF(ISNUMBER(INDEX(Import.PLE,Detalhamento!$E39,Detalhamento!BI$15)),IF(INDEX(Import.PLE,Detalhamento!$E39,Detalhamento!BI$15)<=mediçao,OFFSET(Import.PLQ,$A39-1,BI$15-1,1,1),0),0),PLE!$AA$28*OFFSET(Import.PLQ,$A39-1,BI$15-1,1,1)),IF($E39<>1,IF(ISNUMBER(INDEX(Import.PLE,Detalhamento!$E39,Detalhamento!BI$15)),IF(INDEX(Import.PLE,Detalhamento!$E39,Detalhamento!BI$15)<=mediçao,0,OFFSET(Import.PLQ,$A39-1,BI$15-1,1,1)),OFFSET(Import.PLQ,$A39-1,BI$15-1,1,1)),(1-PLE!$AA$28)*OFFSET(Import.PLQ,$A39-1,BI$15-1,1,1)))) -> 0
E41: =Eventograma_e_Quantitativos!C42 -> COREMAS/PB, 31 de julho de 2023
E42: Local e Data | M42: Responsável Técnico: | N42: =Eventograma_e_Quantitativos!$P$43 -> 0 | S42: Responsável Técnico: | T42: =Eventograma_e_Quantitativos!$P$43 -> 0 | Y42: Responsável Técnico: | Z42: =Eventograma_e_Quantitativos!$P$43 -> 0 | AE42: Responsável Técnico: | AF42: =Eventograma_e_Quantitativos!$P$43 -> 0 | AK42: Responsável Técnico: | AL42: =Eventograma_e_Quantitativos!$P$43 -> 0 | AQ42: Responsável Técnico: | AR42: =Eventograma_e_Quantitativos!$P$43 -> 0 | AW42: Responsável Técnico: | AX42: =Eventograma_e_Quantitativos!$P$43 -> 0 | BC42: Responsável Técnico: | BD42: =Eventograma_e_Quantitativos!$P$43 -> 0
M43: CREA / CAU: | N43: =Eventograma_e_Quantitativos!$P$44 -> 0 | S43: CREA / CAU: | T43: =Eventograma_e_Quantitativos!$P$44 -> 0 | Y43: CREA / CAU: | Z43: =Eventograma_e_Quantitativos!$P$44 -> 0 | AE43: CREA / CAU: | AF43: =Eventograma_e_Quantitativos!$P$44 -> 0 | AK43: CREA / CAU: | AL43: =Eventograma_e_Quantitativos!$P$44 -> 0 | AQ43: CREA / CAU: | AR43: =Eventograma_e_Quantitativos!$P$44 -> 0 | AW43: CREA / CAU: | AX43: =Eventograma_e_Quantitativos!$P$44 -> 0 | BC43: CREA / CAU: | BD43: =Eventograma_e_Quantitativos!$P$44 -> 0

Sheet Cronograma
B1: =OFFSET(B1,-1,0)+1 -> #REF! | C1: =IF($B1<=numEventos,INDEX(Eventos,B1,2),"") -> #REF!
D20: PLE - Planilha de Levantamento de Eventos Cronograma | AY20: Grau de Sigilo #PUBLICO | BC20: =Cronograma.MesesQuadro -> 12
E30: =IF(Eventograma_e_Quantitativos!N15<>"",Eventograma_e_Quantitativos!N15,"") -> Rua Oficial de Justiça Vicente Gregório Antão | F30: =IF(Eventograma_e_Quantitativos!O15<>"",Eventograma_e_Quantitativos!O15,"") -> Rua Francisca Garrido de Sousa | G30: =IF(Eventograma_e_Quantitativos!P15<>"",Eventograma_e_Quantitativos!P15,"") -> Rua Francisco Batista Silva | H30: =IF(Eventograma_e_Quantitativos!Q15<>"",Eventograma_e_Quantitativos!Q15,"") -> Rua Bartolomeu Buriti | I30: =IF(Eventograma_e_Quantitativos!R15<>"",Eventograma_e_Quantitativos!R15,"") -> Rua Maria Farias de Assis | J30: =IF(Eventograma_e_Quantitativos!S15<>"",Eventograma_e_Quantitativos!S15,"") -> Rua Roberto Wilson Moura | K30: =IF(Eventograma_e_Quantitativos!T15<>"",Eventograma_e_Quantitativos!T15,"") -> Rua Cícero Eufrásio da Silva | L30: =IF(Eventograma_e_Quantitativos!U15<>"",Eventograma_e_Quantitativos!U15,"") -> Rua Firmino da Silva Lacerda | ... BB30: =IF(Eventograma_e_Quantitativos!BK15<>"",Eventograma_e_Quantitativos!BK15,"")
B31: Nº do Evento | C31: Título dos Eventos | E31: 1 | F31: 2 | G31: 3 | H31: 4 | I31: 5 | J31: 6 | K31: 7 | L31: 8 | M31: 9 | N31: 10 | O31: 11 | P31: 12 | Q31: 13 | R31: 14 | S31: 15 | T31: 16 | U31: 17 | V31: 18 | W31: 19 | X31: 20 | Y31: 21 | Z31: 22 | AA31: 23 | AB31: 24 | AC31: 25 | AD31: 26 | AE31: 27 | AF31: 28 | AG31: 29 | AH31: 30 | AI31: 31 | AJ31: 32 | AK31: 33 | AL31: 34 | AM31: 35 | AN31: 36 | AO31: 37 | AP31: 38 | AQ31: 39 | AR31: 40 | AS31: 41 | AT31: 42 | AU31: 43 | AV31: 44 | AW31: 45 | AX31: 46 | AY31: 47 | AZ31: 48 | BA31: 49 | BB31: 50
E32: Informe abaixo o NÚMERO DO PERÍODO em que os eventos serão concluídos (medição por eventos)
B34: =OFFSET(B34,-1,0)+1 -> 1 | C34: =IF($B34<=numEventos,INDEX(Eventos,B34,2),"") -> Administração Local | E34: A administração local será proporcional a execução dos demais eventos, independente de frentes de obra.
B35: =OFFSET(B35,-1,0)+1 -> 2 | C35: =IF($B35<=numEventos,INDEX(Eventos,B35,2),"") -> PAVIMENTAÇÃO | E35: 1 | F35: 2 | G35: 2 | H35: 3 | I35: 6 | J35: 5 | K35: 4 | L35: 6
B36: =OFFSET(B36,-1,0)+1 -> 3 | C36: =IF($B36<=numEventos,INDEX(Eventos,B36,2),"") -> CALÇADAS E RAMPAS | E36: 1 | F36: 2 | G36: 2 | H36: 3 | I36: 6 | J36: 5 | K36: 4 | L36: 6
B37: =OFFSET(B37,-1,0)+1 -> 4 | C37: =IF($B37<=numEventos,INDEX(Eventos,B37,2),"") -> SINALIZAÇÃO E SERVIÇOS FINAIS | E37: 4 | F37: 4 | G37: 4 | H37: 4 | I37: 6 | J37: 6 | K37: 4 | L37: 6
B39: Cronograma | G39: =(ROW($G39)-ROW($G$39))/6*12+1 -> 1 | K39: =G39+1 -> 2 | O39: =K39+1 -> 3 | S39: =O39+1 -> 4 | W39: =S39+1 -> 5 | AA39: =W39+1 -> 6 | AE39: =AA39+1 -> 7 | AI39: =AE39+1 -> 8 | AM39: =AI39+1 -> 9 | AQ39: =AM39+1 -> 10 | AU39: =AQ39+1 -> 11 | AY39: =AU39+1 -> 12
B40: Parcela | E40: % | G40: =IF(TotalEventos=0,0,G41/TotalEventos) -> 0.19732785 | K40: =IF(TotalEventos=0,0,K41/TotalEventos) -> 0.21371811 | O40: =IF(TotalEventos=0,0,O41/TotalEventos) -> 0.1915036 | S40: =IF(TotalEventos=0,0,S41/TotalEventos) -> 0.11277542 | W40: =IF(TotalEventos=0,0,W41/TotalEventos) -> 0.13392979 | AA40: =IF(TotalEventos=0,0,AA41/TotalEventos) -> 0.15074523 | AE40: =IF(TotalEventos=0,0,AE41/TotalEventos) -> 0 | AI40: =IF(TotalEventos=0,0,AI41/TotalEventos) -> 0 | AM40: =IF(TotalEventos=0,0,AM41/TotalEventos) -> 0 | AQ40: =IF(TotalEventos=0,0,AQ41/TotalEventos) -> 0 | AU40: =IF(TotalEventos=0,0,AU41/TotalEventos) -> 0 | AY40: =IF(TotalEventos=0,0,AY41/TotalEventos) -> 0
E41: R$ | G41: =SUMIF(OFFSET($E$34:$BB$34,1,0,numEventos-1),G39,OFFSET(ValoresPorEvento,1,0,numEventos-1))*(1+INDEX(TotalPorEvento,1,0)/(TotalEventos-INDEX(TotalPorEvento,1,0))) -> 157462.14 | K41: =SUMIF(OFFSET($E$34:$BB$34,1,0,numEventos-1),K39,OFFSET(ValoresPorEvento,1,0,numEventos-1))*(1+INDEX(TotalPorEvento,1,0)/(TotalEventos-INDEX(TotalPorEvento,1,0))) -> 170541.11 | O41: =SUMIF(OFFSET($E$34:$BB$34,1,0,numEventos-1),O39,OFFSET(ValoresPorEvento,1,0,numEventos-1))*(1+INDEX(TotalPorEvento,1,0)/(TotalEventos-INDEX(TotalPorEvento,1,0))) -> 152814.55 | S41: =SUMIF(OFFSET($E$34:$BB$34,1,0,numEventos-1),S39,OFFSET(ValoresPorEvento,1,0,numEventos-1))*(1+INDEX(TotalPorEvento,1,0)/(TotalEventos-INDEX(TotalPorEvento,1,0))) -> 89991.652 | W41: =SUMIF(OFFSET($E$34:$BB$34,1,0,numEventos-1),W39,OFFSET(ValoresPorEvento,1,0,numEventos-1))*(1+INDEX(TotalPorEvento,1,0)/(TotalEventos-INDEX(TotalPorEvento,1,0))) -> 106872.25 | AA41: =SUMIF(OFFSET($E$34:$BB$34,1,0,numEventos-1),AA39,OFFSET(ValoresPorEvento,1,0,numEventos-1))*(1+INDEX(TotalPorEvento,1,0)/(TotalEventos-INDEX(TotalPorEvento,1,0))) -> 120290.51 | AE41: =SUMIF(OFFSET($E$34:$BB$34,1,0,numEventos-1),AE39,OFFSET(ValoresPorEvento,1,0,numEventos-1))*(1+INDEX(TotalPorEvento,1,0)/(TotalEventos-INDEX(TotalPorEvento,1,0))) -> 0 | AI41: =SUMIF(OFFSET($E$34:$BB$34,1,0,numEventos-1),AI39,OFFSET(ValoresPorEvento,1,0,numEventos-1))*(1+INDEX(TotalPorEvento,1,0)/(TotalEventos-INDEX(TotalPorEvento,1,0))) -> 0 | AM41: =SUMIF(OFFSET($E$34:$BB$34,1,0,numEventos-1),AM39,OFFSET(ValoresPorEvento,1,0,numEventos-1))*(1+INDEX(TotalPorEvento,1,0)/(TotalEventos-INDEX(TotalPorEvento,1,0))) -> 0 | AQ41: =SUMIF(OFFSET($E$34:$BB$34,1,0,numEventos-1),AQ39,OFFSET(ValoresPorEvento,1,0,numEventos-1))*(1+INDEX(TotalPorEvento,1,0)/(TotalEventos-INDEX(TotalPorEvento,1,0))) -> 0 | AU41: =SUMIF(OFFSET($E$34:$BB$34,1,0,numEventos-1),AU39,OFFSET(ValoresPorEvento,1,0,numEventos-1))*(1+INDEX(TotalPorEvento,1,0)/(TotalEventos-INDEX(TotalPorEvento,1,0))) -> 0 | AY41: =SUMIF(OFFSET($E$34:$BB$34,1,0,numEventos-1),AY39,OFFSET(ValoresPorEvento,1,0,numEventos-1))*(1+INDEX(TotalPorEvento,1,0)/(TotalEventos-INDEX(TotalPorEvento,1,0))) -> 0
B42: Acumulado | E42: % | G42: =IF(TotalEventos=0,0,G43/TotalEventos) -> 0.19732785 | K42: =IF(TotalEventos=0,0,K43/TotalEventos) -> 0.41104596 | O42: =IF(TotalEventos=0,0,O43/TotalEventos) -> 0.60254956 | S42: =IF(TotalEventos=0,0,S43/TotalEventos) -> 0.71532498 | W42: =IF(TotalEventos=0,0,W43/TotalEventos) -> 0.84925477 | AA42: =IF(TotalEventos=0,0,AA43/TotalEventos) -> 1 | AE42: =IF(TotalEventos=0,0,AE43/TotalEventos) -> 1 | AI42: =IF(TotalEventos=0,0,AI43/TotalEventos) -> 1 | AM42: =IF(TotalEventos=0,0,AM43/TotalEventos) -> 1 | AQ42: =IF(TotalEventos=0,0,AQ43/TotalEventos) -> 1 | AU42: =IF(TotalEventos=0,0,AU43/TotalEventos) -> 1 | AY42: =IF(TotalEventos=0,0,AY43/TotalEventos) -> 1
E43: R$ | G43: =SUMIF(OFFSET($E$34:$BB$34,1,0,numEventos-1),"<="&G39,OFFSET(ValoresPorEvento,1,0,numEventos-1))*(1+INDEX(TotalPorEvento,1,0)/(TotalEventos-INDEX(TotalPorEvento,1,0))) -> 157462.14 | K43: =K41+G43 -> 328003.25 | O43: =O41+K43 -> 480817.8 | S43: =S41+O43 -> 570809.46 | W43: =W41+S43 -> 677681.7 | AA43: =AA41+W43 -> 797972.21 | AE43: =AE41+AA43 -> 797972.21 | AI43: =AI41+AE43 -> 797972.21 | AM43: =AM41+AI43 -> 797972.21 | AQ43: =AQ41+AM43 -> 797972.21 | AU43: =AU41+AQ43 -> 797972.21 | AY43: =AY41+AU43 -> 797972.21
B47: =Import.Município&", "&TEXT(hoje,"dd")&" de "&TEXT(hoje,"mmmm")&" de "&TEXT(hoje,"aaaa") -> COREMAS/PB, 31 de julho de 2023
B48: Local e Data | AQ48: Responsável Técnico: | AR48: =respPLE -> 0
AQ49: CREA / CAU: | AR49: =creaPLE -> 0

Sheet PLE
B1: =OFFSET(B1,-1,0)+1 -> #REF! | C1: =IF(B1<=numEventos,INDEX(Eventos,B1,2),"") -> #REF!
D20: PLE - Planilha de Levantamento de Eventos Planilha de Levantamento de Eventos | AY20: Grau de Sigilo #PUBLICO | BC20: =COUNTA(OFFSET(Medições,0,0,,2))/3*12 -> 12
Z28: % Realizado Acum.: | AA28: =OFFSET(G44,TRUNC((mediçao-G41)/12,0)*8,(mediçao-OFFSET(G41,TRUNC((mediçao-G41)/12,0)*8,0))*4) -> 0 | AH28: Período: | AI28: =IF(OFFSET(G40,TRUNC((mediçao-G41)/12,0)*8,(mediçao-OFFSET(G40,1+TRUNC((mediçao-G41)/12,0)*8,0))*4)="","DIGITE A DATA DA MEDIÇÃO",TEXT(IF(mediçao=G41,dataInicioObra,1+OFFSET(G40,TRUNC((mediçao-G41)/12,0)*8,(mediçao-1-OFFSET(G40,1+TRUNC((mediçao-G41)/12,0)*8,0))*4)),"dd/mm/aaaa")&" a "&TEXT(OFFSET(G40,TRUNC((mediçao-G41)/12,0)*8,(mediçao-OFFSET(G40,1+TRUNC((mediçao-G41)/12,0)*8,0))*4),"dd/mm/aaaa")) -> DIGITE A DATA DA MEDIÇÃO | AW28: Medição: | AX28: 1
BA29: =mediçao -> 1 | BB29: =CONCATENATE(mediçao,".") -> 1.
E30: =IF(Eventograma_e_Quantitativos!N15<>"",Eventograma_e_Quantitativos!N15,"") -> Rua Oficial de Justiça Vicente Gregório Antão | F30: =IF(Eventograma_e_Quantitativos!O15<>"",Eventograma_e_Quantitativos!O15,"") -> Rua Francisca Garrido de Sousa | G30: =IF(Eventograma_e_Quantitativos!P15<>"",Eventograma_e_Quantitativos!P15,"") -> Rua Francisco Batista Silva | H30: =IF(Eventograma_e_Quantitativos!Q15<>"",Eventograma_e_Quantitativos!Q15,"") -> Rua Bartolomeu Buriti | I30: =IF(Eventograma_e_Quantitativos!R15<>"",Eventograma_e_Quantitativos!R15,"") -> Rua Maria Farias de Assis | J30: =IF(Eventograma_e_Quantitativos!S15<>"",Eventograma_e_Quantitativos!S15,"") -> Rua Roberto Wilson Moura | K30: =IF(Eventograma_e_Quantitativos!T15<>"",Eventograma_e_Quantitativos!T15,"") -> Rua Cícero Eufrásio da Silva | L30: =IF(Eventograma_e_Quantitativos!U15<>"",Eventograma_e_Quantitativos!U15,"") -> Rua Firmino da Silva Lacerda | ... BB30: =IF(Eventograma_e_Quantitativos!BK15<>"",Eventograma_e_Quantitativos!BK15,"")
B31: Nº do Evento | C31: Título dos Eventos | E31: 1 | F31: 2 | G31: 3 | H31: 4 | I31: 5 | J31: 6 | K31: 7 | L31: 8 | M31: 9 | N31: 10 | O31: 11 | P31: 12 | Q31: 13 | R31: 14 | S31: 15 | T31: 16 | U31: 17 | V31: 18 | W31: 19 | X31: 20 | Y31: 21 | Z31: 22 | AA31: 23 | AB31: 24 | AC31: 25 | AD31: 26 | AE31: 27 | AF31: 28 | AG31: 29 | AH31: 30 | AI31: 31 | AJ31: 32 | AK31: 33 | AL31: 34 | AM31: 35 | AN31: 36 | AO31: 37 | AP31: 38 | AQ31: 39 | AR31: 40 | AS31: 41 | AT31: 42 | AU31: 43 | AV31: 44 | AW31: 45 | AX31: 46 | AY31: 47 | AZ31: 48 | BA31: 49 | BB31: 50
E32: Informe abaixo o NÚMERO DA MEDIÇÃO em que os eventos foram concluídos (medição por eventos)
B34: =OFFSET(B34,-1,0)+1 -> 1 | C34: =IF(B34<=numEventos,INDEX(Eventos,B34,2),"") -> Administração Local | E34: A administração local será proporcional a execução dos demais eventos, indenpendente de frentes de obra.
B35: =OFFSET(B35,-1,0)+1 -> 2 | C35: =IF(B35<=numEventos,INDEX(Eventos,B35,2),"") -> PAVIMENTAÇÃO
B36: =OFFSET(B36,-1,0)+1 -> 3 | C36: =IF(B36<=numEventos,INDEX(Eventos,B36,2),"") -> CALÇADAS E RAMPAS
B37: =OFFSET(B37,-1,0)+1 -> 4 | C37: =IF(B37<=numEventos,INDEX(Eventos,B37,2),"") -> SINALIZAÇÃO E SERVIÇOS FINAIS
G39: Datas das medições
B41: Medições | G41: =(ROW($G41)-ROW($G$41))/8*12+1 -> 1 | K41: =G41+1 -> 2 | O41: =K41+1 -> 3 | S41: =O41+1 -> 4 | W41: =S41+1 -> 5 | AA41: =W41+1 -> 6 | AE41: =AA41+1 -> 7 | AI41: =AE41+1 -> 8 | AM41: =AI41+1 -> 9 | AQ41: =AM41+1 -> 10 | AU41: =AQ41+1 -> 11 | AY41: =AU41+1 -> 12
B42: Período | E42: % | G42: =IF(TotalEventos=0,0,G43/TotalEventos) -> 0 | K42: =IF(TotalEventos=0,0,K43/TotalEventos) -> 0 | O42: =IF(TotalEventos=0,0,O43/TotalEventos) -> 0 | S42: =IF(TotalEventos=0,0,S43/TotalEventos) -> 0 | W42: =IF(TotalEventos=0,0,W43/TotalEventos) -> 0 | AA42: =IF(TotalEventos=0,0,AA43/TotalEventos) -> 0 | AE42: =IF(TotalEventos=0,0,AE43/TotalEventos) -> 0 | AI42: =IF(TotalEventos=0,0,AI43/TotalEventos) -> 0 | AM42: =IF(TotalEventos=0,0,AM43/TotalEventos) -> 0 | AQ42: =IF(TotalEventos=0,0,AQ43/TotalEventos) -> 0 | AU42: =IF(TotalEventos=0,0,AU43/TotalEventos) -> 0 | AY42: =IF(TotalEventos=0,0,AY43/TotalEventos) -> 0
E43: R$ | G43: =SUMIF(OFFSET(Import.PLE,1,0,numEventos-1),G41,OFFSET(ValoresPorEvento,1,0,numEventos-1))*(1+INDEX(TotalPorEvento,1,0)/(TotalEventos-INDEX(TotalPorEvento,1,0))) -> 0 | K43: =SUMIF(OFFSET(Import.PLE,1,0,numEventos-1),K41,OFFSET(ValoresPorEvento,1,0,numEventos-1))*(1+INDEX(TotalPorEvento,1,0)/(TotalEventos-INDEX(TotalPorEvento,1,0))) -> 0 | O43: =SUMIF(OFFSET(Import.PLE,1,0,numEventos-1),O41,OFFSET(ValoresPorEvento,1,0,numEventos-1))*(1+INDEX(TotalPorEvento,1,0)/(TotalEventos-INDEX(TotalPorEvento,1,0))) -> 0 | S43: =SUMIF(OFFSET(Import.PLE,1,0,numEventos-1),S41,OFFSET(ValoresPorEvento,1,0,numEventos-1))*(1+INDEX(TotalPorEvento,1,0)/(TotalEventos-INDEX(TotalPorEvento,1,0))) -> 0 | W43: =SUMIF(OFFSET(Import.PLE,1,0,numEventos-1),W41,OFFSET(ValoresPorEvento,1,0,numEventos-1))*(1+INDEX(TotalPorEvento,1,0)/(TotalEventos-INDEX(TotalPorEvento,1,0))) -> 0 | AA43: =SUMIF(OFFSET(Import.PLE,1,0,numEventos-1),AA41,OFFSET(ValoresPorEvento,1,0,numEventos-1))*(1+INDEX(TotalPorEvento,1,0)/(TotalEventos-INDEX(TotalPorEvento,1,0))) -> 0 | AE43: =SUMIF(OFFSET(Import.PLE,1,0,numEventos-1),AE41,OFFSET(ValoresPorEvento,1,0,numEventos-1))*(1+INDEX(TotalPorEvento,1,0)/(TotalEventos-INDEX(TotalPorEvento,1,0))) -> 0 | AI43: =SUMIF(OFFSET(Import.PLE,1,0,numEventos-1),AI41,OFFSET(ValoresPorEvento,1,0,numEventos-1))*(1+INDEX(TotalPorEvento,1,0)/(TotalEventos-INDEX(TotalPorEvento,1,0))) -> 0 | AM43: =SUMIF(OFFSET(Import.PLE,1,0,numEventos-1),AM41,OFFSET(ValoresPorEvento,1,0,numEventos-1))*(1+INDEX(TotalPorEvento,1,0)/(TotalEventos-INDEX(TotalPorEvento,1,0))) -> 0 | AQ43: =SUMIF(OFFSET(Import.PLE,1,0,numEventos-1),AQ41,OFFSET(ValoresPorEvento,1,0,numEventos-1))*(1+INDEX(TotalPorEvento,1,0)/(TotalEventos-INDEX(TotalPorEvento,1,0))) -> 0 | AU43: =SUMIF(OFFSET(Import.PLE,1,0,numEventos-1),AU41,OFFSET(ValoresPorEvento,1,0,numEventos-1))*(1+INDEX(TotalPorEvento,1,0)/(TotalEventos-INDEX(TotalPorEvento,1,0))) -> 0 | AY43: =SUMIF(OFFSET(Import.PLE,1,0,numEventos-1),AY41,OFFSET(ValoresPorEvento,1,0,numEventos-1))*(1+INDEX(TotalPorEvento,1,0)/(TotalEventos-INDEX(TotalPorEvento,1,0))) -> 0
B44: Acumulado | E44: % | G44: =IF(TotalEventos=0,0,G45/TotalEventos) -> 0 | K44: =IF(TotalEventos=0,0,K45/TotalEventos) -> 0 | O44: =IF(TotalEventos=0,0,O45/TotalEventos) -> 0 | S44: =IF(TotalEventos=0,0,S45/TotalEventos) -> 0 | W44: =IF(TotalEventos=0,0,W45/TotalEventos) -> 0 | AA44: =IF(TotalEventos=0,0,AA45/TotalEventos) -> 0 | AE44: =IF(TotalEventos=0,0,AE45/TotalEventos) -> 0 | AI44: =IF(TotalEventos=0,0,AI45/TotalEventos) -> 0 | AM44: =IF(TotalEventos=0,0,AM45/TotalEventos) -> 0 | AQ44: =IF(TotalEventos=0,0,AQ45/TotalEventos) -> 0 | AU44: =IF(TotalEventos=0,0,AU45/TotalEventos) -> 0 | AY44: =IF(TotalEventos=0,0,AY45/TotalEventos) -> 0
E45: R$ | G45: =SUMIF(OFFSET(Import.PLE,1,0,numEventos-1),"<="&G41,OFFSET(ValoresPorEvento,1,0,numEventos-1))*(1+INDEX(TotalPorEvento,1,0)/(TotalEventos-INDEX(TotalPorEvento,1,0))) -> 0 | K45: =K43+G45 -> 0 | O45: =O43+K45 -> 0 | S45: =S43+O45 -> 0 | W45: =W43+S45 -> 0 | AA45: =AA43+W45 -> 0 | AE45: =AE43+AA45 -> 0 | AI45: =AI43+AE45 -> 0 | AM45: =AM43+AI45 -> 0 | AQ45: =AQ43+AM45 -> 0 | AU45: =AU43+AQ45 -> 0 | AY45: =AY43+AU45 -> 0
B48: =Import.Município&", "&TEXT(hoje,"dd")&" de "&TEXT(hoje,"mmmm")&" de "&TEXT(hoje,"aaaa") -> COREMAS/PB, 31 de julho de 2023
B49: Local e Data | AR49: Resp. Tec. Fiscal.: | AS49: =respFiscal -> FERNANDO
AR50: CREA / CAU: | AS50: =creaFiscal -> 0
AR51: ART: | AS51: =artFiscal -> 0

Sheet Resumo_de_Acompanhamento
B1: =OFFSET(B1,-1,0)+1 -> #REF! | C1: =IF(OR(D1="",D1<dataInicioObra),"",COUNTIF(CronoPrev!$C$14:$C$25,"<"&(D1-7))+1) -> 1 | D1: =OFFSET(PLE!$G$40,TRUNC((ROW($B1)-ROW($B$14))/12,0)*8,MOD(ROW($B1)-ROW($B$14),12)*4) -> 0 | E1: =OFFSET(PLE!$G$43,TRUNC((ROW($B1)-ROW($B$14))/12,0)*8,MOD(ROW(B1)-ROW($B$14),12)*4) -> 0 | F1: =E1+OFFSET(F1,-1,0) -> #REF! | G1: =OFFSET(PLE!$G$42,TRUNC((ROW($B1)-ROW($B$14))/12,0)*8,MOD(ROW(B1)-ROW($B$14),12)*4) -> 0 | H1: =G1+OFFSET(H1,-1,0) -> #REF! | I1: =IF(C1="","",IF(C1>Cronograma.NumPeríodos,1,VLOOKUP(C1,CronoPrev!$B$14:$G$25,6,FALSE))) -> 0.19732785 | J1: =D1-dataInicioObra -> 0 | K1: =INDEX(OFFSET(CronoPrev,0,3,,1),COUNTIF(OFFSET(CronoPrev,0,5,,1),"<"&H1))+ROUND((H1-IF(""=(INDEX(OFFSET(CronoPrev,0,5,,1),COUNTIF(OFFSET(CronoPrev,0,5,,1),"<"&H1))),0,INDEX(OFFSET(CronoPrev,0,5,,1),COUNTIF(OFFSET(CronoPrev,0,5,,1),"<"&H1))))/INDEX(OFFSET(CronoPrev,0,4,,1),COUNTIF(OFFSET(CronoPrev,0,5,,1),"<"&H1)+1)*INDEX(OFFSET(CronoPrev,0,2,,1),COUNTIF(OFFSET(CronoPrev,0,5,,1),"<"&H1)+1),0) -> #VALUE! | L1: =IF(C1="","",K1-J1) -> #VALUE! | M1: =IF(C1="","",L1/SUM(OFFSET(CronoPrev!$D$14,0,0,Cronograma.NumPeríodos))) -> #VALUE!
E2: PLE - Planilha de Levantamento de Eventos Resumo de Acompanhamento | P2: Grau de Sigilo #PUBLICO
B10: ACOMPANHAMENTO | M10: ="Valor de Investimento: R$ "&TEXT(TotalEventos,"#.###,00") -> Valor de Investimento: R$ 797.972,21 | O10: METAS
B11: N.º da Medição | C11: N.º do Período | D11: Data da medição | E11: Valores Medidos (R$) | G11: % Global | I11: % Global Previsto | J11: Prazo Decorrido (dias) | K11: Equivalente dias-obra | L11: Dias Atraso (-) Adiant. (+) | M11: % Atraso / Adiant. | O11: # Meta | P11: Valores Medidos Acum. (R$)
E12: No Período | F12: Acumulado | G12: No Período | H12: Acumulado
D13: -
B14: =OFFSET(B14,-1,0)+1 -> 1 | C14: =IF(OR(D14="",D14<dataInicioObra),"",COUNTIF(CronoPrev!$C$14:$C$25,"<"&(D14-7))+1) -> 1 | D14: =OFFSET(PLE!$G$40,TRUNC((ROW($B14)-ROW($B$14))/12,0)*8,MOD(ROW($B14)-ROW($B$14),12)*4) -> 0 | E14: =OFFSET(PLE!$G$43,TRUNC((ROW($B14)-ROW($B$14))/12,0)*8,MOD(ROW(B14)-ROW($B$14),12)*4) -> 0 | F14: =E14+OFFSET(F14,-1,0) -> 0 | G14: =OFFSET(PLE!$G$42,TRUNC((ROW($B14)-ROW($B$14))/12,0)*8,MOD(ROW(B14)-ROW($B$14),12)*4) -> 0 | H14: =G14+OFFSET(H14,-1,0) -> 0 | I14: =IF(C14="","",IF(C14>Cronograma.NumPeríodos,1,VLOOKUP(C14,CronoPrev!$B$14:$G$25,6,FALSE))) -> 0.19732785 | J14: =D14-dataInicioObra -> 0 | K14: =INDEX(OFFSET(CronoPrev,0,3,,1),COUNTIF(OFFSET(CronoPrev,0,5,,1),"<"&H14))+ROUND((H14-IF(""=(INDEX(OFFSET(CronoPrev,0,5,,1),COUNTIF(OFFSET(CronoPrev,0,5,,1),"<"&H14))),0,INDEX(OFFSET(CronoPrev,0,5,,1),COUNTIF(OFFSET(CronoPrev,0,5,,1),"<"&H14))))/INDEX(OFFSET(CronoPrev,0,4,,1),COUNTIF(OFFSET(CronoPrev,0,5,,1),"<"&H14)+1)*INDEX(OFFSET(CronoPrev,0,2,,1),COUNTIF(OFFSET(CronoPrev,0,5,,1),"<"&H14)+1),0) -> 0 | L14: =IF(C14="","",K14-J14) -> 0 | M14: =IF(C14="","",L14/SUM(OFFSET(CronoPrev!$D$14,0,0,Cronograma.NumPeríodos))) -> 0 | O14: 1 | P14: =SUMIF(OFFSET(Eventograma_e_Quantitativos!$DK$17,1,0):OFFSET(Eventograma_e_Quantitativos!$DK$37,-1,0),Resumo_de_Acompanhamento!$O14,OFFSET(Eventograma_e_Quantitativos!$DL$17,1,0):OFFSET(Eventograma_e_Quantitativos!$DL$37,-1,0)) -> 0
B15: =OFFSET(B15,-1,0)+1 -> 2 | C15: =IF(OR(D15="",D15<dataInicioObra),"",COUNTIF(CronoPrev!$C$14:$C$25,"<"&(D15-7))+1) -> 1 | D15: =OFFSET(PLE!$G$40,TRUNC((ROW($B15)-ROW($B$14))/12,0)*8,MOD(ROW($B15)-ROW($B$14),12)*4) -> 0 | E15: =OFFSET(PLE!$G$43,TRUNC((ROW($B15)-ROW($B$14))/12,0)*8,MOD(ROW(B15)-ROW($B$14),12)*4) -> 0 | F15: =E15+OFFSET(F15,-1,0) -> 0 | G15: =OFFSET(PLE!$G$42,TRUNC((ROW($B15)-ROW($B$14))/12,0)*8,MOD(ROW(B15)-ROW($B$14),12)*4) -> 0 | H15: =G15+OFFSET(H15,-1,0) -> 0 | I15: =IF(C15="","",IF(C15>Cronograma.NumPeríodos,1,VLOOKUP(C15,CronoPrev!$B$14:$G$25,6,FALSE))) -> 0.19732785 | J15: =D15-dataInicioObra -> 0 | K15: =INDEX(OFFSET(CronoPrev,0,3,,1),COUNTIF(OFFSET(CronoPrev,0,5,,1),"<"&H15))+ROUND((H15-IF(""=(INDEX(OFFSET(CronoPrev,0,5,,1),COUNTIF(OFFSET(CronoPrev,0,5,,1),"<"&H15))),0,INDEX(OFFSET(CronoPrev,0,5,,1),COUNTIF(OFFSET(CronoPrev,0,5,,1),"<"&H15))))/INDEX(OFFSET(CronoPrev,0,4,,1),COUNTIF(OFFSET(CronoPrev,0,5,,1),"<"&H15)+1)*INDEX(OFFSET(CronoPrev,0,2,,1),COUNTIF(OFFSET(CronoPrev,0,5,,1),"<"&H15)+1),0) -> -34 | L15: =IF(C15="","",K15-J15) -> -34 | M15: =IF(C15="","",L15/SUM(OFFSET(CronoPrev!$D$14,0,0,Cronograma.NumPeríodos))) -> -0.15962441 | O15: 2 | P15: =SUMIF(OFFSET(Eventograma_e_Quantitativos!$DK$17,1,0):OFFSET(Eventograma_e_Quantitativos!$DK$37,-1,0),Resumo_de_Acompanhamento!$O15,OFFSET(Eventograma_e_Quantitativos!$DL$17,1,0):OFFSET(Eventograma_e_Quantitativos!$DL$37,-1,0)) -> 0
B16: =OFFSET(B16,-1,0)+1 -> 3 | C16: =IF(OR(D16="",D16<dataInicioObra),"",COUNTIF(CronoPrev!$C$14:$C$25,"<"&(D16-7))+1) -> 1 | D16: =OFFSET(PLE!$G$40,TRUNC((ROW($B16)-ROW($B$14))/12,0)*8,MOD(ROW($B16)-ROW($B$14),12)*4) -> 0 | E16: =OFFSET(PLE!$G$43,TRUNC((ROW($B16)-ROW($B$14))/12,0)*8,MOD(ROW(B16)-ROW($B$14),12)*4) -> 0 | F16: =E16+OFFSET(F16,-1,0) -> 0 | G16: =OFFSET(PLE!$G$42,TRUNC((ROW($B16)-ROW($B$14))/12,0)*8,MOD(ROW(B16)-ROW($B$14),12)*4) -> 0 | H16: =G16+OFFSET(H16,-1,0) -> 0 | I16: =IF(C16="","",IF(C16>Cronograma.NumPeríodos,1,VLOOKUP(C16,CronoPrev!$B$14:$G$25,6,FALSE))) -> 0.19732785 | J16: =D16-dataInicioObra -> 0 | K16: =INDEX(OFFSET(CronoPrev,0,3,,1),COUNTIF(OFFSET(CronoPrev,0,5,,1),"<"&H16))+ROUND((H16-IF(""=(INDEX(OFFSET(CronoPrev,0,5,,1),COUNTIF(OFFSET(CronoPrev,0,5,,1),"<"&H16))),0,INDEX(OFFSET(CronoPrev,0,5,,1),COUNTIF(OFFSET(CronoPrev,0,5,,1),"<"&H16))))/INDEX(OFFSET(CronoPrev,0,4,,1),COUNTIF(OFFSET(CronoPrev,0,5,,1),"<"&H16)+1)*INDEX(OFFSET(CronoPrev,0,2,,1),COUNTIF(OFFSET(CronoPrev,0,5,,1),"<"&H16)+1),0) -> -62 | L16: =IF(C16="","",K16-J16) -> -62 | M16: =IF(C16="","",L16/SUM(OFFSET(CronoPrev!$D$14,0,0,Cronograma.NumPeríodos))) -> -0.29107981 | O16: 3 | P16: =SUMIF(OFFSET(Eventograma_e_Quantitativos!$DK$17,1,0):OFFSET(Eventograma_e_Quantitativos!$DK$37,-1,0),Resumo_de_Acompanhamento!$O16,OFFSET(Eventograma_e_Quantitativos!$DL$17,1,0):OFFSET(Eventograma_e_Quantitativos!$DL$37,-1,0)) -> 0
B17: =OFFSET(B17,-1,0)+1 -> 4 | C17: =IF(OR(D17="",D17<dataInicioObra),"",COUNTIF(CronoPrev!$C$14:$C$25,"<"&(D17-7))+1) -> 1 | D17: =OFFSET(PLE!$G$40,TRUNC((ROW($B17)-ROW($B$14))/12,0)*8,MOD(ROW($B17)-ROW($B$14),12)*4) -> 0 | E17: =OFFSET(PLE!$G$43,TRUNC((ROW($B17)-ROW($B$14))/12,0)*8,MOD(ROW(B17)-ROW($B$14),12)*4) -> 0 | F17: =E17+OFFSET(F17,-1,0) -> 0 | G17: =OFFSET(PLE!$G$42,TRUNC((ROW($B17)-ROW($B$14))/12,0)*8,MOD(ROW(B17)-ROW($B$14),12)*4) -> 0 | H17: =G17+OFFSET(H17,-1,0) -> 0 | I17: =IF(C17="","",IF(C17>Cronograma.NumPeríodos,1,VLOOKUP(C17,CronoPrev!$B$14:$G$25,6,FALSE))) -> 0.19732785 | J17: =D17-dataInicioObra -> 0 | K17: =INDEX(OFFSET(CronoPrev,0,3,,1),COUNTIF(OFFSET(CronoPrev,0,5,,1),"<"&H17))+ROUND((H17-IF(""=(INDEX(OFFSET(CronoPrev,0,5,,1),COUNTIF(OFFSET(CronoPrev,0,5,,1),"<"&H17))),0,INDEX(OFFSET(CronoPrev,0,5,,1),COUNTIF(OFFSET(CronoPrev,0,5,,1),"<"&H17))))/INDEX(OFFSET(CronoPrev,0,4,,1),COUNTIF(OFFSET(CronoPrev,0,5,,1),"<"&H17)+1)*INDEX(OFFSET(CronoPrev,0,2,,1),COUNTIF(OFFSET(CronoPrev,0,5,,1),"<"&H17)+1),0) -> -66 | L17: =IF(C17="","",K17-J17) -> -66 | M17: =IF(C17="","",L17/SUM(OFFSET(CronoPrev!$D$14,0,0,Cronograma.NumPeríodos))) -> -0.30985915 | O17: 4 | P17: =SUMIF(OFFSET(Eventograma_e_Quantitativos!$DK$17,1,0):OFFSET(Eventograma_e_Quantitativos!$DK$37,-1,0),Resumo_de_Acompanhamento!$O17,OFFSET(Eventograma_e_Quantitativos!$DL$17,1,0):OFFSET(Eventograma_e_Quantitativos!$DL$37,-1,0)) -> 0
B18: =OFFSET(B18,-1,0)+1 -> 5 | C18: =IF(OR(D18="",D18<dataInicioObra),"",COUNTIF(CronoPrev!$C$14:$C$25,"<"&(D18-7))+1) -> 1 | D18: =OFFSET(PLE!$G$40,TRUNC((ROW($B18)-ROW($B$14))/12,0)*8,MOD(ROW($B18)-ROW($B$14),12)*4) -> 0 | E18: =OFFSET(PLE!$G$43,TRUNC((ROW($B18)-ROW($B$14))/12,0)*8,MOD(ROW(B18)-ROW($B$14),12)*4) -> 0 | F18: =E18+OFFSET(F18,-1,0) -> 0 | G18: =OFFSET(PLE!$G$42,TRUNC((ROW($B18)-ROW($B$14))/12,0)*8,MOD(ROW(B18)-ROW($B$14),12)*4) -> 0 | H18: =G18+OFFSET(H18,-1,0) -> 0 | I18: =IF(C18="","",IF(C18>Cronograma.NumPeríodos,1,VLOOKUP(C18,CronoPrev!$B$14:$G$25,6,FALSE))) -> 0.19732785 | J18: =D18-dataInicioObra -> 0 | K18: =INDEX(OFFSET(CronoPrev,0,3,,1),COUNTIF(OFFSET(CronoPrev,0,5,,1),"<"&H18))+ROUND((H18-IF(""=(INDEX(OFFSET(CronoPrev,0,5,,1),COUNTIF(OFFSET(CronoPrev,0,5,,1),"<"&H18))),0,INDEX(OFFSET(CronoPrev,0,5,,1),COUNTIF(OFFSET(CronoPrev,0,5,,1),"<"&H18))))/INDEX(OFFSET(CronoPrev,0,4,,1),COUNTIF(OFFSET(CronoPrev,0,5,,1),"<"&H18)+1)*INDEX(OFFSET(CronoPrev,0,2,,1),COUNTIF(OFFSET(CronoPrev,0,5,,1),"<"&H18)+1),0) -> -76 | L18: =IF(C18="","",K18-J18) -> -76 | M18: =IF(C18="","",L18/SUM(OFFSET(CronoPrev!$D$14,0,0,Cronograma.NumPeríodos))) -> -0.35680751 | O18: 5 | P18: =SUMIF(OFFSET(Eventograma_e_Quantitativos!$DK$17,1,0):OFFSET(Eventograma_e_Quantitativos!$DK$37,-1,0),Resumo_de_Acompanhamento!$O18,OFFSET(Eventograma_e_Quantitativos!$DL$17,1,0):OFFSET(Eventograma_e_Quantitativos!$DL$37,-1,0)) -> 0
B19: =OFFSET(B19,-1,0)+1 -> 6 | C19: =IF(OR(D19="",D19<dataInicioObra),"",COUNTIF(CronoPrev!$C$14:$C$25,"<"&(D19-7))+1) -> 1 | D19: =OFFSET(PLE!$G$40,TRUNC((ROW($B19)-ROW($B$14))/12,0)*8,MOD(ROW($B19)-ROW($B$14),12)*4) -> 0 | E19: =OFFSET(PLE!$G$43,TRUNC((ROW($B19)-ROW($B$14))/12,0)*8,MOD(ROW(B19)-ROW($B$14),12)*4) -> 0 | F19: =E19+OFFSET(F19,-1,0) -> 0 | G19: =OFFSET(PLE!$G$42,TRUNC((ROW($B19)-ROW($B$14))/12,0)*8,MOD(ROW(B19)-ROW($B$14),12)*4) -> 0 | H19: =G19+OFFSET(H19,-1,0) -> 0 | I19: =IF(C19="","",IF(C19>Cronograma.NumPeríodos,1,VLOOKUP(C19,CronoPrev!$B$14:$G$25,6,FALSE))) -> 0.19732785 | J19: =D19-dataInicioObra -> 0 | K19: =INDEX(OFFSET(CronoPrev,0,3,,1),COUNTIF(OFFSET(CronoPrev,0,5,,1),"<"&H19))+ROUND((H19-IF(""=(INDEX(OFFSET(CronoPrev,0,5,,1),COUNTIF(OFFSET(CronoPrev,0,5,,1),"<"&H19))),0,INDEX(OFFSET(CronoPrev,0,5,,1),COUNTIF(OFFSET(CronoPrev,0,5,,1),"<"&H19))))/INDEX(OFFSET(CronoPrev,0,4,,1),COUNTIF(OFFSET(CronoPrev,0,5,,1),"<"&H19)+1)*INDEX(OFFSET(CronoPrev,0,2,,1),COUNTIF(OFFSET(CronoPrev,0,5,,1),"<"&H19)+1),0) -> -91 | L19: =IF(C19="","",K19-J19) -> -91 | M19: =IF(C19="","",L19/SUM(OFFSET(CronoPrev!$D$14,0,0,Cronograma.NumPeríodos))) -> -0.42723005 | O19: 6 | P19: =SUMIF(OFFSET(Eventograma_e_Quantitativos!$DK$17,1,0):OFFSET(Eventograma_e_Quantitativos!$DK$37,-1,0),Resumo_de_Acompanhamento!$O19,OFFSET(Eventograma_e_Quantitativos!$DL$17,1,0):OFFSET(Eventograma_e_Quantitativos!$DL$37,-1,0)) -> 0
B20: =OFFSET(B20,-1,0)+1 -> 7 | C20: =IF(OR(D20="",D20<dataInicioObra),"",COUNTIF(CronoPrev!$C$14:$C$25,"<"&(D20-7))+1) -> 1 | D20: =OFFSET(PLE!$G$40,TRUNC((ROW($B20)-ROW($B$14))/12,0)*8,MOD(ROW($B20)-ROW($B$14),12)*4) -> 0 | E20: =OFFSET(PLE!$G$43,TRUNC((ROW($B20)-ROW($B$14))/12,0)*8,MOD(ROW(B20)-ROW($B$14),12)*4) -> 0 | F20: =E20+OFFSET(F20,-1,0) -> 0 | G20: =OFFSET(PLE!$G$42,TRUNC((ROW($B20)-ROW($B$14))/12,0)*8,MOD(ROW(B20)-ROW($B$14),12)*4) -> 0 | H20: =G20+OFFSET(H20,-1,0) -> 0 | I20: =IF(C20="","",IF(C20>Cronograma.NumPeríodos,1,VLOOKUP(C20,CronoPrev!$B$14:$G$25,6,FALSE))) -> 0.19732785 | J20: =D20-dataInicioObra -> 0 | K20: =INDEX(OFFSET(CronoPrev,0,3,,1),COUNTIF(OFFSET(CronoPrev,0,5,,1),"<"&H20))+ROUND((H20-IF(""=(INDEX(OFFSET(CronoPrev,0,5,,1),COUNTIF(OFFSET(CronoPrev,0,5,,1),"<"&H20))),0,INDEX(OFFSET(CronoPrev,0,5,,1),COUNTIF(OFFSET(CronoPrev,0,5,,1),"<"&H20))))/INDEX(OFFSET(CronoPrev,0,4,,1),COUNTIF(OFFSET(CronoPrev,0,5,,1),"<"&H20)+1)*INDEX(OFFSET(CronoPrev,0,2,,1),COUNTIF(OFFSET(CronoPrev,0,5,,1),"<"&H20)+1),0) -> -60 | L20: =IF(C20="","",K20-J20) -> -60 | M20: =IF(C20="","",L20/SUM(OFFSET(CronoPrev!$D$14,0,0,Cronograma.NumPeríodos))) -> -0.28169014 | O20: 7 | P20: =SUMIF(OFFSET(Eventograma_e_Quantitativos!$DK$17,1,0):OFFSET(Eventograma_e_Quantitativos!$DK$37,-1,0),Resumo_de_Acompanhamento!$O20,OFFSET(Eventograma_e_Quantitativos!$DL$17,1,0):OFFSET(Eventograma_e_Quantitativos!$DL$37,-1,0)) -> 0
B21: =OFFSET(B21,-1,0)+1 -> 8 | C21: =IF(OR(D21="",D21<dataInicioObra),"",COUNTIF(CronoPrev!$C$14:$C$25,"<"&(D21-7))+1) -> 1 | D21: =OFFSET(PLE!$G$40,TRUNC((ROW($B21)-ROW($B$14))/12,0)*8,MOD(ROW($B21)-ROW($B$14),12)*4) -> 0 | E21: =OFFSET(PLE!$G$43,TRUNC((ROW($B21)-ROW($B$14))/12,0)*8,MOD(ROW(B21)-ROW($B$14),12)*4) -> 0 | F21: =E21+OFFSET(F21,-1,0) -> 0 | G21: =OFFSET(PLE!$G$42,TRUNC((ROW($B21)-ROW($B$14))/12,0)*8,MOD(ROW(B21)-ROW($B$14),12)*4) -> 0 | H21: =G21+OFFSET(H21,-1,0) -> 0 | I21: =IF(C21="","",IF(C21>Cronograma.NumPeríodos,1,VLOOKUP(C21,CronoPrev!$B$14:$G$25,6,FALSE))) -> 0.19732785 | J21: =D21-dataInicioObra -> 0 | K21: =INDEX(OFFSET(CronoPrev,0,3,,1),COUNTIF(OFFSET(CronoPrev,0,5,,1),"<"&H21))+ROUND((H21-IF(""=(INDEX(OFFSET(CronoPrev,0,5,,1),COUNTIF(OFFSET(CronoPrev,0,5,,1),"<"&H21))),0,INDEX(OFFSET(CronoPrev,0,5,,1),COUNTIF(OFFSET(CronoPrev,0,5,,1),"<"&H21))))/INDEX(OFFSET(CronoPrev,0,4,,1),COUNTIF(OFFSET(CronoPrev,0,5,,1),"<"&H21)+1)*INDEX(OFFSET(CronoPrev,0,2,,1),COUNTIF(OFFSET(CronoPrev,0,5,,1),"<"&H21)+1),0) -> -30 | L21: =IF(C21="","",K21-J21) -> -30 | M21: =IF(C21="","",L21/SUM(OFFSET(CronoPrev!$D$14,0,0,Cronograma.NumPeríodos))) -> -0.14084507 | O21: 8 | P21: =SUMIF(OFFSET(Eventograma_e_Quantitativos!$DK$17,1,0):OFFSET(Eventograma_e_Quantitativos!$DK$37,-1,0),Resumo_de_Acompanhamento!$O21,OFFSET(Eventograma_e_Quantitativos!$DL$17,1,0):OFFSET(Eventograma_e_Quantitativos!$DL$37,-1,0)) -> 0
B22: =OFFSET(B22,-1,0)+1 -> 9 | C22: =IF(OR(D22="",D22<dataInicioObra),"",COUNTIF(CronoPrev!$C$14:$C$25,"<"&(D22-7))+1) -> 1 | D22: =OFFSET(PLE!$G$40,TRUNC((ROW($B22)-ROW($B$14))/12,0)*8,MOD(ROW($B22)-ROW($B$14),12)*4) -> 0 | E22: =OFFSET(PLE!$G$43,TRUNC((ROW($B22)-ROW($B$14))/12,0)*8,MOD(ROW(B22)-ROW($B$14),12)*4) -> 0 | F22: =E22+OFFSET(F22,-1,0) -> 0 | G22: =OFFSET(PLE!$G$42,TRUNC((ROW($B22)-ROW($B$14))/12,0)*8,MOD(ROW(B22)-ROW($B$14),12)*4) -> 0 | H22: =G22+OFFSET(H22,-1,0) -> 0 | I22: =IF(C22="","",IF(C22>Cronograma.NumPeríodos,1,VLOOKUP(C22,CronoPrev!$B$14:$G$25,6,FALSE))) -> 0.19732785 | J22: =D22-dataInicioObra -> 0 | K22: =INDEX(OFFSET(CronoPrev,0,3,,1),COUNTIF(OFFSET(CronoPrev,0,5,,1),"<"&H22))+ROUND((H22-IF(""=(INDEX(OFFSET(CronoPrev,0,5,,1),COUNTIF(OFFSET(CronoPrev,0,5,,1),"<"&H22))),0,INDEX(OFFSET(CronoPrev,0,5,,1),COUNTIF(OFFSET(CronoPrev,0,5,,1),"<"&H22))))/INDEX(OFFSET(CronoPrev,0,4,,1),COUNTIF(OFFSET(CronoPrev,0,5,,1),"<"&H22)+1)*INDEX(OFFSET(CronoPrev,0,2,,1),COUNTIF(OFFSET(CronoPrev,0,5,,1),"<"&H22)+1),0) -> 1 | L22: =IF(C22="","",K22-J22) -> 1 | M22: =IF(C22="","",L22/SUM(OFFSET(CronoPrev!$D$14,0,0,Cronograma.NumPeríodos))) -> 0.0046948357 | O22: 9 | P22: =SUMIF(OFFSET(Eventograma_e_Quantitativos!$DK$17,1,0):OFFSET(Eventograma_e_Quantitativos!$DK$37,-1,0),Resumo_de_Acompanhamento!$O22,OFFSET(Eventograma_e_Quantitativos!$DL$17,1,0):OFFSET(Eventograma_e_Quantitativos!$DL$37,-1,0)) -> 0
B23: =OFFSET(B23,-1,0)+1 -> 10 | C23: =IF(OR(D23="",D23<dataInicioObra),"",COUNTIF(CronoPrev!$C$14:$C$25,"<"&(D23-7))+1) -> 1 | D23: =OFFSET(PLE!$G$40,TRUNC((ROW($B23)-ROW($B$14))/12,0)*8,MOD(ROW($B23)-ROW($B$14),12)*4) -> 0 | E23: =OFFSET(PLE!$G$43,TRUNC((ROW($B23)-ROW($B$14))/12,0)*8,MOD(ROW(B23)-ROW($B$14),12)*4) -> 0 | F23: =E23+OFFSET(F23,-1,0) -> 0 | G23: =OFFSET(PLE!$G$42,TRUNC((ROW($B23)-ROW($B$14))/12,0)*8,MOD(ROW(B23)-ROW($B$14),12)*4) -> 0 | H23: =G23+OFFSET(H23,-1,0) -> 0 | I23: =IF(C23="","",IF(C23>Cronograma.NumPeríodos,1,VLOOKUP(C23,CronoPrev!$B$14:$G$25,6,FALSE))) -> 0.19732785 | J23: =D23-dataInicioObra -> 0 | K23: =INDEX(OFFSET(CronoPrev,0,3,,1),COUNTIF(OFFSET(CronoPrev,0,5,,1),"<"&H23))+ROUND((H23-IF(""=(INDEX(OFFSET(CronoPrev,0,5,,1),COUNTIF(OFFSET(CronoPrev,0,5,,1),"<"&H23))),0,INDEX(OFFSET(CronoPrev,0,5,,1),COUNTIF(OFFSET(CronoPrev,0,5,,1),"<"&H23))))/INDEX(OFFSET(CronoPrev,0,4,,1),COUNTIF(OFFSET(CronoPrev,0,5,,1),"<"&H23)+1)*INDEX(OFFSET(CronoPrev,0,2,,1),COUNTIF(OFFSET(CronoPrev,0,5,,1),"<"&H23)+1),0) -> 31 | L23: =IF(C23="","",K23-J23) -> 31 | M23: =IF(C23="","",L23/SUM(OFFSET(CronoPrev!$D$14,0,0,Cronograma.NumPeríodos))) -> 0.14553991 | O23: 10 | P23: =SUMIF(OFFSET(Eventograma_e_Quantitativos!$DK$17,1,0):OFFSET(Eventograma_e_Quantitativos!$DK$37,-1,0),Resumo_de_Acompanhamento!$O23,OFFSET(Eventograma_e_Quantitativos!$DL$17,1,0):OFFSET(Eventograma_e_Quantitativos!$DL$37,-1,0)) -> 0
B24: =OFFSET(B24,-1,0)+1 -> 11 | C24: =IF(OR(D24="",D24<dataInicioObra),"",COUNTIF(CronoPrev!$C$14:$C$25,"<"&(D24-7))+1) -> 1 | D24: =OFFSET(PLE!$G$40,TRUNC((ROW($B24)-ROW($B$14))/12,0)*8,MOD(ROW($B24)-ROW($B$14),12)*4) -> 0 | E24: =OFFSET(PLE!$G$43,TRUNC((ROW($B24)-ROW($B$14))/12,0)*8,MOD(ROW(B24)-ROW($B$14),12)*4) -> 0 | F24: =E24+OFFSET(F24,-1,0) -> 0 | G24: =OFFSET(PLE!$G$42,TRUNC((ROW($B24)-ROW($B$14))/12,0)*8,MOD(ROW(B24)-ROW($B$14),12)*4) -> 0 | H24: =G24+OFFSET(H24,-1,0) -> 0 | I24: =IF(C24="","",IF(C24>Cronograma.NumPeríodos,1,VLOOKUP(C24,CronoPrev!$B$14:$G$25,6,FALSE))) -> 0.19732785 | J24: =D24-dataInicioObra -> 0 | K24: =INDEX(OFFSET(CronoPrev,0,3,,1),COUNTIF(OFFSET(CronoPrev,0,5,,1),"<"&H24))+ROUND((H24-IF(""=(INDEX(OFFSET(CronoPrev,0,5,,1),COUNTIF(OFFSET(CronoPrev,0,5,,1),"<"&H24))),0,INDEX(OFFSET(CronoPrev,0,5,,1),COUNTIF(OFFSET(CronoPrev,0,5,,1),"<"&H24))))/INDEX(OFFSET(CronoPrev,0,4,,1),COUNTIF(OFFSET(CronoPrev,0,5,,1),"<"&H24)+1)*INDEX(OFFSET(CronoPrev,0,2,,1),COUNTIF(OFFSET(CronoPrev,0,5,,1),"<"&H24)+1),0) -> 62 | L24: =IF(C24="","",K24-J24) -> 62 | M24: =IF(C24="","",L24/SUM(OFFSET(CronoPrev!$D$14,0,0,Cronograma.NumPeríodos))) -> 0.29107981 | O24: 11 | P24: =SUMIF(OFFSET(Eventograma_e_Quantitativos!$DK$17,1,0):OFFSET(Eventograma_e_Quantitativos!$DK$37,-1,0),Resumo_de_Acompanhamento!$O24,OFFSET(Eventograma_e_Quantitativos!$DL$17,1,0):OFFSET(Eventograma_e_Quantitativos!$DL$37,-1,0)) -> 0
B25: =OFFSET(B25,-1,0)+1 -> 12 | C25: =IF(OR(D25="",D25<dataInicioObra),"",COUNTIF(CronoPrev!$C$14:$C$25,"<"&(D25-7))+1) -> 1 | D25: =OFFSET(PLE!$G$40,TRUNC((ROW($B25)-ROW($B$14))/12,0)*8,MOD(ROW($B25)-ROW($B$14),12)*4) -> 0 | E25: =OFFSET(PLE!$G$43,TRUNC((ROW($B25)-ROW($B$14))/12,0)*8,MOD(ROW(B25)-ROW($B$14),12)*4) -> 0 | F25: =E25+OFFSET(F25,-1,0) -> 0 | G25: =OFFSET(PLE!$G$42,TRUNC((ROW($B25)-ROW($B$14))/12,0)*8,MOD(ROW(B25)-ROW($B$14),12)*4) -> 0 | H25: =G25+OFFSET(H25,-1,0) -> 0 | I25: =IF(C25="","",IF(C25>Cronograma.NumPeríodos,1,VLOOKUP(C25,CronoPrev!$B$14:$G$25,6,FALSE))) -> 0.19732785 | J25: =D25-dataInicioObra -> 0 | K25: =INDEX(OFFSET(CronoPrev,0,3,,1),COUNTIF(OFFSET(CronoPrev,0,5,,1),"<"&H25))+ROUND((H25-IF(""=(INDEX(OFFSET(CronoPrev,0,5,,1),COUNTIF(OFFSET(CronoPrev,0,5,,1),"<"&H25))),0,INDEX(OFFSET(CronoPrev,0,5,,1),COUNTIF(OFFSET(CronoPrev,0,5,,1),"<"&H25))))/INDEX(OFFSET(CronoPrev,0,4,,1),COUNTIF(OFFSET(CronoPrev,0,5,,1),"<"&H25)+1)*INDEX(OFFSET(CronoPrev,0,2,,1),COUNTIF(OFFSET(CronoPrev,0,5,,1),"<"&H25)+1),0) -> 93 | L25: =IF(C25="","",K25-J25) -> 93 | M25: =IF(C25="","",L25/SUM(OFFSET(CronoPrev!$D$14,0,0,Cronograma.NumPeríodos))) -> 0.43661972 | O25: 12 | P25: =SUMIF(OFFSET(Eventograma_e_Quantitativos!$DK$17,1,0):OFFSET(Eventograma_e_Quantitativos!$DK$37,-1,0),Resumo_de_Acompanhamento!$O25,OFFSET(Eventograma_e_Quantitativos!$DL$17,1,0):OFFSET(Eventograma_e_Quantitativos!$DL$37,-1,0)) -> 0
... B33: =OFFSET(B33,-1,0)+1 -> 20 | C33: =IF(OR(D33="",D33<dataInicioObra),"",COUNTIF(CronoPrev!$C$14:$C$25,"<"&(D33-7))+1) -> 1 | D33: =OFFSET(PLE!$G$40,TRUNC((ROW($B33)-ROW($B$14))/12,0)*8,MOD(ROW($B33)-ROW($B$14),12)*4) -> 0 | E33: =OFFSET(PLE!$G$43,TRUNC((ROW($B33)-ROW($B$14))/12,0)*8,MOD(ROW(B33)-ROW($B$14),12)*4) -> 0 | F33: =E33+OFFSET(F33,-1,0) -> 0 | G33: =OFFSET(PLE!$G$42,TRUNC((ROW($B33)-ROW($B$14))/12,0)*8,MOD(ROW(B33)-ROW($B$14),12)*4) -> 0 | H33: =G33+OFFSET(H33,-1,0) -> 0 | I33: =IF(C33="","",IF(C33>Cronograma.NumPeríodos,1,VLOOKUP(C33,CronoPrev!$B$14:$G$25,6,FALSE))) -> 0.19732785 | J33: =D33-dataInicioObra -> 0 | K33: =INDEX(OFFSET(CronoPrev,0,3,,1),COUNTIF(OFFSET(CronoPrev,0,5,,1),"<"&H33))+ROUND((H33-IF(""=(INDEX(OFFSET(CronoPrev,0,5,,1),COUNTIF(OFFSET(CronoPrev,0,5,,1),"<"&H33))),0,INDEX(OFFSET(CronoPrev,0,5,,1),COUNTIF(OFFSET(CronoPrev,0,5,,1),"<"&H33))))/INDEX(OFFSET(CronoPrev,0,4,,1),COUNTIF(OFFSET(CronoPrev,0,5,,1),"<"&H33)+1)*INDEX(OFFSET(CronoPrev,0,2,,1),COUNTIF(OFFSET(CronoPrev,0,5,,1),"<"&H33)+1),0) -> #VALUE! | L33: =IF(C33="","",K33-J33) -> #VALUE! | M33: =IF(C33="","",L33/SUM(OFFSET(CronoPrev!$D$14,0,0,Cronograma.NumPeríodos))) -> #VALUE! | O33: 20 | P33: =SUMIF(OFFSET(Eventograma_e_Quantitativos!$DK$17,1,0):OFFSET(Eventograma_e_Quantitativos!$DK$37,-1,0),Resumo_de_Acompanhamento!$O33,OFFSET(Eventograma_e_Quantitativos!$DL$17,1,0):OFFSET(Eventograma_e_Quantitativos!$DL$37,-1,0)) -> 0
B34: =OFFSET(B34,-1,0)+1 -> 21 | C34: =IF(OR(D34="",D34<dataInicioObra),"",COUNTIF(CronoPrev!$C$14:$C$25,"<"&(D34-7))+1) -> 1 | D34: =OFFSET(PLE!$G$40,TRUNC((ROW($B34)-ROW($B$14))/12,0)*8,MOD(ROW($B34)-ROW($B$14),12)*4) -> 0 | E34: =OFFSET(PLE!$G$43,TRUNC((ROW($B34)-ROW($B$14))/12,0)*8,MOD(ROW(B34)-ROW($B$14),12)*4) -> 0 | F34: =E34+OFFSET(F34,-1,0) -> 0 | G34: =OFFSET(PLE!$G$42,TRUNC((ROW($B34)-ROW($B$14))/12,0)*8,MOD(ROW(B34)-ROW($B$14),12)*4) -> 0 | H34: =G34+OFFSET(H34,-1,0) -> 0 | I34: =IF(C34="","",IF(C34>Cronograma.NumPeríodos,1,VLOOKUP(C34,CronoPrev!$B$14:$G$25,6,FALSE))) -> 0.19732785 | J34: =D34-dataInicioObra -> 0 | K34: =INDEX(OFFSET(CronoPrev,0,3,,1),COUNTIF(OFFSET(CronoPrev,0,5,,1),"<"&H34))+ROUND((H34-IF(""=(INDEX(OFFSET(CronoPrev,0,5,,1),COUNTIF(OFFSET(CronoPrev,0,5,,1),"<"&H34))),0,INDEX(OFFSET(CronoPrev,0,5,,1),COUNTIF(OFFSET(CronoPrev,0,5,,1),"<"&H34))))/INDEX(OFFSET(CronoPrev,0,4,,1),COUNTIF(OFFSET(CronoPrev,0,5,,1),"<"&H34)+1)*INDEX(OFFSET(CronoPrev,0,2,,1),COUNTIF(OFFSET(CronoPrev,0,5,,1),"<"&H34)+1),0) -> #VALUE! | L34: =IF(C34="","",K34-J34) -> #VALUE! | M34: =IF(C34="","",L34/SUM(OFFSET(CronoPrev!$D$14,0,0,Cronograma.NumPeríodos))) -> #VALUE!
