Workbook

Sheet RESUMO REV_1
A1: PLANILHA RESUMO
A2: Secretaria de Atenção Especializada à Saúde BDI Geral: Encargo Social Mensalista: Data:
A3: Centro de Atenção Psicossocial - Porte 1, no município de Coremas/PB 26,87% 69,85% 12/12/2025 Bancos: Encargo Social Horista: 113,60% SINAPI (09/2025) - CPOS/CDHU (09/2025) - SBC (12/2025) - ORSE (09/2025) - IOPES (08/2025) - EMOP (10/2025) - SETOP (07/2025) - 113,60% SEINFRA (028) - AGETOP CIVIL (08/2025) - AGESUL (06/2025)
A4: ITEM | B4: DESCRIÇÃO | E4: PREÇO | G4: %
A5: 1 | B5: SERVIÇOS PRELIMINARES E INDIRETOS | E5: R$ | F5: ='SINTÉTICO REV_01'!J6 -> 162825.53 | G5: =F5/F25 -> 0.066453675
A6: 2 | B6: FUNDAÇÃO | E6: R$ | F6: ='SINTÉTICO REV_01'!J24 -> 207935.32 | G6: =F6/F25 -> 0.084864251
A7: 3 | B7: ESTRUTURA | E7: R$ | F7: ='SINTÉTICO REV_01'!J41 -> 300443.72 | G7: =F7/F25 -> 0.12261953
A8: 4 | B8: ALVENARIA, VEDAÇÕES E DIVISÓRIAS | E8: R$ | F8: ='SINTÉTICO REV_01'!J72 -> 195823.09 | G8: =F8/F25 -> 0.079920908
A9: 5 | B9: COBERTURA | E9: R$ | F9: ='SINTÉTICO REV_01'!J87 -> 102452.36 | G9: =F9/F25 -> 0.04181369
A10: 6 | B10: IMPERMEABILIZAÇÃO | E10: R$ | F10: ='SINTÉTICO REV_01'!J97 -> 40341.332 | G10: =F10/F25 -> 0.016464432
A11: 7 | B11: ESQUADRIAS | E11: R$ | F11: ='SINTÉTICO REV_01'!J101 -> 255123.7 | G11: =F11/F25 -> 0.10412316
A12: 8 | B12: REVESTIMENTO DE PAREDE | E12: R$ | F12: ='SINTÉTICO REV_01'!J128 -> 105077.27 | G12: =F12/F25 -> 0.042884989
A13: 9 | B13: REVESTIMENTO DE PISO INTERNO | E13: R$ | F13: ='SINTÉTICO REV_01'!J135 -> 138994.45 | G13: =F13/F25 -> 0.056727542
A14: 10 | B14: REVESTIMENTO DE PISO EXTERNO | E14: R$ | F14: ='SINTÉTICO REV_01'!J144 -> 37635.545 | G14: =F14/F25 -> 0.015360124
A15: 11 | B15: REVESTIMENTO DE TETO | E15: R$ | F15: ='SINTÉTICO REV_01'!J147 -> 45069.659 | G15: =F15/F25 -> 0.018394195
A16: 12 | B16: PINTURA | E16: R$ | F16: ='SINTÉTICO REV_01'!J150 -> 82409.807 | G16: =F16/F25 -> 0.033633759
A17: 13 | B17: MARMORARIA | E17: R$ | F17: ='SINTÉTICO REV_01'!J163 -> 8379.8122 | G17: =F17/F25 -> 0.003420037
A18: 14 | B18: LOUÇAS, METAIS E ACESSÓRIOS | E18: R$ | F18: ='SINTÉTICO REV_01'!J166 -> 63864.558 | G18: =F18/F25 -> 0.026064922
A19: 15 | B19: INSTALAÇÕES HIDROSSANITÁRIAS | E19: R$ | F19: ='SINTÉTICO REV_01'!J193 -> 171422.78 | G19: =F19/F25 -> 0.069962457
A20: 16 | B20: INSTALAÇÕES ELÉTRICAS | E20: R$ | F20: ='SINTÉTICO REV_01'!J309 -> 334017.29 | G20: =F20/F25 -> 0.13632185
A21: 17 | B21: CLIMATIZAÇÃO | E21: R$ | F21: ='SINTÉTICO REV_01'!J415 -> 151556.94 | G21: =F21/F25 -> 0.061854649
A22: 18 | B22: DADOS E VOZ | E22: R$ | F22: ='SINTÉTICO REV_01'!J438 -> 21580.296 | G22: =F22/F25 -> 0.0088075258
A23: 19 | B23: URBANIZAÇÃO | E23: R$ | F23: ='SINTÉTICO REV_01'!J460 -> 14283.411 | G23: =F23/F25 -> 0.0058294618
A24: 20 | B24: SERVIÇOS COMPLEMENTARES | E24: R$ | F24: ='SINTÉTICO REV_01'!J468 -> 10974.113 | G24: =F24/F25 -> 0.0044788442
A25: TOTAL | E25: R$ | F25: =SUM(F5:F24) -> 2450211 | G25: =SUM(G5:G24) -> 1
A26: Notas:
A27: Estão exclusos do escopo: movimentação de terra, mobiliário e equipamentos, piso intertravado, chapas metálicas das portas, instalações de automação, CFTV, energia fotovoltaica, controle de acesso, CATV, sonorização, luminárias externas, arborização, muro perimetral e equipamentos de ar condicionado.
A28: _______________________________________________________________ Luzikenyo L. M. Veloso Chianca - CREA PB n° 1612617590 Engenheiro Civil

Sheet SINTÉTICO REV_01
A1: PLANILHA DE ORÇAMENTO SINTÉTICO
A2: Secretaria de Atenção Especializada à Saúde BDI Geral: Encargo Social Mensalista: Data:
A3: Centro de Atenção Psicossocial - Porte 1, no município de Coremas/PB - L7 ENGENHARIA LTDA 26,87% 69,85% 12/12/2025 Bancos: SINAPI (09/2025) - CPOS/CDHU (09/2025) - SBC (12/2025) - ORSE (09/2025) - IOPES (08/2025) - EMOP (10/2025) - SETOP (07/2025) - SEINFRA (028) - AGETOP CIVIL (08/2025) - AGESUL (06/2025) Encargo Social Horista: 113,60%
A5: Item | B5: Código | C5: Banco | D5: Descrição | E5: Und | F5: Quant. | G5: Valor Unit | H5: Valor Unit c/ Desconto | I5: Valor Unit com BDI | J5: Total
A6: 1 | D6: SERVIÇOS PRELIMINARES E INDIRETOS | J6: =J7+J18+J20+J22 -> 162825.53
A7: 1.1 | D7: CANTEIRO DE OBRAS | J7: =SUM(J8:J17) -> 99885.999
A8: 1.1.1 | B8: CPU2526 | C8: Próprio | D8: LOCAÇÃO DE CONTAINER TIPO DEPÓSITO - ÁREA MÍNIMA DE 13,80 M2 | E8: UNXMÊS | F8: 14 | G8: 967.29 | H8: =G8-(G8*M8) -> 924.53544 | I8: =H8+(H8*L8) -> 1172.9581 | J8: =I8*F8 -> 16421.414 | L8: 0.2687 | M8: 0.04420035
A9: 1.1.2 | B9: CPU2527 | C9: Próprio | D9: BARRACÃO ABERTO PARA APOIO À PRODUÇÃO (CARPINTARIA, CENTRAL DE ARMAÇÃO, OFICINA, ETC.) C/ | E9: m² | F9: 15 | G9: 245.8 | H9: =G9-(G9*M9) -> 234.93555 | I9: =H9+(H9*L9) -> 298.06274 | J9: =I9*F9 -> 4470.9411 | L9: 0.2687 | M9: 0.04420035
A10: 1.1.3 | B10: CPU2528 | C10: Próprio | D10: LOCAÇÃO DE CONTAINER - BANHEIRO COM CHUVEIROS E VASOS - 4,30 X 2,30M | E10: MÊS | F10: 0 | G10: 962.26 | H10: 0 | I10: =H10+(H10*L10) -> 0 | J10: =I10*F10 -> 0 | L10: 0.2687 | M10: 0.04420035
A11: 1.1.4 | B11: CPU2529 | C11: Próprio | D11: BARRACAO PARA REFEITORIO EM OBRAS EM COMPENSADO | E11: m² | F11: 13 | G11: 1057.99 | H11: =G11-(G11*M11) -> 1011.2265 | I11: =H11+(H11*L11) -> 1282.943 | J11: =I11*F11 -> 16678.259 | L11: 0.2687 | M11: 0.04420035
A12: 1.1.5 | B12: 95648 | C12: SINAPI | D12: KIT CAVALETE PARA MEDIÇÃO DE ÁGUA - ENTRADA INDIVIDUALIZADA, EM CPVC DN 28 MM (1"), PARA 1 MEDIDOR | E12: UN | F12: 1 | G12: 594.6 | H12: =G12-(G12*M12) -> 568.31847 | I12: =H12+(H12*L12) -> 721.02565 | J12: =I12*F12 -> 721.02565 | L12: 0.2687 | M12: 0.04420035
A13: 1.1.6 | B13: 95673 | C13: SINAPI | D13: HIDRÔMETRO DN 1/2", 1,5 M3/H - FORNECIMENTO E INSTALAÇÃO. AF_03/2024 | E13: UN | F13: 1 | G13: 130.69 | H13: =G13-(G13*M13) -> 124.91346 | I13: =H13+(H13*L13) -> 158.4777 | J13: =I13*F13 -> 158.4777 | L13: 0.2687 | M13: 0.04420035
A14: 1.1.7 | B14: 101509 | C14: SINAPI | D14: ENTRADA DE ENERGIA ELÉTRICA, AÉREA, TRIFÁSICA, COM CAIXA DE EMBUTIR, CABO DE 10 MM2 E DISJUNTOR | E14: UN | F14: 1 | G14: 1954.86 | H14: =G14-(G14*M14) -> 1868.4545 | I14: =H14+(H14*L14) -> 2370.5082 | J14: =I14*F14 -> 2370.5082 | L14: 0.2687 | M14: 0.04420035
A15: 1.1.8 | B15: 103689 | C15: SINAPI | D15: FORNECIMENTO E INSTALAÇÃO DE PLACA DE OBRA COM CHAPA GALVANIZADA E ESTRUTURA DE MADEIRA. | E15: m² | F15: 6 | G15: 465.84 | H15: =G15-(G15*M15) -> 445.24971 | I15: =H15+(H15*L15) -> 564.88831 | J15: =I15*F15 -> 3389.3298 | L15: 0.2687 | M15: 0.04420035
A16: 1.1.9 | B16: CPU2530 | C16: Próprio | D16: REMOÇÃO DE ENTULHO SEPARADO DE OBRA COM CAÇAMBA METÁLICA - TERRA, ALVENARIA, CONCRETO, | E16: m³ | F16: 140 | G16: 110.78 | H16: =G16-(G16*M16) -> 105.88349 | I16: =H16+(H16*L16) -> 134.33438 | J16: =I16*F16 -> 18806.813 | L16: 0.2687 | M16: 0.04420035
A17: 40179 | B17: 98459 | C17: SINAPI | D17: TAPUME COM TELHA METÁLICA. AF_03/2024 | E17: m² | F17: 325.6 | G17: 93.38 | H17: =G17-(G17*M17) -> 89.252571 | I17: =H17+(H17*L17) -> 113.23474 | J17: =I17*F17 -> 36869.23 | L17: 0.2687 | M17: 0.04420035
A18: 1.2 | D18: ADMINISTRAÇÃO LOCAL DA OBRA | J18: =J19 -> 47945.998 | M18: 0.04420035
A19: 1.2.1 | B19: 93565 | C19: SINAPI | D19: ENGENHEIRO CIVIL DE OBRA JUNIOR COM ENCARGOS COMPLEMENTARES | E19: MES | F19: 1.75 | G19: 22593.76 | H19: =G19-(G19*M19) -> 21595.108 | I19: =H19+(H19*L19) -> 27397.713 | J19: =I19*F19 -> 47945.998 | L19: 0.2687 | M19: 0.04420035
A20: 1.3 | D20: MOBILIZAÇÃO E DESMOBILIZAÇÃO | J20: =J21 -> 7839.0864 | M20: 0.04420035
A21: 1.3.1 | B21: CPU2531 | C21: Próprio | D21: MOBILIZACAO E DESMOBILIZACAO DE CANTEIRO | E21: UN | F21: 1 | G21: 6464.57 | H21: =G21-(G21*M21) -> 6178.8337 | I21: =H21+(H21*L21) -> 7839.0864 | J21: =I21*F21 -> 7839.0864 | L21: 0.2687 | M21: 0.04420035
A22: 1.4 | D22: EQUIPAMENTOS DE APOIO | J22: =J23 -> 7154.4418 | M22: 0.04420035
A23: 1.4.1 | B23: CPU1926 | C23: Próprio | D23: LOCACAO DE ANDAIME METALICO TIPO FACHADEIRO, PECAS COM APROXIMADAMENTE 1,20 M DE LARGURA E | E23: M2XMÊS | F23: 273.4 | G23: 21.58 | H23: =G23-(G23*M23) -> 20.626156 | I23: =H23+(H23*L23) -> 26.168405 | J23: =I23*F23 -> 7154.4418 | L23: 0.2687 | M23: 0.04420035
A24: 2 | D24: FUNDAÇÃO | J24: =SUM(J25:J40) -> 207935.32 | M24: 0.04420035
A25: 2.1 | B25: 99059 | C25: SINAPI | D25: LOCAÇÃO CONVENCIONAL DE OBRA, UTILIZANDO GABARITO DE TÁBUAS CORRIDAS PONTALETADAS A CADA | E25: M | F25: 97.5 | G25: 62.21 | H25: =G25-(G25*M25) -> 59.460296 | I25: =H25+(H25*L25) -> 75.437278 | J25: =I25*F25 -> 7355.1346 | L25: 0.2687 | M25: 0.04420035
A26: 2.2 | B26: 90100 | C26: SINAPI | D26: ESCAVAÇÃO MECANIZADA DE VALA COM PROF. ATÉ 1,5 M (MÉDIA MONTANTE E JUSANTE/UMA COMPOSIÇÃO | E26: m³ | F26: 208.39 | G26: 12.45 | H26: =G26-(G26*M26) -> 11.899706 | I26: =H26+(H26*L26) -> 15.097157 | J26: =I26*F26 -> 3146.0965 | L26: 0.2687 | M26: 0.04420035
A27: 2.3 | B27: 93358 | C27: SINAPI | D27: ESCAVAÇÃO MANUAL DE VALA COM PROFUNDIDADE MENOR OU IGUAL A 1,30 M. AF_02/2021 | E27: m³ | F27: 52.1 | G27: 84.33 | H27: =G27-(G27*M27) -> 80.602584 | I27: =H27+(H27*L27) -> 102.2605 | J27: =I27*F27 -> 5327.772 | L27: 0.2687 | M27: 0.04420035
A28: 2.4 | B28: 100324 | C28: SINAPI | D28: LASTRO COM MATERIAL GRANULAR (PEDRA BRITADA N.1 E PEDRA BRITADA N.2), APLICADO EM PISOS OU LAJES | E28: m³ | F28: 60.58 | G28: 175 | H28: =G28-(G28*M28) -> 167.26494 | I28: =H28+(H28*L28) -> 212.20903 | J28: =I28*F28 -> 12855.623 | L28: 0.2687 | M28: 0.04420035
A29: 2.5 | B29: 96534 | C29: SINAPI | D29: FABRICAÇÃO, MONTAGEM E DESMONTAGEM DE FÔRMA PARA BLOCO DE COROAMENTO, EM MADEIRA | E29: m² | F29: 403.5 | G29: 85.12 | H29: =G29-(G29*M29) -> 81.357666 | I29: =H29+(H29*L29) -> 103.21847 | J29: =I29*F29 -> 41648.653 | L29: 0.2687 | M29: 0.04420035
A30: 2.6 | B30: 96543 | C30: SINAPI | D30: ARMAÇÃO DE BLOCO UTILIZANDO AÇO CA-60 DE 5 MM - MONTAGEM. AF_01/2024 | E30: KG | F30: 415.5 | G30: 18.55 | H30: =G30-(G30*M30) -> 17.730084 | I30: =H30+(H30*L30) -> 22.494157 | J30: =I30*F30 -> 9346.3222 | L30: 0.2687 | M30: 0.04420035
A31: 2.7 | B31: 96544 | C31: SINAPI | D31: ARMAÇÃO DE BLOCO UTILIZANDO AÇO CA-50 DE 6,3 MM - MONTAGEM. AF_01/2024 | E31: KG | F31: 4.4 | G31: 16.48 | H31: =G31-(G31*M31) -> 15.751578 | I31: =H31+(H31*L31) -> 19.984027 | J31: =I31*F31 -> 87.92972 | L31: 0.2687 | M31: 0.04420035
A32: 2.8 | B32: 96545 | C32: SINAPI | D32: ARMAÇÃO DE BLOCO UTILIZANDO AÇO CA-50 DE 8 MM - MONTAGEM. AF_01/2024 | E32: KG | F32: 1092.4 | G32: 14.69 | H32: =G32-(G32*M32) -> 14.040697 | I32: =H32+(H32*L32) -> 17.813432 | J32: =I32*F32 -> 19459.393 | L32: 0.2687 | M32: 0.04420035
A33: 2.9 | B33: 96546 | C33: SINAPI | D33: ARMAÇÃO DE BLOCO UTILIZANDO AÇO CA-50 DE 10 MM - MONTAGEM. AF_01/2024 | E33: KG | F33: 787.4 | G33: 12.76 | H33: =G33-(G33*M33) -> 12.196004 | I33: =H33+(H33*L33) -> 15.47307 | J33: =I33*F33 -> 12183.495 | L33: 0.2687 | M33: 0.04420035
A34: 2.10 | B34: 104920 | C34: SINAPI | D34: ARMAÇÃO DE BLOCO, SAPATA ISOLADA, VIGA BALDRAME E SAPATA CORRIDA UTILIZANDO AÇO CA-50 DE 12,5 | E34: KG | F34: 436.8 | G34: 9.75 | H34: =G34-(G34*M34) -> 9.3190466 | I34: =H34+(H34*L34) -> 11.823074 | J34: =I34*F34 -> 5164.3189 | L34: 0.2687 | M34: 0.04420035
A35: 2.11 | B35: 104921 | C35: SINAPI | D35: ARMAÇÃO DE BLOCO, SAPATA ISOLADA, VIGA BALDRAME E SAPATA CORRIDA UTILIZANDO AÇO CA-50 DE 16 MM - | E35: KG | F35: 207.1 | G35: 9.14 | H35: =G35-(G35*M35) -> 8.7360088 | I35: =H35+(H35*L35) -> 11.083374 | J35: =I35*F35 -> 2295.3668 | L35: 0.2687 | M35: 0.04420035
A36: 2.12 | B36: 96557 | C36: SINAPI | D36: CONCRETAGEM DE BLOCO DE COROAMENTO OU VIGA BALDRAME, FCK 30 MPA, COM USO DE BOMBA - | E36: m³ | F36: 54.3 | G36: 761.22 | H36: =G36-(G36*M36) -> 727.57381 | I36: =H36+(H36*L36) -> 923.07289 | J36: =I36*F36 -> 50122.858 | L36: 0.2687 | M36: 0.04420035
... A39: 2.15 | B39: 98557 | C39: SINAPI | D39: IMPERMEABILIZAÇÃO DE SUPERFÍCIE COM EMULSÃO ASFÁLTICA, 2 DEMÃOS. AF_09/2023 | E39: m² | F39: 403.5 | G39: 48.94 | H39: =G39-(G39*M39) -> 46.776835 | I39: =H39+(H39*L39) -> 59.34577 | J39: =I39*F39 -> 23946.018 | L39: 0.2687 | M39: 0.04420035
A40: 2.16 | B40: CPU2532 | C40: Próprio | D40: CONTROLE TECNOLOGICO DE CONCRETOS | E40: m³ | F40: 54.3 | G40: 102.92 | H40: =G40-(G40*M40) -> 98.3709 | I40: =H40+(H40*L40) -> 124.80316 | J40: =I40*F40 -> 6776.8116 | L40: 0.2687 | M40: 0.04420035
A41: 3 | D41: ESTRUTURA | J41: =J42+J49+J59+J70 -> 300443.72 | M41: 0.04420035
A42: 3.1 | D42: PILARES | J42: =SUM(J43:J48) -> 45759.592 | M42: 0.04420035
A43: 3.1.1 | B43: 92423 | C43: SINAPI | D43: MONTAGEM E DESMONTAGEM DE FÔRMA DE PILARES RETANGULARES E ESTRUTURAS SIMILARES, PÉ-DIREITO | E43: m² | F43: 231.1 | G43: 65.77 | H43: =G43-(G43*M43) -> 62.862943 | I43: =H43+(H43*L43) -> 79.754216 | J43: =I43*F43 -> 18431.199 | L43: 0.2687 | M43: 0.04420035
A44: 3.1.2 | B44: 92762 | C44: SINAPI | D44: ARMAÇÃO DE PILAR OU VIGA DE ESTRUTURA CONVENCIONAL DE CONCRETO ARMADO UTILIZANDO AÇO CA-50 DE 10,0 MM - MONTAGEM. AF_06/2022 | E44: KG | F44: 584.9 | G44: 9.89 | H44: =G44-(G44*M44) -> 9.4528585 | I44: =H44+(H44*L44) -> 11.992842 | J44: =I44*F44 -> 7014.6131 | L44: 0.2687 | M44: 0.04420035
A45: 3.1.3 | B45: 92763 | C45: SINAPI | D45: ARMAÇÃO DE PILAR OU VIGA DE ESTRUTURA CONVENCIONAL DE CONCRETO ARMADO UTILIZANDO AÇO CA-50 | E45: KG | F45: 151.3 | G45: 8.29 | H45: =G45-(G45*M45) -> 7.9235791 | I45: =H45+(H45*L45) -> 10.052645 | J45: =I45*F45 -> 1520.9652 | L45: 0.2687 | M45: 0.04420035
A46: 3.1.4 | B46: 92759 | C46: SINAPI | D46: ARMAÇÃO DE PILAR OU VIGA DE ESTRUTURA CONVENCIONAL DE CONCRETO ARMADO UTILIZANDO AÇO CA-60 | E46: KG | F46: 310.8 | G46: 12.92 | H46: =G46-(G46*M46) -> 12.348931 | I46: =H46+(H46*L46) -> 15.667089 | J46: =I46*F46 -> 4869.3314 | L46: 0.2687 | M46: 0.04420035
A47: 3.1.5 | B47: CPU2284 | C47: Próprio | D47: CONCRETAGEM DE PILARES, FCK = 30 MPA, COM USO DE BOMBA - LANÇAMENTO, ADENSAMENTO E | E47: m³ | F47: 14.2 | G47: 705.68 | H47: =G47-(G47*M47) -> 674.4887 | I47: =H47+(H47*L47) -> 855.72381 | J47: =I47*F47 -> 12151.278 | L47: 0.2687 | M47: 0.04420035
A48: 3.1.6 | B48: CPU2532 | C48: Próprio | D48: CONTROLE TECNOLOGICO DE CONCRETOS | E48: m³ | F48: 14.2 | G48: 102.92 | H48: =G48-(G48*M48) -> 98.3709 | I48: =H48+(H48*L48) -> 124.80316 | J48: =I48*F48 -> 1772.2049 | L48: 0.2687 | M48: 0.04420035
A49: 3.2 | D49: VIGAS | J49: =SUM(J50:J58) -> 74998.366 | M49: 0.04420035
A50: 3.2.1 | B50: 92460 | C50: SINAPI | D50: MONTAGEM E DESMONTAGEM DE FÔRMA DE VIGA, ESCORAMENTO METÁLICO, PÉ-DIREITO SIMPLES, EM CHAPA | E50: m² | F50: 205.1 | G50: 112.94 | H50: =G50-(G50*M50) -> 107.94801 | I50: =H50+(H50*L50) -> 136.95364 | J50: =I50*F50 -> 28089.192 | L50: 0.2687 | M50: 0.04420035
A51: 3.2.2 | B51: 92760 | C51: SINAPI | D51: ARMAÇÃO DE PILAR OU VIGA DE ESTRUTURA CONVENCIONAL DE CONCRETO ARMADO UTILIZANDO AÇO CA-50 DE 6,3 MM - MONTAGEM. AF_06/2022 | E51: KG | F51: 54.6 | G51: 12 | H51: =G51-(G51*M51) -> 11.469596 | I51: =H51+(H51*L51) -> 14.551476 | J51: =I51*F51 -> 794.5106 | L51: 0.2687 | M51: 0.04420035
A52: 3.2.3 | B52: 92761 | C52: SINAPI | D52: ARMAÇÃO DE PILAR OU VIGA DE ESTRUTURA CONVENCIONAL DE CONCRETO ARMADO UTILIZANDO AÇO CA-50 | E52: KG | F52: 296.7 | G52: 11.15 | H52: =G52-(G52*M52) -> 10.657166 | I52: =H52+(H52*L52) -> 13.520747 | J52: =I52*F52 -> 4011.6055 | L52: 0.2687 | M52: 0.04420035
A53: 3.2.4 | B53: 92762 | C53: SINAPI | D53: ARMAÇÃO DE PILAR OU VIGA DE ESTRUTURA CONVENCIONAL DE CONCRETO ARMADO UTILIZANDO AÇO CA-50 | E53: KG | F53: 370 | G53: 9.89 | H53: =G53-(G53*M53) -> 9.4528585 | I53: =H53+(H53*L53) -> 11.992842 | J53: =I53*F53 -> 4437.3514 | L53: 0.2687 | M53: 0.04420035
A54: 3.2.5 | B54: 92763 | C54: SINAPI | D54: ARMAÇÃO DE PILAR OU VIGA DE ESTRUTURA CONVENCIONAL DE CONCRETO ARMADO UTILIZANDO AÇO CA-50 | E54: KG | F54: 545.5 | G54: 8.29 | H54: =G54-(G54*M54) -> 7.9235791 | I54: =H54+(H54*L54) -> 10.052645 | J54: =I54*F54 -> 5483.7177 | L54: 0.2687 | M54: 0.04420035
A55: 3.2.6 | B55: 92764 | C55: SINAPI | D55: ARMAÇÃO DE PILAR OU VIGA DE ESTRUTURA CONVENCIONAL DE CONCRETO ARMADO UTILIZANDO AÇO CA-50 | E55: KG | F55: 467.8 | G55: 7.99 | H55: =G55-(G55*M55) -> 7.6368392 | I55: =H55+(H55*L55) -> 9.6888579 | J55: =I55*F55 -> 4532.4477 | L55: 0.2687 | M55: 0.04420035
A56: 3.2.7 | B56: 92759 | C56: SINAPI | D56: ARMAÇÃO DE PILAR OU VIGA DE ESTRUTURA CONVENCIONAL DE CONCRETO ARMADO UTILIZANDO AÇO CA-60 | E56: KG | F56: 311.8 | G56: 12.92 | H56: =G56-(G56*M56) -> 12.348931 | I56: =H56+(H56*L56) -> 15.667089 | J56: =I56*F56 -> 4884.9985 | L56: 0.2687 | M56: 0.04420035
A57: 3.2.8 | B57: CPU2283 | C57: Próprio | D57: CONCRETAGEM DE VIGAS E LAJES, FCK=30 MPA, PARA LAJES MACIÇAS OU NERVURADAS COM USO DE BOMBA - | E57: m³ | F57: 23.2 | G57: 706.26 | H57: =G57-(G57*M57) -> 675.04306 | I57: =H57+(H57*L57) -> 856.42713 | J57: =I57*F57 -> 19869.109 | L57: 0.2687 | M57: 0.04420035
A58: 3.2.9 | B58: CPU2532 | C58: Próprio | D58: CONTROLE TECNOLOGICO DE CONCRETOS | E58: m³ | F58: 23.2 | G58: 102.92 | H58: =G58-(G58*M58) -> 98.3709 | I58: =H58+(H58*L58) -> 124.80316 | J58: =I58*F58 -> 2895.4333 | L58: 0.2687 | M58: 0.04420035
A59: 3.3 | D59: LAJES | J59: =SUM(J60:J69) -> 177753.37 | M59: 0.04420035
A60: 3.3.1 | B60: 92768 | C60: SINAPI | D60: ARMAÇÃO DE LAJE DE ESTRUTURA CONVENCIONAL DE CONCRETO ARMADO UTILIZANDO AÇO CA-60 DE 5,0 MM - | E60: KG | F60: 429.2 | G60: 12.42 | H60: =G60-(G60*M60) -> 11.871032 | I60: =H60+(H60*L60) -> 15.060778 | J60: =I60*F60 -> 6464.0859 | L60: 0.2687 | M60: 0.04420035
A61: 3.3.2 | B61: 92769 | C61: SINAPI | D61: ARMAÇÃO DE LAJE DE ESTRUTURA CONVENCIONAL DE CONCRETO ARMADO UTILIZANDO AÇO CA-50 DE 6,3 MM - | E61: KG | F61: 128.4 | G61: 11.5 | H61: =G61-(G61*M61) -> 10.991696 | I61: =H61+(H61*L61) -> 13.945165 | J61: =I61*F61 -> 1790.5591 | L61: 0.2687 | M61: 0.04420035
A62: 3.3.3 | B62: 92770 | C62: SINAPI | D62: ARMAÇÃO DE LAJE DE ESTRUTURA CONVENCIONAL DE CONCRETO ARMADO UTILIZANDO AÇO CA-50 DE 8,0 MM - | E62: KG | F62: 70.1 | G62: 10.67 | H62: =G62-(G62*M62) -> 10.198382 | I62: =H62+(H62*L62) -> 12.938688 | J62: =I62*F62 -> 907.002 | L62: 0.2687 | M62: 0.04420035
A63: 3.3.4 | B63: 92771 | C63: SINAPI | D63: ARMAÇÃO DE LAJE DE ESTRUTURA CONVENCIONAL DE CONCRETO ARMADO UTILIZANDO AÇO CA-50 DE 10,0 | E63: KG | F63: 126 | G63: 9.45 | H63: =G63-(G63*M63) -> 9.0323067 | I63: =H63+(H63*L63) -> 11.459288 | J63: =I63*F63 -> 1443.8702 | L63: 0.2687 | M63: 0.04420035
A64: 3.3.5 | B64: 92772 | C64: SINAPI | D64: ARMAÇÃO DE LAJE DE ESTRUTURA CONVENCIONAL DE CONCRETO ARMADO UTILIZANDO AÇO CA-50 DE 12,5 | E64: KG | F64: 252.4 | G64: 7.9 | H64: =G64-(G64*M64) -> 7.5508172 | I64: =H64+(H64*L64) -> 9.5797218 | J64: =I64*F64 -> 2417.9218 | L64: 0.2687 | M64: 0.04420035
A65: 3.3.6 | B65: CPU2283 | C65: Próprio | D65: CONCRETAGEM DE VIGAS E LAJES, FCK=30 MPA, PARA LAJES MACIÇAS OU NERVURADAS COM USO DE BOMBA - | E65: m³ | F65: 34.7 | G65: 706.26 | H65: =G65-(G65*M65) -> 675.04306 | I65: =H65+(H65*L65) -> 856.42713 | J65: =I65*F65 -> 29718.021 | L65: 0.2687 | M65: 0.04420035
A66: 3.3.7 | B66: CPU2532 | C66: Próprio | D66: CONTROLE TECNOLOGICO DE CONCRETOS | E66: m³ | F66: 34.7 | G66: 102.92 | H66: =G66-(G66*M66) -> 98.3709 | I66: =H66+(H66*L66) -> 124.80316 | J66: =I66*F66 -> 4330.6697 | L66: 0.2687 | M66: 0.04420035
A67: 3.3.8 | B67: CPU2100 | C67: Próprio | D67: Laje pré-fabricada unidirecional em viga treliçada/lajota em EPS LT 16 (12 + 4), exceto capa de concreto | E67: m² | F67: 539.41 | G67: 115.9 | H67: =G67-(G67*M67) -> 110.77718 | I67: =H67+(H67*L67) -> 140.54301 | J67: =I67*F67 -> 75810.304 | L67: 0.2687 | M67: 0.04420035
A68: 3.3.9 | B68: CPU2534 | C68: Próprio | D68: FORNECIMENTO E INSTALAÇÃO DE TELA AÇO SOLDADA NERVURADA CA-60, MALHA 20X20CM,FERRO 3.4MM, | E68: m² | F68: 631.11 | G68: 15.02 | H68: =G68-(G68*M68) -> 14.356111 | I68: =H68+(H68*L68) -> 18.213598 | J68: =I68*F68 -> 11494.784 | L68: 0.2687 | M68: 0.04420035
A69: 40240 | B69: 101792 | C69: SINAPI | D69: ESCORAMENTO DE FÔRMAS DE LAJE EM MADEIRA NÃO APARELHADA, PÉ-DIREITO SIMPLES, INCLUSO | E69: m³ | F69: 1914.91 | G69: 18.68 | H69: =G69-(G69*M69) -> 17.854337 | I69: =H69+(H69*L69) -> 22.651798 | J69: =I69*F69 -> 43376.154 | L69: 0.2687 | M69: 0.04420035
A70: 3.4 | D70: BASE RESERVATÓRIO | J70: =J71 -> 1932.3906 | M70: 0.04420035
A71: 3.4.1 | B71: 97103 | C71: SINAPI | D71: EXECUÇÃO DE RADIER, ESPESSURA DE 20 CM, FCK = 30 MPA, COM USO DE FORMAS EM MADEIRA SERRADA. | E71: m² | F71: 6.25 | G71: 254.97 | H71: =G71-(G71*M71) -> 243.70024 | I71: =H71+(H71*L71) -> 309.18249 | J71: =I71*F71 -> 1932.3906 | L71: 0.2687 | M71: 0.04420035
A72: 4 | D72: ALVENARIA, VEDAÇÕES E DIVISÓRIAS | J72: =J73+J79+J85 -> 195823.09 | M72: 0.04420035
A73: 4.1 | D73: ALVENARIA DE VEDAÇÃO | J73: =SUM(J74:J78) -> 123354.72 | M73: 0.04420035
A74: 4.1.1 | B74: 103324 | C74: SINAPI | D74: ALVENARIA DE VEDAÇÃO DE BLOCOS CERÂMICOS FURADOS NA VERTICAL DE 14X19X39 CM (ESPESSURA 14 | E74: m² | F74: 888.77 | G74: 78.18 | H74: =G74-(G74*M74) -> 74.724417 | I74: =H74+(H74*L74) -> 94.802867 | J74: =I74*F74 -> 84257.944 | L74: 0.2687 | M74: 0.04420035
A75: 4.1.2 | B75: CPU2535 | C75: Próprio | D75: COBOGO DE CIMENTO (ELEMENTO VAZADO, CIRCULAR), 30 X 30 X 5CM, ASSENTADO COM ARGAMASSA DE | E75: m² | F75: 76.23 | G75: 222.63 | H75: =G75-(G75*M75) -> 212.78968 | I75: =H75+(H75*L75) -> 269.96626 | J75: =I75*F75 -> 20579.528 | L75: 0.2687 | M75: 0.04420035
A76: 4.1.3 | B76: 93191 | C76: SINAPI | D76: VERGA MOLDADA IN LOCO COM UTILIZAÇÃO DE BLOCOS CANALETA, ESPESSURA DE *20* CM. AF_03/2024 | E76: M | F76: 114.15 | G76: 71.49 | H76: =G76-(G76*M76) -> 68.330117 | I76: =H76+(H76*L76) -> 86.690419 | J76: =I76*F76 -> 9895.7114 | L76: 0.2687 | M76: 0.04420035
A77: 4.1.4 | B77: 93199 | C77: SINAPI | D77: CONTRAVERGA MOLDADA IN LOCO COM UTILIZAÇÃO DE BLOCOS CANALETA, ESPESSURA DE *20* CM. | E77: M | F77: 48.8 | G77: 49.81 | H77: =G77-(G77*M77) -> 47.608381 | I77: =H77+(H77*L77) -> 60.400752 | J77: =I77*F77 -> 2947.5567 | L77: 0.2687 | M77: 0.04420035
A78: 4.1.5 | B78: 93200 | C78: SINAPI | D78: FIXAÇÃO (ENCUNHAMENTO) DE ALVENARIA DE VEDAÇÃO COM ARGAMASSA APLICADA COM BISNAGA. | E78: M | F78: 416.29 | G78: 11.24 | H78: =G78-(G78*M78) -> 10.743188 | I78: =H78+(H78*L78) -> 13.629883 | J78: =I78*F78 -> 5673.9839 | L78: 0.2687 | M78: 0.04420035
A79: 4.2 | D79: DRYWALL | J79: =SUM(J80:J84) -> 56926.567 | M79: 0.04420035
A80: 4.2.1 | B80: CPU1942 | C80: Próprio | D80: PAREDE COM SISTEMA EM CHAPAS DE GESSO RU PARA DRYWALL, USO INTERNO, COM DUAS FACES SIMPLES | E80: m² | F80: 107.07 | G80: 113.39 | H80: =G80-(G80*M80) -> 108.37812 | I80: =H80+(H80*L80) -> 137.49932 | J80: =I80*F80 -> 14722.053 | L80: 0.2687 | M80: 0.04420035
A81: 4.2.2 | B81: CPU2286 | C81: Próprio | D81: PAREDE COM SISTEMA EM CHAPAS DE GESSO RU PARA DRYWALL COM ISOLAMENTO ACUSTICO, USO | E81: m² | F81: 91.66 | G81: 183.49 | H81: =G81-(G81*M81) -> 175.37968 | I81: =H81+(H81*L81) -> 222.5042 | J81: =I81*F81 -> 20394.735 | L81: 0.2687 | M81: 0.04420035
A82: 4.2.3 | B82: CPU2520 | C82: Próprio | D82: PAREDE COM SISTEMA EM CHAPAS DE GESSO RU PARA DRYWALL COM ISOLAMENTO ACUSTICO, USO | E82: m² | F82: 10.56 | G82: 285.27 | H82: =G82-(G82*M82) -> 272.66097 | I82: =H82+(H82*L82) -> 345.92497 | J82: =I82*F82 -> 3652.9677 | L82: 0.2687 | M82: 0.04420035
A83: 4.2.4 | B83: CPU2522 | C83: Próprio | D83: PAREDE COM SISTEMA EM CHAPAS DE GESSO ST PARA DRYWALL COM ISOLAMENTO ACUSTICO, USO INTERNO, | E83: m² | F83: 50.5 | G83: 257.05 | H83: =G83-(G83*M83) -> 245.6883 | I83: =H83+(H83*L83) -> 311.70475 | J83: =I83*F83 -> 15741.09 | L83: 0.2687 | M83: 0.04420035
A84: 4.2.5 | B84: 96374 | C84: SINAPI | D84: INSTALAÇÃO DE REFORÇO DE MADEIRA EM PAREDE DRYWALL. AF_07/2023 | E84: M | F84: 77.94 | G84: 25.56 | H84: =G84-(G84*M84) -> 24.430239 | I84: =H84+(H84*L84) -> 30.994644 | J84: =I84*F84 -> 2415.7226 | L84: 0.2687 | M84: 0.04420035
A85: 4.3 | D85: DIVISÓRIAS | J85: =J86 -> 15541.794 | M85: 0.04420035
A86: 4.3.1 | B86: 102257 | C86: SINAPI | D86: DIVISORIA SANITÁRIA, TIPO CABINE, EM PAINEL DE GRANILITE, ESP = 3CM, ASSENTADO COM ARGAMASSA | E86: m² | F86: 36.38 | G86: 352.3 | H86: =G86-(G86*M86) -> 336.72822 | I86: =H86+(H86*L86) -> 427.20709 | J86: =I86*F86 -> 15541.794 | L86: 0.2687 | M86: 0.04420035
A87: 5 | D87: COBERTURA | J87: =J88+J91+J93 -> 102452.36 | M87: 0.04420035
A88: 5.1 | D88: ESTRUTURA | J88: =J89+J90 -> 26204.045 | M88: 0.04420035
A89: 5.1.1 | B89: 100383 | C89: SINAPI | D89: FABRICAÇÃO E INSTALAÇÃO DE PONTALETES DE MADEIRA NÃO APARELHADA PARA TELHADOS COM ATÉ 2 | E89: m² | F89: 490.12 | G89: 23.35 | H89: =G89-(G89*M89) -> 22.317922 | I89: =H89+(H89*L89) -> 28.314747 | J89: =I89*F89 -> 13877.624 | L89: 0.2687 | M89: 0.04420035
A90: 5.1.2 | B90: 92543 | C90: SINAPI | D90: TRAMA DE MADEIRA COMPOSTA POR TERÇAS PARA TELHADOS DE ATÉ 2 ÁGUAS PARA TELHA ONDULADA DE | E90: m² | F90: 490.12 | G90: 20.74 | H90: =G90-(G90*M90) -> 19.823285 | I90: =H90+(H90*L90) -> 25.149801 | J90: =I90*F90 -> 12326.421 | L90: 0.2687 | M90: 0.04420035
A91: 5.2 | D91: TELHAMENTO | J91: =J92 -> 36010.503 | M91: 0.04420035
A92: 5.2.1 | B92: 94207 | C92: SINAPI | D92: TELHAMENTO COM TELHA ONDULADA DE FIBROCIMENTO E = 6 MM, COM RECOBRIMENTO LATERAL DE 1/4 DE | E92: m² | F92: 490.12 | G92: 60.59 | H92: =G92-(G92*M92) -> 57.911901 | I92: =H92+(H92*L92) -> 73.472829 | J92: =I92*F92 -> 36010.503 | L92: 0.2687 | M92: 0.04420035
A93: 5.3 | D93: COMPLEMENTOS | J93: =J94+J95+J96 -> 40237.814 | M93: 0.04420035
A94: 5.3.1 | B94: 94229 | C94: SINAPI | D94: CALHA EM CHAPA DE AÇO GALVANIZADO NÚMERO 24, DESENVOLVIMENTO DE 100 CM, INCLUSO TRANSPORTE | E94: M | F94: 154.4 | G94: 141.76 | H94: =G94-(G94*M94) -> 135.49416 | I94: =H94+(H94*L94) -> 171.90144 | J94: =I94*F94 -> 26541.582 | L94: 0.2687 | M94: 0.04420035
A95: 5.3.2 | B95: 94231 | C95: SINAPI | D95: RUFO EM CHAPA DE AÇO GALVANIZADO NÚMERO 24, CORTE DE 25 CM, INCLUSO TRANSPORTE VERTICAL. | E95: M | F95: 53.63 | G95: 45.92 | H95: =G95-(G95*M95) -> 43.89032 | I95: =H95+(H95*L95) -> 55.683649 | J95: =I95*F95 -> 2986.3141 | L95: 0.2687 | M95: 0.04420035
A96: 5.3.3 | B96: 94451 | C96: SINAPI | D96: CUMEEIRA PARA TELHA DE FIBROCIMENTO ESTRUTURAL E = 6 MM, INCLUSO ACESSÓRIOS DE FIXAÇÃO E | E96: M | F96: 74.2 | G96: 119.03 | H96: =G96-(G96*M96) -> 113.76883 | I96: =H96+(H96*L96) -> 144.33852 | J96: =I96*F96 -> 10709.918 | L96: 0.2687 | M96: 0.04420035
A97: 6 | D97: IMPERMEABILIZAÇÃO | J97: =SUM(J98:J100) -> 40341.332 | M97: 0.04420035
A98: 6.1 | B98: 98565 | C98: SINAPI | D98: PROTEÇÃO MECÂNICA DE SUPERFICIE HORIZONTAL COM ARGAMASSA DE CIMENTO E AREIA, TRAÇO 1:3, | E98: m² | F98: 107.01 | G98: 53.54 | H98: =G98-(G98*M98) -> 51.173513 | I98: =H98+(H98*L98) -> 64.923836 | J98: =I98*F98 -> 6947.4997 | L98: 0.2687 | M98: 0.04420035
A99: 6.2 | B99: 98556 | C99: SINAPI | D99: IMPERMEABILIZAÇÃO DE SUPERFÍCIE COM ARGAMASSA POLIMÉRICA / MEMBRANA ACRÍLICA, 4 DEMÃOS, | E99: m² | F99: 222.3 | G99: 61.09 | H99: =G99-(G99*M99) -> 58.389801 | I99: =H99+(H99*L99) -> 74.07914 | J99: =I99*F99 -> 16467.793 | L99: 0.2687 | M99: 0.04420035
A100: 6.3 | B100: 98555 | C100: SINAPI | D100: IMPERMEABILIZAÇÃO DE SUPERFÍCIE COM ARGAMASSA POLIMÉRICA / MEMBRANA ACRÍLICA, 3 DEMÃOS. | E100: m² | F100: 416.29 | G100: 33.53 | H100: =G100-(G100*M100) -> 32.047962 | I100: =H100+(H100*L100) -> 40.65925 | J100: =I100*F100 -> 16926.039 | L100: 0.2687 | M100: 0.04420035
A101: 7 | D101: ESQUADRIAS | J101: =J102+J107+J117+J120 -> 255123.7 | M101: 0.04420035
A102: 7.1 | D102: ESQUADRIAS DE MADEIRA | J102: =J103 -> 62613.232 | M102: 0.04420035
A103: 7.1.1 | D103: PORTAS DE MADEIRA | J103: =SUM(J104:J106) -> 62613.232 | M103: 0.04420035
...

Sheet CPU REV_1
A1: PLANILHA DE COMPOSIÇÕES UNITÁRIAS
A2: Secretaria de Atenção Especializada à Saúde BDI Geral: Encargo Social Mensalista: Data:
A3: Centro de Atenção Psicossocial - Porte 1, no município de Coremas/PB - L7 ENGENHARIA LTDA 26,87% 69,85% 12/12/2025 Bancos: Encargo Social Horista: 113,60% SINAPI (09/2025) - CPOS/CDHU (09/2025) - SBC (12/2025) - ORSE (09/2025) - IOPES (08/2025) - EMOP (10/2025) - SETOP (07/2025) - SEINFRA (028) - AGETOP CIVIL (08/2025) - AGESUL (06/2025)
A4: Composições Principais
A5: 1.1.1 | B5: Código | C5: Banco | D5: Descrição | F5: Tipo | J5: Und | L5: Quant. | M5: Valor Unit | O5: Valor Unit. c Desconto | P5: Total
A6: Composição | B6: CPU2526 | C6: Próprio | D6: LOCAÇÃO DE CONTAINER TIPO DEPÓSITO - ÁREA MÍNIMA DE 13,80 M2 | F6: CANT - CANTEIRO | J6: UNXMÊS | L6: 1 | M6: 967.29 | O6: =SUM(O7:O10) -> 905.31903 | P6: =SUM(P7:P10) -> 918.41345
A7: Composição A | B7: 88316 | C7: SINAPI | D7: SERVENTE COM ENCARGOS COMPLEMENTARES | F7: SEDI - SERVIÇOS | J7: H | L7: 1.32 | M7: 21.32 | O7: =M7-(M7*T7) -> 20.242687 | P7: =O7*L7 -> 26.720346 | T7: 0.050530643
A8: Composição A | B8: 88247 | C8: SINAPI | D8: AUXILIAR DE ELETRICISTA COM ENCARGOS COMPLEMENTARES | F8: SEDI - SERVIÇOS | J8: H | L8: 1.32 | M8: 22.63 | O8: =M8-(M8*T8) -> 21.486492 | P8: =O8*L8 -> 28.362169 | T8: 0.050530643
A9: Composição A | B9: 88264 | C9: SINAPI | D9: ELETRICISTA COM ENCARGOS COMPLEMENTARES | F9: SEDI - SERVIÇOS | J9: H | L9: 0.99 | M9: 27.27 | O9: =M9-(M9*T9) -> 25.892029 | P9: =O9*L9 -> 25.633109 | T9: 0.050530643
A10: Insumo | B10: A.12.000.021099 | C10: CPOS/CDHU | D10: CONTAINER DEPÓSITO, MÓDULO METÁLICO EM AÇO GALVANIZADO DE 6,0X2,3X2,5M, VÃO LIVRE, PISO DE CONCRETO, CIMENTADO, MADEIRA OU MATERIAL EQUIVALENTE | F10: Material | J10: unxmês | L10: 1 | M10: 882.28 | O10: =M10-(M10*T10) -> 837.69782 | P10: =O10*L10 -> 837.69782 | T10: 0.050530643
A11: 2
A12: MO sem LS | H12: LS => | L12: 0 | N12: MO com LS =>
A13: Valor do BDI | L13: Valor com BDI
A14: Observação Composição de Referência: 02.02.150 CPOS/CDHUA composição foi ajustada para utilizar os insumos e a mão de obra conforme a base SINAPI, garantindo maior aderência aos parâmetros de mercado e normativas vigentes. Apenas os insumos que não possuem correspondência na base SINAPI foram mant
A16: 1.1.2 | B16: Código | C16: Banco | D16: Descrição | F16: Tipo | J16: Und | L16: Quant. | M16: Valor Unit | O16: Valor Unit. c Desconto | P16: Total
A17: Composição | B17: CPU2527 | C17: Próprio | D17: BARRACÃO ABERTO PARA APOIO À PRODUÇÃO (CARPINTARIA, CENTRAL DE ARMAÇÃO, OFICINA, ETC.) C/ TESOURAS, TELHA 4MM, PISO EM CONCRETO DESEMPOLADO | F17: CANT - CANTEIRO | J17: m² | L17: 1 | M17: 245.8 | O17: =SUM(O18:O22) -> 2363.4001 | P17: =SUM(P18:P22) -> 233.38223
A18: Composição A | B18: 94207 | C18: SINAPI | D18: TELHAMENTO COM TELHA ONDULADA DE FIBROCIMENTO E = 6 MM, COM RECOBRIMENTO LATERAL DE 1/4 DE ONDA PARA TELHADO COM INCLINAÇÃO MAIOR QUE 10°, COM ATÉ 2 ÁGUAS, INCLUSO IÇAMENTO. AF_07/2019 | F18: COBE - COBERTURA | J18: m² | L18: 1 | M18: 60.59 | O18: =M18-(M18*T18) -> 57.528348 | P18: =O18*L18 -> 57.528348 | T18: 0.050530643
A19: Composição A | B19: 101747 | C19: SINAPI | D19: PISO EM CONCRETO 20 MPA PREPARO MECÂNICO, ESPESSURA 7CM. AF_09/2020 | F19: PISO - PISOS | J19: m² | L19: 1 | M19: 91.04 | O19: =M19-(M19*T19) -> 86.43969 | P19: =O19*L19 -> 86.43969 | T19: 0.050530643
A20: Composição A | B20: 92562 | C20: SINAPI | D20: FABRICAÇÃO E INSTALAÇÃO DE TESOURA INTEIRA EM MADEIRA NÃO APARELHADA, VÃO DE 10 M, PARA TELHA ONDULADA DE FIBROCIMENTO, METÁLICA, PLÁSTICA OU TERMOACÚSTICA, INCLUSO IÇAMENTO. AF_07/2019 | F20: COBE - COBERTURA | J20: UN | L20: 0.03 | M20: 2312.76 | O20: =M20-(M20*T20) -> 2195.8947 | P20: =O20*L20 -> 65.876842 | T20: 0.050530643
A21: Composição A | B21: 97083 | C21: SINAPI | D21: COMPACTAÇÃO MECÂNICA DE SOLO PARA EXECUÇÃO DE RADIER, PISO DE CONCRETO OU LAJE SOBRE SOLO, COM COMPACTADOR DE SOLOS A PERCUSSÃO. AF_09/2021 | F21: FUES - FUNDAÇÕES | J21: m² | L21: 1 | M21: 3.29 | O21: =M21-(M21*T21) -> 3.1237542 | P21: =O21*L21 -> 3.1237542 | T21: 0.050530643
A22: Composição A | B22: 100382 | C22: SINAPI | D22: FABRICAÇÃO E INSTALAÇÃO DE PONTALETES DE MADEIRA NÃO APARELHADA PARA TELHADOS COM ATÉ 2 ÁGUAS E COM TELHA ONDULADA DE FIBROCIMENTO, ALUMÍNIO OU PLÁSTICA EM EDIFÍCIO RESIDENCIAL TÉRREO, INCLUSO TRANSPORTE | F22: COBE - COBERTURA | J22: m² | L22: 1 | M22: 21.5 | O22: =M22-(M22*T22) -> 20.413591 | P22: =O22*L22 -> 20.413591 | T22: 0.050530643
A23: Observação | E23: MO sem LS => Valor do BDI => | I23: LS => 0,00 MO com LS => Valor com BDI => | T23: 0.050530643
A24: Composição de Referência: ORSE 11703. A composição foi ajustada para utilizar os insumos e a mão de obra conforme a base SINAPI, garantindo maior aderência aos parâmetros de mercado e normativas vigentes. Apenas os insumos que não possuem correspondência na base SINAPI foram mantidos conf | T24: 0.050530643
T25: 0.050530643
A26: 1.1.3 | B26: Código | C26: Banco | D26: Descrição | F26: Tipo | J26: Und | L26: Quant. | M26: Valor Unit | O26: Valor Unit. c Desconto | P26: Total | T26: 0.050530643
A27: Composição | B27: CPU2528 | C27: Próprio | D27: LOCAÇÃO DE CONTAINER - BANHEIRO COM CHUVEIROS E VASOS - 4,30 X 2,30M | F27: CANT - CANTEIRO | J27: MÊS | L27: 1 | M27: 0 | O27: =O28 -> 913.63638 | P27: =P28 -> 913.63638 | T27: 0.050530643
A28: Insumo | B28: 10777 | C28: SINAPI | D28: LOCACAO DE CONTAINER 2,30 X 4,30 M, ALT. 2,50 M, PARA SANITARIO, COM 3 BACIAS, 4 CHUVEIROS, 1 LAVATORIO E 1 MICTORIO (NAO INCLUI MOBILIZACAO/DESMOBILIZACAO) | F28: Equipamento | J28: MES | L28: 1 | M28: 962.26 | O28: =M28-(M28*T28) -> 913.63638 | P28: =O28*L28 -> 913.63638 | T28: 0.050530643
A29: Observação | E29: MO sem LS => Valor do BDI => | I29: LS => 0,00 MO com LS => Valor com BDI => | T29: 0.050530643
A30: Composição de Referência: ORSE 4656. A composição foi ajustada para utilizar os insumos e a mão de obra conforme a base SINAPI, garantindo maior aderência aos parâmetros de mercado e normativas vigentes. Apenas os insumos que não possuem correspondência na base SINAPI foram mantidos confo | T30: 0.050530643
T31: 0.050530643
A32: 1.1.4 | B32: Código | C32: Banco | D32: Descrição | F32: Tipo | J32: Und | L32: Quant. | M32: Valor Unit | P32: Total | T32: 0.050530643
A33: Composição | B33: CPU2529 | C33: Próprio | D33: BARRACAO PARA REFEITORIO EM OBRAS EM COMPENSADO | F33: CANT - CANTEIRO | J33: m² | L33: 1 | M33: 1057.99 | O33: =SUM(O34:O43) -> 174.52196 | P33: =SUM(P34:P43) -> 1004.5281 | T33: 0.050530643
A34: Composição A | B34: 88316 | C34: SINAPI | D34: SERVENTE COM ENCARGOS COMPLEMENTARES | F34: SEDI - SERVIÇOS | J34: H | L34: 13.053 | M34: 21.32 | O34: =M34-(M34*R34) -> 20.242687 | P34: =O34*L34 -> 264.22779 | R34: 0.050530643 | T34: 0.050530643
A35: Composição A | B35: 88239 | C35: SINAPI | D35: AJUDANTE DE CARPINTEIRO COM ENCARGOS COMPLEMENTARES | F35: SEDI - SERVIÇOS | J35: H | L35: 12.075 | M35: 22 | O35: =M35-(M35*R35) -> 20.888326 | P35: =O35*L35 -> 252.22653 | R35: 0.050530643 | T35: 0.050530643
A36: Composição A | B36: 88262 | C36: SINAPI | D36: CARPINTEIRO DE FORMAS COM ENCARGOS COMPLEMENTARES | F36: SEDI - SERVIÇOS | J36: H | L36: 8.419 | M36: 26.48 | O36: =M36-(M36*R36) -> 25.141949 | P36: =O36*L36 -> 211.67006 | R36: 0.050530643 | T36: 0.050530643
A37: Insumo | B37: 20205 | C37: SINAPI | D37: RIPA APARELHADA *1,5 X 5* CM, EM MACARANDUBA/MASSARANDUBA, ANGELIM OU EQUIVALENTE DA REGIAO | F37: Material | J37: M | L37: 4.949 | M37: 2.9 | O37: =M37-(M37*R37) -> 2.7534611 | P37: =O37*L37 -> 13.626879 | R37: 0.050530643 | T37: 0.050530643
A38: Insumo | B38: 5068 | C38: SINAPI | D38: PREGO DE ACO POLIDO COM CABECA 17 X 21 (2 X 11) | F38: Material | J38: KG | L38: 0.421 | M38: 21.36 | O38: =M38-(M38*R38) -> 20.280665 | P38: =O38*L38 -> 8.5381602 | R38: 0.050530643 | T38: 0.050530643
A39: Insumo | B39: 39027 | C39: SINAPI | D39: PREGO DE ACO POLIDO COM CABECA 19 X 36 (3 1/4 X 9) | F39: Material | J39: KG | L39: 1.68 | M39: 21.34 | O39: =M39-(M39*R39) -> 20.261676 | P39: =O39*L39 -> 34.039616 | R39: 0.050530643 | T39: 0.050530643
A40: Insumo | B40: 43614 | C40: SINAPI | D40: TABUA NAO APARELHADA *2,5 X 15* CM, EM MACARANDUBA/MASSARANDUBA, ANGELIM OU EQUIVALENTE DA REGIAO - BRUTA | F40: Material | J40: M | L40: 6.26 | M40: 13.26 | O40: =M40-(M40*R40) -> 12.589964 | P40: =O40*L40 -> 78.813173 | R40: 0.050530643 | T40: 0.050530643
A41: Insumo | B41: 2420 | C41: SINAPI | D41: DOBRADICA EM ACO/FERRO, 3" X 2 1/2", E= 1,9 A 2 MM, SEM ANEL, CROMADO OU ZINCADO, TAMPA BOLA, COM PARAFUSOS | F41: Material | J41: UN | L41: 0.48 | M41: 18.19 | O41: =M41-(M41*R41) -> 17.270848 | P41: =O41*L41 -> 8.2900068 | R41: 0.050530643 | T41: 0.050530643
A42: Insumo | B42: 4491 | C42: SINAPI | D42: PONTALETE *7,5 X 7,5* CM EM PINUS, MISTA OU EQUIVALENTE DA REGIAO - BRUTA | F42: Material | J42: M | L42: 10.12 | M42: 11.76 | O42: =M42-(M42*R42) -> 11.16576 | P42: =O42*L42 -> 112.99749 | R42: 0.050530643 | T42: 0.050530643
A43: Insumo | B43: 7213 | C43: SINAPI | D43: TELHA DE FIBROCIMENTO ONDULADA E = 4 MM, DE 2,44 X 0,50 M (SEM AMIANTO) | F43: Material | J43: M² | L43: 0.84 | M43: 25.2 | O43: =M43-(M43*R43) -> 23.926628 | P43: =O43*L43 -> 20.098367 | R43: 0.050530643 | T43: 0.050530643
A44: MO sem LS | H44: LS => | L44: 0 | N44: MO com LS => | T44: 0.050530643
A45: => | T45: 0.050530643
A46: Valor do BDI | L46: Valor com BDI | T46: 0.050530643
A47: => | L47: => | T47: 0.050530643
A48: MO sem LS | H48: LS => | L48: 0 | N48: MO com LS => | T48: 0.050530643
A49: => | T49: 0.050530643
T50: 0.050530643
A51: 1.1.9 | B51: Código | C51: Banco | D51: Descrição | F51: Tipo | J51: Und | L51: Quant. | M51: Valor Unit | P51: Total | T51: 0.050530643
A52: Composição | B52: CPU2530 | C52: Próprio | D52: REMOÇÃO DE ENTULHO SEPARADO DE OBRA COM CAÇAMBA METÁLICA - TERRA, ALVENARIA, CONCRETO, ARGAMASSA, MADEIRA, PAPEL, PLÁSTICO OU METAL | F52: CANT - CANTEIRO DE OBRAS | J52: m³ | L52: 1 | M52: 110.78 | O52: =SUM(O53:O54) -> 113.28119 | P52: =SUM(P53:P54) -> 105.18411 | T52: 0.050530643
A53: Composição A | B53: 88316 | C53: SINAPI | D53: SERVENTE COM ENCARGOS COMPLEMENTARES | F53: SEDI - SERVIÇOS DIVERSOS | J53: H | L53: 0.6 | M53: 21.32 | O53: =M53-(M53*R53) -> 20.242687 | P53: =O53*L53 -> 12.145612 | R53: 0.050530643 | T53: 0.050530643
A54: Insumo | B54: A.05.000.020358 | C54: CPOS/CDHU | D54: REMOÇÃO DE ENTULHO DE OBRA, TERRA, ALVENARIA, CONCRETO, ARGAMASSA, MADEIRA, PAPEL, PLÁSTICO, METAL, CAPACIDADE DE 4M³ | F54: Material | J54: m³ | L54: 1 | M54: 97.99 | O54: =M54-(M54*R54) -> 93.038502 | P54: =O54*L54 -> 93.038502 | R54: 0.050530643 | T54: 0.050530643
A55: MO sem LS => | H55: LS => | L55: 0 | N55: MO com LS => | T55: 0.050530643
A56: Valor do BDI => | L56: Valor com BDI => | T56: 0.050530643
T57: 0.050530643
A58: 1.3.1 | B58: Código | C58: Banco | D58: Descrição | F58: Tipo | J58: Und | L58: Quant. | M58: Valor Unit | P58: Total | T58: 0.050530643
A59: Composição | B59: CPU2531 | C59: Próprio | D59: MOBILIZACAO E DESMOBILIZACAO DE CANTEIRO | F59: CANT - CANTEIRO | J59: UN | L59: 1 | M59: 6464.57 | O59: =SUM(O60:O68) -> 210.45938 | P59: =SUM(P60:P68) -> 6137.9133 | T59: 0.050530643
A60: Composição A | B60: 88264 | C60: SINAPI | D60: ELETRICISTA COM ENCARGOS COMPLEMENTARES | F60: SEDI - SERVIÇOS | J60: H | L60: 28.7 | M60: 27.27 | O60: =M60-(M60*T60) -> 25.892029 | P60: =O60*L60 -> 743.10124 | T60: 0.050530643
A61: Composição A | B61: 88247 | C61: SINAPI | D61: AUXILIAR DE ELETRICISTA COM ENCARGOS COMPLEMENTARES | F61: SEDI - SERVIÇOS | J61: H | L61: 57.4 | M61: 22.63 | O61: =M61-(M61*T61) -> 21.486492 | P61: =O61*L61 -> 1233.3246 | T61: 0.050530643
A62: Composição A | B62: 88325 | C62: SINAPI | D62: VIDRACEIRO COM ENCARGOS COMPLEMENTARES | F62: SEDI - SERVIÇOS | J62: H | L62: 12.756 | M62: 22.22 | O62: =M62-(M62*T62) -> 21.097209 | P62: =O62*L62 -> 269.116 | T62: 0.050530643
A63: Composição A | B63: 88239 | C63: SINAPI | D63: AJUDANTE DE CARPINTEIRO COM ENCARGOS COMPLEMENTARES | F63: SEDI - SERVIÇOS | J63: H | L63: 18.07 | M63: 22 | O63: =M63-(M63*T63) -> 20.888326 | P63: =O63*L63 -> 377.45205 | T63: 0.050530643
A64: Composição A | B64: 88261 | C64: SINAPI | D64: CARPINTEIRO DE ESQUADRIA COM ENCARGOS COMPLEMENTARES | F64: SEDI - SERVIÇOS | J64: H | L64: 18.07 | M64: 25.53 | O64: =M64-(M64*T64) -> 24.239953 | P64: =O64*L64 -> 438.01594 | T64: 0.050530643
A65: Composição A | B65: 88267 | C65: SINAPI | D65: ENCANADOR OU BOMBEIRO HIDRÁULICO COM ENCARGOS COMPLEMENTARES | F65: SEDI - SERVIÇOS | J65: H | L65: 20.196 | M65: 26.19 | O65: =M65-(M65*T65) -> 24.866602 | P65: =O65*L65 -> 502.2059 | T65: 0.050530643
A66: Composição A | B66: 88310 | C66: SINAPI | D66: PINTOR COM ENCARGOS COMPLEMENTARES | F66: SEDI - SERVIÇOS | J66: H | L66: 13.818 | M66: 28.58 | O66: =M66-(M66*T66) -> 27.135834 | P66: =O66*L66 -> 374.96296 | T66: 0.050530643
A67: Composição A | B67: 88316 | C67: SINAPI | D67: SERVENTE COM ENCARGOS COMPLEMENTARES | F67: SEDI - SERVIÇOS | J67: H | L67: 100.914 | M67: 21.32 | O67: =M67-(M67*T67) -> 20.242687 | P67: =O67*L67 -> 2042.7705 | T67: 0.050530643
A68: Composição A | B68: 88273 | C68: SINAPI | D68: MARCENEIRO COM ENCARGOS COMPLEMENTARES | F68: SEDI - SERVIÇOS | J68: H | L68: 6.378 | M68: 25.92 | O68: =M68-(M68*T68) -> 24.610246 | P68: =O68*L68 -> 156.96415 | T68: 0.050530643
A69: MO sem LS => Valor do BDI => | K69: LS => 0,00 MO com LS => Valor com BDI => | T69: 0.050530643
A70: Observação | T70: 0.050530643
A71: Composição de Referência: SBC 012689. A composição foi ajustada para utilizar os insumos e a mão de obra conforme a base SINAPI, garantindo maior aderência aos parâmetros de mercado e normativas vigentes. Apenas os insumos que não possuem correspondência na base SINAPI foram mantidos confo | T71: 0.050530643
T72: 0.050530643
A73: 1.4.1 | B73: Código | C73: Banco | D73: Descrição | F73: Tipo | J73: Und | L73: Quant. | M73: Valor Unit | P73: Total | T73: 0.050530643
A74: Composição | B74: CPU1926 | C74: Próprio | D74: LOCACAO DE ANDAIME METALICO TIPO FACHADEIRO, PECAS COM APROXIMADAMENTE 1,20 M DE LARGURA E 2,0 M DE ALTURA, INCLUINDO DIAGONAIS EM X, BARRAS DE LIGACAO, SAPATAS E DEMAIS ITENS NECESSARIOS A MONTAGEM, | F74: ASTU - ASSENTAME | J74: M2XMÊS | L74: 1 | M74: 21.58 | O74: =SUM(O75:O83) -> 278.51734 | P74: =SUM(P75:P83) -> 118.20769 | T74: 0.050530643
A75: Composição A | B75: 97063 | C75: SINAPI | D75: MONTAGEM E DESMONTAGEM DE ANDAIME MODULAR FACHADEIRO, COM PISO METÁLICO, PARA EDIFÍCIOS COM MULTIPLOS PAVIMENTOS (EXCLUSIVE ANDAIME E LIMPEZA). AF_03/2024 | F75: SEDI - SERVIÇOS | J75: m² | L75: 0.416 | M75: 16.17 | O75: =M75-(M75*T75) -> 15.352919 | P75: =O75*L75 -> 6.3868145 | T75: 0.050530643
A76: Insumo | B76: 20193 | C76: SINAPI | D76: LOCACAO DE ANDAIME METALICO TIPO FACHADEIRO, PECAS COM APROXIMADAMENTE 1,20 M DE LARGURA E 2,0 M DE ALTURA, INCLUINDO DIAGONAIS EM X, BARRAS DE LIGACAO, SAPATAS E DEMAIS ITENS NECESSARIOS A MONTAGEM (NAO | F76: Equipamento | J76: M2/MES | L76: 1 | M76: 14.85 | O76: =M76-(M76*T76) -> 14.09962 | P76: =O76*L76 -> 14.09962 | T76: 0.050530643
A77: MO sem LS | H77: LS => | L77: 0 | N77: MO com LS => | T77: 0.050530643
A78: => | T78: 0.050530643
A79: Valor do BDI | L79: Valor com BDI | T79: 0.050530643
A80: => | L80: => | T80: 0.050530643
T81: 0.050530643
A82: 2.16 | B82: Código | C82: Banco | D82: Descrição | F82: Tipo | J82: Und | L82: Quant. | M82: Valor Unit | P82: Total | T82: 0.050530643
A83: Composição | B83: CPU2532 | C83: Próprio | D83: CONTROLE TECNOLOGICO DE CONCRETOS | F83: FUES - FUNDAÇÕES | J83: m³ | L83: 1 | M83: 102.92 | O83: =SUM(O84:O92) -> 249.0648 | P83: =SUM(P84:P92) -> 97.721257 | T83: 0.050530643
A84: Composição A | B84: 90776 | C84: SINAPI | D84: ENCARREGADO GERAL COM ENCARGOS COMPLEMENTARES | F84: SEDI - SERVIÇOS | J84: H | L84: 0.039 | M84: 25.91 | O84: =M84-(M84*T84) -> 24.600751 | P84: =O84*L84 -> 0.95942929 | T84: 0.050530643
A85: Composição A | B85: 90778 | C85: SINAPI | D85: ENGENHEIRO CIVIL PLENO COM ENCARGOS COMPLEMENTARES | F85: SEDI - SERVIÇOS | J85: H | L85: 0.009 | M85: 135.72 | O85: =M85-(M85*T85) -> 128.86198 | P85: =O85*L85 -> 1.1597578 | T85: 0.050530643
A86: Insumo | B86: 8823 | C86: SBC | D86: ENSAIO - ENSAIO DE RESISTENCIA A COMPRESSAO SIMPLES - CONCRETO | F86: Material | J86: UN | L86: 1 | M86: 100.69 | O86: =M86-(M86*T86) -> 95.60207 | P86: =O86*L86 -> 95.60207 | T86: 0.050530643
A87: MO sem LS | H87: LS => | L87: 0 | N87: MO com LS => | T87: 0.050530643
A88: => | T88: 0.050530643
A89: Valor do BDI | L89: Valor com BDI | T89: 0.050530643
A90: => | L90: => | T90: 0.050530643
T91: 0.050530643
A92: 3.1.5 | B92: Código | C92: Banco | D92: Descrição | F92: Tipo | J92: Und | L92: Quant. | M92: Valor Unit | P92: Total | T92: 0.050530643
A93: Composição | B93: CPU2284 | C93: Próprio | D93: CONCRETAGEM DE PILARES, FCK = 30 MPA, COM USO DE BOMBA - LANÇAMENTO, ADENSAMENTO E ACABAMENTO. AF_02/2022_PS | F93: FUES - FUNDAÇÕES | J93: m³ | L93: 1 | M93: 705.68 | O93: =SUM(O94:O102) -> 645.01251 | P93: =SUM(P94:P102) -> 670.02511 | T93: 0.050530643
A94: Composição A | B94: 90587 | C94: SINAPI | D94: VIBRADOR DE IMERSÃO, DIÂMETRO DE PONTEIRA 45MM, MOTOR ELÉTRICO TRIFÁSICO POTÊNCIA DE 2 CV - CHI DIURNO. AF_06/2015 | F94: CHOR - CUSTOS | J94: CHI | L94: 0.13 | M94: 0.56 | O94: =M94-(M94*T94) -> 0.53170284 | P94: =O94*L94 -> 0.069121369 | T94: 0.050530643
A95: Composição A | B95: 88316 | C95: SINAPI | D95: SERVENTE COM ENCARGOS COMPLEMENTARES | F95: SEDI - | J95: H | L95: 1.345 | M95: 21.32 | O95: =M95-(M95*T95) -> 20.242687 | P95: =O95*L95 -> 27.226414 | T95: 0.050530643
A96: Composição A | B96: 90586 | C96: SINAPI | D96: VIBRADOR DE IMERSÃO, DIÂMETRO DE PONTEIRA 45MM, MOTOR ELÉTRICO TRIFÁSICO POTÊNCIA DE 2 CV - CHP DIURNO. | F96: CHOR - | J96: CHP | L96: 0.094 | M96: 1.31 | O96: =M96-(M96*T96) -> 1.2438049 | P96: =O96*L96 -> 0.11691766 | T96: 0.050530643
A97: Composição A | B97: 88262 | C97: SINAPI | D97: CARPINTEIRO DE FORMAS COM ENCARGOS COMPLEMENTARES | F97: SEDI - | J97: H | L97: 0.224 | M97: 26.48 | O97: =M97-(M97*T97) -> 25.141949 | P97: =O97*L97 -> 5.6317965 | T97: 0.050530643
A98: Composição A | B98: 88309 | C98: SINAPI | D98: PEDREIRO COM ENCARGOS COMPLEMENTARES | F98: SEDI - | J98: H | L98: 0.224 | M98: 26.9 | O98: =M98-(M98*T98) -> 25.540726 | P98: =O98*L98 -> 5.7211226 | T98: 0.050530643
A99: Insumo | B99: 1525 | C99: SINAPI | D99: CONCRETO USINADO BOMBEAVEL, CLASSE DE RESISTENCIA C30, BRITA 0 E 1, SLUMP = 100 +/- 20 MM, COM BOMBEAMENTO | F99: Material | J99: M³ | L99: 1.103 | M99: 602.77 | O99: =M99-(M99*T99) -> 572.31164 | P99: =O99*L99 -> 631.25974 | T99: 0.050530643
A100: MO sem LS | H100: LS => | L100: 0 | N100: MO com LS => | T100: 0.050530643
A101: Valor do BDI | L101: Valor com BDI | T101: 0.050530643
...

Sheet CRONOGRAMA REV_1
A1: CRONOGRAMA
A5: Secretaria de Atenção Especializada à Saúde BDI Geral: 26,87% Encargo Social Mensalista: 69,85% Encargo Social Horista: 113,60% Data: 12/12/2025
A6: Centro de Atenção Psicossocial - Porte 1, no município de Coremas/PB Bancos: SINAPI (09/2025) - CPOS/CDHU (09/2025) - SBC (12/2025) - ORSE (09/2025) - IOPES (08/2025) - EMOP (10/2025) - SETOP (07/2025) - 113,60% SEINFRA (028) - AGETOP CIVIL (08/2025) - AGESUL (06/2025)
A9: ITEM | B9: DESCRIÇÃO | E9: PREÇO | G9: % | H9: Mês 01 | J9: Mês 02 | M9: Mês 03 | O9: Mês 04 | Q9: Mês 05 | T9: Mês 06 | V9: Mês 07 | X9: Mês 08 | AA9: Mês 09 | AC9: Mês 10 | AE9: Mês 11
H10: Concedente R$ | I10: % | J10: Concedente R$ | L10: % | M10: Concedente R$ | N10: % | O10: Concedente R$ | P10: % | Q10: Concedente R$ | S10: % | T10: Concedente R$ | U10: % | V10: Concedente R$ | W10: % | X10: Concedente R$ | Z10: % | AA10: Concedente R$ | AB10: % | AC10: Concedente R$ | AD10: % | AE10: Concedente R$ | AG10: %
A11: 1 | B11: SERVIÇOS PRELIMINARES E INDIRETOS | E11: R$ | F11: ='SINTÉTICO REV_01'!J6 -> 162825.53 | G11: =F11/F33 -> 0.066453675 | H11: =(F11*I11) -> 81412.763 | I11: 0.5 | J11: =F11*L11 -> 81412.763 | L11: 0.5 | M11: - | O11: - | Q11: - | T11: - | V11: - | AA11: - | AC11: -
A12: 2 | B12: FUNDAÇÃO | E12: R$ | F12: ='SINTÉTICO REV_01'!J24 -> 207935.32 | G12: =F12/F33 -> 0.084864251 | H12: =(F12*I12) -> 62380.596 | I12: 0.3 | J12: =F12*L12 -> 62380.596 | L12: 0.3 | M12: =(F12*N12) -> 83174.128 | N12: 0.4 | O12: - | Q12: - | T12: - | V12: - | AA12: - | AC12: -
A13: 3 | B13: ESTRUTURA | E13: R$ | F13: ='SINTÉTICO REV_01'!J41 -> 300443.72 | G13: =F13/F33 -> 0.12261953 | H13: =(F13*I13) -> 75110.93 | I13: 0.25 | J13: =F13*L13 -> 75110.93 | L13: 0.25 | M13: =(F13*N13) -> 150221.86 | N13: 0.5 | O13: - | Q13: - | T13: - | V13: - | AA13: - | AC13: -
A14: 4 | B14: ALVENARIA, VEDAÇÕES E DIVISÓRIAS | E14: R$ | F14: ='SINTÉTICO REV_01'!J72 -> 195823.09 | G14: =F14/F33 -> 0.079920908 | H14: - | J14: =F14*L14 -> 48955.771 | L14: 0.25 | M14: =(F14*N14) -> 48955.771 | N14: 0.25 | O14: =(F14*P14) -> 48955.771 | P14: 0.25 | Q14: =(F14*S14) -> 48955.771 | R14: =(I14*S14) -> 0 | S14: 0.25 | T14: - | V14: - | AA14: - | AC14: -
A15: 5 | B15: COBERTURA | E15: R$ | F15: ='SINTÉTICO REV_01'!J87 -> 102452.36 | G15: =F15/F33 -> 0.04181369 | H15: - | J15: - | M15: - | O15: =(F15*P15) -> 51226.181 | P15: 0.5 | Q15: =(F15*S15) -> 51226.181 | R15: =(I15*S15) -> 0 | S15: 0.5 | T15: - | V15: - | AA15: - | AC15: -
A16: 6 | B16: IMPERMEABILIZAÇÃO | E16: R$ | F16: ='SINTÉTICO REV_01'!J97 -> 40341.332 | G16: =F16/F33 -> 0.016464432 | H16: - | J16: - | M16: - | O16: =(F16*P16) -> 20170.666 | P16: 0.5 | Q16: =(F16*S16) -> 20170.666 | R16: =(I16*S16) -> 0 | S16: 0.5 | T16: - | V16: - | AA16: - | AC16: -
A17: 7 | B17: ESQUADRIAS | E17: R$ | F17: ='SINTÉTICO REV_01'!J101 -> 255123.7 | G17: =F17/F33 -> 0.10412316 | H17: - | J17: - | M17: - | O17: =(F17*P17) -> 76537.11 | P17: 0.3 | Q17: =(F17*S17) -> 76537.11 | R17: =(I17*S17) -> 0 | S17: 0.3 | T17: =F17*U17 -> 102049.48 | U17: 0.4 | V17: - | X17: - | AA17: - | AC17: -
A18: 8 | B18: REVESTIMENTO DE PAREDE | E18: R$ | F18: ='SINTÉTICO REV_01'!J128 -> 105077.27 | G18: =F18/F33 -> 0.042884989 | H18: - | J18: - | M18: - | O18: =(F18*P18) -> 52538.636 | P18: 0.5 | Q18: =(F18*S18) -> 52538.636 | R18: =(I18*S18) -> 0 | S18: 0.5 | T18: - | V18: - | X18: - | AA18: - | AC18: - | AE18: -
A19: 9 | B19: REVESTIMENTO DE PISO INTERNO | E19: R$ | F19: ='SINTÉTICO REV_01'!J135 -> 138994.45 | G19: =F19/F33 -> 0.056727542 | H19: - | J19: - | M19: - | O19: =(F19*P19) -> 41698.334 | P19: 0.3 | Q19: =(F19*S19) -> 41698.334 | R19: =(I19*S19) -> 0 | S19: 0.3 | T19: =F19*U19 -> 55597.779 | U19: 0.4 | V19: - | X19: - | AA19: - | AC19: - | AE19: -
A20: 10 | B20: REVESTIMENTO DE PISO EXTERNO | E20: R$ | F20: ='SINTÉTICO REV_01'!J144 -> 37635.545 | G20: =F20/F33 -> 0.015360124 | H20: - | J20: - | M20: - | O20: - | Q20: - | T20: =F20*U20 -> 37635.545 | U20: 1 | V20: - | X20: - | AA20: - | AC20: - | AE20: -
A21: 11 | B21: REVESTIMENTO DE TETO | E21: R$ | F21: ='SINTÉTICO REV_01'!J147 -> 45069.659 | G21: =F21/F33 -> 0.018394195 | H21: - | J21: - | M21: - | O21: - | Q21: - | T21: =F21*U21 -> 22534.829 | U21: 0.5 | V21: =F21*W21 -> 22534.829 | W21: 0.5 | X21: - | AA21: - | AC21: - | AE21: -
A22: 12 | B22: PINTURA | E22: R$ | F22: ='SINTÉTICO REV_01'!J150 -> 82409.807 | G22: =F22/F33 -> 0.033633759 | H22: - | J22: - | M22: - | O22: - | Q22: - | T22: =F22*U22 -> 41204.903 | U22: 0.5 | V22: =F22*W22 -> 41204.903 | W22: 0.5 | X22: - | AA22: - | AC22: - | AE22: -
A23: 13 | B23: MARMORARIA | E23: R$ | F23: ='SINTÉTICO REV_01'!J163 -> 8379.8122 | G23: =F23/F33 -> 0.003420037 | H23: - | J23: - | M23: - | O23: - | Q23: - | T23: - | V23: =F23*W23 -> 8379.8122 | W23: 1 | X23: - | AA23: - | AC23: - | AE23: -
A24: 14 | B24: LOUÇAS, METAIS E ACESSÓRIOS | E24: R$ | F24: ='SINTÉTICO REV_01'!J166 -> 63864.558 | G24: =F24/F33 -> 0.026064922 | H24: - | J24: - | M24: - | V24: =F24*W24 -> 31932.279 | W24: 0.5 | X24: =F24*Z24 -> 31932.279 | Y24: =I24*Z24 -> 0 | Z24: 0.5 | AA24: - | AC24: - | AE24: -
A25: 15 | B25: INSTALAÇÕES HIDROSSANITÁRIAS | E25: R$ | F25: ='SINTÉTICO REV_01'!J193 -> 171422.78 | G25: =F25/F33 -> 0.069962457 | H25: - | J25: - | M25: - | V25: =F25*W25 -> 51426.834 | W25: 0.3 | X25: =F25*Z25 -> 51426.834 | Y25: =I25*Z25 -> 0 | Z25: 0.3 | AA25: =F25*AB25 -> 68569.113 | AB25: 0.4 | AC25: - | AE25: -
A26: 16 | B26: INSTALAÇÕES ELÉTRICAS | E26: R$ | F26: ='SINTÉTICO REV_01'!J309 -> 334017.29 | G26: =F26/F33 -> 0.13632185 | H26: - | J26: - | M26: - | V26: - | X26: =F26*Z26 -> 83504.324 | Y26: =I26*Z26 -> 0 | Z26: 0.25 | AA26: =F26*AB26 -> 83504.324 | AB26: 0.25 | AC26: =F26*AD26 -> 83504.324 | AD26: 0.25 | AE26: =F26*AG26 -> 83504.324 | AG26: 0.25
A27: 17 | B27: CLIMATIZAÇÃO | E27: R$ | F27: ='SINTÉTICO REV_01'!J415 -> 151556.94 | G27: =F27/F33 -> 0.061854649 | H27: - | J27: - | M27: - | V27: - | X27: =F27*Z27 -> 75778.471 | Y27: =I27*Z27 -> 0 | Z27: 0.5 | AA27: =F27*AB27 -> 75778.471 | AB27: 0.5 | AC27: - | AE27: -
A28: 18 | B28: DADOS E VOZ | E28: R$ | F28: ='SINTÉTICO REV_01'!J438 -> 21580.296 | G28: =F28/F33 -> 0.0088075258 | H28: - | J28: - | M28: - | V28: - | X28: - | AA28: - | AC28: =F28*AD28 -> 21580.296 | AD28: 1 | AE28: -
A29: 19 | B29: URBANIZAÇÃO | E29: R$ | F29: ='SINTÉTICO REV_01'!J460 -> 14283.411 | G29: =F29/F33 -> 0.0058294618 | H29: - | J29: - | M29: - | V29: - | X29: - | AA29: - | AC29: =F29*AD29 -> 14283.411 | AD29: 1 | AE29: -
A30: 20 | B30: SERVIÇOS COMPLEMENTARES | E30: R$ | F30: ='SINTÉTICO REV_01'!J468 -> 10974.113 | G30: =F30/F33 -> 0.0044788442 | H30: - | J30: - | M30: - | V30: - | X30: - | AA30: - | AE30: =F30*AG30 -> 10974.113 | AG30: 1
A33: TOTAL | E33: R$ | F33: =SUM(F11:F30) -> 2450211 | G33: =SUM(G11:G30) -> 1 | H33: =SUM(H11:H13) -> 218904.29 | I33: =H33/F33 -> 0.089340996 | J33: =SUM(J11:K14) -> 267860.06 | L33: =J33/F33 -> 0.10932122 | M33: =SUM(M12:M14) -> 282351.76 | N33: =M33/F33 -> 0.11523569 | O33: =SUM(O14:O19) -> 291126.7 | P33: =O33/F33 -> 0.11881699 | Q33: =SUM(Q14:R19) -> 291126.7 | S33: =Q33/F33 -> 0.11881699 | T33: =SUM(T19:T22,T17) -> 259022.54 | U33: =T33/F33 -> 0.10571438 | V33: =SUM(V21:V25) -> 155478.66 | W33: =V33/F33 -> 0.063455213 | X33: =SUM(X24:Y27) -> 242641.91 | Z33: =X33/F33 -> 0.099028985 | AA33: =SUM(AA25:AA27) -> 227851.91 | AB33: =AA33/F33 -> 0.09299277 | AC33: =AC26+AC28+AC29 -> 119368.03 | AD33: =AC33/F33 -> 0.04871745 | AE33: =AE26+AE30 -> 94478.437 | AG33: =AE33/F33 -> 0.038559307
A34: TOTAL ACUMULADO | H34: - | J34: =H33+J33 -> 486764.35 | L34: =J34/F33 -> 0.19866222 | M34: =J34+M33 -> 769116.11 | N34: =M34/F33 -> 0.31389791 | O34: =M34+O33 -> 1060242.8 | P34: =O34/F33 -> 0.4327149 | Q34: =O34+Q33 -> 1351369.5 | S34: =Q34/F33 -> 0.55153189 | T34: =Q34+T33 -> 1610392 | U34: =T34/F33 -> 0.65724627 | V34: =T34+V33 -> 1765870.7 | W34: =V34/F33 -> 0.72070149 | X34: =V34+X33 -> 2008512.6 | Z34: =X34/F33 -> 0.81973047 | AA34: =X34+AA33 -> 2236364.5 | AB34: =AA34/F33 -> 0.91272324 | AC34: =AA34+AC33 -> 2355732.5 | AD34: =AC34/F33 -> 0.96144069 | AE34: =AC34+AE33 -> 2450211 | AG34: =AE34/F33 -> 1
A35: _______________________________________________________________ Luzikenyo L. M. Veloso Chianca - CREA PB n° 1612617590 Engenheiro Civil

Sheet ENCARGOS REV_1
A1: COMPOSIÇÃO ANALÍTICA DAS TAXAS DE ENCARGOS SOCIAIS
A2: Secretaria de Atenção Especializada à Saúde BDI Geral: Encargo Social Mensalista: Data:
A3: Centro de Atenção Psicossocial - Porte 1, no município de Coremas/PB 26,87% 69,85% 12/12/2025 Bancos: Encargo Social Horista: 113,60% SINAPI (09/2025) - CPOS/CDHU (09/2025) - SBC (12/2025) - ORSE (09/2025) - IOPES (08/2025) - EMOP (10/2025) - SETOP (07/2025) - SEINFRA (028) - AGETOP CIVIL (08/2025) - AGESUL (06/2025)
A5: ENCARGOS SOCIAIS SOBRE A MÃO DE OBRA
A6: CÓDIGO | B6: DESCRIÇÃO | E6: SEM DESONERAÇÃO
E7: HORISTA (%) | F7: MENSALISTA (%)
A8: GRUPO A
A9: A1 | B9: INSS | E9: 0.2 | F9: 0.2
A10: A2 | B10: SESI | E10: 0.015 | F10: 0.015
A11: A3 | B11: SENAI | E11: 0.01 | F11: 0.01
A12: A4 | B12: INCRA | E12: 0.002 | F12: 0.002
A13: A5 | B13: SEBRAE | E13: 0.006 | F13: 0.006
A14: A6 | B14: Salário Educação | E14: 0.025 | F14: 0.025
A15: A7 | B15: Seguro Contra Acidentes de Trabalho | E15: 0.03 | F15: 0.03
A16: A8 | B16: FGTS | E16: 0.08 | F16: 0.08
A17: A9 | B17: SECONCI | E17: 0 | F17: 0
A18: A | B18: Total | E18: 0.368 | F18: 0.368
A19: GRUPO B
A20: B1 | B20: Repouso Semanal Remunerado | E20: 0.1802 | F20: Não incide
A21: B2 | B21: Feriados | E21: 0.0431 | F21: Não incide
A22: B3 | B22: Auxílio-Enfermidade | E22: 0.0086 | F22: 0.0065
A23: B4 | B23: 13º Salário | E23: 0.1096 | F23: 0.0833
A24: B5 | B24: Licença Paternidade | E24: 0.0007 | F24: 0.0005
A25: B6 | B25: Faltas Justificadas | E25: 0.0073 | F25: 0.0056
A26: B7 | B26: Dias de Chuva | E26: 0.0204 | F26: Não incide
A27: B8 | B27: Auxílo Acidente de Trabalho | E27: 0.001 | F27: 0.0007
A28: B9 | B28: Férias Gozadas | E28: 0.0976 | F28: 0.0742
A29: B10 | B29: Salário Maternidade | E29: 0.0003 | F29: 0.0003
A30: B | B30: Total | E30: 0.4688 | F30: 0.1711
A31: GRUPO C
A32: C1 | B32: Aviso Prévio Indenizado | E32: 0.0453 | F32: 0.0345
A33: C2 | B33: Aviso Prévio Trabalhado | E33: 0.0011 | F33: 0.0008
A34: C3 | B34: Férias Indenizadas | E34: 0.0429 | F34: 0.0326
A35: C4 | B35: Depósito Recisão sem justa causa | E35: 0.0296 | F35: 0.0225
A36: C5 | B36: Indenização Adicional | E36: 0.0038 | F36: 0.0029
A37: C | B37: Total | E37: 0.1227 | F37: 0.0933
A38: GRUPO D
A39: D1 | B39: Reincidência de Grupo A sobre Grupo B | E39: 0.1725 | F39: 0.063
A40: D2 | B40: Reincidência de Grupo A sobre Aviso Prévio Trabalhado e Reincidência do FGTS sobre Aviso Prévio Indenizado | E40: 0.004 | F40: 0.0031
A41: D | B41: Total | E41: 0.1765 | F41: 0.0661
A42: TOTAL (A+B+C+D) | E42: 1.136 | F42: 0.6985
A45: _______________________________________________________________ Luzikenyo L. M. Veloso Chianca - CREA PB n° 1612617590 Engenheiro Civil

Sheet BDI REV_1
A1: BONIFICAÇÕES E DESPESAS INDIRETAS
A2: Secretaria de Atenção Especializada à Saúde BDI Geral: Encargo Social Mensalista: Data:
A3: Centro de Atenção Psicossocial - Porte 1, no município de Coremas/PB 26,87% 69,85% 12/12/2025 Bancos: Encargo Social Horista: 113,60% SINAPI (09/2025) - CPOS/CDHU (09/2025) - SBC (12/2025) - ORSE (09/2025) - IOPES (08/2025) - EMOP (10/2025) - SETOP (07/2025) - SEINFRA (028) - AGETOP CIVIL (08/2025) - AGESUL (06/2025)
A4: Fórmula (Bonificações e Despesas Indiretas):
A5: ITEM | B5: DESCRIÇÃO | C5: CÓD | E5: GERAL VALORES PROPOSTOS (%) | F5: EQUIPAMENTOS VALORES PROPOSTOS (%)
A6: 1 | B6: Administração Central | C6: AC | E6: 4,00% | F6: 3,45%
A7: 2 | B7: Riscos | C7: R | E7: 1,27% | F7: 0,85%
A8: 3 | B8: Seguros e Garantias | C8: SG | E8: 0,80% | F8: 0,48%
A9: 4 | B9: Despesas Financeiras | C9: DF | E9: 1,23% | F9: 0,85%
A10: 5 | B10: Lucro | C10: L | E10: 6,16% | F10: 3,50%
A11: 6 | B11: Impostos | C11: I | E11: 10,15% | F11: 8,15%
A12: 6.1 | B12: PIS | E12: 0,65% | F12: 0,65%
A13: 6.2 | B13: COFINS | E13: 3,00% | F13: 3,00%
A14: 6.3 | B14: ISSQN | E14: 2,00% | F14: 0,00%
A15: 6.4 | B15: CPRB
A17: BDI | E17: 26,87% | F17: 19,07%
A19: _______________________________________________________________ Luzikenyo L. M. Veloso Chianca - CREA PB n° 1612617590 Engenheiro Civil
