Workbook
Name _______MDO1: [2]INSUMOS!$C$8
Name _______MDO2: [3]INSUMOS!$C$6
Name _______R: #REF!
Name ______MDO1: [2]INSUMOS!$C$8
Name ______MDO2: [3]INSUMOS!$C$6
Name ______R: #REF!
Name ______R: #REF!
Name ______rua1: #REF!
Name ______rua1: #REF!
Name _____MDO1: [2]INSUMOS!$C$8
Name _____MDO2: [3]INSUMOS!$C$6
Name _____R: #REF!
Name _____R: #REF!
Name _____rua1: #REF!
Name _____rua1: #REF!
Name ____MDO1: [2]INSUMOS!$C$8
Name ____MDO2: [3]INSUMOS!$C$6
Name ____R: #REF!
Name ____R: #REF!
Name ____rua1: #REF!
Name ____rua1: #REF!
Name ___MDO1: [2]INSUMOS!$C$8
Name ___MDO2: [3]INSUMOS!$C$6
Name ___R: #REF!
Name ___R: #REF!
Name ___rua1: #REF!
Name ___rua1: #REF!
Name __MDO1: [4]INSUMOS!$C$8
Name __MDO1: [4]INSUMOS!$C$8
Name __MDO2: [3]INSUMOS!$C$6
Name __R: #REF!
Name __R: #REF!
Name __rua1: #REF!
Name __rua1: #REF!
Name __xlnm.Print_Titles_2: #REF!
Name __xlnm.Print_Titles_2: #REF!
Name _MDO1: [4]INSUMOS!$C$8
Name _MDO1: [4]INSUMOS!$C$8
Name _MDO2: [3]INSUMOS!$C$6
Name _R: #REF!
Name _R: #REF!
Name _rua1: #REF!
Name _rua1: #REF!
Name A: #REF!
Name AA: [5]CUBACAO!#REF!
Name AA: [5]CUBACAO!#REF!
Name AAA: [5]CUBACAO!#REF!
Name AAA: [5]CUBACAO!#REF!
Name Ac: #REF!
Name Ac: #REF!
Name artFiscal: [6]DADOS!$D$23
Name ASDFASDFAS: #REF!
Name ASDFASDFAS: #REF!
Name BB: [5]CUBACAO!#REF!
Name BB: [5]CUBACAO!#REF!
Name BBB: [5]CUBACAO!#REF!
Name BBB: [5]CUBACAO!#REF!
Name bdi: [7]Orçamento!$J$10
Name bdi: [7]Orçamento!$J$10
Name BDIc: #REF!

Sheet BM-01
A1: ESTADO DA PARAÍBA
A2: PREFEITURA MUNICIPAL DE COREMAS | Q2: VALOR EDITAL | R2: R$ 1.252.370,60
A3: CONTRATO Nº 10004/2023 | Q3: VALOR C/DESC. | R3: =L213 -> 1039467.6
A4: OBRA: CONSTRUÇÃO DE UMA UNIDADE ESCOLAR DE 06 (SEIS) SALAS DE AULA PARA O MUNICÍPIO DE COREMAS-PB | J4: BDI = | K4: 0.25
A5: LOCAL: MUNICÍPIO DE COREMAS-PB | Q5: DESCONTO: | R5: 0.17
A6: BOLETIM DE MEDIÇÃO - BM-01
A7: ITEM | B7: CÓDIGO | C7: REFERÊNCIA | D7: DESCRIÇÃO | E7: ORIGEM | F7: UNID | G7: QUANTIDADES | K7: VALOR UNIT COM BDI | L7: VALORES TOTAIS
G8: LICITADA | H8: ACUMULADA ATÉ O PERÍODO | I8: MEDIDA NO PERÍODO | J8: ACUMULADA INCLUINDO O PERÍODO | L8: LICITADO | M8: ACUMULADO ATÉ O PERÍODO | N8: MEDIDO NO PERÍODO | O8: ACUMULADO INCLUINDO O PERÍODO
A9: 1 ETAPA 01: GERAL | L9: =SUM(L10,L16) -> 66229.186 | M9: =SUM(M10,M16) -> 0 | N9: =SUM(N10,N16) -> 7723.8406 | O9: =SUM(O10,O16) -> 7723.8406
A10: 1.1 1 ADMINISTRACAO LOCAL | L10: =SUM(L11:L15) -> 64365.338 | M10: =SUM(M11:M15) -> 0 | N10: =SUM(N11:N15) -> 7723.8406 | O10: =SUM(O11:O15) -> 7723.8406
A11: 1.1.1 | B11: 164471 | C11: O13221 | D11: ADMINSTRACAO LOCAL - PESSOAL | E11: SUPLAN | F11: UN | G11: 8 | I11: ='MEMORIAL DE CÁLCULOS'!J11 -> 0.96 | J11: =H11+I11 -> 0.96 | K11: 4208.9549 | L11: =G11*K11 -> 33671.639 | M11: =H11*K11 -> 0 | N11: =I11*K11 -> 4040.5967 | O11: =J11*K11 -> 4040.5967 | V11: 5071.03 | W11: =V11-V11*$R$5 -> 4208.9549
A12: 1.1.2 | B12: 164472 | C12: O13221 | D12: ADMINISTRACAO LOCAL - DESPESAS GERAIS MENSAIS | E12: SUPLAN | F12: UN | G12: 8 | I12: ='MEMORIAL DE CÁLCULOS'!J14 -> 0.96 | J12: =H12+I12 -> 0.96 | K12: 1588.6449 | L12: =G12*K12 -> 12709.159 | M12: =H12*K12 -> 0 | N12: =I12*K12 -> 1525.0991 | O12: =J12*K12 -> 1525.0991 | V12: 1914.03 | W12: =V12-V12*$R$5 -> 1588.6449
A13: 1.1.3 | B13: 164473 | C13: O13221 | D13: ADMINISTRACAO LOCAL - DESPESAS GERAIS FIXAS | E13: SUPLAN | F13: UN | G13: 1 | I13: ='MEMORIAL DE CÁLCULOS'!J17 -> 0.12 | J13: =H13+I13 -> 0.12 | K13: 2489.2862 | L13: =G13*K13 -> 2489.2862 | M13: =H13*K13 -> 0 | N13: =I13*K13 -> 298.71434 | O13: =J13*K13 -> 298.71434 | V13: 2999.14 | W13: =V13-V13*$R$5 -> 2489.2862
A14: 1.1.4 | B14: 164474 | C14: O13221 | D14: ADMINISTRACAO LOCAL - VECULOS E EQUIPAMENTOS | E14: SUPLAN | F14: UN | G14: 8 | I14: ='MEMORIAL DE CÁLCULOS'!J20 -> 0.96 | J14: =H14+I14 -> 0.96 | K14: 1279.8185 | L14: =G14*K14 -> 10238.548 | M14: =H14*K14 -> 0 | N14: =I14*K14 -> 1228.6258 | O14: =J14*K14 -> 1228.6258 | V14: 1541.95 | W14: =V14-V14*$R$5 -> 1279.8185
A15: 1.1.5 | B15: 164475 | C15: O13221 | D15: ADMINISTRACAO LOCAL - MOVEIS E UTENSILIOS | E15: SUPLAN | F15: UN | G15: 1 | I15: ='MEMORIAL DE CÁLCULOS'!J23 -> 0.12 | J15: =H15+I15 -> 0.12 | K15: 5256.7054 | L15: =G15*K15 -> 5256.7054 | M15: =H15*K15 -> 0 | N15: =I15*K15 -> 630.80465 | O15: =J15*K15 -> 630.80465 | V15: 6333.38 | W15: =V15-V15*$R$5 -> 5256.7054
A16: 1.2 DIVERSOS | L16: =SUM(L17) -> 1863.848 | M16: =SUM(M17) -> 0 | N16: =SUM(N17) -> 0 | O16: =SUM(O17) -> 0
A17: 1.2.1 | B17: 164476 | D17: "AS BUILT" DO PROJETO ARQUITETONICO E DOS PROJETOS DE ENGENHARIA DE ESTRUTURAS E DE INSTALACOES ELETRICAS, INSTALACOES HIDRAULICAS E INSTALACOES SANITARIAS - ESCOLAS | E17: SINAPI | F17: UN | G17: 1 | J17: =H17+I17 -> 0 | K17: 1863.848 | L17: =G17*K17 -> 1863.848 | M17: =H17*K17 -> 0 | N17: =I17*K17 -> 0 | O17: =J17*K17 -> 0 | V17: 2245.6 | W17: =V17-V17*$R$5 -> 1863.848
A18: 2 ETAPA 02: CONSTRUCAO DA ESCOLA | L18: =SUM(L19,L28,L32,L38,L47,L52,L63,L72,L80,L91,L102,L133,L141,L165,L176,) -> 930676.59 | M18: =SUM(M19,M28,M32,M38,M47,M52,M63,M72,M80,M91,M102,M133,M141,M165,M176,) -> 0 | N18: =SUM(N19,N28,N32,N38,N47,N52,N63,N72,N80,N91,N102,N133,N141,N165,N176,) -> 121891.57 | O18: =SUM(O19,O28,O32,O38,O47,O52,O63,O72,O80,O91,O102,O133,O141,O165,O176,) -> 121891.57
A19: 2.1 1 SERVICOS PRELIMINARES | L19: =SUM(L20:L27) -> 20901.206 | M19: =SUM(M20:M27) -> 0 | N19: =SUM(N20:N27) -> 9189.5164 | O19: =SUM(O20:O27) -> 9189.5164
A20: 2.1.1 | B20: 132583 | C20: 74209/001 | D20: PLACA DE OBRA EM CHAPA DE ACO GALVANIZADO | E20: SINAPI | F20: M2 | G20: 10 | I20: ='MEMORIAL DE CÁLCULOS'!J28 -> 10 | J20: =H20+I20 -> 10 | K20: 342.8979 | L20: =G20*K20 -> 3428.979 | M20: =H20*K20 -> 0 | N20: =I20*K20 -> 3428.979 | O20: =J20*K20 -> 3428.979 | V20: 413.13 | W20: =V20-V20*$R$5 -> 342.8979
A21: 2.1.2 | B21: 163387 | C21: 74077/3 | D21: LOCACAO CONVENCIONAL DE OBRA, ATRAVES DE GABARITO DE TABUAS CORRIDAS PONTALETADAS, COM REAPROVEITAMENTO DE 3 VEZES - | E21: SINAPI | F21: M2 | G21: 771.45 | I21: ='MEMORIAL DE CÁLCULOS'!J31 -> 771.45 | J21: =H21+I21 -> 771.45 | K21: 4.9551 | L21: =G21*K21 -> 3822.6119 | M21: =H21*K21 -> 0 | N21: =I21*K21 -> 3822.6119 | O21: =J21*K21 -> 3822.6119 | V21: 5.97 | W21: =V21-V21*$R$5 -> 4.9551
A22: 2.1.3 | B22: 137043 | C22: 73822/002 | D22: LIMPEZA MECANIZADA DE TERRENO COM REMOCAO DE CAMADA VEGETAL, UTILIZAND O MOTONIVELADORA | E22: SINAPI | F22: M2 | G22: 2000 | I22: ='MEMORIAL DE CÁLCULOS'!J34 -> 2000 | J22: =H22+I22 -> 2000 | K22: 0.2739 | L22: =G22*K22 -> 547.8 | M22: =H22*K22 -> 0 | N22: =I22*K22 -> 547.8 | O22: =J22*K22 -> 547.8 | V22: 0.33 | W22: =V22-V22*$R$5 -> 0.2739
A23: 2.1.4 | B23: 163443 | C23: C2851 | D23: INSTALACOES PROVISORIAS DE AGUA, INCLUSIVE CAIXA DAGUA DE 1000L | E23: SINAPI | F23: UN | G23: 1 | I23: ='MEMORIAL DE CÁLCULOS'!J37 -> 1 | J23: =H23+I23 -> 1 | K23: 1390.1255 | L23: =G23*K23 -> 1390.1255 | M23: =H23*K23 -> 0 | N23: =I23*K23 -> 1390.1255 | O23: =J23*K23 -> 1390.1255 | V23: 1674.85 | W23: =V23-V23*$R$5 -> 1390.1255
A24: 2.1.5 | B24: 163442 | C24: 11122/ORS | D24: ENTRADA DE ENERGIA ELETRICA MONOFASICA COM POSTE DE CONCRETO, INCLUSIVE CABEAMENTO, CAIXA DE PROTECAO PARA MEDIDOR E | E24: SINAPI | F24: UN | G24: 1 | J24: =H24+I24 -> 0 | K24: 1506.3255 | L24: =G24*K24 -> 1506.3255 | M24: =H24*K24 -> 0 | N24: =I24*K24 -> 0 | O24: =J24*K24 -> 0 | V24: 1814.85 | W24: =V24-V24*$R$5 -> 1506.3255
A25: 2.1.6 | B25: 135723 | C25: 73658 | D25: LIGACAO DOMICILIAR DE ESGOTO DN 100MM, DA CASA ATE A CAIXA, COMPOSTO P OR 10,0M TUBO DE PVC ESGOTO PREDIAL DN 100MM E CAIXA DE ALVENARIA COM TAMPA DE CONCRETO - FORNECIMENTO E | E25: SINAPI | F25: UN | G25: 1 | J25: =H25+I25 -> 0 | K25: 442.5062 | L25: =G25*K25 -> 442.5062 | M25: =H25*K25 -> 0 | N25: =I25*K25 -> 0 | O25: =J25*K25 -> 0 | V25: 533.14 | W25: =V25-V25*$R$5 -> 442.5062
A26: 2.1.7 | B26: 162175 | D26: LOCACAO DE CONTAINER 2,30 X 4,30 M, ALT. 2,50 M, P/ SANITARIO, C/ 5 BACIAS, 1 LAVATORIO E 4 MICTORIOS, INCLUSIVE TRANSP/CARGA/DESCARGA | E26: SUPLAN | F26: MÊS | G26: 8 | J26: =H26+I26 -> 0 | K26: 654.9198 | L26: =G26*K26 -> 5239.3584 | M26: =H26*K26 -> 0 | N26: =I26*K26 -> 0 | O26: =J26*K26 -> 0 | V26: 789.06 | W26: =V26-V26*$R$5 -> 654.9198
A27: 2.1.8 | B27: 163536 | D27: ALUGUEL CONTAINER/ESCRIT INCL INST ELET LARG=2,20 COMP=6,20M ALT=2,50M CHAPA ACO C/NERV TRAPEZ FORRO C/ISOLTERMO/ACUSTICO CHASSIS REFORC P I S O C O M P E N S N A V A L I N C T R A N S P / C A R G A / D E S C A R G A | E27: SINAPI | F27: MÊS | G27: 8 | J27: =H27+I27 -> 0 | K27: 565.4375 | L27: =G27*K27 -> 4523.5 | M27: =H27*K27 -> 0 | N27: =I27*K27 -> 0 | O27: =J27*K27 -> 0 | V27: 681.25 | W27: =V27-V27*$R$5 -> 565.4375
A28: 2.2 2 MOVIMENTO DE TERRA | L28: =SUM(L29:L31) -> 43621.441 | M28: =SUM(M29:M31) -> 0 | N28: =SUM(N29:N31) -> 42875.185 | O28: =SUM(O29:O31) -> 42875.185
A29: 2.2.1 | B29: 160239 | D29: ESCAVACAO MANUAL DE VALA EM MATERIAL DE QUALQUER CATEGORIA, EXCETO ROCHA COM PROFUNDIDADE ATE 2M. | E29: SINAPI | F29: M3 | G29: 157.35 | I29: ='MEMORIAL DE CÁLCULOS'!J41 -> 157.35 | J29: =H29+I29 -> 157.35 | K29: 63.1132 | L29: =G29*K29 -> 9930.862 | M29: =H29*K29 -> 0 | N29: =I29*K29 -> 9930.862 | O29: =J29*K29 -> 9930.862 | V29: 76.04 | W29: =V29-V29*$R$5 -> 63.1132
A30: 2.2.2 | B30: 164368 | C30: 24824/SIN | D30: ATERRO DO CAIXAO SEM AQUISICAO DO MATERIAL (REATERRO MANUAL) | E30: SINAPI | F30: M3 | G30: 157.35 | I30: ='MEMORIAL DE CÁLCULOS'!J80 -> 137.8 | J30: =H30+I30 -> 137.8 | K30: 38.1717 | L30: =G30*K30 -> 6006.317 | M30: =H30*K30 -> 0 | N30: =I30*K30 -> 5260.0603 | O30: =J30*K30 -> 5260.0603 | V30: 45.99 | W30: =V30-V30*$R$5 -> 38.1717
A31: 2.2.3 | B31: 153622 | D31: ATERRO DO CAIXAO COM AQUISICAO DO MATERIAL/AREIA, APILOADO EM CAMADAS DE 0,20M | E31: SINAPI | F31: M3 | G31: 195.41 | I31: ='MEMORIAL DE CÁLCULOS'!J83 -> 195.41 | J31: =H31+I31 -> 195.41 | K31: 141.6727 | L31: =G31*K31 -> 27684.262 | M31: =H31*K31 -> 0 | N31: =I31*K31 -> 27684.262 | O31: =J31*K31 -> 27684.262 | V31: 170.69 | W31: =V31-V31*$R$5 -> 141.6727
A32: 2.3 3 INFRAESTRUTURA | L32: =SUM(L33:L37) -> 69826.867 | M32: =SUM(M33:M37) -> 0 | N32: =SUM(N33:N37) -> 69826.867 | O32: =SUM(O33:O37) -> 69826.867
A33: 2.3.1 | B33: 146934 | C33: 95467 | D33: EMBASAMENTO C/PEDRA ARGAMASSADA UTILIZANDO ARG.CIM/AREIA 1:4 | E33: SINAPI | F33: M3 | G33: 105.04 | I33: ='MEMORIAL DE CÁLCULOS'!J88 -> 105.04 | J33: =H33+I33 -> 105.04 | K33: 316.5952 | L33: =G33*K33 -> 33255.16 | M33: =H33*K33 -> 0 | N33: =I33*K33 -> 33255.16 | O33: =J33*K33 -> 33255.16 | V33: 381.44 | W33: =V33-V33*$R$5 -> 316.5952
A34: 2.3.2 | B34: 160126 | D34: ALVENARIA DE 1 VEZ VEDACAO COM BLOCOS CERAMICO FURADOS 9 X 19 X 19 CM FUROS HORIZONTAIS, ESPESSURA DA PAREDE 19 CM, JUNTAS DE 10 MM COM ARGAMASSA TRACO 1:2:8 (CIMENTO, CAL E AREIA MEDIA) | E34: SINAPI | F34: M2 | G34: 35.13 | I34: ='MEMORIAL DE CÁLCULOS'!J92 -> 35.13 | J34: =H34+I34 -> 35.13 | K34: 45.4342 | L34: =G34*K34 -> 1596.1034 | M34: =H34*K34 -> 0 | N34: =I34*K34 -> 1596.1034 | O34: =J34*K34 -> 1596.1034 | V34: 54.74 | W34: =V34-V34*$R$5 -> 45.4342
A35: 2.3.3 | B35: 154476 | C35: 96616 | D35: LASTRO DE CONCRETO MAGRO, APLICADO EM BLOCOS DE COROAMENTO OU SAPATAS.AF_08/2017 | E35: SINAPI | F35: M3 | G35: 6.13 | I35: ='MEMORIAL DE CÁLCULOS'!J96 -> 6.13 | J35: =H35+I35 -> 6.13 | K35: 463.804 | L35: =G35*K35 -> 2843.1185 | M35: =H35*K35 -> 0 | N35: =I35*K35 -> 2843.1185 | O35: =J35*K35 -> 2843.1185 | V35: 558.8 | W35: =V35-V35*$R$5 -> 463.804
A36: 2.3.4 | B36: 161024 | D36: CONCRETO ARMADO (PREPARO E LANCAMENTO)PARA SAPATAS COM FCK >= 25MPA, COM FORMA DE TABUA, COM APROVEI TAMENTO DE 2 VEZES, COM BETONEIRA - | E36: SINAPI | F36: M3 | G36: 19.55 | I36: ='MEMORIAL DE CÁLCULOS'!J133 -> 19.55 | J36: =H36+I36 -> 19.55 | K36: 1008.533 | L36: =G36*K36 -> 19716.82 | M36: =H36*K36 -> 0 | N36: =I36*K36 -> 19716.82 | O36: =J36*K36 -> 19716.82 | V36: 1215.1 | W36: =V36-V36*$R$5 -> 1008.533
A37: 2.3.5 | B37: 161026 | D37: CONCRETO ARMADO (PREPARO E LANCAMENTO) PARA RADIER COM FCK>=25MPA, COM TABUA DE MADEIRA, COM APROVEITAMENTO DE 3 VEZES COM BETONEIRA - | E37: SINAPI | F37: M3 | G37: 12.33 | I37: ='MEMORIAL DE CÁLCULOS'!J136 -> 12.33 | J37: =H37+I37 -> 12.33 | K37: 1006.9477 | L37: =G37*K37 -> 12415.665 | M37: =H37*K37 -> 0 | N37: =I37*K37 -> 12415.665 | O37: =J37*K37 -> 12415.665 | V37: 1213.19 | W37: =V37-V37*$R$5 -> 1006.9477
A38: 2.4 4 SUPER-ESTRUTURA | L38: =SUM(L39:L46) -> 187786.33 | M38: =SUM(M39:M46) -> 0 | N38: =SUM(N39:N46) -> 0 | O38: =SUM(O39:O46) -> 0
A39: 2.4.1 | B39: 161030 | D39: CONCRETO ARMADO (PREPARO E LANCAMENTO) PARA VIGA COM FCK>=30MPA, COM FORMA EM CHAPA DE MADEIRA COM- P E N S A D A R E S I N A D A , C O M APROVEITAMENTO DE 3 VEZES COM BETONEIRA - | E39: SINAPI | F39: M3 | G39: 18.92 | J39: =H39+I39 -> 0 | K39: 2838.0273 | L39: =G39*K39 -> 53695.477 | M39: =H39*K39 -> 0 | N39: =I39*K39 -> 0 | O39: =J39*K39 -> 0 | V39: 3419.31 | W39: =V39-V39*$R$5 -> 2838.0273
A40: 2.4.2 | B40: 161031 | D40: CONCRETO ARMADO (PREPARO E LANCAMENTO) P/ PILARES COM FCK>=30MPA, COM FORMA EM CHAPA DE MADEIRA COM- P E N S A D A R E S I N A D A , C O M APROVEITAMENTO DE 3 VEZES, COM BETONEIRA - | E40: SUPLAN | F40: M3 | G40: 18.39 | J40: =H40+I40 -> 0 | K40: 2812.9032 | L40: =G40*K40 -> 51729.29 | M40: =H40*K40 -> 0 | N40: =I40*K40 -> 0 | O40: =J40*K40 -> 0 | V40: 3389.04 | W40: =V40-V40*$R$5 -> 2812.9032
A41: 2.4.3 | B41: 161027 | D41: CONCRETO ARMADO (PREPARO E LANCAMENTO) PARA CINTA COM FCK>=30MPA, COM TABUA DE MADEIRA, COM APROVEITAMENTO DE 3 VEZES COM BETONEIRA - | E41: SINAPI | F41: M3 | G41: 3.34 | J41: =H41+I41 -> 0 | K41: 2012.5259 | L41: =G41*K41 -> 6721.8365 | M41: =H41*K41 -> 0 | N41: =I41*K41 -> 0 | O41: =J41*K41 -> 0 | V41: 2424.73 | W41: =V41-V41*$R$5 -> 2012.5259
A42: 2.4.4 | B42: 134255 | C42: 74202/001 | D42: LAJE PRE-MOLDADA P/FORRO, SOBRECARGA 100KG/M2, VAOS ATE 3,50M/E=8CM, C /LAJOTAS E CAP.C/CONC FCK=20MPA, 3CM, INTER-EIXO 38CM, C/ESCORAMENTO ( REAPR.3X) E FERRAGEM NEGATIVA | E42: SINAPI | F42: M2 | G42: 625 | J42: =H42+I42 -> 0 | K42: 112.9215 | L42: =G42*K42 -> 70575.938 | M42: =H42*K42 -> 0 | N42: =I42*K42 -> 0 | O42: =J42*K42 -> 0 | V42: 136.05 | W42: =V42-V42*$R$5 -> 112.9215
A43: 2.4.5 | B43: 145501 | D43: PRATELEIRA EM CONCRETO ARMADO COM E=0,05M E L=0,40M COM REVESTIMENTO CERAMICA | E43: SINAPI | F43: M | G43: 17.85 | J43: =H43+I43 -> 0 | K43: 119.1548 | L43: =G43*K43 -> 2126.9132 | M43: =H43*K43 -> 0 | N43: =I43*K43 -> 0 | O43: =J43*K43 -> 0 | V43: 143.56 | W43: =V43-V43*$R$5 -> 119.1548
A44: 2.4.6 | B44: 145226 | D44: PRATELEIRA EM CONCRETO ARMADO COM E=0,05M E L=0,45M COM REVESTIMENTO CERAMICA | E44: SINAPI | F44: M | G44: 9.9 | J44: =H44+I44 -> 0 | K44: 119.1548 | L44: =G44*K44 -> 1179.6325 | M44: =H44*K44 -> 0 | N44: =I44*K44 -> 0 | O44: =J44*K44 -> 0 | V44: 143.56 | W44: =V44-V44*$R$5 -> 119.1548
A45: 2.4.7 | B45: 144469 | D45: PRATELEIRA EM CONCRETO ARMADO COM E=0,05M E L=0,50M E REVESTIMENTO EM CERAMICA | E45: SINAPI | F45: M | G45: 1.6 | J45: =H45+I45 -> 0 | K45: 194.1702 | L45: =G45*K45 -> 310.67232 | M45: =H45*K45 -> 0 | N45: =I45*K45 -> 0 | O45: =J45*K45 -> 0 | V45: 233.94 | W45: =V45-V45*$R$5 -> 194.1702
A46: 2.4.8 | B46: 144116 | D46: PRATELEIRA EM CONCRETO ARMADO COM E=0,05M E L=0,60M E REVESTIMENTO EM CERAMICA | E46: SINAPI | F46: M | G46: 7.45 | J46: =H46+I46 -> 0 | K46: 194.1702 | L46: =G46*K46 -> 1446.568 | M46: =H46*K46 -> 0 | N46: =I46*K46 -> 0 | O46: =J46*K46 -> 0 | V46: 233.94 | W46: =V46-V46*$R$5 -> 194.1702
A47: 2.5 5 PAREDES E PAINEIS | L47: =SUM(L48:L51) -> 85866.042 | M47: =SUM(M48:M51) -> 0 | N47: =SUM(N48:N51) -> 0 | O47: =SUM(O48:O51) -> 0
A48: 2.5.1 | B48: 160118 | D48: ALVENARIA DE 1/2 VEZ VEDACAO COM BLOCOS CERAMICO FURADOS 9 X 19 X 19 CM FUROS HORIZONTAIS, ESPESSURA DA PAREDE 9 CM, JUNTAS DE 10 MM COM ARGAMASSA TRACO 1:2:8 (CIMENTO, CAL E | E48: SINAPI | F48: M2 | G48: 954.17 | J48: =H48+I48 -> 0 | K48: 34.0632 | L48: =G48*K48 -> 32502.084 | M48: =H48*K48 -> 0 | N48: =I48*K48 -> 0 | O48: =J48*K48 -> 0 | V48: 41.04 | W48: =V48-V48*$R$5 -> 34.0632
A49: 2.5.2 | B49: 136101 | C49: 73937/005 | D49: COBOGO DE CONCRETO (ELEMENTO VAZADO), 10X29X39CM ABERTURA COM VIDRO, A SSENTADO COM ARGAMASSA TRACO 1:4 (CIMENTO E AREIA MEDIA NAO PENEIRADA) | E49: SINAPI | F49: M2 | G49: 37.44 | J49: =H49+I49 -> 0 | K49: 149.2423 | L49: =G49*K49 -> 5587.6317 | M49: =H49*K49 -> 0 | N49: =I49*K49 -> 0 | O49: =J49*K49 -> 0 | V49: 179.81 | W49: =V49-V49*$R$5 -> 149.2423
A50: 2.5.3 | B50: 164273 | D50: MURO EM ALVENARIA DE 1/2 VEZ COM TIJOLOS DE 8 FUROS COM LOCACAO E I N C L U S I V E E X E C U C A O D E GABARITO,ESCAVACAO MANUAL DE VALAS, ALVENARIA DE PEDRA ARGAMASSADA, EMBASAMENTO EM ALVENARIA DE 1 VEZ, CONCRETO ARMADOPARA RADIER E CINTA SUPERIOR, COLUNAS DE CONCRETO ARMADO A CADA 3,0M, CHAPISCADO, REBOCADO, SELADOR ACRILICO EPINTADO, | E50: SINAPI | F50: M | G50: 150 | J50: =H50+I50 -> 0 | K50: 285.3789 | L50: =G50*K50 -> 42806.835 | M50: =H50*K50 -> 0 | N50: =I50*K50 -> 0 | O50: =J50*K50 -> 0 | V50: 343.83 | W50: =V50-V50*$R$5 -> 285.3789
A51: 2.5.4 | B51: 151091 | D51: MURETA EM ALVENARIA DE 1 VEZ COM TIJOLO DE 8 FUROS (H=0,50M)(ESCAVACAO, ALVENARIA DE PEDRA ARGAMASSADA, ALVENARIA, CHAPISCO, REBOCO E PINTURA PVA) | E51: SINAPI | F51: M | G51: 58 | J51: =H51+I51 -> 0 | K51: 85.6809 | L51: =G51*K51 -> 4969.4922 | M51: =H51*K51 -> 0 | N51: =I51*K51 -> 0 | O51: =J51*K51 -> 0 | V51: 103.23 | W51: =V51-V51*$R$5 -> 85.6809
A52: 2.6 6 ESQUADRIAS, FERRAGENS E VIDROS | L52: =SUM(L53:L62) -> 86978.585 | M52: =SUM(M53:M62) -> 0 | N52: =SUM(N53:N62) -> 0 | O52: =SUM(O53:O62) -> 0
A53: 2.6.1 | B53: 153844 | D53: PORTA MADEIRA DE LEI TIPO MACICA, INCLUSO ARO/FORRA, ALIZAR, DOBRADICAS, PARAFUSOS DE FIXACAO, EXCLUSIVE FECHADURA - FORNECIMENTO E | E53: SINAPI | F53: M2 | G53: 35.91 | J53: =H53+I53 -> 0 | K53: 538.836 | L53: =G53*K53 -> 19349.601 | M53: =H53*K53 -> 0 | N53: =I53*K53 -> 0 | O53: =J53*K53 -> 0 | V53: 649.2 | W53: =V53-V53*$R$5 -> 538.836
A54: 2.6.2 | B54: 146852 | C54: 94559 | D54: JANELA DE ACO BASCULANTE, FIXACAO COM ARGAMASSA, SEM VIDROS, PADRONIZA DA. AF_07/2016 | E54: SINAPI | F54: M2 | G54: 59.11 | J54: =H54+I54 -> 0 | K54: 622.5415 | L54: =G54*K54 -> 36798.428 | M54: =H54*K54 -> 0 | N54: =I54*K54 -> 0 | O54: =J54*K54 -> 0 | V54: 750.05 | W54: =V54-V54*$R$5 -> 622.5415
A55: 2.6.3 | B55: 145509 | D55: GRADIL NYLOFOR 3D, MALHA 20X5CM, 5MM 250X243 CM, PINTURA BRANCA, VERDE E PRETA, BELGO OU SIMILAR, INCLUSIVE POSTES (SECCAO 60X40MM E H=3,20M) E ACESSORIOS | E55: SUPLAN | F55: M2 | G55: 3 | J55: =H55+I55 -> 0 | K55: 200.8683 | L55: =G55*K55 -> 602.6049 | M55: =H55*K55 -> 0 | N55: =I55*K55 -> 0 | O55: =J55*K55 -> 0 | V55: 242.01 | W55: =V55-V55*$R$5 -> 200.8683
A56: 2.6.4 | B56: 151970 | D56: MONTANTE E PAINEL BELGO LINHA NYLOFOR OU SIMILAR NA COR BRANCA, COM CHUMBADORES, INCLUSIVE POSTES (SECCAO 60X40MM) E ACESSORIOS | E56: SUPLAN | F56: M2 | G56: 60 | J56: =H56+I56 -> 0 | K56: 242.4762 | L56: =G56*K56 -> 14548.572 | M56: =H56*K56 -> 0 | N56: =I56*K56 -> 0 | O56: =J56*K56 -> 0 | V56: 292.14 | W56: =V56-V56*$R$5 -> 242.4762
A57: 2.6.5 | B57: 151982 | D57: PORTAO EM GRADIL BELGO NYLOFOR 3D, DE CORRER,SOLDADO EM QUADRO DE TUBO GALVANIZADO 2" COM CANTONEIRA 3/4", MONTANTES EM TUBO DE FERRO GALVANIZADO DE 4", INCLUSIVE FERROLHO E RODIZIOS | E57: SUPLAN | F57: M2 | G57: 1.68 | J57: =H57+I57 -> 0 | K57: 605.4435 | L57: =G57*K57 -> 1017.1451 | M57: =H57*K57 -> 0 | N57: =I57*K57 -> 0 | O57: =J57*K57 -> 0 | V57: 729.45 | W57: =V57-V57*$R$5 -> 605.4435
A58: 2.6.6 | B58: 163453 | C58: 08492/ORS | D58: BARRA DE APOIO RETA, EM ACO INOX POLIDO PARA PCD, DIAMETRO =1 1/2" | E58: SINAPI | F58: M | G58: 3.4 | J58: =H58+I58 -> 0 | K58: 126.2264 | L58: =G58*K58 -> 429.16976 | M58: =H58*K58 -> 0 | N58: =I58*K58 -> 0 | O58: =J58*K58 -> 0 | V58: 152.08 | W58: =V58-V58*$R$5 -> 126.2264
A59: 2.6.7 | B59: 133889 | C59: 72122 | D59: VIDRO FANTASIA TIPO CANELADO, ESPESSURA 4MM | E59: SINAPI | F59: M2 | G59: 59.11 | J59: =H59+I59 -> 0 | K59: 203.8812 | L59: =G59*K59 -> 12051.418 | M59: =H59*K59 -> 0 | N59: =I59*K59 -> 0 | O59: =J59*K59 -> 0 | V59: 245.64 | W59: =V59-V59*$R$5 -> 203.8812
A60: 2.6.8 | B60: 138518 | C60: 5085 | D60: CADEADO SIMPLES, EM LATAO MACICO CROMADO, LARGURA DE 35 MM, HASTE DE ACO TEMPERADO, CEMENTADO (NAO LONGA), INCLUI 2 CHAVES | E60: SINAPI | F60: UN | G60: 2 | J60: =H60+I60 -> 0 | K60: 17.8118 | L60: =G60*K60 -> 35.6236 | M60: =H60*K60 -> 0 | N60: =I60*K60 -> 0 | O60: =J60*K60 -> 0 | V60: 21.46 | W60: =V60-V60*$R$5 -> 17.8118
A61: 2.6.9 | B61: 163824 | D61: FECHADURA PARA PORTA EXTERNA , COM CILINDRO E MACANETA TIPO TACO DE GOLFE, PADRAO MEDIO - FORNECIMENTO E INSTALACAO | E61: SINAPI | F61: UN | G61: 17 | J61: =H61+I61 -> 0 | K61: 118.8975 | L61: =G61*K61 -> 2021.2575 | M61: =H61*K61 -> 0 | N61: =I61*K61 -> 0 | O61: =J61*K61 -> 0 | V61: 143.25 | W61: =V61-V61*$R$5 -> 118.8975
A62: 2.6.10 | B62: 163827 | D62: FECHADURA DE EMBUTIR PARA PORTA EXTERNA / ENTRADA, MAQUINA 55 MM, COM CJ 60,39CILINDRO, MACANETA TIPOO TACO DE GOLFE E ESPELHO EM METAL CROMADO - NIVEL SEGURANCAMEDIO - COMPLETA | E62: SUPLAN | F62: UN | G62: 2 | J62: =H62+I62 -> 0 | K62: 62.3828 | L62: =G62*K62 -> 124.7656 | M62: =H62*K62 -> 0 | N62: =I62*K62 -> 0 | O62: =J62*K62 -> 0 | V62: 75.16 | W62: =V62-V62*$R$5 -> 62.3828
A63: 2.7 COBERTA | L63: =SUM(L64:L71) -> 69042.859 | M63: =SUM(M64:M71) -> 0 | N63: =SUM(N64:N71) -> 0 | O63: =SUM(O64:O71) -> 0
A64: 2.7.1 | B64: 133392 | C64: 92565 | D64: FABRICACAO E INTALACAO DE ESTRUTURA PONTALETADA DE MADEIRA NAO APAREL HADA PARA TELHADOS COM ATE 2 AGUAS E PARA TELHA CERAMICA OU DE CONCRET O, INCLUSO TRANSPORTE VERTICAL. | E64: SINAPI | F64: M2 | G64: 615.05 | J64: =H64+I64 -> 0 | K64: 28.967 | L64: =G64*K64 -> 17816.153 | M64: =H64*K64 -> 0 | N64: =I64*K64 -> 0 | O64: =J64*K64 -> 0 | V64: 34.9 | W64: =V64-V64*$R$5 -> 28.967
A65: 2.7.2 | B65: 133371 | C65: 92542 | D65: TRAMA DE MADEIRA COMPOSTA POR RIPAS, CAIBROS E TERCAS PARA TELHADOS DE MAIS QUE 2 AGUAS PARA TELHA CERAMICA CAPA-CANAL, INCLUSO TRANSPORTE V ERTICAL. AF_12/2015 | E65: SINAPI | F65: M2 | G65: 77.02 | J65: =H65+I65 -> 0 | K65: 74.43025 | L65: =G65*K65 -> 5732.6179 | M65: =H65*K65 -> 0 | N65: =I65*K65 -> 0 | O65: =J65*K65 -> 0 | V65: 89.675 | W65: =V65-V65*$R$5 -> 74.43025
A66: 2.7.3 | B66: 146764 | C66: 94445 | D66: TELHAMENTO COM TELHA CERAMICA CAPA- CANAL, TIPO PLAN, COM ATE 2 AGUAS, INCLUSO TRANSPORTE VERTICAL. | E66: SINAPI | F66: M2 | G66: 672.85 | J66: =H66+I66 -> 0 | K66: 30.544 | L66: =G66*K66 -> 20551.53 | M66: =H66*K66 -> 0 | N66: =I66*K66 -> 0 | O66: =J66*K66 -> 0 | V66: 36.8 | W66: =V66-V66*$R$5 -> 30.544
A67: 2.7.4 | B67: 146775 | C67: 94221 | D67: CUMEEIRA PARA TELHA CERAMICA EMBOCADA COM ARGAMASSA TRACO 1:2:9 (CIMEN TO, CAL E AREIA) PARA TELHADOS COM ATE 2 AGUAS, INCLUSO TRANSPORTE VER TICAL. AF_06/2016 | E67: SINAPI | F67: M | G67: 85.33 | J67: =H67+I67 -> 0 | K67: 16.6 | L67: =G67*K67 -> 1416.478 | M67: =H67*K67 -> 0 | N67: =I67*K67 -> 0 | O67: =J67*K67 -> 0 | V67: 20 | W67: =V67-V67*$R$5 -> 16.6
A68: 2.7.5 | B68: 163731 | D68: ALGEROZ/RUFO DE CONCRETO ARMADO FCK=20MPA L=40CM, E=5CM | E68: SINAPI | F68: M | G68: 41.57 | J68: =H68+I68 -> 0 | K68: 18.6418 | L68: =G68*K68 -> 774.93963 | M68: =H68*K68 -> 0 | N68: =I68*K68 -> 0 | O68: =J68*K68 -> 0 | V68: 22.46 | W68: =V68-V68*$R$5 -> 18.6418
A69: 2.7.6 | B69: 146757 | C69: 94224 | D69: EMBOCAMENTO COM ARGAMASSA TRACO 1:2:9 (CIMENTO, CAL E AREIA). AF_06/20 16 | E69: SINAPI | F69: M | G69: 8.78 | J69: =H69+I69 -> 0 | K69: 18.592 | L69: =G69*K69 -> 163.23776 | M69: =H69*K69 -> 0 | N69: =I69*K69 -> 0 | O69: =J69*K69 -> 0 | V69: 22.4 | W69: =V69-V69*$R$5 -> 18.592
A70: 2.7.7 | B70: 161738 | D70: IMPERMEABILIZACAO COM APLICACAO DE ARGAMASSA POLIMERICA TIPO DENVERTEC 100 OU SIMILAR | E70: SINAPI | F70: M2 | G70: 8.31 | J70: =H70+I70 -> 0 | K70: 38.3377 | L70: =G70*K70 -> 318.58629 | M70: =H70*K70 -> 0 | N70: =I70*K70 -> 0 | O70: =J70*K70 -> 0 | V70: 46.19 | W70: =V70-V70*$R$5 -> 38.3377
A71: 2.7.8 | B71: 153541 | C71: 96111 | D71: FORRO EM REGUAS DE PVC, PARA AMBIENTES RESIDENCIAIS, INCLUSIVE ESTRUTURA DE FIXACAO. AF_05/2017_P | E71: SINAPI | F71: M2 | G71: 356.67 | J71: =H71+I71 -> 0 | K71: 62.43675 | L71: =G71*K71 -> 22269.316 | M71: =H71*K71 -> 0 | N71: =I71*K71 -> 0 | O71: =J71*K71 -> 0 | V71: 75.225 | W71: =V71-V71*$R$5 -> 62.43675
A72: 2.8 REVESTIMENTO E FORRO | L72: =SUM(L73:L79) -> 112951.45 | M72: =SUM(M73:M79) -> 0 | N72: =SUM(N73:N79) -> 0 | O72: =SUM(O73:O79) -> 0
A73: 2.8.1 | B73: 160114 | D73: CHAPISCO EM PAREDES VERTICAIS TRACO 1:3 (CIMENTO E AREIA), ESPESSURA 0,5CM, PREPARO MECANICO; | E73: SINAPI | F73: M2 | G73: 2159.76 | J73: =H73+I73 -> 0 | K73: 2.9714 | L73: =G73*K73 -> 6417.5109 | M73: =H73*K73 -> 0 | N73: =I73*K73 -> 0 | O73: =J73*K73 -> 0 | V73: 3.58 | W73: =V73-V73*$R$5 -> 2.9714
A74: 2.8.2 | B74: 161080 | C74: S77005 | D74: REBOCO VERTICAL, EM ARGAMASSA TRACO 1:2:8 - PREPARO MECANICO COM BETONEIRA 400L, ESPESSURA DE 20MM | E74: SINAPI | F74: M2 | G74: 1314.79 | J74: =H74+I74 -> 0 | K74: 18.0027 | L74: =G74*K74 -> 23669.77 | M74: =H74*K74 -> 0 | N74: =I74*K74 -> 0 | O74: =J74*K74 -> 0 | V74: 21.69 | W74: =V74-V74*$R$5 -> 18.0027
A75: 2.8.3 | B75: 160138 | D75: EMBOCO, PARA RECEBIMENTO DE CERAMICA, EM ARGAMASSA TRAO 1:2:8, PREPARO MECANICO COM BETONEIRA 400L, APLICADO MANUALMENTE, ESPESSURA DE | E75: SINAPI | F75: M2 | G75: 844.79 | J75: =H75+I75 -> 0 | K75: 14.4752 | L75: =G75*K75 -> 12228.504 | M75: =H75*K75 -> 0 | N75: =I75*K75 -> 0 | O75: =J75*K75 -> 0 | V75: 17.44 | W75: =V75-V75*$R$5 -> 14.4752
A76: 2.8.4 | B76: 160279 | D76: REVESTIMENTO PARA MOSAICO MONDRIAN EM CERAMICA 10 X 10 CM, ELIZABETH, DIVERSAS CORES, PEI -5, OU SIMILAR, ASSENTADA COM ARGAMASSA COLANTE AC II E REJUNTAMENTO INDUSTRIALIZADO | E76: SINAPI | F76: M2 | G76: 108.2 | J76: =H76+I76 -> 0 | K76: 87.7476 | L76: =G76*K76 -> 9494.2903 | M76: =H76*K76 -> 0 | N76: =I76*K76 -> 0 | O76: =J76*K76 -> 0 | V76: 105.72 | W76: =V76-V76*$R$5 -> 87.7476
A77: 2.8.5 | B77: 161082 | C77: S77022 | D77: REVESTIMENTO EM CERAMICA 10 X 10 CM, ELIZABETH, PEI -5, OU SIMILAR, ASSENTADA COM ARGAMASSA COLANTE AC II, REJUNTAMENTO. INDUSTRIALIZADO | E77: SINAPI | F77: M2 | G77: 736.59 | J77: =H77+I77 -> 0 | K77: 53.1947 | L77: =G77*K77 -> 39182.684 | M77: =H77*K77 -> 0 | N77: =I77*K77 -> 0 | O77: =J77*K77 -> 0 | V77: 64.09 | W77: =V77-V77*$R$5 -> 53.1947
A78: 2.8.6 | B78: 161922 | D78: CHAPISCO TETO/HORIZONTAL APLICADO COM COLHER DE PEDREIRO. ARGAMASSA TRACO 1:3 COM PREPARO EM BETONEIRA 400L | E78: SINAPI | F78: M2 | G78: 625 | J78: =H78+I78 -> 0 | K78: 4.2579 | L78: =G78*K78 -> 2661.1875 | M78: =H78*K78 -> 0 | N78: =I78*K78 -> 0 | O78: =J78*K78 -> 0 | V78: 5.13 | W78: =V78-V78*$R$5 -> 4.2579
A79: 2.8.7 | B79: 161923 | C79: 87532 | D79: REBOCO TETO/HORIZONTAL, EM ARGAMASSA TRACO 1:2:8, ESPESSURA DE 20MM, COM EXECUCAO DE TALISCAS. | E79: SINAPI | F79: M2 | G79: 625 | J79: =H79+I79 -> 0 | K79: 30.876 | L79: =G79*K79 -> 19297.5 | M79: =H79*K79 -> 0 | N79: =I79*K79 -> 0 | O79: =J79*K79 -> 0 | V79: 37.2 | W79: =V79-V79*$R$5 -> 30.876
A80: 2.9 PINTURA | L80: =SUM(L81:L90) -> 60696.528 | M80: =SUM(M81:M90) -> 0 | N80: =SUM(N81:N90) -> 0 | O80: =SUM(O81:O90) -> 0
A81: 2.9.1 | B81: 162595 | D81: EMASSAMENTO COM MASSA ACRILICA, DUAS D E M A O S , E M P A R E D E S INTERNAS/EXTERNAS/TETO, INCLUSIVE LIXAMENTO | E81: SINAPI | F81: M2 | G81: 407.76 | J81: =H81+I81 -> 0 | K81: 27.8548 | L81: =G81*K81 -> 11358.073 | M81: =H81*K81 -> 0 | N81: =I81*K81 -> 0 | O81: =J81*K81 -> 0 | V81: 33.56 | W81: =V81-V81*$R$5 -> 27.8548
A82: 2.9.2 | B82: 136253 | C82: 88485 | D82: APLICACAO DE FUNDO SELADOR ACRILICO EM PAREDES, UMA DEMAO. AF_06/2014 | E82: SINAPI | F82: M2 | G82: 407.76 | J82: =H82+I82 -> 0 | K82: 2.158 | L82: =G82*K82 -> 879.94608 | M82: =H82*K82 -> 0 | N82: =I82*K82 -> 0 | O82: =J82*K82 -> 0 | V82: 2.6 | W82: =V82-V82*$R$5 -> 2.158
A83: 2.9.3 | B83: 136257 | C83: 88489 | D83: APLICACAO MANUAL DE PINTURA COM TINTA LATEX ACRILICA EM PAREDES, DUAS DEMAOS. AF_06/2014 | E83: SINAPI | F83: M2 | G83: 407.76 | J83: =H83+I83 -> 0 | K83: 11.2548 | L83: =G83*K83 -> 4589.2572 | M83: =H83*K83 -> 0 | N83: =I83*K83 -> 0 | O83: =J83*K83 -> 0 | V83: 13.56 | W83: =V83-V83*$R$5 -> 11.2548
A84: 2.9.4 | B84: 136273 | C84: 74065/001 | D84: PINTURA ESMALTE FOSCO PARA MADEIRA, DUAS DEMAOS, SOBRE FUNDO NIVELADOR BRANCO | E84: SINAPI | F84: M2 | G84: 89.78 | J84: =H84+I84 -> 0 | K84: 10.4995 | L84: =G84*K84 -> 942.64511 | M84: =H84*K84 -> 0 | N84: =I84*K84 -> 0 | O84: =J84*K84 -> 0 | V84: 12.65 | W84: =V84-V84*$R$5 -> 10.4995
A85: 2.9.5 | B85: 136289 | C85: 73924/002 | D85: PINTURA ESMALTE ACETINADO, DUAS DEMAOS, SOBRE SUPERFICIE METALICA | E85: SINAPI | F85: M2 | G85: 118.22 | J85: =H85+I85 -> 0 | K85: 32.1957 | L85: =G85*K85 -> 3806.1757 | M85: =H85*K85 -> 0 | N85: =I85*K85 -> 0 | O85: =J85*K85 -> 0 | V85: 38.79 | W85: =V85-V85*$R$5 -> 32.1957
A86: 2.9.6 | B86: 136244 | C86: 88423 | D86: APLICACAO MANUAL DE PINTURA COM TINTA TEXTURIZADA ACRILICA EM PAREDES EXTERNAS DE CASAS, UMA COR. AF_06/2014 | E86: SINAPI | F86: M2 | G86: 2.53 | J86: =H86+I86 -> 0 | K86: 16.0605 | L86: =G86*K86 -> 40.633065 | M86: =H86*K86 -> 0 | N86: =I86*K86 -> 0 | O86: =J86*K86 -> 0 | V86: 19.35 | W86: =V86-V86*$R$5 -> 16.0605
A87: 2.9.7 | B87: 136255 | C87: 88487 | D87: APLICACAO MANUAL DE PINTURA COM TINTA LATEX PVA EM PAREDES, DUAS DEMAO S. AF_06/2014 | E87: SINAPI | F87: M2 | G87: 1578.41 | J87: =H87+I87 -> 0 | K87: 11.2548 | L87: =G87*K87 -> 17764.689 | M87: =H87*K87 -> 0 | N87: =I87*K87 -> 0 | O87: =J87*K87 -> 0 | V87: 13.56 | W87: =V87-V87*$R$5 -> 11.2548
A88: 2.9.8 | B88: 133361 | C88: 55960 | D88: IMUNIZACAO DE MADEIRAMENTO PARA COBERTURA UTILIZANDO CUPINICIDA INCOLO R | E88: SINAPI | F88: M2 | G88: 1009.28 | J88: =H88+I88 -> 0 | K88: 4.5484 | L88: =G88*K88 -> 4590.6092 | M88: =H88*K88 -> 0 | N88: =I88*K88 -> 0 | O88: =J88*K88 -> 0 | V88: 5.48 | W88: =V88-V88*$R$5 -> 4.5484
A89: 2.9.9 | B89: 136258 | C89: 88494 | D89: APLICACAO E LIXAMENTO DE MASSA LATEX EM TETO, UMA DEMAO. AF_06/2014 | E89: SINAPI | F89: M2 | G89: 625 | J89: =H89+I89 -> 0 | K89: 14.11 | L89: =G89*K89 -> 8818.75 | M89: =H89*K89 -> 0 | N89: =I89*K89 -> 0 | O89: =J89*K89 -> 0 | V89: 17 | W89: =V89-V89*$R$5 -> 14.11
A90: 40423 | B90: 136254 | C90: 88486 | D90: APLICACAO MANUAL DE PINTURA COM TINTA LATEX PVA EM TETO, DUAS DEMAOS. AF_06/2014 | E90: SINAPI | F90: M2 | G90: 625 | J90: =H90+I90 -> 0 | K90: 12.6492 | L90: =G90*K90 -> 7905.75 | M90: =H90*K90 -> 0 | N90: =I90*K90 -> 0 | O90: =J90*K90 -> 0 | V90: 15.24 | W90: =V90-V90*$R$5 -> 12.6492
A91: 2.10 PAVIMENTACAO | L91: =SUM(L92:L101) -> 95361.855 | M91: =SUM(M92:M101) -> 0 | N91: =SUM(N92:N101) -> 0 | O91: =SUM(O92:O101) -> 0
A92: 2.10.1 | B92: 148340 | D92: LAJE DE IMPERMEABILIZACAO, LASTRO DE CONCRETO - PREPARO MECANICO | E92: SINAPI | F92: M3 | G92: 44.86 | J92: =H92+I92 -> 0 | K92: 244.5429 | L92: =G92*K92 -> 10970.194 | M92: =H92*K92 -> 0 | N92: =I92*K92 -> 0 | O92: =J92*K92 -> 0 | V92: 294.63 | W92: =V92-V92*$R$5 -> 244.5429
A93: 2.10.2 | B93: 161761 | D93: REGULARIZACAO DE BASE PARA REVESTIMENTO DE PISO, COM ARGAMASSA DE CIMENTO E AREIA NO TRACO 1:5, COM ESPESSURA DE 2CM. | E93: SUPLAN | F93: M2 | G93: 45.74 | J93: =H93+I93 -> 0 | K93: 21.6547 | L93: =G93*K93 -> 990.48598 | M93: =H93*K93 -> 0 | N93: =I93*K93 -> 0 | O93: =J93*K93 -> 0 | V93: 26.09 | W93: =V93-V93*$R$5 -> 21.6547
A94: 2.10.3 | B94: 161754 | D94: PISO EM CERAMICA FAB. ELIZABETH, PEI-5, TIPO A, OU SIMILAR, ASSENTADA COM ARGAMASSA COLANTE E REJUNTAMENTO INDUSTRIALIZADO | E94: SINAPI | F94: M2 | G94: 45.74 | J94: =H94+I94 -> 0 | K94: 46.1065 | L94: =G94*K94 -> 2108.9113 | M94: =H94*K94 -> 0 | N94: =I94*K94 -> 0 | O94: =J94*K94 -> 0 | V94: 55.55 | W94: =V94-V94*$R$5 -> 46.1065
A95: 2.10.4 | B95: 161085 | C95: S77010 | D95: PISO EM GRANILITE, MARMORITE OU GRANITINA ESPESSURA 8MM, INCLUSO JUNTAS DE DILATACAO PLASTICAS, INCLUSIVE REGULARIZACAO E POLIMENTO | E95: SINAPI | F95: M2 | G95: 515.01 | J95: =H95+I95 -> 0 | K95: 95.5579 | L95: =G95*K95 -> 49213.274 | M95: =H95*K95 -> 0 | N95: =I95*K95 -> 0 | O95: =J95*K95 -> 0 | V95: 115.13 | W95: =V95-V95*$R$5 -> 95.5579
A96: 2.10.5 | B96: 162295 | D96: APLICACAO DE RESINA A BASE DE POLIURETANO EM PISO DE GRANILITE/ALTA RESISTENCIA EM TRES DEMAOS.. | E96: SINAPI | F96: M2 | G96: 515.01 | J96: =H96+I96 -> 0 | K96: 16.1103 | L96: =G96*K96 -> 8296.9656 | M96: =H96*K96 -> 0 | N96: =I96*K96 -> 0 | O96: =J96*K96 -> 0 | V96: 19.41 | W96: =V96-V96*$R$5 -> 16.1103
A97: 2.10.6 | B97: 161037 | D97: CALCADA DE PROTECAO/CONTORNO - (LARGURA= 0,60M) | E97: SUPLAN | F97: M | G97: 165.62 | J97: =H97+I97 -> 0 | K97: 101.5422 | L97: =G97*K97 -> 16817.419 | M97: =H97*K97 -> 0 | N97: =I97*K97 -> 0 | O97: =J97*K97 -> 0 | V97: 122.34 | W97: =V97-V97*$R$5 -> 101.5422
A98: 2.10.7 | B98: 147444 | C98: 94992 | D98: EXECUCAO DE PASSEIO (CALCADA) OU PISO DE CONCRETO COM CONCRETO MOLDADO IN LOCO, FEITO EM OBRA, ACABAMENTO CONVENCIONAL, ESPESSURA 6 CM, ARMA DO. AF_07/2016 | E98: SINAPI | F98: M2 | G98: 6.5 | J98: =H98+I98 -> 0 | K98: 70.1018 | L98: =G98*K98 -> 455.6617 | M98: =H98*K98 -> 0 | N98: =I98*K98 -> 0 | O98: =J98*K98 -> 0 | V98: 84.46 | W98: =V98-V98*$R$5 -> 70.1018
A99: 2.10.8 | B99: 136198 | C99: 92396 | D99: EXECUCAO DE PASSEIO EM PISO INTERTRAVADO, COM BLOCO RETANGULAR COR NAT URAL DE 20 X 10 CM, ESPESSURA 6 CM. AF_12/2015 | E99: SINAPI | F99: M2 | G99: 101 | J99: =H99+I99 -> 0 | K99: 50.9537 | L99: =G99*K99 -> 5146.3237 | M99: =H99*K99 -> 0 | N99: =I99*K99 -> 0 | O99: =J99*K99 -> 0 | V99: 61.39 | W99: =V99-V99*$R$5 -> 50.9537
A100: 2.10.9 | B100: 161981 | D100: RAMPA EM CALCADA DE PASSEIO EM CONCRETO PARA ACESSIBILIDADE DE PORTADORES DE NECESSIDADES ESPECIAIS (PNE), EXECUTADA CONCRETO ESTRUTURAL, INCLUSIVE SINALIZACAO TATIL DE ALERTA (25X25CM) E SINALIZACAO UNIVERSAL EM TINTA ACRILICA-ESTIRENADA (0,80 X 1,60)M | E100: SINAPI | F100: UN | G100: 1 | J100: =H100+I100 -> 0 | K100: 280.4155 | L100: =G100*K100 -> 280.4155 | M100: =H100*K100 -> 0 | N100: =I100*K100 -> 0 | O100: =J100*K100 -> 0 | V100: 337.85 | W100: =V100-V100*$R$5 -> 280.4155
...

Sheet MEMORIAL DE CÁLCULOS
A1: =[13]ORÇAMENTO!A1:J1 -> ESTADO DA PARAÍBA
A2: ESTADO DA PARAÍBA
A3: PREFEITURA MUNICIPAL DE COREMAS
A4: ='BM-01'!A3 -> CONTRATO Nº 10004/2023
A5: ='BM-01'!A4 -> OBRA: CONSTRUÇÃO DE UMA UNIDADE ESCOLAR DE 06 (SEIS) SALAS DE AULA PARA O MUNICÍPIO DE COREMAS-PB
A6: MEMORIAL DE CÁLCULOS
A7: ITEM | B7: DESCRIÇÃO | C7: DADOS | G7: Descontos | I7: RESULTADO | K7: UN.
C8: Quantid. | D8: Comprim. (m) | E8: Largura (m) | F8: Altura (m) | G8: Descrição | H8: Valor | I8: PARCIAL | J8: GERAL
A9: 1 | B9: ETAPA 01: GERAL
A10: 1.1 | B10: ADMINISTRAÇÃO LOCAL
A11: ='BM-01'!A11 -> 1.1.1 | B11: ='BM-01'!D11 -> ADMINSTRACAO LOCAL - PESSOAL | J11: =ROUND(SUM(J12:J12),2) -> 0.96 | K11: ='BM-01'!F11 -> UN
B12: Proporcional ao valor da medição | C12: 0.96 | J12: =C12 -> 0.96
A14: ='BM-01'!A12 -> 1.1.2 | B14: ='BM-01'!D12 -> ADMINISTRACAO LOCAL - DESPESAS GERAIS MENSAIS | J14: =ROUND(SUM(J15:J15),2) -> 0.96 | K14: ='BM-01'!F12 -> UN
B15: Proporcional ao valor da medição | C15: 0.96 | J15: =C15 -> 0.96
A17: ='BM-01'!A13 -> 1.1.3 | B17: ='BM-01'!D13 -> ADMINISTRACAO LOCAL - DESPESAS GERAIS FIXAS | J17: =ROUND(SUM(J18:J18),2) -> 0.12 | K17: ='BM-01'!F13 -> UN
B18: Proporcional ao valor da medição | C18: 0.12 | J18: =C18 -> 0.12
A20: ='BM-01'!A14 -> 1.1.4 | B20: ='BM-01'!D14 -> ADMINISTRACAO LOCAL - VECULOS E EQUIPAMENTOS | J20: =ROUND(SUM(J21:J21),2) -> 0.96 | K20: ='BM-01'!F14 -> UN
B21: Proporcional ao valor da medição | C21: 0.96 | J21: =C21 -> 0.96
A23: ='BM-01'!A15 -> 1.1.5 | B23: ='BM-01'!D15 -> ADMINISTRACAO LOCAL - MOVEIS E UTENSILIOS | J23: =ROUND(SUM(J24:J24),2) -> 0.12 | K23: ='BM-01'!F15 -> UN
B24: Proporcional ao valor da medição | C24: 0.12 | J24: =C24 -> 0.12
A26: 2 | B26: ETAPA 02: CONSTRUÇÃO DA ESCOLA
A27: 2.1 | B27: SERVIÇOS PRELIMINARES
A28: ='BM-01'!A20 -> 2.1.1 | B28: ='BM-01'!D20 -> PLACA DE OBRA EM CHAPA DE ACO GALVANIZADO | J28: =ROUND(SUM(J29:J29),2) -> 10 | K28: ='BM-01'!F20 -> M2
B29: Placa da obra | C29: 1 | D29: 4 | F29: 2.5 | I29: =D29*F29 -> 10 | J29: =C29*I29 -> 10
A31: ='BM-01'!A21 -> 2.1.2 | B31: ='BM-01'!D21 -> LOCACAO CONVENCIONAL DE OBRA, ATRAVES DE GABARITO DE TABUAS CORRIDAS PONTALETADAS, COM REAPROVEITAMENTO DE 3 VEZES - | J31: =ROUND(SUM(J32:J32),2) -> 771.45 | K31: ='BM-01'!F21 -> M2
B32: Área da construção com offset de 0,50m (Auxílio CAD) | C32: 771.45 | J32: =C32 -> 771.45
A34: ='BM-01'!A22 -> 2.1.3 | B34: ='BM-01'!D22 -> LIMPEZA MECANIZADA DE TERRENO COM REMOCAO DE CAMADA VEGETAL, UTILIZAND O MOTONIVELADORA | J34: =ROUND(SUM(J35:J35),2) -> 2000 | K34: ='BM-01'!F22 -> M2
B35: Área de limpeza | C35: =2000 -> 2000 | J35: =C35 -> 2000
A37: ='BM-01'!A23 -> 2.1.4 | B37: ='BM-01'!D23 -> INSTALACOES PROVISORIAS DE AGUA, INCLUSIVE CAIXA DAGUA DE 1000L | J37: =ROUND(SUM(J38:J38),2) -> 1 | K37: ='BM-01'!F23 -> UN
B38: Reservatório provisório construído | C38: 1 | J38: =C38 -> 1
A40: 2.2 | B40: MOVIMENTO DE TERRA
A41: ='BM-01'!A29 -> 2.2.1 | B41: ='BM-01'!D29 -> ESCAVACAO MANUAL DE VALA EM MATERIAL DE QUALQUER CATEGORIA, EXCETO ROCHA COM PROFUNDIDADE ATE 2M. | J41: =ROUND(SUM(J42:J43),2) -> 157.35 | K41: ='BM-01'!F29 -> M3
B42: Escavações para alvenaria de pedra (Item 2.3.1) | C42: =J88 -> 105.04 | J42: =C42 -> 105.04 | L42: 2.6
B43: Escavações de sapatas = Dimensões mais folga x profundidade média (medido cerca de 40% do total devido ao quantitativo insuficiente na planilha): | J43: =0.4352*(SUM(J44:J78)) -> 52.314304 | L43: 2.85
B44: S41=S48=S50=S66=S73 | C44: 5 | D44: 1.1 | E44: 0.95 | F44: 1 | I44: =D44*E44*F44 -> 1.045 | J44: =C44*I44 -> 5.225 | L44: 3.15
B45: S28=S37=S40 | C45: 3 | D45: 1.1 | E45: 1.1 | F45: 1 | I45: =D45*E45*F45 -> 1.21 | J45: =C45*I45 -> 3.63
B46: S1=S4=S6=S8=S10=S52 | C46: 6 | D46: 1.2 | E46: 1.05 | F46: 1 | I46: =D46*E46*F46 -> 1.26 | J46: =C46*I46 -> 7.56
B47: S13 | C47: 1 | D47: 1.25 | E47: 1.05 | F47: 1 | I47: =D47*E47*F47 -> 1.3125 | J47: =C47*I47 -> 1.3125
B48: S31=S33=S35 | C48: 3 | D48: 1.15 | E48: 1.5 | F48: 1 | I48: =D48*E48*F48 -> 1.725 | J48: =C48*I48 -> 5.175
B49: S32=S34=S36=S38=S43 | C49: 5 | D49: 0.9 | E49: 0.9 | F49: 1 | I49: =D49*E49*F49 -> 0.81 | J49: =C49*I49 -> 4.05
B50: S30 | C50: 1 | D50: 0.95 | E50: 0.95 | F50: 1 | I50: =D50*E50*F50 -> 0.9025 | J50: =C50*I50 -> 0.9025
B51: S47 | C51: 1 | D51: 1.05 | E51: 0.9 | F51: 1 | I51: =D51*E51*F51 -> 0.945 | J51: =C51*I51 -> 0.945
B52: S49 | C52: 1 | D52: 1.1 | E52: 0.9 | F52: 1 | I52: =D52*E52*F52 -> 0.99 | J52: =C52*I52 -> 0.99
B53: S2=S12 | C53: 2 | D53: 1.25 | E53: 1.1 | F53: 1 | I53: =D53*E53*F53 -> 1.375 | J53: =C53*I53 -> 2.75 | L53: 3.55
B54: S58=S59 | C54: 2 | D54: 1.3 | E54: 1.1 | F54: 1 | I54: =D54*E54*F54 -> 1.43 | J54: =C54*I54 -> 2.86 | L54: 3.9
B55: S27=S53 | C55: 2 | D55: 1.3 | E55: 1.15 | F55: 1 | I55: =D55*E55*F55 -> 1.495 | J55: =C55*I55 -> 2.99 | L55: 4.03
B56: S3=S5=S7 | C56: 3 | D56: 1.35 | E56: 1.15 | F56: 1 | I56: =D56*E56*F56 -> 1.5525 | J56: =C56*I56 -> 4.6575 | L56: 4.4
B57: S39 | C57: 1 | D57: 1.25 | E57: 1.25 | F57: 1 | I57: =D57*E57*F57 -> 1.5625 | J57: =C57*I57 -> 1.5625 | L57: 4.65
B58: S51 | C58: 1 | D58: 1.05 | E58: 0.95 | F58: 1 | I58: =D58*E58*F58 -> 0.9975 | J58: =C58*I58 -> 0.9975 | L58: 4.85
B59: S42 | C59: 1 | D59: 1 | E59: 1 | F59: 1 | I59: =D59*E59*F59 -> 1 | J59: =C59*I59 -> 1 | L59: 5.25
B60: S9=S11=S60 | C60: 3 | D60: 1.35 | E60: 1.2 | F60: 1 | I60: =D60*E60*F60 -> 1.62 | J60: =C60*I60 -> 4.86 | L60: 5.47
B61: S55=S67 | C61: 2 | D61: 1.4 | E61: 1.2 | F61: 1 | I61: =D61*E61*F61 -> 1.68 | J61: =C61*I61 -> 3.36
B62: S29 | C62: 1 | D62: 1.3 | E62: 1.3 | F62: 1 | I62: =D62*E62*F62 -> 1.69 | J62: =C62*I62 -> 1.69
B63: S45 | C63: 1 | D63: 1.4 | E63: 1.25 | F63: 1 | I63: =D63*E63*F63 -> 1.75 | J63: =C63*I63 -> 1.75
B64: S14=S20=S46=S63=S64 | C64: 5 | D64: 1.45 | E64: 1.25 | F64: 1 | I64: =D64*E64*F64 -> 1.8125 | J64: =C64*I64 -> 9.0625
B65: S70 | C65: 1 | D65: 1.4 | E65: 1.3 | F65: 1 | I65: =D65*E65*F65 -> 1.82 | J65: =C65*I65 -> 1.82
B66: S21=S54=S57=S71=S72 | C66: 5 | D66: 1.45 | E66: 1.3 | F66: 1 | I66: =D66*E66*F66 -> 1.885 | J66: =C66*I66 -> 9.425
B67: S61=S68 | C67: 2 | D67: 1.5 | E67: 1.3 | F67: 1 | I67: =D67*E67*F67 -> 1.95 | J67: =C67*I67 -> 3.9
B68: S44 | C68: 1 | D68: 1.5 | E68: 1.35 | F68: 1 | I68: =D68*E68*F68 -> 2.025 | J68: =C68*I68 -> 2.025
B69: S65 | C69: 1 | D69: 1.55 | E69: 1.35 | F69: 1 | I69: =D69*E69*F69 -> 2.0925 | J69: =C69*I69 -> 2.0925
B70: S25=S62 | C70: 2 | D70: 1.55 | E70: 1.4 | F70: 1 | I70: =D70*E70*F70 -> 2.17 | J70: =C70*I70 -> 4.34
B71: S23=S24 | C71: 2 | D71: 1.6 | E71: 1.4 | F71: 1 | I71: =D71*E71*F71 -> 2.24 | J71: =C71*I71 -> 4.48
B72: S22=S69 | C72: 2 | D72: 1.6 | E72: 1.45 | F72: 1 | I72: =D72*E72*F72 -> 2.32 | J72: =C72*I72 -> 4.64
... B78: S15 | C78: 1 | D78: 1.85 | E78: 1.75 | F78: 1 | I78: =D78*E78*F78 -> 3.2375 | J78: =C78*I78 -> 3.2375
L79: 2.35
A80: ='BM-01'!A30 -> 2.2.2 | B80: ='BM-01'!D30 -> ATERRO DO CAIXAO SEM AQUISICAO DO MATERIAL (REATERRO MANUAL) | J80: =ROUND(SUM(J81:J81),2) -> 137.8 | K80: ='BM-01'!F30 -> M3 | L80: 2.55
B81: Igual ao volume de alvenaria de pedra mais escavações das sapatas menos volume de concreto das sapatas= (Item 2.2.1 menos 2.3.4) | C81: =J41-J133 -> 137.8 | J81: =C81 -> 137.8 | L81: 3.55
L82: 4
A83: ='BM-01'!A31 -> 2.2.3 | B83: ='BM-01'!D31 -> ATERRO DO CAIXAO COM AQUISICAO DO MATERIAL/AREIA, APILOADO EM CAMADAS DE 0,20M | J83: =J84 -> 195.41 | K83: ='BM-01'!F31 -> M3
B84: Volume calculado abaixo, sendo medido apenas o quantitativo existente na planilha | J84: =195.41 -> 195.41
B85: Área construída da edificação 475,00 m² multiplicado pela média de 1,10 m de altura (fundos esq. 1,40 m, fundos direito 1,70 m, lateral direita centro 1,45m, frente direito 0,85 m, frente esquerdo 0,70 m e lateral esquerda centro 0,50m) = 522,50 m³ | C85: =475 -> 475 | F85: =(1.4+1.7+1.45+0.85+0.7+0.5)/6 -> 1.1 | G85: Reaterro | H85: =J80 -> 137.8 | J85: =(C85*F85)-H85 -> 384.7
A87: 2.3 | B87: INFRAESTRUTURA
A88: ='BM-01'!A33 -> 2.3.1 | B88: ='BM-01'!D33 -> EMBASAMENTO C/PEDRA ARGAMASSADA UTILIZANDO ARG.CIM/AREIA 1:4 | J88: =ROUND(SUM(J89:J90),2) -> 105.04 | K88: ='BM-01'!F33 -> M3
B89: Escavações alvenaria de pedra (Perímetro das vigas baldrames x Larg. x Altura): (Volume/Seção) x (Larg. x Altura)= (12,40/(0,19*0,19))*(0,45*0,60) | C89: =((12.4/(0.19*0.19))*(0.45*0.6)) -> 92.742382 | J89: =C89 -> 92.742382 | Q89: =C89*D89 -> 0
B90: Embasamento paredes do corredor central (8,60+38,90)*(0,45*0,60) | C90: =(8.6+38.9)*(0.4314*0.6) -> 12.2949 | J90: =C90 -> 12.2949 | Q90: =C90*D90 -> 0
A92: ='BM-01'!A34 -> 2.3.2 | B92: ='BM-01'!D34 -> ALVENARIA DE 1 VEZ VEDACAO COM BLOCOS CERAMICO FURADOS 9 X 19 X 19 CM FUROS HORIZONTAIS, ESPESSURA DA PAREDE 19 CM, JUNTAS DE 10 MM COM ARGAMASSA TRACO 1:2:8 (CIMENTO, CAL E AREIA MEDIA) | J92: =J93 -> 35.13 | K92: ='BM-01'!F34 -> M2
B93: Quantitativo calculado abaixo, sendo medido apenas o quantitativo existente na planilha | J93: =35.13 -> 35.13
B94: Comprimento das paredes x altura média com relação ao terreno natural: (12,40/(0,19*0,19))*(1,10-0,19) | C94: 1 | D94: =(12.4/(0.19*0.19)) -> 343.4903 | F94: =(1.1-0.19) -> 0.91 | I94: =D94*F94 -> 312.57618 | J94: =C94*I94 -> 312.57618
A96: ='BM-01'!A35 -> 2.3.3 | B96: ='BM-01'!D35 -> LASTRO DE CONCRETO MAGRO, APLICADO EM BLOCOS DE COROAMENTO OU SAPATAS.AF_08/2017 | J96: =ROUND(SUM(J97:J131),2) -> 6.13 | K96: ='BM-01'!F35 -> M3
B97: S41=S48=S50=S66=S73 | C97: 5 | D97: 0.9 | E97: 0.75 | F97: 0.0712 | I97: =D97*E97*F97 -> 0.04806 | J97: =C97*I97 -> 0.2403
B98: S28=S37=S40 | C98: 3 | D98: 0.9 | E98: 0.9 | F98: 0.0712 | I98: =D98*E98*F98 -> 0.057672 | J98: =C98*I98 -> 0.173016
B99: S1=S4=S6=S8=S10=S52 | C99: 6 | D99: 1 | E99: 0.85 | F99: 0.0712 | I99: =D99*E99*F99 -> 0.06052 | J99: =C99*I99 -> 0.36312
B100: S13 | C100: 1 | D100: 1.05 | E100: 0.85 | F100: 0.0712 | I100: =D100*E100*F100 -> 0.063546 | J100: =C100*I100 -> 0.063546
B101: S31=S33=S35 | C101: 3 | D101: 0.95 | E101: 1.3 | F101: 0.0712 | I101: =D101*E101*F101 -> 0.087932 | J101: =C101*I101 -> 0.263796
B102: S32=S34=S36=S38=S43 | C102: 5 | D102: 0.7 | E102: 0.7 | F102: 0.0712 | I102: =D102*E102*F102 -> 0.034888 | J102: =C102*I102 -> 0.17444
B103: S30 | C103: 1 | D103: 0.75 | E103: 0.75 | F103: 0.0712 | I103: =D103*E103*F103 -> 0.04005 | J103: =C103*I103 -> 0.04005
B104: S47 | C104: 1 | D104: 0.85 | E104: 0.7 | F104: 0.0712 | I104: =D104*E104*F104 -> 0.042364 | J104: =C104*I104 -> 0.042364
B105: S49 | C105: 1 | D105: 0.9 | E105: 0.7 | F105: 0.0712 | I105: =D105*E105*F105 -> 0.044856 | J105: =C105*I105 -> 0.044856
B106: S2=S12 | C106: 2 | D106: 1.05 | E106: 0.9 | F106: 0.0712 | I106: =D106*E106*F106 -> 0.067284 | J106: =C106*I106 -> 0.134568
B107: S58=S59 | C107: 2 | D107: 1.1 | E107: 0.9 | F107: 0.0712 | I107: =D107*E107*F107 -> 0.070488 | J107: =C107*I107 -> 0.140976
B108: S27=S53 | C108: 2 | D108: 1.1 | E108: 0.95 | F108: 0.0712 | I108: =D108*E108*F108 -> 0.074404 | J108: =C108*I108 -> 0.148808
... B131: S15 | C131: 1 | D131: 1.65 | E131: 1.55 | F131: 0.0712 | I131: =D131*E131*F131 -> 0.182094 | J131: =C131*I131 -> 0.182094
A133: ='BM-01'!A36 -> 2.3.4 | B133: ='BM-01'!D36 -> CONCRETO ARMADO (PREPARO E LANCAMENTO)PARA SAPATAS COM FCK >= 25MPA, COM FORMA DE TABUA, COM APROVEI TAMENTO DE 2 VEZES, COM BETONEIRA - | J133: =ROUND(SUM(J134:J134),2) -> 19.55 | K133: ='BM-01'!F36 -> M3
B134: Projeto estrutural das sapatas | C134: =19.55 -> 19.55 | J134: =C134 -> 19.55
A136: ='BM-01'!A37 -> 2.3.5 | B136: ='BM-01'!D37 -> CONCRETO ARMADO (PREPARO E LANCAMENTO) PARA RADIER COM FCK>=25MPA, COM TABUA DE MADEIRA, COM APROVEITAMENTO DE 3 VEZES COM BETONEIRA - | J136: =ROUND(SUM(J137:J137),2) -> 12.33 | K136: ='BM-01'!F37 -> M3
B137: Projeto estrutural das vigas baldrames (12,40 m³), sendo medido 12,33 m³ disponível na planilha | C137: =12.33 -> 12.33 | J137: =C137 -> 12.33
