Workbook

Sheet ADITIVO
E1: PREFEITURA MUNICIPAL DE COREMAS
E2: OBRA: REFORMA DA ESCOLA DO LOGRADOURO - ADITIVO | L2: Data Base: | M2: Outubro/2019
E3: MUNICÍPIO: COREMAS-PB | L3: BDI: | M3: 0.19211564
E4: ENDEREÇO: ZONA URBANA | L4: Encargos | M4: Não Desonerados
B6: PLANILHA ORÇAMENTÁRIA | L6: BDI = 19,21% Não Desonerado117,54% hora 73,43%mês
B8: ITEM | C8: CÓDIGO | D8: FONTE | E8: DESCRIÇÃO DOS SERVIÇOS | F8: UNID. | G8: QUANTIDADE | J8: V.Unit.(R$) | K8: V.Unit. com BDI (R$) | L8: VALOR TOTAL R$
G9: LICITADA | H9: ACRESCIDO/SUPRIMIDO | I9: TOTAL 1° REPROGRAMAÇÃO | L9: LICITADA | M9: ACRESCIDO/SUPRIMIDO | N9: TOTAL 1° REPROGRAMAÇÃO
E10: REFORMA DA ESCOLA LOGRADOURO
B11: 1.0 | E11: DEMOLIÇÕES E RETIRADAS
B12: 1.1 | C12: 97622 | D12: SINAPI | E12: Demolição de alvenaria de bloco furado, de forma manual, sem reaproveitamento. af_12/2017 | F12: m² | G12: 39.72 | H12: 0 | I12: =G12+H12 -> 39.72 | J12: 1.03 | K12: =ROUND(J12*(1+$M$3),2) -> 1.23 | L12: =ROUND(G12*$K12,2) -> 48.86 | M12: =ROUND(H12*$K12,2) -> 0 | N12: =ROUND(I12*$K12,2) -> 48.86
B13: 1.2 | C13: 97644 | D13: SINAPI | E13: Remoção de portas, de forma manual, sem reaproveitamento. af_12/2017 | F13: m² | G13: 4.83 | I13: =G13+H13 -> 4.83 | J13: 5.49 | K13: =ROUND(J13*(1+$M$3),2) -> 6.54 | L13: =ROUND(G13*$K13,2) -> 31.59 | M13: =ROUND(H13*$K13,2) -> 0 | N13: =ROUND(I13*$K13,2) -> 31.59
B14: 1.3 | C14: 97663 | D14: SINAPI | E14: Remoção de louças, de forma manual, sem reaproveitamento. | F14: un | G14: 7 | I14: =G14+H14 -> 7 | J14: 7.25 | K14: =ROUND(J14*(1+$M$3),2) -> 8.64 | L14: =ROUND(G14*$K14,2) -> 60.48 | M14: =ROUND(H14*$K14,2) -> 0 | N14: =ROUND(I14*$K14,2) -> 60.48
B15: 1.4 | D15: CPU | E15: Demolição de piso cimentado | F15: m² | G15: 42.825 | I15: =G15+H15 -> 42.825 | J15: 18.99 | K15: =ROUND(J15*(1+$M$3),2) -> 22.64 | L15: =ROUND(G15*$K15,2) -> 969.56 | M15: =ROUND(H15*$K15,2) -> 0 | N15: =ROUND(I15*$K15,2) -> 969.56
B16: 1.5 | C16: 97636 | D16: SINAPI | E16: Demolição de revestimento cerâmico, de forma manual, sem reaproveitamento. af_12/2017 - Cozinha e WC | F16: m² | G16: 143.585 | I16: =G16+H16 -> 143.585 | J16: 8.24 | K16: =ROUND(J16*(1+$M$3),2) -> 9.82 | L16: =ROUND(G16*$K16,2) -> 1410 | M16: =ROUND(H16*$K16,2) -> 0 | N16: =ROUND(I16*$K16,2) -> 1410
B17: 1.6 | C17: 72897 | D17: SINAPI | E17: Carga manual de entulho em caminhão basculante 6 m³. | F17: m³ | G17: 12.4072 | I17: =G17+H17 -> 12.4072 | J17: 16.56 | K17: =ROUND(J17*(1+$M$3),2) -> 19.74 | L17: =ROUND(G17*$K17,2) -> 244.92 | M17: =ROUND(H17*$K17,2) -> 0 | N17: =ROUND(I17*$K17,2) -> 244.92
B18: 1.7 | C18: 97914 | D18: SINAPI | E18: Transporte com caminhão basculante de 6 m3, em via urbana pavimentada dmt até 30 km (unidade: m3xkm). af_01/2018 - material excedente(bota-fora) | F18: m3 x km | G18: 16.133 | I18: =G18+H18 -> 16.133 | J18: 1.09 | K18: =ROUND(J18*(1+$M$3),2) -> 1.3 | L18: =ROUND(G18*$K18,2) -> 20.97 | M18: =ROUND(H18*$K18,2) -> 0 | N18: =ROUND(I18*$K18,2) -> 20.97
B19: Subtotal 1.0 | L19: =SUM(L12:L18) -> 2786.38 | M19: =SUM(M12:M18) -> 0 | N19: =SUM(N12:N18) -> 2786.38
B20: 2.0 | E20: REVESTIMENTOS - PISOS E PAREDES
B21: 2.1 | C21: 94990 | D21: SINAPI | E21: Execução de passeio (calçada) ou piso de concreto com concreto, espessura de 5 cm moldado in loco, feito em obra, acabamento convencional, não armado. af_07/2016 | F21: m³ | G21: 2.14125 | I21: =G21+H21 -> 2.14125 | J21: 481.46 | K21: =ROUND(J21*(1+$M$3),2) -> 573.96 | L21: =ROUND(G21*$K21,2) -> 1228.99 | M21: =ROUND(H21*$K21,2) -> 0 | N21: =ROUND(I21*$K21,2) -> 1228.99
B22: 2.2 | C22: 87894 | D22: SINAPI | E22: Chapisco aplicado em alvenaria (sem presença de vãos) e estruturas de concreto de fachada, com colher de pedreiro. argamassa traço 1:3 com preparo em betoneira 400l. af_06/2014 | F22: m² | G22: 5.4 | I22: =G22+H22 -> 5.4 | J22: 4.05 | K22: =ROUND(J22*(1+$M$3),2) -> 4.83 | L22: =ROUND(G22*$K22,2) -> 26.08 | M22: =ROUND(H22*$K22,2) -> 0 | N22: =ROUND(I22*$K22,2) -> 26.08
B23: 2.3 | C23: 87777 | D23: SINAPI | E23: Emboço ou massa única em argamassa traço 1:2:8, preparo manual, aplicada manualmente em panos de fachada com presença de vãos, espessura de 25 mm. af_06/2014 | F23: m² | G23: 5.4 | I23: =G23+H23 -> 5.4 | J23: 36.51 | K23: =ROUND(J23*(1+$M$3),2) -> 43.52 | L23: =ROUND(G23*$K23,2) -> 235.01 | M23: =ROUND(H23*$K23,2) -> 0 | N23: =ROUND(I23*$K23,2) -> 235.01
B24: 2.4 | C24: 88497 | D24: SINAPI | E24: Aplicação e lixamento de massa látex em paredes, duas demãos | F24: m² | G24: 809.27 | I24: =G24+H24 -> 809.27 | J24: 9.6 | K24: =ROUND(J24*(1+$M$3),2) -> 11.44 | L24: =ROUND(G24*$K24,2) -> 9258.05 | M24: =ROUND(H24*$K24,2) -> 0 | N24: =ROUND(I24*$K24,2) -> 9258.05
B25: 2.5 | C25: 88485 | D25: SINAPI | E25: Aplicação de fundo selador acrílico em paredes, uma demão. af_06/2014 | F25: m² | G25: 809.27 | I25: =G25+H25 -> 809.27 | J25: 1.7 | K25: =ROUND(J25*(1+$M$3),2) -> 2.03 | L25: =ROUND(G25*$K25,2) -> 1642.82 | M25: =ROUND(H25*$K25,2) -> 0 | N25: =ROUND(I25*$K25,2) -> 1642.82
B26: 2.6 | C26: 88489 | D26: SINAPI | E26: Aplicação manual de pintura com tinta látex acrílica em paredes, duas demãos. af_06/2014 | F26: m² | G26: 809.27 | I26: =G26+H26 -> 809.27 | J26: 11.22 | K26: =ROUND(J26*(1+$M$3),2) -> 13.38 | L26: =ROUND(G26*$K26,2) -> 10828.03 | M26: =ROUND(H26*$K26,2) -> 0 | N26: =ROUND(I26*$K26,2) -> 10828.03
B27: 2.7 | C27: 87272 | D27: SINAPI | E27: Revestimento cerâmico para paredes internas com placas tipo esmaltadaextra de dimensões 33x45 cm aplicadas em ambientes de área menor que 5 m² na altura inteira das paredes. af_06/2014 - WCs | F27: m² | G27: 238.47 | I27: =G27+H27 -> 238.47 | J27: 53.57 | K27: =ROUND(J27*(1+$M$3),2) -> 63.86 | L27: =ROUND(G27*$K27,2) -> 15228.69 | M27: =ROUND(H27*$K27,2) -> 0 | N27: =ROUND(I27*$K27,2) -> 15228.69 | P27: =800.8+142.1+936.6 -> 1879.5
B28: 2.8 | C28: 87273 | D28: SINAPI | E28: Revestimento cerâmico para paredes internas com placas tipo esmaltadaextra de dimensões 33x45 cm aplicadas em ambientes de área maior que 5 m² na altura inteira das paredes. af_06/2014 - Cozinha/Serviço | F28: m² | G28: 4.272 | H28: 35.46941 | I28: =G28+H28 -> 39.74141 | J28: 45.66 | K28: =ROUND(J28*(1+$M$3),2) -> 54.43 | L28: =ROUND(G28*$K28,2) -> 232.52 | M28: =ROUND(H28*$K28,2) -> 1930.6 | N28: =ROUND(I28*$K28,2) -> 2163.12 | P28: =P27/K28 -> 34.53059
B29: 2.9 | C29: 87246 | D29: SINAPI | E29: Revestimento cerâmico para piso com placas tipo grês de dimensões 35x35 cm aplicada em ambientes de área maior que 10 m² | F29: m2 | G29: 298.35 | I29: =G29+H29 -> 298.35 | J29: 43.73 | K29: =ROUND(J29*(1+$M$3),2) -> 52.13 | L29: =ROUND(G29*$K29,2) -> 15552.99 | M29: =ROUND(H29*$K29,2) -> 0 | N29: =ROUND(I29*$K29,2) -> 15552.99
B30: 2.10 | C30: 92402 | D30: SINAPI | E30: Execução de passeio em piso intertravado, com bloco 16 faces (na coloração natural) de (22 x 11) cm, espessura de 6cm. AF_12/2015.- PASSEIO EXTERNO | F30: m² | G30: 0 | H30: ='Memória de Cálculo'!D7 -> 105.19 | I30: =G30+H30 -> 105.19 | J30: 44.85 | K30: =ROUND(J30*(1+$M$3),2) -> 53.47 | L30: =ROUND(G30*$K30,2) -> 0 | M30: =ROUND(H30*$K30,2) -> 5624.51 | N30: =ROUND(I30*$K30,2) -> 5624.51 | Q30: 3810.1
B31: Subtotal 2.0 | L31: =SUM(L21:L30) -> 54233.18 | M31: =SUM(M21:M30) -> 7555.11 | N31: =SUM(N21:N30) -> 61788.29
B32: 3.0 | E32: COBERTA
B33: 3.1 | C33: 88496 | D33: SINAPI | E33: Aplicação e lixamento de massa látex em teto, duas demãos. | F33: m² | G33: 293.1055 | I33: =G33+H33 -> 293.1055 | J33: 17.55 | K33: =ROUND(J33*(1+$M$3),2) -> 20.92 | L33: =ROUND(G33*$K33,2) -> 6131.77 | M33: =ROUND(H33*$K33,2) -> 0 | N33: =ROUND(I33*$K33,2) -> 6131.77
B34: 3.2 | C34: 88482 | D34: SINAPI | E34: Aplicação de fundo selador látex pva em teto, uma demão. af_06/2014 | F34: m² | G34: 293.1055 | I34: =G34+H34 -> 293.1055 | J34: 2.4 | K34: =ROUND(J34*(1+$M$3),2) -> 2.86 | L34: =ROUND(G34*$K34,2) -> 838.28 | M34: =ROUND(H34*$K34,2) -> 0 | N34: =ROUND(I34*$K34,2) -> 838.28
B35: 3.3 | C35: 88486 | D35: SINAPI | E35: Aplicação manual de pintura com tinta látex pva em teto, duas demãos.af_06/2014 | F35: m² | G35: 293.1055 | I35: =G35+H35 -> 293.1055 | J35: 9.88 | K35: =ROUND(J35*(1+$M$3),2) -> 11.78 | L35: =ROUND(G35*$K35,2) -> 3452.78 | M35: =ROUND(H35*$K35,2) -> 0 | N35: =ROUND(I35*$K35,2) -> 3452.78
B36: 3.4 | C36: 92542 | D36: SINAPI | E36: Trama de madeira composta por ripas, caibros e terças para telhados demais que 2 águas para telha cerâmica capa-canal, incluso transporte v ertical. af_07/2019 | F36: m² | G36: 298.35 | I36: =G36+H36 -> 298.35 | J36: 57.97 | K36: =ROUND(J36*(1+$M$3),2) -> 69.11 | L36: =ROUND(G36*$K36,2) -> 20618.97 | M36: =ROUND(H36*$K36,2) -> 0 | N36: =ROUND(I36*$K36,2) -> 20618.97
B37: 3.4 | C37: 94445 | D37: SINAPI | E37: Telhamento com telha cerâmica capa-canal, tipo plan, com até 2 águas,incluso transporte vertical. af_07/2019 | F37: m² | G37: 298.35 | I37: =G37+H37 -> 298.35 | J37: 23.34 | K37: =ROUND(J37*(1+$M$3),2) -> 27.82 | L37: =ROUND(G37*$K37,2) -> 8300.1 | M37: =ROUND(H37*$K37,2) -> 0 | N37: =ROUND(I37*$K37,2) -> 8300.1
B38: Subtotal 3.0 | L38: =SUM(L33:L37) -> 39341.9 | M38: =SUM(M33:M37) -> 0 | N38: =SUM(N33:N37) -> 39341.9
B39: 4.0 | E39: ESQUADRIAS
B40: 4.1 | C40: 73739/001 | D40: SINAPI | E40: Pintura esmalte acetinado em madeira, duas demaos | F40: m² | G40: 11.76 | I40: =G40+H40 -> 11.76 | J40: 13.29 | K40: =ROUND(J40*(1+$M$3),2) -> 15.84 | L40: =ROUND(G40*$K40,2) -> 186.28 | M40: =ROUND(H40*$K40,2) -> 0 | N40: =ROUND(I40*$K40,2) -> 186.28
B41: 4.2 | C41: 73924/002 | D41: SINAPI | E41: Pintura esmalte acetinado, duas demaos, sobre superficie metalica | F41: m² | G41: 37.31 | I41: =G41+H41 -> 37.31 | J41: 20.31 | K41: =ROUND(J41*(1+$M$3),2) -> 24.21 | L41: =ROUND(G41*$K41,2) -> 903.28 | M41: =ROUND(H41*$K41,2) -> 0 | N41: =ROUND(I41*$K41,2) -> 903.28
B42: Subtotal 4.0 | L42: =SUM(L40:L41) -> 1089.56 | M42: =SUM(M40:M41) -> 0 | N42: =SUM(N40:N41) -> 1089.56
B43: 5.0 | E43: INSTALAÇÕES HIDROSANITÁRIAS
B44: 5.1 | C44: 86931 | D44: SINAPI | E44: Vaso sanitário sifonado com caixa acoplada louça branca, incluso engate flexível em plástico branco, 1/2 x 40cm - fornecimento e instalação . af_12/2013 | F44: un | G44: 4 | I44: =G44+H44 -> 4 | J44: 353.39 | K44: =ROUND(J44*(1+$M$3),2) -> 421.28 | L44: =ROUND(G44*$K44,2) -> 1685.12 | M44: =ROUND(H44*$K44,2) -> 0 | N44: =ROUND(I44*$K44,2) -> 1685.12
B45: 5.2 | C45: 86943 | D45: SINAPI | E45: Lavatório louça branca suspenso, 29,5 x 39cm ou equivalente, padrão popular, incluso sifão flexível em pvc, válvula e engate flexível 30cm em plástico e torneira cromada de mesa, padrão popular - fornecimento e instalação. af_12/2013 | F45: un | G45: 2 | I45: =G45+H45 -> 2 | J45: 160.6 | K45: =ROUND(J45*(1+$M$3),2) -> 191.45 | L45: =ROUND(G45*$K45,2) -> 382.9 | M45: =ROUND(H45*$K45,2) -> 0 | N45: =ROUND(I45*$K45,2) -> 382.9
B46: 5.3 | C46: I 007608 | D46: SINAPI | E46: Chuveiro plastico branco simples 5 '' para acoplar em haste 1/2 ", agua fria | F46: un | G46: 1 | I46: =G46+H46 -> 1 | J46: 3.13 | K46: =ROUND(J46*(1+$M$3),2) -> 3.73 | L46: =ROUND(G46*$K46,2) -> 3.73 | M46: =ROUND(H46*$K46,2) -> 0 | N46: =ROUND(I46*$K46,2) -> 3.73
B47: 5.4 | C47: 95544 | D47: SINAPI | E47: Papeleira de parede em metal cromado sem tampa, incluso fixação | F47: un | G47: 4 | I47: =G47+H47 -> 4 | J47: 24.27 | K47: =ROUND(J47*(1+$M$3),2) -> 28.93 | L47: =ROUND(G47*$K47,2) -> 115.72 | M47: =ROUND(H47*$K47,2) -> 0 | N47: =ROUND(I47*$K47,2) -> 115.72
B48: 5.5 | C48: 95547 | D48: SINAPI | E48: Saboneteira plastica tipo dispenser para sabonete liquido | F48: un | G48: 1 | I48: =G48+H48 -> 1 | J48: 54.36 | K48: =ROUND(J48*(1+$M$3),2) -> 64.8 | L48: =ROUND(G48*$K48,2) -> 64.8 | M48: =ROUND(H48*$K48,2) -> 0 | N48: =ROUND(I48*$K48,2) -> 64.8
B49: Subtotal 5.0 | L49: =SUM(L44:L48) -> 2252.27 | M49: =SUM(M44:M48) -> 0 | N49: =SUM(N44:N48) -> 2252.27
B50: 6.0 | E50: SERVIÇOS FINAIS
B51: 6.1 | C51: 83696/001 | D51: SINAPI | E51: Pintura de alvenaria com cal. | F51: m² | G51: 241.5 | I51: =G51+H51 -> 241.5 | J51: 4.33 | K51: =ROUND(J51*(1+$M$3),2) -> 5.16 | L51: =ROUND(G51*$K51,2) -> 1246.14 | M51: =ROUND(H51*$K51,2) -> 0 | N51: =ROUND(I51*$K51,2) -> 1246.14
B52: 6.2 | D52: CPU | E52: Limpeza final da obra | F52: m² | G52: 282.82 | I52: =G52+H52 -> 282.82 | J52: 2.04 | K52: =ROUND(J52*(1+$M$3),2) -> 2.43 | L52: =ROUND(G52*$K52,2) -> 687.25 | M52: =ROUND(H52*$K52,2) -> 0 | N52: =ROUND(I52*$K52,2) -> 687.25
B53: Subtotal 6.0 | L53: =SUM(L51:L52) -> 1933.39 | M53: =SUM(M51:M52) -> 0 | N53: =SUM(N51:N52) -> 1933.39 | O53: =N19+N31+N38+N49+N53 -> 108102.23
E54: AMPLIAÇÃO DA ESCOLA
B55: 7.0 | E55: SERVIÇOS PRELIMINARES
B56: 7.1 | C56: 73859/002 | D56: SINAPI | E56: Capina e limpeza manual de terreno. | F56: m² | G56: 282.9305 | I56: =G56+H56 -> 282.9305 | J56: 1.03 | K56: =ROUND(J56*(1+$M$3),2) -> 1.23 | L56: =ROUND(G56*$K56,2) -> 348 | M56: =ROUND(H56*$K56,2) -> 0 | N56: =ROUND(I56*$K56,2) -> 348
B57: 7.2 | C57: 79472 | D57: SINAPI | E57: Regularizacao de superficies em terra com motoniveladora | F57: m² | G57: 282.9305 | I57: =G57+H57 -> 282.9305 | J57: 0.38 | K57: =ROUND(J57*(1+$M$3),2) -> 0.45 | L57: =ROUND(G57*$K57,2) -> 127.32 | M57: =ROUND(H57*$K57,2) -> 0 | N57: =ROUND(I57*$K57,2) -> 127.32
B58: 7.3 | D58: CPU | E58: Locação convencional de obra, através de gabarito de tábuas corridas pontaletadas a cada 1,50m, sem reaproveitamento | F58: m² | G58: 351.2369 | I58: =G58+H58 -> 351.2369 | J58: 3.87 | K58: =ROUND(J58*(1+$M$3),2) -> 4.61 | L58: =ROUND(G58*$K58,2) -> 1619.2 | M58: =ROUND(H58*$K58,2) -> 0 | N58: =ROUND(I58*$K58,2) -> 1619.2
B59: 7.4 | C59: 74209/001 | D59: SINAPI | E59: Placa indicativa de obra em chapa de aço galvanizado | F59: m² | G59: 8 | I59: =G59+H59 -> 8 | J59: 357.23 | K59: =ROUND(J59*(1+$M$3),2) -> 425.86 | L59: =ROUND(G59*$K59,2) -> 3406.88 | M59: =ROUND(H59*$K59,2) -> 0 | N59: =ROUND(I59*$K59,2) -> 3406.88
B60: Subtotal 7.0 | L60: =SUM(L56:L59) -> 5501.4 | M60: =SUM(M56:M59) -> 0 | N60: =SUM(N56:N59) -> 5501.4
B61: 8.0 | E61: MOVIMENTO DE TERRA
B62: 8.1 | C62: 93358 | D62: SINAPI | E62: Escavação manual em campo aberto, em solo exceto rocha, até 2,00m de profunididade | F62: m³ | G62: 10.71129 | I62: =G62+H62 -> 10.71129 | J62: 51.38 | K62: =ROUND(J62*(1+$M$3),2) -> 61.25 | L62: =ROUND(G62*$K62,2) -> 656.07 | M62: =ROUND(H62*$K62,2) -> 0 | N62: =ROUND(I62*$K62,2) -> 656.07
B63: 8.2 | C63: 94342 | D63: SINAPI | E63: Aterro apiloado (manual) em camadas de 20cm, com material de empréstimo | F63: m³ | G63: 24.496 | I63: =G63+H63 -> 24.496 | J63: 80.38 | K63: =ROUND(J63*(1+$M$3),2) -> 95.82 | L63: =ROUND(G63*$K63,2) -> 2347.21 | M63: =ROUND(H63*$K63,2) -> 0 | N63: =ROUND(I63*$K63,2) -> 2347.21
B64: Subtotal 8.0 | L64: =SUM(L62:L63) -> 3003.28 | M64: =SUM(M62:M63) -> 0 | N64: =SUM(N62:N63) -> 3003.28
B65: 9.0 | E65: INFRAESTRUTURA
B66: 9.1 | C66: 94962 | D66: SINAPI | E66: Concreto magro para lastro, traço 1:4,5:4,5 (cimento/ areia média/ brita 1) - preparo mecânico com betoneira 400 l. af_07/2016 | F66: m3 | G66: 0.44019 | I66: =G66+H66 -> 0.44019 | J66: 229.15 | K66: =ROUND(J66*(1+$M$3),2) -> 273.17 | L66: =ROUND(G66*$K66,2) -> 120.25 | M66: =ROUND(H66*$K66,2) -> 0 | N66: =ROUND(I66*$K66,2) -> 120.25
B67: 9.2 | C67: 92873 | D67: SINAPI | E67: Lançamento com uso de baldes, adensamento e acabamento de concreto em estruturas. af_12/2015 | F67: m3 | G67: 0.44019 | I67: =G67+H67 -> 0.44019 | J67: 132.98 | K67: =ROUND(J67*(1+$M$3),2) -> 158.53 | L67: =ROUND(G67*$K67,2) -> 69.78 | M67: =ROUND(H67*$K67,2) -> 0 | N67: =ROUND(I67*$K67,2) -> 69.78
B68: 9.3 | C68: 95467 | D68: SINAPI | E68: Embasamento com pedra argamassada utilizando argamassa de cimento e areia no traço 1:4 | F68: m3 | G68: 24.455 | I68: =G68+H68 -> 24.455 | J68: 332.9 | K68: =ROUND(J68*(1+$M$3),2) -> 396.86 | L68: =ROUND(G68*$K68,2) -> 9705.21 | M68: =ROUND(H68*$K68,2) -> 0 | N68: =ROUND(I68*$K68,2) -> 9705.21
B69: 9.4 | C69: 95955 | D69: SINAPI | E69: Execução de estruturas de concreto armado, para edificação habitacional unifamiliar térrea (casa isolada), fck = 25 mpa. af_01/2017 - vigas baldrames e blocos | F69: m³ | G69: 1.5782 | I69: =G69+H69 -> 1.5782 | J69: 1880.82 | K69: =ROUND(J69*(1+$M$3),2) -> 2242.15 | L69: =ROUND(G69*$K69,2) -> 3538.56 | M69: =ROUND(H69*$K69,2) -> 0 | N69: =ROUND(I69*$K69,2) -> 3538.56
B70: 9.5 | C70: 74106/001 | D70: SINAPI | E70: Impermeabilização de superfície com argamassa de cimento e areia média no traço 1:3, com aditivo impermeabilizante, e = 2cm, para funidação corrida | F70: m² | G70: 19.564 | I70: =G70+H70 -> 19.564 | J70: 8.48 | K70: =ROUND(J70*(1+$M$3),2) -> 10.11 | L70: =ROUND(G70*$K70,2) -> 197.79 | M70: =ROUND(H70*$K70,2) -> 0 | N70: =ROUND(I70*$K70,2) -> 197.79
B71: Subtotal 9.0 | L71: =SUM(L66:L70) -> 13631.59 | M71: =SUM(M66:M70) -> 0 | N71: =SUM(N66:N70) -> 13631.59
B72: 10.0 | E72: PAREDES E PAINÉIS
B73: 10.1 | C73: 87495 | D73: SINAPI | E73: Alvenaria de vedação de blocos cerâmicos furados na horizontal de 9x19x19cm (espessura 9cm) de paredes com área líquida maior ou igual a 6m² sem vãos e argamassa de assentamento com preparo em betoneira | F73: m2 | G73: 149.127 | I73: =G73+H73 -> 149.127 | J73: 53.36 | K73: =ROUND(J73*(1+$M$3),2) -> 63.61 | L73: =ROUND(G73*$K73,2) -> 9485.97 | M73: =ROUND(H73*$K73,2) -> 0 | N73: =ROUND(I73*$K73,2) -> 9485.97
B74: 10.2 | C74: 95955 | D74: SINAPI | E74: Execução de estruturas de concreto armado, para edificação habitacional unifamiliar térrea (casa isolada), fck = 25 mpa. af_01/2017 - Pilares e Vigas | F74: m3 | G74: 3.52935 | I74: =G74+H74 -> 3.52935 | J74: 1880.82 | K74: =ROUND(J74*(1+$M$3),2) -> 2242.15 | L74: =ROUND(G74*$K74,2) -> 7913.33 | M74: =ROUND(H74*$K74,2) -> 0 | N74: =ROUND(I74*$K74,2) -> 7913.33
B75: Subtotal 10.0 | L75: =SUM(L73:L74) -> 17399.3 | M75: =SUM(M73:M74) -> 0 | N75: =SUM(N73:N74) -> 17399.3
B76: 11.0 | E76: COBERTA
B77: 11.1 | D77: CPU | E77: Laje pre-moldada trelicada (lajotas + vigotas) para até 100 kg/m² vaos até 6,00m/incl vigotas tijolos armadura negativa capeamento 3cm concreto 20mpa escoramento material e mao de obra. | F77: m² | G77: 61.24 | I77: =G77+H77 -> 61.24 | J77: 79.48 | K77: =ROUND(J77*(1+$M$3),2) -> 94.75 | L77: =ROUND(G77*$K77,2) -> 5802.49 | M77: =ROUND(H77*$K77,2) -> 0 | N77: =ROUND(I77*$K77,2) -> 5802.49
B78: 11.2 | C78: 92542 | D78: SINAPI | E78: Estrutura de madeira de lei primeira qualidade, serrada, nao aparelhada, para telhas cerâmicas | F78: m² | G78: 44.8216 | I78: =G78+H78 -> 44.8216 | J78: 57.97 | K78: =ROUND(J78*(1+$M$3),2) -> 69.11 | L78: =ROUND(G78*$K78,2) -> 3097.62 | M78: =ROUND(H78*$K78,2) -> 0 | N78: =ROUND(I78*$K78,2) -> 3097.62
B79: 11.3 | C79: 94204 | D79: SINAPI | E79: Cobertura com telha cerâmica, com argamassa traço 1:3 de cimento e areia e arame recozido | F79: m² | G79: 44.8216 | I79: =G79+H79 -> 44.8216 | J79: 27.18 | K79: =ROUND(J79*(1+$M$3),2) -> 32.4 | L79: =ROUND(G79*$K79,2) -> 1452.22 | M79: =ROUND(H79*$K79,2) -> 0 | N79: =ROUND(I79*$K79,2) -> 1452.22
B80: 11.4 | C80: 74066/002 | D80: SINAPI | E80: Impermeabilizacao de superficie, com impermeabilizante flexivel a base acrilica. | F80: m² | G80: 61.24 | I80: =G80+H80 -> 61.24 | J80: 77.88 | K80: =ROUND(J80*(1+$M$3),2) -> 92.84 | L80: =ROUND(G80*$K80,2) -> 5685.52 | M80: =ROUND(H80*$K80,2) -> 0 | N80: =ROUND(I80*$K80,2) -> 5685.52
B81: 11.5 | C81: 94229 | D81: SINAPI | E81: Calha em chapa de aço galvanizado número 24, desenvolvimento de 100 cm, incluso transporte vertical. af_06/2016 | F81: m² | G81: 1.26 | I81: =G81+H81 -> 1.26 | J81: 111.38 | K81: =ROUND(J81*(1+$M$3),2) -> 132.78 | L81: =ROUND(G81*$K81,2) -> 167.3 | M81: =ROUND(H81*$K81,2) -> 0 | N81: =ROUND(I81*$K81,2) -> 167.3
B82: 11.6 | C82: 100435 | D82: SINAPI | E82: Rufo em fibrocimento para telha ondulada e = 6 mm, aba de 26 cm, incluso transporte vertical. af_06/2016 | F82: m | G82: 20.58 | I82: =G82+H82 -> 20.58 | J82: 28 | K82: =ROUND(J82*(1+$M$3),2) -> 33.38 | L82: =ROUND(G82*$K82,2) -> 686.96 | M82: =ROUND(H82*$K82,2) -> 0 | N82: =ROUND(I82*$K82,2) -> 686.96
B83: 11.7 | C83: 96113 | D83: SINAPI | E83: Forro em placas de gesso, para ambientes comerciais. af_05/2017_p | F83: m² | G83: 61.24 | I83: =G83+H83 -> 61.24 | J83: 24.55 | K83: =ROUND(J83*(1+$M$3),2) -> 29.27 | L83: =ROUND(G83*$K83,2) -> 1792.49 | M83: =ROUND(H83*$K83,2) -> 0 | N83: =ROUND(I83*$K83,2) -> 1792.49
B84: Subtotal 11.0 | L84: =SUM(L77:L83) -> 18684.6 | M84: =SUM(M77:M83) -> 0 | N84: =SUM(N77:N83) -> 18684.6
B85: 12.0 | E85: ESQUADRIAS
B86: 12.1 | C86: 90843 | D86: SINAPI | E86: Kit de porta de madeira para pintura, semi-oca (leve ou média), padrão médio, 80x210cm, espessura de 3,5cm, itens inclusos: dobradiças, montagem e instalação do batente, fechadura com execução do furo - fornecimento e instalação. af_08/2015 | F86: un | G86: 2 | I86: =G86+H86 -> 2 | J86: 673.66 | K86: =ROUND(J86*(1+$M$3),2) -> 803.08 | L86: =ROUND(G86*$K86,2) -> 1606.16 | M86: =ROUND(H86*$K86,2) -> 0 | N86: =ROUND(I86*$K86,2) -> 1606.16
B87: 12.2 | C87: 90842 | D87: SINAPI | E87: Kit de porta de madeira para pintura, semi-oca (leve ou média), padrão médio, 70x210cm, espessura de 3,5cm, itens inclusos: dobradiças, montagem e instalação do batente, fechadura com execução do furo - fornecimento e instalação. af_08/2015 | G87: 1 | I87: =G87+H87 -> 1 | J87: 653.86 | K87: =ROUND(J87*(1+$M$3),2) -> 779.48 | L87: =ROUND(G87*$K87,2) -> 779.48 | M87: =ROUND(H87*$K87,2) -> 0 | N87: =ROUND(I87*$K87,2) -> 779.48
B88: 12.3 | C88: 93190 | D88: SINAPI | E88: Verga moldada in loco com utilização de blocos canaleta para janelas com até 1,5 m de vão. af_03/2016 | F88: m | G88: 4.1 | I88: =G88+H88 -> 4.1 | J88: 24.59 | K88: =ROUND(J88*(1+$M$3),2) -> 29.31 | L88: =ROUND(G88*$K88,2) -> 120.17 | M88: =ROUND(H88*$K88,2) -> 0 | N88: =ROUND(I88*$K88,2) -> 120.17
B89: 12.4 | C89: 93198 | D89: SINAPI | E89: Contraverga moldada in loco com utilização de blocos canaleta para vãos de até 1,5 m de comprimento. af_03/2016 | F89: m | G89: 0.6 | I89: =G89+H89 -> 0.6 | J89: 21.23 | K89: =ROUND(J89*(1+$M$3),2) -> 25.31 | L89: =ROUND(G89*$K89,2) -> 15.19 | M89: =ROUND(H89*$K89,2) -> 0 | N89: =ROUND(I89*$K89,2) -> 15.19
B90: 12.5 | C90: 93191 | D90: SINAPI | E90: Verga moldada in loco com utilização de blocos canaleta para janelas com mais de 1,5 m de vão. af_03/2016 | F90: m | G90: 3.6 | I90: =G90+H90 -> 3.6 | J90: 25.55 | K90: =ROUND(J90*(1+$M$3),2) -> 30.46 | L90: =ROUND(G90*$K90,2) -> 109.66 | M90: =ROUND(H90*$K90,2) -> 0 | N90: =ROUND(I90*$K90,2) -> 109.66
B91: 12.6 | C91: 93199 | D91: SINAPI | E91: Contraverga moldada in loco com utilização de blocos canaleta para vãos de mais de 1,5 m de comprimento. af_03/2016 | F91: m | G91: 3.6 | I91: =G91+H91 -> 3.6 | J91: 20.86 | K91: =ROUND(J91*(1+$M$3),2) -> 24.87 | L91: =ROUND(G91*$K91,2) -> 89.53 | M91: =ROUND(H91*$K91,2) -> 0 | N91: =ROUND(I91*$K91,2) -> 89.53
B92: 12.7 | C92: 94581 | D92: SINAPI | E92: Janela de alumínio maxim-ar, fixação com argamassa, com vidros, padronizada. af_07/2016 - WC | F92: m² | G92: 0.16 | I92: =G92+H92 -> 0.16 | J92: 507.78 | K92: =ROUND(J92*(1+$M$3),2) -> 605.33 | L92: =ROUND(G92*$K92,2) -> 96.85 | M92: =ROUND(H92*$K92,2) -> 0 | N92: =ROUND(I92*$K92,2) -> 96.85
B93: 12.8 | C93: C1518 | D93: SEINFRA | E93: Janela de ferro | F93: m² | G93: 0 | H93: ='Memória de Cálculo'!D9 -> 4.2 | I93: =G93+H93 -> 4.2 | J93: =Resumo_Valor_Desconto!H19 -> 250.9214 | K93: =ROUND(J93*(1+$M$3),2) -> 299.13 | L93: =ROUND(G93*$K93,2) -> 0 | M93: =ROUND(H93*$K93,2) -> 1256.35 | N93: =ROUND(I93*$K93,2) -> 1256.35
B94: 12.9 | C94: C3659 | D94: SEINFRA | E94: Portão de metalon e barra chata de ferro c/fechadura e dobradiça, inclus. pintura esmalte sintético | F94: m² | G94: 0 | H94: ='Memória de Cálculo'!D10 -> 12.96 | I94: =G94+H94 -> 12.96 | J94: =Resumo_Valor_Desconto!H20 -> 364.16752 | K94: =ROUND(J94*(1+$M$3),2) -> 434.13 | L94: =ROUND(G94*$K94,2) -> 0 | M94: =ROUND(H94*$K94,2) -> 5626.32 | N94: =ROUND(I94*$K94,2) -> 5626.32
B95: Subtotal 12.0 | L95: =SUM(L86:L94) -> 2817.04 | M95: =SUM(M86:M94) -> 6882.67 | N95: =SUM(N86:N94) -> 9699.71
B96: 13.0 | E96: REVESTIMENTO
B97: 13.1 | C97: 87878 | D97: SINAPI | E97: Chapisco aplicado tanto em pilares e vigas de concreto como em alvenarias de paredes internas, com colher de pedreiro, argamassa traço 1:3 com preparo manual | F97: m² | G97: 303.084 | I97: =G97+H97 -> 303.084 | J97: 2.82 | K97: =ROUND(J97*(1+$M$3),2) -> 3.36 | L97: =ROUND(G97*$K97,2) -> 1018.36 | M97: =ROUND(H97*$K97,2) -> 0 | N97: =ROUND(I97*$K97,2) -> 1018.36
B98: 13.2 | C98: 87527 | D98: SINAPI | E98: Emboço, para recebimento de cerâmica, em argamassa traço 1:2:8, preparo manual com betoneira 400L, aplicado manualmente em faces internas de paredes de ambientes, espessura de 20mm, com execução de taliscas | F98: m2 | G98: 16.6155 | I98: =G98+H98 -> 16.6155 | J98: 23.68 | K98: =ROUND(J98*(1+$M$3),2) -> 28.23 | L98: =ROUND(G98*$K98,2) -> 469.06 | M98: =ROUND(H98*$K98,2) -> 0 | N98: =ROUND(I98*$K98,2) -> 469.06
B99: 13.3 | C99: 87264 | D99: SINAPI | E99: Revestimento cerâmico para paredes internas com placas tipo grês ou semi-grês de dimensões 25x35 cm aplicadas em ambientes de área maior que 5m² na altura inteira das paredes | F99: m2 | G99: 16.6155 | I99: =G99+H99 -> 16.6155 | J99: 46.65 | K99: =ROUND(J99*(1+$M$3),2) -> 55.61 | L99: =ROUND(G99*$K99,2) -> 923.99 | M99: =ROUND(H99*$K99,2) -> 0 | N99: =ROUND(I99*$K99,2) -> 923.99
B100: 13.4 | C100: 87530 | D100: SINAPI | E100: Massa única, para recebimento de pintura ou cerâmica, preparo manual em argamassa no traço 1:2:8, aplicado manualmente, em faces internas de paredes de ambientes com área maior que 10m2, espessura 10mm, sem taliscas | F100: m2 | G100: 303.084 | I100: =G100+H100 -> 303.084 | J100: 24.49 | K100: =ROUND(J100*(1+$M$3),2) -> 29.19 | L100: =ROUND(G100*$K100,2) -> 8847.02 | M100: =ROUND(H100*$K100,2) -> 0 | N100: =ROUND(I100*$K100,2) -> 8847.02
B101: Subtotal 13.0 | L101: =SUM(L97:L100) -> 11258.43 | M101: =SUM(M97:M100) -> 0 | N101: =SUM(N97:N100) -> 11258.43
B102: 14.0 | E102: PAVIMENTAÇÃO
...

Sheet cronograma
A2: =[1]ORÇAMENTO!E1 -> PREFEITURA MUNICIPAL DE COREMAS
A3: =[1]ORÇAMENTO!E2 -> OBRA: REFORMA DA ESCOLA DO LOGRADOURO
A4: =[1]ORÇAMENTO!E3 -> MUNICÍPIO: COREMAS-PB
A5: =[1]ORÇAMENTO!E4 -> ENDEREÇO: ZONA URBANA
A7: CRONOGRAMA FÍSICOFINANCEIRO - CFF
A9: ITEM | B9: DESCRIÇÃO DOS SERVIÇOS | C9: TOTAL | E9: MÊS 1 | F9: MÊS 2 | G9: MÊS 3 | H9: 2786.38
H10: 61788.29
B11: REFORMA DA ESCOLA DO LOGRADOURO | H11: 39341.9
A12: 1 | B12: DEMOLIÇÕES E RETIRADAS | C12: =H9 -> 2786.38 | D12: % | E12: 1 | H12: 1089.56
D13: DIAS | H13: 2252.27
D14: R$ | E14: =C12 -> 2786.38 | H14: 1933.39
A15: 2 | B15: REVESTIMENTOS - PISOS E PAREDES | C15: =H10 -> 61788.29 | D15: % | E15: 0.6 | F15: 0.4 | H15: 5501.4
D16: DIAS | H16: 3003.28
D17: R$ | E17: =C15*E15 -> 37072.974 | F17: =C15-E17 -> 24715.316 | H17: 13631.59
A18: 3 | B18: COBERTA | C18: =H11 -> 39341.9 | D18: % | E18: 0.6 | F18: 0.4 | H18: 17399.3
D19: DIAS | H19: 18684.6
D20: R$ | E20: =C18*E18 -> 23605.14 | F20: =C18-E20 -> 15736.76 | H20: 9699.71
A21: 4 | B21: ESQUADRIAS | C21: =H12 -> 1089.56 | D21: % | F21: 1 | H21: 11258.43
D22: DIAS | H22: 5310.86
D23: R$ | F23: =C21 -> 1089.56 | H23: 1348.59
A24: 5 | B24: INSTALAÇÕES HIDROSANITÁRIAS | C24: =H13 -> 2252.27 | D24: % | F24: 1 | H24: 3448.64
D25: DIAS | H25: 8319.31
D26: R$ | F26: =C24 -> 2252.27 | H26: 75518.72
A27: 6 | B27: SERVIÇOS FINAIS | C27: =H14 -> 1933.39 | D27: % | F27: 1 | H27: 4310.77
D28: DIAS | H28: 812.03
D29: R$ | F29: =C27 -> 1933.39 | H29: 220.13
B30: AMPLIAÇÃO DA ESCOLA DO LOGRADOURO | H30: 2694.36
A31: 7 | B31: SERVIÇOS PRELIMINARES | C31: =H15 -> 5501.4 | D31: % | E31: 1 | H31: 33913.07
D32: DIAS | H32: 10328.58
D33: R$ | E33: =C31 -> 5501.4 | H33: 18745.34
A34: 8 | B34: MOVIMENTO DE TERRA | C34: =H16 -> 3003.28 | D34: % | E34: 1 | H34: 53.52
D35: DIAS | H35: 355.36
D36: R$ | E36: =C34 -> 3003.28 | H36: 3341.62
A37: 9 | B37: INFRAESTRUTURA | C37: =H17 -> 13631.59 | D37: % | E37: 0.8 | F37: 0.2 | H37: 4402.09
D38: DIAS | H38: 7610.59
D39: R$ | E39: =C37*E37 -> 10905.272 | F39: =C37-E39 -> 2726.318
A40: 10 | B40: PAREDES E PAINÉIS | C40: =[1]ORÇAMENTO!J73 -> 17399.3 | D40: % | E40: 0.3 | F40: 0.7
D41: DIAS
D42: R$ | E42: =C40*E40 -> 5219.79 | F42: =C40-E42 -> 12179.51
A43: 11 | B43: COBERTA | C43: =[1]ORÇAMENTO!J82 -> 18684.6 | D43: % | F43: 0.7 | G43: 0.3
D44: DIAS
D45: R$ | F45: =C43*F43 -> 13079.22 | G45: =C43-F45 -> 5605.38
A46: 12 | B46: ESQUADRIAS | C46: =ADITIVO!N95 -> 9699.71 | D46: % | G46: 1
D47: DIAS
D48: R$ | G48: =C46 -> 9699.71
A49: 13 | B49: REVESTIMENTO | C49: =[1]ORÇAMENTO!J97 -> 11258.43 | D49: % | F49: 0.6 | G49: 0.4
D50: DIAS
D51: R$ | F51: =C49*F49 -> 6755.058 | G51: =C49-F51 -> 4503.372 | H51: 4310.77
A52: 14 | B52: PAVIMENTAÇÃO | C52: =[1]ORÇAMENTO!J102 -> 5310.86 | D52: % | F52: 0.4 | G52: 0.6 | H52: 812.03
D53: DIAS | H53: 220.13
D54: R$ | F54: =C52*F52 -> 2124.344 | G54: =C52-F54 -> 3186.516 | H54: 2694.36
A55: 15 | B55: INSTALAÇÃO HIDROSSANITÁRIA | C55: =[1]ORÇAMENTO!J126 -> 1348.59 | D55: % | G55: 1 | H55: 33913.07
D56: DIAS | H56: 10328.58
D57: R$ | G57: =C55 -> 1348.59 | H57: 18745.34
A58: 16 | B58: INSTALAÇÃO ELÉTRICA | C58: =[1]ORÇAMENTO!J132 -> 3448.64 | D58: % | G58: 1 | H58: 53.52
D59: DIAS | H59: 355.36
D60: R$ | G60: =C58 -> 3448.64 | H60: 3341.62
A61: 17 | B61: PINTURA | C61: =[1]ORÇAMENTO!J139 -> 8319.31 | D61: % | F61: 0.4 | G61: 0.6 | H61: 4402.09
D62: DIAS | H62: 7610.59
D63: R$ | F63: =C61*F61 -> 3327.724 | G63: =C61-F63 -> 4991.586
A64: 18 | B64: ÁREA DE RECREAÇÃO | C64: =ADITIVO!N161 -> 75518.72 | D64: % | E64: 0.3 | F64: 0.4 | G64: 0.3
D65: DIAS
D66: R$ | E66: =C64*E64 -> 22655.616 | F66: =C64*F64 -> 30207.488 | G66: =C64-E66-F66 -> 22655.616
A67: 19 | B67: JARDINAGEM | C67: =ADITIVO!N166 -> 4310.77 | G67: 1
G69: =C67 -> 4310.77
A70: 20 | B70: SERVIÇOS FINAIS | C70: =H52 -> 812.03 | D70: % | G70: 1
D71: DIAS
D72: R$ | G72: =C70 -> 812.03
B73: MURO DE ARRIMO
A74: 20 | B74: SERVIÇOS PRELIMINARES | C74: =ADITIVO!N173 -> 220.13 | D74: % | G74: 1
D75: DIAS
D76: R$ | G76: =C74 -> 220.13
A77: 20 | B77: MOVIMENTO DE TERRA | C77: =ADITIVO!N177 -> 2694.36 | D77: % | G77: 1
D78: DIAS
D79: R$ | G79: =C77 -> 2694.36
A80: 20 | B80: INFRAESTRUTURA - MURO DE ARRIMO | C80: =ADITIVO!N185 -> 33913.07 | D80: % | G80: 1
D81: DIAS
D82: R$ | G82: =C80 -> 33913.07
A83: 20 | B83: SUPERESTRUTURA - PILARES E VIGAS | C83: =ADITIVO!N201 -> 10328.58 | D83: % | G83: 1
D84: DIAS
D85: R$ | G85: =C83 -> 10328.58
A86: 20 | B86: PAREDES E PAINÉIS | C86: =ADITIVO!N209 -> 18745.34 | D86: % | G86: 1
D87: DIAS
D88: R$ | G88: =C86 -> 18745.34
B89: MURO LATERAL DIREITO
A90: 20 | B90: SERVIÇOS PRELIMINARES | C90: =ADITIVO!N214 -> 53.52 | D90: % | G90: 1 | H90: 355.36
D91: DIAS | H91: 3341.62
D92: R$ | G92: =C90 -> 53.52 | H92: 4402.09
A93: 20 | B93: MOVIMENTO DE TERRA | C93: =ADITIVO!N218 -> 355.36 | D93: % | G93: 1 | H93: 7610.59
D94: DIAS
D95: R$ | G95: =C93 -> 355.36
A96: 20 | B96: INFRAESTRUTURA | C96: =ADITIVO!N227 -> 3341.62 | D96: % | G96: 1
D97: DIAS
D98: R$ | G98: =C96 -> 3341.62
A99: 20 | B99: SUPERESTRUTURA - PILARES E VIGAS | C99: =ADITIVO!N243 -> 4402.09 | D99: % | G99: 1
D100: DIAS
D101: R$ | G101: =C99 -> 4402.09
A102: 20 | B102: PAREDES E PAINÉIS | C102: =ADITIVO!N251 -> 7610.59 | D102: % | G102: 1
D103: DIAS
D104: R$ | G104: =C102 -> 7610.59
...

Sheet Memória de Cálculo
B1: OBRA: REFORMA DA ESCOLA LOGRADOURO - ADITIVO
B2: MUNICÍPIO: COREMAS - PB
B3: ENDEREÇO: ZONA URBANA
A4: Item | B4: Descrição | C4: Und | D4: Quant. | E4: Memória de Cálculo
A5: 2.0 | B5: REVESTIMENTO - PISO E PAREDE
A6: 2.8 | B6: REVESTIMENTO CERÂMICO PARA PAREDES INTERNAS COM PLACAS TIPO ESMALTADAEXTRA DE DIMENSÕES 33X45 CM APLICADAS EM AMBIENTES DE ÁREA MAIOR QUE 5 M² NA ALTURA INTEIRA DAS PAREDES. AF_06/2014 - COZINHA/SERVIÇO | C6: m² | D6: 35.47 | E6: 35.47
A7: 2.10 | B7: EXECUÇÃO DE PASSEIO EM PISO INTERTRAVADO, COM BLOCO 16 FACES (NA COLORAÇÃO NATURAL) DE (22 X 11) CM, ESPESSURA DE 6CM. AF_12/2015. - PASSEIO EXTERNO e ACESSO LATERAL | C7: m² | D7: =TRUNC((24.61*1.2) + (25.22*3),2) -> 105.19 | E7: (24,61 x 1,20) + (25,22 X 3,00)
A8: 12 | B8: ESQUADRIAS
A9: 12.8 | B9: JANELA DE FERRO | C9: m² | D9: =(1.4*1)*2+(1.4*1)*1 -> 4.2 | E9: (1,40 x 1,00) x 2 + (1,40 x 1,00) x 1
A10: 12.9 | B10: PORTÃO DE METALON E BARRA CHATA DE FERRO C/FECHADURA E DOBRADIÇA, INCLUS. PINTURA ESMALTE SINTÉTICO | C10: m² | D10: =(2.4*2.4)+(3*2.4) -> 12.96 | E10: (2,40 x 2,40) + (3,00 x 2,40)
A11: 18 | B11: QUADRA
A12: 18.11 | B12: ALAMBRADO PARA QUADRA POLIESPORTIVA, ESTRUTURADO POR TUBOS DE ACO GALVANIZADO, COM COSTURA, DIN 2440, DIAMETRO 2", COM TELA DE ARAME GALVANIZADO, FIO 14 BWG E MALHA QUADRADA 5X5CM | C12: m² | D12: =TRUNC(188.2+((18.8+9.83)*3.5*2),2) -> 388.61 | E12: 188,20 + (18,80 + 9,83) x 3,50 x 2
A13: 18.12 | B13: FORNECIMENTO/INSTALACAO LONA PLASTICA PRETA, PARA IMPERMEABILIZACAO, ESPESSURA 150 MICRAS. | C13: m² | D13: 188.2 | E13: 188.2
A14: 18.13 | B14: PINTURA ACRILICA DE FAIXAS DE DEMARCACAO EM QUADRA , 5 CM DE LARGURA | D14: =796.09*0.05 -> 39.8045 | E14: 796,09 X 0,05
A15: 18.14 | B15: CONJUNTO PARA FUTSAL COM TRAVES OFICIAIS DE 3,00 X 2,00 M EM TUBO DE ACO GALVANIZADO 3" COM REQUADRO EM TUBO DE 1", PINTURA EM PRIMER COM TINTA ESMALTE SINTETICO E REDES DE POLIETILENO FIO 4 MM | D15: 1 | E15: 1
A16: 19 | B16: JADINAGEM
A17: 19.2 | B17: ESPALHAMETO MANUAL DE TERRA VEGETAL PARA PLANTIO DE GRAMA TIPO ESMERALDA. | C17: m³ | D17: =D18*0.1 -> 11.221 | E17: Área x Espessura = 112,21 x 0,10
A18: 19.3 | B18: PLANTIO DE GRAMA TIPO ESMERALDA, INCLUSIVE PREPARO DO SOLO. | C18: m² | D18: =44.58+67.63 -> 112.21 | E18: Área obtida no AutoCAD = Pátio 1 + Pátio 2 = 44,58 + 67,33
B19: MURO DE ARRIMO
A20: 21 | B20: SERVIÇOS PRELIMINARES
A21: 21.1 | B21: LOCACAO CONVENCIONAL DE OBRA, UTILIZANDO GABARITO DE TÁBUAS CORRIDAS PONTALETADAS A CADA 2,00M - 2 UTILIZAÇÕES. AF_10/2018 | C21: m² | D21: =TRUNC(((13.5 + 15.35 + 4.86) * 0.75) + ((6.34+5.26) * 1) + ((6.57 + 2.13) * 1.25),2) -> 47.75 | E21: [(13,50 + 15,35 + 4,86) x 0,75] + [(6,34 + 5,26) x 1,00] + [(6,57 + 2,13) x 1,25]
A22: 22.0 | B22: MOVIMENTO DE TERRA
A23: 22.1 | B23: ESCAVAÇÃO MANUAL DE VALA COM PROFUNDIDADE MENOR OU IGUAL A 1,30 M. AF_03/2016 | C23: m³ | D23: =TRUNC(((13.5 + 15.35 + 4.86) * 1.75)* 0.33 + ((6.34+5.26) * 2) * 0.25 + ((6.57 + 2.13)* 2.25)* 0.57,2) -> 36.42 | E23: [(13,50 + 15,35 + 4,86) x 1,75] x 0,33 + [(6,34+5,26) x 2,00] x 0,25 + [(6,57 + 2,13) x 2,25] x 0,57
A24: 22.2 | B24: REATERRO MANUAL DE VALAS COM COMPACTAÇÃO MECANIZADA. AF_04/2016 | C24: m³ | D24: =TRUNC((((13.5 + 15.35 + 4.86) * 1.75)* 0.33 + ((6.34+5.26) * 2) * 0.25 + ((6.57 + 2.13) * 2.25)* 0.57) - (13.5 + 15.35 + 4.86) * 0.75 * 0.33 - (5.26 * 1 * 0.25) -(6.57 + 2.13) *1.25* 0.57,2) -> 20.56 | E24: {[(13,50 + 15,35 + 4,86) x 1,75] x 0,33 + [(6,34+5,26) x 2,00] x 0,25 + [(6,57 + 2,13) x 2,25] x 0,57} - (13,50 + 15,35 + 4,86) x 0,75 x 0,33 + (5,26 x 1,00 x 0,25) + (6,57 + 2,13) x 1,25 x 0,57
A25: 23.0 | B25: INFRAESTRUTURA - MURO DE ARRIMO
A26: 23.1 | B26: CONCRETO MAGRO PARA LASTRO, TRAÇO 1:4,5:4,5 (CIMENTO/ AREIA MÉDIA/ BRITA 1) - PREPARO MECÂNICO COM BETONEIRA 400 L. AF_07/2016 | C26: m³ | D26: =TRUNC((((13.5+15.35+4.86)*0.85)+((6.34+5.26)*1.1)+((6.57+2.13)*1.35))*0.05,2) -> 2.65 | E26: {[(13,50 + 15,35 + 4,86) x 0,85] +[(6,34+5,26) x 1,10] + [(6,57 + 2,13) x 1,35]} x 0,05
A27: 23.2 | B27: LANÇAMENTO COM USO DE BALDES, ADENSAMENTO E ACABAMENTO DE CONCRETO EM ESTRUTURAS. AF_12/2015 | C27: m³ | D27: =TRUNC((((13.5+15.35+4.86)*0.85)+((6.34+5.26)*1.1)+((6.57+2.13)*1.35))*0.05,2) -> 2.65 | E27: {[(13,50 + 15,35 + 4,86) x 0,85] + [(6,34+5,26) x 1,10] + [(6,57 + 2,13) x 1,35]} x 0,05
A28: 23.3 | B28: EMBASAMENTO C/PEDRA ARGAMASSADA UTILIZANDO ARG.CIM/AREIA 1:4 | C28: m³ | D28: =TRUNC((0.68*13.5)+(0.68*15.35)+(1.18*6.34)+(1.93*6.57)+(1.93*2.13)+(1.18*5.26)+(0.67*4.86),2) -> 53.35 | E28: (0,68 x 13,50) + (0,68 x 15,35) + (1,18 x 6,34) + (1,93 x 6,57) + (1,93 x 2,13) + (1,18 x 5,26) + (0,67 x 4,86)
A29: 23.4 | B29: FABRICAÇÃO, MONTAGEM E DESMONTAGEM, EM MADEIRA SERRADA, E=25 MM, 4 UTILIZAÇÕES. AF_06/2017 | C29: m² | D29: =TRUNC((2.4*13.5)+(2.4*15.35)+(3.4*6.34)+(4.6*6.57)+(4.6*2.13)+(3.4*5.26)+(2.4*4.86),2) -> 160.36 | E29: (2,40 x 13,50) + (2,40 x 15,35) + (3,40 x 6,34) + (4,60 x 6,57) + (4,60 x 2,13) + (3,40 x 5,26) + (2,40 x 4,86)
A30: 23.5 | B30: IMPERMEABILIZACAO DE ESTRUTURAS ENTERRADAS, COM TINTA ASFALTICA, DUAS DEMAOS. | C30: m² | D30: =TRUNC((2.4*13.5)+(2.4*15.35)+(3.4*6.34)+(4.6*6.57)+(4.6*2.13)+(3.4*5.26)+(2.4*4.86),2) -> 160.36 | E30: (2,40 x 13,50) + (2,40 x 15,35) + (3,40 x 6,34) + (4,60 x 6,57) + (4,60 x 2,13) + (3,40 x 5,26) + (2,40 x 4,86)
A31: 23.6 | B31: EXECUCAO DE DRENO COM TUBOS DE PVC CORRUGADO FLÉXIVEL DE 50 MM | C31: M | D31: =(0.5*6)+(0.5*8)+((0.5*3)+(0.75*2))+((0.5*3)+(0.75*3))+((0.5*1)+(0.75*1))+((0.5*3)+(0.75*1))+(0.5*2) -> 18.25 | E31: (0,50 x 6) + (0,50 x 8) + [(0,50 x 3) + (0,75 x 2)] + [(0,50 x 3) + (0,75 x 3)] + [(0,50 x 1) + (0,75 x 1)] + [(0,50 x 3) + (0,75 x 1)] + (0,50 x 2)
A32: 24.0 | B32: SUPERESTRUTURA - PILARES E VIGAS
B33: PILARES
A34: 24.1 | B34: FABRICAÇÃO, MONTAGEM E DESMONTAGEM, EM MADEIRA SERRADA, E=25 MM, 4 UTILIZAÇÕES. AF_06/2017 | C34: m² | D34: =TRUNC((0.19+0.19+0.19+0.19)*1.83*18,2) -> 25.03 | E34: (0,19 + 0,19 + 0,19 + 0,19) x 1,83 x 18
A35: 24.2 | B35: ARMAÇÃO DE PILAR UTILIZANDO AÇO CA-60 DE 5 MM - MONTAGEM. AF_06/2017 | C35: KG | D35: =E35 -> 44 | E35: 44
A36: 24.3 | B36: ARMAÇÃO DE PILAR UTILIZANDO AÇO CA-50 DE 10 MM - MONTAGEM. AF_06/2017 | C36: KG | D36: =E36 -> 130 | E36: 130
A37: 24.4 | B37: CONCRETO FCK = 25MPA, TRAÇO 1:2,3:2,7 (CIMENTO/ AREIA MÉDIA/ BRITA 1) - PREPARO MECÂNICO COM BETONEIRA 400 L. AF_07/2016 | C37: m³ | D37: =TRUNC((0.19*0.19*1.83)*18,2) -> 1.18 | E37: (0,19 x 0,19 x 1,83) x 18
A38: 24.5 | B38: LANÇAMENTO COM USO DE BALDES, ADENSAMENTO E ACABAMENTO DE CONCRETO EM ESTRUTURAS. AF_12/2015 | C38: m³ | D38: =TRUNC((0.19*0.19*1.83)*18,2) -> 1.18 | E38: (0,19 x 0,19 x 1,83) x 18
B39: VIGAS BALDRAME E DE TOPO
A40: 24.6 | B40: FABRICAÇÃO, MONTAGEM E DESMONTAGEM, EM MADEIRA SERRADA, E=25 MM, 4 UTILIZAÇÕES. AF_06/2017 | C40: m² | D40: =TRUNC(((0.15+0.15)*(13.5+29.01+13.5))+((0.12+0.15+0.12)*(13.5+29.01+13.5)),2) -> 38.64 | E40: [(0,15 + 0,15) x (13,50 + 29,01 + 13,50)] + [(0,12 + 0,15 + 0,12) x (13,50 + 29,01 + 13,50)]
A41: 24.7 | B41: ARMAÇÃO DE BLOCO, VIGA UTILIZANDO AÇO CA-60 DE 5 MM - MONTAGEM. AF_06/2017 | C41: KG | D41: =E41 -> 85 | E41: 85
A42: 24.8 | B42: ARMAÇÃO DE BLOCO, VIGA UTILIZANDO AÇO CA-50 DE 6,3 MM - MONTAGEM. AF_06/2017 | C42: KG | D42: =E42 -> 31 | E42: 31
A43: 24.9 | B43: ARMAÇÃO DE BLOCO, VIGA UTILIZANDO AÇO CA-50 DE 8 MM - MONTAGEM. AF_06/2017 | C43: KG | D43: =E43 -> 89 | E43: 89
A44: 24.10 | B44: ARMAÇÃO DE BLOCO, VIGA UTILIZANDO AÇO CA-50 DE 10 MM - MONTAGEM. AF_06/2017 | C44: KG | D44: =E44 -> 84 | E44: 84
A45: 24.11 | B45: CONCRETO FCK = 25MPA, TRAÇO 1:2,3:2,7 (CIMENTO/ AREIA MÉDIA/ BRITA 1) - PREPARO MECÂNICO COM BETONEIRA 400 L. AF_07/2016 | C45: m³ | D45: =TRUNC(((0.15*0.19)*(13.5+29.01+13.5))+((0.12*0.15)*(13.5+29.01+13.5)),2) -> 2.6 | E45: [(0,15 x 0,19) x (13,50 + 29,01 + 13,50)] + [(0,12 x 0,15) x (13,50 + 29,01 + 13,50)]
A46: 24.12 | B46: LANÇAMENTO COM USO DE BALDES, ADENSAMENTO E ACABAMENTO DE CONCRETO EM ESTRUTURAS. AF_12/2015 | C46: m³ | D46: =TRUNC(((0.15*0.19)*(13.5+29.01+13.5))+((0.12*0.15)*(13.5+29.01+13.5)),2) -> 2.6 | E46: [(0,15 x 0,19) x (13,50 + 29,01 + 13,50)] + [(0,12 x 0,15) x (13,50 + 29,01 + 13,50)]
A47: 25.0 | B47: PAREDES E PAINÉIS
A48: 25.1 | B48: ALVENARIA DE VEDAÇÃO DE BLOCOS CERÂMICOS FURADOS NA HORIZONTAL DE 9X19X19CM (ESPESSURA 9CM) DE PAREDES COM ÁREA LÍQUIDA MENOR QUE 6M² SEM VÃOS E ARGAMASSA DE ASSENTAMENTO COM PREPARO EM BETONEIRA. AF_06/2014 | C48: m² | D48: =TRUNC((1.83*(13.5+29.01+13.5))-(0.19*1.83)*18,2) -> 96.23 | E48: 1,83 x (13,50 + 29,01 + 13,50) - (0,19 x 1,83) x 18
A49: 25.2 | B49: CHAPISCO APLICADO EM ALVENARIAS E ESTRUTURAS DE CONCRETO INTERNAS, COM COLHER DE PEDREIRO. ARGAMASSA TRAÇO 1:3 COM PREPARO MANUAL. AF_06/2014 | C49: m² | D49: =TRUNC(1.83*(13.5+29.01+13.5)*2+(13.5+29.01+13.5)*0.15,2) -> 213.39 | E49: [1,83 x (13,50 + 29,01 + 13,50)] x 2 + (13,50 + 29,01 + 13,50) x 0,15
A50: 25.3 | B50: MASSA ÚNICA, PARA RECEBIMENTO DE PINTURA, EM ARGAMASSA TRAÇO 1:2:8, PREPARO MANUAL, APLICADA MANUALMENTE EM FACES INTERNAS DE PAREDES, ESPESSURA DE 20MM, COM EXECUÇÃO DE TALISCAS. AF_06/2014 | C50: m² | D50: =TRUNC(1.83*(13.5+29.01+13.5)*2+(13.5+29.01+13.5)*0.15,2) -> 213.39 | E50: [1,83 x (13,50 + 29,01 + 13,50)] x 2 + (13,50 + 29,01 + 13,50) x 0,15
A51: 25.4 | B51: APLICAÇÃO DE FUNDO SELADOR ACRÍLICO EM PAREDES, UMA DEMÃO. AF_06/2014 | C51: m² | D51: =TRUNC(1.83*(13.5+29.01+13.5)*2+(13.5+29.01+13.5)*0.15,2) -> 213.39 | E51: [1,83 x (13,50 + 29,01 + 13,50)] x 2 + (13,50 + 29,01 + 13,50) x 0,15
A52: 25.5 | B52: APLICAÇÃO E LIXAMENTO DE MASSA LÁTEX EM PAREDES, DUAS DEMÃOS. AF_06/2014 | C52: m² | D52: =TRUNC(1.83*(13.5+29.01+13.5)*2+(13.5+29.01+13.5)*0.15,2) -> 213.39 | E52: [1,83 x (13,50 + 29,01 + 13,50)] x 2 + (13,50 + 29,01 + 13,50) x 0,15
A53: 25.6 | B53: APLICAÇÃO MANUAL DE PINTURA COM TINTA LÁTEX ACRÍLICA EM PAREDES, DUAS DEMÃOS. AF_06/2014 | C53: m² | D53: =TRUNC(1.83*(13.5+29.01+13.5)*2+(13.5+29.01+13.5)*0.15,2) -> 213.39 | E53: [1,83 x (13,50 + 29,01 + 13,50)] x 2 + (13,50 + 29,01 + 13,50) x 0,15
B54: MURO LATERAL DIREITA
A55: 26.0 | B55: SERVIÇOS PRELIMINARES
A56: 26.1 | B56: LOCACAO CONVENCIONAL DE OBRA, UTILIZANDO GABARITO DE TÁBUAS CORRIDAS PONTALETADAS A CADA 2,00M - 2 UTILIZAÇÕES. AF_10/2018 | C56: m² | D56: =TRUNC(0.5*23.22,2) -> 11.61 | E56: 0,50 X 23,22
A57: 27.0 | B57: MOVIMENTO DE TERRA
A58: 27.1 | B58: ESCAVAÇÃO MANUAL DE VALA COM PROFUNDIDADE MENOR OU IGUAL A 1,30 M. AF_03/2016 | C58: m³ | D58: =TRUNC(0.5*0.45*23.22,2) -> 5.22 | E58: 0,50 X 0,45 X 23,22
A59: 27.2 | B59: REATERRO MANUAL DE VALAS COM COMPACTAÇÃO MECANIZADA. AF_04/2016 | C59: m³ | D59: =TRUNC((0.5*0.45*23.22)-(0.4*0.4*22.72),2) -> 1.58 | E59: (0,50 X 0,45 X 23,22) - (0,40 X 0,40 X 22,72)
A60: 28.0 | B60: INFRAESTRUTURA
A61: 28.1 | B61: CONCRETO MAGRO PARA LASTRO, TRAÇO 1:4,5:4,5 (CIMENTO/ AREIA MÉDIA/ BRITA 1) - PREPARO MECÂNICO COM BETONEIRA 400 L. AF_07/2016 | C61: m³ | D61: =TRUNC(22.72*0.5*0.05,2) -> 0.56 | E61: 22,72 X 0,50 X 0,05
A62: 28.2 | B62: ARMAÇÃO DE PILAR UTILIZANDO AÇO CA-50 DE 10 MM - MONTAGEM. AF_06/2017 | C62: KG | D62: 15.55 | E62: 15.55
A63: 28.3 | B63: CONCRETO FCK = 25MPA, TRAÇO 1:2,3:2,7 (CIMENTO/ AREIA MÉDIA/ BRITA 1) - PREPARO MECÂNICO COM BETONEIRA 400 L. AF_07/2016 | C63: m³ | D63: =TRUNC((0.4*0.4*0.4)*7,2) -> 0.44 | E63: (0,40 X 0,40 X 0,40) X 7
A64: 28.4 | B64: LANÇAMENTO COM USO DE BALDES, ADENSAMENTO E ACABAMENTO DE CONCRETO EM ESTRUTURAS. AF_12/2015 | C64: m³ | D64: =TRUNC(D63+D61,2) -> 1 | E64: (22,72 X 0,50 X 0,05) + ((0,40 X 0,40 X 0,40) X 7)
A65: 28.5 | B65: EMBASAMENTO C/PEDRA ARGAMASSADA UTILIZANDO ARG.CIM/AREIA 1:4 | C65: m³ | D65: =TRUNC((22.72*0.4*0.4)-(0.4*0.4*0.4)*7,2) -> 3.18 | E65: (22,72 X 0,40 X 0,40) - (0,40 X 0,40 X 0,40) X 7
A66: 28.6 | B66: FABRICAÇÃO, MONTAGEM E DESMONTAGEM, EM MADEIRA SERRADA, E=25 MM, 4 UTILIZAÇÕES. AF_06/2017 | C66: m² | D66: =TRUNC(((22.72*0.4)*2+(0.4*0.4)*2),2) -> 18.49 | E66: (22,72 X 0,40) X 2 + (0,40 X 0,40) X 2
A67: 28.7 | B67: IMPERMEABILIZACAO DE ESTRUTURAS ENTERRADAS, COM TINTA ASFALTICA, DUAS DEMAOS. | C67: m² | D67: =TRUNC((0.4+0.4+0.4)*22.72+(0.4*0.4)+(0.15+0.19+0.15)*22.72,2) -> 38.55 | E67: (0,40 + 0,40 + 0,40) X 22,72 + (0,40 X 0,40) + (0,15 + 0,19 + 0,15) X 22,72
A68: 29.0 | B68: SUPERESTRUTURA - PILARES E VIGAS
B69: PILARES
A70: 29.1 | B70: FABRICAÇÃO, MONTAGEM E DESMONTAGEM, EM MADEIRA SERRADA, E=25 MM, 4 UTILIZAÇÕES. AF_06/2017 | C70: m² | D70: =TRUNC((0.19+0.19+0.19+0.19)*1.83*7,2) -> 9.73 | E70: (0,19 + 0,19 + 0,19 + 0,19) x 1,83 x 7
A71: 29.2 | B71: ARMAÇÃO DE PILAR UTILIZANDO AÇO CA-60 DE 5 MM - MONTAGEM. AF_06/2017 | C71: KG | D71: =E71 -> 17.28 | E71: 17.28
A72: 29.3 | B72: ARMAÇÃO DE PILAR UTILIZANDO AÇO CA-50 DE 10 MM - MONTAGEM. AF_06/2017 | C72: KG | D72: =E72 -> 50.61 | E72: 50.61
A73: 29.4 | B73: CONCRETO FCK = 25MPA, TRAÇO 1:2,3:2,7 (CIMENTO/ AREIA MÉDIA/ BRITA 1) - PREPARO MECÂNICO COM BETONEIRA 400 L. AF_07/2016 | C73: m³ | D73: =TRUNC((0.19*0.19*1.83)*7,2) -> 0.46 | E73: (0,19 x 0,19 x 1,83) x 7
A74: 29.5 | B74: LANÇAMENTO COM USO DE BALDES, ADENSAMENTO E ACABAMENTO DE CONCRETO EM ESTRUTURAS. AF_12/2015 | C74: m³ | D74: =TRUNC((0.19*0.19*1.83)*7,2) -> 0.46 | E74: (0,19 x 0,19 x 1,83) x 7
B75: VIGAS BALDRAME E DE TOPO
A76: 29.6 | B76: FABRICAÇÃO, MONTAGEM E DESMONTAGEM, EM MADEIRA SERRADA, E=25 MM, 4 UTILIZAÇÕES. AF_06/2017 | C76: m² | D76: =TRUNC(((0.15+0.15)*22.72)+((0.12+0.15+0.12)*22.72),2) -> 15.67 | E76: [(0,15 + 0,15) x 22,72] + [(0,12 + 0,15 + 0,12) x 22,72]
A77: 29.7 | B77: ARMAÇÃO DE BLOCO, VIGA UTILIZANDO AÇO CA-60 DE 5 MM - MONTAGEM. AF_06/2017 | C77: KG | D77: =28+30 -> 58 | E77: 28+30
A78: 29.8 | B78: ARMAÇÃO DE BLOCO, VIGA UTILIZANDO AÇO CA-50 DE 6,3 MM - MONTAGEM. AF_06/2017 | C78: KG | D78: =E78 -> 12 | E78: 12
A79: 29.9 | B79: ARMAÇÃO DE BLOCO, VIGA UTILIZANDO AÇO CA-50 DE 8 MM - MONTAGEM. AF_06/2017 | C79: KG | D79: =E79 -> 36 | E79: 36
A80: 29.10 | B80: ARMAÇÃO DE BLOCO, VIGA UTILIZANDO AÇO CA-50 DE 10 MM - MONTAGEM. AF_06/2017 | C80: KG | D80: =E80 -> 33 | E80: 33
A81: 29.11 | B81: CONCRETO FCK = 25MPA, TRAÇO 1:2,3:2,7 (CIMENTO/ AREIA MÉDIA/ BRITA 1) - PREPARO MECÂNICO COM BETONEIRA 400 L. AF_07/2016 | C81: m³ | D81: =TRUNC(((0.15*0.19)*22.72)+((0.12*0.15)*22.72),2) -> 1.05 | E81: [(0,15 x 0,19) x 22,72] + [(0,12 x 0,15) x 22,72]
A82: 29.12 | B82: LANÇAMENTO COM USO DE BALDES, ADENSAMENTO E ACABAMENTO DE CONCRETO EM ESTRUTURAS. AF_12/2015 | C82: m³ | D82: =TRUNC(((0.15*0.19)*22.72)+((0.12*0.15)*22.72),2) -> 1.05 | E82: [(0,15 x 0,19) x 22,72] + [(0,12 x 0,15) x 22,72]
A83: 30.0 | B83: PAREDES E PAINÉIS
A84: 30.1 | B84: ALVENARIA DE VEDAÇÃO DE BLOCOS CERÂMICOS FURADOS NA HORIZONTAL DE 9X19X19CM (ESPESSURA 9CM) DE PAREDES COM ÁREA LÍQUIDA MENOR QUE 6M² SEM VÃOS E ARGAMASSA DE ASSENTAMENTO COM PREPARO EM BETONEIRA. AF_06/2014 | C84: m² | D84: =TRUNC((1.83*22.72)-(0.19*1.83)*7,2) -> 39.14 | E84: 1,83 x 22,72 - (0,19 x 1,83) x 7
A85: 30.2 | B85: CHAPISCO APLICADO EM ALVENARIAS E ESTRUTURAS DE CONCRETO INTERNAS, COM COLHER DE PEDREIRO. ARGAMASSA TRAÇO 1:3 COM PREPARO MANUAL. AF_06/2014 | C85: m² | D85: =TRUNC(1.83*(22.72)*2+(22.72)*0.15,2) -> 86.56 | E85: [1,83 x 22,72] x 2 +( 22,72 x 0,15)
A86: 30.3 | B86: MASSA ÚNICA, PARA RECEBIMENTO DE PINTURA, EM ARGAMASSA TRAÇO 1:2:8, PREPARO MANUAL, APLICADA MANUALMENTE EM FACES INTERNAS DE PAREDES, ESPESSURA DE 20MM, COM EXECUÇÃO DE TALISCAS. AF_06/2014 | C86: m² | D86: =TRUNC(1.83*(22.72)*2+(22.72)*0.15,2) -> 86.56 | E86: [1,83 x 22,72] x 2 +( 22,72 x 0,15)
A87: 30.4 | B87: APLICAÇÃO DE FUNDO SELADOR ACRÍLICO EM PAREDES, UMA DEMÃO. AF_06/2014 | C87: m² | D87: =TRUNC(1.83*(22.72)*2+(22.72)*0.15,2) -> 86.56 | E87: [1,83 x 22,72] x 2 +( 22,72 x 0,15)
A88: 30.5 | B88: APLICAÇÃO E LIXAMENTO DE MASSA LÁTEX EM PAREDES, DUAS DEMÃOS. AF_06/2014 | C88: m² | D88: =TRUNC(1.83*(22.72)*2+(22.72)*0.15,2) -> 86.56 | E88: [1,83 x 22,72] x 2 +( 22,72 x 0,15)
A89: 30.6 | B89: APLICAÇÃO MANUAL DE PINTURA COM TINTA LÁTEX ACRÍLICA EM PAREDES, DUAS DEMÃOS. AF_06/2014 | C89: m² | D89: =TRUNC(1.83*(22.72)*2+(22.72)*0.15,2) -> 86.56 | E89: [1,83 x 22,72] x 2 +( 22,72 x 0,15)

Sheet CFF
B1: OBRA: REFORMA DA ESCOLA LOGRADOURO - ADITIVO
B2: MUNICÍPIO: COREMAS - PB
B3: ENDEREÇO: ZONA URBANA
A4: Cronograma Físico e Financeiro
A5: Item | B5: Descrição | C5: Total Por Etapa | D5: 30 DIAS | E5: 60 DIAS
A6: 1.0 | B6: REFORMA | C6: 100,00% 108.102,23 | D6: 100,00% 108.102,23
A7: 2.0 | B7: AMPLIAÇÃO | C7: 100,00% 172.936,37 | D7: 100,00% 172.936,37
A8: 3.0 | B8: MURO DE ARRIMO | C8: 100,00% 65.901,48 | D8: 40,00% 26.360,59 | E8: 60,00% 39.540,89
A9: 4.0 | B9: MURO LATERAL DIREITA | C9: 100,00% 17.763,18 | D9: 40,00% 7.105,27 | E9: 60,00% 10.657,91
A10: Porcentagem | C10: 369103.68 | D10: =D11/C10 -> 0.8639981 | E10: =E11/C10 -> 0.1360019
A11: Custo | D11: =C10-E11 -> 318904.88 | E11: =39540.89+10657.91 -> 50198.8 | G11: =SUM(G10:G10) -> 0 | H11: =SUM(H10:H10) -> 0
A12: Porcentagem Acumulado | D12: =D13/C10 -> 0.8639981 | E12: 100,0%
A13: Custo Acumulado | D13: =D11 -> 318904.88 | E13: =D13+E11 -> 369103.68

Sheet Resumo_Valor_Desconto
C1: OBRA: REFORMA DA ESCOLA LOGRADOURO - ADITIVO | E1: VALOR | H1: DESCONTO
C2: MUNICÍPIO: COREMAS - PB | E2: ORÇADO | G2: 287139.68 | H2: =1-(G3/G2) -> 0.050187734
C3: ENDEREÇO: ZONA URBANA | E3: LICITAÇÃO | G3: 272728.79
A4: Planilha de Preços Com Desconto
A5: Item | B5: Código | C5: Banco | D5: Descrição | E5: Und | F5: Valor Unit SINAPI 10/2019 | G5: Desconto | H5: Valor Unit sem BDI
A6: 1 | B6: 93382 | C6: SINAPI | D6: REATERRO MANUAL DE VALAS COM COMPACTAÇÃO MECANIZADA. AF_04/2016 | E6: m³ | F6: 19.92 | G6: =(F6*$H$2) -> 0.99973967 | H6: =F6-G6 -> 18.92026
A7: 2 | B7: 96534 | C7: SINAPI | D7: FABRICAÇÃO, MONTAGEM E DESMONTAGEM, EM MADEIRA SERRADA, E=25 MM, 4 UTILIZAÇÕES. AF_06/2017 | E7: m² | F7: 52.36 | G7: =(F7*$H$2) -> 2.6278298 | H7: =F7-G7 -> 49.73217
A8: 3 | B8: 00000057 | C8: Próprio | D8: EXECUCAO DE DRENO COM TUBOS DE PVC CORRUGADO FLEXIVEL PERFURADO - DN 50 | E8: M | F8: 22.71 | G8: =(F8*$H$2) -> 1.1397634 | H8: =F8-G8 -> 21.570237
A9: 4 | B9: 96543 | C9: SINAPI | D9: ARMAÇÃO DE PILAR UTILIZANDO AÇO CA-60 DE 5 MM - MONTAGEM. AF_06/2017 | E9: KG | F9: 10.92 | G9: =(F9*$H$2) -> 0.54805006 | H9: =F9-G9 -> 10.37195
A10: 5 | B10: 96546 | C10: SINAPI | D10: ARMAÇÃO DE PILAR UTILIZANDO AÇO CA-50 DE 10 MM - MONTAGEM. AF_06/2017 | E10: KG | F10: 7.48 | G10: =(F10*$H$2) -> 0.37540425 | H10: =F10-G10 -> 7.1045957
A11: 6 | B11: 94965 | C11: SINAPI | D11: CONCRETO FCK = 25MPA, TRAÇO 1:2,3:2,7 (CIMENTO/ AREIA MÉDIA/ BRITA 1) - PREPARO MECÂNICO COM BETONEIRA 400 L. AF_07/2016 | E11: m³ | F11: 302.53 | G11: =(F11*$H$2) -> 15.183295 | H11: =F11-G11 -> 287.3467
A12: 7 | B12: 96543 | C12: SINAPI | D12: ARMAÇÃO DE BLOCO, VIGA UTILIZANDO AÇO CA-60 DE 5 MM - MONTAGEM. AF_06/2017 | E12: KG | F12: 10.92 | G12: =(F12*$H$2) -> 0.54805006 | H12: =F12-G12 -> 10.37195
A13: 8 | B13: 96544 | C13: SINAPI | D13: ARMAÇÃO DE BLOCO, VIGA UTILIZANDO AÇO CA-50 DE 6,3 MM - MONTAGEM. AF_06/2017 | E13: KG | F13: 9.5 | G13: =(F13*$H$2) -> 0.47678348 | H13: =F13-G13 -> 9.0232165
A14: 9 | B14: 96545 | C14: SINAPI | D14: ARMAÇÃO DE BLOCO, VIGA UTILIZANDO AÇO CA-50 DE 8 MM - MONTAGEM. AF_06/2017 | E14: KG | F14: 9.15 | G14: =(F14*$H$2) -> 0.45921777 | H14: =F14-G14 -> 8.6907822
A15: 10 | B15: 96546 | C15: SINAPI | D15: ARMAÇÃO DE BLOCO, VIGA UTILIZANDO AÇO CA-50 DE 10 MM - MONTAGEM. AF_06/2017 | E15: KG | F15: 7.48 | G15: =(F15*$H$2) -> 0.37540425 | H15: =F15-G15 -> 7.1045957
A16: 11 | B16: 94965 | C16: SINAPI | D16: CONCRETO FCK = 25MPA, TRAÇO 1:2,3:2,7 (CIMENTO/ AREIA MÉDIA/ BRITA 1) - PREPARO MECÂNICO COM BETONEIRA 400 L. AF_07/2016 | E16: m³ | F16: 302.53 | G16: =(F16*$H$2) -> 15.183295 | H16: =F16-G16 -> 287.3467
A17: 12 | B17: 87894 | C17: SINAPI | D17: CHAPISCO APLICADO EM ALVENARIA (SEM PRESENÇA DE VÃOS) E ESTRUTURAS DE CONCRETO DE FACHADA, COM COLHER DE PEDREIRO. ARGAMASSA TRAÇO 1:3 COM PREPARO EM BETONEIRA 400L. AF_06/2014 | E17: m² | F17: 4.05 | G17: =(F17*$H$2) -> 0.20326032 | H17: =F17-G17 -> 3.8467397
A18: 13 | B18: 87530 | C18: SINAPI | D18: MASSA ÚNICA, PARA RECEBIMENTO DE PINTURA, EM ARGAMASSA TRAÇO 1:2:8, PREPARO MANUAL, APLICADA MANUALMENTE EM FACES INTERNAS DE PAREDES, ESPESSURA DE 20MM, COM EXECUÇÃO DE TALISCAS. AF_06/2014 | E18: m² | F18: 24.49 | G18: =(F18*$H$2) -> 1.2290976 | H18: =F18-G18 -> 23.260902
A19: 14 | B19: C1518 | C19: SEINFRA | D19: JANELA DE FERRO | E19: m² | F19: 264.18 | G19: =(F19*$H$2) -> 13.258596 | H19: =F19-G19 -> 250.9214
A20: 15 | B20: C3659 | C20: SEINFRA | D20: PORTÃO DE METALON E BARRA CHATA DE FERRO C/FECHADURA E DOBRADIÇA, INCLUS. PINTURA ESMALTE SINTÉTICO | E20: m² | F20: 383.41 | G20: =(F20*$H$2) -> 19.242479 | H20: =F20-G20 -> 364.16752
A21: 16 | C21: CPU | D21: ESPALHAMETO MANUAL DE TERRA VEGETAL PARA PLANTIO DE GRAMA TIPO ESMERALDA. | E21: m² | F21: ='COMPOS_NÃO_DESONER.'!F12 -> 159.54 | G21: =(F21*$H$2) -> 8.0069511 | H21: =F21-G21 -> 151.53305
A22: 17 | B22: 85180 | C22: SINAPI | D22: PLANTIO DE GRAMA TIPO ESMERALDA, INCLUSIVE PREPARO DO SOLO. | E22: m² | F22: 15.5 | G22: =(F22*$H$2) -> 0.77790988 | H22: =F22-G22 -> 14.72209
A23: 18 | B23: 74244/001 | C23: SINAPI | D23: ALAMBRADO PARA QUADRA POLIESPORTIVA, ESTRUTURADO POR TUBOS DE ACO GALVANIZADO, COM COSTURA, DIN 2440, DIAMETRO 2", COM TELA DE ARAME GALVANIZADO, FIO 14 BWG E MALHA QUADRADA 5X5CM | E23: m² | F23: 114.78 | G23: =(F23*$H$2) -> 5.7605482 | H23: =F23-G23 -> 109.01945
A24: 19 | C24: CPU | D24: PORTÃO METÁLICO 1 FOLHAS DE ABRIR COM ESTRUTURA EM TUBOS DE AÇO E TELA GALVANIZADA | E24: und | G24: =(F24*$H$2) -> 0 | H24: =F24-G24 -> 0
A25: 19 | B25: 68053 | C25: SINAPI | D25: FORNECIMENTO/INSTALACAO LONA PLASTICA PRETA, PARA IMPERMEABILIZACAO, ESPESSURA 150 MICRAS. | F25: 4.79 | G25: =(F25*$H$2) -> 0.24039925 | H25: =F25-G25 -> 4.5496008
A26: 19 | B26: 41595 | C26: SINAPI | D26: PINTURA ACRILICA DE FAIXAS DE DEMARCACAO EM QUADRA , 5 CM DE LARGURA | E26: m² | F26: 9.23 | G26: =(F26*$H$2) -> 0.46323279 | H26: =F26-G26 -> 8.7667672
A27: 19 | B27: I 25398 | C27: SINAPI | D27: CONJUNTO PARA FUTSAL COM TRAVES OFICIAIS DE 3,00 X 2,00 M EM TUBO DE ACO GALVANIZADO 3" COM REQUADRO EM TUBO DE 1", PINTURA EM PRIMER COM TINTA ESMALTE SINTETICO E REDES DE POLIETILENO FIO 4 MM | E27: und | F27: 2497.16 | G27: =(F27*$H$2) -> 125.3268 | H27: =F27-G27 -> 2371.8332

Sheet COMPOS_NÃO_DESONER.
B1: PREFEITURA MUNICIPAL DE COREMAS
B2: OBRA: REFORMA DA ESCOLA LOGRADOURO - ADITIVO | D2: Data Base: | F2: Outubro/2019
B3: MUNICÍPIO: COREMAS | D3: BDI: | F3: 0.1921
B4: ENDEREÇO: ZONA URBANA | D4: Encargos | F4: Não Desonerados
A6: COMPOSIÇÕES DE CUSTO NÃO DESONERADAS
A8: 04358/ORSE | B8: Espalhamento manual de terra vegetal para o plantio de grama tipo esmeralda. | C8: m³
A9: Cód. SINAPI | B9: Descrição do Insumo | C9: Unid. | D9: Coef. | E9: Valor Unit. | F9: Valor Total
A10: 7253 Insumos | B10: Terra vegetal (granel) | C10: m³ | D10: 1.3 | E10: 96.42 | F10: =TRUNC(D10*E10,2) -> 125.34
A11: 88316 Composicao | B11: Servente com encargos complementares | C11: h | D11: 2.5 | E11: 13.68 | F11: =TRUNC(D11*E11,2) -> 34.2
A12: Valor Total Unitário | F12: =SUM(F10:F11) -> 159.54
