Workbook
Name JR_PAGE_ANCHOR_0_1: 'MEMORIAL DE CALCULO'!#REF!
Name JR_PAGE_ANCHOR_0_1: 'PLANILHA DE MEDIÇÃO'!#REF!

Sheet PLANILHA DE MEDIÇÃO
B1: CONTRATAÇÃO DE UMA EMPRESA ESPECIALIZADA PARA CONSTRUÇÃO DE 01 (UM) CENTRO ESPECIALIZADO EM ATENÇÃO A SAÚDE MENTAL PARA ATENDER AS NECESSIDADES DA SECRETARIA MUNICIPAL DE SAÚDE EM COREMAS/PB | E1: BANCO DE DADOS: SINAPI - 05/2024-Paraiba ORSE - 0412024- Sergipe | G1: B.D.I. = 22,47% ENCARGOS SOCIAIS: Nao Desonerado: embutido nos presos unitário dos insumos de mão de obra, de acordo com as bases. | I1: DATA DE INÍCIO DO CONTRATO: 15/10/2024. VIGÊNCIA: 12 MESES
A2: DADOS DO CONTRATANTE: Prefeitura Municipal de Coremas. CNPJ: 08.939.936/0001-94 POCESSO LICITATÓRIO: Processo Administrativo N°. 176/2024 e Concorrência Eletrônica N°. 0004/2024 CONTRATO N°. 328/2024 VALOR DA OBRA/CONTRATO: 1.150.000,00 (Um milhão, cento e cinquenta mil reais). | E2: NÚMERO DA MEDIÇÃO: 7ª MEDIÇÃO. | G2: REFERÊNCIA/PERÍODO DA MEDIÇÃO: De 26/06/2025 a 11/08/2025 | I2: VALOR MEDIDO NO PERÍODO: R$ 330.767,00
A3: DADOS DO CONTRATADO: CL CONSTRUÇÕES E SERVIÇOS LTDA CNPJ: 09.335.002/0001-06 ENDEREÇO: Rua Cel. João Severino, SN - Sala D - Centro - Itaporanga - PB. | E3: FONTE DOS RECURSOS: Próprio (Diversos) do Município, prevista no orçamento da União, para o exercício de 2024. | J3: TOTAL DA MEDIÇÃO 01 = | L3: =L127 -> 143165.41 | M3: TOTAL DA MEDIÇÃO 02 = | O3: =O127 -> 90821.55 | P3: TOTAL DA MEDIÇÃO 03 = | R3: =R127 -> 66728 | V3: TOTAL DA MEDIÇÃO 05 = | X3: =X127 -> 41614.02 | Y3: TOTAL DA MEDIÇÃO 06 = | AA3: =AA127 -> 330767 | AB3: TOTAL DA MEDIÇÃO 07 = | AD3: =AD127 -> 167779
J4: MEDIÇÕES | M4: MEDIÇÕES | P4: MEDIÇÕES | V4: MEDIÇÕES | Y4: MEDIÇÕES | AB4: MEDIÇÕES | AE4: AVANÇO
A5: ITEM | B5: CÓDIGO | C5: DESCRIÇÃO | D5: FONTE | E5: UND | F5: QUANTIDADE | G5: PREÇO UNITÁRIO R$ | H5: PREÇO TOTAL R$ | J5: AVANÇO PERCENTUAL NO PERÍODO | K5: QUANTIDADE MEDIDA NO PERÍODO | L5: VALOR MEDIDO NO PERÍODO | M5: AVANÇO PERCENTUAL NO PERÍODO | N5: QUANTIDADE MEDIDA NO PERÍODO | O5: VALOR MEDIDO NO PERÍODO | P5: AVANÇO PERCENTUAL NO PERÍODO | Q5: QUANTIDADE MEDIDA NO PERÍODO | R5: VALOR MEDIDO NO PERÍODO | S5: AVANÇO PERCENTUAL NO PERÍODO | T5: QUANTIDADE MEDIDA NO PERÍODO | U5: VALOR MEDIDO NO PERÍODO | V5: AVANÇO PERCENTUAL NO PERÍODO | W5: QUANTIDADE MEDIDA NO PERÍODO | X5: VALOR MEDIDO NO PERÍODO | Y5: AVANÇO PERCENTUAL NO PERÍODO | Z5: QUANTIDADE MEDIDA NO PERÍODO | AA5: VALOR MEDIDO NO PERÍODO | AB5: AVANÇO PERCENTUAL NO PERÍODO | AC5: QUANTIDADE MEDIDA NO PERÍODO | AD5: VALOR MEDIDO NO PERÍODO | AE5: % ACUMULADO | AF5: QUANT. ACUMULADA | AG5: TOTAL ACUMULADO | AH5: STATUS DO ÍTEM | AI5: QUANTIDADE A SER ACRESCENTADA NO ADITIVO
A6: 1 | B6: SERVIÇOS PRELIMINARES | H6: =SUM(H7:H8) -> 4383.8738 | J6: MEDIÇÃO 01 | M6: MEDIÇÃO 02 | P6: MEDIÇÃO 03 | S6: MEDIÇÃO 04 | V6: MEDIÇÃO 05 | Y6: MEDIÇÃO 06 | AB6: MEDIÇÃO 07
A7: 1.1 | B7: 51 | C7: Placa de obra em chapa aco galvanizado, instalada - Rev 02_O1/2022 | D7: ORSE | E7: M2 | F7: 6 | G7: 350.91 | H7: =F7*G7 -> 2105.46 | J7: 1 | K7: =TRUNC(J7*F7,2) -> 6 | L7: =TRUNC(K7*G7)+0.46 -> 2105.46 | M7: 0 | N7: =TRUNC(M7*F7,2) -> 0 | O7: =TRUNC(N7*G7)+0 -> 0 | P7: 0 | Q7: =TRUNC(P7*F7,2) -> 0 | R7: =TRUNC(Q7*G7) -> 0 | U7: =TRUNC(G7*T7)+0 -> 0 | V7: 0 | W7: =TRUNC(V7*F7,2) -> 0 | X7: =TRUNC(W7*G7)+0 -> 0 | Y7: =Z7/F7 -> 0 | AA7: =TRUNC(Z7*G7)+0 -> 0 | AB7: =AC7/F7 -> 0 | AD7: =TRUNC(AC7*G7) -> 0 | AE7: =SUM(J7,M7,P7,V7,Y7,AB7) -> 1 | AF7: =SUM(K7,N7,Q7,W7,Z7,T7,AC7) -> 6 | AG7: =SUM(L7,O7,R7,X7,AA7,U7,AD7) -> 2105.46 | AH7: =IF(AE7=100%,"ITEM FINALIZADO",AE7) -> ITEM FINALIZADO
A8: 1.2 | B8: 98524 | C8: LIMPEZA MANUAL DE VEGETAÇÃO EM TERRENO COM EXADA AF 03/2024 | D8: SINAPI | E8: M2 | F8: 488.93 | G8: 4.66 | H8: =F8*G8 -> 2278.4138 | J8: 1 | K8: =TRUNC(J8*F8,2) -> 488.93 | L8: =TRUNC(K8*G8)+0.41 -> 2278.41 | U8: =TRUNC(G8*T8)+0 -> 0 | W8: =TRUNC(V8*F8,2) -> 0 | X8: =TRUNC(W8*G8)+0 -> 0 | Y8: =Z8/F8 -> 0 | AA8: =TRUNC(Z8*G8)+0 -> 0 | AB8: =AC8/F8 -> 0 | AD8: =TRUNC(AC8*G8) -> 0 | AE8: =SUM(J8,M8,P8,V8,Y8,AB8) -> 1 | AF8: =SUM(K8,N8,Q8,W8,Z8,T8,AC8) -> 488.93 | AG8: =SUM(L8,O8,R8,X8,AA8,U8,AD8) -> 2278.41 | AH8: =IF(AE8=100%,"ITEM FINALIZADO",AE8) -> ITEM FINALIZADO
A9: 2 | B9: MOVIMENTO DE TERRA | H9: =SUM(H10:H12) -> 31651.318
A10: 2.1 | B10: 99059 | C10: LOCAÇÃO CONVENCIONAL DE OBRA, UTILIZANDO DE GABARITO DE TÁBUAS CORRIDAS PONTALETADAS A CADA 2,00M - 2 UTILIZAÇÕES. AF_03/2024 | D10: SINAPI | E10: M | F10: 335.2 | G10: 61.14 | H10: =(F10*G10)-0.01 -> 20494.118 | J10: 1 | K10: =TRUNC(J10*F10,2) -> 335.2 | L10: =TRUNC(K10*G10)+0.12 -> 20494.12 | U10: =TRUNC(G10*T10)+0 -> 0 | W10: =TRUNC(V10*F10,2) -> 0 | X10: =TRUNC(W10*G10)+0 -> 0 | Y10: =Z10/F10 -> 0 | AA10: =TRUNC(Z10*G10)+0 -> 0 | AB10: =AC10/F10 -> 0 | AD10: =TRUNC(AC10*G10) -> 0 | AE10: =SUM(J10,M10,P10,V10,Y10,AB10) -> 1 | AF10: =SUM(K10,N10,Q10,W10,Z10,T10,AC10) -> 335.2 | AG10: =SUM(L10,O10,R10,X10,AA10,U10,AD10) -> 20494.12 | AH10: =IF(AE10=100%,"ITEM FINALIZADO",AE10) -> ITEM FINALIZADO
A11: 2.2 | B11: 93358 | C11: ESCAVAÇÃO MANUAL DE VALA COM PROFUNDIDADE MENOR OU IGUAL A 1,30M AF 02/2021 | D11: SINAPI | E11: M3 | F11: 81.25 | G11: 86.72 | H11: =F11*G11 -> 7046 | J11: 1 | K11: =TRUNC(J11*F11,2) -> 81.25 | L11: =TRUNC(K11*G11)+0 -> 7046 | U11: =TRUNC(G11*T11)+0 -> 0 | W11: =TRUNC(V11*F11,2) -> 0 | X11: =TRUNC(W11*G11)+0 -> 0 | Y11: =Z11/F11 -> 0 | AA11: =TRUNC(Z11*G11)+0 -> 0 | AB11: =AC11/F11 -> 0 | AD11: =TRUNC(AC11*G11) -> 0 | AE11: =SUM(J11,M11,P11,V11,Y11,AB11) -> 1 | AF11: =SUM(K11,N11,Q11,W11,Z11,T11,AC11) -> 81.25 | AG11: =SUM(L11,O11,R11,X11,AA11,U11,AD11) -> 7046 | AH11: =IF(AE11=100%,"ITEM FINALIZADO",AE11) -> ITEM FINALIZADO
A12: 2.3 | B12: 94319 | C12: ATERRO MANUAL DE VALAS COM SOLO ARGILO-ARENOSO. AF_08/2023 | D12: SINAPI | E12: M3 | F12: 57.1 | G12: 72 | H12: =(F12*G12) -> 4111.2 | J12: 1 | K12: =TRUNC(J12*F12,2) -> 57.1 | L12: =TRUNC(K12*G12)+0.2 -> 4111.2 | U12: =TRUNC(G12*T12)+0 -> 0 | W12: =TRUNC(V12*F12,2) -> 0 | X12: =TRUNC(W12*G12)+0 -> 0 | Y12: =Z12/F12 -> 0 | AA12: =TRUNC(Z12*G12)+0 -> 0 | AB12: =AC12/F12 -> 0 | AD12: =TRUNC(AC12*G12) -> 0 | AE12: =SUM(J12,M12,P12,V12,Y12,AB12) -> 1 | AF12: =SUM(K12,N12,Q12,W12,Z12,T12,AC12) -> 57.1 | AG12: =SUM(L12,O12,R12,X12,AA12,U12,AD12) -> 4111.2 | AH12: =IF(AE12=100%,"ITEM FINALIZADO",AE12) -> ITEM FINALIZADO
A13: 3 | B13: ESTRUTURA | H13: =SUM(H15,H22) -> 200390.71
A14: 3.1 | B14: INFRAESTUTURA | H14: =H15 -> 79073.708
A15: 3.1.1 | B15: FUNDAÇÃO | H15: =SUM(H16:H21) -> 79073.708
A16: 3.1.1.1 | B16: 102486 | C16: CONCRETO FCK = 15MPA, TRACO 13,4.3,4 (EM MASSA SECA DE CIMENTO / AREIA MÉDIA/ SEIXO ROLADO) - PREPARO MANUAL. AF_05/2021 | D16: SINAPI | E16: M3 | F16: 10.59 | G16: 569.3 | H16: =(F16*G16)-0.01 -> 6028.877 | J16: 0.8 | K16: =TRUNC(J16*F16,2) -> 8.47 | L16: =TRUNC(K16*G16)+0.1 -> 4821.1 | M16: 0.2 | N16: =TRUNC(M16*F16,2)+0.01 -> 2.12 | O16: =TRUNC(N16*G16)+1.78 -> 1207.78 | U16: =TRUNC(G16*T16)+0 -> 0 | W16: =TRUNC(V16*F16,2) -> 0 | X16: =TRUNC(W16*G16)+0 -> 0 | Y16: =Z16/F16 -> 0 | AA16: =TRUNC(Z16*G16)+0 -> 0 | AB16: =AC16/F16 -> 0 | AD16: =TRUNC(AC16*G16) -> 0 | AE16: =SUM(J16,M16,P16,V16,Y16,AB16) -> 1 | AF16: =SUM(K16,N16,Q16,W16,Z16,T16,AC16) -> 10.59 | AG16: =SUM(L16,O16,R16,X16,AA16,U16,AD16) -> 6028.88 | AH16: =IF(AE16=100%,"ITEM FINALIZADO",AE16) -> ITEM FINALIZADO
A17: 3.1.1.2 | B17: 94965 | C17: CONCRETO FCK = 25MPA, TRACO 12,3:2,7 (EM MASSA SECA DE CIMENTO/ AREIA MEDIA/ BRITA 1) - PREPARO MECANICO COM BETONEIRA 400 L. AF 05/2021 | D17: SINAPI | E17: M3 | F17: 30.05 | G17: 433.53 | H17: =(F17*G17)-0.01 -> 13027.566 | J17: 0.8 | K17: =TRUNC(J17*F17,2) -> 24.04 | L17: =TRUNC(K17*G17)+0.05 -> 10422.05 | M17: 0.2 | N17: =TRUNC(M17*F17,2) -> 6.01 | O17: =TRUNC(N17*G17)+0.52 -> 2605.52 | U17: =TRUNC(G17*T17)+0 -> 0 | W17: =TRUNC(V17*F17,2) -> 0 | X17: =TRUNC(W17*G17)+0 -> 0 | Y17: =Z17/F17 -> 0 | AA17: =TRUNC(Z17*G17)+0 -> 0 | AB17: =AC17/F17 -> 0 | AD17: =TRUNC(AC17*G17) -> 0 | AE17: =SUM(J17,M17,P17,V17,Y17,AB17) -> 1 | AF17: =SUM(K17,N17,Q17,W17,Z17,T17,AC17) -> 30.05 | AG17: =SUM(L17,O17,R17,X17,AA17,U17,AD17) -> 13027.57 | AH17: =IF(AE17=100%,"ITEM FINALIZADO",AE17) -> ITEM FINALIZADO
A18: 3.1.1.3 | B18: 96544 | C18: ARMAÇÃO DE BLOCO UTILIZANDO AÇO CA-50 DE 6,3 MM - MONTAGEM. AF 01/2024 | D18: SINAPI | E18: KG | F18: 33.4 | G18: 16.48 | H18: =(F18*G18) -> 550.432 | J18: 0.8 | K18: =TRUNC(J18*F18,2) -> 26.72 | L18: =TRUNC(K18*G18)+0.34 -> 440.34 | M18: 0.2 | N18: =TRUNC(M18*F18,2) -> 6.68 | O18: =TRUNC(N18*G18)+0.09 -> 110.09 | U18: =TRUNC(G18*T18)+0 -> 0 | W18: =TRUNC(V18*F18,2) -> 0 | X18: =TRUNC(W18*G18)+0 -> 0 | Y18: =Z18/F18 -> 0 | AA18: =TRUNC(Z18*G18)+0 -> 0 | AB18: =AC18/F18 -> 0 | AD18: =TRUNC(AC18*G18) -> 0 | AE18: =SUM(J18,M18,P18,V18,Y18,AB18) -> 1 | AF18: =SUM(K18,N18,Q18,W18,Z18,T18,AC18) -> 33.4 | AG18: =SUM(L18,O18,R18,X18,AA18,U18,AD18) -> 550.43 | AH18: =IF(AE18=100%,"ITEM FINALIZADO",AE18) -> ITEM FINALIZADO
A19: 3.1.1.4 | B19: 98545 | C19: ARMAÇÃO DE BLOCO UTILZANDO AÇO CASO DE 8 MM - MONTAGEM. AF 01/2024 | D19: SINAPI | E19: KG | F19: 2842 | G19: 14.61 | H19: =(F19*G19) -> 41521.62 | J19: 0.8 | K19: =TRUNC(J19*F19,2) -> 2273.6 | L19: =TRUNC(K19*G19)+0.3 -> 33217.3 | M19: 0.2 | N19: =TRUNC(M19*F19,2) -> 568.4 | O19: =TRUNC(N19*G19)+0.32 -> 8304.32 | U19: =TRUNC(G19*T19)+0 -> 0 | W19: =TRUNC(V19*F19,2) -> 0 | X19: =TRUNC(W19*G19)+0 -> 0 | Y19: =Z19/F19 -> 0 | AA19: =TRUNC(Z19*G19)+0 -> 0 | AB19: =AC19/F19 -> 0 | AD19: =TRUNC(AC19*G19) -> 0 | AE19: =SUM(J19,M19,P19,V19,Y19,AB19) -> 1 | AF19: =SUM(K19,N19,Q19,W19,Z19,T19,AC19) -> 2842 | AG19: =SUM(L19,O19,R19,X19,AA19,U19,AD19) -> 41521.62 | AH19: =IF(AE19=100%,"ITEM FINALIZADO",AE19) -> ITEM FINALIZADO
A20: 3.1.1.5 | B20: 96543 | C20: ARMAÇÃO DE BLOCO UTILIZANDO AÇO CA-60 DE 5 MM - MONTAGEM. AF 01/2024 | D20: SINAPI | E20: KG | F20: 580.1 | G20: 18.71 | H20: =(F20*G20) -> 10853.671 | J20: 0.8 | K20: =TRUNC(J20*F20,2) -> 464.08 | L20: =TRUNC(K20*G20)+0.94 -> 8682.94 | M20: 0.2 | N20: =TRUNC(M20*F20,2) -> 116.02 | O20: =TRUNC(N20*G20)+0.73 -> 2170.73 | U20: =TRUNC(G20*T20)+0 -> 0 | W20: =TRUNC(V20*F20,2) -> 0 | X20: =TRUNC(W20*G20)+0 -> 0 | Y20: =Z20/F20 -> 0 | AA20: =TRUNC(Z20*G20)+0 -> 0 | AB20: =AC20/F20 -> 0 | AD20: =TRUNC(AC20*G20) -> 0 | AE20: =SUM(J20,M20,P20,V20,Y20,AB20) -> 1 | AF20: =SUM(K20,N20,Q20,W20,Z20,T20,AC20) -> 580.1 | AG20: =SUM(L20,O20,R20,X20,AA20,U20,AD20) -> 10853.67 | AH20: =IF(AE20=100%,"ITEM FINALIZADO",AE20) -> ITEM FINALIZADO
A21: 3.1.1.6 | B21: 98557 | C21: IMPERMEABILIZAÇÃO DE SUPERFÍCIE COM EMULSÃO ASFÁLTICA, 2 DEMÃOS. AF 09/2023 | D21: SINAPI | E21: M2 | F21: 154.03 | G21: 46.04 | H21: =(F21*G21) -> 7091.5412 | J21: 0.2 | K21: =TRUNC(J21*F21,2) -> 30.8 | L21: =TRUNC(K21*G21)+0.23 -> 1418.23 | M21: 0.8 | N21: =TRUNC(M21*F21,2) -> 123.22 | O21: =TRUNC(N21*G21)+0.31 -> 5673.31 | U21: =TRUNC(G21*T21)+0 -> 0 | W21: =TRUNC(V21*F21,2) -> 0 | X21: =TRUNC(W21*G21)+0 -> 0 | Y21: =Z21/F21 -> 0 | AA21: =TRUNC(Z21*G21)+0 -> 0 | AB21: =AC21/F21 -> 0 | AD21: =TRUNC(AC21*G21) -> 0 | AE21: =SUM(J21,M21,P21,V21,Y21,AB21) -> 1 | AF21: =SUM(K21,N21,Q21,W21,Z21,T21,AC21) -> 154.02 | AG21: =SUM(L21,O21,R21,X21,AA21,U21,AD21) -> 7091.54 | AH21: =IF(AE21=100%,"ITEM FINALIZADO",AE21) -> ITEM FINALIZADO
A22: 3.2 | B22: SUPERESTRUTURA | H22: =SUM(H23,H30,H38)+0.01 -> 121317
A23: 3.2.1 | B23: PILARES | H23: =SUM(H24:H29) -> 46405.309
A24: 3.2.1.1 | B24: 102476 | C24: CONCRETO FCK = 25MPA, TRACO 1:2,2:2,5 (EM MASSA SECA DE CIMENTO/ AREIA MEDIA/ SEIXO ROLADO) - PREPARO MECANICO COM BETONEIRA 400 L. AF 05/2021 | D24: SINAPI | E24: M3 | F24: 15.1 | G24: 557.58 | H24: =(F24*G24)-0.01 -> 8419.448 | J24: 0.5 | K24: =TRUNC(J24*F24,2) -> 7.55 | L24: =TRUNC(K24*G24)+0.73 -> 4209.73 | M24: 0.4 | N24: =TRUNC(M24*F24,2) -> 6.04 | O24: =TRUNC(N24*G24)+0.78 -> 3367.78 | P24: 0.1 | Q24: =TRUNC(P24*F24,2) -> 1.51 | R24: =TRUNC(Q24*G24) -> 841 | U24: =TRUNC(G24*T24)+0 -> 0 | W24: =TRUNC(V24*F24,2) -> 0 | X24: =TRUNC(W24*G24)+0 -> 0 | Y24: =Z24/F24 -> 0 | AA24: =TRUNC(Z24*G24)+0 -> 0 | AB24: =AC24/F24 -> 0 | AD24: =TRUNC(AC24*G24) -> 0 | AE24: =SUM(J24,M24,P24,V24,Y24,AB24) -> 1 | AF24: =SUM(K24,N24,Q24,W24,Z24,T24,AC24) -> 15.1 | AG24: =SUM(L24,O24,R24,X24,AA24,U24,AD24) -> 8418.51 | AH24: =IF(AE24=100%,"ITEM FINALIZADO",AE24) -> ITEM FINALIZADO
A25: 3.2.1.2 | B25: 96546 | C25: ARMAÇÃO DE BLOCO UTILIZANDO AÇO CA-SO DE 10 MM - MONTAGEM. AF 01/2024 | D25: SINAPI | E25: KG | F25: 90.3 | G25: 12.61 | H25: =(F25*G25) -> 1138.683 | J25: 0.5 | K25: =TRUNC(J25*F25,2) -> 45.15 | L25: =TRUNC(K25*G25)+0.34 -> 569.34 | M25: 0.4 | N25: =TRUNC(M25*F25,2) -> 36.12 | O25: =TRUNC(N25*G25)+0.47 -> 455.47 | P25: 0.1 | Q25: =TRUNC(P25*F25,2) -> 9.03 | R25: =TRUNC(Q25*G25) -> 113 | U25: =TRUNC(G25*T25)+0 -> 0 | W25: =TRUNC(V25*F25,2) -> 0 | X25: =TRUNC(W25*G25)+0 -> 0 | Y25: =Z25/F25 -> 0 | AA25: =TRUNC(Z25*G25)+0 -> 0 | AB25: =AC25/F25 -> 0 | AD25: =TRUNC(AC25*G25) -> 0 | AE25: =SUM(J25,M25,P25,V25,Y25,AB25) -> 1 | AF25: =SUM(K25,N25,Q25,W25,Z25,T25,AC25) -> 90.3 | AG25: =SUM(L25,O25,R25,X25,AA25,U25,AD25) -> 1137.81 | AH25: =IF(AE25=100%,"ITEM FINALIZADO",AE25) -> ITEM FINALIZADO
A26: 3.2.1.3 | B26: 98543 | C26: ARMAÇÃO DE BLOCO UTILIZANDO AÇO CA-CO DE 5 MM - MONTAGEM. AF 01/2024 | D26: SINAPI | E26: KG | F26: 466.7 | G26: 18.71 | H26: =(F26*G26)-0.01 -> 8731.947 | J26: 1 | K26: =TRUNC(J26*F26,2) -> 466.7 | L26: =TRUNC(K26*G26)+0.95 -> 8731.95 | Q26: =TRUNC(P26*F26,2) -> 0 | R26: =TRUNC(Q26*G26) -> 0 | U26: =TRUNC(G26*T26)+0 -> 0 | W26: =TRUNC(V26*F26,2) -> 0 | X26: =TRUNC(W26*G26)+0 -> 0 | Y26: =Z26/F26 -> 0 | AA26: =TRUNC(Z26*G26)+0 -> 0 | AB26: =AC26/F26 -> 0 | AD26: =TRUNC(AC26*G26) -> 0 | AE26: =SUM(J26,M26,P26,V26,Y26,AB26) -> 1 | AF26: =SUM(K26,N26,Q26,W26,Z26,T26,AC26) -> 466.7 | AG26: =SUM(L26,O26,R26,X26,AA26,U26,AD26) -> 8731.95 | AH26: =IF(AE26=100%,"ITEM FINALIZADO",AE26) -> ITEM FINALIZADO
A27: 3.2.1.4 | B27: 96545 | C27: ARMAÇÃO DE BLOCO UTILZANDO AÇO CA-50 DES MM - MONTAGEM, AF 01/2024 | D27: SINAPI | E27: KG | F27: 636.3 | G27: 14.61 | H27: =(F27*G27) -> 9296.343 | J27: 1 | K27: =TRUNC(J27*F27,2) -> 636.3 | L27: =TRUNC(K27*G27)+0.34 -> 9296.34 | Q27: =TRUNC(P27*F27,2) -> 0 | R27: =TRUNC(Q27*G27) -> 0 | U27: =TRUNC(G27*T27)+0 -> 0 | W27: =TRUNC(V27*F27,2) -> 0 | X27: =TRUNC(W27*G27)+0 -> 0 | Y27: =Z27/F27 -> 0 | AA27: =TRUNC(Z27*G27)+0 -> 0 | AB27: =AC27/F27 -> 0 | AD27: =TRUNC(AC27*G27) -> 0 | AE27: =SUM(J27,M27,P27,V27,Y27,AB27) -> 1 | AF27: =SUM(K27,N27,Q27,W27,Z27,T27,AC27) -> 636.3 | AG27: =SUM(L27,O27,R27,X27,AA27,U27,AD27) -> 9296.34 | AH27: =IF(AE27=100%,"ITEM FINALIZADO",AE27) -> ITEM FINALIZADO
A28: 3.2.1.5 | B28: 96547 | C28: ARMAÇÃO DE BLOCO, VIGA BALDRAME OU SAPATA UTILIZANDO AÇO CA- 50 DE 12,5 MM - MONTAGEM. AF 06/2017 | D28: SINAPI | E28: KG | F28: 17.11 | G28: 9.6 | H28: =(F28*G28)-0.01 -> 164.246 | J28: 1 | K28: =TRUNC(J28*F28,2) -> 17.11 | L28: =TRUNC(K28*G28)+0.25 -> 164.25 | Q28: =TRUNC(P28*F28,2) -> 0 | R28: =TRUNC(Q28*G28) -> 0 | U28: =TRUNC(G28*T28)+0 -> 0 | W28: =TRUNC(V28*F28,2) -> 0 | X28: =TRUNC(W28*G28)+0 -> 0 | Y28: =Z28/F28 -> 0 | AA28: =TRUNC(Z28*G28)+0 -> 0 | AB28: =AC28/F28 -> 0 | AD28: =TRUNC(AC28*G28) -> 0 | AE28: =SUM(J28,M28,P28,V28,Y28,AB28) -> 1 | AF28: =SUM(K28,N28,Q28,W28,Z28,T28,AC28) -> 17.11 | AG28: =SUM(L28,O28,R28,X28,AA28,U28,AD28) -> 164.25 | AH28: =IF(AE28=100%,"ITEM FINALIZADO",AE28) -> ITEM FINALIZADO
A29: 3.2.1.6 | B29: 103795 | C29: FABRICAÇÃO, MONTAGEM E DESMONTAGEM DE FÔRMA PARA ESCADA HIDRAULICA, EM CHAPA DE MADEIRA COMPENSADA RESINADA, E = 17 MM, 3 UTILIZAÇÕES. AF 08/2022 | D29: SINAPI | E29: M2 | F29: 227.69 | G29: 81.93 | H29: =(F29*G29) -> 18654.642 | J29: 0.5 | K29: =TRUNC(J29*F29,2) -> 113.84 | L29: =TRUNC(K29*G29)+1.32 -> 9327.32 | M29: 0.5 | N29: =TRUNC(M29*F29,2) -> 113.84 | O29: =TRUNC(N29*G29)+1.32 -> 9327.32 | P29: 0.1 | Q29: =TRUNC(P29*F29,2) -> 22.76 | R29: =TRUNC(Q29*G29) -> 1864 | T29: -22.76 | U29: =TRUNC(G29*T29)+0 -> -1864 | V29: -0.1 | W29: =TRUNC(V29*F29,2) -> -22.76 | Y29: =Z29/F29 -> 0 | AA29: =TRUNC(Z29*G29)+0 -> 0 | AB29: =AC29/F29 -> 0 | AD29: =TRUNC(AC29*G29) -> 0 | AE29: =SUM(J29,M29,P29,V29,Y29,AB29) -> 1 | AF29: =SUM(K29,N29,Q29,W29,Z29,T29,AC29) -> 204.92 | AG29: =SUM(L29,O29,R29,X29,AA29,U29,AD29) -> 18654.64 | AH29: =IF(AE29=100%,"ITEM FINALIZADO",AE29) -> ITEM FINALIZADO
A30: 3.2.2 | B30: VIGAS | H30: =SUM(H31:H37) -> 32909.86 | AH30: =SUM(AH31) -> 0
A31: 3.2.2.1 | B31: 102476 | C31: CONCRETO FCK = 25MPA, TRAGO 12,2:2,5 (EM MASSA SECA DE CIMENTO/ AREIA MEDIA/ SEIXO ROLADO) - PREPARO MECANICO COM BETONEIRA 400 L. AF 05/2021 | D31: SINAPI | E31: M3 | F31: 15.81 | G31: 557.58 | H31: =(F31*G31)-0.01 -> 8815.3298 | M31: 0.4 | N31: =TRUNC(M31*F31,2) -> 6.32 | O31: =TRUNC(N31*G31)+3.13 -> 3526.13 | P31: 0.6 | Q31: =TRUNC(P31*F31,2) -> 9.48 | R31: =TRUNC(Q31*G31) -> 5285 | U31: =TRUNC(G31*T31)+0 -> 0 | W31: =TRUNC(V31*F31,2) -> 0 | X31: =TRUNC(W31*G31)+0 -> 0 | Y31: =Z31/F31 -> 0 | AA31: =TRUNC(Z31*G31)+0 -> 0 | AB31: =AC31/F31 -> 0 | AD31: =TRUNC(AC31*G31) -> 0 | AE31: =SUM(J31,M31,P31,V31,Y31,AB31) -> 1 | AF31: =SUM(K31,N31,Q31,W31,Z31,T31,AC31) -> 15.8 | AG31: =SUM(L31,O31,R31,X31,AA31,U31,AD31) -> 8811.13 | AH31: =IF(AE31=100%,"ITEM FINALIZADO",AE31) -> ITEM FINALIZADO
A32: 3.2.2.2 | B32: 92760 | C32: ARMAÇÃO DE PILAR OU VIGA DE ESTRUTURA CONVENCIONAL DE CONCRETO ARMADO UTILIZANDO AÇO CA-50 06 8,3 MM - MONTAGEM. AF 06/2022 | D32: SINAPI | E32: KG | F32: 39.6 | G32: 11.8 | H32: =(F32*G32) -> 467.28 | M32: 0.8 | N32: =TRUNC(M32*F32,2) -> 31.68 | O32: =TRUNC(N32*G32)+0.82 -> 373.82 | P32: 0.2 | Q32: =TRUNC(P32*F32,2) -> 7.92 | R32: =TRUNC(Q32*G32) -> 93 | U32: =TRUNC(G32*T32)+0 -> 0 | W32: =TRUNC(V32*F32,2) -> 0 | X32: =TRUNC(W32*G32)+0 -> 0 | Y32: =Z32/F32 -> 0 | AA32: =TRUNC(Z32*G32)+0 -> 0 | AB32: =AC32/F32 -> 0 | AD32: =TRUNC(AC32*G32) -> 0 | AE32: =SUM(J32,M32,P32,V32,Y32,AB32) -> 1 | AF32: =SUM(K32,N32,Q32,W32,Z32,T32,AC32) -> 39.6 | AG32: =SUM(L32,O32,R32,X32,AA32,U32,AD32) -> 466.82 | AH32: =IF(AE32=100%,"ITEM FINALIZADO",AE32) -> ITEM FINALIZADO
A33: 3.2.2.3 | B33: 92761 | C33: ARMAÇÃO DE PILAR OU VIGA DE ESTRUTURA CONVENCIONAL DE CONCRETO ARMADO UTILIZANDO AÇO CA-50 DE 8,0 MM - MONTAGEM. AF 06/2022 | D33: SINAPI | E33: KG | F33: 80 | G33: 10.88 | H33: =(F33*G33) -> 870.4 | M33: 0.8 | N33: =TRUNC(M33*F33,2) -> 64 | O33: =TRUNC(N33*G33)+0.32 -> 696.32 | P33: 0.2 | Q33: =TRUNC(P33*F33,2) -> 16 | R33: =TRUNC(Q33*G33) -> 174 | U33: =TRUNC(G33*T33)+0 -> 0 | W33: =TRUNC(V33*F33,2) -> 0 | X33: =TRUNC(W33*G33)+0 -> 0 | Y33: =Z33/F33 -> 0 | AA33: =TRUNC(Z33*G33)+0 -> 0 | AB33: =AC33/F33 -> 0 | AD33: =TRUNC(AC33*G33) -> 0 | AE33: =SUM(J33,M33,P33,V33,Y33,AB33) -> 1 | AF33: =SUM(K33,N33,Q33,W33,Z33,T33,AC33) -> 80 | AG33: =SUM(L33,O33,R33,X33,AA33,U33,AD33) -> 870.32 | AH33: =IF(AE33=100%,"ITEM FINALIZADO",AE33) -> ITEM FINALIZADO
A34: 3.2.2.4 | B34: 92762 | C34: ARMAÇÃO DE PILAR OU VIGA DE ESTRUTURA CONVENCIONAL DE CONCRETO ARMADO UTILIZANDO AÇO CA-50 DE 10,0 MM - MONTAGEM. AF 06/2022 | D34: SINAPI | E34: KG | F34: 337.7 | G34: 9.61 | H34: =(F34*G34)-0.01 -> 3245.287 | M34: 0.8 | N34: =TRUNC(M34*F34,2) -> 270.16 | O34: =TRUNC(N34*G34)+0.23 -> 2596.23 | P34: 0.2 | Q34: =TRUNC(P34*F34,2) -> 67.54 | R34: =TRUNC(Q34*G34) -> 649 | U34: =TRUNC(G34*T34)+0 -> 0 | W34: =TRUNC(V34*F34,2) -> 0 | X34: =TRUNC(W34*G34)+0 -> 0 | Y34: =Z34/F34 -> 0 | AA34: =TRUNC(Z34*G34)+0 -> 0 | AB34: =AC34/F34 -> 0 | AD34: =TRUNC(AC34*G34) -> 0 | AE34: =SUM(J34,M34,P34,V34,Y34,AB34) -> 1 | AF34: =SUM(K34,N34,Q34,W34,Z34,T34,AC34) -> 337.7 | AG34: =SUM(L34,O34,R34,X34,AA34,U34,AD34) -> 3245.23 | AH34: =IF(AE34=100%,"ITEM FINALIZADO",AE34) -> ITEM FINALIZADO
A35: 3.2.2.5 | B35: 92763 | C35: ARMAÇÃO DE PILAR OU VIGA DE ESTRUTURA CONVENCIONAL DE CONCRETO ARMADO UTILZANDO AÇO CA-50 DE 12,5 MM - MONTAGEM. AF 06/2022 | D35: SINAPI | E35: KG | F35: 189.7 | G35: 8.02 | H35: =(F35*G35) -> 1521.394 | M35: 0.8 | N35: =TRUNC(M35*F35,2) -> 151.76 | O35: =TRUNC(N35*G35)+0.11 -> 1217.11 | P35: 0.2 | Q35: =TRUNC(P35*F35,2) -> 37.94 | R35: =TRUNC(Q35*G35) -> 304 | U35: =TRUNC(G35*T35)+0 -> 0 | W35: =TRUNC(V35*F35,2) -> 0 | X35: =TRUNC(W35*G35)+0 -> 0 | Y35: =Z35/F35 -> 0 | AA35: =TRUNC(Z35*G35)+0 -> 0 | AB35: =AC35/F35 -> 0 | AD35: =TRUNC(AC35*G35) -> 0 | AE35: =SUM(J35,M35,P35,V35,Y35,AB35) -> 1 | AF35: =SUM(K35,N35,Q35,W35,Z35,T35,AC35) -> 189.7 | AG35: =SUM(L35,O35,R35,X35,AA35,U35,AD35) -> 1521.11 | AH35: =IF(AE35=100%,"ITEM FINALIZADO",AE35) -> ITEM FINALIZADO
A36: 3.2.2.6 | B36: 92759 | C36: ARMAÇÃO DE PILAR OU VIGA DE ESTRUTURA CONVENCIONAL DE CONCRETO ARMADO UTILIZANDO AÇO CA-CO DE 5,0 MM - MONTAGEM. AF 06/2022 | D36: SINAPI | E36: KG | F36: 179.1 | G36: 12.82 | H36: =(F36*G36) -> 2296.062 | M36: 0.8 | N36: =TRUNC(M36*F36,2) -> 143.28 | O36: =TRUNC(N36*G36)+0.85 -> 1836.85 | P36: 0.2 | Q36: =TRUNC(P36*F36,2) -> 35.82 | R36: =TRUNC(Q36*G36) -> 459 | U36: =TRUNC(G36*T36)+0 -> 0 | W36: =TRUNC(V36*F36,2) -> 0 | X36: =TRUNC(W36*G36)+0 -> 0 | Y36: =Z36/F36 -> 0 | AA36: =TRUNC(Z36*G36)+0 -> 0 | AB36: =AC36/F36 -> 0 | AD36: =TRUNC(AC36*G36) -> 0 | AE36: =SUM(J36,M36,P36,V36,Y36,AB36) -> 1 | AF36: =SUM(K36,N36,Q36,W36,Z36,T36,AC36) -> 179.1 | AG36: =SUM(L36,O36,R36,X36,AA36,U36,AD36) -> 2295.85 | AH36: =IF(AE36=100%,"ITEM FINALIZADO",AE36) -> ITEM FINALIZADO
A37: 3.2.2.7 | B37: 92265 | C37: FABRICAÇÃO DE FORMA PARA VIGAS, EM CHAPA DE MADEIRA COMPENSADA RESINADA, E = 17 MM. AF 09/2020 | D37: SINAPI | E37: M2 | F37: 154.03 | G37: 101.89 | H37: =(F37*G37)-0.01 -> 15694.107 | M37: 1 | N37: =TRUNC(M37*F37,2) -> 154.03 | O37: =TRUNC(N37*G37)+0.11 -> 15694.11 | U37: =TRUNC(G37*T37)+0 -> 0 | W37: =TRUNC(V37*F37,2) -> 0 | X37: =TRUNC(W37*G37)+0 -> 0 | Y37: =Z37/F37 -> 0 | AA37: =TRUNC(Z37*G37)+0 -> 0 | AB37: =AC37/F37 -> 0 | AD37: =TRUNC(AC37*G37) -> 0 | AE37: =SUM(J37,M37,P37,V37,Y37,AB37) -> 1 | AF37: =SUM(K37,N37,Q37,W37,Z37,T37,AC37) -> 154.03 | AG37: =SUM(L37,O37,R37,X37,AA37,U37,AD37) -> 15694.11 | AH37: =IF(AE37=100%,"ITEM FINALIZADO",AE37) -> ITEM FINALIZADO
A38: 3.2.3 | B38: LAJE | H38: =SUM(H39:H44) -> 42001.827 | AH38: =SUM(AH39) -> 0
A39: 3.2.3.1 | B39: 94965 | C39: CONCRETO FCK = 25MPA, TRACO 1:2,3:2,7 (EM MASSA SECA DE CIMENTO/AREIA MEDIA/ BRITA 1) - PREPARO MECANICO COM BETONEIRA 400 L. AF 05/2021 | D39: SINAPI | E39: M3 | F39: 46.31 | G39: 433.53 | H39: =(F39*G39) -> 20076.774 | U39: =TRUNC(G39*T39)+0 -> 0 | V39: 0 | W39: =TRUNC(V39*F39,2) -> 0 | X39: =TRUNC(W39*G39)+0 -> 0 | Y39: =Z39/F39 -> 0 | AA39: =TRUNC(Z39*G39)+0 -> 0 | AB39: =AC39/F39 -> 0 | AD39: =TRUNC(AC39*G39) -> 0 | AE39: =SUM(J39,M39,P39,V39,Y39,AB39) -> 0 | AF39: =SUM(K39,N39,Q39,W39,Z39,T39,AC39) -> 0 | AG39: =SUM(L39,O39,R39,X39,AA39,U39,AD39) -> 0 | AH39: =IF(AE39=100%,"ITEM FINALIZADO",AE39) -> 0
A40: 3.2.3.2 | B40: 92267 | C40: FABRICAÇÃO DE FÔRMA PARA LAJES, EM CHAPA DE MADEIRA COMPENSADA RESINADA, E = 17 MM. AF 09/2020 | D40: SINAPI | E40: M2 | F40: 312.27 | G40: 26.89 | H40: =(F40*G40) -> 8396.9403 | U40: =TRUNC(G40*T40)+0 -> 0 | V40: 0 | W40: =TRUNC(V40*F40,2) -> 0 | X40: =TRUNC(W40*G40)+0 -> 0 | Y40: =Z40/F40 -> 0 | AA40: =TRUNC(Z40*G40)+0 -> 0 | AB40: =AC40/F40 -> 0 | AD40: =TRUNC(AC40*G40) -> 0 | AE40: =SUM(J40,M40,P40,V40,Y40,AB40) -> 0 | AF40: =SUM(K40,N40,Q40,W40,Z40,T40,AC40) -> 0 | AG40: =SUM(L40,O40,R40,X40,AA40,U40,AD40) -> 0 | AH40: =IF(AE40=100%,"ITEM FINALIZADO",AE40) -> 0
A41: 3.2.3.3 | B41: 92769 | C41: ARMAÇÃO DE LAJE DE ESTRUTURA CONVENCIONAL DE CONCRETO ARMADO UTILIZANDO AÇO CA-SO DE 6,3 MM - MONTAGEM. AF_06/2022 | D41: SINAPI | E41: KG | F41: 885.8 | G41: 11.26 | H41: =(F41*G41)-0.01 -> 9974.098 | U41: =TRUNC(G41*T41)+0 -> 0 | V41: 0 | W41: =TRUNC(V41*F41,2) -> 0 | X41: =TRUNC(W41*G41)+0 -> 0 | Y41: =Z41/F41 -> 0 | AA41: =TRUNC(Z41*G41)+0 -> 0 | AB41: =AC41/F41 -> 0 | AD41: =TRUNC(AC41*G41) -> 0 | AE41: =SUM(J41,M41,P41,V41,Y41,AB41) -> 0 | AF41: =SUM(K41,N41,Q41,W41,Z41,T41,AC41) -> 0 | AG41: =SUM(L41,O41,R41,X41,AA41,U41,AD41) -> 0 | AH41: =IF(AE41=100%,"ITEM FINALIZADO",AE41) -> 0
A42: 3.2.3.4 | B42: 92770 | C42: ARMAÇÃO DE LAJE DE ESTRUTURA CONVENCIONAL DE CONCRETO ARMADO UTILIZANDO AÇO CA-SO DE 8,0 MM - MONTAGEM. AF_06/2022 | D42: SINAPI | E42: KG | F42: 229.5 | G42: 10.37 | H42: =(F42*G42)-0.01 -> 2379.905 | U42: =TRUNC(G42*T42)+0 -> 0 | V42: 0 | W42: =TRUNC(V42*F42,2) -> 0 | X42: =TRUNC(W42*G42)+0 -> 0 | Y42: =Z42/F42 -> 0 | AA42: =TRUNC(Z42*G42)+0 -> 0 | AB42: =AC42/F42 -> 0 | AD42: =TRUNC(AC42*G42) -> 0 | AE42: =SUM(J42,M42,P42,V42,Y42,AB42) -> 0 | AF42: =SUM(K42,N42,Q42,W42,Z42,T42,AC42) -> 0 | AG42: =SUM(L42,O42,R42,X42,AA42,U42,AD42) -> 0 | AH42: =IF(AE42=100%,"ITEM FINALIZADO",AE42) -> 0
A43: 3.2.3.5 | B43: 92771 | C43: ARMAÇAO DE LAJE DE ESTRUTURA CONVENCIONAL DE CONCRETO ARMADO UTILIZANDO AÇO CA-50 DE 10,0 MM - MONTAGEM. AF_08/2022 | D43: SINAPI | E43: KG | F43: 39.6 | G43: 9.14 | H43: =(F43*G43) -> 361.944 | U43: =TRUNC(G43*T43)+0 -> 0 | V43: 0 | W43: =TRUNC(V43*F43,2) -> 0 | X43: =TRUNC(W43*G43)+0 -> 0 | Y43: =Z43/F43 -> 0 | AA43: =TRUNC(Z43*G43)+0 -> 0 | AB43: =AC43/F43 -> 0 | AD43: =TRUNC(AC43*G43) -> 0 | AE43: =SUM(J43,M43,P43,V43,Y43,AB43) -> 0 | AF43: =SUM(K43,N43,Q43,W43,Z43,T43,AC43) -> 0 | AG43: =SUM(L43,O43,R43,X43,AA43,U43,AD43) -> 0 | AH43: =IF(AE43=100%,"ITEM FINALIZADO",AE43) -> 0
A44: 3.2.3.6 | B44: 92768 | C44: ARMAÇÃO DE LAJE DE ESTRUTURA CONVENCIONAL DE CONCRETO ARMADO UTILIZANDO AÇO CA-CO DE 5,0 MM - MONTAGEM. AF_06/2022 | D44: SINAPI | E44: KG | F44: 66.3 | G44: 12.25 | H44: =(F44*G44)-0.01 -> 812.165 | U44: =TRUNC(G44*T44)+0 -> 0 | V44: 0 | W44: =TRUNC(V44*F44,2) -> 0 | X44: =TRUNC(W44*G44)+0 -> 0 | Y44: =Z44/F44 -> 0 | AA44: =TRUNC(Z44*G44)+0 -> 0 | AB44: =AC44/F44 -> 0 | AD44: =TRUNC(AC44*G44) -> 0 | AE44: =SUM(J44,M44,P44,V44,Y44,AB44) -> 0 | AF44: =SUM(K44,N44,Q44,W44,Z44,T44,AC44) -> 0 | AG44: =SUM(L44,O44,R44,X44,AA44,U44,AD44) -> 0 | AH44: =IF(AE44=100%,"ITEM FINALIZADO",AE44) -> 0
A45: 4 | B45: ELEVAÇÃO | H45: =SUM(H46:H46) -> 52764.439
A46: 4.1 | B46: 103328 | C46: ALVENARIA DE VEDAÇÃO DE BLOCOS CERAMICOS FURADOS NA HORIZONTAL DE 9X19X19 CM (ESPESSURA 9 CM) E ARGAMASSA DE ASSENTAMENTO COM PREPARO EM BETONEIRA. AF_12/2021 | D46: SINAPI | E46: M2 | F46: 609.43 | G46: 86.58 | H46: =(F46*G46)-0.01 -> 52764.439 | J46: 0.3 | K46: =TRUNC(J46*F46,2) -> 182.82 | L46: =TRUNC(K46*G46)+1.33 -> 15829.33 | M46: 0.6 | N46: =TRUNC(M46*F46,2) -> 365.65 | O46: =TRUNC(N46*G46)+1.66 -> 31658.66 | T46: 60.94 | U46: =TRUNC(G46*T46)+0 -> 5276 | V46: 0.1 | W46: =TRUNC(V46*F46,2) -> 60.94 | X46: 0 | Y46: =Z46/F46 -> 0 | AA46: =TRUNC(Z46*G46)+0 -> 0 | AB46: =AC46/F46 -> 0 | AD46: =TRUNC(AC46*G46) -> 0 | AE46: =SUM(J46,M46,P46,V46,Y46,AB46) -> 1 | AF46: =SUM(K46,N46,Q46,W46,Z46,T46,AC46) -> 670.35 | AG46: =SUM(L46,O46,R46,X46,AA46,U46,AD46) -> 52763.99 | AH46: =IF(AE46=100%,"ITEM FINALIZADO",AE46) -> ITEM FINALIZADO | AI46: =((F48/2)+F50)-F46 -> 709.27
A47: 5 | B47: REVESTIMENTO | H47: =SUM(H48:H51) -> 141718.33
A48: 5.1 | B48: 87894 | C48: CHAPISCO APLICADO EM ALVENARIA (SEM PRESENÇA DE VÃOS) E ESTRUTURAS DE CONCRETO DE FACHADA, COM COLHER DE PEDREIRO. ARGAMASSA TRAÇO 1.3 COM PREPARO EM BETONEIRA 400L. AF_10/2022 | D48: SINAPI | E48: M2 | F48: 2157.32 | G48: 6.63 | H48: =(F48*G48) -> 14303.032 | P48: 0.5 | Q48: =TRUNC(P48*F48,2) -> 1078.66 | R48: =TRUNC(Q48*G48) -> 7151 | T48: 1078.66 | U48: =TRUNC(G48*T48)+0 -> 7151 | V48: 0.5 | W48: =TRUNC(V48*F48,2) -> 1078.66 | X48: 0 | Y48: =Z48/F48 -> 0 | AA48: =TRUNC(Z48*G48)+0 -> 0 | AB48: =AC48/F48 -> 0 | AD48: =TRUNC(AC48*G48) -> 0 | AE48: =SUM(J48,M48,P48,V48,Y48,AB48) -> 1 | AF48: =SUM(K48,N48,Q48,W48,Z48,T48,AC48) -> 3235.98 | AG48: =SUM(L48,O48,R48,X48,AA48,U48,AD48) -> 14302 | AH48: =IF(AE48=100%,"ITEM FINALIZADO",AE48) -> ITEM FINALIZADO
A49: 5.2 | B49: 87548 | C49: MASSA ÚNICA, EM ARGAMASSA TRAÇO 1:2:8, PREPARO MANUAL, APLICADA MANUALMENTE EM PAREDES INTERNAS DE AMBIENTES COM ÁREA ENTRE 5M² E 10M², E = 10MM, COM TALISCAS, AF_03/2024 | D49: SINAPI | E49: M2 | F49: 2157.32 | G49: 27.55 | H49: =(F49*G49) -> 59434.166 | P49: 0.5 | Q49: =TRUNC(P49*F49,2) -> 1078.66 | R49: =TRUNC(Q49*G49) -> 29717 | T49: 1078.66 | U49: =TRUNC(G49*T49)+0 -> 29717 | V49: 0.5 | W49: =TRUNC(V49*F49,2) -> 1078.66 | X49: 0 | Y49: =Z49/F49 -> 0 | AA49: =TRUNC(Z49*G49)+0 -> 0 | AB49: =AC49/F49 -> 0 | AD49: =TRUNC(AC49*G49) -> 0 | AE49: =SUM(J49,M49,P49,V49,Y49,AB49) -> 1 | AF49: =SUM(K49,N49,Q49,W49,Z49,T49,AC49) -> 3235.98 | AG49: =SUM(L49,O49,R49,X49,AA49,U49,AD49) -> 59434 | AH49: =IF(AE49=100%,"ITEM FINALIZADO",AE49) -> ITEM FINALIZADO
A50: 5.3 | B50: 104817 | C50: REVESTIMENTO CERÂMICO PARA PAREDES INTERNAS COM PLACAS TIPO PASTILHA DE DIMENSÕES 5 X 5 CM (PLACAS DE 30 X 30 CM) CM APLICADAS A MEIA ALTURA DAS PAREDES. AF_02/2023 | D50: SINAPI | E50: M2 | F50: 240.04 | G50: 218.41 | H50: =(F50*G50) -> 52427.136 | Q50: =TRUNC(P50*F50,2) -> 0 | R50: =TRUNC(Q50*G50) -> 0 | T50: 72.01 | U50: =TRUNC(G50*T50)+0 -> 15727 | V50: 1 | W50: =TRUNC(V50*F50,2) -> 240.04 | X50: 36700.13 | Y50: =Z50/F50 -> 0 | AA50: =TRUNC(Z50*G50)+0 -> 0 | AB50: =AC50/F50 -> 0 | AD50: =TRUNC(AC50*G50) -> 0 | AE50: =SUM(J50,M50,P50,V50,Y50,AB50) -> 1 | AF50: =SUM(K50,N50,Q50,W50,Z50,T50,AC50) -> 312.05 | AG50: =SUM(L50,O50,R50,X50,AA50,U50,AD50) -> 52427.13 | AH50: =IF(AE50=100%,"ITEM FINALIZADO",AE50) -> ITEM FINALIZADO
A51: 5.4 | B51: 87262 | C51: REVESTIMENTO CERÂMICO PARA PISO COM PLACAS TIPO PORCELANATO DE DIMENSÕES 60X60 CM APLICADA EM AMBIENTES DE ÁREA ENTRE 5 M² E 10 M². AF 02/2023 PE | D51: SINAPI | E51: M2 | F51: 92.76 | G51: 167.68 | H51: =(F51*G51) -> 15553.997 | U51: =TRUNC(G51*T51)+0 -> 0 | V51: 0 | W51: =TRUNC(V51*F51,2) -> 0 | X51: =TRUNC(W51*G51)+0 -> 0 | Y51: =Z51/F51 -> 0 | AA51: =TRUNC(Z51*G51)+0 -> 0 | AB51: =AC51/F51 -> 0 | AD51: =TRUNC(AC51*G51) -> 0 | AE51: =SUM(J51,M51,P51,V51,Y51,AB51) -> 0 | AF51: =SUM(K51,N51,Q51,W51,Z51,T51,AC51) -> 0 | AG51: =SUM(L51,O51,R51,X51,AA51,U51,AD51) -> 0 | AH51: =IF(AE51=100%,"ITEM FINALIZADO",AE51) -> 0
A52: 6 | B52: PISO | H52: =SUM(H53:H54) -> 67783.043
A53: 6.1 | B53: 87298 | C53: ARGAMASSA TRAÇO 1:3 (EM VOLUME DE CIMENTO E AREIA MÉDIA ÚMIDA) PARA CONTRAPISO, PREPARO MECANICO COM BETONEIRA 400 L. AF 08/2019 | D53: SINAPI | E53: M3 | F53: 16.97 | G53: 578.78 | H53: =(F53*G53)-0.01 -> 9821.8866 | S53: 0 | T53: 8.48 | U53: =TRUNC(G53*T53)+0 -> 4908 | V53: 1 | W53: =TRUNC(V53*F53,2) -> 16.97 | X53: 4913.89 | Y53: =Z53/F53 -> 0 | AA53: =TRUNC(Z53*G53)+0 -> 0 | AB53: =AC53/F53 -> 0 | AD53: =TRUNC(AC53*G53) -> 0 | AE53: =SUM(J53,M53,P53,V53,Y53,AB53) -> 1 | AF53: =SUM(K53,N53,Q53,W53,Z53,T53,AC53) -> 25.45 | AG53: =SUM(L53,O53,R53,X53,AA53,U53,AD53) -> 9821.89 | AH53: =IF(AE53=100%,"ITEM FINALIZADO",AE53) -> ITEM FINALIZADO
A54: 6.2 | B54: 104597 | C54: REVESTIMENTO CERÂMICO PARA PISO COM PLACAS TIPO PORCELANATO DE DIMENSOES 80X80 CM APLICADA EM AMBIENTES DE AREA ENTRE 556 E 10 M'. AF 022023 PE | D54: SINAPI | E54: M2 | F54: 339.53 | G54: 170.71 | H54: =(F54*G54)-0.01 -> 57961.156 | U54: =TRUNC(G54*T54)+0 -> 0 | W54: =TRUNC(V54*F54,2) -> 0 | X54: =TRUNC(W54*G54)+0 -> 0 | Y54: =Z54/F54 -> 0 | AA54: =TRUNC(Z54*G54)+0 -> 0 | AB54: =AC54/F54 -> 0 | AD54: =TRUNC(AC54*G54) -> 0 | AE54: =SUM(J54,M54,P54,V54,Y54,AB54) -> 0 | AF54: =SUM(K54,N54,Q54,W54,Z54,T54,AC54) -> 0 | AG54: =SUM(L54,O54,R54,X54,AA54,U54,AD54) -> 0
A55: 7 | B55: INSTALAÇÕES SANITÁRIAS | H55: =SUM(H56,H71) -> 45511.361
A56: 7.1 | B56: SANITÁRIA | H56: =SUM(H57:H70) -> 16853.64
A57: 7.1.1 | B57: 86931 | C57: VASO SANITARIO SIFONADO COM CAIXA ACOPLADA LOUÇA BRANCA, INCLUSO ENGATE FLEXÍVEL EM PLASTICO BRANCO, 1/2 X 40CM - FORNECIMENTO E INSTALAÇÃO. AF_01/2020 | D57: SINAPI | E57: UNID | F57: 10 | G57: 453.87 | H57: =(F57*G57) -> 4538.7 | U57: =TRUNC(G57*T57)+0 -> 0 | W57: =TRUNC(V57*F57,2) -> 0 | X57: =TRUNC(W57*G57)+0 -> 0 | Y57: =Z57/F57 -> 0 | AA57: =TRUNC(Z57*G57)+0 -> 0 | AB57: =AC57/F57 -> 0 | AD57: =TRUNC(AC57*G57) -> 0 | AE57: =SUM(J57,M57,P57,V57,Y57,AB57) -> 0 | AF57: =SUM(K57,N57,Q57,W57,Z57,T57,AC57) -> 0 | AG57: =SUM(L57,O57,R57,X57,AA57,U57,AD57) -> 0 | AH57: =IF(AE57=100%,"ITEM FINALIZADO",AE57) -> 0
A58: 7.1.2 | B58: 86939 | C58: LAVATÓRIO LOUÇA BRANCA COM COLUNA, *44 X 35,5* CM, PADRÃO POPULAR, INCLUSO SIFAO FLEXÍVEL EM PVC, VALVULA E ENGATE FLEXÍVEL 30CM EM PLASTICO E COM TORNEIRA CROMADA PADRAO POPULAR-FORNECIMENTO E INSTALAÇÃO. AF_01/2020 | D58: SINAPI | E58: UNID | F58: 10 | G58: 384.59 | H58: =(F58*G58) -> 3845.9 | U58: =TRUNC(G58*T58)+0 -> 0 | W58: =TRUNC(V58*F58,2) -> 0 | X58: =TRUNC(W58*G58)+0 -> 0 | Y58: =Z58/F58 -> 0 | AA58: =TRUNC(Z58*G58)+0 -> 0 | AB58: =AC58/F58 -> 0 | AD58: =TRUNC(AC58*G58) -> 0 | AE58: =SUM(J58,M58,P58,V58,Y58,AB58) -> 0 | AF58: =SUM(K58,N58,Q58,W58,Z58,T58,AC58) -> 0 | AG58: =SUM(L58,O58,R58,X58,AA58,U58,AD58) -> 0 | AH58: =IF(AE58=100%,"ITEM FINALIZADO",AE58) -> 0
A59: 7.1.3 | B59: 89714 | C59: TUBO PVC, SERIE NORMAL, ESGOTO PREDIAL, DN 100 MM, FORNECIDO E INSTALADO EM RAMAL DE DESCARGA OU RAMAL DE ESGOTO SANITARIO. AF 08/2022 | D59: SINAPI | E59: M | F59: 100 | G59: 34.63 | H59: =(F59*G59) -> 3463 | P59: 0.8 | Q59: =TRUNC(P59*F59,2) -> 80 | R59: =TRUNC(Q59*G59) -> 2770 | T59: 20 | U59: =TRUNC(G59*T59)+0 -> 692 | V59: 0.2 | W59: =TRUNC(V59*F59,2) -> 20 | X59: 0 | Y59: =Z59/F59 -> 0 | AA59: =TRUNC(Z59*G59)+0 -> 0 | AB59: =AC59/F59 -> 0 | AD59: =TRUNC(AC59*G59) -> 0 | AE59: =SUM(J59,M59,P59,V59,Y59,AB59) -> 1 | AF59: =SUM(K59,N59,Q59,W59,Z59,T59,AC59) -> 120 | AG59: =SUM(L59,O59,R59,X59,AA59,U59,AD59) -> 3462 | AH59: =IF(AE59=100%,"ITEM FINALIZADO",AE59) -> ITEM FINALIZADO
A60: 7.1.4 | B60: 89711 | C60: TUBO PVC, SERIE NORMAL, ESGOTO PREDIAL, DN 40 MM, FORNECIDO E INSTALADO EM RAMAL DE DESCARGA OU RAMAL DE ESGOTO SANITARIO. AF 08/2022 | D60: SINAPI | E60: M | F60: 20 | G60: 20.06 | H60: =(F60*G60) -> 401.2 | P60: 0.8 | Q60: =TRUNC(P60*F60,2) -> 16 | R60: =TRUNC(Q60*G60) -> 320 | T60: 4 | U60: =TRUNC(G60*T60)+0 -> 80 | V60: 0.2 | W60: =TRUNC(V60*F60,2) -> 4 | X60: 0 | Y60: =Z60/F60 -> 0 | AA60: =TRUNC(Z60*G60)+0 -> 0 | AB60: =AC60/F60 -> 0 | AD60: =TRUNC(AC60*G60) -> 0 | AE60: =SUM(J60,M60,P60,V60,Y60,AB60) -> 1 | AF60: =SUM(K60,N60,Q60,W60,Z60,T60,AC60) -> 24 | AG60: =SUM(L60,O60,R60,X60,AA60,U60,AD60) -> 400 | AH60: =IF(AE60=100%,"ITEM FINALIZADO",AE60) -> ITEM FINALIZADO
A61: 7.1.5 | B61: 89798 | C61: TUBO PVC, SERIE NORMAL, ESGOTO PREDIAL, DN 50 MM, FORNECIDO E INSTALADO EM PRUMADA DE ESGOTO SANITARIO OU VENTILAÇÃO. AF 08/2022 | D61: SINAPI | E61: M | F61: 65 | G61: 11.08 | H61: =(F61*G61) -> 720.2 | P61: 0.8 | Q61: =TRUNC(P61*F61,2) -> 52 | R61: =TRUNC(Q61*G61) -> 576 | U61: =TRUNC(G61*T61)+0 -> 0 | W61: =TRUNC(V61*F61,2) -> 0 | X61: =TRUNC(W61*G61)+0 -> 0 | Y61: =Z61/F61 -> 0.2 | Z61: 13 | AA61: =TRUNC(Z61*G61)+0 -> 144 | AB61: =AC61/F61 -> 0 | AD61: =TRUNC(AC61*G61) -> 0 | AE61: =SUM(J61,M61,P61,V61,Y61,AB61) -> 1 | AF61: =SUM(K61,N61,Q61,W61,Z61,T61,AC61) -> 65 | AG61: =SUM(L61,O61,R61,X61,AA61,U61,AD61) -> 720 | AH61: =IF(AE61=100%,"ITEM FINALIZADO",AE61) -> ITEM FINALIZADO
A62: 7.1.6 | B62: 104326 | C62: RALO SECO CONICO, PVC, DN 100 X 40 MM, JUNTA SOLDAVEL, FORNECIDO E INSTALADO EM RAMAL DE DESCARGA OU EM RAMAL DE ESGOTO SANITARIO. AF 08/2022 | D62: SINAPI | E62: UNID | F62: 10 | G62: 19.2 | H62: =(F62*G62) -> 192 | U62: =TRUNC(G62*T62)+0 -> 0 | W62: =TRUNC(V62*F62,2) -> 0 | X62: =TRUNC(W62*G62)+0 -> 0 | Y62: =Z62/F62 -> 0 | AA62: =TRUNC(Z62*G62)+0 -> 0 | AB62: =AC62/F62 -> 0 | AD62: =TRUNC(AC62*G62) -> 0 | AE62: =SUM(J62,M62,P62,V62,Y62,AB62) -> 0 | AF62: =SUM(K62,N62,Q62,W62,Z62,T62,AC62) -> 0 | AG62: =SUM(L62,O62,R62,X62,AA62,U62,AD62) -> 0 | AH62: =IF(AE62=100%,"ITEM FINALIZADO",AE62) -> 0
A63: 7.1.7 | B63: 104327 | C63: RALO SIFONADO REDONDO, PVC, DN 100 X 40 MM, JUNTA SOLDAVEL, FORNECIDO E INSTALADO EM RAMAL DE DESCARGA OU EM RAMAL DE ESGOTO SANITARIO. AF 08/2022 | D63: SINAPI | E63: UNID | F63: 10 | G63: 18.32 | H63: =(F63*G63) -> 183.2 | U63: =TRUNC(G63*T63)+0 -> 0 | W63: =TRUNC(V63*F63,2) -> 0 | X63: =TRUNC(W63*G63)+0 -> 0 | Y63: =Z63/F63 -> 0 | AA63: =TRUNC(Z63*G63)+0 -> 0 | AB63: =AC63/F63 -> 0 | AD63: =TRUNC(AC63*G63) -> 0 | AE63: =SUM(J63,M63,P63,V63,Y63,AB63) -> 0 | AF63: =SUM(K63,N63,Q63,W63,Z63,T63,AC63) -> 0 | AG63: =SUM(L63,O63,R63,X63,AA63,U63,AD63) -> 0 | AH63: =IF(AE63=100%,"ITEM FINALIZADO",AE63) -> 0
A64: 7.1.8 | B64: 89726 | C64: JOELHO 45 GRAUS, PVC, SERIE NORMAL, ESGOTO PREDIAL, DN 40 MM, JUNTA SOLDAVEL, FORNECIDO E INSTALADO EM RAMAL DE DESCARGA OU RAMAL DE ESGOTO SANITARIO. AF 08/2022 | D64: SINAPI | E64: UNID | F64: 7 | G64: 9.43 | H64: =(F64*G64) -> 66.01 | P64: 0.8 | Q64: =TRUNC(P64*F64,2) -> 5.6 | R64: =TRUNC(Q64*G64) -> 52 | T64: 1.4 | U64: =TRUNC(G64*T64)+0 -> 13 | V64: 0.2 | W64: =TRUNC(V64*F64,2) -> 1.4 | X64: 0 | Y64: =Z64/F64 -> 0 | AA64: =TRUNC(Z64*G64)+0 -> 0 | AB64: =AC64/F64 -> 0 | AD64: =TRUNC(AC64*G64) -> 0 | AE64: =SUM(J64,M64,P64,V64,Y64,AB64) -> 1 | AF64: =SUM(K64,N64,Q64,W64,Z64,T64,AC64) -> 8.4 | AG64: =SUM(L64,O64,R64,X64,AA64,U64,AD64) -> 65 | AH64: =IF(AE64=100%,"ITEM FINALIZADO",AE64) -> ITEM FINALIZADO
A65: 7.1.9 | B65: 89732 | C65: JOELHO 45 GRAUS, PVC, SERIE NORMAL, ESGOTO PREDIAL, DN 50 MM, JUNTA ELASTICA, FORNECIDO E INSTALADO EM RAMAL DE DESCARGA OU RAMAL DE ESGOTO SANITARIO. AF 08/2022 | D65: SINAPI | E65: UNID | F65: 7 | G65: 14.36 | H65: =(F65*G65) -> 100.52 | P65: 0.8 | Q65: =TRUNC(P65*F65,2) -> 5.6 | R65: =TRUNC(Q65*G65) -> 80 | T65: 1.4 | U65: =TRUNC(G65*T65)+0 -> 20 | V65: 0.2 | W65: =TRUNC(V65*F65,2) -> 1.4 | X65: 0 | Y65: =Z65/F65 -> 0 | AA65: =TRUNC(Z65*G65)+0 -> 0 | AB65: =AC65/F65 -> 0 | AD65: =TRUNC(AC65*G65) -> 0 | AE65: =SUM(J65,M65,P65,V65,Y65,AB65) -> 1 | AF65: =SUM(K65,N65,Q65,W65,Z65,T65,AC65) -> 8.4 | AG65: =SUM(L65,O65,R65,X65,AA65,U65,AD65) -> 100 | AH65: =IF(AE65=100%,"ITEM FINALIZADO",AE65) -> ITEM FINALIZADO
A66: 7.1.10 | B66: 89809 | C66: JOELHO 90 GRAUS, PVC, SERIE NORMAL, ESGOTO PREDIAL, DN 100 MM, JUNTA ELASTICA, FORNECIDO E INSTALADO EM PRUMADA DE ESGOTO SANITARIO OU VENTILACAO. AF_08/2022 | D66: SINAPI | E66: UNID | F66: 10 | G66: 25.87 | H66: =(F66*G66) -> 258.7 | P66: 0.8 | Q66: =TRUNC(P66*F66,2) -> 8 | R66: =TRUNC(Q66*G66) -> 206 | T66: 2 | U66: =TRUNC(G66*T66)+0 -> 51 | V66: 0.2 | W66: =TRUNC(V66*F66,2) -> 2 | X66: 0 | Y66: =Z66/F66 -> 0 | AA66: =TRUNC(Z66*G66)+0 -> 0 | AB66: =AC66/F66 -> 0 | AD66: =TRUNC(AC66*G66) -> 0 | AE66: =SUM(J66,M66,P66,V66,Y66,AB66) -> 1 | AF66: =SUM(K66,N66,Q66,W66,Z66,T66,AC66) -> 12 | AG66: =SUM(L66,O66,R66,X66,AA66,U66,AD66) -> 257 | AH66: =IF(AE66=100%,"ITEM FINALIZADO",AE66) -> ITEM FINALIZADO
A67: 7.1.11 | B67: 69810 | C67: JOELHO 45 GRAUS, PVC, SERIE NORMAL, ESGOTO PREDIAL, DN 100 MM, JUNTA ELASTICA, FORNECIDO E INSTALADO EM PRUMADA DE ESGOTO SANITARIO OU VENTILACAO. AF_08/2022 | D67: SINAPI | E67: UNID | F67: 6 | G67: 26.53 | H67: =(F67*G67) -> 159.18 | P67: 0.8 | Q67: =TRUNC(P67*F67,2) -> 4.8 | R67: =TRUNC(Q67*G67) -> 127 | T67: 1.2 | U67: =TRUNC(G67*T67)+0 -> 31 | V67: 0.2 | W67: =TRUNC(V67*F67,2) -> 1.2 | X67: 0 | Y67: =Z67/F67 -> 0 | AA67: =TRUNC(Z67*G67)+0 -> 0 | AB67: =AC67/F67 -> 0 | AD67: =TRUNC(AC67*G67) -> 0 | AE67: =SUM(J67,M67,P67,V67,Y67,AB67) -> 1 | AF67: =SUM(K67,N67,Q67,W67,Z67,T67,AC67) -> 7.2 | AG67: =SUM(L67,O67,R67,X67,AA67,U67,AD67) -> 158 | AH67: =IF(AE67=100%,"ITEM FINALIZADO",AE67) -> ITEM FINALIZADO
A68: 7.1.12 | B68: 100864 | C68: BARRA DE APOIO EM "L", EM ACO INOX POLIDO 80 X 80 CM, FIXADA NA PAREDE - FORNECIMENTO E INSTALAÇÃO. AF 01/2020 | D68: SINAPI | E68: UNID | F68: 4 | G68: 632.21 | H68: =(F68*G68) -> 2528.84 | U68: =TRUNC(G68*T68)+0 -> 0 | W68: =TRUNC(V68*F68,2) -> 0 | X68: =TRUNC(W68*G68)+0 -> 0 | Y68: =Z68/F68 -> 0 | AA68: =TRUNC(Z68*G68)+0 -> 0 | AB68: =AC68/F68 -> 0 | AD68: =TRUNC(AC68*G68) -> 0 | AE68: =SUM(J68,M68,P68,V68,Y68,AB68) -> 0 | AF68: =SUM(K68,N68,Q68,W68,Z68,T68,AC68) -> 0 | AG68: =SUM(L68,O68,R68,X68,AA68,U68,AD68) -> 0 | AH68: =IF(AE68=100%,"ITEM FINALIZADO",AE68) -> 0
A69: 7.1.13 | B69: 89833 | C69: TE, PVC, SERIE NORMAL, ESGOTO PREDIAL, DN 100 X 100 MM, JUNTA ELASTICA, FORNECIDO E INSTALADO EM PRUMADA DE ESGOTO SANITARIO OU VENTILAÇÃO. AF_08/2022 | D69: SINAPI | E69: UNID | F69: 3 | G69: 39.81 | H69: =(F69*G69) -> 119.43 | P69: 0.8 | Q69: =TRUNC(P69*F69,2) -> 2.4 | R69: =TRUNC(Q69*G69) -> 95 | T69: 0.6 | U69: =TRUNC(G69*T69)+0 -> 23 | V69: 0.2 | W69: =TRUNC(V69*F69,2) -> 0.6 | X69: 0 | Y69: =Z69/F69 -> 0 | AA69: =TRUNC(Z69*G69)+0 -> 0 | AB69: =AC69/F69 -> 0 | AD69: =TRUNC(AC69*G69) -> 0 | AE69: =SUM(J69,M69,P69,V69,Y69,AB69) -> 1 | AF69: =SUM(K69,N69,Q69,W69,Z69,T69,AC69) -> 3.6 | AG69: =SUM(L69,O69,R69,X69,AA69,U69,AD69) -> 118 | AH69: =IF(AE69=100%,"ITEM FINALIZADO",AE69) -> ITEM FINALIZADO
A70: 7.1.14 | B70: 102711 | C70: JUNÇÃO DUPLA DE PVC, SERIE NORMAL, PARA ESGOTO PREDIAL, DN 100 X 100 X 100 MM, INSTALADA EM DRENO - FORNECIMENTO E INSTALAÇÃO. AF 07/2021 | D70: SINAPI | E70: UNID | F70: 4 | G70: 69.19 | H70: =(F70*G70) -> 276.76 | P70: 0.8 | Q70: =TRUNC(P70*F70,2) -> 3.2 | R70: =TRUNC(Q70*G70) -> 221 | T70: 0.8 | U70: =TRUNC(G70*T70)+0 -> 55 | V70: 0.2 | W70: =TRUNC(V70*F70,2) -> 0.8 | X70: 0 | Y70: =Z70/F70 -> 0 | AA70: =TRUNC(Z70*G70)+0 -> 0 | AB70: =AC70/F70 -> 0 | AD70: =TRUNC(AC70*G70) -> 0 | AE70: =SUM(J70,M70,P70,V70,Y70,AB70) -> 1 | AF70: =SUM(K70,N70,Q70,W70,Z70,T70,AC70) -> 4.8 | AG70: =SUM(L70,O70,R70,X70,AA70,U70,AD70) -> 276 | AH70: =IF(AE70=100%,"ITEM FINALIZADO",AE70) -> ITEM FINALIZADO
A71: 7.2 | B71: HIDRÁULICA | H71: =SUM(H72:H90) -> 28657.721
A72: 7.2.1 | B72: 102616 | C72: CAIXA D'AGUA EM POLIESTER REFORCADO COM FIBRA DE VIDRO, 3000 LITROS - FORNECIMENTO E INSTALAÇÃO. AF_06/2021 | D72: SINAPI | E72: UNID | F72: 2 | G72: 1826.49 | H72: =(F72*G72) -> 3652.98 | U72: =TRUNC(G72*T72)+0 -> 0 | W72: =TRUNC(V72*F72,2) -> 0 | X72: =TRUNC(W72*G72)+0 -> 0 | Y72: =Z72/F72 -> 0 | AA72: =TRUNC(Z72*G72)+0 -> 0 | AB72: =AC72/F72 -> 1 | AC72: 2 | AD72: =TRUNC(AC72*G72) -> 3652 | AE72: =SUM(J72,M72,P72,V72,Y72,AB72) -> 1 | AF72: =SUM(K72,N72,Q72,W72,Z72,T72,AC72) -> 2 | AG72: =SUM(L72,O72,R72,X72,AA72,U72,AD72) -> 3652 | AH72: =IF(AE72=100%,"ITEM FINALIZADO",AE72) -> ITEM FINALIZADO
A73: 7.2.2 | B73: 89446 | C73: TUBO, PVC, SOLDAVEL, DN 25MM, INSTALADO EM PRUMADA DE ÁGUA - FORNECIMENTO E INSTALAÇÃO. AF 06/2022 | D73: SINAPI | E73: M | F73: 100 | G73: 4.93 | H73: =(F73*G73) -> 493 | U73: =TRUNC(G73*T73)+0 -> 0 | W73: =TRUNC(V73*F73,2) -> 0 | X73: =TRUNC(W73*G73)+0 -> 0 | Y73: =Z73/F73 -> 0 | AA73: =TRUNC(Z73*G73)+0 -> 0 | AB73: =AC73/F73 -> 1 | AC73: 100 | AD73: =TRUNC(AC73*G73) -> 493 | AE73: =SUM(J73,M73,P73,V73,Y73,AB73) -> 1 | AF73: =SUM(K73,N73,Q73,W73,Z73,T73,AC73) -> 100 | AG73: =SUM(L73,O73,R73,X73,AA73,U73,AD73) -> 493 | AH73: =IF(AE73=100%,"ITEM FINALIZADO",AE73) -> ITEM FINALIZADO
A74: 7.2.3 | B74: 89366 | C74: JOELHO 90 GRAUS COM BUCHA DE LATAO, PVC, SOLDAVEL, DN 25MM, X 3/4 INSTALADO EM RAMAL OU SUB-RAMAL DE ÁGUA - FORNECIMENTO E INSTALAÇÃO. AF 06/2022 | D74: SINAPI | E74: UNID | F74: 10 | G74: 15.08 | H74: =(F74*G74) -> 150.8 | U74: =TRUNC(G74*T74)+0 -> 0 | W74: =TRUNC(V74*F74,2) -> 0 | X74: =TRUNC(W74*G74)+0 -> 0 | Y74: =Z74/F74 -> 0 | AA74: =TRUNC(Z74*G74)+0 -> 0 | AB74: =AC74/F74 -> 1 | AC74: 10 | AD74: =TRUNC(AC74*G74) -> 150 | AE74: =SUM(J74,M74,P74,V74,Y74,AB74) -> 1 | AF74: =SUM(K74,N74,Q74,W74,Z74,T74,AC74) -> 10 | AG74: =SUM(L74,O74,R74,X74,AA74,U74,AD74) -> 150 | AH74: =IF(AE74=100%,"ITEM FINALIZADO",AE74) -> ITEM FINALIZADO
A75: 7.2.4 | B75: 89355 | C75: TUBO, PVC, SOLDAVEL, DN 20MM, INSTALADO EM RAMAL OU SUB-RAMAL DE ÁGUA - FORNECIMENTO E INSTALAÇÃO. AF_06/2022 | D75: SINAPI | E75: M | F75: 8 | G75: 19.97 | H75: =(F75*G75) -> 159.76 | U75: =TRUNC(G75*T75)+0 -> 0 | W75: =TRUNC(V75*F75,2) -> 0 | X75: =TRUNC(W75*G75)+0 -> 0 | Y75: =Z75/F75 -> 0 | AA75: =TRUNC(Z75*G75)+0 -> 0 | AB75: =AC75/F75 -> 1 | AC75: 8 | AD75: =TRUNC(AC75*G75) -> 159 | AE75: =SUM(J75,M75,P75,V75,Y75,AB75) -> 1 | AF75: =SUM(K75,N75,Q75,W75,Z75,T75,AC75) -> 8 | AG75: =SUM(L75,O75,R75,X75,AA75,U75,AD75) -> 159 | AH75: =IF(AE75=100%,"ITEM FINALIZADO",AE75) -> ITEM FINALIZADO
A76: 7.2.5 | B76: 100860 | C76: CHUVEIRO ELÉTRICO COMUM CORPO PLASTICO, TIPO DUCHA - FORNECIMENTO E INSTALAÇÃO. AF 01/2020 | D76: SINAPI | E76: UNID | F76: 9 | G76: 96.06 | H76: =(F76*G76) -> 864.54 | U76: =TRUNC(G76*T76)+0 -> 0 | W76: =TRUNC(V76*F76,2) -> 0 | X76: =TRUNC(W76*G76)+0 -> 0 | Y76: =Z76/F76 -> 0 | AA76: =TRUNC(Z76*G76)+0 -> 0 | AB76: =AC76/F76 -> 1 | AC76: 9 | AD76: =TRUNC(AC76*G76) -> 864 | AE76: =SUM(J76,M76,P76,V76,Y76,AB76) -> 1 | AF76: =SUM(K76,N76,Q76,W76,Z76,T76,AC76) -> 9 | AG76: =SUM(L76,O76,R76,X76,AA76,U76,AD76) -> 864 | AH76: =IF(AE76=100%,"ITEM FINALIZADO",AE76) -> ITEM FINALIZADO
A77: 7.2.6 | B77: 89528 | C77: LUVA, PVC, SOLDAVEL, DN 25MM, INSTALADO EM PRUMADA DE ÁGUA - FORNECIMENTO E INSTALAÇÃO. AF 06/2022 | D77: SINAPI | E77: UNID | F77: 20 | G77: 3.83 | H77: =(F77*G77) -> 76.6 | U77: =TRUNC(G77*T77)+0 -> 0 | W77: =TRUNC(V77*F77,2) -> 0 | X77: =TRUNC(W77*G77)+0 -> 0 | Y77: =Z77/F77 -> 0 | AA77: =TRUNC(Z77*G77)+0 -> 0 | AB77: =AC77/F77 -> 1 | AC77: 20 | AD77: =TRUNC(AC77*G77) -> 76 | AE77: =SUM(J77,M77,P77,V77,Y77,AB77) -> 1 | AF77: =SUM(K77,N77,Q77,W77,Z77,T77,AC77) -> 20 | AG77: =SUM(L77,O77,R77,X77,AA77,U77,AD77) -> 76 | AH77: =IF(AE77=100%,"ITEM FINALIZADO",AE77) -> ITEM FINALIZADO
A78: 7.2.7 | B78: 104199 | C78: JOELHO 90 GRAUS, PPR, DN 20 MM, INSTALADO EM RAMAL OU SUB - RAMAL DE ÁGUA - FORNECIMENTO E INSTALAÇÃO. AF_082022 | D78: SINAPI | E78: UNID | F78: 5 | G78: 7.02 | H78: =(F78*G78) -> 35.1 | U78: =TRUNC(G78*T78)+0 -> 0 | W78: =TRUNC(V78*F78,2) -> 0 | X78: =TRUNC(W78*G78)+0 -> 0 | Y78: =Z78/F78 -> 0 | AA78: =TRUNC(Z78*G78)+0 -> 0 | AB78: =AC78/F78 -> 1 | AC78: 5 | AD78: =TRUNC(AC78*G78) -> 35 | AE78: =SUM(J78,M78,P78,V78,Y78,AB78) -> 1 | AF78: =SUM(K78,N78,Q78,W78,Z78,T78,AC78) -> 5 | AG78: =SUM(L78,O78,R78,X78,AA78,U78,AD78) -> 35 | AH78: =IF(AE78=100%,"ITEM FINALIZADO",AE78) -> ITEM FINALIZADO
A79: 7.2.8 | B79: 101964 | C79: LAJE PRE-MOLDADA UNIDIRECIONAL, BIAPOIADA, PARA FORRO, ENCHIMENTO EM CERÂMICA, VIGOTA CONVENCIONAL, ALTURA TOTAL DA LAJE (ENCHIMENTO+CAPA) = (8+3). AF_11/2020_PA | D79: SINAPI | E79: M2 | F79: 9 | G79: 152.7 | H79: =(F79*G79) -> 1374.3 | U79: =TRUNC(G79*T79)+0 -> 0 | W79: =TRUNC(V79*F79,2) -> 0 | X79: =TRUNC(W79*G79)+0 -> 0 | Y79: =Z79/F79 -> 0 | AA79: =TRUNC(Z79*G79)+0 -> 0 | AB79: =AC79/F79 -> 0 | AD79: =TRUNC(AC79*G79) -> 0 | AE79: =SUM(J79,M79,P79,V79,Y79,AB79) -> 0 | AF79: =SUM(K79,N79,Q79,W79,Z79,T79,AC79) -> 0 | AG79: =SUM(L79,O79,R79,X79,AA79,U79,AD79) -> 0 | AH79: =IF(AE79=100%,"ITEM FINALIZADO",AE79) -> 0
A80: 7.2.9 | B80: 95545 | C80: SABONETEIRA DE PAREDE EM METAL CROMADO, INCLUSO FIXAÇÃO. AF 01/2020 | D80: SINAPI | E80: UNID | F80: 9 | G80: 33.31 | H80: =(F80*G80) -> 299.79 | U80: =TRUNC(G80*T80)+0 -> 0 | W80: =TRUNC(V80*F80,2) -> 0 | X80: =TRUNC(W80*G80)+0 -> 0 | Y80: =Z80/F80 -> 0 | AA80: =TRUNC(Z80*G80)+0 -> 0 | AB80: =AC80/F80 -> 0 | AD80: =TRUNC(AC80*G80) -> 0 | AE80: =SUM(J80,M80,P80,V80,Y80,AB80) -> 0 | AF80: =SUM(K80,N80,Q80,W80,Z80,T80,AC80) -> 0 | AG80: =SUM(L80,O80,R80,X80,AA80,U80,AD80) -> 0 | AH80: =IF(AE80=100%,"ITEM FINALIZADO",AE80) -> 0
A81: 7.2.10 | B81: 95547 | C81: SABONETEIRA PLÁSTICA TIPO DISPENSER PARA SABONETE LIQUIDO COM RESERVATÓRIO 600 A 1500 ML, INCLUSO FIXAÇÃO. AF_01/2020 | D81: SINAPI | E81: UNID | F81: 10 | G81: 91.61 | H81: =(F81*G81) -> 916.1 | U81: =TRUNC(G81*T81)+0 -> 0 | W81: =TRUNC(V81*F81,2) -> 0 | X81: =TRUNC(W81*G81)+0 -> 0 | Y81: =Z81/F81 -> 0 | AA81: =TRUNC(Z81*G81)+0 -> 0 | AB81: =AC81/F81 -> 0 | AD81: =TRUNC(AC81*G81) -> 0 | AE81: =SUM(J81,M81,P81,V81,Y81,AB81) -> 0 | AF81: =SUM(K81,N81,Q81,W81,Z81,T81,AC81) -> 0 | AG81: =SUM(L81,O81,R81,X81,AA81,U81,AD81) -> 0 | AH81: =IF(AE81=100%,"ITEM FINALIZADO",AE81) -> 0
A82: 7.2.11 | B82: 95547 | C82: SABONETEIRA PLÁSTICA TIPO DISPENSER PARA SABONETE LIQUIDO COM RESERVATÓRIO 800 A 1500 ML, INCLUSO FIXAÇÃO. AF_01/2020 | D82: SINAPI | E82: UNID | F82: 12 | G82: 91.61 | H82: =(F82*G82) -> 1099.32 | U82: =TRUNC(G82*T82)+0 -> 0 | W82: =TRUNC(V82*F82,2) -> 0 | X82: =TRUNC(W82*G82)+0 -> 0 | Y82: =Z82/F82 -> 0 | AA82: =TRUNC(Z82*G82)+0 -> 0 | AB82: =AC82/F82 -> 0 | AD82: =TRUNC(AC82*G82) -> 0 | AE82: =SUM(J82,M82,P82,V82,Y82,AB82) -> 0 | AF82: =SUM(K82,N82,Q82,W82,Z82,T82,AC82) -> 0 | AG82: =SUM(L82,O82,R82,X82,AA82,U82,AD82) -> 0 | AH82: =IF(AE82=100%,"ITEM FINALIZADO",AE82) -> 0
A83: 7.2.12 | B83: 90373 | C83: JOELHO 90 GRAUS COM BUCHA DE LATÃO, PVC, SOLDÁVEL, DN 25MM, X 1/2 INSTALADO EM RAMAL OU SUB-RAMAL DE ÁGUA - FORNECIMENTO E INSTALAÇÃO. AF 06/2022 | D83: SINAPI | E83: UNID | F83: 10 | G83: 12.1 | H83: =(F83*G83) -> 121 | U83: =TRUNC(G83*T83)+0 -> 0 | W83: =TRUNC(V83*F83,2) -> 0 | X83: =TRUNC(W83*G83)+0 -> 0 | Y83: =Z83/F83 -> 0 | AA83: =TRUNC(Z83*G83)+0 -> 0 | AB83: =AC83/F83 -> 1 | AC83: 10 | AD83: =TRUNC(AC83*G83) -> 121 | AE83: =SUM(J83,M83,P83,V83,Y83,AB83) -> 1 | AF83: =SUM(K83,N83,Q83,W83,Z83,T83,AC83) -> 10 | AG83: =SUM(L83,O83,R83,X83,AA83,U83,AD83) -> 121 | AH83: =IF(AE83=100%,"ITEM FINALIZADO",AE83) -> ITEM FINALIZADO
A84: 7.2.13 | B84: 89985 | C84: REGISTRO DE PRESSÃO BRUTO, LATÃO, ROSCÁVEL, 3/4", COM ACABAMENTO E CANOPLA CROMADOS - FORNECIMENTO E INSTALAÇÃO, AF 08/2021 | D84: SINAPI | E84: UNID | F84: 9 | G84: 91.43 | H84: =(F84*G84) -> 822.87 | U84: =TRUNC(G84*T84)+0 -> 0 | W84: =TRUNC(V84*F84,2) -> 0 | X84: =TRUNC(W84*G84)+0 -> 0 | Y84: =Z84/F84 -> 0 | AA84: =TRUNC(Z84*G84)+0 -> 0 | AB84: =AC84/F84 -> 1 | AC84: 9 | AD84: =TRUNC(AC84*G84) -> 822 | AE84: =SUM(J84,M84,P84,V84,Y84,AB84) -> 1 | AF84: =SUM(K84,N84,Q84,W84,Z84,T84,AC84) -> 9 | AG84: =SUM(L84,O84,R84,X84,AA84,U84,AD84) -> 822 | AH84: =IF(AE84=100%,"ITEM FINALIZADO",AE84) -> ITEM FINALIZADO
A85: 7.2.14 | B85: 86915 | C85: TORNEIRA CROMADA DE MESA, 1/2" OU 3/4", PARA LAVATÓRIO, PADRÃO MÉDIO - FORNECIMENTO E INSTALAÇÃO. AF_01/2020 | D85: SINAPI | E85: UNID | F85: 10 | G85: 126.1 | H85: =(F85*G85) -> 1261 | U85: =TRUNC(G85*T85)+0 -> 0 | W85: =TRUNC(V85*F85,2) -> 0 | X85: =TRUNC(W85*G85)+0 -> 0 | Y85: =Z85/F85 -> 0 | AA85: =TRUNC(Z85*G85)+0 -> 0 | AB85: =AC85/F85 -> 0 | AD85: =TRUNC(AC85*G85) -> 0 | AE85: =SUM(J85,M85,P85,V85,Y85,AB85) -> 0 | AF85: =SUM(K85,N85,Q85,W85,Z85,T85,AC85) -> 0 | AG85: =SUM(L85,O85,R85,X85,AA85,U85,AD85) -> 0 | AH85: =IF(AE85=100%,"ITEM FINALIZADO",AE85) -> 0
A86: 7.2.15 | B86: 86911 | C86: TORNEIRA CROMADA LONGA, DE PAREDE, 1/2" OU 3/4", PARA PIA DE COZINHA. PADRÃO POPULAR - FORNECIMENTO E INSTALAÇÃO. AF 01/2020 | D86: SINAPI | E86: UNID | F86: 1 | G86: 77.43 | H86: =(F86*G86) -> 77.43 | U86: =TRUNC(G86*T86)+0 -> 0 | W86: =TRUNC(V86*F86,2) -> 0 | X86: =TRUNC(W86*G86)+0 -> 0 | Y86: =Z86/F86 -> 0 | AA86: =TRUNC(Z86*G86)+0 -> 0 | AB86: =AC86/F86 -> 0 | AD86: =TRUNC(AC86*G86) -> 0 | AE86: =SUM(J86,M86,P86,V86,Y86,AB86) -> 0 | AF86: =SUM(K86,N86,Q86,W86,Z86,T86,AC86) -> 0 | AG86: =SUM(L86,O86,R86,X86,AA86,U86,AD86) -> 0 | AH86: =IF(AE86=100%,"ITEM FINALIZADO",AE86) -> 0
A87: 7.2.16 | B87: 94497 | C87: REGISTRO DE GAVETA BRUTO, LATÃO, ROSCÁVEL, 1 1/2" - FORNECIMENTO E INSTALAÇÃO. AF 08/2021 | D87: SINAPI | E87: UNID | F87: 9 | G87: 108.06 | H87: =(F87*G87) -> 972.54 | U87: =TRUNC(G87*T87)+0 -> 0 | W87: =TRUNC(V87*F87,2) -> 0 | X87: =TRUNC(W87*G87)+0 -> 0 | Y87: =Z87/F87 -> 0 | AA87: =TRUNC(Z87*G87)+0 -> 0 | AB87: =AC87/F87 -> 1 | AC87: 9 | AD87: =TRUNC(AC87*G87) -> 972 | AE87: =SUM(J87,M87,P87,V87,Y87,AB87) -> 1 | AF87: =SUM(K87,N87,Q87,W87,Z87,T87,AC87) -> 9 | AG87: =SUM(L87,O87,R87,X87,AA87,U87,AD87) -> 972 | AH87: =IF(AE87=100%,"ITEM FINALIZADO",AE87) -> ITEM FINALIZADO
A88: 7.2.17 | B88: 103039 | C88: REGISTRO DE ESFERA, PVC, ROSCÁVEL, COM VOLANTE, 1 1/2" - FORNECIMENTO E INSTALAÇÃO. AF 08/2021 | D88: SINAPI | E88: UNID | F88: 5 | G88: 50.13 | H88: =(F88*G88) -> 250.65 | U88: =TRUNC(G88*T88)+0 -> 0 | W88: =TRUNC(V88*F88,2) -> 0 | X88: =TRUNC(W88*G88)+0 -> 0 | Y88: =Z88/F88 -> 0 | AA88: =TRUNC(Z88*G88)+0 -> 0 | AB88: =AC88/F88 -> 1 | AC88: 5 | AD88: =TRUNC(AC88*G88) -> 250 | AE88: =SUM(J88,M88,P88,V88,Y88,AB88) -> 1 | AF88: =SUM(K88,N88,Q88,W88,Z88,T88,AC88) -> 5 | AG88: =SUM(L88,O88,R88,X88,AA88,U88,AD88) -> 250 | AH88: =IF(AE88=100%,"ITEM FINALIZADO",AE88) -> ITEM FINALIZADO
A89: 7.2.18 | B89: 94782 | C89: (COMPOSIÇÃO REPRESENTATIVA) DO SERVIÇO DE CONTRAPISO EM ARGAMASSA TRAÇO 1:4 (CIM E AREIA), BETONEIRA 400 L, E = 4 CM ÁREAS SECAS E MOLHADAS SOBRE LAJE , E = 3 CM ÁREAS MOLHADAS SOBRE IMPERMEABILIZAÇÃO, PARA EDIFICAÇÃO MULTIFAMILIAR. AF_11/2014 | D89: SINAPI | E89: M2 | F89: 9 | G89: 44.22 | H89: =(F89*G89) -> 397.98 | U89: =TRUNC(G89*T89)+0 -> 0 | W89: =TRUNC(V89*F89,2) -> 0 | X89: =TRUNC(W89*G89)+0 -> 0 | Y89: =Z89/F89 -> 0 | AA89: =TRUNC(Z89*G89)+0 -> 0 | AB89: =AC89/F89 -> 0 | AD89: =TRUNC(AC89*G89) -> 0 | AE89: =SUM(J89,M89,P89,V89,Y89,AB89) -> 0 | AF89: =SUM(K89,N89,Q89,W89,Z89,T89,AC89) -> 0 | AG89: =SUM(L89,O89,R89,X89,AA89,U89,AD89) -> 0 | AH89: =IF(AE89=100%,"ITEM FINALIZADO",AE89) -> 0
A90: 7.2.19 | B90: 98557 | C90: IMPERMEABILIZAÇÃO DE SUPERFICIE COM EMULSAO ASFALTICA, 2 DEMAOS. AF 09/2023 | D90: SINAPI | E90: M2 | F90: 339.53 | G90: 46.04 | H90: =(F90*G90) -> 15631.961 | P90: 1 | Q90: =TRUNC(P90*F90,2) -> 339.53 | R90: =TRUNC(Q90*G90) -> 15631 | U90: =TRUNC(G90*T90)+0 -> 0 | W90: =TRUNC(V90*F90,2) -> 0 | X90: =TRUNC(W90*G90)+0 -> 0 | Y90: =Z90/F90 -> 0 | AA90: =TRUNC(Z90*G90)+0 -> 0 | AB90: =AC90/F90 -> 0 | AD90: =TRUNC(AC90*G90) -> 0 | AE90: =SUM(J90,M90,P90,V90,Y90,AB90) -> 1 | AF90: =SUM(K90,N90,Q90,W90,Z90,T90,AC90) -> 339.53 | AG90: =SUM(L90,O90,R90,X90,AA90,U90,AD90) -> 15631 | AH90: =IF(AE90=100%,"ITEM FINALIZADO",AE90) -> ITEM FINALIZADO
A91: 8 | B91: PINTURA | H91: =SUM(H92:H97) -> 109225.03
A92: 8.1 | B92: 98135 | C92: APLICAÇÃO MANUAL DE MASSA ACRÍLICA EM PAREDES EXTERNAS DE CASAS, DUAS DEMÃOS. AF 03/2024 | D92: SINAPI | E92: M2 | F92: 2157.32 | G92: 28.15 | H92: =(F92*G92)-0.01 -> 60728.548 | U92: =TRUNC(G92*T92)+0 -> 0 | W92: =TRUNC(V92*F92,2) -> 0 | X92: =TRUNC(W92*G92)+0 -> 0 | Y92: =Z92/F92 -> 0 | AA92: =TRUNC(Z92*G92)+0 -> 0 | AB92: =AC92/F92 -> 0.1605733 | AC92: ='MEMORIAL DE CALCULO'!AW107 -> 346.408 | AD92: =TRUNC(AC92*G92) -> 9751 | AE92: =SUM(J92,M92,P92,V92,Y92,AB92) -> 0.1605733 | AF92: =SUM(K92,N92,Q92,W92,Z92,T92,AC92) -> 346.408 | AG92: =SUM(L92,O92,R92,X92,AA92,U92,AD92) -> 9751
A93: 8.2 | B93: 96129 | C93: APLICAÇÃO MANUAL DE MASSA ACRÍLICA EM SUPERFICIES INTERNAS DE SACADA DE EDIFÍCIOS DE MÚLTIPLOS PAVIMENTOS. UMA DEMÃO. AF 03/2024 | D93: SINAPI | E93: M2 | F93: 57.02 | G93: 33.53 | H93: =(F93*G93) -> 1911.8806 | U93: =TRUNC(G93*T93)+0 -> 0 | W93: =TRUNC(V93*F93,2) -> 0 | X93: =TRUNC(W93*G93)+0 -> 0 | Y93: =Z93/F93 -> 0 | AA93: =TRUNC(Z93*G93)+0 -> 0 | AB93: =AC93/F93 -> 0 | AD93: =TRUNC(AC93*G93) -> 0 | AE93: =SUM(J93,M93,P93,V93,Y93,AB93) -> 0 | AF93: =SUM(K93,N93,Q93,W93,Z93,T93,AC93) -> 0 | AG93: =SUM(L93,O93,R93,X93,AA93,U93,AD93) -> 0
A94: 8.3 | B94: 104641 | C94: PINTURA LATÉX ACRÍLICA ECONÔMICA, APLICAÇÃO MANUAL EM PAREDES, DUAS DEMÃOS. AF 04/2023 | D94: SINAPI | E94: M2 | F94: 2157.32 | G94: 8.75 | H94: =(F94*G94) -> 18876.55 | U94: =TRUNC(G94*T94)+0 -> 0 | W94: =TRUNC(V94*F94,2) -> 0 | X94: =TRUNC(W94*G94)+0 -> 0 | Y94: =Z94/F94 -> 0 | AA94: =TRUNC(Z94*G94)+0 -> 0 | AB94: =AC94/F94 -> 0 | AD94: =TRUNC(AC94*G94) -> 0 | AE94: =SUM(J94,M94,P94,V94,Y94,AB94) -> 0 | AF94: =SUM(K94,N94,Q94,W94,Z94,T94,AC94) -> 0 | AG94: =SUM(L94,O94,R94,X94,AA94,U94,AD94) -> 0
A95: 8.4 | B95: 88415 | C95: APLICAÇÃO MANUAL DE FUNDO SELADOR ACRÍLICO EM PAREDES EXTERNAS DE CASAS. AF 03/2024 | D95: SINAPI | E95: M2 | F95: 2157.32 | G95: 4.49 | H95: =(F95*G95)-0.01 -> 9686.3568 | U95: =TRUNC(G95*T95)+0 -> 0 | W95: =TRUNC(V95*F95,2) -> 0 | X95: =TRUNC(W95*G95)+0 -> 0 | Y95: =Z95/F95 -> 0 | AA95: =TRUNC(Z95*G95)+0 -> 0 | AB95: =AC95/F95 -> 0.30186639 | AC95: ='MEMORIAL DE CALCULO'!AW154 -> 651.2224 | AD95: =TRUNC(AC95*G95) -> 2923 | AE95: =SUM(J95,M95,P95,V95,Y95,AB95) -> 0.30186639 | AF95: =SUM(K95,N95,Q95,W95,Z95,T95,AC95) -> 651.2224 | AG95: =SUM(L95,O95,R95,X95,AA95,U95,AD95) -> 2923
A96: 8.5 | B96: 88485 | C96: FUNDO SELADOR ACRÍLICO, APLICAÇÃO MANUAL EM PAREDE, UMA DEMÃO. AF 04/2023 | D96: SINAPI | E96: M2 | F96: 2157.32 | G96: 3.93 | H96: =(F96*G96)-0.01 -> 8478.2576 | U96: =TRUNC(G96*T96)+0 -> 0 | W96: =TRUNC(V96*F96,2) -> 0 | X96: =TRUNC(W96*G96)+0 -> 0 | Y96: =Z96/F96 -> 0 | AA96: =TRUNC(Z96*G96)+0 -> 0 | AB96: =AC96/F96 -> 0.30186639 | AC96: ='MEMORIAL DE CALCULO'!AW199 -> 651.2224 | AD96: =TRUNC(AC96*G96) -> 2559 | AE96: =SUM(J96,M96,P96,V96,Y96,AB96) -> 0.30186639 | AF96: =SUM(K96,N96,Q96,W96,Z96,T96,AC96) -> 651.2224 | AG96: =SUM(L96,O96,R96,X96,AA96,U96,AD96) -> 2559
A97: 8.6 | B97: 95306 | C97: TEXTURA ACRÍLICA, APLICAÇÃO MANUAL EM TETO, UMA DEMÃO. AF 04/2023 | D97: SINAPI | E97: M2 | F97: 667.84 | G97: 14.29 | H97: =(F97*G97) -> 9543.4336 | U97: =TRUNC(G97*T97)+0 -> 0 | W97: =TRUNC(V97*F97,2) -> 0 | X97: =TRUNC(W97*G97)+0 -> 0 | Y97: =Z97/F97 -> 0 | AA97: =TRUNC(Z97*G97)+0 -> 0 | AB97: =AC97/F97 -> 0.4564183 | AC97: ='MEMORIAL DE CALCULO'!AW227 -> 304.8144 | AD97: =TRUNC(AC97*G97) -> 4355 | AE97: =SUM(J97,M97,P97,V97,Y97,AB97) -> 0.4564183 | AF97: =SUM(K97,N97,Q97,W97,Z97,T97,AC97) -> 304.8144 | AG97: =SUM(L97,O97,R97,X97,AA97,U97,AD97) -> 4355
A98: 9 | B98: INSTALAÇÕES ELÉTRICAS | H98: =SUM(H99:H108) -> 15377.03
A99: 9.1 | B99: 101492 | C99: ENTRADA DE ENERGIA ELÉTRICA, AEREA, MONOFASICA, COM CAIXA DE SOBREPOR, CABO DE 35 MM2 E DISJUNTOR DIN 50A (NÃO INCLUSO O POSTE DE CONCRETO). AF_07/2020_PS | D99: SINAPI | E99: UNID | F99: 1 | G99: 1667.43 | H99: =(F99*G99) -> 1667.43 | U99: =TRUNC(G99*T99)+0 -> 0 | W99: =TRUNC(V99*F99,2) -> 0 | X99: =TRUNC(W99*G99)+0 -> 0 | Y99: =Z99/F99 -> 0 | AA99: =TRUNC(Z99*G99)+0 -> 0 | AB99: =AC99/F99 -> 1 | AC99: 1 | AD99: =TRUNC(AC99*G99) -> 1667 | AE99: =SUM(J99,M99,P99,V99,Y99,AB99) -> 1 | AF99: =SUM(K99,N99,Q99,W99,Z99,T99,AC99) -> 1 | AG99: =SUM(L99,O99,R99,X99,AA99,U99,AD99) -> 1667 | AH99: =IF(AE99=100%,"ITEM FINALIZADO",AE99) -> ITEM FINALIZADO
A100: 9.2 | B100: 93660 | C100: DISJUNTOR BIPOLAR TIPO DIN, CORRENTE NOMINAL DE 10A - FORNECIMENTO E INSTALAÇÃO. AF 10/2020 | D100: SINAPI | E100: UNID | F100: 10 | G100: 47.17 | H100: =(F100*G100) -> 471.7 | U100: =TRUNC(G100*T100)+0 -> 0 | W100: =TRUNC(V100*F100,2) -> 0 | X100: =TRUNC(W100*G100)+0 -> 0 | Y100: =Z100/F100 -> 0 | AA100: =TRUNC(Z100*G100)+0 -> 0 | AB100: =AC100/F100 -> 1 | AC100: 10 | AD100: =TRUNC(AC100*G100) -> 471 | AE100: =SUM(J100,M100,P100,V100,Y100,AB100) -> 1 | AF100: =SUM(K100,N100,Q100,W100,Z100,T100,AC100) -> 10 | AG100: =SUM(L100,O100,R100,X100,AA100,U100,AD100) -> 471 | AH100: =IF(AE100=100%,"ITEM FINALIZADO",AE100) -> ITEM FINALIZADO
...

Sheet MEMORIAL DE CALCULO
B1: CONTRATAÇÃO DE UMA EMPRESA ESPECIALIZADA PARA CONSTRUÇÃO DE 01 (UM) CENTRO ESPECIALIZADO EM ATENÇÃO A SAÚDE MENTAL PARA ATENDER AS NECESSIDADES DA SECRETARIA MUNICIPAL DE SAÚDE EM COREMAS/PB | E1: BANCO DE DADOS: SINAPI - 05/2024-Paraiba ORSE - 0412024- Sergipe | V1: B.D.I. = 22,47% ENCARGOS SOCIAIS: Nao Desonerado: embutido nos presos unitário dos insumos de mão de obra, de acordo com as bases. | AW1: DATA DE INÍCIO DO CONTRATO: 15/10/2024. VIGÊNCIA: 12 MESES
A2: DADOS DO CONTRATANTE: Prefeitura Municipal de Coremas. CNPJ: 08.939.936/0001-94 POCESSO LICITATÓRIO: Processo Administrativo N°. 176/2024 e Concorrência Eletrônica N°. 0004/2024 CONTRATO N°. 328/2024 VALOR DA OBRA/CONTRATO: 1.150.000,00 (Um milhão, cento e cinquenta mil reais). | E2: NÚMERO DA MEDIÇÃO: 7ª MEDIÇÃO. | V2: REFERÊNCIA/PERÍODO DA MEDIÇÃO: 26/06/2025 a 11/08/2025 | AW2: ='PLANILHA DE MEDIÇÃO'!I2 -> VALOR MEDIDO NO PERÍODO: R$ 330.767,00
A3: DADOS DO CONTRATADO: CL CONSTRUÇÕES E SERVIÇOS LTDA CNPJ: 09.335.002/0001-06 ENDEREÇO: Rua Cel. João Severino, SN - Sala D - Centro - Itaporanga - PB. | E3: FONTE DOS RECURSOS: Próprio (Diversos) do Município, prevista no orçamento da União, para o exercício de 2024. | AX3: TOTAL DA MEDIÇÃO 01 = | AZ3: =#REF! -> #REF! | BA3: TOTAL DA MEDIÇÃO 02 = | BC3: =#REF! -> #REF! | BD3: TOTAL DA MEDIÇÃO 03 = | BF3: =#REF! -> #REF! | BJ3: TOTAL DA MEDIÇÃO 05 = | BL3: =#REF! -> #REF!
A4: MEMORIAL DE CALCULO 07 | AX4: MEDIÇÕES | BA4: MEDIÇÕES | BD4: MEDIÇÕES | BJ4: MEDIÇÕES
A5: ITEM | B5: CÓDIGO | C5: DESCRIÇÃO | D5: CALCULOS | AX5: AVANÇO PERCENTUAL NO PERÍODO | AY5: QUANTIDADE MEDIDA NO PERÍODO | AZ5: VALOR MEDIDO NO PERÍODO | BA5: AVANÇO PERCENTUAL NO PERÍODO | BB5: QUANTIDADE MEDIDA NO PERÍODO | BC5: VALOR MEDIDO NO PERÍODO | BD5: AVANÇO PERCENTUAL NO PERÍODO | BE5: QUANTIDADE MEDIDA NO PERÍODO | BF5: VALOR MEDIDO NO PERÍODO | BG5: AVANÇO PERCENTUAL NO PERÍODO | BH5: QUANTIDADE MEDIDA NO PERÍODO | BI5: VALOR MEDIDO NO PERÍODO | BJ5: AVANÇO PERCENTUAL NO PERÍODO | BK5: QUANTIDADE MEDIDA NO PERÍODO | BL5: VALOR MEDIDO NO PERÍODO
A6: 1 | B6: SERVIÇOS PRELIMINARES | AX6: MEDIÇÃO 01 | BA6: MEDIÇÃO 02 | BD6: MEDIÇÃO 03 | BG6: MEDIÇÃO 04 | BJ6: MEDIÇÃO 05
A7: 1.1 | B7: 51 | C7: Placa de obra em chapa aco galvanizado, instalada - Rev 02_O1/2022 | AX7: 1 | AY7: =TRUNC(AX7*U7,2) -> 0 | AZ7: =TRUNC(AY7*V7)+0.46 -> 0.46 | BA7: 0 | BB7: =TRUNC(BA7*U7,2) -> 0 | BC7: =TRUNC(BB7*V7)+0 -> 0 | BD7: 0 | BE7: =TRUNC(BD7*U7,2) -> 0 | BF7: =TRUNC(BE7*V7) -> 0 | BI7: =TRUNC(V7*BH7)+0 -> 0 | BJ7: 0 | BK7: =TRUNC(BJ7*U7,2) -> 0 | BL7: =TRUNC(BK7*V7)+0 -> 0
A8: 1.2 | B8: 98524 | C8: LIMPEZA MANUAL DE VEGETAÇÃO EM TERRENO COM EXADA AF 03/2024 | AX8: 1 | AY8: =TRUNC(AX8*U8,2) -> 0 | AZ8: =TRUNC(AY8*V8)+0.41 -> 0.41 | BI8: =TRUNC(V8*BH8)+0 -> 0 | BK8: =TRUNC(BJ8*U8,2) -> 0 | BL8: =TRUNC(BK8*V8)+0 -> 0
A9: 2 | B9: MOVIMENTO DE TERRA
A10: 2.1 | B10: 99059 | C10: LOCAÇÃO CONVENCIONAL DE OBRA, UTILIZANDO DE GABARITO DE TÁBUAS CORRIDAS PONTALETADAS A CADA 2,00M - 2 UTILIZAÇÕES. AF_03/2024 | AX10: 1 | AY10: =TRUNC(AX10*U10,2) -> 0 | AZ10: =TRUNC(AY10*V10)+0.12 -> 0.12 | BI10: =TRUNC(V10*BH10)+0 -> 0 | BK10: =TRUNC(BJ10*U10,2) -> 0 | BL10: =TRUNC(BK10*V10)+0 -> 0
A11: 2.2 | B11: 93358 | C11: ESCAVAÇÃO MANUAL DE VALA COM PROFUNDIDADE MENOR OU IGUAL A 1,30M AF 02/2021 | AX11: 1 | AY11: =TRUNC(AX11*U11,2) -> 0 | AZ11: =TRUNC(AY11*V11)+0 -> 0 | BI11: =TRUNC(V11*BH11)+0 -> 0 | BK11: =TRUNC(BJ11*U11,2) -> 0 | BL11: =TRUNC(BK11*V11)+0 -> 0
A12: 2.3 | B12: 94319 | C12: ATERRO MANUAL DE VALAS COM SOLO ARGILO-ARENOSO. AF_08/2023 | AX12: 1 | AY12: =TRUNC(AX12*U12,2) -> 0 | AZ12: =TRUNC(AY12*V12)+0.2 -> 0.2 | BI12: =TRUNC(V12*BH12)+0 -> 0 | BK12: =TRUNC(BJ12*U12,2) -> 0 | BL12: =TRUNC(BK12*V12)+0 -> 0
A13: 3 | B13: ESTRUTURA
A14: 3.1 | B14: INFRAESTUTURA
A15: 3.1.1 | B15: FUNDAÇÃO
A16: 3.1.1.1 | B16: 102486 | C16: CONCRETO FCK = 15MPA, TRACO 13,4.3,4 (EM MASSA SECA DE CIMENTO / AREIA MÉDIA/ SEIXO ROLADO) - PREPARO MANUAL. AF_05/2021 | AX16: 0.8 | AY16: =TRUNC(AX16*U16,2) -> 0 | AZ16: =TRUNC(AY16*V16)+0.1 -> 0.1 | BA16: 0.2 | BB16: =TRUNC(BA16*U16,2)+0.01 -> 0.01 | BC16: =TRUNC(BB16*V16)+1.78 -> 1.78 | BI16: =TRUNC(V16*BH16)+0 -> 0 | BK16: =TRUNC(BJ16*U16,2) -> 0 | BL16: =TRUNC(BK16*V16)+0 -> 0
A17: 3.1.1.2 | B17: 94965 | C17: CONCRETO FCK = 25MPA, TRACO 12,3:2,7 (EM MASSA SECA DE CIMENTO/ AREIA MEDIA/ BRITA 1) - PREPARO MECANICO COM BETONEIRA 400 L. AF 05/2021 | AX17: 0.8 | AY17: =TRUNC(AX17*U17,2) -> 0 | AZ17: =TRUNC(AY17*V17)+0.05 -> 0.05 | BA17: 0.2 | BB17: =TRUNC(BA17*U17,2) -> 0 | BC17: =TRUNC(BB17*V17)+0.52 -> 0.52 | BI17: =TRUNC(V17*BH17)+0 -> 0 | BK17: =TRUNC(BJ17*U17,2) -> 0 | BL17: =TRUNC(BK17*V17)+0 -> 0
A18: 3.1.1.3 | B18: 96544 | C18: ARMAÇÃO DE BLOCO UTILIZANDO AÇO CA-50 DE 6,3 MM - MONTAGEM. AF 01/2024 | AX18: 0.8 | AY18: =TRUNC(AX18*U18,2) -> 0 | AZ18: =TRUNC(AY18*V18)+0.34 -> 0.34 | BA18: 0.2 | BB18: =TRUNC(BA18*U18,2) -> 0 | BC18: =TRUNC(BB18*V18)+0.09 -> 0.09 | BI18: =TRUNC(V18*BH18)+0 -> 0 | BK18: =TRUNC(BJ18*U18,2) -> 0 | BL18: =TRUNC(BK18*V18)+0 -> 0
A19: 3.1.1.4 | B19: 98545 | C19: ARMAÇÃO DE BLOCO UTILZANDO AÇO CASO DE 8 MM - MONTAGEM. AF 01/2024 | AX19: 0.8 | AY19: =TRUNC(AX19*U19,2) -> 0 | AZ19: =TRUNC(AY19*V19)+0.3 -> 0.3 | BA19: 0.2 | BB19: =TRUNC(BA19*U19,2) -> 0 | BC19: =TRUNC(BB19*V19)+0.32 -> 0.32 | BI19: =TRUNC(V19*BH19)+0 -> 0 | BK19: =TRUNC(BJ19*U19,2) -> 0 | BL19: =TRUNC(BK19*V19)+0 -> 0
A20: 3.1.1.5 | B20: 96543 | C20: ARMAÇÃO DE BLOCO UTILIZANDO AÇO CA-60 DE 5 MM - MONTAGEM. AF 01/2024 | AX20: 0.8 | AY20: =TRUNC(AX20*U20,2) -> 0 | AZ20: =TRUNC(AY20*V20)+0.94 -> 0.94 | BA20: 0.2 | BB20: =TRUNC(BA20*U20,2) -> 0 | BC20: =TRUNC(BB20*V20)+0.73 -> 0.73 | BI20: =TRUNC(V20*BH20)+0 -> 0 | BK20: =TRUNC(BJ20*U20,2) -> 0 | BL20: =TRUNC(BK20*V20)+0 -> 0
A21: 3.1.1.6 | B21: 98557 | C21: IMPERMEABILIZAÇÃO DE SUPERFÍCIE COM EMULSÃO ASFÁLTICA, 2 DEMÃOS. AF 09/2023 | AX21: 0.2 | AY21: =TRUNC(AX21*U21,2) -> 0 | AZ21: =TRUNC(AY21*V21)+0.23 -> 0.23 | BA21: 0.8 | BB21: =TRUNC(BA21*U21,2) -> 0 | BC21: =TRUNC(BB21*V21)+0.31 -> 0.31 | BI21: =TRUNC(V21*BH21)+0 -> 0 | BK21: =TRUNC(BJ21*U21,2) -> 0 | BL21: =TRUNC(BK21*V21)+0 -> 0
A22: 3.2 | B22: SUPERESTRUTURA
A23: 3.2.1 | B23: PILARES
A24: 3.2.1.1 | B24: 102476 | C24: CONCRETO FCK = 25MPA, TRACO 1:2,2:2,5 (EM MASSA SECA DE CIMENTO/ AREIA MEDIA/ SEIXO ROLADO) - PREPARO MECANICO COM BETONEIRA 400 L. AF 05/2021 | AX24: 0.5 | AY24: =TRUNC(AX24*U24,2) -> 0 | AZ24: =TRUNC(AY24*V24)+0.73 -> 0.73 | BA24: 0.4 | BB24: =TRUNC(BA24*U24,2) -> 0 | BC24: =TRUNC(BB24*V24)+0.78 -> 0.78 | BD24: 0.1 | BE24: =TRUNC(BD24*U24,2) -> 0 | BF24: =TRUNC(BE24*V24) -> 0 | BI24: =TRUNC(V24*BH24)+0 -> 0 | BK24: =TRUNC(BJ24*U24,2) -> 0 | BL24: =TRUNC(BK24*V24)+0 -> 0
A25: 3.2.1.2 | B25: 96546 | C25: ARMAÇÃO DE BLOCO UTILIZANDO AÇO CA-SO DE 10 MM - MONTAGEM. AF 01/2024 | AX25: 0.5 | AY25: =TRUNC(AX25*U25,2) -> 0 | AZ25: =TRUNC(AY25*V25)+0.34 -> 0.34 | BA25: 0.4 | BB25: =TRUNC(BA25*U25,2) -> 0 | BC25: =TRUNC(BB25*V25)+0.47 -> 0.47 | BD25: 0.1 | BE25: =TRUNC(BD25*U25,2) -> 0 | BF25: =TRUNC(BE25*V25) -> 0 | BI25: =TRUNC(V25*BH25)+0 -> 0 | BK25: =TRUNC(BJ25*U25,2) -> 0 | BL25: =TRUNC(BK25*V25)+0 -> 0
A26: 3.2.1.3 | B26: 98543 | C26: ARMAÇÃO DE BLOCO UTILIZANDO AÇO CA-CO DE 5 MM - MONTAGEM. AF 01/2024 | AX26: 1 | AY26: =TRUNC(AX26*U26,2) -> 0 | AZ26: =TRUNC(AY26*V26)+0.95 -> 0.95 | BE26: =TRUNC(BD26*U26,2) -> 0 | BF26: =TRUNC(BE26*V26) -> 0 | BI26: =TRUNC(V26*BH26)+0 -> 0 | BK26: =TRUNC(BJ26*U26,2) -> 0 | BL26: =TRUNC(BK26*V26)+0 -> 0
A27: 3.2.1.4 | B27: 96545 | C27: ARMAÇÃO DE BLOCO UTILZANDO AÇO CA-50 DES MM - MONTAGEM, AF 01/2024 | AX27: 1 | AY27: =TRUNC(AX27*U27,2) -> 0 | AZ27: =TRUNC(AY27*V27)+0.34 -> 0.34 | BE27: =TRUNC(BD27*U27,2) -> 0 | BF27: =TRUNC(BE27*V27) -> 0 | BI27: =TRUNC(V27*BH27)+0 -> 0 | BK27: =TRUNC(BJ27*U27,2) -> 0 | BL27: =TRUNC(BK27*V27)+0 -> 0
A28: 3.2.1.5 | B28: 96547 | C28: ARMAÇÃO DE BLOCO, VIGA BALDRAME OU SAPATA UTILIZANDO AÇO CA- 50 DE 12,5 MM - MONTAGEM. AF 06/2017 | AX28: 1 | AY28: =TRUNC(AX28*U28,2) -> 0 | AZ28: =TRUNC(AY28*V28)+0.25 -> 0.25 | BE28: =TRUNC(BD28*U28,2) -> 0 | BF28: =TRUNC(BE28*V28) -> 0 | BI28: =TRUNC(V28*BH28)+0 -> 0 | BK28: =TRUNC(BJ28*U28,2) -> 0 | BL28: =TRUNC(BK28*V28)+0 -> 0
A29: 3.2.1.6 | B29: 103795 | C29: FABRICAÇÃO, MONTAGEM E DESMONTAGEM DE FÔRMA PARA ESCADA HIDRAULICA, EM CHAPA DE MADEIRA COMPENSADA RESINADA, E = 17 MM, 3 UTILIZAÇÕES. AF 08/2022 | AX29: 0.5 | AY29: =TRUNC(AX29*U29,2) -> 0 | AZ29: =TRUNC(AY29*V29)+1.32 -> 1.32 | BA29: 0.5 | BB29: =TRUNC(BA29*U29,2) -> 0 | BC29: =TRUNC(BB29*V29)+1.32 -> 1.32 | BD29: 0.1 | BE29: =TRUNC(BD29*U29,2) -> 0 | BF29: =TRUNC(BE29*V29) -> 0 | BH29: -22.76 | BI29: =TRUNC(V29*BH29)+0 -> 0 | BJ29: -0.1 | BK29: =TRUNC(BJ29*U29,2) -> 0
A30: 3.2.2 | B30: VIGAS
A31: 3.2.2.1 | B31: 102476 | C31: CONCRETO FCK = 25MPA, TRAGO 12,2:2,5 (EM MASSA SECA DE CIMENTO/ AREIA MEDIA/ SEIXO ROLADO) - PREPARO MECANICO COM BETONEIRA 400 L. AF 05/2021 | BA31: 0.4 | BB31: =TRUNC(BA31*U31,2) -> 0 | BC31: =TRUNC(BB31*V31)+3.13 -> 3.13 | BD31: 0.6 | BE31: =TRUNC(BD31*U31,2) -> 0 | BF31: =TRUNC(BE31*V31) -> 0 | BI31: =TRUNC(V31*BH31)+0 -> 0 | BK31: =TRUNC(BJ31*U31,2) -> 0 | BL31: =TRUNC(BK31*V31)+0 -> 0
A32: 3.2.2.2 | B32: 92760 | C32: ARMAÇÃO DE PILAR OU VIGA DE ESTRUTURA CONVENCIONAL DE CONCRETO ARMADO UTILIZANDO AÇO CA-50 06 8,3 MM - MONTAGEM. AF 06/2022 | BA32: 0.8 | BB32: =TRUNC(BA32*U32,2) -> 0 | BC32: =TRUNC(BB32*V32)+0.82 -> 0.82 | BD32: 0.2 | BE32: =TRUNC(BD32*U32,2) -> 0 | BF32: =TRUNC(BE32*V32) -> 0 | BI32: =TRUNC(V32*BH32)+0 -> 0 | BK32: =TRUNC(BJ32*U32,2) -> 0 | BL32: =TRUNC(BK32*V32)+0 -> 0
A33: 3.2.2.3 | B33: 92761 | C33: ARMAÇÃO DE PILAR OU VIGA DE ESTRUTURA CONVENCIONAL DE CONCRETO ARMADO UTILIZANDO AÇO CA-50 DE 8,0 MM - MONTAGEM. AF 06/2022 | BA33: 0.8 | BB33: =TRUNC(BA33*U33,2) -> 0 | BC33: =TRUNC(BB33*V33)+0.32 -> 0.32 | BD33: 0.2 | BE33: =TRUNC(BD33*U33,2) -> 0 | BF33: =TRUNC(BE33*V33) -> 0 | BI33: =TRUNC(V33*BH33)+0 -> 0 | BK33: =TRUNC(BJ33*U33,2) -> 0 | BL33: =TRUNC(BK33*V33)+0 -> 0
A34: 3.2.2.4 | B34: 92762 | C34: ARMAÇÃO DE PILAR OU VIGA DE ESTRUTURA CONVENCIONAL DE CONCRETO ARMADO UTILIZANDO AÇO CA-50 DE 10,0 MM - MONTAGEM. AF 06/2022 | BA34: 0.8 | BB34: =TRUNC(BA34*U34,2) -> 0 | BC34: =TRUNC(BB34*V34)+0.23 -> 0.23 | BD34: 0.2 | BE34: =TRUNC(BD34*U34,2) -> 0 | BF34: =TRUNC(BE34*V34) -> 0 | BI34: =TRUNC(V34*BH34)+0 -> 0 | BK34: =TRUNC(BJ34*U34,2) -> 0 | BL34: =TRUNC(BK34*V34)+0 -> 0
A35: 3.2.2.5 | B35: 92763 | C35: ARMAÇÃO DE PILAR OU VIGA DE ESTRUTURA CONVENCIONAL DE CONCRETO ARMADO UTILZANDO AÇO CA-50 DE 12,5 MM - MONTAGEM. AF 06/2022 | BA35: 0.8 | BB35: =TRUNC(BA35*U35,2) -> 0 | BC35: =TRUNC(BB35*V35)+0.11 -> 0.11 | BD35: 0.2 | BE35: =TRUNC(BD35*U35,2) -> 0 | BF35: =TRUNC(BE35*V35) -> 0 | BI35: =TRUNC(V35*BH35)+0 -> 0 | BK35: =TRUNC(BJ35*U35,2) -> 0 | BL35: =TRUNC(BK35*V35)+0 -> 0
A36: 3.2.2.6 | B36: 92759 | C36: ARMAÇÃO DE PILAR OU VIGA DE ESTRUTURA CONVENCIONAL DE CONCRETO ARMADO UTILIZANDO AÇO CA-CO DE 5,0 MM - MONTAGEM. AF 06/2022 | BA36: 0.8 | BB36: =TRUNC(BA36*U36,2) -> 0 | BC36: =TRUNC(BB36*V36)+0.85 -> 0.85 | BD36: 0.2 | BE36: =TRUNC(BD36*U36,2) -> 0 | BF36: =TRUNC(BE36*V36) -> 0 | BI36: =TRUNC(V36*BH36)+0 -> 0 | BK36: =TRUNC(BJ36*U36,2) -> 0 | BL36: =TRUNC(BK36*V36)+0 -> 0
A37: 3.2.2.7 | B37: 92265 | C37: FABRICAÇÃO DE FORMA PARA VIGAS, EM CHAPA DE MADEIRA COMPENSADA RESINADA, E = 17 MM. AF 09/2020 | BA37: 1 | BB37: =TRUNC(BA37*U37,2) -> 0 | BC37: =TRUNC(BB37*V37)+0.11 -> 0.11 | BI37: =TRUNC(V37*BH37)+0 -> 0 | BK37: =TRUNC(BJ37*U37,2) -> 0 | BL37: =TRUNC(BK37*V37)+0 -> 0
A38: 3.2.3 | B38: LAJE
A39: 3.2.3.1 | B39: 94965 | C39: CONCRETO FCK = 25MPA, TRACO 1:2,3:2,7 (EM MASSA SECA DE CIMENTO/AREIA MEDIA/ BRITA 1) - PREPARO MECANICO COM BETONEIRA 400 L. AF 05/2021 | BI39: =TRUNC(V39*BH39)+0 -> 0 | BJ39: 0 | BK39: =TRUNC(BJ39*U39,2) -> 0 | BL39: =TRUNC(BK39*V39)+0 -> 0
A40: 3.2.3.2 | B40: 92267 | C40: FABRICAÇÃO DE FÔRMA PARA LAJES, EM CHAPA DE MADEIRA COMPENSADA RESINADA, E = 17 MM. AF 09/2020 | BI40: =TRUNC(V40*BH40)+0 -> 0 | BJ40: 0 | BK40: =TRUNC(BJ40*U40,2) -> 0 | BL40: =TRUNC(BK40*V40)+0 -> 0
A41: 3.2.3.3 | B41: 92769 | C41: ARMAÇÃO DE LAJE DE ESTRUTURA CONVENCIONAL DE CONCRETO ARMADO UTILIZANDO AÇO CA-SO DE 6,3 MM - MONTAGEM. AF_06/2022 | BI41: =TRUNC(V41*BH41)+0 -> 0 | BJ41: 0 | BK41: =TRUNC(BJ41*U41,2) -> 0 | BL41: =TRUNC(BK41*V41)+0 -> 0
A42: 3.2.3.4 | B42: 92770 | C42: ARMAÇÃO DE LAJE DE ESTRUTURA CONVENCIONAL DE CONCRETO ARMADO UTILIZANDO AÇO CA-SO DE 8,0 MM - MONTAGEM. AF_06/2022 | BI42: =TRUNC(V42*BH42)+0 -> 0 | BJ42: 0 | BK42: =TRUNC(BJ42*U42,2) -> 0 | BL42: =TRUNC(BK42*V42)+0 -> 0
A43: 3.2.3.5 | B43: 92771 | C43: ARMAÇAO DE LAJE DE ESTRUTURA CONVENCIONAL DE CONCRETO ARMADO UTILIZANDO AÇO CA-50 DE 10,0 MM - MONTAGEM. AF_08/2022 | BI43: =TRUNC(V43*BH43)+0 -> 0 | BJ43: 0 | BK43: =TRUNC(BJ43*U43,2) -> 0 | BL43: =TRUNC(BK43*V43)+0 -> 0
A44: 3.2.3.6 | B44: 92768 | C44: ARMAÇÃO DE LAJE DE ESTRUTURA CONVENCIONAL DE CONCRETO ARMADO UTILIZANDO AÇO CA-CO DE 5,0 MM - MONTAGEM. AF_06/2022 | BI44: =TRUNC(V44*BH44)+0 -> 0 | BJ44: 0 | BK44: =TRUNC(BJ44*U44,2) -> 0 | BL44: =TRUNC(BK44*V44)+0 -> 0
A45: 4 | B45: ELEVAÇÃO
A46: 4.1 | B46: 103328 | C46: ALVENARIA DE VEDAÇÃO DE BLOCOS CERAMICOS FURADOS NA HORIZONTAL DE 9X19X19 CM (ESPESSURA 9 CM) E ARGAMASSA DE ASSENTAMENTO COM PREPARO EM BETONEIRA. AF_12/2021 | AX46: 0.3 | AY46: =TRUNC(AX46*U46,2) -> 0 | AZ46: =TRUNC(AY46*V46)+1.33 -> 1.33 | BA46: 0.6 | BB46: =TRUNC(BA46*U46,2) -> 0 | BC46: =TRUNC(BB46*V46)+1.66 -> 1.66 | BH46: 60.94 | BI46: =TRUNC(V46*BH46)+0 -> 0 | BJ46: 0.1 | BK46: =TRUNC(BJ46*U46,2) -> 0 | BL46: 0
A47: 5 | B47: REVESTIMENTO
A48: 5.1 | B48: 87894 | C48: CHAPISCO APLICADO EM ALVENARIA (SEM PRESENÇA DE VÃOS) E ESTRUTURAS DE CONCRETO DE FACHADA, COM COLHER DE PEDREIRO. ARGAMASSA TRAÇO 1.3 COM PREPARO EM BETONEIRA 400L. AF_10/2022 | BD48: 0.5 | BE48: =TRUNC(BD48*U48,2) -> 0 | BF48: =TRUNC(BE48*V48) -> 0 | BH48: 1078.66 | BI48: =TRUNC(V48*BH48)+0 -> 0 | BJ48: 0.5 | BK48: =TRUNC(BJ48*U48,2) -> 0 | BL48: 0
A49: 5.2 | B49: 87548 | C49: MASSA ÚNICA, EM ARGAMASSA TRAÇO 1:2:8, PREPARO MANUAL, APLICADA MANUALMENTE EM PAREDES INTERNAS DE AMBIENTES COM ÁREA ENTRE 5M² E 10M², E = 10MM, COM TALISCAS, AF_03/2024 | BD49: 0.5 | BE49: =TRUNC(BD49*U49,2) -> 0 | BF49: =TRUNC(BE49*V49) -> 0 | BH49: 1078.66 | BI49: =TRUNC(V49*BH49)+0 -> 0 | BJ49: 0.5 | BK49: =TRUNC(BJ49*U49,2) -> 0 | BL49: 0
A50: 5.3 | B50: 104817 | C50: REVESTIMENTO CERÂMICO PARA PAREDES INTERNAS COM PLACAS TIPO PASTILHA DE DIMENSÕES 5 X 5 CM (PLACAS DE 30 X 30 CM) CM APLICADAS A MEIA ALTURA DAS PAREDES. AF_02/2023 | BE50: =TRUNC(BD50*U50,2) -> 0 | BF50: =TRUNC(BE50*V50) -> 0 | BH50: 72.01 | BI50: =TRUNC(V50*BH50)+0 -> 0 | BJ50: 1 | BK50: =TRUNC(BJ50*U50,2) -> 0 | BL50: 36700.13
A51: 5.4 | B51: 87262 | C51: REVESTIMENTO CERÂMICO PARA PISO COM PLACAS TIPO PORCELANATO DE DIMENSÕES 60X60 CM APLICADA EM AMBIENTES DE ÁREA ENTRE 5 M² E 10 M². AF 02/2023 PE | BI51: =TRUNC(V51*BH51)+0 -> 0 | BJ51: 0 | BK51: =TRUNC(BJ51*U51,2) -> 0 | BL51: =TRUNC(BK51*V51)+0 -> 0
A52: 6 | B52: PISO
A53: 6.1 | B53: 87298 | C53: ARGAMASSA TRAÇO 1:3 (EM VOLUME DE CIMENTO E AREIA MÉDIA ÚMIDA) PARA CONTRAPISO, PREPARO MECANICO COM BETONEIRA 400 L. AF 08/2019 | BG53: 0 | BH53: 8.48 | BI53: =TRUNC(V53*BH53)+0 -> 0 | BJ53: 1 | BK53: =TRUNC(BJ53*U53,2) -> 0 | BL53: 4913.89
A54: 6.2 | B54: 104597 | C54: REVESTIMENTO CERÂMICO PARA PISO COM PLACAS TIPO PORCELANATO DE DIMENSOES 80X80 CM APLICADA EM AMBIENTES DE AREA ENTRE 556 E 10 M'. AF 022023 PE | BI54: =TRUNC(V54*BH54)+0 -> 0 | BK54: =TRUNC(BJ54*U54,2) -> 0 | BL54: =TRUNC(BK54*V54)+0 -> 0
A55: 7 | B55: INSTALAÇÕES SANITÁRIAS
A56: 7.1 | B56: SANITÁRIA
A57: 7.1.1 | B57: 86931 | C57: VASO SANITARIO SIFONADO COM CAIXA ACOPLADA LOUÇA BRANCA, INCLUSO ENGATE FLEXÍVEL EM PLASTICO BRANCO, 1/2 X 40CM - FORNECIMENTO E INSTALAÇÃO. AF_01/2020 | BI57: =TRUNC(V57*BH57)+0 -> 0 | BK57: =TRUNC(BJ57*U57,2) -> 0 | BL57: =TRUNC(BK57*V57)+0 -> 0
A58: 7.1.2 | B58: 86939 | C58: LAVATÓRIO LOUÇA BRANCA COM COLUNA, *44 X 35,5* CM, PADRÃO POPULAR, INCLUSO SIFAO FLEXÍVEL EM PVC, VALVULA E ENGATE FLEXÍVEL 30CM EM PLASTICO E COM TORNEIRA CROMADA PADRAO POPULAR-FORNECIMENTO E INSTALAÇÃO. AF_01/2020 | BI58: =TRUNC(V58*BH58)+0 -> 0 | BK58: =TRUNC(BJ58*U58,2) -> 0 | BL58: =TRUNC(BK58*V58)+0 -> 0
A59: 7.1.3 | B59: 89714 | C59: TUBO PVC, SERIE NORMAL, ESGOTO PREDIAL, DN 100 MM, FORNECIDO E INSTALADO EM RAMAL DE DESCARGA OU RAMAL DE ESGOTO SANITARIO. AF 08/2022 | BD59: 0.8 | BE59: =TRUNC(BD59*U59,2) -> 0 | BF59: =TRUNC(BE59*V59) -> 0 | BH59: 20 | BI59: =TRUNC(V59*BH59)+0 -> 0 | BJ59: 0.2 | BK59: =TRUNC(BJ59*U59,2) -> 0 | BL59: 0
A60: 7.1.4 | B60: 89711 | C60: TUBO PVC, SERIE NORMAL, ESGOTO PREDIAL, DN 40 MM, FORNECIDO E INSTALADO EM RAMAL DE DESCARGA OU RAMAL DE ESGOTO SANITARIO. AF 08/2022 | BD60: 0.8 | BE60: =TRUNC(BD60*U60,2) -> 0 | BF60: =TRUNC(BE60*V60) -> 0 | BH60: 4 | BI60: =TRUNC(V60*BH60)+0 -> 0 | BJ60: 0.2 | BK60: =TRUNC(BJ60*U60,2) -> 0 | BL60: 0
A61: 7.1.5 | B61: 89798 | C61: TUBO PVC, SERIE NORMAL, ESGOTO PREDIAL, DN 50 MM, FORNECIDO E INSTALADO EM PRUMADA DE ESGOTO SANITARIO OU VENTILAÇÃO. AF 08/2022 | BD61: 0.8 | BE61: =TRUNC(BD61*U61,2) -> 0 | BF61: =TRUNC(BE61*V61) -> 0 | BI61: =TRUNC(V61*BH61)+0 -> 0 | BK61: =TRUNC(BJ61*U61,2) -> 0 | BL61: =TRUNC(BK61*V61)+0 -> 0
A62: 7.1.6 | B62: 104326 | C62: RALO SECO CONICO, PVC, DN 100 X 40 MM, JUNTA SOLDAVEL, FORNECIDO E INSTALADO EM RAMAL DE DESCARGA OU EM RAMAL DE ESGOTO SANITARIO. AF 08/2022 | BI62: =TRUNC(V62*BH62)+0 -> 0 | BK62: =TRUNC(BJ62*U62,2) -> 0 | BL62: =TRUNC(BK62*V62)+0 -> 0
A63: 7.1.7 | B63: 104327 | C63: RALO SIFONADO REDONDO, PVC, DN 100 X 40 MM, JUNTA SOLDAVEL, FORNECIDO E INSTALADO EM RAMAL DE DESCARGA OU EM RAMAL DE ESGOTO SANITARIO. AF 08/2022 | BI63: =TRUNC(V63*BH63)+0 -> 0 | BK63: =TRUNC(BJ63*U63,2) -> 0 | BL63: =TRUNC(BK63*V63)+0 -> 0
A64: 7.1.8 | B64: 89726 | C64: JOELHO 45 GRAUS, PVC, SERIE NORMAL, ESGOTO PREDIAL, DN 40 MM, JUNTA SOLDAVEL, FORNECIDO E INSTALADO EM RAMAL DE DESCARGA OU RAMAL DE ESGOTO SANITARIO. AF 08/2022 | BD64: 0.8 | BE64: =TRUNC(BD64*U64,2) -> 0 | BF64: =TRUNC(BE64*V64) -> 0 | BH64: 1.4 | BI64: =TRUNC(V64*BH64)+0 -> 0 | BJ64: 0.2 | BK64: =TRUNC(BJ64*U64,2) -> 0 | BL64: 0
A65: 7.1.9 | B65: 89732 | C65: JOELHO 45 GRAUS, PVC, SERIE NORMAL, ESGOTO PREDIAL, DN 50 MM, JUNTA ELASTICA, FORNECIDO E INSTALADO EM RAMAL DE DESCARGA OU RAMAL DE ESGOTO SANITARIO. AF 08/2022 | BD65: 0.8 | BE65: =TRUNC(BD65*U65,2) -> 0 | BF65: =TRUNC(BE65*V65) -> 0 | BH65: 1.4 | BI65: =TRUNC(V65*BH65)+0 -> 0 | BJ65: 0.2 | BK65: =TRUNC(BJ65*U65,2) -> 0 | BL65: 0
A66: 7.1.10 | B66: 89809 | C66: JOELHO 90 GRAUS, PVC, SERIE NORMAL, ESGOTO PREDIAL, DN 100 MM, JUNTA ELASTICA, FORNECIDO E INSTALADO EM PRUMADA DE ESGOTO SANITARIO OU VENTILACAO. AF_08/2022 | BD66: 0.8 | BE66: =TRUNC(BD66*U66,2) -> 0 | BF66: =TRUNC(BE66*V66) -> 0 | BH66: 2 | BI66: =TRUNC(V66*BH66)+0 -> 0 | BJ66: 0.2 | BK66: =TRUNC(BJ66*U66,2) -> 0 | BL66: 0
A67: 7.1.11 | B67: 69810 | C67: JOELHO 45 GRAUS, PVC, SERIE NORMAL, ESGOTO PREDIAL, DN 100 MM, JUNTA ELASTICA, FORNECIDO E INSTALADO EM PRUMADA DE ESGOTO SANITARIO OU VENTILACAO. AF_08/2022 | BD67: 0.8 | BE67: =TRUNC(BD67*U67,2) -> 0 | BF67: =TRUNC(BE67*V67) -> 0 | BH67: 1.2 | BI67: =TRUNC(V67*BH67)+0 -> 0 | BJ67: 0.2 | BK67: =TRUNC(BJ67*U67,2) -> 0 | BL67: 0
A68: 7.1.12 | B68: 100864 | C68: BARRA DE APOIO EM "L", EM ACO INOX POLIDO 80 X 80 CM, FIXADA NA PAREDE - FORNECIMENTO E INSTALAÇÃO. AF 01/2020 | BI68: =TRUNC(V68*BH68)+0 -> 0 | BK68: =TRUNC(BJ68*U68,2) -> 0 | BL68: =TRUNC(BK68*V68)+0 -> 0
A69: 7.1.13 | B69: 89833 | C69: TE, PVC, SERIE NORMAL, ESGOTO PREDIAL, DN 100 X 100 MM, JUNTA ELASTICA, FORNECIDO E INSTALADO EM PRUMADA DE ESGOTO SANITARIO OU VENTILAÇÃO. AF_08/2022 | BD69: 0.8 | BE69: =TRUNC(BD69*U69,2) -> 0 | BF69: =TRUNC(BE69*V69) -> 0 | BH69: 0.6 | BI69: =TRUNC(V69*BH69)+0 -> 0 | BJ69: 0.2 | BK69: =TRUNC(BJ69*U69,2) -> 0 | BL69: 0
A70: 7.1.14 | B70: 102711 | C70: JUNÇÃO DUPLA DE PVC, SERIE NORMAL, PARA ESGOTO PREDIAL, DN 100 X 100 X 100 MM, INSTALADA EM DRENO - FORNECIMENTO E INSTALAÇÃO. AF 07/2021 | BD70: 0.8 | BE70: =TRUNC(BD70*U70,2) -> 0 | BF70: =TRUNC(BE70*V70) -> 0 | BH70: 0.8 | BI70: =TRUNC(V70*BH70)+0 -> 0 | BJ70: 0.2 | BK70: =TRUNC(BJ70*U70,2) -> 0 | BL70: 0
A71: 7.2 | B71: HIDRÁULICA
A72: 7.2.1 | B72: 102616 | C72: CAIXA D'AGUA EM POLIESTER REFORCADO COM FIBRA DE VIDRO, 3000 LITROS - FORNECIMENTO E INSTALAÇÃO. AF_06/2021 | D72: CONFORME O PROJETO HIDRAÚLICO | BI72: =TRUNC(V72*BH72)+0 -> 0 | BK72: =TRUNC(BJ72*U72,2) -> 0 | BL72: =TRUNC(BK72*V72)+0 -> 0
A73: 7.2.2 | B73: 89446 | C73: TUBO, PVC, SOLDAVEL, DN 25MM, INSTALADO EM PRUMADA DE ÁGUA - FORNECIMENTO E INSTALAÇÃO. AF 06/2022 | D73: CONFORME O PROJETO HIDRAÚLICO | BI73: =TRUNC(V73*BH73)+0 -> 0 | BK73: =TRUNC(BJ73*U73,2) -> 0 | BL73: =TRUNC(BK73*V73)+0 -> 0
A74: 7.2.3 | B74: 89366 | C74: JOELHO 90 GRAUS COM BUCHA DE LATAO, PVC, SOLDAVEL, DN 25MM, X 3/4 INSTALADO EM RAMAL OU SUB-RAMAL DE ÁGUA - FORNECIMENTO E INSTALAÇÃO. AF 06/2022 | D74: CONFORME O PROJETO HIDRAÚLICO | BI74: =TRUNC(V74*BH74)+0 -> 0 | BK74: =TRUNC(BJ74*U74,2) -> 0 | BL74: =TRUNC(BK74*V74)+0 -> 0
A75: 7.2.4 | B75: 89355 | C75: TUBO, PVC, SOLDAVEL, DN 20MM, INSTALADO EM RAMAL OU SUB-RAMAL DE ÁGUA - FORNECIMENTO E INSTALAÇÃO. AF_06/2022 | D75: CONFORME O PROJETO HIDRAÚLICO | BI75: =TRUNC(V75*BH75)+0 -> 0 | BK75: =TRUNC(BJ75*U75,2) -> 0 | BL75: =TRUNC(BK75*V75)+0 -> 0
A76: 7.2.5 | B76: 100860 | C76: CHUVEIRO ELÉTRICO COMUM CORPO PLASTICO, TIPO DUCHA - FORNECIMENTO E INSTALAÇÃO. AF 01/2020 | D76: CONFORME O PROJETO HIDRAÚLICO | BI76: =TRUNC(V76*BH76)+0 -> 0 | BK76: =TRUNC(BJ76*U76,2) -> 0 | BL76: =TRUNC(BK76*V76)+0 -> 0
A77: 7.2.6 | B77: 89528 | C77: LUVA, PVC, SOLDAVEL, DN 25MM, INSTALADO EM PRUMADA DE ÁGUA - FORNECIMENTO E INSTALAÇÃO. AF 06/2022 | D77: CONFORME O PROJETO HIDRAÚLICO | BI77: =TRUNC(V77*BH77)+0 -> 0 | BK77: =TRUNC(BJ77*U77,2) -> 0 | BL77: =TRUNC(BK77*V77)+0 -> 0
A78: 7.2.7 | B78: 104199 | C78: JOELHO 90 GRAUS, PPR, DN 20 MM, INSTALADO EM RAMAL OU SUB - RAMAL DE ÁGUA - FORNECIMENTO E INSTALAÇÃO. AF_082022 | D78: CONFORME O PROJETO HIDRAÚLICO | BI78: =TRUNC(V78*BH78)+0 -> 0 | BK78: =TRUNC(BJ78*U78,2) -> 0 | BL78: =TRUNC(BK78*V78)+0 -> 0
A79: 7.2.8 | B79: 101964 | C79: LAJE PRE-MOLDADA UNIDIRECIONAL, BIAPOIADA, PARA FORRO, ENCHIMENTO EM CERÂMICA, VIGOTA CONVENCIONAL, ALTURA TOTAL DA LAJE (ENCHIMENTO+CAPA) = (8+3). AF_11/2020_PA | D79: CONFORME O PROJETO HIDRAÚLICO | BI79: =TRUNC(V79*BH79)+0 -> 0 | BK79: =TRUNC(BJ79*U79,2) -> 0 | BL79: =TRUNC(BK79*V79)+0 -> 0
A80: 7.2.9 | B80: 95545 | C80: SABONETEIRA DE PAREDE EM METAL CROMADO, INCLUSO FIXAÇÃO. AF 01/2020 | BI80: =TRUNC(V80*BH80)+0 -> 0 | BK80: =TRUNC(BJ80*U80,2) -> 0 | BL80: =TRUNC(BK80*V80)+0 -> 0
A81: 7.2.10 | B81: 95547 | C81: SABONETEIRA PLÁSTICA TIPO DISPENSER PARA SABONETE LIQUIDO COM RESERVATÓRIO 600 A 1500 ML, INCLUSO FIXAÇÃO. AF_01/2020 | BI81: =TRUNC(V81*BH81)+0 -> 0 | BK81: =TRUNC(BJ81*U81,2) -> 0 | BL81: =TRUNC(BK81*V81)+0 -> 0
A82: 7.2.11 | B82: 95547 | C82: SABONETEIRA PLÁSTICA TIPO DISPENSER PARA SABONETE LIQUIDO COM RESERVATÓRIO 800 A 1500 ML, INCLUSO FIXAÇÃO. AF_01/2020 | BI82: =TRUNC(V82*BH82)+0 -> 0 | BK82: =TRUNC(BJ82*U82,2) -> 0 | BL82: =TRUNC(BK82*V82)+0 -> 0
A83: 7.2.12 | B83: 90373 | C83: JOELHO 90 GRAUS COM BUCHA DE LATÃO, PVC, SOLDÁVEL, DN 25MM, X 1/2 INSTALADO EM RAMAL OU SUB-RAMAL DE ÁGUA - FORNECIMENTO E INSTALAÇÃO. AF 06/2022 | D83: CONFORME O PROJETO HIDRAÚLICO | BI83: =TRUNC(V83*BH83)+0 -> 0 | BK83: =TRUNC(BJ83*U83,2) -> 0 | BL83: =TRUNC(BK83*V83)+0 -> 0
A84: 7.2.13 | B84: 89985 | C84: REGISTRO DE PRESSÃO BRUTO, LATÃO, ROSCÁVEL, 3/4", COM ACABAMENTO E CANOPLA CROMADOS - FORNECIMENTO E INSTALAÇÃO, AF 08/2021 | D84: CONFORME O PROJETO HIDRAÚLICO | BI84: =TRUNC(V84*BH84)+0 -> 0 | BK84: =TRUNC(BJ84*U84,2) -> 0 | BL84: =TRUNC(BK84*V84)+0 -> 0
A85: 7.2.14 | B85: 86915 | C85: TORNEIRA CROMADA DE MESA, 1/2" OU 3/4", PARA LAVATÓRIO, PADRÃO MÉDIO - FORNECIMENTO E INSTALAÇÃO. AF_01/2020 | BI85: =TRUNC(V85*BH85)+0 -> 0 | BK85: =TRUNC(BJ85*U85,2) -> 0 | BL85: =TRUNC(BK85*V85)+0 -> 0
A86: 7.2.15 | B86: 86911 | C86: TORNEIRA CROMADA LONGA, DE PAREDE, 1/2" OU 3/4", PARA PIA DE COZINHA. PADRÃO POPULAR - FORNECIMENTO E INSTALAÇÃO. AF 01/2020 | BI86: =TRUNC(V86*BH86)+0 -> 0 | BK86: =TRUNC(BJ86*U86,2) -> 0 | BL86: =TRUNC(BK86*V86)+0 -> 0
A87: 7.2.16 | B87: 94497 | C87: REGISTRO DE GAVETA BRUTO, LATÃO, ROSCÁVEL, 1 1/2" - FORNECIMENTO E INSTALAÇÃO. AF 08/2021 | D87: CONFORME O PROJETO HIDRAÚLICO | BI87: =TRUNC(V87*BH87)+0 -> 0 | BK87: =TRUNC(BJ87*U87,2) -> 0 | BL87: =TRUNC(BK87*V87)+0 -> 0
A88: 7.2.17 | B88: 103039 | C88: REGISTRO DE ESFERA, PVC, ROSCÁVEL, COM VOLANTE, 1 1/2" - FORNECIMENTO E INSTALAÇÃO. AF 08/2021 | D88: CONFORME O PROJETO HIDRAÚLICO | BI88: =TRUNC(V88*BH88)+0 -> 0 | BK88: =TRUNC(BJ88*U88,2) -> 0 | BL88: =TRUNC(BK88*V88)+0 -> 0
A89: 7.2.18 | B89: 94782 | C89: (COMPOSIÇÃO REPRESENTATIVA) DO SERVIÇO DE CONTRAPISO EM ARGAMASSA TRAÇO 1:4 (CIM E AREIA), BETONEIRA 400 L, E = 4 CM ÁREAS SECAS E MOLHADAS SOBRE LAJE , E = 3 CM ÁREAS MOLHADAS SOBRE IMPERMEABILIZAÇÃO, PARA EDIFICAÇÃO MULTIFAMILIAR. AF_11/2014 | BI89: =TRUNC(V89*BH89)+0 -> 0 | BK89: =TRUNC(BJ89*U89,2) -> 0 | BL89: =TRUNC(BK89*V89)+0 -> 0
A90: 7.2.19 | B90: 98557 | C90: IMPERMEABILIZAÇÃO DE SUPERFICIE COM EMULSAO ASFALTICA, 2 DEMAOS. AF 09/2023 | BD90: 1 | BE90: =TRUNC(BD90*U90,2) -> 0 | BF90: =TRUNC(BE90*V90) -> 0 | BI90: =TRUNC(V90*BH90)+0 -> 0 | BK90: =TRUNC(BJ90*U90,2) -> 0 | BL90: =TRUNC(BK90*V90)+0 -> 0
A91: 8 | B91: PINTURA
A92: 8.1 | B92: 98135 | C92: APLICAÇÃO MANUAL DE MASSA ACRÍLICA EM PAREDES EXTERNAS DE CASAS, DUAS DEMÃOS. AF 03/2024 | BI92: =TRUNC(V92*BH92)+0 -> 0 | BK92: =TRUNC(BJ92*U92,2) -> 0 | BL92: =TRUNC(BK92*V92)+0 -> 0
C93: Fachada frontal | D93: 5.75 | E93: x | F93: 5.3 | G93: + | H93: 13.65 | I93: x | J93: 4.45 | K93: + | L93: 2.1 | M93: x | N93: 7.68 | O93: + | P93: 2.2 | Q93: x | R93: 0.3 | S93: + | T93: 0.3 | U93: x | V93: 1 | W93: + | X93: 1.45 | Y93: x | Z93: 4.45 | AA93: + | AB93: 1.45 | AC93: x | AD93: 4.45 | AE93: + | AF93: 1.45 | AG93: x | AH93: 4.45 | AI93: + | AJ93: 1.45 | AK93: x | AL93: 4.45 | AM93: + | AN93: 1.1 | AO93: x | AP93: 4.45 | AQ93: + | AR93: 1 | AS93: x | AT93: 4.45 | AV93: = | AW93: =D93*F93+H93*J93+L93*N93+P93*R93+T93*V93+X93*Z93+AB93*AD93+AF93*AH93+AJ93*AL93+AN93*AP93+AR93*AT93 -> 143.4605
C94: Fachada Lateral Esquerda | D94: 4.65 | E94: x | F94: 5.4 | G94: + | H94: 2.1 | I94: x | J94: 2.55 | K94: + | L94: 5.45 | M94: x | N94: 0.15 | O94: + | P94: 5.7 | Q94: x | R94: 0.15 | S94: + | T94: 5.45 | U94: x | V94: 0.6 | W94: + | X94: 5.7 | Y94: x | Z94: 0.6 | AA94: + | AB94: 5.45 | AC94: x | AD94: 0.6 | AE94: + | AF94: 5.7 | AG94: x | AH94: 0.6 | AV94: = | AW94: =D94*F94+H94*J94+L94*N94+P94*R94+T94*V94+X94*Z94+AB94*AD94+AF94*AH94+AJ94*AL94+AN94*AP94+AR94*AT94 -> 45.5175
C95: Fachada Lateral direita | D95: 8.04 | E95: x | F95: 2.1 | AV95: = | AW95: =D95*F95+H95*J95+L95*N95+P95*R95+T95*V95+X95*Z95+AB95*AD95+AF95*AH95+AJ95*AL95+AN95*AP95+AR95*AT95 -> 16.884
C96: Fachada Lateral fundo | D96: 8.05 | E96: x | F96: 5.3 | G96: + | H96: 3.2 | I96: x | J96: 5.3 | K96: + | L96: 2.2 | M96: x | N96: 3.3 | O96: + | P96: 4.65 | Q96: x | R96: 4.45 | S96: + | T96: 6.35 | U96: x | V96: 4.45 | W96: + | X96: 1.45 | Y96: x | Z96: 4.45 | AA96: + | AB96: 1.45 | AC96: x | AD96: 4.45 | AE96: + | AF96: 5.25 | AG96: x | AH96: 4.45 | AI96: + | AJ96: 1.45 | AK96: x | AL96: 4.45 | AM96: + | AN96: 1.1 | AO96: x | AP96: 4.45 | AQ96: + | AR96: =1.1+0.98 -> 2.08 | AS96: x | AT96: 4.45 | AV96: = | AW96: =D96*F96+H96*J96+L96*N96+P96*R96+T96*V96+X96*Z96+AB96*AD96+AF96*AH96+AJ96*AL96+AN96*AP96+AR96*AT96 -> 172.706
D97: TOTAL | AV97: = | AW97: =SUM(AW93:AW96) -> 378.568
D98: DESCONTO DAS ESQUADRIAS
C99: P1 | D99: 2.2 | E99: x | F99: 2.5 | AT99: x | AU99: 1 | AV99: = | AW99: =(D99*F99)*AU99 -> 5.5
C100: P3 | D100: 2 | E100: x | F100: 2.1 | AT100: x | AU100: 1 | AV100: = | AW100: =(D100*F100)*AU100 -> 4.2
...
