Workbook
Name JR_PAGE_ANCHOR_0_1: 'MEMORIAL DE CALCULO'!#REF!
Name JR_PAGE_ANCHOR_0_1: 'PLANILHA DE MEDIÇÃO'!#REF!

Sheet PLANILHA DE MEDIÇÃO
B1: CONTRATAÇÃO DE UMA EMPRESA ESPECIALIZADA PARA CONSTRUÇÃO DE 01 (UM) CENTRO ESPECIALIZADO EM ATENÇÃO A SAÚDE MENTAL PARA ATENDER AS NECESSIDADES DA SECRETARIA MUNICIPAL DE SAÚDE EM COREMAS/PB | E1: BANCO DE DADOS: SINAPI - 05/2024-Paraiba ORSE - 0412024- Sergipe | G1: B.D.I. = 22,47% ENCARGOS SOCIAIS: Nao Desonerado: embutido nos presos unitário dos insumos de mão de obra, de acordo com as bases. | I1: DATA DE INÍCIO DO CONTRATO: 15/10/2024. VIGÊNCIA: 12 MESES
A2: DADOS DO CONTRATANTE: Prefeitura Municipal de Coremas. CNPJ: 08.939.936/0001-94 POCESSO LICITATÓRIO: Processo Administrativo N°. 176/2024 e Concorrência Eletrônica N°. 0004/2024 CONTRATO N°. 328/2024 VALOR DA OBRA/CONTRATO: 1.150.000,00 (Um milhão, cento e cinquenta mil reais). | E2: NÚMERO DA MEDIÇÃO: 8ª MEDIÇÃO. | G2: REFERÊNCIA/PERÍODO DA MEDIÇÃO: De 11/08/2025 A 11/09/2025 | I2: VALOR MEDIDO NO PERÍODO: R$ 330.767,00
A3: DADOS DO CONTRATADO: CL CONSTRUÇÕES E SERVIÇOS LTDA CNPJ: 09.335.002/0001-06 ENDEREÇO: Rua Cel. João Severino, SN - Sala D - Centro - Itaporanga - PB. | E3: FONTE DOS RECURSOS: Próprio (Diversos) do Município, prevista no orçamento da União, para o exercício de 2024. | J3: TOTAL DA MEDIÇÃO 01 = | L3: =L127 -> 143165.41 | M3: TOTAL DA MEDIÇÃO 02 = | O3: =O127 -> 90821.55 | P3: TOTAL DA MEDIÇÃO 03 = | R3: =R127 -> 66728 | V3: TOTAL DA MEDIÇÃO 05 = | X3: =X127 -> 41614.02 | Y3: TOTAL DA MEDIÇÃO 06 = | AA3: =AA127 -> 330767 | AB3: TOTAL DA MEDIÇÃO 07 = | AD3: =AD127 -> 167779 | AE3: TOTAL DA MEDIÇÃO 08= | AG3: =AG127 -> 80725
J4: MEDIÇÕES | M4: MEDIÇÕES | P4: MEDIÇÕES | V4: MEDIÇÕES | Y4: MEDIÇÕES | AB4: MEDIÇÕES | AH4: AVANÇO
A5: ITEM | B5: CÓDIGO | C5: DESCRIÇÃO | D5: FONTE | E5: UND | F5: QUANTIDADE | G5: PREÇO UNITÁRIO R$ | H5: PREÇO TOTAL R$ | J5: AVANÇO PERCENTUAL NO PERÍODO | K5: QUANTIDADE MEDIDA NO PERÍODO | L5: VALOR MEDIDO NO PERÍODO | M5: AVANÇO PERCENTUAL NO PERÍODO | N5: QUANTIDADE MEDIDA NO PERÍODO | O5: VALOR MEDIDO NO PERÍODO | P5: AVANÇO PERCENTUAL NO PERÍODO | Q5: QUANTIDADE MEDIDA NO PERÍODO | R5: VALOR MEDIDO NO PERÍODO | S5: AVANÇO PERCENTUAL NO PERÍODO | T5: QUANTIDADE MEDIDA NO PERÍODO | U5: VALOR MEDIDO NO PERÍODO | V5: AVANÇO PERCENTUAL NO PERÍODO | W5: QUANTIDADE MEDIDA NO PERÍODO | X5: VALOR MEDIDO NO PERÍODO | Y5: AVANÇO PERCENTUAL NO PERÍODO | Z5: QUANTIDADE MEDIDA NO PERÍODO | AA5: VALOR MEDIDO NO PERÍODO | AB5: AVANÇO PERCENTUAL NO PERÍODO | AC5: QUANTIDADE MEDIDA NO PERÍODO | AD5: VALOR MEDIDO NO PERÍODO | AE5: AVANÇO PERCENTUAL NO PERÍODO | AF5: QUANTIDADE MEDIDA NO PERÍODO | AG5: VALOR MEDIDO NO PERÍODO | AH5: % ACUMULADO | AI5: QUANT. ACUMULADA | AJ5: TOTAL ACUMULADO | AK5: STATUS DO ÍTEM | AL5: QUANTIDADE A SER ACRESCENTADA NO ADITIVO
A6: 1 | B6: SERVIÇOS PRELIMINARES | H6: =SUM(H7:H8) -> 4383.8738 | J6: MEDIÇÃO 01 | M6: MEDIÇÃO 02 | P6: MEDIÇÃO 03 | S6: MEDIÇÃO 04 | V6: MEDIÇÃO 05 | Y6: MEDIÇÃO 06 | AB6: MEDIÇÃO 07 | AE6: MEDIÇÃO 08
A7: 1.1 | B7: 51 | C7: Placa de obra em chapa aco galvanizado, instalada - Rev 02_O1/2022 | D7: ORSE | E7: M2 | F7: 6 | G7: 350.91 | H7: =F7*G7 -> 2105.46 | J7: 1 | K7: =TRUNC(J7*F7,2) -> 6 | L7: =TRUNC(K7*G7)+0.46 -> 2105.46 | M7: 0 | N7: =TRUNC(M7*F7,2) -> 0 | O7: =TRUNC(N7*G7)+0 -> 0 | P7: 0 | Q7: =TRUNC(P7*F7,2) -> 0 | R7: =TRUNC(Q7*G7) -> 0 | U7: =TRUNC(G7*T7)+0 -> 0 | V7: 0 | W7: =TRUNC(V7*F7,2) -> 0 | X7: =TRUNC(W7*G7)+0 -> 0 | Y7: =Z7/F7 -> 0 | AA7: =TRUNC(Z7*G7)+0 -> 0 | AB7: =AC7/F7 -> 0 | AD7: =TRUNC(AC7*G7) -> 0 | AE7: =AF7/F7 -> 0 | AG7: =TRUNC(AF7*G7) -> 0 | AH7: =SUM(J7,M7,P7,V7,Y7,AB7,AE7) -> 1 | AI7: =SUM(K7,N7,Q7,W7,Z7,T7,AC7) -> 6 | AJ7: =SUM(L7,O7,R7,X7,AA7,U7,AD7,AG7) -> 2105.46 | AK7: =IF(AH7=100%,"ITEM FINALIZADO",AH7) -> ITEM FINALIZADO
A8: 1.2 | B8: 98524 | C8: LIMPEZA MANUAL DE VEGETAÇÃO EM TERRENO COM EXADA AF 03/2024 | D8: SINAPI | E8: M2 | F8: 488.93 | G8: 4.66 | H8: =F8*G8 -> 2278.4138 | J8: 1 | K8: =TRUNC(J8*F8,2) -> 488.93 | L8: =TRUNC(K8*G8)+0.41 -> 2278.41 | U8: =TRUNC(G8*T8)+0 -> 0 | W8: =TRUNC(V8*F8,2) -> 0 | X8: =TRUNC(W8*G8)+0 -> 0 | Y8: =Z8/F8 -> 0 | AA8: =TRUNC(Z8*G8)+0 -> 0 | AB8: =AC8/F8 -> 0 | AD8: =TRUNC(AC8*G8) -> 0 | AE8: =AF8/F8 -> 0 | AG8: =TRUNC(AF8*G8) -> 0 | AH8: =SUM(J8,M8,P8,V8,Y8,AB8,AE8) -> 1 | AI8: =SUM(K8,N8,Q8,W8,Z8,T8,AC8) -> 488.93 | AJ8: =SUM(L8,O8,R8,X8,AA8,U8,AD8,AG8) -> 2278.41 | AK8: =IF(AH8=100%,"ITEM FINALIZADO",AH8) -> ITEM FINALIZADO
A9: 2 | B9: MOVIMENTO DE TERRA | H9: =SUM(H10:H12) -> 31651.318
A10: 2.1 | B10: 99059 | C10: LOCAÇÃO CONVENCIONAL DE OBRA, UTILIZANDO DE GABARITO DE TÁBUAS CORRIDAS PONTALETADAS A CADA 2,00M - 2 UTILIZAÇÕES. AF_03/2024 | D10: SINAPI | E10: M | F10: 335.2 | G10: 61.14 | H10: =(F10*G10)-0.01 -> 20494.118 | J10: 1 | K10: =TRUNC(J10*F10,2) -> 335.2 | L10: =TRUNC(K10*G10)+0.12 -> 20494.12 | U10: =TRUNC(G10*T10)+0 -> 0 | W10: =TRUNC(V10*F10,2) -> 0 | X10: =TRUNC(W10*G10)+0 -> 0 | Y10: =Z10/F10 -> 0 | AA10: =TRUNC(Z10*G10)+0 -> 0 | AB10: =AC10/F10 -> 0 | AD10: =TRUNC(AC10*G10) -> 0 | AE10: =AF10/F10 -> 0 | AG10: =TRUNC(AF10*G10) -> 0 | AH10: =SUM(J10,M10,P10,V10,Y10,AB10,AE10) -> 1 | AI10: =SUM(K10,N10,Q10,W10,Z10,T10,AC10) -> 335.2 | AJ10: =SUM(L10,O10,R10,X10,AA10,U10,AD10,AG10) -> 20494.12 | AK10: =IF(AH10=100%,"ITEM FINALIZADO",AH10) -> ITEM FINALIZADO
A11: 2.2 | B11: 93358 | C11: ESCAVAÇÃO MANUAL DE VALA COM PROFUNDIDADE MENOR OU IGUAL A 1,30M AF 02/2021 | D11: SINAPI | E11: M3 | F11: 81.25 | G11: 86.72 | H11: =F11*G11 -> 7046 | J11: 1 | K11: =TRUNC(J11*F11,2) -> 81.25 | L11: =TRUNC(K11*G11)+0 -> 7046 | U11: =TRUNC(G11*T11)+0 -> 0 | W11: =TRUNC(V11*F11,2) -> 0 | X11: =TRUNC(W11*G11)+0 -> 0 | Y11: =Z11/F11 -> 0 | AA11: =TRUNC(Z11*G11)+0 -> 0 | AB11: =AC11/F11 -> 0 | AD11: =TRUNC(AC11*G11) -> 0 | AE11: =AF11/F11 -> 0 | AG11: =TRUNC(AF11*G11) -> 0 | AH11: =SUM(J11,M11,P11,V11,Y11,AB11,AE11) -> 1 | AI11: =SUM(K11,N11,Q11,W11,Z11,T11,AC11) -> 81.25 | AJ11: =SUM(L11,O11,R11,X11,AA11,U11,AD11,AG11) -> 7046 | AK11: =IF(AH11=100%,"ITEM FINALIZADO",AH11) -> ITEM FINALIZADO
A12: 2.3 | B12: 94319 | C12: ATERRO MANUAL DE VALAS COM SOLO ARGILO-ARENOSO. AF_08/2023 | D12: SINAPI | E12: M3 | F12: 57.1 | G12: 72 | H12: =(F12*G12) -> 4111.2 | J12: 1 | K12: =TRUNC(J12*F12,2) -> 57.1 | L12: =TRUNC(K12*G12)+0.2 -> 4111.2 | U12: =TRUNC(G12*T12)+0 -> 0 | W12: =TRUNC(V12*F12,2) -> 0 | X12: =TRUNC(W12*G12)+0 -> 0 | Y12: =Z12/F12 -> 0 | AA12: =TRUNC(Z12*G12)+0 -> 0 | AB12: =AC12/F12 -> 0 | AD12: =TRUNC(AC12*G12) -> 0 | AE12: =AF12/F12 -> 0 | AG12: =TRUNC(AF12*G12) -> 0 | AH12: =SUM(J12,M12,P12,V12,Y12,AB12,AE12) -> 1 | AI12: =SUM(K12,N12,Q12,W12,Z12,T12,AC12) -> 57.1 | AJ12: =SUM(L12,O12,R12,X12,AA12,U12,AD12,AG12) -> 4111.2 | AK12: =IF(AH12=100%,"ITEM FINALIZADO",AH12) -> ITEM FINALIZADO
A13: 3 | B13: ESTRUTURA | H13: =SUM(H15,H22) -> 200390.71
A14: 3.1 | B14: INFRAESTUTURA | H14: =H15 -> 79073.708
A15: 3.1.1 | B15: FUNDAÇÃO | H15: =SUM(H16:H21) -> 79073.708
A16: 3.1.1.1 | B16: 102486 | C16: CONCRETO FCK = 15MPA, TRACO 13,4.3,4 (EM MASSA SECA DE CIMENTO / AREIA MÉDIA/ SEIXO ROLADO) - PREPARO MANUAL. AF_05/2021 | D16: SINAPI | E16: M3 | F16: 10.59 | G16: 569.3 | H16: =(F16*G16)-0.01 -> 6028.877 | J16: 0.8 | K16: =TRUNC(J16*F16,2) -> 8.47 | L16: =TRUNC(K16*G16)+0.1 -> 4821.1 | M16: 0.2 | N16: =TRUNC(M16*F16,2)+0.01 -> 2.12 | O16: =TRUNC(N16*G16)+1.78 -> 1207.78 | U16: =TRUNC(G16*T16)+0 -> 0 | W16: =TRUNC(V16*F16,2) -> 0 | X16: =TRUNC(W16*G16)+0 -> 0 | Y16: =Z16/F16 -> 0 | AA16: =TRUNC(Z16*G16)+0 -> 0 | AB16: =AC16/F16 -> 0 | AD16: =TRUNC(AC16*G16) -> 0 | AE16: =AF16/F16 -> 0 | AG16: =TRUNC(AF16*G16) -> 0 | AH16: =SUM(J16,M16,P16,V16,Y16,AB16,AE16) -> 1 | AI16: =SUM(K16,N16,Q16,W16,Z16,T16,AC16) -> 10.59 | AJ16: =SUM(L16,O16,R16,X16,AA16,U16,AD16,AG16) -> 6028.88 | AK16: =IF(AH16=100%,"ITEM FINALIZADO",AH16) -> ITEM FINALIZADO
A17: 3.1.1.2 | B17: 94965 | C17: CONCRETO FCK = 25MPA, TRACO 12,3:2,7 (EM MASSA SECA DE CIMENTO/ AREIA MEDIA/ BRITA 1) - PREPARO MECANICO COM BETONEIRA 400 L. AF 05/2021 | D17: SINAPI | E17: M3 | F17: 30.05 | G17: 433.53 | H17: =(F17*G17)-0.01 -> 13027.566 | J17: 0.8 | K17: =TRUNC(J17*F17,2) -> 24.04 | L17: =TRUNC(K17*G17)+0.05 -> 10422.05 | M17: 0.2 | N17: =TRUNC(M17*F17,2) -> 6.01 | O17: =TRUNC(N17*G17)+0.52 -> 2605.52 | U17: =TRUNC(G17*T17)+0 -> 0 | W17: =TRUNC(V17*F17,2) -> 0 | X17: =TRUNC(W17*G17)+0 -> 0 | Y17: =Z17/F17 -> 0 | AA17: =TRUNC(Z17*G17)+0 -> 0 | AB17: =AC17/F17 -> 0 | AD17: =TRUNC(AC17*G17) -> 0 | AE17: =AF17/F17 -> 0 | AG17: =TRUNC(AF17*G17) -> 0 | AH17: =SUM(J17,M17,P17,V17,Y17,AB17,AE17) -> 1 | AI17: =SUM(K17,N17,Q17,W17,Z17,T17,AC17) -> 30.05 | AJ17: =SUM(L17,O17,R17,X17,AA17,U17,AD17,AG17) -> 13027.57 | AK17: =IF(AH17=100%,"ITEM FINALIZADO",AH17) -> ITEM FINALIZADO
A18: 3.1.1.3 | B18: 96544 | C18: ARMAÇÃO DE BLOCO UTILIZANDO AÇO CA-50 DE 6,3 MM - MONTAGEM. AF 01/2024 | D18: SINAPI | E18: KG | F18: 33.4 | G18: 16.48 | H18: =(F18*G18) -> 550.432 | J18: 0.8 | K18: =TRUNC(J18*F18,2) -> 26.72 | L18: =TRUNC(K18*G18)+0.34 -> 440.34 | M18: 0.2 | N18: =TRUNC(M18*F18,2) -> 6.68 | O18: =TRUNC(N18*G18)+0.09 -> 110.09 | U18: =TRUNC(G18*T18)+0 -> 0 | W18: =TRUNC(V18*F18,2) -> 0 | X18: =TRUNC(W18*G18)+0 -> 0 | Y18: =Z18/F18 -> 0 | AA18: =TRUNC(Z18*G18)+0 -> 0 | AB18: =AC18/F18 -> 0 | AD18: =TRUNC(AC18*G18) -> 0 | AE18: =AF18/F18 -> 0 | AG18: =TRUNC(AF18*G18) -> 0 | AH18: =SUM(J18,M18,P18,V18,Y18,AB18,AE18) -> 1 | AI18: =SUM(K18,N18,Q18,W18,Z18,T18,AC18) -> 33.4 | AJ18: =SUM(L18,O18,R18,X18,AA18,U18,AD18,AG18) -> 550.43 | AK18: =IF(AH18=100%,"ITEM FINALIZADO",AH18) -> ITEM FINALIZADO
A19: 3.1.1.4 | B19: 98545 | C19: ARMAÇÃO DE BLOCO UTILZANDO AÇO CASO DE 8 MM - MONTAGEM. AF 01/2024 | D19: SINAPI | E19: KG | F19: 2842 | G19: 14.61 | H19: =(F19*G19) -> 41521.62 | J19: 0.8 | K19: =TRUNC(J19*F19,2) -> 2273.6 | L19: =TRUNC(K19*G19)+0.3 -> 33217.3 | M19: 0.2 | N19: =TRUNC(M19*F19,2) -> 568.4 | O19: =TRUNC(N19*G19)+0.32 -> 8304.32 | U19: =TRUNC(G19*T19)+0 -> 0 | W19: =TRUNC(V19*F19,2) -> 0 | X19: =TRUNC(W19*G19)+0 -> 0 | Y19: =Z19/F19 -> 0 | AA19: =TRUNC(Z19*G19)+0 -> 0 | AB19: =AC19/F19 -> 0 | AD19: =TRUNC(AC19*G19) -> 0 | AE19: =AF19/F19 -> 0 | AG19: =TRUNC(AF19*G19) -> 0 | AH19: =SUM(J19,M19,P19,V19,Y19,AB19,AE19) -> 1 | AI19: =SUM(K19,N19,Q19,W19,Z19,T19,AC19) -> 2842 | AJ19: =SUM(L19,O19,R19,X19,AA19,U19,AD19,AG19) -> 41521.62 | AK19: =IF(AH19=100%,"ITEM FINALIZADO",AH19) -> ITEM FINALIZADO
A20: 3.1.1.5 | B20: 96543 | C20: ARMAÇÃO DE BLOCO UTILIZANDO AÇO CA-60 DE 5 MM - MONTAGEM. AF 01/2024 | D20: SINAPI | E20: KG | F20: 580.1 | G20: 18.71 | H20: =(F20*G20) -> 10853.671 | J20: 0.8 | K20: =TRUNC(J20*F20,2) -> 464.08 | L20: =TRUNC(K20*G20)+0.94 -> 8682.94 | M20: 0.2 | N20: =TRUNC(M20*F20,2) -> 116.02 | O20: =TRUNC(N20*G20)+0.73 -> 2170.73 | U20: =TRUNC(G20*T20)+0 -> 0 | W20: =TRUNC(V20*F20,2) -> 0 | X20: =TRUNC(W20*G20)+0 -> 0 | Y20: =Z20/F20 -> 0 | AA20: =TRUNC(Z20*G20)+0 -> 0 | AB20: =AC20/F20 -> 0 | AD20: =TRUNC(AC20*G20) -> 0 | AE20: =AF20/F20 -> 0 | AG20: =TRUNC(AF20*G20) -> 0 | AH20: =SUM(J20,M20,P20,V20,Y20,AB20,AE20) -> 1 | AI20: =SUM(K20,N20,Q20,W20,Z20,T20,AC20) -> 580.1 | AJ20: =SUM(L20,O20,R20,X20,AA20,U20,AD20,AG20) -> 10853.67 | AK20: =IF(AH20=100%,"ITEM FINALIZADO",AH20) -> ITEM FINALIZADO
A21: 3.1.1.6 | B21: 98557 | C21: IMPERMEABILIZAÇÃO DE SUPERFÍCIE COM EMULSÃO ASFÁLTICA, 2 DEMÃOS. AF 09/2023 | D21: SINAPI | E21: M2 | F21: 154.03 | G21: 46.04 | H21: =(F21*G21) -> 7091.5412 | J21: 0.2 | K21: =TRUNC(J21*F21,2) -> 30.8 | L21: =TRUNC(K21*G21)+0.23 -> 1418.23 | M21: 0.8 | N21: =TRUNC(M21*F21,2) -> 123.22 | O21: =TRUNC(N21*G21)+0.31 -> 5673.31 | U21: =TRUNC(G21*T21)+0 -> 0 | W21: =TRUNC(V21*F21,2) -> 0 | X21: =TRUNC(W21*G21)+0 -> 0 | Y21: =Z21/F21 -> 0 | AA21: =TRUNC(Z21*G21)+0 -> 0 | AB21: =AC21/F21 -> 0 | AD21: =TRUNC(AC21*G21) -> 0 | AE21: =AF21/F21 -> 0 | AG21: =TRUNC(AF21*G21) -> 0 | AH21: =SUM(J21,M21,P21,V21,Y21,AB21,AE21) -> 1 | AI21: =SUM(K21,N21,Q21,W21,Z21,T21,AC21) -> 154.02 | AJ21: =SUM(L21,O21,R21,X21,AA21,U21,AD21,AG21) -> 7091.54 | AK21: =IF(AH21=100%,"ITEM FINALIZADO",AH21) -> ITEM FINALIZADO
A22: 3.2 | B22: SUPERESTRUTURA | H22: =SUM(H23,H30,H38)+0.01 -> 121317
A23: 3.2.1 | B23: PILARES | H23: =SUM(H24:H29) -> 46405.309
A24: 3.2.1.1 | B24: 102476 | C24: CONCRETO FCK = 25MPA, TRACO 1:2,2:2,5 (EM MASSA SECA DE CIMENTO/ AREIA MEDIA/ SEIXO ROLADO) - PREPARO MECANICO COM BETONEIRA 400 L. AF 05/2021 | D24: SINAPI | E24: M3 | F24: 15.1 | G24: 557.58 | H24: =(F24*G24)-0.01 -> 8419.448 | J24: 0.5 | K24: =TRUNC(J24*F24,2) -> 7.55 | L24: =TRUNC(K24*G24)+0.73 -> 4209.73 | M24: 0.4 | N24: =TRUNC(M24*F24,2) -> 6.04 | O24: =TRUNC(N24*G24)+0.78 -> 3367.78 | P24: 0.1 | Q24: =TRUNC(P24*F24,2) -> 1.51 | R24: =TRUNC(Q24*G24) -> 841 | U24: =TRUNC(G24*T24)+0 -> 0 | W24: =TRUNC(V24*F24,2) -> 0 | X24: =TRUNC(W24*G24)+0 -> 0 | Y24: =Z24/F24 -> 0 | AA24: =TRUNC(Z24*G24)+0 -> 0 | AB24: =AC24/F24 -> 0 | AD24: =TRUNC(AC24*G24) -> 0 | AE24: =AF24/F24 -> 0 | AG24: =TRUNC(AF24*G24) -> 0 | AH24: =SUM(J24,M24,P24,V24,Y24,AB24,AE24) -> 1 | AI24: =SUM(K24,N24,Q24,W24,Z24,T24,AC24) -> 15.1 | AJ24: =SUM(L24,O24,R24,X24,AA24,U24,AD24,AG24) -> 8418.51 | AK24: =IF(AH24=100%,"ITEM FINALIZADO",AH24) -> ITEM FINALIZADO
A25: 3.2.1.2 | B25: 96546 | C25: ARMAÇÃO DE BLOCO UTILIZANDO AÇO CA-SO DE 10 MM - MONTAGEM. AF 01/2024 | D25: SINAPI | E25: KG | F25: 90.3 | G25: 12.61 | H25: =(F25*G25) -> 1138.683 | J25: 0.5 | K25: =TRUNC(J25*F25,2) -> 45.15 | L25: =TRUNC(K25*G25)+0.34 -> 569.34 | M25: 0.4 | N25: =TRUNC(M25*F25,2) -> 36.12 | O25: =TRUNC(N25*G25)+0.47 -> 455.47 | P25: 0.1 | Q25: =TRUNC(P25*F25,2) -> 9.03 | R25: =TRUNC(Q25*G25) -> 113 | U25: =TRUNC(G25*T25)+0 -> 0 | W25: =TRUNC(V25*F25,2) -> 0 | X25: =TRUNC(W25*G25)+0 -> 0 | Y25: =Z25/F25 -> 0 | AA25: =TRUNC(Z25*G25)+0 -> 0 | AB25: =AC25/F25 -> 0 | AD25: =TRUNC(AC25*G25) -> 0 | AE25: =AF25/F25 -> 0 | AG25: =TRUNC(AF25*G25) -> 0 | AH25: =SUM(J25,M25,P25,V25,Y25,AB25,AE25) -> 1 | AI25: =SUM(K25,N25,Q25,W25,Z25,T25,AC25) -> 90.3 | AJ25: =SUM(L25,O25,R25,X25,AA25,U25,AD25,AG25) -> 1137.81 | AK25: =IF(AH25=100%,"ITEM FINALIZADO",AH25) -> ITEM FINALIZADO
A26: 3.2.1.3 | B26: 98543 | C26: ARMAÇÃO DE BLOCO UTILIZANDO AÇO CA-CO DE 5 MM - MONTAGEM. AF 01/2024 | D26: SINAPI | E26: KG | F26: 466.7 | G26: 18.71 | H26: =(F26*G26)-0.01 -> 8731.947 | J26: 1 | K26: =TRUNC(J26*F26,2) -> 466.7 | L26: =TRUNC(K26*G26)+0.95 -> 8731.95 | Q26: =TRUNC(P26*F26,2) -> 0 | R26: =TRUNC(Q26*G26) -> 0 | U26: =TRUNC(G26*T26)+0 -> 0 | W26: =TRUNC(V26*F26,2) -> 0 | X26: =TRUNC(W26*G26)+0 -> 0 | Y26: =Z26/F26 -> 0 | AA26: =TRUNC(Z26*G26)+0 -> 0 | AB26: =AC26/F26 -> 0 | AD26: =TRUNC(AC26*G26) -> 0 | AE26: =AF26/F26 -> 0 | AG26: =TRUNC(AF26*G26) -> 0 | AH26: =SUM(J26,M26,P26,V26,Y26,AB26,AE26) -> 1 | AI26: =SUM(K26,N26,Q26,W26,Z26,T26,AC26) -> 466.7 | AJ26: =SUM(L26,O26,R26,X26,AA26,U26,AD26,AG26) -> 8731.95 | AK26: =IF(AH26=100%,"ITEM FINALIZADO",AH26) -> ITEM FINALIZADO
A27: 3.2.1.4 | B27: 96545 | C27: ARMAÇÃO DE BLOCO UTILZANDO AÇO CA-50 DES MM - MONTAGEM, AF 01/2024 | D27: SINAPI | E27: KG | F27: 636.3 | G27: 14.61 | H27: =(F27*G27) -> 9296.343 | J27: 1 | K27: =TRUNC(J27*F27,2) -> 636.3 | L27: =TRUNC(K27*G27)+0.34 -> 9296.34 | Q27: =TRUNC(P27*F27,2) -> 0 | R27: =TRUNC(Q27*G27) -> 0 | U27: =TRUNC(G27*T27)+0 -> 0 | W27: =TRUNC(V27*F27,2) -> 0 | X27: =TRUNC(W27*G27)+0 -> 0 | Y27: =Z27/F27 -> 0 | AA27: =TRUNC(Z27*G27)+0 -> 0 | AB27: =AC27/F27 -> 0 | AD27: =TRUNC(AC27*G27) -> 0 | AE27: =AF27/F27 -> 0 | AG27: =TRUNC(AF27*G27) -> 0 | AH27: =SUM(J27,M27,P27,V27,Y27,AB27,AE27) -> 1 | AI27: =SUM(K27,N27,Q27,W27,Z27,T27,AC27) -> 636.3 | AJ27: =SUM(L27,O27,R27,X27,AA27,U27,AD27,AG27) -> 9296.34 | AK27: =IF(AH27=100%,"ITEM FINALIZADO",AH27) -> ITEM FINALIZADO
A28: 3.2.1.5 | B28: 96547 | C28: ARMAÇÃO DE BLOCO, VIGA BALDRAME OU SAPATA UTILIZANDO AÇO CA- 50 DE 12,5 MM - MONTAGEM. AF 06/2017 | D28: SINAPI | E28: KG | F28: 17.11 | G28: 9.6 | H28: =(F28*G28)-0.01 -> 164.246 | J28: 1 | K28: =TRUNC(J28*F28,2) -> 17.11 | L28: =TRUNC(K28*G28)+0.25 -> 164.25 | Q28: =TRUNC(P28*F28,2) -> 0 | R28: =TRUNC(Q28*G28) -> 0 | U28: =TRUNC(G28*T28)+0 -> 0 | W28: =TRUNC(V28*F28,2) -> 0 | X28: =TRUNC(W28*G28)+0 -> 0 | Y28: =Z28/F28 -> 0 | AA28: =TRUNC(Z28*G28)+0 -> 0 | AB28: =AC28/F28 -> 0 | AD28: =TRUNC(AC28*G28) -> 0 | AE28: =AF28/F28 -> 0 | AG28: =TRUNC(AF28*G28) -> 0 | AH28: =SUM(J28,M28,P28,V28,Y28,AB28,AE28) -> 1 | AI28: =SUM(K28,N28,Q28,W28,Z28,T28,AC28) -> 17.11 | AJ28: =SUM(L28,O28,R28,X28,AA28,U28,AD28,AG28) -> 164.25 | AK28: =IF(AH28=100%,"ITEM FINALIZADO",AH28) -> ITEM FINALIZADO
A29: 3.2.1.6 | B29: 103795 | C29: FABRICAÇÃO, MONTAGEM E DESMONTAGEM DE FÔRMA PARA ESCADA HIDRAULICA, EM CHAPA DE MADEIRA COMPENSADA RESINADA, E = 17 MM, 3 UTILIZAÇÕES. AF 08/2022 | D29: SINAPI | E29: M2 | F29: 227.69 | G29: 81.93 | H29: =(F29*G29) -> 18654.642 | J29: 0.5 | K29: =TRUNC(J29*F29,2) -> 113.84 | L29: =TRUNC(K29*G29)+1.32 -> 9327.32 | M29: 0.5 | N29: =TRUNC(M29*F29,2) -> 113.84 | O29: =TRUNC(N29*G29)+1.32 -> 9327.32 | P29: 0.1 | Q29: =TRUNC(P29*F29,2) -> 22.76 | R29: =TRUNC(Q29*G29) -> 1864 | T29: -22.76 | U29: =TRUNC(G29*T29)+0 -> -1864 | V29: -0.1 | W29: =TRUNC(V29*F29,2) -> -22.76 | Y29: =Z29/F29 -> 0 | AA29: =TRUNC(Z29*G29)+0 -> 0 | AB29: =AC29/F29 -> 0 | AD29: =TRUNC(AC29*G29) -> 0 | AE29: =AF29/F29 -> 0 | AG29: =TRUNC(AF29*G29) -> 0 | AH29: =SUM(J29,M29,P29,V29,Y29,AB29,AE29) -> 1 | AI29: =SUM(K29,N29,Q29,W29,Z29,T29,AC29) -> 204.92 | AJ29: =SUM(L29,O29,R29,X29,AA29,U29,AD29,AG29) -> 18654.64 | AK29: =IF(AH29=100%,"ITEM FINALIZADO",AH29) -> ITEM FINALIZADO
A30: 3.2.2 | B30: VIGAS | H30: =SUM(H31:H37) -> 32909.86 | AK30: =SUM(AK31) -> 0
A31: 3.2.2.1 | B31: 102476 | C31: CONCRETO FCK = 25MPA, TRAGO 12,2:2,5 (EM MASSA SECA DE CIMENTO/ AREIA MEDIA/ SEIXO ROLADO) - PREPARO MECANICO COM BETONEIRA 400 L. AF 05/2021 | D31: SINAPI | E31: M3 | F31: 15.81 | G31: 557.58 | H31: =(F31*G31)-0.01 -> 8815.3298 | M31: 0.4 | N31: =TRUNC(M31*F31,2) -> 6.32 | O31: =TRUNC(N31*G31)+3.13 -> 3526.13 | P31: 0.6 | Q31: =TRUNC(P31*F31,2) -> 9.48 | R31: =TRUNC(Q31*G31) -> 5285 | U31: =TRUNC(G31*T31)+0 -> 0 | W31: =TRUNC(V31*F31,2) -> 0 | X31: =TRUNC(W31*G31)+0 -> 0 | Y31: =Z31/F31 -> 0 | AA31: =TRUNC(Z31*G31)+0 -> 0 | AB31: =AC31/F31 -> 0 | AD31: =TRUNC(AC31*G31) -> 0 | AE31: =AF31/F31 -> 0 | AG31: =TRUNC(AF31*G31) -> 0 | AH31: =SUM(J31,M31,P31,V31,Y31,AB31,AE31) -> 1 | AI31: =SUM(K31,N31,Q31,W31,Z31,T31,AC31) -> 15.8 | AJ31: =SUM(L31,O31,R31,X31,AA31,U31,AD31,AG31) -> 8811.13 | AK31: =IF(AH31=100%,"ITEM FINALIZADO",AH31) -> ITEM FINALIZADO
A32: 3.2.2.2 | B32: 92760 | C32: ARMAÇÃO DE PILAR OU VIGA DE ESTRUTURA CONVENCIONAL DE CONCRETO ARMADO UTILIZANDO AÇO CA-50 06 8,3 MM - MONTAGEM. AF 06/2022 | D32: SINAPI | E32: KG | F32: 39.6 | G32: 11.8 | H32: =(F32*G32) -> 467.28 | M32: 0.8 | N32: =TRUNC(M32*F32,2) -> 31.68 | O32: =TRUNC(N32*G32)+0.82 -> 373.82 | P32: 0.2 | Q32: =TRUNC(P32*F32,2) -> 7.92 | R32: =TRUNC(Q32*G32) -> 93 | U32: =TRUNC(G32*T32)+0 -> 0 | W32: =TRUNC(V32*F32,2) -> 0 | X32: =TRUNC(W32*G32)+0 -> 0 | Y32: =Z32/F32 -> 0 | AA32: =TRUNC(Z32*G32)+0 -> 0 | AB32: =AC32/F32 -> 0 | AD32: =TRUNC(AC32*G32) -> 0 | AE32: =AF32/F32 -> 0 | AG32: =TRUNC(AF32*G32) -> 0 | AH32: =SUM(J32,M32,P32,V32,Y32,AB32,AE32) -> 1 | AI32: =SUM(K32,N32,Q32,W32,Z32,T32,AC32) -> 39.6 | AJ32: =SUM(L32,O32,R32,X32,AA32,U32,AD32,AG32) -> 466.82 | AK32: =IF(AH32=100%,"ITEM FINALIZADO",AH32) -> ITEM FINALIZADO
A33: 3.2.2.3 | B33: 92761 | C33: ARMAÇÃO DE PILAR OU VIGA DE ESTRUTURA CONVENCIONAL DE CONCRETO ARMADO UTILIZANDO AÇO CA-50 DE 8,0 MM - MONTAGEM. AF 06/2022 | D33: SINAPI | E33: KG | F33: 80 | G33: 10.88 | H33: =(F33*G33) -> 870.4 | M33: 0.8 | N33: =TRUNC(M33*F33,2) -> 64 | O33: =TRUNC(N33*G33)+0.32 -> 696.32 | P33: 0.2 | Q33: =TRUNC(P33*F33,2) -> 16 | R33: =TRUNC(Q33*G33) -> 174 | U33: =TRUNC(G33*T33)+0 -> 0 | W33: =TRUNC(V33*F33,2) -> 0 | X33: =TRUNC(W33*G33)+0 -> 0 | Y33: =Z33/F33 -> 0 | AA33: =TRUNC(Z33*G33)+0 -> 0 | AB33: =AC33/F33 -> 0 | AD33: =TRUNC(AC33*G33) -> 0 | AE33: =AF33/F33 -> 0 | AG33: =TRUNC(AF33*G33) -> 0 | AH33: =SUM(J33,M33,P33,V33,Y33,AB33,AE33) -> 1 | AI33: =SUM(K33,N33,Q33,W33,Z33,T33,AC33) -> 80 | AJ33: =SUM(L33,O33,R33,X33,AA33,U33,AD33,AG33) -> 870.32 | AK33: =IF(AH33=100%,"ITEM FINALIZADO",AH33) -> ITEM FINALIZADO
A34: 3.2.2.4 | B34: 92762 | C34: ARMAÇÃO DE PILAR OU VIGA DE ESTRUTURA CONVENCIONAL DE CONCRETO ARMADO UTILIZANDO AÇO CA-50 DE 10,0 MM - MONTAGEM. AF 06/2022 | D34: SINAPI | E34: KG | F34: 337.7 | G34: 9.61 | H34: =(F34*G34)-0.01 -> 3245.287 | M34: 0.8 | N34: =TRUNC(M34*F34,2) -> 270.16 | O34: =TRUNC(N34*G34)+0.23 -> 2596.23 | P34: 0.2 | Q34: =TRUNC(P34*F34,2) -> 67.54 | R34: =TRUNC(Q34*G34) -> 649 | U34: =TRUNC(G34*T34)+0 -> 0 | W34: =TRUNC(V34*F34,2) -> 0 | X34: =TRUNC(W34*G34)+0 -> 0 | Y34: =Z34/F34 -> 0 | AA34: =TRUNC(Z34*G34)+0 -> 0 | AB34: =AC34/F34 -> 0 | AD34: =TRUNC(AC34*G34) -> 0 | AE34: =AF34/F34 -> 0 | AG34: =TRUNC(AF34*G34) -> 0 | AH34: =SUM(J34,M34,P34,V34,Y34,AB34,AE34) -> 1 | AI34: =SUM(K34,N34,Q34,W34,Z34,T34,AC34) -> 337.7 | AJ34: =SUM(L34,O34,R34,X34,AA34,U34,AD34,AG34) -> 3245.23 | AK34: =IF(AH34=100%,"ITEM FINALIZADO",AH34) -> ITEM FINALIZADO
A35: 3.2.2.5 | B35: 92763 | C35: ARMAÇÃO DE PILAR OU VIGA DE ESTRUTURA CONVENCIONAL DE CONCRETO ARMADO UTILZANDO AÇO CA-50 DE 12,5 MM - MONTAGEM. AF 06/2022 | D35: SINAPI | E35: KG | F35: 189.7 | G35: 8.02 | H35: =(F35*G35) -> 1521.394 | M35: 0.8 | N35: =TRUNC(M35*F35,2) -> 151.76 | O35: =TRUNC(N35*G35)+0.11 -> 1217.11 | P35: 0.2 | Q35: =TRUNC(P35*F35,2) -> 37.94 | R35: =TRUNC(Q35*G35) -> 304 | U35: =TRUNC(G35*T35)+0 -> 0 | W35: =TRUNC(V35*F35,2) -> 0 | X35: =TRUNC(W35*G35)+0 -> 0 | Y35: =Z35/F35 -> 0 | AA35: =TRUNC(Z35*G35)+0 -> 0 | AB35: =AC35/F35 -> 0 | AD35: =TRUNC(AC35*G35) -> 0 | AE35: =AF35/F35 -> 0 | AG35: =TRUNC(AF35*G35) -> 0 | AH35: =SUM(J35,M35,P35,V35,Y35,AB35,AE35) -> 1 | AI35: =SUM(K35,N35,Q35,W35,Z35,T35,AC35) -> 189.7 | AJ35: =SUM(L35,O35,R35,X35,AA35,U35,AD35,AG35) -> 1521.11 | AK35: =IF(AH35=100%,"ITEM FINALIZADO",AH35) -> ITEM FINALIZADO
A36: 3.2.2.6 | B36: 92759 | C36: ARMAÇÃO DE PILAR OU VIGA DE ESTRUTURA CONVENCIONAL DE CONCRETO ARMADO UTILIZANDO AÇO CA-CO DE 5,0 MM - MONTAGEM. AF 06/2022 | D36: SINAPI | E36: KG | F36: 179.1 | G36: 12.82 | H36: =(F36*G36) -> 2296.062 | M36: 0.8 | N36: =TRUNC(M36*F36,2) -> 143.28 | O36: =TRUNC(N36*G36)+0.85 -> 1836.85 | P36: 0.2 | Q36: =TRUNC(P36*F36,2) -> 35.82 | R36: =TRUNC(Q36*G36) -> 459 | U36: =TRUNC(G36*T36)+0 -> 0 | W36: =TRUNC(V36*F36,2) -> 0 | X36: =TRUNC(W36*G36)+0 -> 0 | Y36: =Z36/F36 -> 0 | AA36: =TRUNC(Z36*G36)+0 -> 0 | AB36: =AC36/F36 -> 0 | AD36: =TRUNC(AC36*G36) -> 0 | AE36: =AF36/F36 -> 0 | AG36: =TRUNC(AF36*G36) -> 0 | AH36: =SUM(J36,M36,P36,V36,Y36,AB36,AE36) -> 1 | AI36: =SUM(K36,N36,Q36,W36,Z36,T36,AC36) -> 179.1 | AJ36: =SUM(L36,O36,R36,X36,AA36,U36,AD36,AG36) -> 2295.85 | AK36: =IF(AH36=100%,"ITEM FINALIZADO",AH36) -> ITEM FINALIZADO
A37: 3.2.2.7 | B37: 92265 | C37: FABRICAÇÃO DE FORMA PARA VIGAS, EM CHAPA DE MADEIRA COMPENSADA RESINADA, E = 17 MM. AF 09/2020 | D37: SINAPI | E37: M2 | F37: 154.03 | G37: 101.89 | H37: =(F37*G37)-0.01 -> 15694.107 | M37: 1 | N37: =TRUNC(M37*F37,2) -> 154.03 | O37: =TRUNC(N37*G37)+0.11 -> 15694.11 | U37: =TRUNC(G37*T37)+0 -> 0 | W37: =TRUNC(V37*F37,2) -> 0 | X37: =TRUNC(W37*G37)+0 -> 0 | Y37: =Z37/F37 -> 0 | AA37: =TRUNC(Z37*G37)+0 -> 0 | AB37: =AC37/F37 -> 0 | AD37: =TRUNC(AC37*G37) -> 0 | AE37: =AF37/F37 -> 0 | AG37: =TRUNC(AF37*G37) -> 0 | AH37: =SUM(J37,M37,P37,V37,Y37,AB37,AE37) -> 1 | AI37: =SUM(K37,N37,Q37,W37,Z37,T37,AC37) -> 154.03 | AJ37: =SUM(L37,O37,R37,X37,AA37,U37,AD37,AG37) -> 15694.11 | AK37: =IF(AH37=100%,"ITEM FINALIZADO",AH37) -> ITEM FINALIZADO
A38: 3.2.3 | B38: LAJE | H38: =SUM(H39:H44) -> 42001.827 | AK38: =SUM(AK39) -> 0
A39: 3.2.3.1 | B39: 94965 | C39: CONCRETO FCK = 25MPA, TRACO 1:2,3:2,7 (EM MASSA SECA DE CIMENTO/AREIA MEDIA/ BRITA 1) - PREPARO MECANICO COM BETONEIRA 400 L. AF 05/2021 | D39: SINAPI | E39: M3 | F39: 46.31 | G39: 433.53 | H39: =(F39*G39) -> 20076.774 | U39: =TRUNC(G39*T39)+0 -> 0 | V39: 0 | W39: =TRUNC(V39*F39,2) -> 0 | X39: =TRUNC(W39*G39)+0 -> 0 | Y39: =Z39/F39 -> 0 | AA39: =TRUNC(Z39*G39)+0 -> 0 | AB39: =AC39/F39 -> 0 | AD39: =TRUNC(AC39*G39) -> 0 | AE39: =AF39/F39 -> 0 | AG39: =TRUNC(AF39*G39) -> 0 | AH39: =SUM(J39,M39,P39,V39,Y39,AB39,AE39) -> 0 | AI39: =SUM(K39,N39,Q39,W39,Z39,T39,AC39) -> 0 | AJ39: =SUM(L39,O39,R39,X39,AA39,U39,AD39,AG39) -> 0 | AK39: =IF(AH39=100%,"ITEM FINALIZADO",AH39) -> 0
A40: 3.2.3.2 | B40: 92267 | C40: FABRICAÇÃO DE FÔRMA PARA LAJES, EM CHAPA DE MADEIRA COMPENSADA RESINADA, E = 17 MM. AF 09/2020 | D40: SINAPI | E40: M2 | F40: 312.27 | G40: 26.89 | H40: =(F40*G40) -> 8396.9403 | U40: =TRUNC(G40*T40)+0 -> 0 | V40: 0 | W40: =TRUNC(V40*F40,2) -> 0 | X40: =TRUNC(W40*G40)+0 -> 0 | Y40: =Z40/F40 -> 0 | AA40: =TRUNC(Z40*G40)+0 -> 0 | AB40: =AC40/F40 -> 0 | AD40: =TRUNC(AC40*G40) -> 0 | AE40: =AF40/F40 -> 0 | AG40: =TRUNC(AF40*G40) -> 0 | AH40: =SUM(J40,M40,P40,V40,Y40,AB40,AE40) -> 0 | AI40: =SUM(K40,N40,Q40,W40,Z40,T40,AC40) -> 0 | AJ40: =SUM(L40,O40,R40,X40,AA40,U40,AD40,AG40) -> 0 | AK40: =IF(AH40=100%,"ITEM FINALIZADO",AH40) -> 0
A41: 3.2.3.3 | B41: 92769 | C41: ARMAÇÃO DE LAJE DE ESTRUTURA CONVENCIONAL DE CONCRETO ARMADO UTILIZANDO AÇO CA-SO DE 6,3 MM - MONTAGEM. AF_06/2022 | D41: SINAPI | E41: KG | F41: 885.8 | G41: 11.26 | H41: =(F41*G41)-0.01 -> 9974.098 | U41: =TRUNC(G41*T41)+0 -> 0 | V41: 0 | W41: =TRUNC(V41*F41,2) -> 0 | X41: =TRUNC(W41*G41)+0 -> 0 | Y41: =Z41/F41 -> 0 | AA41: =TRUNC(Z41*G41)+0 -> 0 | AB41: =AC41/F41 -> 0 | AD41: =TRUNC(AC41*G41) -> 0 | AE41: =AF41/F41 -> 0 | AG41: =TRUNC(AF41*G41) -> 0 | AH41: =SUM(J41,M41,P41,V41,Y41,AB41,AE41) -> 0 | AI41: =SUM(K41,N41,Q41,W41,Z41,T41,AC41) -> 0 | AJ41: =SUM(L41,O41,R41,X41,AA41,U41,AD41,AG41) -> 0 | AK41: =IF(AH41=100%,"ITEM FINALIZADO",AH41) -> 0
A42: 3.2.3.4 | B42: 92770 | C42: ARMAÇÃO DE LAJE DE ESTRUTURA CONVENCIONAL DE CONCRETO ARMADO UTILIZANDO AÇO CA-SO DE 8,0 MM - MONTAGEM. AF_06/2022 | D42: SINAPI | E42: KG | F42: 229.5 | G42: 10.37 | H42: =(F42*G42)-0.01 -> 2379.905 | U42: =TRUNC(G42*T42)+0 -> 0 | V42: 0 | W42: =TRUNC(V42*F42,2) -> 0 | X42: =TRUNC(W42*G42)+0 -> 0 | Y42: =Z42/F42 -> 0 | AA42: =TRUNC(Z42*G42)+0 -> 0 | AB42: =AC42/F42 -> 0 | AD42: =TRUNC(AC42*G42) -> 0 | AE42: =AF42/F42 -> 0 | AG42: =TRUNC(AF42*G42) -> 0 | AH42: =SUM(J42,M42,P42,V42,Y42,AB42,AE42) -> 0 | AI42: =SUM(K42,N42,Q42,W42,Z42,T42,AC42) -> 0 | AJ42: =SUM(L42,O42,R42,X42,AA42,U42,AD42,AG42) -> 0 | AK42: =IF(AH42=100%,"ITEM FINALIZADO",AH42) -> 0
A43: 3.2.3.5 | B43: 92771 | C43: ARMAÇAO DE LAJE DE ESTRUTURA CONVENCIONAL DE CONCRETO ARMADO UTILIZANDO AÇO CA-50 DE 10,0 MM - MONTAGEM. AF_08/2022 | D43: SINAPI | E43: KG | F43: 39.6 | G43: 9.14 | H43: =(F43*G43) -> 361.944 | U43: =TRUNC(G43*T43)+0 -> 0 | V43: 0 | W43: =TRUNC(V43*F43,2) -> 0 | X43: =TRUNC(W43*G43)+0 -> 0 | Y43: =Z43/F43 -> 0 | AA43: =TRUNC(Z43*G43)+0 -> 0 | AB43: =AC43/F43 -> 0 | AD43: =TRUNC(AC43*G43) -> 0 | AE43: =AF43/F43 -> 0 | AG43: =TRUNC(AF43*G43) -> 0 | AH43: =SUM(J43,M43,P43,V43,Y43,AB43,AE43) -> 0 | AI43: =SUM(K43,N43,Q43,W43,Z43,T43,AC43) -> 0 | AJ43: =SUM(L43,O43,R43,X43,AA43,U43,AD43,AG43) -> 0 | AK43: =IF(AH43=100%,"ITEM FINALIZADO",AH43) -> 0
A44: 3.2.3.6 | B44: 92768 | C44: ARMAÇÃO DE LAJE DE ESTRUTURA CONVENCIONAL DE CONCRETO ARMADO UTILIZANDO AÇO CA-CO DE 5,0 MM - MONTAGEM. AF_06/2022 | D44: SINAPI | E44: KG | F44: 66.3 | G44: 12.25 | H44: =(F44*G44)-0.01 -> 812.165 | U44: =TRUNC(G44*T44)+0 -> 0 | V44: 0 | W44: =TRUNC(V44*F44,2) -> 0 | X44: =TRUNC(W44*G44)+0 -> 0 | Y44: =Z44/F44 -> 0 | AA44: =TRUNC(Z44*G44)+0 -> 0 | AB44: =AC44/F44 -> 0 | AD44: =TRUNC(AC44*G44) -> 0 | AE44: =AF44/F44 -> 0 | AG44: =TRUNC(AF44*G44) -> 0 | AH44: =SUM(J44,M44,P44,V44,Y44,AB44,AE44) -> 0 | AI44: =SUM(K44,N44,Q44,W44,Z44,T44,AC44) -> 0 | AJ44: =SUM(L44,O44,R44,X44,AA44,U44,AD44,AG44) -> 0 | AK44: =IF(AH44=100%,"ITEM FINALIZADO",AH44) -> 0
A45: 4 | B45: ELEVAÇÃO | H45: =SUM(H46:H46) -> 52764.439
A46: 4.1 | B46: 103328 | C46: ALVENARIA DE VEDAÇÃO DE BLOCOS CERAMICOS FURADOS NA HORIZONTAL DE 9X19X19 CM (ESPESSURA 9 CM) E ARGAMASSA DE ASSENTAMENTO COM PREPARO EM BETONEIRA. AF_12/2021 | D46: SINAPI | E46: M2 | F46: 609.43 | G46: 86.58 | H46: =(F46*G46)-0.01 -> 52764.439 | J46: 0.3 | K46: =TRUNC(J46*F46,2) -> 182.82 | L46: =TRUNC(K46*G46)+1.33 -> 15829.33 | M46: 0.6 | N46: =TRUNC(M46*F46,2) -> 365.65 | O46: =TRUNC(N46*G46)+1.66 -> 31658.66 | T46: 60.94 | U46: =TRUNC(G46*T46)+0 -> 5276 | V46: 0.1 | W46: =TRUNC(V46*F46,2) -> 60.94 | X46: 0 | Y46: =Z46/F46 -> 0 | AA46: =TRUNC(Z46*G46)+0 -> 0 | AB46: =AC46/F46 -> 0 | AD46: =TRUNC(AC46*G46) -> 0 | AE46: =AF46/F46 -> 0 | AG46: =TRUNC(AF46*G46) -> 0 | AH46: =SUM(J46,M46,P46,V46,Y46,AB46,AE46) -> 1 | AI46: =SUM(K46,N46,Q46,W46,Z46,T46,AC46) -> 670.35 | AJ46: =SUM(L46,O46,R46,X46,AA46,U46,AD46,AG46) -> 52763.99 | AK46: =IF(AH46=100%,"ITEM FINALIZADO",AH46) -> ITEM FINALIZADO | AL46: =((F48/2)+F50)-F46 -> 709.27
A47: 5 | B47: REVESTIMENTO | H47: =SUM(H48:H51) -> 141718.33
A48: 5.1 | B48: 87894 | C48: CHAPISCO APLICADO EM ALVENARIA (SEM PRESENÇA DE VÃOS) E ESTRUTURAS DE CONCRETO DE FACHADA, COM COLHER DE PEDREIRO. ARGAMASSA TRAÇO 1.3 COM PREPARO EM BETONEIRA 400L. AF_10/2022 | D48: SINAPI | E48: M2 | F48: 2157.32 | G48: 6.63 | H48: =(F48*G48) -> 14303.032 | P48: 0.5 | Q48: =TRUNC(P48*F48,2) -> 1078.66 | R48: =TRUNC(Q48*G48) -> 7151 | T48: 1078.66 | U48: =TRUNC(G48*T48)+0 -> 7151 | V48: 0.5 | W48: =TRUNC(V48*F48,2) -> 1078.66 | X48: 0 | Y48: =Z48/F48 -> 0 | AA48: =TRUNC(Z48*G48)+0 -> 0 | AB48: =AC48/F48 -> 0 | AD48: =TRUNC(AC48*G48) -> 0 | AE48: =AF48/F48 -> 0 | AG48: =TRUNC(AF48*G48) -> 0 | AH48: =SUM(J48,M48,P48,V48,Y48,AB48,AE48) -> 1 | AI48: =SUM(K48,N48,Q48,W48,Z48,T48,AC48) -> 3235.98 | AJ48: =SUM(L48,O48,R48,X48,AA48,U48,AD48,AG48) -> 14302 | AK48: =IF(AH48=100%,"ITEM FINALIZADO",AH48) -> ITEM FINALIZADO
A49: 5.2 | B49: 87548 | C49: MASSA ÚNICA, EM ARGAMASSA TRAÇO 1:2:8, PREPARO MANUAL, APLICADA MANUALMENTE EM PAREDES INTERNAS DE AMBIENTES COM ÁREA ENTRE 5M² E 10M², E = 10MM, COM TALISCAS, AF_03/2024 | D49: SINAPI | E49: M2 | F49: 2157.32 | G49: 27.55 | H49: =(F49*G49) -> 59434.166 | P49: 0.5 | Q49: =TRUNC(P49*F49,2) -> 1078.66 | R49: =TRUNC(Q49*G49) -> 29717 | T49: 1078.66 | U49: =TRUNC(G49*T49)+0 -> 29717 | V49: 0.5 | W49: =TRUNC(V49*F49,2) -> 1078.66 | X49: 0 | Y49: =Z49/F49 -> 0 | AA49: =TRUNC(Z49*G49)+0 -> 0 | AB49: =AC49/F49 -> 0 | AD49: =TRUNC(AC49*G49) -> 0 | AE49: =AF49/F49 -> 0 | AG49: =TRUNC(AF49*G49) -> 0 | AH49: =SUM(J49,M49,P49,V49,Y49,AB49,AE49) -> 1 | AI49: =SUM(K49,N49,Q49,W49,Z49,T49,AC49) -> 3235.98 | AJ49: =SUM(L49,O49,R49,X49,AA49,U49,AD49,AG49) -> 59434 | AK49: =IF(AH49=100%,"ITEM FINALIZADO",AH49) -> ITEM FINALIZADO
A50: 5.3 | B50: 104817 | C50: REVESTIMENTO CERÂMICO PARA PAREDES INTERNAS COM PLACAS TIPO PASTILHA DE DIMENSÕES 5 X 5 CM (PLACAS DE 30 X 30 CM) CM APLICADAS A MEIA ALTURA DAS PAREDES. AF_02/2023 | D50: SINAPI | E50: M2 | F50: 240.04 | G50: 218.41 | H50: =(F50*G50) -> 52427.136 | Q50: =TRUNC(P50*F50,2) -> 0 | R50: =TRUNC(Q50*G50) -> 0 | T50: 72.01 | U50: =TRUNC(G50*T50)+0 -> 15727 | V50: 1 | W50: =TRUNC(V50*F50,2) -> 240.04 | X50: 36700.13 | Y50: =Z50/F50 -> 0 | AA50: =TRUNC(Z50*G50)+0 -> 0 | AB50: =AC50/F50 -> 0 | AD50: =TRUNC(AC50*G50) -> 0 | AE50: =AF50/F50 -> 0 | AG50: =TRUNC(AF50*G50) -> 0 | AH50: =SUM(J50,M50,P50,V50,Y50,AB50,AE50) -> 1 | AI50: =SUM(K50,N50,Q50,W50,Z50,T50,AC50) -> 312.05 | AJ50: =SUM(L50,O50,R50,X50,AA50,U50,AD50,AG50) -> 52427.13 | AK50: =IF(AH50=100%,"ITEM FINALIZADO",AH50) -> ITEM FINALIZADO
A51: 5.4 | B51: 87262 | C51: REVESTIMENTO CERÂMICO PARA PISO COM PLACAS TIPO PORCELANATO DE DIMENSÕES 60X60 CM APLICADA EM AMBIENTES DE ÁREA ENTRE 5 M² E 10 M². AF 02/2023 PE | D51: SINAPI | E51: M2 | F51: 92.76 | G51: 167.68 | H51: =(F51*G51) -> 15553.997 | U51: =TRUNC(G51*T51)+0 -> 0 | V51: 0 | W51: =TRUNC(V51*F51,2) -> 0 | X51: =TRUNC(W51*G51)+0 -> 0 | Y51: =Z51/F51 -> 0 | AA51: =TRUNC(Z51*G51)+0 -> 0 | AB51: =AC51/F51 -> 0 | AD51: =TRUNC(AC51*G51) -> 0 | AE51: =AF51/F51 -> 1 | AF51: 92.76 | AG51: =TRUNC(AF51*G51) -> 15553 | AH51: =SUM(J51,M51,P51,V51,Y51,AB51,AE51) -> 1 | AI51: =SUM(K51,N51,Q51,W51,Z51,T51,AC51) -> 0 | AJ51: =SUM(L51,O51,R51,X51,AA51,U51,AD51,AG51) -> 15553 | AK51: =IF(AH51=100%,"ITEM FINALIZADO",AH51) -> ITEM FINALIZADO
A52: 6 | B52: PISO | H52: =SUM(H53:H54) -> 67783.043
A53: 6.1 | B53: 87298 | C53: ARGAMASSA TRAÇO 1:3 (EM VOLUME DE CIMENTO E AREIA MÉDIA ÚMIDA) PARA CONTRAPISO, PREPARO MECANICO COM BETONEIRA 400 L. AF 08/2019 | D53: SINAPI | E53: M3 | F53: 16.97 | G53: 578.78 | H53: =(F53*G53)-0.01 -> 9821.8866 | S53: 0 | T53: 8.48 | U53: =TRUNC(G53*T53)+0 -> 4908 | V53: 1 | W53: =TRUNC(V53*F53,2) -> 16.97 | X53: 4913.89 | Y53: =Z53/F53 -> 0 | AA53: =TRUNC(Z53*G53)+0 -> 0 | AB53: =AC53/F53 -> 0 | AD53: =TRUNC(AC53*G53) -> 0 | AE53: =AF53/F53 -> 0 | AG53: =TRUNC(AF53*G53) -> 0 | AH53: =SUM(J53,M53,P53,V53,Y53,AB53,AE53) -> 1 | AI53: =SUM(K53,N53,Q53,W53,Z53,T53,AC53) -> 25.45 | AJ53: =SUM(L53,O53,R53,X53,AA53,U53,AD53,AG53) -> 9821.89 | AK53: =IF(AH53=100%,"ITEM FINALIZADO",AH53) -> ITEM FINALIZADO
A54: 6.2 | B54: 104597 | C54: REVESTIMENTO CERÂMICO PARA PISO COM PLACAS TIPO PORCELANATO DE DIMENSOES 80X80 CM APLICADA EM AMBIENTES DE AREA ENTRE 556 E 10 M'. AF 022023 PE | D54: SINAPI | E54: M2 | F54: 339.53 | G54: 170.71 | H54: =(F54*G54)-0.01 -> 57961.156 | U54: =TRUNC(G54*T54)+0 -> 0 | W54: =TRUNC(V54*F54,2) -> 0 | X54: =TRUNC(W54*G54)+0 -> 0 | Y54: =Z54/F54 -> 0 | AA54: =TRUNC(Z54*G54)+0 -> 0 | AB54: =AC54/F54 -> 0 | AD54: =TRUNC(AC54*G54) -> 0 | AE54: =AF54/F54 -> 0.73336936 | AF54: ='MEMORIAL DE CALCULO'!BY95 -> 249.0009 | AG54: =TRUNC(AF54*G54) -> 42506 | AH54: =SUM(J54,M54,P54,V54,Y54,AB54,AE54) -> 0.73336936 | AI54: =SUM(K54,N54,Q54,W54,Z54,T54,AC54) -> 0 | AJ54: =SUM(L54,O54,R54,X54,AA54,U54,AD54,AG54) -> 42506
A55: 7 | B55: INSTALAÇÕES SANITÁRIAS | H55: =SUM(H56,H71) -> 45511.361
A56: 7.1 | B56: SANITÁRIA | H56: =SUM(H57:H70) -> 16853.64
A57: 7.1.1 | B57: 86931 | C57: VASO SANITARIO SIFONADO COM CAIXA ACOPLADA LOUÇA BRANCA, INCLUSO ENGATE FLEXÍVEL EM PLASTICO BRANCO, 1/2 X 40CM - FORNECIMENTO E INSTALAÇÃO. AF_01/2020 | D57: SINAPI | E57: UNID | F57: 10 | G57: 453.87 | H57: =(F57*G57) -> 4538.7 | U57: =TRUNC(G57*T57)+0 -> 0 | W57: =TRUNC(V57*F57,2) -> 0 | X57: =TRUNC(W57*G57)+0 -> 0 | Y57: =Z57/F57 -> 0 | AA57: =TRUNC(Z57*G57)+0 -> 0 | AB57: =AC57/F57 -> 0 | AD57: =TRUNC(AC57*G57) -> 0 | AE57: =AF57/F57 -> 0 | AG57: =TRUNC(AF57*G57) -> 0 | AH57: =SUM(J57,M57,P57,V57,Y57,AB57,AE57) -> 0 | AI57: =SUM(K57,N57,Q57,W57,Z57,T57,AC57) -> 0 | AJ57: =SUM(L57,O57,R57,X57,AA57,U57,AD57,AG57) -> 0 | AK57: =IF(AH57=100%,"ITEM FINALIZADO",AH57) -> 0
A58: 7.1.2 | B58: 86939 | C58: LAVATÓRIO LOUÇA BRANCA COM COLUNA, *44 X 35,5* CM, PADRÃO POPULAR, INCLUSO SIFAO FLEXÍVEL EM PVC, VALVULA E ENGATE FLEXÍVEL 30CM EM PLASTICO E COM TORNEIRA CROMADA PADRAO POPULAR-FORNECIMENTO E INSTALAÇÃO. AF_01/2020 | D58: SINAPI | E58: UNID | F58: 10 | G58: 384.59 | H58: =(F58*G58) -> 3845.9 | U58: =TRUNC(G58*T58)+0 -> 0 | W58: =TRUNC(V58*F58,2) -> 0 | X58: =TRUNC(W58*G58)+0 -> 0 | Y58: =Z58/F58 -> 0 | AA58: =TRUNC(Z58*G58)+0 -> 0 | AB58: =AC58/F58 -> 0 | AD58: =TRUNC(AC58*G58) -> 0 | AE58: =AF58/F58 -> 0 | AG58: =TRUNC(AF58*G58) -> 0 | AH58: =SUM(J58,M58,P58,V58,Y58,AB58,AE58) -> 0 | AI58: =SUM(K58,N58,Q58,W58,Z58,T58,AC58) -> 0 | AJ58: =SUM(L58,O58,R58,X58,AA58,U58,AD58,AG58) -> 0 | AK58: =IF(AH58=100%,"ITEM FINALIZADO",AH58) -> 0
A59: 7.1.3 | B59: 89714 | C59: TUBO PVC, SERIE NORMAL, ESGOTO PREDIAL, DN 100 MM, FORNECIDO E INSTALADO EM RAMAL DE DESCARGA OU RAMAL DE ESGOTO SANITARIO. AF 08/2022 | D59: SINAPI | E59: M | F59: 100 | G59: 34.63 | H59: =(F59*G59) -> 3463 | P59: 0.8 | Q59: =TRUNC(P59*F59,2) -> 80 | R59: =TRUNC(Q59*G59) -> 2770 | T59: 20 | U59: =TRUNC(G59*T59)+0 -> 692 | V59: 0.2 | W59: =TRUNC(V59*F59,2) -> 20 | X59: 0 | Y59: =Z59/F59 -> 0 | AA59: =TRUNC(Z59*G59)+0 -> 0 | AB59: =AC59/F59 -> 0 | AD59: =TRUNC(AC59*G59) -> 0 | AE59: =AF59/F59 -> 0 | AG59: =TRUNC(AF59*G59) -> 0 | AH59: =SUM(J59,M59,P59,V59,Y59,AB59,AE59) -> 1 | AI59: =SUM(K59,N59,Q59,W59,Z59,T59,AC59) -> 120 | AJ59: =SUM(L59,O59,R59,X59,AA59,U59,AD59,AG59) -> 3462 | AK59: =IF(AH59=100%,"ITEM FINALIZADO",AH59) -> ITEM FINALIZADO
A60: 7.1.4 | B60: 89711 | C60: TUBO PVC, SERIE NORMAL, ESGOTO PREDIAL, DN 40 MM, FORNECIDO E INSTALADO EM RAMAL DE DESCARGA OU RAMAL DE ESGOTO SANITARIO. AF 08/2022 | D60: SINAPI | E60: M | F60: 20 | G60: 20.06 | H60: =(F60*G60) -> 401.2 | P60: 0.8 | Q60: =TRUNC(P60*F60,2) -> 16 | R60: =TRUNC(Q60*G60) -> 320 | T60: 4 | U60: =TRUNC(G60*T60)+0 -> 80 | V60: 0.2 | W60: =TRUNC(V60*F60,2) -> 4 | X60: 0 | Y60: =Z60/F60 -> 0 | AA60: =TRUNC(Z60*G60)+0 -> 0 | AB60: =AC60/F60 -> 0 | AD60: =TRUNC(AC60*G60) -> 0 | AE60: =AF60/F60 -> 0 | AG60: =TRUNC(AF60*G60) -> 0 | AH60: =SUM(J60,M60,P60,V60,Y60,AB60,AE60) -> 1 | AI60: =SUM(K60,N60,Q60,W60,Z60,T60,AC60) -> 24 | AJ60: =SUM(L60,O60,R60,X60,AA60,U60,AD60,AG60) -> 400 | AK60: =IF(AH60=100%,"ITEM FINALIZADO",AH60) -> ITEM FINALIZADO
A61: 7.1.5 | B61: 89798 | C61: TUBO PVC, SERIE NORMAL, ESGOTO PREDIAL, DN 50 MM, FORNECIDO E INSTALADO EM PRUMADA DE ESGOTO SANITARIO OU VENTILAÇÃO. AF 08/2022 | D61: SINAPI | E61: M | F61: 65 | G61: 11.08 | H61: =(F61*G61) -> 720.2 | P61: 0.8 | Q61: =TRUNC(P61*F61,2) -> 52 | R61: =TRUNC(Q61*G61) -> 576 | U61: =TRUNC(G61*T61)+0 -> 0 | W61: =TRUNC(V61*F61,2) -> 0 | X61: =TRUNC(W61*G61)+0 -> 0 | Y61: =Z61/F61 -> 0.2 | Z61: 13 | AA61: =TRUNC(Z61*G61)+0 -> 144 | AB61: =AC61/F61 -> 0 | AD61: =TRUNC(AC61*G61) -> 0 | AE61: =AF61/F61 -> 0 | AG61: =TRUNC(AF61*G61) -> 0 | AH61: =SUM(J61,M61,P61,V61,Y61,AB61,AE61) -> 1 | AI61: =SUM(K61,N61,Q61,W61,Z61,T61,AC61) -> 65 | AJ61: =SUM(L61,O61,R61,X61,AA61,U61,AD61,AG61) -> 720 | AK61: =IF(AH61=100%,"ITEM FINALIZADO",AH61) -> ITEM FINALIZADO
A62: 7.1.6 | B62: 104326 | C62: RALO SECO CONICO, PVC, DN 100 X 40 MM, JUNTA SOLDAVEL, FORNECIDO E INSTALADO EM RAMAL DE DESCARGA OU EM RAMAL DE ESGOTO SANITARIO. AF 08/2022 | D62: SINAPI | E62: UNID | F62: 10 | G62: 19.2 | H62: =(F62*G62) -> 192 | U62: =TRUNC(G62*T62)+0 -> 0 | W62: =TRUNC(V62*F62,2) -> 0 | X62: =TRUNC(W62*G62)+0 -> 0 | Y62: =Z62/F62 -> 0 | AA62: =TRUNC(Z62*G62)+0 -> 0 | AB62: =AC62/F62 -> 0 | AD62: =TRUNC(AC62*G62) -> 0 | AE62: =AF62/F62 -> 0 | AG62: =TRUNC(AF62*G62) -> 0 | AH62: =SUM(J62,M62,P62,V62,Y62,AB62,AE62) -> 0 | AI62: =SUM(K62,N62,Q62,W62,Z62,T62,AC62) -> 0 | AJ62: =SUM(L62,O62,R62,X62,AA62,U62,AD62,AG62) -> 0 | AK62: =IF(AH62=100%,"ITEM FINALIZADO",AH62) -> 0
A63: 7.1.7 | B63: 104327 | C63: RALO SIFONADO REDONDO, PVC, DN 100 X 40 MM, JUNTA SOLDAVEL, FORNECIDO E INSTALADO EM RAMAL DE DESCARGA OU EM RAMAL DE ESGOTO SANITARIO. AF 08/2022 | D63: SINAPI | E63: UNID | F63: 10 | G63: 18.32 | H63: =(F63*G63) -> 183.2 | U63: =TRUNC(G63*T63)+0 -> 0 | W63: =TRUNC(V63*F63,2) -> 0 | X63: =TRUNC(W63*G63)+0 -> 0 | Y63: =Z63/F63 -> 0 | AA63: =TRUNC(Z63*G63)+0 -> 0 | AB63: =AC63/F63 -> 0 | AD63: =TRUNC(AC63*G63) -> 0 | AE63: =AF63/F63 -> 0 | AG63: =TRUNC(AF63*G63) -> 0 | AH63: =SUM(J63,M63,P63,V63,Y63,AB63,AE63) -> 0 | AI63: =SUM(K63,N63,Q63,W63,Z63,T63,AC63) -> 0 | AJ63: =SUM(L63,O63,R63,X63,AA63,U63,AD63,AG63) -> 0 | AK63: =IF(AH63=100%,"ITEM FINALIZADO",AH63) -> 0
A64: 7.1.8 | B64: 89726 | C64: JOELHO 45 GRAUS, PVC, SERIE NORMAL, ESGOTO PREDIAL, DN 40 MM, JUNTA SOLDAVEL, FORNECIDO E INSTALADO EM RAMAL DE DESCARGA OU RAMAL DE ESGOTO SANITARIO. AF 08/2022 | D64: SINAPI | E64: UNID | F64: 7 | G64: 9.43 | H64: =(F64*G64) -> 66.01 | P64: 0.8 | Q64: =TRUNC(P64*F64,2) -> 5.6 | R64: =TRUNC(Q64*G64) -> 52 | T64: 1.4 | U64: =TRUNC(G64*T64)+0 -> 13 | V64: 0.2 | W64: =TRUNC(V64*F64,2) -> 1.4 | X64: 0 | Y64: =Z64/F64 -> 0 | AA64: =TRUNC(Z64*G64)+0 -> 0 | AB64: =AC64/F64 -> 0 | AD64: =TRUNC(AC64*G64) -> 0 | AE64: =AF64/F64 -> 0 | AG64: =TRUNC(AF64*G64) -> 0 | AH64: =SUM(J64,M64,P64,V64,Y64,AB64,AE64) -> 1 | AI64: =SUM(K64,N64,Q64,W64,Z64,T64,AC64) -> 8.4 | AJ64: =SUM(L64,O64,R64,X64,AA64,U64,AD64,AG64) -> 65 | AK64: =IF(AH64=100%,"ITEM FINALIZADO",AH64) -> ITEM FINALIZADO
A65: 7.1.9 | B65: 89732 | C65: JOELHO 45 GRAUS, PVC, SERIE NORMAL, ESGOTO PREDIAL, DN 50 MM, JUNTA ELASTICA, FORNECIDO E INSTALADO EM RAMAL DE DESCARGA OU RAMAL DE ESGOTO SANITARIO. AF 08/2022 | D65: SINAPI | E65: UNID | F65: 7 | G65: 14.36 | H65: =(F65*G65) -> 100.52 | P65: 0.8 | Q65: =TRUNC(P65*F65,2) -> 5.6 | R65: =TRUNC(Q65*G65) -> 80 | T65: 1.4 | U65: =TRUNC(G65*T65)+0 -> 20 | V65: 0.2 | W65: =TRUNC(V65*F65,2) -> 1.4 | X65: 0 | Y65: =Z65/F65 -> 0 | AA65: =TRUNC(Z65*G65)+0 -> 0 | AB65: =AC65/F65 -> 0 | AD65: =TRUNC(AC65*G65) -> 0 | AE65: =AF65/F65 -> 0 | AG65: =TRUNC(AF65*G65) -> 0 | AH65: =SUM(J65,M65,P65,V65,Y65,AB65,AE65) -> 1 | AI65: =SUM(K65,N65,Q65,W65,Z65,T65,AC65) -> 8.4 | AJ65: =SUM(L65,O65,R65,X65,AA65,U65,AD65,AG65) -> 100 | AK65: =IF(AH65=100%,"ITEM FINALIZADO",AH65) -> ITEM FINALIZADO
A66: 7.1.10 | B66: 89809 | C66: JOELHO 90 GRAUS, PVC, SERIE NORMAL, ESGOTO PREDIAL, DN 100 MM, JUNTA ELASTICA, FORNECIDO E INSTALADO EM PRUMADA DE ESGOTO SANITARIO OU VENTILACAO. AF_08/2022 | D66: SINAPI | E66: UNID | F66: 10 | G66: 25.87 | H66: =(F66*G66) -> 258.7 | P66: 0.8 | Q66: =TRUNC(P66*F66,2) -> 8 | R66: =TRUNC(Q66*G66) -> 206 | T66: 2 | U66: =TRUNC(G66*T66)+0 -> 51 | V66: 0.2 | W66: =TRUNC(V66*F66,2) -> 2 | X66: 0 | Y66: =Z66/F66 -> 0 | AA66: =TRUNC(Z66*G66)+0 -> 0 | AB66: =AC66/F66 -> 0 | AD66: =TRUNC(AC66*G66) -> 0 | AE66: =AF66/F66 -> 0 | AG66: =TRUNC(AF66*G66) -> 0 | AH66: =SUM(J66,M66,P66,V66,Y66,AB66,AE66) -> 1 | AI66: =SUM(K66,N66,Q66,W66,Z66,T66,AC66) -> 12 | AJ66: =SUM(L66,O66,R66,X66,AA66,U66,AD66,AG66) -> 257 | AK66: =IF(AH66=100%,"ITEM FINALIZADO",AH66) -> ITEM FINALIZADO
A67: 7.1.11 | B67: 69810 | C67: JOELHO 45 GRAUS, PVC, SERIE NORMAL, ESGOTO PREDIAL, DN 100 MM, JUNTA ELASTICA, FORNECIDO E INSTALADO EM PRUMADA DE ESGOTO SANITARIO OU VENTILACAO. AF_08/2022 | D67: SINAPI | E67: UNID | F67: 6 | G67: 26.53 | H67: =(F67*G67) -> 159.18 | P67: 0.8 | Q67: =TRUNC(P67*F67,2) -> 4.8 | R67: =TRUNC(Q67*G67) -> 127 | T67: 1.2 | U67: =TRUNC(G67*T67)+0 -> 31 | V67: 0.2 | W67: =TRUNC(V67*F67,2) -> 1.2 | X67: 0 | Y67: =Z67/F67 -> 0 | AA67: =TRUNC(Z67*G67)+0 -> 0 | AB67: =AC67/F67 -> 0 | AD67: =TRUNC(AC67*G67) -> 0 | AE67: =AF67/F67 -> 0 | AG67: =TRUNC(AF67*G67) -> 0 | AH67: =SUM(J67,M67,P67,V67,Y67,AB67,AE67) -> 1 | AI67: =SUM(K67,N67,Q67,W67,Z67,T67,AC67) -> 7.2 | AJ67: =SUM(L67,O67,R67,X67,AA67,U67,AD67,AG67) -> 158 | AK67: =IF(AH67=100%,"ITEM FINALIZADO",AH67) -> ITEM FINALIZADO
A68: 7.1.12 | B68: 100864 | C68: BARRA DE APOIO EM "L", EM ACO INOX POLIDO 80 X 80 CM, FIXADA NA PAREDE - FORNECIMENTO E INSTALAÇÃO. AF 01/2020 | D68: SINAPI | E68: UNID | F68: 4 | G68: 632.21 | H68: =(F68*G68) -> 2528.84 | U68: =TRUNC(G68*T68)+0 -> 0 | W68: =TRUNC(V68*F68,2) -> 0 | X68: =TRUNC(W68*G68)+0 -> 0 | Y68: =Z68/F68 -> 0 | AA68: =TRUNC(Z68*G68)+0 -> 0 | AB68: =AC68/F68 -> 0 | AD68: =TRUNC(AC68*G68) -> 0 | AE68: =AF68/F68 -> 0 | AG68: =TRUNC(AF68*G68) -> 0 | AH68: =SUM(J68,M68,P68,V68,Y68,AB68,AE68) -> 0 | AI68: =SUM(K68,N68,Q68,W68,Z68,T68,AC68) -> 0 | AJ68: =SUM(L68,O68,R68,X68,AA68,U68,AD68,AG68) -> 0 | AK68: =IF(AH68=100%,"ITEM FINALIZADO",AH68) -> 0
A69: 7.1.13 | B69: 89833 | C69: TE, PVC, SERIE NORMAL, ESGOTO PREDIAL, DN 100 X 100 MM, JUNTA ELASTICA, FORNECIDO E INSTALADO EM PRUMADA DE ESGOTO SANITARIO OU VENTILAÇÃO. AF_08/2022 | D69: SINAPI | E69: UNID | F69: 3 | G69: 39.81 | H69: =(F69*G69) -> 119.43 | P69: 0.8 | Q69: =TRUNC(P69*F69,2) -> 2.4 | R69: =TRUNC(Q69*G69) -> 95 | T69: 0.6 | U69: =TRUNC(G69*T69)+0 -> 23 | V69: 0.2 | W69: =TRUNC(V69*F69,2) -> 0.6 | X69: 0 | Y69: =Z69/F69 -> 0 | AA69: =TRUNC(Z69*G69)+0 -> 0 | AB69: =AC69/F69 -> 0 | AD69: =TRUNC(AC69*G69) -> 0 | AE69: =AF69/F69 -> 0 | AG69: =TRUNC(AF69*G69) -> 0 | AH69: =SUM(J69,M69,P69,V69,Y69,AB69,AE69) -> 1 | AI69: =SUM(K69,N69,Q69,W69,Z69,T69,AC69) -> 3.6 | AJ69: =SUM(L69,O69,R69,X69,AA69,U69,AD69,AG69) -> 118 | AK69: =IF(AH69=100%,"ITEM FINALIZADO",AH69) -> ITEM FINALIZADO
A70: 7.1.14 | B70: 102711 | C70: JUNÇÃO DUPLA DE PVC, SERIE NORMAL, PARA ESGOTO PREDIAL, DN 100 X 100 X 100 MM, INSTALADA EM DRENO - FORNECIMENTO E INSTALAÇÃO. AF 07/2021 | D70: SINAPI | E70: UNID | F70: 4 | G70: 69.19 | H70: =(F70*G70) -> 276.76 | P70: 0.8 | Q70: =TRUNC(P70*F70,2) -> 3.2 | R70: =TRUNC(Q70*G70) -> 221 | T70: 0.8 | U70: =TRUNC(G70*T70)+0 -> 55 | V70: 0.2 | W70: =TRUNC(V70*F70,2) -> 0.8 | X70: 0 | Y70: =Z70/F70 -> 0 | AA70: =TRUNC(Z70*G70)+0 -> 0 | AB70: =AC70/F70 -> 0 | AD70: =TRUNC(AC70*G70) -> 0 | AE70: =AF70/F70 -> 0 | AG70: =TRUNC(AF70*G70) -> 0 | AH70: =SUM(J70,M70,P70,V70,Y70,AB70,AE70) -> 1 | AI70: =SUM(K70,N70,Q70,W70,Z70,T70,AC70) -> 4.8 | AJ70: =SUM(L70,O70,R70,X70,AA70,U70,AD70,AG70) -> 276 | AK70: =IF(AH70=100%,"ITEM FINALIZADO",AH70) -> ITEM FINALIZADO
A71: 7.2 | B71: HIDRÁULICA | H71: =SUM(H72:H90) -> 28657.721
A72: 7.2.1 | B72: 102616 | C72: CAIXA D'AGUA EM POLIESTER REFORCADO COM FIBRA DE VIDRO, 3000 LITROS - FORNECIMENTO E INSTALAÇÃO. AF_06/2021 | D72: SINAPI | E72: UNID | F72: 2 | G72: 1826.49 | H72: =(F72*G72) -> 3652.98 | U72: =TRUNC(G72*T72)+0 -> 0 | W72: =TRUNC(V72*F72,2) -> 0 | X72: =TRUNC(W72*G72)+0 -> 0 | Y72: =Z72/F72 -> 0 | AA72: =TRUNC(Z72*G72)+0 -> 0 | AB72: =AC72/F72 -> 1 | AC72: 2 | AD72: =TRUNC(AC72*G72) -> 3652 | AE72: =AF72/F72 -> 0 | AG72: =TRUNC(AF72*G72) -> 0 | AH72: =SUM(J72,M72,P72,V72,Y72,AB72,AE72) -> 1 | AI72: =SUM(K72,N72,Q72,W72,Z72,T72,AC72) -> 2 | AJ72: =SUM(L72,O72,R72,X72,AA72,U72,AD72,AG72) -> 3652 | AK72: =IF(AH72=100%,"ITEM FINALIZADO",AH72) -> ITEM FINALIZADO
A73: 7.2.2 | B73: 89446 | C73: TUBO, PVC, SOLDAVEL, DN 25MM, INSTALADO EM PRUMADA DE ÁGUA - FORNECIMENTO E INSTALAÇÃO. AF 06/2022 | D73: SINAPI | E73: M | F73: 100 | G73: 4.93 | H73: =(F73*G73) -> 493 | U73: =TRUNC(G73*T73)+0 -> 0 | W73: =TRUNC(V73*F73,2) -> 0 | X73: =TRUNC(W73*G73)+0 -> 0 | Y73: =Z73/F73 -> 0 | AA73: =TRUNC(Z73*G73)+0 -> 0 | AB73: =AC73/F73 -> 1 | AC73: 100 | AD73: =TRUNC(AC73*G73) -> 493 | AE73: =AF73/F73 -> 0 | AG73: =TRUNC(AF73*G73) -> 0 | AH73: =SUM(J73,M73,P73,V73,Y73,AB73,AE73) -> 1 | AI73: =SUM(K73,N73,Q73,W73,Z73,T73,AC73) -> 100 | AJ73: =SUM(L73,O73,R73,X73,AA73,U73,AD73,AG73) -> 493 | AK73: =IF(AH73=100%,"ITEM FINALIZADO",AH73) -> ITEM FINALIZADO
A74: 7.2.3 | B74: 89366 | C74: JOELHO 90 GRAUS COM BUCHA DE LATAO, PVC, SOLDAVEL, DN 25MM, X 3/4 INSTALADO EM RAMAL OU SUB-RAMAL DE ÁGUA - FORNECIMENTO E INSTALAÇÃO. AF 06/2022 | D74: SINAPI | E74: UNID | F74: 10 | G74: 15.08 | H74: =(F74*G74) -> 150.8 | U74: =TRUNC(G74*T74)+0 -> 0 | W74: =TRUNC(V74*F74,2) -> 0 | X74: =TRUNC(W74*G74)+0 -> 0 | Y74: =Z74/F74 -> 0 | AA74: =TRUNC(Z74*G74)+0 -> 0 | AB74: =AC74/F74 -> 1 | AC74: 10 | AD74: =TRUNC(AC74*G74) -> 150 | AE74: =AF74/F74 -> 0 | AG74: =TRUNC(AF74*G74) -> 0 | AH74: =SUM(J74,M74,P74,V74,Y74,AB74,AE74) -> 1 | AI74: =SUM(K74,N74,Q74,W74,Z74,T74,AC74) -> 10 | AJ74: =SUM(L74,O74,R74,X74,AA74,U74,AD74,AG74) -> 150 | AK74: =IF(AH74=100%,"ITEM FINALIZADO",AH74) -> ITEM FINALIZADO
A75: 7.2.4 | B75: 89355 | C75: TUBO, PVC, SOLDAVEL, DN 20MM, INSTALADO EM RAMAL OU SUB-RAMAL DE ÁGUA - FORNECIMENTO E INSTALAÇÃO. AF_06/2022 | D75: SINAPI | E75: M | F75: 8 | G75: 19.97 | H75: =(F75*G75) -> 159.76 | U75: =TRUNC(G75*T75)+0 -> 0 | W75: =TRUNC(V75*F75,2) -> 0 | X75: =TRUNC(W75*G75)+0 -> 0 | Y75: =Z75/F75 -> 0 | AA75: =TRUNC(Z75*G75)+0 -> 0 | AB75: =AC75/F75 -> 1 | AC75: 8 | AD75: =TRUNC(AC75*G75) -> 159 | AE75: =AF75/F75 -> 0 | AG75: =TRUNC(AF75*G75) -> 0 | AH75: =SUM(J75,M75,P75,V75,Y75,AB75,AE75) -> 1 | AI75: =SUM(K75,N75,Q75,W75,Z75,T75,AC75) -> 8 | AJ75: =SUM(L75,O75,R75,X75,AA75,U75,AD75,AG75) -> 159 | AK75: =IF(AH75=100%,"ITEM FINALIZADO",AH75) -> ITEM FINALIZADO
A76: 7.2.5 | B76: 100860 | C76: CHUVEIRO ELÉTRICO COMUM CORPO PLASTICO, TIPO DUCHA - FORNECIMENTO E INSTALAÇÃO. AF 01/2020 | D76: SINAPI | E76: UNID | F76: 9 | G76: 96.06 | H76: =(F76*G76) -> 864.54 | U76: =TRUNC(G76*T76)+0 -> 0 | W76: =TRUNC(V76*F76,2) -> 0 | X76: =TRUNC(W76*G76)+0 -> 0 | Y76: =Z76/F76 -> 0 | AA76: =TRUNC(Z76*G76)+0 -> 0 | AB76: =AC76/F76 -> 1 | AC76: 9 | AD76: =TRUNC(AC76*G76) -> 864 | AE76: =AF76/F76 -> 0 | AG76: =TRUNC(AF76*G76) -> 0 | AH76: =SUM(J76,M76,P76,V76,Y76,AB76,AE76) -> 1 | AI76: =SUM(K76,N76,Q76,W76,Z76,T76,AC76) -> 9 | AJ76: =SUM(L76,O76,R76,X76,AA76,U76,AD76,AG76) -> 864 | AK76: =IF(AH76=100%,"ITEM FINALIZADO",AH76) -> ITEM FINALIZADO
A77: 7.2.6 | B77: 89528 | C77: LUVA, PVC, SOLDAVEL, DN 25MM, INSTALADO EM PRUMADA DE ÁGUA - FORNECIMENTO E INSTALAÇÃO. AF 06/2022 | D77: SINAPI | E77: UNID | F77: 20 | G77: 3.83 | H77: =(F77*G77) -> 76.6 | U77: =TRUNC(G77*T77)+0 -> 0 | W77: =TRUNC(V77*F77,2) -> 0 | X77: =TRUNC(W77*G77)+0 -> 0 | Y77: =Z77/F77 -> 0 | AA77: =TRUNC(Z77*G77)+0 -> 0 | AB77: =AC77/F77 -> 1 | AC77: 20 | AD77: =TRUNC(AC77*G77) -> 76 | AE77: =AF77/F77 -> 0 | AG77: =TRUNC(AF77*G77) -> 0 | AH77: =SUM(J77,M77,P77,V77,Y77,AB77,AE77) -> 1 | AI77: =SUM(K77,N77,Q77,W77,Z77,T77,AC77) -> 20 | AJ77: =SUM(L77,O77,R77,X77,AA77,U77,AD77,AG77) -> 76 | AK77: =IF(AH77=100%,"ITEM FINALIZADO",AH77) -> ITEM FINALIZADO
A78: 7.2.7 | B78: 104199 | C78: JOELHO 90 GRAUS, PPR, DN 20 MM, INSTALADO EM RAMAL OU SUB - RAMAL DE ÁGUA - FORNECIMENTO E INSTALAÇÃO. AF_082022 | D78: SINAPI | E78: UNID | F78: 5 | G78: 7.02 | H78: =(F78*G78) -> 35.1 | U78: =TRUNC(G78*T78)+0 -> 0 | W78: =TRUNC(V78*F78,2) -> 0 | X78: =TRUNC(W78*G78)+0 -> 0 | Y78: =Z78/F78 -> 0 | AA78: =TRUNC(Z78*G78)+0 -> 0 | AB78: =AC78/F78 -> 1 | AC78: 5 | AD78: =TRUNC(AC78*G78) -> 35 | AE78: =AF78/F78 -> 0 | AG78: =TRUNC(AF78*G78) -> 0 | AH78: =SUM(J78,M78,P78,V78,Y78,AB78,AE78) -> 1 | AI78: =SUM(K78,N78,Q78,W78,Z78,T78,AC78) -> 5 | AJ78: =SUM(L78,O78,R78,X78,AA78,U78,AD78,AG78) -> 35 | AK78: =IF(AH78=100%,"ITEM FINALIZADO",AH78) -> ITEM FINALIZADO
A79: 7.2.8 | B79: 101964 | C79: LAJE PRE-MOLDADA UNIDIRECIONAL, BIAPOIADA, PARA FORRO, ENCHIMENTO EM CERÂMICA, VIGOTA CONVENCIONAL, ALTURA TOTAL DA LAJE (ENCHIMENTO+CAPA) = (8+3). AF_11/2020_PA | D79: SINAPI | E79: M2 | F79: 9 | G79: 152.7 | H79: =(F79*G79) -> 1374.3 | U79: =TRUNC(G79*T79)+0 -> 0 | W79: =TRUNC(V79*F79,2) -> 0 | X79: =TRUNC(W79*G79)+0 -> 0 | Y79: =Z79/F79 -> 0 | AA79: =TRUNC(Z79*G79)+0 -> 0 | AB79: =AC79/F79 -> 0 | AD79: =TRUNC(AC79*G79) -> 0 | AE79: =AF79/F79 -> 0 | AG79: =TRUNC(AF79*G79) -> 0 | AH79: =SUM(J79,M79,P79,V79,Y79,AB79,AE79) -> 0 | AI79: =SUM(K79,N79,Q79,W79,Z79,T79,AC79) -> 0 | AJ79: =SUM(L79,O79,R79,X79,AA79,U79,AD79,AG79) -> 0 | AK79: =IF(AH79=100%,"ITEM FINALIZADO",AH79) -> 0
A80: 7.2.9 | B80: 95545 | C80: SABONETEIRA DE PAREDE EM METAL CROMADO, INCLUSO FIXAÇÃO. AF 01/2020 | D80: SINAPI | E80: UNID | F80: 9 | G80: 33.31 | H80: =(F80*G80) -> 299.79 | U80: =TRUNC(G80*T80)+0 -> 0 | W80: =TRUNC(V80*F80,2) -> 0 | X80: =TRUNC(W80*G80)+0 -> 0 | Y80: =Z80/F80 -> 0 | AA80: =TRUNC(Z80*G80)+0 -> 0 | AB80: =AC80/F80 -> 0 | AD80: =TRUNC(AC80*G80) -> 0 | AE80: =AF80/F80 -> 0 | AG80: =TRUNC(AF80*G80) -> 0 | AH80: =SUM(J80,M80,P80,V80,Y80,AB80,AE80) -> 0 | AI80: =SUM(K80,N80,Q80,W80,Z80,T80,AC80) -> 0 | AJ80: =SUM(L80,O80,R80,X80,AA80,U80,AD80,AG80) -> 0 | AK80: =IF(AH80=100%,"ITEM FINALIZADO",AH80) -> 0
A81: 7.2.10 | B81: 95547 | C81: SABONETEIRA PLÁSTICA TIPO DISPENSER PARA SABONETE LIQUIDO COM RESERVATÓRIO 600 A 1500 ML, INCLUSO FIXAÇÃO. AF_01/2020 | D81: SINAPI | E81: UNID | F81: 10 | G81: 91.61 | H81: =(F81*G81) -> 916.1 | U81: =TRUNC(G81*T81)+0 -> 0 | W81: =TRUNC(V81*F81,2) -> 0 | X81: =TRUNC(W81*G81)+0 -> 0 | Y81: =Z81/F81 -> 0 | AA81: =TRUNC(Z81*G81)+0 -> 0 | AB81: =AC81/F81 -> 0 | AD81: =TRUNC(AC81*G81) -> 0 | AE81: =AF81/F81 -> 0 | AG81: =TRUNC(AF81*G81) -> 0 | AH81: =SUM(J81,M81,P81,V81,Y81,AB81,AE81) -> 0 | AI81: =SUM(K81,N81,Q81,W81,Z81,T81,AC81) -> 0 | AJ81: =SUM(L81,O81,R81,X81,AA81,U81,AD81,AG81) -> 0 | AK81: =IF(AH81=100%,"ITEM FINALIZADO",AH81) -> 0
A82: 7.2.11 | B82: 95547 | C82: SABONETEIRA PLÁSTICA TIPO DISPENSER PARA SABONETE LIQUIDO COM RESERVATÓRIO 800 A 1500 ML, INCLUSO FIXAÇÃO. AF_01/2020 | D82: SINAPI | E82: UNID | F82: 12 | G82: 91.61 | H82: =(F82*G82) -> 1099.32 | U82: =TRUNC(G82*T82)+0 -> 0 | W82: =TRUNC(V82*F82,2) -> 0 | X82: =TRUNC(W82*G82)+0 -> 0 | Y82: =Z82/F82 -> 0 | AA82: =TRUNC(Z82*G82)+0 -> 0 | AB82: =AC82/F82 -> 0 | AD82: =TRUNC(AC82*G82) -> 0 | AE82: =AF82/F82 -> 0 | AG82: =TRUNC(AF82*G82) -> 0 | AH82: =SUM(J82,M82,P82,V82,Y82,AB82,AE82) -> 0 | AI82: =SUM(K82,N82,Q82,W82,Z82,T82,AC82) -> 0 | AJ82: =SUM(L82,O82,R82,X82,AA82,U82,AD82,AG82) -> 0 | AK82: =IF(AH82=100%,"ITEM FINALIZADO",AH82) -> 0
A83: 7.2.12 | B83: 90373 | C83: JOELHO 90 GRAUS COM BUCHA DE LATÃO, PVC, SOLDÁVEL, DN 25MM, X 1/2 INSTALADO EM RAMAL OU SUB-RAMAL DE ÁGUA - FORNECIMENTO E INSTALAÇÃO. AF 06/2022 | D83: SINAPI | E83: UNID | F83: 10 | G83: 12.1 | H83: =(F83*G83) -> 121 | U83: =TRUNC(G83*T83)+0 -> 0 | W83: =TRUNC(V83*F83,2) -> 0 | X83: =TRUNC(W83*G83)+0 -> 0 | Y83: =Z83/F83 -> 0 | AA83: =TRUNC(Z83*G83)+0 -> 0 | AB83: =AC83/F83 -> 1 | AC83: 10 | AD83: =TRUNC(AC83*G83) -> 121 | AE83: =AF83/F83 -> 0 | AG83: =TRUNC(AF83*G83) -> 0 | AH83: =SUM(J83,M83,P83,V83,Y83,AB83,AE83) -> 1 | AI83: =SUM(K83,N83,Q83,W83,Z83,T83,AC83) -> 10 | AJ83: =SUM(L83,O83,R83,X83,AA83,U83,AD83,AG83) -> 121 | AK83: =IF(AH83=100%,"ITEM FINALIZADO",AH83) -> ITEM FINALIZADO
A84: 7.2.13 | B84: 89985 | C84: REGISTRO DE PRESSÃO BRUTO, LATÃO, ROSCÁVEL, 3/4", COM ACABAMENTO E CANOPLA CROMADOS - FORNECIMENTO E INSTALAÇÃO, AF 08/2021 | D84: SINAPI | E84: UNID | F84: 9 | G84: 91.43 | H84: =(F84*G84) -> 822.87 | U84: =TRUNC(G84*T84)+0 -> 0 | W84: =TRUNC(V84*F84,2) -> 0 | X84: =TRUNC(W84*G84)+0 -> 0 | Y84: =Z84/F84 -> 0 | AA84: =TRUNC(Z84*G84)+0 -> 0 | AB84: =AC84/F84 -> 1 | AC84: 9 | AD84: =TRUNC(AC84*G84) -> 822 | AE84: =AF84/F84 -> 0 | AG84: =TRUNC(AF84*G84) -> 0 | AH84: =SUM(J84,M84,P84,V84,Y84,AB84,AE84) -> 1 | AI84: =SUM(K84,N84,Q84,W84,Z84,T84,AC84) -> 9 | AJ84: =SUM(L84,O84,R84,X84,AA84,U84,AD84,AG84) -> 822 | AK84: =IF(AH84=100%,"ITEM FINALIZADO",AH84) -> ITEM FINALIZADO
A85: 7.2.14 | B85: 86915 | C85: TORNEIRA CROMADA DE MESA, 1/2" OU 3/4", PARA LAVATÓRIO, PADRÃO MÉDIO - FORNECIMENTO E INSTALAÇÃO. AF_01/2020 | D85: SINAPI | E85: UNID | F85: 10 | G85: 126.1 | H85: =(F85*G85) -> 1261 | U85: =TRUNC(G85*T85)+0 -> 0 | W85: =TRUNC(V85*F85,2) -> 0 | X85: =TRUNC(W85*G85)+0 -> 0 | Y85: =Z85/F85 -> 0 | AA85: =TRUNC(Z85*G85)+0 -> 0 | AB85: =AC85/F85 -> 0 | AD85: =TRUNC(AC85*G85) -> 0 | AE85: =AF85/F85 -> 0 | AG85: =TRUNC(AF85*G85) -> 0 | AH85: =SUM(J85,M85,P85,V85,Y85,AB85,AE85) -> 0 | AI85: =SUM(K85,N85,Q85,W85,Z85,T85,AC85) -> 0 | AJ85: =SUM(L85,O85,R85,X85,AA85,U85,AD85,AG85) -> 0 | AK85: =IF(AH85=100%,"ITEM FINALIZADO",AH85) -> 0
A86: 7.2.15 | B86: 86911 | C86: TORNEIRA CROMADA LONGA, DE PAREDE, 1/2" OU 3/4", PARA PIA DE COZINHA. PADRÃO POPULAR - FORNECIMENTO E INSTALAÇÃO. AF 01/2020 | D86: SINAPI | E86: UNID | F86: 1 | G86: 77.43 | H86: =(F86*G86) -> 77.43 | U86: =TRUNC(G86*T86)+0 -> 0 | W86: =TRUNC(V86*F86,2) -> 0 | X86: =TRUNC(W86*G86)+0 -> 0 | Y86: =Z86/F86 -> 0 | AA86: =TRUNC(Z86*G86)+0 -> 0 | AB86: =AC86/F86 -> 0 | AD86: =TRUNC(AC86*G86) -> 0 | AE86: =AF86/F86 -> 0 | AG86: =TRUNC(AF86*G86) -> 0 | AH86: =SUM(J86,M86,P86,V86,Y86,AB86,AE86) -> 0 | AI86: =SUM(K86,N86,Q86,W86,Z86,T86,AC86) -> 0 | AJ86: =SUM(L86,O86,R86,X86,AA86,U86,AD86,AG86) -> 0 | AK86: =IF(AH86=100%,"ITEM FINALIZADO",AH86) -> 0
A87: 7.2.16 | B87: 94497 | C87: REGISTRO DE GAVETA BRUTO, LATÃO, ROSCÁVEL, 1 1/2" - FORNECIMENTO E INSTALAÇÃO. AF 08/2021 | D87: SINAPI | E87: UNID | F87: 9 | G87: 108.06 | H87: =(F87*G87) -> 972.54 | U87: =TRUNC(G87*T87)+0 -> 0 | W87: =TRUNC(V87*F87,2) -> 0 | X87: =TRUNC(W87*G87)+0 -> 0 | Y87: =Z87/F87 -> 0 | AA87: =TRUNC(Z87*G87)+0 -> 0 | AB87: =AC87/F87 -> 1 | AC87: 9 | AD87: =TRUNC(AC87*G87) -> 972 | AE87: =AF87/F87 -> 0 | AG87: =TRUNC(AF87*G87) -> 0 | AH87: =SUM(J87,M87,P87,V87,Y87,AB87,AE87) -> 1 | AI87: =SUM(K87,N87,Q87,W87,Z87,T87,AC87) -> 9 | AJ87: =SUM(L87,O87,R87,X87,AA87,U87,AD87,AG87) -> 972 | AK87: =IF(AH87=100%,"ITEM FINALIZADO",AH87) -> ITEM FINALIZADO
A88: 7.2.17 | B88: 103039 | C88: REGISTRO DE ESFERA, PVC, ROSCÁVEL, COM VOLANTE, 1 1/2" - FORNECIMENTO E INSTALAÇÃO. AF 08/2021 | D88: SINAPI | E88: UNID | F88: 5 | G88: 50.13 | H88: =(F88*G88) -> 250.65 | U88: =TRUNC(G88*T88)+0 -> 0 | W88: =TRUNC(V88*F88,2) -> 0 | X88: =TRUNC(W88*G88)+0 -> 0 | Y88: =Z88/F88 -> 0 | AA88: =TRUNC(Z88*G88)+0 -> 0 | AB88: =AC88/F88 -> 1 | AC88: 5 | AD88: =TRUNC(AC88*G88) -> 250 | AE88: =AF88/F88 -> 0 | AG88: =TRUNC(AF88*G88) -> 0 | AH88: =SUM(J88,M88,P88,V88,Y88,AB88,AE88) -> 1 | AI88: =SUM(K88,N88,Q88,W88,Z88,T88,AC88) -> 5 | AJ88: =SUM(L88,O88,R88,X88,AA88,U88,AD88,AG88) -> 250 | AK88: =IF(AH88=100%,"ITEM FINALIZADO",AH88) -> ITEM FINALIZADO
A89: 7.2.18 | B89: 94782 | C89: (COMPOSIÇÃO REPRESENTATIVA) DO SERVIÇO DE CONTRAPISO EM ARGAMASSA TRAÇO 1:4 (CIM E AREIA), BETONEIRA 400 L, E = 4 CM ÁREAS SECAS E MOLHADAS SOBRE LAJE , E = 3 CM ÁREAS MOLHADAS SOBRE IMPERMEABILIZAÇÃO, PARA EDIFICAÇÃO MULTIFAMILIAR. AF_11/2014 | D89: SINAPI | E89: M2 | F89: 9 | G89: 44.22 | H89: =(F89*G89) -> 397.98 | U89: =TRUNC(G89*T89)+0 -> 0 | W89: =TRUNC(V89*F89,2) -> 0 | X89: =TRUNC(W89*G89)+0 -> 0 | Y89: =Z89/F89 -> 0 | AA89: =TRUNC(Z89*G89)+0 -> 0 | AB89: =AC89/F89 -> 0 | AD89: =TRUNC(AC89*G89) -> 0 | AE89: =AF89/F89 -> 0 | AG89: =TRUNC(AF89*G89) -> 0 | AH89: =SUM(J89,M89,P89,V89,Y89,AB89,AE89) -> 0 | AI89: =SUM(K89,N89,Q89,W89,Z89,T89,AC89) -> 0 | AJ89: =SUM(L89,O89,R89,X89,AA89,U89,AD89,AG89) -> 0 | AK89: =IF(AH89=100%,"ITEM FINALIZADO",AH89) -> 0
A90: 7.2.19 | B90: 98557 | C90: IMPERMEABILIZAÇÃO DE SUPERFICIE COM EMULSAO ASFALTICA, 2 DEMAOS. AF 09/2023 | D90: SINAPI | E90: M2 | F90: 339.53 | G90: 46.04 | H90: =(F90*G90) -> 15631.961 | P90: 1 | Q90: =TRUNC(P90*F90,2) -> 339.53 | R90: =TRUNC(Q90*G90) -> 15631 | U90: =TRUNC(G90*T90)+0 -> 0 | W90: =TRUNC(V90*F90,2) -> 0 | X90: =TRUNC(W90*G90)+0 -> 0 | Y90: =Z90/F90 -> 0 | AA90: =TRUNC(Z90*G90)+0 -> 0 | AB90: =AC90/F90 -> 0 | AD90: =TRUNC(AC90*G90) -> 0 | AE90: =AF90/F90 -> 0 | AG90: =TRUNC(AF90*G90) -> 0 | AH90: =SUM(J90,M90,P90,V90,Y90,AB90,AE90) -> 1 | AI90: =SUM(K90,N90,Q90,W90,Z90,T90,AC90) -> 339.53 | AJ90: =SUM(L90,O90,R90,X90,AA90,U90,AD90,AG90) -> 15631 | AK90: =IF(AH90=100%,"ITEM FINALIZADO",AH90) -> ITEM FINALIZADO
A91: 8 | B91: PINTURA | H91: =SUM(H92:H97) -> 109225.03
A92: 8.1 | B92: 98135 | C92: APLICAÇÃO MANUAL DE MASSA ACRÍLICA EM PAREDES EXTERNAS DE CASAS, DUAS DEMÃOS. AF 03/2024 | D92: SINAPI | E92: M2 | F92: 2157.32 | G92: 28.15 | H92: =(F92*G92)-0.01 -> 60728.548 | U92: =TRUNC(G92*T92)+0 -> 0 | W92: =TRUNC(V92*F92,2) -> 0 | X92: =TRUNC(W92*G92)+0 -> 0 | Y92: =Z92/F92 -> 0 | AA92: =TRUNC(Z92*G92)+0 -> 0 | AB92: =AC92/F92 -> 0.16057423 | AC92: 346.41 | AD92: =TRUNC(AC92*G92) -> 9751 | AE92: =AF92/F92 -> 0.13864517 | AF92: ='MEMORIAL DE CALCULO'!BY150 -> 299.102 | AG92: =TRUNC(AF92*G92) -> 8419 | AH92: =SUM(J92,M92,P92,V92,Y92,AB92,AE92) -> 0.2992194 | AI92: =SUM(K92,N92,Q92,W92,Z92,T92,AC92) -> 346.41 | AJ92: =SUM(L92,O92,R92,X92,AA92,U92,AD92,AG92) -> 18170
A93: 8.2 | B93: 96129 | C93: APLICAÇÃO MANUAL DE MASSA ACRÍLICA EM SUPERFICIES INTERNAS DE SACADA DE EDIFÍCIOS DE MÚLTIPLOS PAVIMENTOS. UMA DEMÃO. AF 03/2024 | D93: SINAPI | E93: M2 | F93: 57.02 | G93: 33.53 | H93: =(F93*G93) -> 1911.8806 | U93: =TRUNC(G93*T93)+0 -> 0 | W93: =TRUNC(V93*F93,2) -> 0 | X93: =TRUNC(W93*G93)+0 -> 0 | Y93: =Z93/F93 -> 0 | AA93: =TRUNC(Z93*G93)+0 -> 0 | AB93: =AC93/F93 -> 0 | AD93: =TRUNC(AC93*G93) -> 0 | AE93: =AF93/F93 -> 1 | AF93: 57.02 | AG93: =TRUNC(AF93*G93) -> 1911 | AH93: =SUM(J93,M93,P93,V93,Y93,AB93,AE93) -> 1 | AI93: =SUM(K93,N93,Q93,W93,Z93,T93,AC93) -> 0 | AJ93: =SUM(L93,O93,R93,X93,AA93,U93,AD93,AG93) -> 1911
A94: 8.3 | B94: 104641 | C94: PINTURA LATÉX ACRÍLICA ECONÔMICA, APLICAÇÃO MANUAL EM PAREDES, DUAS DEMÃOS. AF 04/2023 | D94: SINAPI | E94: M2 | F94: 2157.32 | G94: 8.75 | H94: =(F94*G94) -> 18876.55 | U94: =TRUNC(G94*T94)+0 -> 0 | W94: =TRUNC(V94*F94,2) -> 0 | X94: =TRUNC(W94*G94)+0 -> 0 | Y94: =Z94/F94 -> 0 | AA94: =TRUNC(Z94*G94)+0 -> 0 | AB94: =AC94/F94 -> 0 | AD94: =TRUNC(AC94*G94) -> 0 | AE94: =AF94/F94 -> 0.52020006 | AF94: ='MEMORIAL DE CALCULO'!BY223 -> 1122.238 | AG94: =TRUNC(AF94*G94) -> 9819 | AH94: =SUM(J94,M94,P94,V94,Y94,AB94,AE94) -> 0.52020006 | AI94: =SUM(K94,N94,Q94,W94,Z94,T94,AC94) -> 0 | AJ94: =SUM(L94,O94,R94,X94,AA94,U94,AD94,AG94) -> 9819
A95: 8.4 | B95: 88415 | C95: APLICAÇÃO MANUAL DE FUNDO SELADOR ACRÍLICO EM PAREDES EXTERNAS DE CASAS. AF 03/2024 | D95: SINAPI | E95: M2 | F95: 2157.32 | G95: 4.49 | H95: =(F95*G95)-0.01 -> 9686.3568 | U95: =TRUNC(G95*T95)+0 -> 0 | W95: =TRUNC(V95*F95,2) -> 0 | X95: =TRUNC(W95*G95)+0 -> 0 | Y95: =Z95/F95 -> 0 | AA95: =TRUNC(Z95*G95)+0 -> 0 | AB95: =AC95/F95 -> 0.30186639 | AC95: ='MEMORIAL DE CALCULO'!BY269 -> 651.2224 | AD95: =TRUNC(AC95*G95) -> 2923 | AE95: =AF95/F95 -> 0.13864517 | AF95: ='MEMORIAL DE CALCULO'!BY270 -> 299.102 | AG95: =TRUNC(AF95*G95) -> 1342 | AH95: =SUM(J95,M95,P95,V95,Y95,AB95,AE95) -> 0.44051156 | AI95: =SUM(K95,N95,Q95,W95,Z95,T95,AC95) -> 651.2224 | AJ95: =SUM(L95,O95,R95,X95,AA95,U95,AD95,AG95) -> 4265
A96: 8.5 | B96: 88485 | C96: FUNDO SELADOR ACRÍLICO, APLICAÇÃO MANUAL EM PAREDE, UMA DEMÃO. AF 04/2023 | D96: SINAPI | E96: M2 | F96: 2157.32 | G96: 3.93 | H96: =(F96*G96)-0.01 -> 8478.2576 | U96: =TRUNC(G96*T96)+0 -> 0 | W96: =TRUNC(V96*F96,2) -> 0 | X96: =TRUNC(W96*G96)+0 -> 0 | Y96: =Z96/F96 -> 0 | AA96: =TRUNC(Z96*G96)+0 -> 0 | AB96: =AC96/F96 -> 0.30186639 | AC96: ='MEMORIAL DE CALCULO'!BY316 -> 651.2224 | AD96: =TRUNC(AC96*G96) -> 2559 | AE96: =AF96/F96 -> 0.13864517 | AF96: ='MEMORIAL DE CALCULO'!BY317 -> 299.102 | AG96: =TRUNC(AF96*G96) -> 1175 | AH96: =SUM(J96,M96,P96,V96,Y96,AB96,AE96) -> 0.44051156 | AI96: =SUM(K96,N96,Q96,W96,Z96,T96,AC96) -> 651.2224 | AJ96: =SUM(L96,O96,R96,X96,AA96,U96,AD96,AG96) -> 3734
A97: 8.6 | B97: 95306 | C97: TEXTURA ACRÍLICA, APLICAÇÃO MANUAL EM TETO, UMA DEMÃO. AF 04/2023 | D97: SINAPI | E97: M2 | F97: 667.84 | G97: 14.29 | H97: =(F97*G97) -> 9543.4336 | U97: =TRUNC(G97*T97)+0 -> 0 | W97: =TRUNC(V97*F97,2) -> 0 | X97: =TRUNC(W97*G97)+0 -> 0 | Y97: =Z97/F97 -> 0 | AA97: =TRUNC(Z97*G97)+0 -> 0 | AB97: =AC97/F97 -> 0.4564183 | AC97: ='MEMORIAL DE CALCULO'!BY345 -> 304.8144 | AD97: =TRUNC(AC97*G97) -> 4355 | AE97: =AF97/F97 -> 0 | AG97: =TRUNC(AF97*G97) -> 0 | AH97: =SUM(J97,M97,P97,V97,Y97,AB97,AE97) -> 0.4564183 | AI97: =SUM(K97,N97,Q97,W97,Z97,T97,AC97) -> 304.8144 | AJ97: =SUM(L97,O97,R97,X97,AA97,U97,AD97,AG97) -> 4355
A98: 9 | B98: INSTALAÇÕES ELÉTRICAS | H98: =SUM(H99:H108) -> 15377.03
A99: 9.1 | B99: 101492 | C99: ENTRADA DE ENERGIA ELÉTRICA, AEREA, MONOFASICA, COM CAIXA DE SOBREPOR, CABO DE 35 MM2 E DISJUNTOR DIN 50A (NÃO INCLUSO O POSTE DE CONCRETO). AF_07/2020_PS | D99: SINAPI | E99: UNID | F99: 1 | G99: 1667.43 | H99: =(F99*G99) -> 1667.43 | U99: =TRUNC(G99*T99)+0 -> 0 | W99: =TRUNC(V99*F99,2) -> 0 | X99: =TRUNC(W99*G99)+0 -> 0 | Y99: =Z99/F99 -> 0 | AA99: =TRUNC(Z99*G99)+0 -> 0 | AB99: =AC99/F99 -> 1 | AC99: 1 | AD99: =TRUNC(AC99*G99) -> 1667 | AE99: =AF99/F99 -> 0 | AG99: =TRUNC(AF99*G99) -> 0 | AH99: =SUM(J99,M99,P99,V99,Y99,AB99,AE99) -> 1 | AI99: =SUM(K99,N99,Q99,W99,Z99,T99,AC99) -> 1 | AJ99: =SUM(L99,O99,R99,X99,AA99,U99,AD99,AG99) -> 1667 | AK99: =IF(AH99=100%,"ITEM FINALIZADO",AH99) -> ITEM FINALIZADO
A100: 9.2 | B100: 93660 | C100: DISJUNTOR BIPOLAR TIPO DIN, CORRENTE NOMINAL DE 10A - FORNECIMENTO E INSTALAÇÃO. AF 10/2020 | D100: SINAPI | E100: UNID | F100: 10 | G100: 47.17 | H100: =(F100*G100) -> 471.7 | U100: =TRUNC(G100*T100)+0 -> 0 | W100: =TRUNC(V100*F100,2) -> 0 | X100: =TRUNC(W100*G100)+0 -> 0 | Y100: =Z100/F100 -> 0 | AA100: =TRUNC(Z100*G100)+0 -> 0 | AB100: =AC100/F100 -> 1 | AC100: 10 | AD100: =TRUNC(AC100*G100) -> 471 | AE100: =AF100/F100 -> 0 | AG100: =TRUNC(AF100*G100) -> 0 | AH100: =SUM(J100,M100,P100,V100,Y100,AB100,AE100) -> 1 | AI100: =SUM(K100,N100,Q100,W100,Z100,T100,AC100) -> 10 | AJ100: =SUM(L100,O100,R100,X100,AA100,U100,AD100,AG100) -> 471 | AK100: =IF(AH100=100%,"ITEM FINALIZADO",AH100) -> ITEM FINALIZADO
...

Sheet MEMORIAL DE CALCULO
B1: CONTRATAÇÃO DE UMA EMPRESA ESPECIALIZADA PARA CONSTRUÇÃO DE 01 (UM) CENTRO ESPECIALIZADO EM ATENÇÃO A SAÚDE MENTAL PARA ATENDER AS NECESSIDADES DA SECRETARIA MUNICIPAL DE SAÚDE EM COREMAS/PB | E1: BANCO DE DADOS: SINAPI - 05/2024-Paraiba ORSE - 0412024- Sergipe | AL1: B.D.I. = 22,47% ENCARGOS SOCIAIS: Nao Desonerado: embutido nos presos unitário dos insumos de mão de obra, de acordo com as bases.
A2: DADOS DO CONTRATANTE: Prefeitura Municipal de Coremas. CNPJ: 08.939.936/0001-94 POCESSO LICITATÓRIO: Processo Administrativo N°. 176/2024 e Concorrência Eletrônica N°. 0004/2024 CONTRATO N°. 328/2024 VALOR DA OBRA/CONTRATO: 1.150.000,00 (Um milhão, cento e cinquenta mil reais). | E2: NÚMERO DA MEDIÇÃO: 8ª MEDIÇÃO. | AL2: REFERÊNCIA/PERÍODO DA MEDIÇÃO: 11/08/2025 A 11/09/2025
A3: DADOS DO CONTRATADO: CL CONSTRUÇÕES E SERVIÇOS LTDA CNPJ: 09.335.002/0001-06 ENDEREÇO: Rua Cel. João Severino, SN - Sala D - Centro - Itaporanga - PB. | E3: FONTE DOS RECURSOS: Próprio (Diversos) do Município, prevista no orçamento da União, para o exercício de 2024. | BZ3: TOTAL DA MEDIÇÃO 01 = | CB3: =#REF! -> #REF! | CC3: TOTAL DA MEDIÇÃO 02 = | CE3: =#REF! -> #REF! | CF3: TOTAL DA MEDIÇÃO 03 = | CH3: =#REF! -> #REF! | CL3: TOTAL DA MEDIÇÃO 05 = | CN3: =#REF! -> #REF!
A4: MEMORIAL DE CALCULO 08 | BZ4: MEDIÇÕES | CC4: MEDIÇÕES | CF4: MEDIÇÕES | CL4: MEDIÇÕES
A5: ITEM | B5: CÓDIGO | C5: DESCRIÇÃO | D5: CALCULOS | BZ5: AVANÇO PERCENTUAL NO PERÍODO | CA5: QUANTIDADE MEDIDA NO PERÍODO | CB5: VALOR MEDIDO NO PERÍODO | CC5: AVANÇO PERCENTUAL NO PERÍODO | CD5: QUANTIDADE MEDIDA NO PERÍODO | CE5: VALOR MEDIDO NO PERÍODO | CF5: AVANÇO PERCENTUAL NO PERÍODO | CG5: QUANTIDADE MEDIDA NO PERÍODO | CH5: VALOR MEDIDO NO PERÍODO | CI5: AVANÇO PERCENTUAL NO PERÍODO | CJ5: QUANTIDADE MEDIDA NO PERÍODO | CK5: VALOR MEDIDO NO PERÍODO | CL5: AVANÇO PERCENTUAL NO PERÍODO | CM5: QUANTIDADE MEDIDA NO PERÍODO | CN5: VALOR MEDIDO NO PERÍODO
A6: 1 | B6: SERVIÇOS PRELIMINARES | BZ6: MEDIÇÃO 01 | CC6: MEDIÇÃO 02 | CF6: MEDIÇÃO 03 | CI6: MEDIÇÃO 04 | CL6: MEDIÇÃO 05
A7: 1.1 | B7: 51 | C7: Placa de obra em chapa aco galvanizado, instalada - Rev 02_O1/2022 | BZ7: 1 | CA7: =TRUNC(BZ7*AK7,2) -> 0 | CB7: =TRUNC(CA7*AL7)+0.46 -> 0.46 | CC7: 0 | CD7: =TRUNC(CC7*AK7,2) -> 0 | CE7: =TRUNC(CD7*AL7)+0 -> 0 | CF7: 0 | CG7: =TRUNC(CF7*AK7,2) -> 0 | CH7: =TRUNC(CG7*AL7) -> 0 | CK7: =TRUNC(AL7*CJ7)+0 -> 0 | CL7: 0 | CM7: =TRUNC(CL7*AK7,2) -> 0 | CN7: =TRUNC(CM7*AL7)+0 -> 0
A8: 1.2 | B8: 98524 | C8: LIMPEZA MANUAL DE VEGETAÇÃO EM TERRENO COM EXADA AF 03/2024 | BZ8: 1 | CA8: =TRUNC(BZ8*AK8,2) -> 0 | CB8: =TRUNC(CA8*AL8)+0.41 -> 0.41 | CK8: =TRUNC(AL8*CJ8)+0 -> 0 | CM8: =TRUNC(CL8*AK8,2) -> 0 | CN8: =TRUNC(CM8*AL8)+0 -> 0
A9: 2 | B9: MOVIMENTO DE TERRA
A10: 2.1 | B10: 99059 | C10: LOCAÇÃO CONVENCIONAL DE OBRA, UTILIZANDO DE GABARITO DE TÁBUAS CORRIDAS PONTALETADAS A CADA 2,00M - 2 UTILIZAÇÕES. AF_03/2024 | BZ10: 1 | CA10: =TRUNC(BZ10*AK10,2) -> 0 | CB10: =TRUNC(CA10*AL10)+0.12 -> 0.12 | CK10: =TRUNC(AL10*CJ10)+0 -> 0 | CM10: =TRUNC(CL10*AK10,2) -> 0 | CN10: =TRUNC(CM10*AL10)+0 -> 0
A11: 2.2 | B11: 93358 | C11: ESCAVAÇÃO MANUAL DE VALA COM PROFUNDIDADE MENOR OU IGUAL A 1,30M AF 02/2021 | BZ11: 1 | CA11: =TRUNC(BZ11*AK11,2) -> 0 | CB11: =TRUNC(CA11*AL11)+0 -> 0 | CK11: =TRUNC(AL11*CJ11)+0 -> 0 | CM11: =TRUNC(CL11*AK11,2) -> 0 | CN11: =TRUNC(CM11*AL11)+0 -> 0
A12: 2.3 | B12: 94319 | C12: ATERRO MANUAL DE VALAS COM SOLO ARGILO-ARENOSO. AF_08/2023 | BZ12: 1 | CA12: =TRUNC(BZ12*AK12,2) -> 0 | CB12: =TRUNC(CA12*AL12)+0.2 -> 0.2 | CK12: =TRUNC(AL12*CJ12)+0 -> 0 | CM12: =TRUNC(CL12*AK12,2) -> 0 | CN12: =TRUNC(CM12*AL12)+0 -> 0
A13: 3 | B13: ESTRUTURA
A14: 3.1 | B14: INFRAESTUTURA
A15: 3.1.1 | B15: FUNDAÇÃO
A16: 3.1.1.1 | B16: 102486 | C16: CONCRETO FCK = 15MPA, TRACO 13,4.3,4 (EM MASSA SECA DE CIMENTO / AREIA MÉDIA/ SEIXO ROLADO) - PREPARO MANUAL. AF_05/2021 | BZ16: 0.8 | CA16: =TRUNC(BZ16*AK16,2) -> 0 | CB16: =TRUNC(CA16*AL16)+0.1 -> 0.1 | CC16: 0.2 | CD16: =TRUNC(CC16*AK16,2)+0.01 -> 0.01 | CE16: =TRUNC(CD16*AL16)+1.78 -> 1.78 | CK16: =TRUNC(AL16*CJ16)+0 -> 0 | CM16: =TRUNC(CL16*AK16,2) -> 0 | CN16: =TRUNC(CM16*AL16)+0 -> 0
A17: 3.1.1.2 | B17: 94965 | C17: CONCRETO FCK = 25MPA, TRACO 12,3:2,7 (EM MASSA SECA DE CIMENTO/ AREIA MEDIA/ BRITA 1) - PREPARO MECANICO COM BETONEIRA 400 L. AF 05/2021 | BZ17: 0.8 | CA17: =TRUNC(BZ17*AK17,2) -> 0 | CB17: =TRUNC(CA17*AL17)+0.05 -> 0.05 | CC17: 0.2 | CD17: =TRUNC(CC17*AK17,2) -> 0 | CE17: =TRUNC(CD17*AL17)+0.52 -> 0.52 | CK17: =TRUNC(AL17*CJ17)+0 -> 0 | CM17: =TRUNC(CL17*AK17,2) -> 0 | CN17: =TRUNC(CM17*AL17)+0 -> 0
A18: 3.1.1.3 | B18: 96544 | C18: ARMAÇÃO DE BLOCO UTILIZANDO AÇO CA-50 DE 6,3 MM - MONTAGEM. AF 01/2024 | BZ18: 0.8 | CA18: =TRUNC(BZ18*AK18,2) -> 0 | CB18: =TRUNC(CA18*AL18)+0.34 -> 0.34 | CC18: 0.2 | CD18: =TRUNC(CC18*AK18,2) -> 0 | CE18: =TRUNC(CD18*AL18)+0.09 -> 0.09 | CK18: =TRUNC(AL18*CJ18)+0 -> 0 | CM18: =TRUNC(CL18*AK18,2) -> 0 | CN18: =TRUNC(CM18*AL18)+0 -> 0
A19: 3.1.1.4 | B19: 98545 | C19: ARMAÇÃO DE BLOCO UTILZANDO AÇO CASO DE 8 MM - MONTAGEM. AF 01/2024 | BZ19: 0.8 | CA19: =TRUNC(BZ19*AK19,2) -> 0 | CB19: =TRUNC(CA19*AL19)+0.3 -> 0.3 | CC19: 0.2 | CD19: =TRUNC(CC19*AK19,2) -> 0 | CE19: =TRUNC(CD19*AL19)+0.32 -> 0.32 | CK19: =TRUNC(AL19*CJ19)+0 -> 0 | CM19: =TRUNC(CL19*AK19,2) -> 0 | CN19: =TRUNC(CM19*AL19)+0 -> 0
A20: 3.1.1.5 | B20: 96543 | C20: ARMAÇÃO DE BLOCO UTILIZANDO AÇO CA-60 DE 5 MM - MONTAGEM. AF 01/2024 | BZ20: 0.8 | CA20: =TRUNC(BZ20*AK20,2) -> 0 | CB20: =TRUNC(CA20*AL20)+0.94 -> 0.94 | CC20: 0.2 | CD20: =TRUNC(CC20*AK20,2) -> 0 | CE20: =TRUNC(CD20*AL20)+0.73 -> 0.73 | CK20: =TRUNC(AL20*CJ20)+0 -> 0 | CM20: =TRUNC(CL20*AK20,2) -> 0 | CN20: =TRUNC(CM20*AL20)+0 -> 0
A21: 3.1.1.6 | B21: 98557 | C21: IMPERMEABILIZAÇÃO DE SUPERFÍCIE COM EMULSÃO ASFÁLTICA, 2 DEMÃOS. AF 09/2023 | BZ21: 0.2 | CA21: =TRUNC(BZ21*AK21,2) -> 0 | CB21: =TRUNC(CA21*AL21)+0.23 -> 0.23 | CC21: 0.8 | CD21: =TRUNC(CC21*AK21,2) -> 0 | CE21: =TRUNC(CD21*AL21)+0.31 -> 0.31 | CK21: =TRUNC(AL21*CJ21)+0 -> 0 | CM21: =TRUNC(CL21*AK21,2) -> 0 | CN21: =TRUNC(CM21*AL21)+0 -> 0
A22: 3.2 | B22: SUPERESTRUTURA
A23: 3.2.1 | B23: PILARES
A24: 3.2.1.1 | B24: 102476 | C24: CONCRETO FCK = 25MPA, TRACO 1:2,2:2,5 (EM MASSA SECA DE CIMENTO/ AREIA MEDIA/ SEIXO ROLADO) - PREPARO MECANICO COM BETONEIRA 400 L. AF 05/2021 | BZ24: 0.5 | CA24: =TRUNC(BZ24*AK24,2) -> 0 | CB24: =TRUNC(CA24*AL24)+0.73 -> 0.73 | CC24: 0.4 | CD24: =TRUNC(CC24*AK24,2) -> 0 | CE24: =TRUNC(CD24*AL24)+0.78 -> 0.78 | CF24: 0.1 | CG24: =TRUNC(CF24*AK24,2) -> 0 | CH24: =TRUNC(CG24*AL24) -> 0 | CK24: =TRUNC(AL24*CJ24)+0 -> 0 | CM24: =TRUNC(CL24*AK24,2) -> 0 | CN24: =TRUNC(CM24*AL24)+0 -> 0
A25: 3.2.1.2 | B25: 96546 | C25: ARMAÇÃO DE BLOCO UTILIZANDO AÇO CA-SO DE 10 MM - MONTAGEM. AF 01/2024 | BZ25: 0.5 | CA25: =TRUNC(BZ25*AK25,2) -> 0 | CB25: =TRUNC(CA25*AL25)+0.34 -> 0.34 | CC25: 0.4 | CD25: =TRUNC(CC25*AK25,2) -> 0 | CE25: =TRUNC(CD25*AL25)+0.47 -> 0.47 | CF25: 0.1 | CG25: =TRUNC(CF25*AK25,2) -> 0 | CH25: =TRUNC(CG25*AL25) -> 0 | CK25: =TRUNC(AL25*CJ25)+0 -> 0 | CM25: =TRUNC(CL25*AK25,2) -> 0 | CN25: =TRUNC(CM25*AL25)+0 -> 0
A26: 3.2.1.3 | B26: 98543 | C26: ARMAÇÃO DE BLOCO UTILIZANDO AÇO CA-CO DE 5 MM - MONTAGEM. AF 01/2024 | BZ26: 1 | CA26: =TRUNC(BZ26*AK26,2) -> 0 | CB26: =TRUNC(CA26*AL26)+0.95 -> 0.95 | CG26: =TRUNC(CF26*AK26,2) -> 0 | CH26: =TRUNC(CG26*AL26) -> 0 | CK26: =TRUNC(AL26*CJ26)+0 -> 0 | CM26: =TRUNC(CL26*AK26,2) -> 0 | CN26: =TRUNC(CM26*AL26)+0 -> 0
A27: 3.2.1.4 | B27: 96545 | C27: ARMAÇÃO DE BLOCO UTILZANDO AÇO CA-50 DES MM - MONTAGEM, AF 01/2024 | BZ27: 1 | CA27: =TRUNC(BZ27*AK27,2) -> 0 | CB27: =TRUNC(CA27*AL27)+0.34 -> 0.34 | CG27: =TRUNC(CF27*AK27,2) -> 0 | CH27: =TRUNC(CG27*AL27) -> 0 | CK27: =TRUNC(AL27*CJ27)+0 -> 0 | CM27: =TRUNC(CL27*AK27,2) -> 0 | CN27: =TRUNC(CM27*AL27)+0 -> 0
A28: 3.2.1.5 | B28: 96547 | C28: ARMAÇÃO DE BLOCO, VIGA BALDRAME OU SAPATA UTILIZANDO AÇO CA- 50 DE 12,5 MM - MONTAGEM. AF 06/2017 | BZ28: 1 | CA28: =TRUNC(BZ28*AK28,2) -> 0 | CB28: =TRUNC(CA28*AL28)+0.25 -> 0.25 | CG28: =TRUNC(CF28*AK28,2) -> 0 | CH28: =TRUNC(CG28*AL28) -> 0 | CK28: =TRUNC(AL28*CJ28)+0 -> 0 | CM28: =TRUNC(CL28*AK28,2) -> 0 | CN28: =TRUNC(CM28*AL28)+0 -> 0
A29: 3.2.1.6 | B29: 103795 | C29: FABRICAÇÃO, MONTAGEM E DESMONTAGEM DE FÔRMA PARA ESCADA HIDRAULICA, EM CHAPA DE MADEIRA COMPENSADA RESINADA, E = 17 MM, 3 UTILIZAÇÕES. AF 08/2022 | BZ29: 0.5 | CA29: =TRUNC(BZ29*AK29,2) -> 0 | CB29: =TRUNC(CA29*AL29)+1.32 -> 1.32 | CC29: 0.5 | CD29: =TRUNC(CC29*AK29,2) -> 0 | CE29: =TRUNC(CD29*AL29)+1.32 -> 1.32 | CF29: 0.1 | CG29: =TRUNC(CF29*AK29,2) -> 0 | CH29: =TRUNC(CG29*AL29) -> 0 | CJ29: -22.76 | CK29: =TRUNC(AL29*CJ29)+0 -> 0 | CL29: -0.1 | CM29: =TRUNC(CL29*AK29,2) -> 0
A30: 3.2.2 | B30: VIGAS
A31: 3.2.2.1 | B31: 102476 | C31: CONCRETO FCK = 25MPA, TRAGO 12,2:2,5 (EM MASSA SECA DE CIMENTO/ AREIA MEDIA/ SEIXO ROLADO) - PREPARO MECANICO COM BETONEIRA 400 L. AF 05/2021 | CC31: 0.4 | CD31: =TRUNC(CC31*AK31,2) -> 0 | CE31: =TRUNC(CD31*AL31)+3.13 -> 3.13 | CF31: 0.6 | CG31: =TRUNC(CF31*AK31,2) -> 0 | CH31: =TRUNC(CG31*AL31) -> 0 | CK31: =TRUNC(AL31*CJ31)+0 -> 0 | CM31: =TRUNC(CL31*AK31,2) -> 0 | CN31: =TRUNC(CM31*AL31)+0 -> 0
A32: 3.2.2.2 | B32: 92760 | C32: ARMAÇÃO DE PILAR OU VIGA DE ESTRUTURA CONVENCIONAL DE CONCRETO ARMADO UTILIZANDO AÇO CA-50 06 8,3 MM - MONTAGEM. AF 06/2022 | CC32: 0.8 | CD32: =TRUNC(CC32*AK32,2) -> 0 | CE32: =TRUNC(CD32*AL32)+0.82 -> 0.82 | CF32: 0.2 | CG32: =TRUNC(CF32*AK32,2) -> 0 | CH32: =TRUNC(CG32*AL32) -> 0 | CK32: =TRUNC(AL32*CJ32)+0 -> 0 | CM32: =TRUNC(CL32*AK32,2) -> 0 | CN32: =TRUNC(CM32*AL32)+0 -> 0
A33: 3.2.2.3 | B33: 92761 | C33: ARMAÇÃO DE PILAR OU VIGA DE ESTRUTURA CONVENCIONAL DE CONCRETO ARMADO UTILIZANDO AÇO CA-50 DE 8,0 MM - MONTAGEM. AF 06/2022 | CC33: 0.8 | CD33: =TRUNC(CC33*AK33,2) -> 0 | CE33: =TRUNC(CD33*AL33)+0.32 -> 0.32 | CF33: 0.2 | CG33: =TRUNC(CF33*AK33,2) -> 0 | CH33: =TRUNC(CG33*AL33) -> 0 | CK33: =TRUNC(AL33*CJ33)+0 -> 0 | CM33: =TRUNC(CL33*AK33,2) -> 0 | CN33: =TRUNC(CM33*AL33)+0 -> 0
A34: 3.2.2.4 | B34: 92762 | C34: ARMAÇÃO DE PILAR OU VIGA DE ESTRUTURA CONVENCIONAL DE CONCRETO ARMADO UTILIZANDO AÇO CA-50 DE 10,0 MM - MONTAGEM. AF 06/2022 | CC34: 0.8 | CD34: =TRUNC(CC34*AK34,2) -> 0 | CE34: =TRUNC(CD34*AL34)+0.23 -> 0.23 | CF34: 0.2 | CG34: =TRUNC(CF34*AK34,2) -> 0 | CH34: =TRUNC(CG34*AL34) -> 0 | CK34: =TRUNC(AL34*CJ34)+0 -> 0 | CM34: =TRUNC(CL34*AK34,2) -> 0 | CN34: =TRUNC(CM34*AL34)+0 -> 0
A35: 3.2.2.5 | B35: 92763 | C35: ARMAÇÃO DE PILAR OU VIGA DE ESTRUTURA CONVENCIONAL DE CONCRETO ARMADO UTILZANDO AÇO CA-50 DE 12,5 MM - MONTAGEM. AF 06/2022 | CC35: 0.8 | CD35: =TRUNC(CC35*AK35,2) -> 0 | CE35: =TRUNC(CD35*AL35)+0.11 -> 0.11 | CF35: 0.2 | CG35: =TRUNC(CF35*AK35,2) -> 0 | CH35: =TRUNC(CG35*AL35) -> 0 | CK35: =TRUNC(AL35*CJ35)+0 -> 0 | CM35: =TRUNC(CL35*AK35,2) -> 0 | CN35: =TRUNC(CM35*AL35)+0 -> 0
A36: 3.2.2.6 | B36: 92759 | C36: ARMAÇÃO DE PILAR OU VIGA DE ESTRUTURA CONVENCIONAL DE CONCRETO ARMADO UTILIZANDO AÇO CA-CO DE 5,0 MM - MONTAGEM. AF 06/2022 | CC36: 0.8 | CD36: =TRUNC(CC36*AK36,2) -> 0 | CE36: =TRUNC(CD36*AL36)+0.85 -> 0.85 | CF36: 0.2 | CG36: =TRUNC(CF36*AK36,2) -> 0 | CH36: =TRUNC(CG36*AL36) -> 0 | CK36: =TRUNC(AL36*CJ36)+0 -> 0 | CM36: =TRUNC(CL36*AK36,2) -> 0 | CN36: =TRUNC(CM36*AL36)+0 -> 0
A37: 3.2.2.7 | B37: 92265 | C37: FABRICAÇÃO DE FORMA PARA VIGAS, EM CHAPA DE MADEIRA COMPENSADA RESINADA, E = 17 MM. AF 09/2020 | CC37: 1 | CD37: =TRUNC(CC37*AK37,2) -> 0 | CE37: =TRUNC(CD37*AL37)+0.11 -> 0.11 | CK37: =TRUNC(AL37*CJ37)+0 -> 0 | CM37: =TRUNC(CL37*AK37,2) -> 0 | CN37: =TRUNC(CM37*AL37)+0 -> 0
A38: 3.2.3 | B38: LAJE
A39: 3.2.3.1 | B39: 94965 | C39: CONCRETO FCK = 25MPA, TRACO 1:2,3:2,7 (EM MASSA SECA DE CIMENTO/AREIA MEDIA/ BRITA 1) - PREPARO MECANICO COM BETONEIRA 400 L. AF 05/2021 | CK39: =TRUNC(AL39*CJ39)+0 -> 0 | CL39: 0 | CM39: =TRUNC(CL39*AK39,2) -> 0 | CN39: =TRUNC(CM39*AL39)+0 -> 0
A40: 3.2.3.2 | B40: 92267 | C40: FABRICAÇÃO DE FÔRMA PARA LAJES, EM CHAPA DE MADEIRA COMPENSADA RESINADA, E = 17 MM. AF 09/2020 | CK40: =TRUNC(AL40*CJ40)+0 -> 0 | CL40: 0 | CM40: =TRUNC(CL40*AK40,2) -> 0 | CN40: =TRUNC(CM40*AL40)+0 -> 0
A41: 3.2.3.3 | B41: 92769 | C41: ARMAÇÃO DE LAJE DE ESTRUTURA CONVENCIONAL DE CONCRETO ARMADO UTILIZANDO AÇO CA-SO DE 6,3 MM - MONTAGEM. AF_06/2022 | CK41: =TRUNC(AL41*CJ41)+0 -> 0 | CL41: 0 | CM41: =TRUNC(CL41*AK41,2) -> 0 | CN41: =TRUNC(CM41*AL41)+0 -> 0
A42: 3.2.3.4 | B42: 92770 | C42: ARMAÇÃO DE LAJE DE ESTRUTURA CONVENCIONAL DE CONCRETO ARMADO UTILIZANDO AÇO CA-SO DE 8,0 MM - MONTAGEM. AF_06/2022 | CK42: =TRUNC(AL42*CJ42)+0 -> 0 | CL42: 0 | CM42: =TRUNC(CL42*AK42,2) -> 0 | CN42: =TRUNC(CM42*AL42)+0 -> 0
A43: 3.2.3.5 | B43: 92771 | C43: ARMAÇAO DE LAJE DE ESTRUTURA CONVENCIONAL DE CONCRETO ARMADO UTILIZANDO AÇO CA-50 DE 10,0 MM - MONTAGEM. AF_08/2022 | CK43: =TRUNC(AL43*CJ43)+0 -> 0 | CL43: 0 | CM43: =TRUNC(CL43*AK43,2) -> 0 | CN43: =TRUNC(CM43*AL43)+0 -> 0
A44: 3.2.3.6 | B44: 92768 | C44: ARMAÇÃO DE LAJE DE ESTRUTURA CONVENCIONAL DE CONCRETO ARMADO UTILIZANDO AÇO CA-CO DE 5,0 MM - MONTAGEM. AF_06/2022 | CK44: =TRUNC(AL44*CJ44)+0 -> 0 | CL44: 0 | CM44: =TRUNC(CL44*AK44,2) -> 0 | CN44: =TRUNC(CM44*AL44)+0 -> 0
A45: 4 | B45: ELEVAÇÃO
A46: 4.1 | B46: 103328 | C46: ALVENARIA DE VEDAÇÃO DE BLOCOS CERAMICOS FURADOS NA HORIZONTAL DE 9X19X19 CM (ESPESSURA 9 CM) E ARGAMASSA DE ASSENTAMENTO COM PREPARO EM BETONEIRA. AF_12/2021 | BZ46: 0.3 | CA46: =TRUNC(BZ46*AK46,2) -> 0 | CB46: =TRUNC(CA46*AL46)+1.33 -> 1.33 | CC46: 0.6 | CD46: =TRUNC(CC46*AK46,2) -> 0 | CE46: =TRUNC(CD46*AL46)+1.66 -> 1.66 | CJ46: 60.94 | CK46: =TRUNC(AL46*CJ46)+0 -> 0 | CL46: 0.1 | CM46: =TRUNC(CL46*AK46,2) -> 0 | CN46: 0
A47: 5 | B47: REVESTIMENTO
A48: 5.1 | B48: 87894 | C48: CHAPISCO APLICADO EM ALVENARIA (SEM PRESENÇA DE VÃOS) E ESTRUTURAS DE CONCRETO DE FACHADA, COM COLHER DE PEDREIRO. ARGAMASSA TRAÇO 1.3 COM PREPARO EM BETONEIRA 400L. AF_10/2022 | CF48: 0.5 | CG48: =TRUNC(CF48*AK48,2) -> 0 | CH48: =TRUNC(CG48*AL48) -> 0 | CJ48: 1078.66 | CK48: =TRUNC(AL48*CJ48)+0 -> 0 | CL48: 0.5 | CM48: =TRUNC(CL48*AK48,2) -> 0 | CN48: 0
A49: 5.2 | B49: 87548 | C49: MASSA ÚNICA, EM ARGAMASSA TRAÇO 1:2:8, PREPARO MANUAL, APLICADA MANUALMENTE EM PAREDES INTERNAS DE AMBIENTES COM ÁREA ENTRE 5M² E 10M², E = 10MM, COM TALISCAS, AF_03/2024 | CF49: 0.5 | CG49: =TRUNC(CF49*AK49,2) -> 0 | CH49: =TRUNC(CG49*AL49) -> 0 | CJ49: 1078.66 | CK49: =TRUNC(AL49*CJ49)+0 -> 0 | CL49: 0.5 | CM49: =TRUNC(CL49*AK49,2) -> 0 | CN49: 0
A50: 5.3 | B50: 104817 | C50: REVESTIMENTO CERÂMICO PARA PAREDES INTERNAS COM PLACAS TIPO PASTILHA DE DIMENSÕES 5 X 5 CM (PLACAS DE 30 X 30 CM) CM APLICADAS A MEIA ALTURA DAS PAREDES. AF_02/2023 | CG50: =TRUNC(CF50*AK50,2) -> 0 | CH50: =TRUNC(CG50*AL50) -> 0 | CJ50: 72.01 | CK50: =TRUNC(AL50*CJ50)+0 -> 0 | CL50: 1 | CM50: =TRUNC(CL50*AK50,2) -> 0 | CN50: 36700.13
A51: 5.4 | B51: 87262 | C51: REVESTIMENTO CERÂMICO PARA PISO COM PLACAS TIPO PORCELANATO DE DIMENSÕES 60X60 CM APLICADA EM AMBIENTES DE ÁREA ENTRE 5 M² E 10 M². AF 02/2023 PE | CK51: =TRUNC(AL51*CJ51)+0 -> 0 | CL51: 0 | CM51: =TRUNC(CL51*AK51,2) -> 0 | CN51: =TRUNC(CM51*AL51)+0 -> 0
D52: REVESTIMENTO
C53: COPA | D53: 3.5 | E53: + | F53: 3.65 | G53: + | H53: 3.5 | I53: + | J53: 3.65 | BV53: x | BW53: 2.7 | BX53: = | BY53: =(D53+F53+H53+J53+L53+N53+P53)*BW53 -> 38.61
C54: DISPENSA | D54: 3.5 | E54: + | F54: 1.3 | G54: + | H54: 3.5 | I54: + | J54: 1.3 | BV54: x | BW54: 2.7 | BX54: = | BY54: =(D54+F54+H54+J54+L54+N54+P54)*BW54 -> 25.92
C55: CTO. LIMPEZA | D55: 1.8 | E55: + | F55: 1.6 | G55: + | H55: 1.8 | I55: + | J55: 1.6 | BV55: x | BW55: 4.4 | BX55: = | BY55: =(D55+F55+H55+J55+L55+N55+P55)*BW55 -> 29.92
C56: REVESTIMENTO DA FACHADA | D56: 4.51 | E56: + | F56: 5.1 | BV56: X | BW56: 5.3 | BX56: = | BY56: =(D56+F56+H56+J56+L56+N56+P56)*BW56 -> 50.933
D57: TOTAL DA MASSA INTERNA | BX57: = | BY57: =SUM(BY53:BY56) -> 145.383
D58: DESCONTO DAS ESQUADRIAS
C59: P2 | D59: 0.8 | E59: x | F59: 2.1 | BV59: x | BW59: 3 | BX59: = | BY59: =(D59*F59)*BW59 -> 5.04
C60: J4 | D60: 1.4 | E60: x | F60: 1 | BV60: x | BW60: 1 | BX60: = | BY60: =(D60*F60)*BW60 -> 1.4
C61: J5 | D61: 1.5 | E61: x | F61: 0.4 | BV61: x | BW61: 2 | BX61: = | BY61: =(D61*F61)*BW61 -> 1.2
C62: J6 | D62: 1.3 | E62: x | F62: 0.4 | BV62: x | BW62: 1 | BX62: = | BY62: =(D62*F62)*BW62 -> 0.52
D63: TOTAL DO DESCONTO DAS ESQUADRIAS | BX63: = | BY63: =SUM(BY59:BY62) -> 8.16
D64: TOTAL DO REVESTIMENTO CERÂMICO | BX64: = | BY64: =BY57-BY63 -> 137.223
A65: 6 | B65: PISO
A66: 6.1 | B66: 87298 | C66: ARGAMASSA TRAÇO 1:3 (EM VOLUME DE CIMENTO E AREIA MÉDIA ÚMIDA) PARA CONTRAPISO, PREPARO MECANICO COM BETONEIRA 400 L. AF 08/2019 | CI66: 0 | CJ66: 8.48 | CK66: =TRUNC(AL66*CJ66)+0 -> 0 | CL66: 1 | CM66: =TRUNC(CL66*AK66,2) -> 0 | CN66: 4913.89
A67: 6.2 | B67: 104597 | C67: REVESTIMENTO CERÂMICO PARA PISO COM PLACAS TIPO PORCELANATO DE DIMENSOES 80X80 CM APLICADA EM AMBIENTES DE AREA ENTRE 556 E 10 M'. AF 022023 PE | CK67: =TRUNC(AL67*CJ67)+0 -> 0 | CM67: =TRUNC(CL67*AK67,2) -> 0 | CN67: =TRUNC(CM67*AL67)+0 -> 0
D68: REVESTIMENTO DO PISO
C69: LAVABO | D69: 1.6 | E69: X | F69: 1.6 | BX69: = | BY69: =D69*F69+H69*J69 -> 2.56
C70: CTO. LIMPEZA | D70: 1.8 | E70: X | F70: 1.6 | BX70: = | BY70: =D70*F70+H70*J70 -> 2.88
C71: DIREÇÃO | D71: 2.75 | E71: X | F71: 3.55 | BX71: = | BY71: =D71*F71+H71*J71 -> 9.7625
C72: BANHEIRO MASCULINO | D72: 2.4 | E72: X | F72: 2.2 | BX72: = | BY72: =D72*F72+H72*J72 -> 5.28
C73: BANHEIRO FEMININO | D73: 3.4 | E73: X | F73: 3.2 | BX73: = | BY73: =D73*F73+H73*J73 -> 10.88
C74: ESPERA | D74: 6.41 | E74: X | F74: 6.39 | G74: + | H74: 1.35 | I74: X | J74: 4.95 | BX74: = | BY74: =D74*F74+H74*J74 -> 47.6424
C75: CIRCULAÇÃO 01 | D75: 3.06 | E75: X | F75: 1.1 | BX75: = | BY75: =D75*F75+H75*J75 -> 3.366
C76: RECEPÇÃO | D76: 2.8 | E76: X | F76: 3.05 | BX76: = | BY76: =D76*F76+H76*J76 -> 8.54
C77: CIRCULAÇÃO 02 | D77: 2 | E77: X | F77: 14.75 | BX77: = | BY77: =D77*F77+H77*J77 -> 29.5
C78: COPA | D78: 3.65 | E78: X | F78: 3.5 | BX78: = | BY78: =D78*F78+H78*J78 -> 12.775
C79: DISPENSA | D79: 3.5 | E79: X | F79: 1.3 | BX79: = | BY79: =D79*F79+H79*J79 -> 4.55
C80: SALA 01 | D80: 3.65 | E80: X | F80: 3.5 | BX80: = | BY80: =D80*F80+H80*J80 -> 12.775
C81: BANHEIRO | D81: 2.4 | E81: X | F81: 1.3 | BX81: = | BY81: =D81*F81+H81*J81 -> 3.12
C82: SALA 02 | D82: 3.65 | E82: X | F82: 3.5 | BX82: = | BY82: =D82*F82+H82*J82 -> 12.775
C83: BANHEIRO | D83: 2.4 | E83: X | F83: 1.3 | BX83: = | BY83: =D83*F83+H83*J83 -> 3.12
C84: SALA 03 | D84: 3.65 | E84: X | F84: 3.5 | BX84: = | BY84: =D84*F84+H84*J84 -> 12.775
C85: BANHEIRO | D85: 2.4 | E85: X | F85: 1.3 | BX85: = | BY85: =D85*F85+H85*J85 -> 3.12
C86: SALA 04 | D86: 3.65 | E86: X | F86: 3.5 | BX86: = | BY86: =D86*F86+H86*J86 -> 12.775
... C93: BANHEIRO | D93: 2.4 | E93: X | F93: 1.3 | BX93: = | BY93: =D93*F93+H93*J93 -> 3.12
C94: RECREAÇÃO | D94: 7.38 | E94: + | F94: 6.75 | G94: X | H94: 7.9 | I94: / | J94: 2 | BX94: = | BY94: =((D94+F94)*H94)/2 -> 55.8135
D95: TOTAL DO REVESTIMENTO CERÂMICO | BX95: = | BY95: =SUM(BY69:BY93) -> 249.0009
A96: 7 | B96: INSTALAÇÕES SANITÁRIAS
A97: 7.1 | B97: SANITÁRIA
A98: 7.1.1 | B98: 86931 | C98: VASO SANITARIO SIFONADO COM CAIXA ACOPLADA LOUÇA BRANCA, INCLUSO ENGATE FLEXÍVEL EM PLASTICO BRANCO, 1/2 X 40CM - FORNECIMENTO E INSTALAÇÃO. AF_01/2020 | CK98: =TRUNC(AL98*CJ98)+0 -> 0 | CM98: =TRUNC(CL98*AK98,2) -> 0 | CN98: =TRUNC(CM98*AL98)+0 -> 0
A99: 7.1.2 | B99: 86939 | C99: LAVATÓRIO LOUÇA BRANCA COM COLUNA, *44 X 35,5* CM, PADRÃO POPULAR, INCLUSO SIFAO FLEXÍVEL EM PVC, VALVULA E ENGATE FLEXÍVEL 30CM EM PLASTICO E COM TORNEIRA CROMADA PADRAO POPULAR-FORNECIMENTO E INSTALAÇÃO. AF_01/2020 | CK99: =TRUNC(AL99*CJ99)+0 -> 0 | CM99: =TRUNC(CL99*AK99,2) -> 0 | CN99: =TRUNC(CM99*AL99)+0 -> 0
A100: 7.1.3 | B100: 89714 | C100: TUBO PVC, SERIE NORMAL, ESGOTO PREDIAL, DN 100 MM, FORNECIDO E INSTALADO EM RAMAL DE DESCARGA OU RAMAL DE ESGOTO SANITARIO. AF 08/2022 | CF100: 0.8 | CG100: =TRUNC(CF100*AK100,2) -> 0 | CH100: =TRUNC(CG100*AL100) -> 0 | CJ100: 20 | CK100: =TRUNC(AL100*CJ100)+0 -> 0 | CL100: 0.2 | CM100: =TRUNC(CL100*AK100,2) -> 0 | CN100: 0
A101: 7.1.4 | B101: 89711 | C101: TUBO PVC, SERIE NORMAL, ESGOTO PREDIAL, DN 40 MM, FORNECIDO E INSTALADO EM RAMAL DE DESCARGA OU RAMAL DE ESGOTO SANITARIO. AF 08/2022 | CF101: 0.8 | CG101: =TRUNC(CF101*AK101,2) -> 0 | CH101: =TRUNC(CG101*AL101) -> 0 | CJ101: 4 | CK101: =TRUNC(AL101*CJ101)+0 -> 0 | CL101: 0.2 | CM101: =TRUNC(CL101*AK101,2) -> 0 | CN101: 0
A102: 7.1.5 | B102: 89798 | C102: TUBO PVC, SERIE NORMAL, ESGOTO PREDIAL, DN 50 MM, FORNECIDO E INSTALADO EM PRUMADA DE ESGOTO SANITARIO OU VENTILAÇÃO. AF 08/2022 | CF102: 0.8 | CG102: =TRUNC(CF102*AK102,2) -> 0 | CH102: =TRUNC(CG102*AL102) -> 0 | CK102: =TRUNC(AL102*CJ102)+0 -> 0 | CM102: =TRUNC(CL102*AK102,2) -> 0 | CN102: =TRUNC(CM102*AL102)+0 -> 0
A103: 7.1.6 | B103: 104326 | C103: RALO SECO CONICO, PVC, DN 100 X 40 MM, JUNTA SOLDAVEL, FORNECIDO E INSTALADO EM RAMAL DE DESCARGA OU EM RAMAL DE ESGOTO SANITARIO. AF 08/2022 | CK103: =TRUNC(AL103*CJ103)+0 -> 0 | CM103: =TRUNC(CL103*AK103,2) -> 0 | CN103: =TRUNC(CM103*AL103)+0 -> 0
A104: 7.1.7 | B104: 104327 | C104: RALO SIFONADO REDONDO, PVC, DN 100 X 40 MM, JUNTA SOLDAVEL, FORNECIDO E INSTALADO EM RAMAL DE DESCARGA OU EM RAMAL DE ESGOTO SANITARIO. AF 08/2022 | CK104: =TRUNC(AL104*CJ104)+0 -> 0 | CM104: =TRUNC(CL104*AK104,2) -> 0 | CN104: =TRUNC(CM104*AL104)+0 -> 0
A105: 7.1.8 | B105: 89726 | C105: JOELHO 45 GRAUS, PVC, SERIE NORMAL, ESGOTO PREDIAL, DN 40 MM, JUNTA SOLDAVEL, FORNECIDO E INSTALADO EM RAMAL DE DESCARGA OU RAMAL DE ESGOTO SANITARIO. AF 08/2022 | CF105: 0.8 | CG105: =TRUNC(CF105*AK105,2) -> 0 | CH105: =TRUNC(CG105*AL105) -> 0 | CJ105: 1.4 | CK105: =TRUNC(AL105*CJ105)+0 -> 0 | CL105: 0.2 | CM105: =TRUNC(CL105*AK105,2) -> 0 | CN105: 0
A106: 7.1.9 | B106: 89732 | C106: JOELHO 45 GRAUS, PVC, SERIE NORMAL, ESGOTO PREDIAL, DN 50 MM, JUNTA ELASTICA, FORNECIDO E INSTALADO EM RAMAL DE DESCARGA OU RAMAL DE ESGOTO SANITARIO. AF 08/2022 | CF106: 0.8 | CG106: =TRUNC(CF106*AK106,2) -> 0 | CH106: =TRUNC(CG106*AL106) -> 0 | CJ106: 1.4 | CK106: =TRUNC(AL106*CJ106)+0 -> 0 | CL106: 0.2 | CM106: =TRUNC(CL106*AK106,2) -> 0 | CN106: 0
...
