Workbook
Name JR_PAGE_ANCHOR_0_1: MEMORIAL!$A$5
Name JR_PAGE_ANCHOR_0_1: REPROGRAMAÇÃO!$A$5
Name JR_PAGE_ANCHOR_0_1: #REF!

Sheet REPROGRAMAÇÃO
A2: OBRA: | B2: CONSTRUÇÃO DE UMA CRECHE COM CAPACIDADE PARA 50 (CEM) CRIANÇAS | K2: PERIODO DA MEDIÇÃO: | N2: VALOR CONTRATADO R$: | V2: VALOR CONTRATADO R$: | X2: 912926.02 | Z2: VALOR CONTRATADO R$:
A3: OBJETO: | B3: PRESTAR SERVIÇOS DE ENGENHARIA PARA CONSTRUÇÃO DE 01 (UMA) CRECHE COM CAPACIDADE PARA 50 (CINQUENTA) CRIANÇAS, COM BASE NO PROGRAMA PARAÍBA PRIMEIRA INFÂNCIA NO MUNICIPIO DE COREMAS-PB. | K3: 13/08/2024 a 12/09/2024 | N3: VALOR REPROGRAMAÇÃO R$: | V3: VALOR REPROGRAMAÇÃO R$: | X3: =X326 -> 1025601.9 | Z3: VALOR REPROGRAMAÇÃO R$:
A4: LOCAL: | B4: COREMAS - PB | W4: BDI: | X4: 0.2247
A5: REPROGRAMAÇÃO
A6: ITEM | B6: CÓDIGO | C6: DESCRIÇÃO | D6: FONTE | E6: UNID | F6: QUANTIDADES CONTRATADA | I6: VALORES CONTRADO R$ | N6: QUANTIDADES MEDIDO | S6: QUANTIDADES A REPROGRAMAR | V6: VALORES MEDIDO R$
F7: QUANTIDADE | G7: SEM BDI | H7: COM BDI | I7: SEM BDI | J7: COM BDI | K7: ACUMULADO ANTERIOR | L7: MEDIÇÃO 04 | M7: MEDIÇÃO 05 | N7: MEDIÇÃO 06 | O7: MEDIÇÃO 07 | P7: MEDIÇÃO 08 | Q7: ACUMULADO INCLUINDO O PERÍODO | R7: PERCENTUAL DE EXECUÇÃO | S7: ACRESCIDA | T7: SUPRIMIDA | U7: A REPROGRAMAR | V7: TOTAL ACRESCIDO R$ | W7: TOTAL SUPRIMIDO R$ | X7: TOTAL A REPROGRAMAR R$
A8: 1 | B8: SERVIÇOS PRELIMINARES | I8: 14740.01 | J8: 18051.88 | V8: =SUM(V9:V12) -> 13098.94 | W8: =SUM(W9:W12) -> 11947.59 | X8: =SUM(X9:X12) -> 19203.23
A9: 1.1 | B9: PRO-46870444 | C9: PLACA INDICATIVA DA OBRA EM CHAPA DE AÇO GALVANIZADO (4,0M X 2,0M) | D9: Composições Próprias | E9: M² | F9: 1 | G9: 153.05 | H9: 187.44 | I9: 153.05 | J9: 187.44 | K9: =F9 -> 1 | L9: =0 -> 0 | Q9: =K9+L9+M9+N9+O9+P9 -> 1 | R9: =Q9/F9 -> 1 | S9: 7 | U9: =F9+S9-T9 -> 8 | V9: =ROUND(H9*S9,2) -> 1312.08 | W9: =ROUND(H9*T9,2) -> 0 | X9: =ROUND(H9*U9,2) -> 1499.52
A10: 1.2 | B10: 93584 | C10: EXECUÇÃO DE DEPÓSITO EM CANTEIRO DE OBRA EM CHAPA DE MADEIRA COMPENSADA, NÃO INCLUSO MOBILIÁRIO. AF_04/2016 | D10: SINAPI | E10: M2 | F10: 12.43 | G10: 784.84 | H10: 961.19 | I10: 9755.56 | J10: 11947.59 | K10: =F10 -> 12.43 | L10: =0 -> 0 | Q10: =K10+L10+M10+N10+O10+P10 -> 12.43 | R10: =Q10/F10 -> 1 | T10: =F10 -> 12.43 | U10: =F10+S10-T10 -> 0 | V10: =ROUND(H10*S10,2) -> 0 | W10: =ROUND(H10*T10,2) -> 11947.59 | X10: =ROUND(H10*U10,2) -> 0
A11: 1.3 | B11: 99059 | C11: LOCACAO CONVENCIONAL DE OBRA, UTILIZANDO GABARITO DE TÁBUAS CORRIDAS PONTALETADAS A CADA 2,00M - 2 UTILIZAÇÕES. AF_10/2018 | D11: SINAPI | E11: M | F11: 101.16 | G11: 47.76 | H11: 58.49 | I11: 4831.4 | J11: 5916.85 | K11: =F11 -> 101.16 | L11: =0 -> 0 | Q11: =K11+L11+M11+N11+O11+P11 -> 101.16 | R11: =Q11/F11 -> 1 | U11: =F11+S11-T11 -> 101.16 | V11: =ROUND(H11*S11,2) -> 0 | W11: =ROUND(H11*T11,2) -> 0 | X11: =ROUND(H11*U11,2) -> 5916.85
A12: 1.4 | B12: PRO-PREF-01 | C12: BARRACÃO DA OBRA EM ALVENARIA | D12: Composições Próprias | E12: M2 | G12: 351.70879 | H12: 430.73702 | I12: 9624.3 | J12: 11786.86 | S12: 27.3644 | U12: =F12+S12-T12 -> 27.3644 | V12: =ROUND(H12*S12,2) -> 11786.86 | W12: =ROUND(H12*T12,2) -> 0 | X12: =ROUND(H12*U12,2) -> 11786.86
A13: 2 | B13: MOVIMENTO DE TERRA | I13: 10582.87 | J13: 12961.54 | V13: =SUM(V14:V18) -> 3724.32 | W13: =SUM(W14:W18) -> 0 | X13: =SUM(X14:X18) -> 16685.86
A14: 2.1 | B14: 93382 | C14: REATERRO MANUAL DE VALAS COM COMPACTAÇÃO MECANIZADA. AF_04/2016 | D14: SINAPI | E14: M3 | F14: 136.71 | G14: 22.2 | H14: 27.19 | I14: 3034.96 | J14: 3717.14 | K14: =F14 -> 136.71 | L14: =0 -> 0 | Q14: =K14+L14+M14+N14+O14+P14 -> 136.71 | R14: =Q14/F14 -> 1 | U14: =F14+S14-T14 -> 136.71 | V14: =ROUND(H14*S14,2) -> 0 | W14: =ROUND(H14*T14,2) -> 0 | X14: =ROUND(H14*U14,2) -> 3717.14
A15: 2.2 | B15: 93358 | C15: ESCAVAÇÃO MANUAL DE VALA COM PROFUNDIDADE MENOR OU IGUAL A 1,30 M. AF_02/2021 | D15: SINAPI | E15: M3 | F15: 72.61 | G15: 59.58 | H15: 72.97 | I15: 4326.1 | J15: 5298.35 | K15: =F15 -> 72.61 | L15: =0 -> 0 | Q15: =K15+L15+M15+N15+O15+P15 -> 72.61 | R15: =Q15/F15 -> 1 | S15: =MEMORIAL!AJ87-F15 -> 21.78725 | U15: =F15+S15-T15 -> 94.39725 | V15: =ROUND(H15*S15,2) -> 1589.82 | W15: =ROUND(H15*T15,2) -> 0 | X15: =ROUND(H15*U15,2) -> 6888.17
A16: 2.3 | B16: 93382 | C16: REATERRO MANUAL DE VALAS COM COMPACTAÇÃO MECANIZADA. AF_04/2016 | D16: SINAPI | E16: M3 | F16: 54.55 | G16: 22.2 | H16: 27.19 | I16: 1211.01 | J16: 1483.21 | K16: =F16 -> 54.55 | L16: =0 -> 0 | Q16: =K16+L16+M16+N16+O16+P16 -> 54.55 | R16: =Q16/F16 -> 1 | U16: =F16+S16-T16 -> 54.55 | V16: =ROUND(H16*S16,2) -> 0 | W16: =ROUND(H16*T16,2) -> 0 | X16: =ROUND(H16*U16,2) -> 1483.21
A17: 2.4 | B17: 96995 | C17: REATERRO MANUAL APILOADO COM SOQUETE. AF_10/2017 | D17: SINAPI | E17: M3 | F17: 55.67 | G17: 36.12 | H17: 44.24 | I17: 2010.8 | J17: 2462.84 | K17: =F17 -> 55.67 | L17: =0 -> 0 | Q17: =K17+L17+M17+N17+O17+P17 -> 55.67 | R17: =Q17/F17 -> 1 | U17: =F17+S17-T17 -> 55.67 | V17: =ROUND(H17*S17,2) -> 0 | W17: =ROUND(H17*T17,2) -> 0 | X17: =ROUND(H17*U17,2) -> 2462.84
A18: 2.5 | B18: 94342 | C18: ATERRO MANUAL DE VALAS COM AREIA PARA ATERRO E COMPACTAÇÃO MECANIZADA. AF_05/2016 | D18: SINAPI | E18: M2 | G18: =92.87*0.980188611 -> 91.030116 | H18: =G18*1.2247 -> 111.48458 | S18: =MEMORIAL!AJ96 -> 19.14615 | U18: =F18+S18-T18 -> 19.14615 | V18: =ROUND(H18*S18,2) -> 2134.5 | W18: =ROUND(H18*T18,2) -> 0 | X18: =ROUND(H18*U18,2) -> 2134.5
A19: 3 | B19: SAPATAS | I19: 31022.9 | J19: 37991.85 | V19: =SUM(V20:V28) -> 0 | W19: =SUM(W20:W28) -> 0 | X19: =SUM(X20:X28) -> 37991.85
A20: 3.1 | B20: 96616 | C20: LASTRO DE CONCRETO MAGRO, APLICADO EM BLOCOS DE COROAMENTO OU SAPATAS. AF_08/2017 | D20: SINAPI | E20: M3 | F20: 1.46 | G20: 551.7 | H20: 675.67 | I20: 805.48 | J20: 986.48 | K20: =F20 -> 1.46 | L20: =0 -> 0 | Q20: =K20+L20+M20+N20+O20+P20 -> 1.46 | R20: =Q20/F20 -> 1 | U20: =F20+S20-T20 -> 1.46 | V20: =ROUND(H20*S20,2) -> 0 | W20: =ROUND(H20*T20,2) -> 0 | X20: =ROUND(H20*U20,2) -> 986.48
A21: 3.2 | B21: 96541 | C21: FABRICAÇÃO, MONTAGEM E DESMONTAGEM DE FÔRMA PARA SAPATA, EM CHAPA DE MADEIRA COMPENSADA RESINADA, E=17 MM, 4 UTILIZAÇÕES. AF_06/2017 | D21: SINAPI | E21: M2 | F21: 96.48 | G21: 160.48 | H21: 196.54 | I21: 15483.11 | J21: 18962.18 | K21: =F21 -> 96.48 | L21: =0 -> 0 | Q21: =K21+L21+M21+N21+O21+P21 -> 96.48 | R21: =Q21/F21 -> 1 | U21: =F21+S21-T21 -> 96.48 | V21: =ROUND(H21*S21,2) -> 0 | W21: =ROUND(H21*T21,2) -> 0 | X21: =ROUND(H21*U21,2) -> 18962.18
A22: 3.3 | B22: 94971 | C22: CONCRETO FCK = 25MPA, TRAÇO 1:2,3:2,7 (EM MASSA SECA DE CIMENTO/ AREIA MÉDIA/ BRITA 1) - PREPARO MECÂNICO COM BETONEIRA 600 L. AF_05/2021 | D22: SINAPI | E22: M3 | F22: 10.06 | G22: 451.82 | H22: 553.34 | I22: 4545.31 | J22: 5566.6 | K22: =F22 -> 10.06 | L22: =0 -> 0 | Q22: =K22+L22+M22+N22+O22+P22 -> 10.06 | R22: =Q22/F22 -> 1 | U22: =F22+S22-T22 -> 10.06 | V22: =ROUND(H22*S22,2) -> 0 | W22: =ROUND(H22*T22,2) -> 0 | X22: =ROUND(H22*U22,2) -> 5566.6
A23: 3.4 | B23: 103670 | C23: LANÇAMENTO COM USO DE BALDES, ADENSAMENTO E ACABAMENTO DE CONCRETO EM ESTRUTURAS. AF_02/2022 | D23: SINAPI | E23: M3 | F23: 10.06 | G23: 205.96 | H23: 252.24 | I23: 2071.96 | J23: 2537.53 | K23: =F23 -> 10.06 | L23: =0 -> 0 | Q23: =K23+L23+M23+N23+O23+P23 -> 10.06 | R23: =Q23/F23 -> 1 | U23: =F23+S23-T23 -> 10.06 | V23: =ROUND(H23*S23,2) -> 0 | W23: =ROUND(H23*T23,2) -> 0 | X23: =ROUND(H23*U23,2) -> 2537.53
A24: 3.5 | B24: 96544 | C24: ARMAÇÃO DE BLOCO, VIGA BALDRAME OU SAPATA UTILIZANDO AÇO CA-50 DE 6,3 MM - MONTAGEM. AF_06/2017 | D24: SINAPI | E24: KG | F24: 241 | G24: 15.37 | H24: 18.82 | I24: 3704.17 | J24: 4535.62 | K24: =F24 -> 241 | L24: =0 -> 0 | Q24: =K24+L24+M24+N24+O24+P24 -> 241 | R24: =Q24/F24 -> 1 | U24: =F24+S24-T24 -> 241 | V24: =ROUND(H24*S24,2) -> 0 | W24: =ROUND(H24*T24,2) -> 0 | X24: =ROUND(H24*U24,2) -> 4535.62
A25: 3.6 | B25: 96546 | C25: ARMAÇÃO DE BLOCO, VIGA BALDRAME OU SAPATA UTILIZANDO AÇO CA-50 DE 10 MM - MONTAGEM. AF_06/2017 | D25: SINAPI | E25: KG | F25: 235.2 | G25: 13.1 | H25: 16.04 | I25: 3081.12 | J25: 3772.61 | K25: =F25 -> 235.2 | L25: =0 -> 0 | Q25: =K25+L25+M25+N25+O25+P25 -> 235.2 | R25: =Q25/F25 -> 1 | U25: =F25+S25-T25 -> 235.2 | V25: =ROUND(H25*S25,2) -> 0 | W25: =ROUND(H25*T25,2) -> 0 | X25: =ROUND(H25*U25,2) -> 3772.61
A26: 3.7 | B26: 96547 | C26: ARMAÇÃO DE BLOCO, VIGA BALDRAME OU SAPATA UTILIZANDO AÇO CA-50 DE 12,5 MM - MONTAGEM. AF_06/2017 | D26: SINAPI | E26: KG | F26: 18.1 | G26: 11.14 | H26: 13.64 | I26: 201.63 | J26: 246.88 | K26: =F26 -> 18.1 | L26: =0 -> 0 | Q26: =K26+L26+M26+N26+O26+P26 -> 18.1 | R26: =Q26/F26 -> 1 | U26: =F26+S26-T26 -> 18.1 | V26: =ROUND(H26*S26,2) -> 0 | W26: =ROUND(H26*T26,2) -> 0 | X26: =ROUND(H26*U26,2) -> 246.88
A27: 3.8 | B27: 96548 | C27: ARMAÇÃO DE BLOCO, VIGA BALDRAME OU SAPATA UTILIZANDO AÇO CA-50 DE 16 MM - MONTAGEM. AF_06/2017 | D27: SINAPI | E27: KG | F27: 7.6 | G27: 10.62 | H27: 13.01 | I27: 80.71 | J27: 98.88 | K27: =F27 -> 7.6 | L27: =0 -> 0 | Q27: =K27+L27+M27+N27+O27+P27 -> 7.6 | R27: =Q27/F27 -> 1 | U27: =F27+S27-T27 -> 7.6 | V27: =ROUND(H27*S27,2) -> 0 | W27: =ROUND(H27*T27,2) -> 0 | X27: =ROUND(H27*U27,2) -> 98.88
A28: 3.9 | B28: 96543 | C28: ARMAÇÃO DE BLOCO, VIGA BALDRAME E SAPATA UTILIZANDO AÇO CA-60 DE 5 MM - MONTAGEM. AF_06/2017 | D28: SINAPI | E28: KG | F28: 65.1 | G28: 16.12 | H28: 19.74 | I28: 1049.41 | J28: 1285.07 | K28: =F28 -> 65.1 | L28: =0 -> 0 | Q28: =K28+L28+M28+N28+O28+P28 -> 65.1 | R28: =Q28/F28 -> 1 | U28: =F28+S28-T28 -> 65.1 | V28: =ROUND(H28*S28,2) -> 0 | W28: =ROUND(H28*T28,2) -> 0 | X28: =ROUND(H28*U28,2) -> 1285.07
A29: 4 | B29: VIGA BALDRAME | I29: 34492.45 | J29: 42240.62 | V29: =SUM(V30:V35) -> 741.07 | W29: =SUM(W30:W35) -> 0 | X29: =SUM(X30:X35) -> 42981.69
A30: 4.1 | B30: 95240 | C30: LASTRO DE CONCRETO MAGRO, APLICADO EM PISOS, LAJES SOBRE SOLO OU RADIERS, ESPESSURA DE 3 CM. AF_07/2016 | D30: SINAPI | E30: M2 | F30: 2.2 | G30: 16 | H30: 19.6 | I30: 35.2 | J30: 43.12 | K30: =F30 -> 2.2 | L30: =0 -> 0 | Q30: =K30+L30+M30+N30+O30+P30 -> 2.2 | R30: =Q30/F30 -> 1 | S30: =MEMORIAL!AJ193-F30 -> 37.8095 | U30: =F30+S30-T30 -> 40.0095 | V30: =ROUND(H30*S30,2) -> 741.07 | W30: =ROUND(H30*T30,2) -> 0 | X30: =ROUND(H30*U30,2) -> 784.19
A31: 4.2 | B31: 96542 | C31: FABRICAÇÃO, MONTAGEM E DESMONTAGEM DE FÔRMA PARA VIGA BALDRAME, EM CHAPA DE MADEIRA COMPENSADA RESINADA, E=17 MM, 4 UTILIZAÇÕES. AF_06/2017 | D31: SINAPI | E31: M2 | F31: 220.31 | G31: 74.24 | H31: 90.92 | I31: 16355.81 | J31: 20030.59 | K31: =F31 -> 220.31 | L31: =0 -> 0 | Q31: =K31+L31+M31+N31+O31+P31 -> 220.31 | R31: =Q31/F31 -> 1 | U31: =F31+S31-T31 -> 220.31 | V31: =ROUND(H31*S31,2) -> 0 | W31: =ROUND(H31*T31,2) -> 0 | X31: =ROUND(H31*U31,2) -> 20030.59
A32: 4.3 | B32: 94971 | C32: CONCRETO FCK = 25MPA, TRAÇO 1:2,3:2,7 (EM MASSA SECA DE CIMENTO/ AREIA MÉDIA/ BRITA 1) - PREPARO MECÂNICO COM BETONEIRA 600 L. AF_05/2021 | D32: SINAPI | E32: M3 | F32: 13.22 | G32: 451.82 | H32: 553.34 | I32: 5973.06 | J32: 7315.15 | K32: =F32 -> 13.22 | L32: =0 -> 0 | Q32: =K32+L32+M32+N32+O32+P32 -> 13.22 | R32: =Q32/F32 -> 1 | U32: =F32+S32-T32 -> 13.22 | V32: =ROUND(H32*S32,2) -> 0 | W32: =ROUND(H32*T32,2) -> 0 | X32: =ROUND(H32*U32,2) -> 7315.15
A33: 4.4 | B33: 103670 | C33: LANÇAMENTO COM USO DE BALDES, ADENSAMENTO E ACABAMENTO DE CONCRETO EM ESTRUTURAS. AF_02/2022 | D33: SINAPI | E33: M3 | F33: 13.22 | G33: 205.96 | H33: 252.24 | I33: 2722.79 | J33: 3334.61 | K33: =F33 -> 13.22 | L33: =0 -> 0 | Q33: =K33+L33+M33+N33+O33+P33 -> 13.22 | R33: =Q33/F33 -> 1 | U33: =F33+S33-T33 -> 13.22 | V33: =ROUND(H33*S33,2) -> 0 | W33: =ROUND(H33*T33,2) -> 0 | X33: =ROUND(H33*U33,2) -> 3334.61
A34: 4.5 | B34: 96544 | C34: ARMAÇÃO DE BLOCO, VIGA BALDRAME OU SAPATA UTILIZANDO AÇO CA-50 DE 6,3 MM - MONTAGEM. AF_06/2017 | D34: SINAPI | E34: KG | F34: 389.6 | G34: 15.37 | H34: 18.82 | I34: 5988.15 | J34: 7332.27 | K34: =F34 -> 389.6 | L34: =0 -> 0 | Q34: =K34+L34+M34+N34+O34+P34 -> 389.6 | R34: =Q34/F34 -> 1 | U34: =F34+S34-T34 -> 389.6 | V34: =ROUND(H34*S34,2) -> 0 | W34: =ROUND(H34*T34,2) -> 0 | X34: =ROUND(H34*U34,2) -> 7332.27
A35: 4.6 | B35: 96543 | C35: ARMAÇÃO DE BLOCO, VIGA BALDRAME E SAPATA UTILIZANDO AÇO CA-60 DE 5 MM - MONTAGEM. AF_06/2017 | D35: SINAPI | E35: KG | F35: 212 | G35: 16.12 | H35: 19.74 | I35: 3417.44 | J35: 4184.88 | K35: =F35 -> 212 | L35: =0 -> 0 | Q35: =K35+L35+M35+N35+O35+P35 -> 212 | R35: =Q35/F35 -> 1 | U35: =F35+S35-T35 -> 212 | V35: =ROUND(H35*S35,2) -> 0 | W35: =ROUND(H35*T35,2) -> 0 | X35: =ROUND(H35*U35,2) -> 4184.88
A36: 5 | B36: PILARES | I36: 25583.47 | J36: 31334.09 | V36: =SUM(V37:V43) -> 0 | W36: =SUM(W37:W43) -> 0 | X36: =SUM(X37:X43) -> 31334.09
A37: 5.1 | B37: 92445 | C37: MONTAGEM E DESMONTAGEM DE FÔRMA DE PILARES RETANGULARES E ESTRUTURAS SIMILARES, PÉ-DIREITO DUPLO, EM CHAPA DE MADEIRA COMPENSADA PLASTIFICADA, 18 UTILIZAÇÕES. AF_09/2020 | D37: SINAPI | E37: M2 | F37: 199.64 | G37: 41.17 | H37: 50.42 | I37: 8219.18 | J37: 10065.85 | K37: 199.64 | L37: 0 | Q37: =K37+L37+M37+N37+O37+P37 -> 199.64 | R37: =Q37/F37 -> 1 | U37: =F37+S37-T37 -> 199.64 | V37: =ROUND(H37*S37,2) -> 0 | W37: =ROUND(H37*T37,2) -> 0 | X37: =ROUND(H37*U37,2) -> 10065.85
A38: 5.2 | B38: 94971 | C38: CONCRETO FCK = 25MPA, TRAÇO 1:2,3:2,7 (EM MASSA SECA DE CIMENTO/ AREIA MÉDIA/ BRITA 1) - PREPARO MECÂNICO COM BETONEIRA 600 L. AF_05/2021 | D38: SINAPI | E38: M3 | F38: 10.08 | G38: 451.82 | H38: 553.34 | I38: 4554.35 | J38: 5577.67 | K38: 10.08 | L38: 0 | Q38: =K38+L38+M38+N38+O38+P38 -> 10.08 | R38: =Q38/F38 -> 1 | U38: =F38+S38-T38 -> 10.08 | V38: =ROUND(H38*S38,2) -> 0 | W38: =ROUND(H38*T38,2) -> 0 | X38: =ROUND(H38*U38,2) -> 5577.67
A39: 5.3 | B39: 103670 | C39: LANÇAMENTO COM USO DE BALDES, ADENSAMENTO E ACABAMENTO DE CONCRETO EM ESTRUTURAS. AF_02/2022 | D39: SINAPI | E39: M3 | F39: 10.08 | G39: 205.96 | H39: 252.24 | I39: 2076.08 | J39: 2542.58 | K39: 10.08 | L39: 0 | Q39: =K39+L39+M39+N39+O39+P39 -> 10.08 | R39: =Q39/F39 -> 1 | U39: =F39+S39-T39 -> 10.08 | V39: =ROUND(H39*S39,2) -> 0 | W39: =ROUND(H39*T39,2) -> 0 | X39: =ROUND(H39*U39,2) -> 2542.58
A40: 5.4 | B40: 92762 | C40: ARMAÇÃO DE PILAR OU VIGA DE ESTRUTURA CONVENCIONAL DE CONCRETO ARMADO UTILIZANDO AÇO CA-50 DE 10,0 MM - MONTAGEM. AF_06/2022 | D40: SINAPI | E40: KG | F40: 580.5 | G40: 11.83 | H40: 14.49 | I40: 6867.32 | J40: 8411.45 | K40: 580.5 | L40: 0 | Q40: =K40+L40+M40+N40+O40+P40 -> 580.5 | R40: =Q40/F40 -> 1 | U40: =F40+S40-T40 -> 580.5 | V40: =ROUND(H40*S40,2) -> 0 | W40: =ROUND(H40*T40,2) -> 0 | X40: =ROUND(H40*U40,2) -> 8411.45
A41: 5.5 | B41: 92763 | C41: ARMAÇÃO DE PILAR OU VIGA DE ESTRUTURA CONVENCIONAL DE CONCRETO ARMADO UTILIZANDO AÇO CA-50 DE 12,5 MM - MONTAGEM. AF_06/2022 | D41: SINAPI | E41: KG | F41: 59.1 | G41: 10.09 | H41: 12.36 | I41: 596.32 | J41: 730.48 | K41: 59.1 | L41: 0 | Q41: =K41+L41+M41+N41+O41+P41 -> 59.1 | R41: =Q41/F41 -> 1 | U41: =F41+S41-T41 -> 59.1 | V41: =ROUND(H41*S41,2) -> 0 | W41: =ROUND(H41*T41,2) -> 0 | X41: =ROUND(H41*U41,2) -> 730.48
A42: 5.6 | B42: 92764 | C42: ARMAÇÃO DE PILAR OU VIGA DE ESTRUTURA CONVENCIONAL DE CONCRETO ARMADO UTILIZANDO AÇO CA-50 DE 16,0 MM - MONTAGEM. AF_06/2022 | D42: SINAPI | E42: KG | F42: 22.7 | G42: 9.86 | H42: 12.08 | I42: 223.82 | J42: 274.22 | K42: 22.7 | L42: 0 | Q42: =K42+L42+M42+N42+O42+P42 -> 22.7 | R42: =Q42/F42 -> 1 | U42: =F42+S42-T42 -> 22.7 | V42: =ROUND(H42*S42,2) -> 0 | W42: =ROUND(H42*T42,2) -> 0 | X42: =ROUND(H42*U42,2) -> 274.22
A43: 5.7 | B43: 92759 | C43: ARMAÇÃO DE PILAR OU VIGA DE ESTRUTURA CONVENCIONAL DE CONCRETO ARMADO UTILIZANDO AÇO CA-60 DE 5,0 MM - MONTAGEM. AF_06/2022 | D43: SINAPI | E43: KG | F43: 224 | G43: 13.6 | H43: 16.66 | I43: 3046.4 | J43: 3731.84 | K43: 224 | L43: 0 | Q43: =K43+L43+M43+N43+O43+P43 -> 224 | R43: =Q43/F43 -> 1 | U43: =F43+S43-T43 -> 224 | V43: =ROUND(H43*S43,2) -> 0 | W43: =ROUND(H43*T43,2) -> 0 | X43: =ROUND(H43*U43,2) -> 3731.84
A44: 6 | B44: VIGAS | I44: 47244.62 | J44: 57860.77 | V44: =SUM(V45:V53) -> 0 | W44: =SUM(W45:W53) -> 0 | X44: =SUM(X45:X53) -> 57860.77
A45: 6.1 | B45: 92265 | C45: FABRICAÇÃO DE FÔRMA PARA VIGAS, EM CHAPA DE MADEIRA COMPENSADA RESINADA, E = 17 MM. AF_09/2020 | D45: SINAPI | E45: M2 | F45: 264.23 | G45: 96.01 | H45: 117.58 | I45: 25368.72 | J45: 31068.16 | K45: 264.23 | L45: 0 | Q45: =K45+L45+M45+N45+O45+P45 -> 264.23 | R45: =Q45/F45 -> 1 | U45: =F45+S45-T45 -> 264.23 | V45: =ROUND(H45*S45,2) -> 0 | W45: =ROUND(H45*T45,2) -> 0 | X45: =ROUND(H45*U45,2) -> 31068.16
A46: 6.2 | B46: 94971 | C46: CONCRETO FCK = 25MPA, TRAÇO 1:2,3:2,7 (EM MASSA SECA DE CIMENTO/ AREIA MÉDIA/ BRITA 1) - PREPARO MECÂNICO COM BETONEIRA 600 L. AF_05/2021 | D46: SINAPI | E46: M3 | F46: 16.49 | G46: 451.82 | H46: 553.34 | I46: 7450.51 | J46: 9124.58 | K46: 16.49 | L46: 0 | Q46: =K46+L46+M46+N46+O46+P46 -> 16.49 | R46: =Q46/F46 -> 1 | U46: =F46+S46-T46 -> 16.49 | V46: =ROUND(H46*S46,2) -> 0 | W46: =ROUND(H46*T46,2) -> 0 | X46: =ROUND(H46*U46,2) -> 9124.58
A47: 6.3 | B47: 103670 | C47: LANÇAMENTO COM USO DE BALDES, ADENSAMENTO E ACABAMENTO DE CONCRETO EM ESTRUTURAS. AF_02/2022 | D47: SINAPI | E47: M3 | F47: 16.49 | G47: 205.96 | H47: 252.24 | I47: 3396.28 | J47: 4159.44 | K47: 16.49 | L47: 0 | Q47: =K47+L47+M47+N47+O47+P47 -> 16.49 | R47: =Q47/F47 -> 1 | U47: =F47+S47-T47 -> 16.49 | V47: =ROUND(H47*S47,2) -> 0 | W47: =ROUND(H47*T47,2) -> 0 | X47: =ROUND(H47*U47,2) -> 4159.44
A48: 6.4 | B48: 92760 | C48: ARMAÇÃO DE PILAR OU VIGA DE ESTRUTURA CONVENCIONAL DE CONCRETO ARMADO UTILIZANDO AÇO CA-50 DE 6,3 MM - MONTAGEM. AF_06/2022 | D48: SINAPI | E48: KG | F48: 285.3 | G48: 13.41 | H48: 16.42 | I48: 3825.87 | J48: 4684.63 | K48: 285.3 | L48: 0 | Q48: =K48+L48+M48+N48+O48+P48 -> 285.3 | R48: =Q48/F48 -> 1 | U48: =F48+S48-T48 -> 285.3 | V48: =ROUND(H48*S48,2) -> 0 | W48: =ROUND(H48*T48,2) -> 0 | X48: =ROUND(H48*U48,2) -> 4684.63
A49: 6.5 | B49: 92761 | C49: ARMAÇÃO DE PILAR OU VIGA DE ESTRUTURA CONVENCIONAL DE CONCRETO ARMADO UTILIZANDO AÇO CA-50 DE 8,0 MM - MONTAGEM. AF_06/2022 | D49: SINAPI | E49: KG | F49: 174.4 | G49: 13.02 | H49: 15.95 | I49: 2270.69 | J49: 2781.68 | K49: 174.4 | L49: 0 | Q49: =K49+L49+M49+N49+O49+P49 -> 174.4 | R49: =Q49/F49 -> 1 | U49: =F49+S49-T49 -> 174.4 | V49: =ROUND(H49*S49,2) -> 0 | W49: =ROUND(H49*T49,2) -> 0 | X49: =ROUND(H49*U49,2) -> 2781.68
A50: 6.6 | B50: 92762 | C50: ARMAÇÃO DE PILAR OU VIGA DE ESTRUTURA CONVENCIONAL DE CONCRETO ARMADO UTILIZANDO AÇO CA-50 DE 10,0 MM - MONTAGEM. AF_06/2022 | D50: SINAPI | E50: KG | F50: 64.9 | G50: 11.83 | H50: 14.49 | I50: 767.77 | J50: 940.4 | K50: 64.9 | L50: 0 | Q50: =K50+L50+M50+N50+O50+P50 -> 64.9 | R50: =Q50/F50 -> 1 | U50: =F50+S50-T50 -> 64.9 | V50: =ROUND(H50*S50,2) -> 0 | W50: =ROUND(H50*T50,2) -> 0 | X50: =ROUND(H50*U50,2) -> 940.4
A51: 6.7 | B51: 92763 | C51: ARMAÇÃO DE PILAR OU VIGA DE ESTRUTURA CONVENCIONAL DE CONCRETO ARMADO UTILIZANDO AÇO CA-50 DE 12,5 MM - MONTAGEM. AF_06/2022 | D51: SINAPI | E51: KG | F51: 18.7 | G51: 10.09 | H51: 12.36 | I51: 188.68 | J51: 231.13 | K51: 18.7 | L51: 0 | Q51: =K51+L51+M51+N51+O51+P51 -> 18.7 | R51: =Q51/F51 -> 1 | U51: =F51+S51-T51 -> 18.7 | V51: =ROUND(H51*S51,2) -> 0 | W51: =ROUND(H51*T51,2) -> 0 | X51: =ROUND(H51*U51,2) -> 231.13
A52: 6.8 | B52: 92764 | C52: ARMAÇÃO DE PILAR OU VIGA DE ESTRUTURA CONVENCIONAL DE CONCRETO ARMADO UTILIZANDO AÇO CA-50 DE 16,0 MM - MONTAGEM. AF_06/2022 | D52: SINAPI | E52: KG | F52: 17.6 | G52: 9.86 | H52: 12.08 | I52: 173.54 | J52: 212.61 | K52: 17.6 | L52: 0 | Q52: =K52+L52+M52+N52+O52+P52 -> 17.6 | R52: =Q52/F52 -> 1 | U52: =F52+S52-T52 -> 17.6 | V52: =ROUND(H52*S52,2) -> 0 | W52: =ROUND(H52*T52,2) -> 0 | X52: =ROUND(H52*U52,2) -> 212.61
A53: 6.9 | B53: 92759 | C53: ARMAÇÃO DE PILAR OU VIGA DE ESTRUTURA CONVENCIONAL DE CONCRETO ARMADO UTILIZANDO AÇO CA-60 DE 5,0 MM - MONTAGEM. AF_06/2022 | D53: SINAPI | E53: KG | F53: 279.6 | G53: 13.6 | H53: 16.66 | I53: 3802.56 | J53: 4658.14 | K53: 279.6 | L53: 0 | Q53: =K53+L53+M53+N53+O53+P53 -> 279.6 | R53: =Q53/F53 -> 1 | U53: =F53+S53-T53 -> 279.6 | V53: =ROUND(H53*S53,2) -> 0 | W53: =ROUND(H53*T53,2) -> 0 | X53: =ROUND(H53*U53,2) -> 4658.14
A54: 7 | B54: VERGAS | I54: 5236.04 | J54: 6412.46 | V54: =SUM(V55:V57) -> 0 | W54: =SUM(W55:W57) -> 0 | X54: =SUM(X55:X57) -> 6412.46
A55: 7.1 | B55: 93182 | C55: VERGA PRÉ-MOLDADA PARA JANELAS COM ATÉ 1,5 M DE VÃO. AF_03/2016 | D55: SINAPI | E55: M | F55: 55.16 | G55: 42.21 | H55: 51.69 | I55: 2328.3 | J55: 2851.22 | K55: =0 -> 0 | L55: =F55 -> 55.16 | Q55: =K55+L55+M55+N55+O55+P55 -> 55.16 | R55: =Q55/F55 -> 1 | U55: =F55+S55-T55 -> 55.16 | V55: =ROUND(H55*S55,2) -> 0 | W55: =ROUND(H55*T55,2) -> 0 | X55: =ROUND(H55*U55,2) -> 2851.22
A56: 7.2 | B56: 93184 | C56: VERGA PRÉ-MOLDADA PARA PORTAS COM ATÉ 1,5 M DE VÃO. AF_03/2016 | D56: SINAPI | E56: M | F56: 20.16 | G56: 31.04 | H56: 38.01 | I56: 625.77 | J56: 766.28 | K56: =0 -> 0 | L56: =F56 -> 20.16 | Q56: =K56+L56+M56+N56+O56+P56 -> 20.16 | R56: =Q56/F56 -> 1 | U56: =F56+S56-T56 -> 20.16 | V56: =ROUND(H56*S56,2) -> 0 | W56: =ROUND(H56*T56,2) -> 0 | X56: =ROUND(H56*U56,2) -> 766.28
A57: 7.3 | B57: 93194 | C57: CONTRAVERGA PRÉ-MOLDADA PARA VÃOS DE ATÉ 1,5 M DE COMPRIMENTO. AF_03/2016 | D57: SINAPI | E57: M | F57: 55.16 | G57: 41.37 | H57: 50.67 | I57: 2281.97 | J57: 2794.96 | K57: =0 -> 0 | L57: =F57 -> 55.16 | Q57: =K57+L57+M57+N57+O57+P57 -> 55.16 | R57: =Q57/F57 -> 1 | U57: =F57+S57-T57 -> 55.16 | V57: =ROUND(H57*S57,2) -> 0 | W57: =ROUND(H57*T57,2) -> 0 | X57: =ROUND(H57*U57,2) -> 2794.96
A58: 8 | B58: LAJE PRÉ-MOLDADA | I58: 88756.13 | J58: 108703.47 | V58: =SUM(V59:V65) -> 0 | W58: =SUM(W59:W65) -> 17947.4 | X58: =SUM(X59:X65) -> 90756.07
A59: 8.1 | B59: 101964 | C59: LAJE PRÉ-MOLDADA UNIDIRECIONAL, BIAPOIADA, PARA FORRO, ENCHIMENTO EM CERÂMICA, VIGOTA CONVENCIONAL, ALTURA TOTAL DA LAJE (ENCHIMENTO+CAPA) = (8+3). AF_11/2020 | D59: SINAPI | E59: M2 | F59: 395.11 | G59: 149.19 | H59: 182.71 | I59: 58946.46 | J59: 72190.55 | K59: =0 -> 0 | L59: 0 | N59: =#REF! -> #REF! | Q59: 385.90189 | R59: =Q59/F59 -> 0.97669482 | U59: =F59+S59-T59 -> 395.11 | V59: =ROUND(H59*S59,2) -> 0 | W59: =ROUND(H59*T59,2) -> 0 | X59: =ROUND(H59*U59,2) -> 72190.55
A60: 8.2 | B60: 92265 | C60: FABRICAÇÃO DE FÔRMA PARA VIGAS, EM CHAPA DE MADEIRA COMPENSADA RESINADA, E = 17 MM. AF_09/2020 | D60: SINAPI | E60: M2 | F60: 54.1 | G60: 96.01 | H60: 117.58 | I60: 5194.14 | J60: 6361.08 | K60: =0 -> 0 | L60: 0 | O60: 54.1 | Q60: =K60+L60+M60+N60+O60+P60 -> 54.1 | R60: =Q60/F60 -> 1 | U60: =F60+S60-T60 -> 54.1 | V60: =ROUND(H60*S60,2) -> 0 | W60: =ROUND(H60*T60,2) -> 0 | X60: =ROUND(H60*U60,2) -> 6361.08
A61: 8.3 | B61: 94971 | C61: CONCRETO FCK = 25MPA, TRAÇO 1:2,3:2,7 (EM MASSA SECA DE CIMENTO/ AREIA MÉDIA/ BRITA 1) - PREPARO MECÂNICO COM BETONEIRA 600 L. AF_05/2021 | D61: SINAPI | E61: M3 | F61: 11.19 | G61: 451.82 | H61: 553.34 | I61: 5055.87 | J61: 6191.87 | K61: =0 -> 0 | L61: 0 | O61: 11.19 | Q61: =K61+L61+M61+N61+O61+P61 -> 11.19 | R61: =Q61/F61 -> 1 | U61: =F61+S61-T61 -> 11.19 | V61: =ROUND(H61*S61,2) -> 0 | W61: =ROUND(H61*T61,2) -> 0 | X61: =ROUND(H61*U61,2) -> 6191.87
A62: 8.4 | B62: 103670 | C62: LANÇAMENTO COM USO DE BALDES, ADENSAMENTO E ACABAMENTO DE CONCRETO EM ESTRUTURAS. AF_02/2022 | D62: SINAPI | E62: M3 | F62: 11.19 | G62: 205.96 | H62: 252.24 | I62: 2304.69 | J62: 2822.57 | K62: =0 -> 0 | L62: 0 | O62: 11.19 | Q62: =K62+L62+M62+N62+O62+P62 -> 11.19 | R62: =Q62/F62 -> 1 | U62: =F62+S62-T62 -> 11.19 | V62: =ROUND(H62*S62,2) -> 0 | W62: =ROUND(H62*T62,2) -> 0 | X62: =ROUND(H62*U62,2) -> 2822.57
A63: 8.5 | B63: 92761 | C63: ARMAÇÃO DE PILAR OU VIGA DE ESTRUTURA CONVENCIONAL DE CONCRETO ARMADO UTILIZANDO AÇO CA-50 DE 8,0 MM - MONTAGEM. AF_06/2022 | D63: SINAPI | E63: KG | F63: 486.6 | G63: 13.02 | H63: 15.95 | I63: 6335.53 | J63: 7761.27 | K63: =0 -> 0 | L63: 0 | O63: 200 | Q63: =K63+L63+M63+N63+O63+P63 -> 200 | R63: =Q63/F63 -> 0.41101521 | T63: =F63-200 -> 286.6 | U63: =F63+S63-T63 -> 200 | V63: =ROUND(H63*S63,2) -> 0 | W63: =ROUND(H63*T63,2) -> 4571.27 | X63: =ROUND(H63*U63,2) -> 3190
A64: 8.6 | B64: 92762 | C64: ARMAÇÃO DE PILAR OU VIGA DE ESTRUTURA CONVENCIONAL DE CONCRETO ARMADO UTILIZANDO AÇO CA-50 DE 10,0 MM - MONTAGEM. AF_06/2022 | D64: SINAPI | E64: KG | F64: 104.5 | G64: 11.83 | H64: 14.49 | I64: 1236.24 | J64: 1514.21 | K64: =0 -> 0 | L64: 0 | Q64: =K64+L64+M64+N64+O64+P64 -> 0 | R64: =Q64/F64 -> 0 | T64: =F64 -> 104.5 | U64: =F64+S64-T64 -> 0 | V64: =ROUND(H64*S64,2) -> 0 | W64: =ROUND(H64*T64,2) -> 1514.21 | X64: =ROUND(H64*U64,2) -> 0
A65: 8.7 | B65: 92759 | C65: ARMAÇÃO DE PILAR OU VIGA DE ESTRUTURA CONVENCIONAL DE CONCRETO ARMADO UTILIZANDO AÇO CA-60 DE 5,0 MM - MONTAGEM. AF_06/2022 | D65: SINAPI | E65: KG | F65: 712 | G65: 13.6 | H65: 16.66 | I65: 9683.2 | J65: 11861.92 | K65: =0 -> 0 | L65: 0 | Q65: =K65+L65+M65+N65+O65+P65 -> 0 | R65: =Q65/F65 -> 0 | T65: =F65 -> 712 | U65: =F65+S65-T65 -> 0 | V65: =ROUND(H65*S65,2) -> 0 | W65: =ROUND(H65*T65,2) -> 11861.92 | X65: =ROUND(H65*U65,2) -> 0
A66: 9 | B66: ELEMENTOS VAZADOS | I66: 5794.92 | J66: 7097.13 | V66: =SUM(V67) -> 0 | W66: =SUM(W67) -> 0 | X66: =SUM(X67) -> 7097.13
A67: 9.1 | B67: 101161 | C67: ALVENARIA DE VEDAÇÃO COM ELEMENTO VAZADO DE CONCRETO (COBOGÓ) DE 7X50X50CM E ARGAMASSA DE ASSENTAMENTO COM PREPARO EM BETONEIRA. AF_05/2020 | D67: SINAPI | E67: M2 | F67: 31.87 | G67: 181.83 | H67: 222.69 | I67: 5794.92 | J67: 7097.13 | K67: =0 -> 0 | L67: 0 | O67: 31.87 | Q67: =K67+L67+M67+N67+O67+P67 -> 31.87 | R67: =Q67/F67 -> 1 | U67: =F67+S67-T67 -> 31.87 | V67: =ROUND(H67*S67,2) -> 0 | W67: =ROUND(H67*T67,2) -> 0 | X67: =ROUND(H67*U67,2) -> 7097.13
A68: 10 | B68: ALVENARIA DE VEDAÇÃO | I68: 67716.74 | J68: 82930.57 | V68: =SUM(V69:V71) -> 44274.29 | W68: =SUM(W69:W71) -> 5299.55 | X68: =SUM(X69:X71) -> 121905.32
A69: 10.1 | B69: 103329 | C69: ALVENARIA DE VEDAÇÃO DE BLOCOS CERÂMICOS FURADOS NA HORIZONTAL DE 9X19X19 CM (ESPESSURA 9 CM) E ARGAMASSA DE ASSENTAMENTO COM PREPARO MANUAL. AF_12/2021 | D69: SINAPI | E69: M2 | F69: 656.2 | G69: 68.55 | H69: 83.95 | I69: 44982.51 | J69: 55087.99 | K69: 350 | L69: 251.41 | O69: 54.79 | Q69: =K69+L69+M69+N69+O69+P69 -> 656.2 | R69: =Q69/F69 -> 1 | S69: =MEMORIAL!AJ392-F69 -> 102.7738 | U69: =F69+S69-T69 -> 758.9738 | V69: =ROUND(H69*S69,2) -> 8627.86 | W69: =ROUND(H69*T69,2) -> 0 | X69: =ROUND(H69*U69,2) -> 63715.85
A70: 10.2 | B70: 102253 | C70: DIVISORIA SANITÁRIA, TIPO CABINE, EM GRANITO CINZA POLIDO, ESP = 3CM, ASSENTADO COM ARGAMASSA COLANTE AC III-E, EXCLUSIVE FERRAGENS. AF_01/2021 | D70: SINAPI | E70: M2 | F70: 21.03 | G70: 561.25 | H70: 687.36 | I70: 11803.09 | J70: 14455.18 | K70: 0 | P70: =#REF! -> #REF! | Q70: =K70+L70+M70+N70+O70+P70 -> #REF! | R70: =Q70/F70 -> #REF! | T70: =F70-13.32 -> 7.71 | U70: =F70+S70-T70 -> 13.32 | V70: =ROUND(H70*S70,2) -> 0 | W70: =ROUND(H70*T70,2) -> 5299.55 | X70: =ROUND(H70*U70,2) -> 9155.64
A71: 10.3 | B71: sico | C71: MURO DE CONTORNO COM PILAR EM CONCRETO ARMADO A CADA 2,50M, CONTENDO: ESCAVAÇÃO, ALV. PEDRA, EMBASAMENTO, RADIER, CINTA, CHAPISCADO, REBOCADO H=2,50M | D71: SINAPI | E71: M | F71: 21.76 | G71: 502.35 | H71: 615.23 | I71: 10931.14 | J71: 13387.4 | K71: 21.76 | Q71: =K71+L71+M71+N71+O71+P71 -> 21.76 | R71: =Q71/F71 -> 1 | S71: =MEMORIAL!AJ398-F71 -> 57.94 | U71: =F71+S71-T71 -> 79.7 | V71: =ROUND(H71*S71,2) -> 35646.43 | W71: =ROUND(H71*T71,2) -> 0 | X71: =ROUND(H71*U71,2) -> 49033.83
A72: 11 | B72: PORTAS DE MADEIRAS E ALUMINIO | I72: 23101.56 | J72: 28292.49 | V72: =SUM(V73:V77) -> 37705.73 | W72: =SUM(W73:W77) -> 28292.49 | X72: =SUM(X73:X77) -> 37705.73
A73: 11.1 | B73: 90790 | C73: KIT DE PORTA-PRONTA DE MADEIRA EM ACABAMENTO MELAMÍNICO BRANCO, FOLHA LEVE OU MÉDIA, 80X210CM, EXCLUSIVE FECHADURA, FIXAÇÃO COM PREENCHIMENTO PARCIAL DE ESPUMA EXPANSIVA - FORNECIMENTO E INSTALAÇÃO. AF_12/2019 | D73: SINAPI | E73: UN | F73: 8 | G73: 864.7 | H73: 1059 | I73: 6917.6 | J73: 8472 | K73: =0 -> 0 | L73: 0 | Q73: =K73+L73+M73+N73+O73+P73 -> 0 | R73: =Q73/F73 -> 0 | T73: =F73 -> 8 | U73: =F73+S73-T73 -> 0 | V73: =ROUND(H73*S73,2) -> 0 | W73: =ROUND(H73*T73,2) -> 8472 | X73: =ROUND(H73*U73,2) -> 0
A74: 11.2 | B74: 90788 | C74: KIT DE PORTA-PRONTA DE MADEIRA EM ACABAMENTO MELAMÍNICO BRANCO, FOLHA LEVE OU MÉDIA, 60X210CM, EXCLUSIVE FECHADURA, FIXAÇÃO COM PREENCHIMENTO PARCIAL DE ESPUMA EXPANSIVA - FORNECIMENTO E INSTALAÇÃO. AF_12/2019 | D74: SINAPI | E74: UN | F74: 9 | G74: 837.44 | H74: 1025.61 | I74: 7536.96 | J74: 9230.49 | K74: =0 -> 0 | L74: 0 | Q74: =K74+L74+M74+N74+O74+P74 -> 0 | R74: =Q74/F74 -> 0 | T74: =F74 -> 9 | U74: =F74+S74-T74 -> 0 | V74: =ROUND(H74*S74,2) -> 0 | W74: =ROUND(H74*T74,2) -> 9230.49 | X74: =ROUND(H74*U74,2) -> 0
A75: 11.3 | B75: 90790 | C75: KIT DE PORTA-PRONTA DE MADEIRA EM ACABAMENTO MELAMÍNICO BRANCO, FOLHA LEVE OU MÉDIA, 80X210CM, EXCLUSIVE FECHADURA, FIXAÇÃO COM PREENCHIMENTO PARCIAL DE ESPUMA EXPANSIVA - FORNECIMENTO E INSTALAÇÃO. AF_12/2019 | D75: SINAPI | E75: UN | F75: 10 | G75: 864.7 | H75: 1059 | I75: 8647 | J75: 10590 | K75: =0 -> 0 | L75: 0 | Q75: =K75+L75+M75+N75+O75+P75 -> 0 | R75: =Q75/F75 -> 0 | T75: =F75 -> 10 | U75: =F75+S75-T75 -> 0 | V75: =ROUND(H75*S75,2) -> 0 | W75: =ROUND(H75*T75,2) -> 10590 | X75: =ROUND(H75*U75,2) -> 0
A76: 11.4 | B76: 100690 | C76: KIT DE PORTA DE MADEIRA FRISADA, SEMI-OCA (LEVE OU MÉDIA), PADRÃO POPULAR, 80X210CM, ESPESSURA DE 3,5CM, ITENS INCLUSOS: DOBRADIÇAS, MONTAGEM E INSTALAÇÃO DE BATENTE, FECHADURA COM EXECUÇÃO DO FURO - FORNECIMENTO E INSTALAÇÃO. AF_12/2019 | D76: SINAPI | E76: UN | G76: =856.34*0.980188611 -> 839.37472 | H76: =G76*1.2247 -> 1027.9822 | S76: 18 | U76: =F76+S76-T76 -> 18 | V76: =ROUND(H76*S76,2) -> 18503.68 | W76: =ROUND(H76*T76,2) -> 0 | X76: =ROUND(H76*U76,2) -> 18503.68
A77: 11.5 | B77: 4716 | C77: Grade em metalon | D77: SINAPI | E77: M2 | G77: =294.41*0.980188611 -> 288.57733 | H77: =G77*1.2247 -> 353.42065 | S77: =MEMORIAL!AJ415 -> 54.332 | U77: =F77+S77-T77 -> 54.332 | V77: =ROUND(H77*S77,2) -> 19202.05 | W77: =ROUND(H77*T77,2) -> 0 | X77: =ROUND(H77*U77,2) -> 19202.05
A78: 12 | B78: PORTOES DE FERRO | I78: 1481.28 | J78: 1814.12 | V78: =SUM(V79:V80) -> 11476.42 | W78: =SUM(W79:W80) -> 1814.12 | X78: =SUM(X79:X80) -> 11476.42
A79: 12.1 | B79: 94805 | C79: PORTA DE ALUMÍNIO DE ABRIR PARA VIDRO SEM GUARNIÇÃO, 87X210CM, FIXAÇÃO COM PARAFUSOS, INCLUSIVE VIDROS - FORNECIMENTO E INSTALAÇÃO. AF_12/2019 | D79: SINAPI | E79: UN | F79: 2 | G79: 740.64 | H79: 907.06 | I79: 1481.28 | J79: 1814.12 | K79: =0 -> 0 | L79: 0 | Q79: =K79+L79+M79+N79+O79+P79 -> 0 | R79: =Q79/F79 -> 0 | T79: =F79 -> 2 | U79: =F79+S79-T79 -> 0 | V79: =ROUND(H79*S79,2) -> 0 | W79: =ROUND(H79*T79,2) -> 1814.12 | X79: =ROUND(H79*U79,2) -> 0
A80: 12.2 | B80: 91341 | C80: PORTA EM ALUMÍNIO DE ABRIR TIPO VENEZIANA COM GUARNIÇÃO, FIXAÇÃO COM PARAFUSOS - FORNECIMENTO E INSTALAÇÃO. AF_12/2019 | D80: SINAPI | E80: M2 | G80: =891.81*0.980188611 -> 874.14201 | H80: =G80*1.2247 -> 1070.5617 | S80: =MEMORIAL!AJ422 -> 10.72 | U80: =F80+S80-T80 -> 10.72 | V80: =ROUND(H80*S80,2) -> 11476.42 | W80: =ROUND(H80*T80,2) -> 0 | X80: =ROUND(H80*U80,2) -> 11476.42
A81: 13 | B81: JANELAS DE FERRO | I81: 31412.61 | J81: 38470.97 | V81: =SUM(V82:V87) -> 32249.29 | W81: =SUM(W82:W87) -> 31727.25 | X81: =SUM(X82:X87) -> 38993
A82: 13.1 | B82: 94559 | C82: JANELA DE AÇO TIPO BASCULANTE PARA VIDROS, COM BATENTE, FERRAGENS E PINTURA ANTICORROSIVA. EXCLUSIVE VIDROS, ACABAMENTO, ALIZAR E CONTRAMARCO. FORNECIMENTO E INSTALAÇÃO. AF_12/2019 | D82: SINAPI | E82: M2 | F82: 2.46 | G82: 757.34 | H82: 927.51 | I82: 1863.06 | J82: 2281.67 | K82: =0 -> 0 | L82: =0 -> 0 | Q82: =K82+L82+M82+N82+O82+P82 -> 0 | R82: =Q82/F82 -> 0 | T82: =F82 -> 2.46 | U82: =F82+S82-T82 -> 0 | V82: =ROUND(H82*S82,2) -> 0 | W82: =ROUND(H82*T82,2) -> 2281.67 | X82: =ROUND(H82*U82,2) -> 0
A83: 13.2 | B83: 94559 | C83: JANELA DE AÇO TIPO BASCULANTE PARA VIDROS, COM BATENTE, FERRAGENS E PINTURA ANTICORROSIVA. EXCLUSIVE VIDROS, ACABAMENTO, ALIZAR E CONTRAMARCO. FORNECIMENTO E INSTALAÇÃO. AF_12/2019 | D83: SINAPI | E83: M2 | F83: 1.12 | G83: 757.34 | H83: 927.51 | I83: 848.22 | J83: 1038.81 | K83: =0 -> 0 | L83: =0 -> 0 | Q83: =K83+L83+M83+N83+O83+P83 -> 0 | R83: =Q83/F83 -> 0 | T83: =F83 -> 1.12 | U83: =F83+S83-T83 -> 0 | V83: =ROUND(H83*S83,2) -> 0 | W83: =ROUND(H83*T83,2) -> 1038.81 | X83: =ROUND(H83*U83,2) -> 0
A84: 13.3 | B84: 94559 | C84: JANELA DE AÇO TIPO BASCULANTE PARA VIDROS, COM BATENTE, FERRAGENS E PINTURA ANTICORROSIVA. EXCLUSIVE VIDROS, ACABAMENTO, ALIZAR E CONTRAMARCO. FORNECIMENTO E INSTALAÇÃO. AF_12/2019 | D84: SINAPI | E84: M2 | F84: 8.05 | G84: 757.34 | H84: 927.51 | I84: 6096.59 | J84: 7466.46 | K84: =0 -> 0 | L84: =0 -> 0 | Q84: =K84+L84+M84+N84+O84+P84 -> 0 | R84: =Q84/F84 -> 0 | T84: =F84 -> 8.05 | U84: =F84+S84-T84 -> 0 | V84: =ROUND(H84*S84,2) -> 0 | W84: =ROUND(H84*T84,2) -> 7466.46 | X84: =ROUND(H84*U84,2) -> 0
A85: 13.4 | B85: 94562 | C85: JANELA DE AÇO DE CORRER COM 4 FOLHAS PARA VIDRO, COM BATENTE, FERRAGENS E PINTURA ANTICORROSIVA. EXCLUSIVE VIDROS, ALIZAR E CONTRAMARCO. FORNECIMENTO E INSTALAÇÃO. AF_12/2019 | D85: SINAPI | E85: M2 | F85: 1.34 | G85: 749.27 | H85: 917.63 | I85: 1004.02 | J85: 1229.62 | K85: =0 -> 0 | L85: =0 -> 0 | Q85: =K85+L85+M85+N85+O85+P85 -> 0 | R85: =Q85/F85 -> 0 | T85: =F85 -> 1.34 | U85: =F85+S85-T85 -> 0 | V85: =ROUND(H85*S85,2) -> 0 | W85: =ROUND(H85*T85,2) -> 1229.62 | X85: =ROUND(H85*U85,2) -> 0
A86: 13.5 | B86: 94562 | C86: JANELA DE AÇO DE CORRER COM 4 FOLHAS PARA VIDRO, COM BATENTE, FERRAGENS E PINTURA ANTICORROSIVA. EXCLUSIVE VIDROS, ALIZAR E CONTRAMARCO. FORNECIMENTO E INSTALAÇÃO. AF_12/2019 | D86: SINAPI | E86: M2 | F86: 21.48 | G86: 749.27 | H86: 917.63 | I86: 16094.32 | J86: 19710.69 | K86: =0 -> 0 | L86: =0 -> 0 | Q86: =K86+L86+M86+N86+O86+P86 -> 0 | R86: =Q86/F86 -> 0 | T86: =F86 -> 21.48 | U86: =F86+S86-T86 -> 0 | V86: =ROUND(H86*S86,2) -> 0 | W86: =ROUND(H86*T86,2) -> 19710.69 | X86: =ROUND(H86*U86,2) -> 0
A87: 13.6 | B87: 94570 | C87: JANELA DE ALUMÍNIO DE CORRER COM 2 FOLHAS PARA VIDROS, COM VIDROS, BATENTE, ACABAMENTO COM ACETATO OU BRILHANTE E FERRAGENS. EXCLUSIVE ALIZAR E CONTRAMARCO. FORNECIMENTO E INSTALAÇÃO. AF_12/2019 | D87: SINAPI | E87: M2 | F87: 7.16 | G87: 769.05 | H87: 941.86 | I87: 5506.4 | J87: 6743.72 | K87: =0 -> 0 | L87: =0 -> 0 | Q87: =K87+L87+M87+N87+O87+P87 -> 0 | R87: =Q87/F87 -> 0 | S87: =MEMORIAL!AJ436-F87 -> 34.24 | U87: =F87+S87-T87 -> 41.4 | V87: =ROUND(H87*S87,2) -> 32249.29 | W87: =ROUND(H87*T87,2) -> 0 | X87: =ROUND(H87*U87,2) -> 38993
A88: 14 | B88: COBERTURA | I88: 18069.54 | J88: 22129.02 | U88: =F88+S88-T88 -> 0 | V88: =SUM(V89:V94) -> 39037.56 | W88: =SUM(W89:W94) -> 0 | X88: =SUM(X89:X94) -> 61166.59
A89: 14.1 | B89: 94446 | C89: TELHAMENTO COM TELHA CERÂMICA CAPA-CANAL, TIPO PLAN, COM MAIS DE 2 ÁGUAS, INCLUSO TRANSPORTE VERTICAL. AF_07/2019 | D89: SINAPI | E89: M2 | F89: 390.67 | G89: 39.48 | H89: 48.35 | I89: 15423.65 | J89: 18888.89 | K89: =0 -> 0 | L89: =0 -> 0 | O89: =F89 -> 390.67 | Q89: =K89+L89+M89+N89+O89+P89 -> 390.67 | R89: =Q89/F89 -> 1 | S89: =MEMORIAL!AJ444-F89 -> 0.5862 | U89: =F89+S89-T89 -> 391.2562 | V89: =ROUND(H89*S89,2) -> 28.34 | W89: =ROUND(H89*T89,2) -> 0 | X89: =ROUND(H89*U89,2) -> 18917.24
A90: 14.2 | B90: 94219 | C90: CUMEEIRA E ESPIGÃO PARA TELHA CERÂMICA EMBOÇADA COM ARGAMASSA TRAÇO 1:2:9 (CIMENTO, CAL E AREIA), PARA TELHADOS COM MAIS DE 2 ÁGUAS, INCLUSO TRANSPORTE VERTICAL. AF_07/2019 | D90: SINAPI | E90: M | F90: 102.05 | G90: 23.6 | H90: 28.9 | I90: 2408.38 | J90: 2949.25 | K90: =0 -> 0 | L90: =0 -> 0 | O90: =F90 -> 102.05 | Q90: =K90+L90+M90+N90+O90+P90 -> 102.05 | R90: =Q90/F90 -> 1 | U90: =F90+S90-T90 -> 102.05 | V90: =ROUND(H90*S90,2) -> 0 | W90: =ROUND(H90*T90,2) -> 0 | X90: =ROUND(H90*U90,2) -> 2949.25
A91: 14.3 | B91: 94227 | C91: CALHA EM CHAPA DE AÇO GALVANIZADO NÚMERO 24, DESENVOLVIMENTO DE 33 CM, INCLUSO TRANSPORTE VERTICAL. AF_07/2019 | D91: SINAPI | E91: M | F91: 4.04 | G91: 58.79 | H91: 72 | I91: 237.51 | J91: 290.88 | K91: =0 -> 0 | L91: =0 -> 0 | O91: =F91 -> 4.04 | Q91: =K91+L91+M91+N91+O91+P91 -> 4.04 | R91: =Q91/F91 -> 1 | S91: =MEMORIAL!AJ448-F91 -> 59.79 | U91: =F91+S91-T91 -> 63.83 | V91: =ROUND(H91*S91,2) -> 4304.88 | W91: =ROUND(H91*T91,2) -> 0 | X91: =ROUND(H91*U91,2) -> 4595.76
A92: 14.4 | B92: 96109 | C92: FORRO EM PLACAS DE GESSO, PARA AMBIENTES RESIDENCIAIS. AF_05/2017_PS | D92: SINAPI | E92: M2 | G92: =36.32*0.980188611 -> 35.60045 | H92: =G92*1.2247 -> 43.599872 | S92: =MEMORIAL!AJ477 -> 366.1129 | U92: =F92+S92-T92 -> 366.1129 | V92: =ROUND(H92*S92,2) -> 15962.48 | W92: =ROUND(H92*T92,2) -> 0 | X92: =ROUND(H92*U92,2) -> 15962.48
A93: 14.5 | B93: 92544 | C93: TRAMA DE MADEIRA COMPOSTA POR TERÇAS PARA TELHADOS DE ATÉ 2 ÁGUAS PARA TELHA ESTRUTURAL DE FIBROCIMENTO, INCLUSO TRANSPORTE VERTICAL. AF_07/2019 | D93: SINAPI | E93: M2 | G93: =14.53*0.980188611 -> 14.242141 | H93: =G93*1.2247 -> 17.442349 | S93: =MEMORIAL!AJ484 -> 391.2562 | U93: =F93+S93-T93 -> 391.2562 | V93: =ROUND(H93*S93,2) -> 6824.43 | W93: =ROUND(H93*T93,2) -> 0 | X93: =ROUND(H93*U93,2) -> 6824.43
A94: 14.6 | B94: Composição 02 RT Praça | C94: Rufo em placa de concreto l=0,5m [adaptado 291] | D94: PROPRIO | E94: m | G94: =55.57*0.980188611 -> 54.469081 | H94: =G94*1.2247 -> 66.708284 | S94: =MEMORIAL!AJ490 -> 178.65 | U94: =F94+S94-T94 -> 178.65 | V94: =ROUND(H94*S94,2) -> 11917.43 | W94: =ROUND(H94*T94,2) -> 0 | X94: =ROUND(H94*U94,2) -> 11917.43
A95: 15 | B95: IMPERMEABILIZAÇÃO | I95: 38022.5 | J95: 46563.02 | V95: =SUM(V96:V97) -> 0 | W95: =SUM(W96:W97) -> 35258.42 | X95: =SUM(X96:X97) -> 11304.6
A96: 15.1 | B96: 98546 | C96: IMPERMEABILIZAÇÃO DE SUPERFÍCIE COM MANTA ASFÁLTICA, UMA CAMADA, INCLUSIVE APLICAÇÃO DE PRIMER ASFÁLTICO, E=3MM. AF_06/2018 | D96: SINAPI | E96: M2 | F96: 92.29 | G96: 100.02 | H96: 122.49 | I96: 9230.85 | J96: 11304.6 | K96: =F96 -> 92.29 | L96: =0 -> 0 | Q96: =K96+L96+M96+N96+O96+P96 -> 92.29 | R96: =Q96/F96 -> 1 | U96: =F96+S96-T96 -> 92.29 | V96: =ROUND(H96*S96,2) -> 0 | W96: =ROUND(H96*T96,2) -> 0 | X96: =ROUND(H96*U96,2) -> 11304.6
A97: 15.2 | B97: 98557 | C97: IMPERMEABILIZAÇÃO DE SUPERFÍCIE COM EMULSÃO ASFÁLTICA, 2 DEMÃOS AF_06/2018 | D97: SINAPI | E97: M2 | F97: 630.29 | G97: 45.68 | H97: 55.94 | I97: 28791.65 | J97: 35258.42 | K97: =0 -> 0 | L97: 0 | Q97: =K97+L97+M97+N97+O97+P97 -> 0 | R97: =Q97/F97 -> 0 | T97: =F97 -> 630.29 | U97: =F97+S97-T97 -> 0 | V97: =ROUND(H97*S97,2) -> 0 | W97: =ROUND(H97*T97,2) -> 35258.42 | X97: =ROUND(H97*U97,2) -> 0
A98: 16 | B98: REVESTIMENTOS DE PAREDES | I98: 80042.11 | J98: 98030.42 | V98: =SUM(V99:V106) -> 53156.92 | W98: =SUM(W99:W106) -> 19045.99 | X98: =SUM(X99:X106) -> 132141.35
A99: 16.1 | B99: 87879 | C99: CHAPISCO APLICADO EM ALVENARIAS E ESTRUTURAS DE CONCRETO INTERNAS, COM COLHER DE PEDREIRO. ARGAMASSA TRAÇO 1:3 COM PREPARO EM BETONEIRA 400L. AF_06/2014 | D99: SINAPI | E99: M2 | F99: 757.22 | G99: 3.38 | H99: 4.14 | I99: 2559.4 | J99: 3134.89 | K99: =0 -> 0 | L99: 757.22 | Q99: =K99+L99+M99+N99+O99+P99 -> 757.22 | R99: =Q99/F99 -> 1 | U99: =F99+S99-T99 -> 757.22 | V99: =ROUND(H99*S99,2) -> 0 | W99: =ROUND(H99*T99,2) -> 0 | X99: =ROUND(H99*U99,2) -> 3134.89
A100: 16.2 | B100: 87894 | C100: CHAPISCO APLICADO EM ALVENARIA (SEM PRESENÇA DE VÃOS) E ESTRUTURAS DE CONCRETO DE FACHADA, COM COLHER DE PEDREIRO. ARGAMASSA TRAÇO 1:3 COM PREPARO EM BETONEIRA 400L. AF_06/2014 | D100: SINAPI | E100: M2 | F100: 378.61 | G100: 5.07 | H100: 6.21 | I100: 1919.55 | J100: 2351.17 | K100: =0 -> 0 | L100: 223.82 | M100: 98 | O100: 56.79 | Q100: =K100+L100+M100+N100+O100+P100 -> 378.61 | R100: =Q100/F100 -> 1 | S100: =MEMORIAL!AJ571-F100 -> 487.4305 | U100: =F100+S100-T100 -> 866.0405 | V100: =ROUND(H100*S100,2) -> 3026.94 | W100: =ROUND(H100*T100,2) -> 0 | X100: =ROUND(H100*U100,2) -> 5378.11
A101: 16.3 | B101: 87878 | C101: CHAPISCO APLICADO EM ALVENARIAS E ESTRUTURAS DE CONCRETO INTERNAS, COM COLHER DE PEDREIRO. ARGAMASSA TRAÇO 1:3 COM PREPARO MANUAL. AF_06/2014 | D101: SINAPI | E101: M2 | F101: 394 | G101: =H101/1.2247 -> 3.7315261 | H101: 4.57 | I101: 1469.62 | J101: 1800.58 | K101: =0 -> 0 | L101: 394 | Q101: =K101+L101+M101+N101+O101+P101 -> 394 | R101: =Q101/F101 -> 1 | T101: =(F99+F101)-MEMORIAL!AJ544 -> 262.098 | U101: =F101+S101-T101 -> 131.902 | V101: =ROUND(H101*S101,2) -> 0 | W101: =ROUND(H101*T101,2) -> 1197.79 | X101: =ROUND(H101*U101,2) -> 602.79
...

Sheet MEMORIAL
A2: OBRA: | B2: CONSTRUÇÃO DE UMA CRECHE COM CAPACIDADE PARA 50 (CEM) CRIANÇAS
A3: OBJETO: | B3: PRESTAR SERVIÇOS DE ENGENHARIA PARA CONSTRUÇÃO DE 01 (UMA) CRECHE COM CAPACIDADE PARA 50 (CINQUENTA) CRIANÇAS, COM BASE NO PROGRAMA PARAÍBA PRIMEIRA INFÂNCIA NO MUNICIPIO DE COREMAS-PB.
A4: LOCAL: | B4: COREMAS - PB | AJ4: 0.2247
A5: MEMORIAL DE CALCULO
A6: ITEM | B6: CÓDIGO | C6: DESCRIÇÃO | D6: CÁLCULOS | AJ6: UNID
A7: 1 | B7: SERVIÇOS PRELIMINARES
A8: 1.1 | B8: PRO-46870444 | C8: PLACA INDICATIVA DA OBRA EM CHAPA DE AÇO GALVANIZADO (4,0M X 2,0M) | AJ8: M²
C9: PLACA | D9: 4 | E9: X | F9: 2 | AI9: = | AJ9: =D9*F9 -> 8
D10: TOTAL | AI10: = | AJ10: =AJ9 -> 8
A11: 1.2 | B11: 93584 | C11: EXECUÇÃO DE DEPÓSITO EM CANTEIRO DE OBRA EM CHAPA DE MADEIRA COMPENSADA, NÃO INCLUSO MOBILIÁRIO. AF_04/2016 | AJ11: M2
A12: 1.3 | B12: 99059 | C12: LOCACAO CONVENCIONAL DE OBRA, UTILIZANDO GABARITO DE TÁBUAS CORRIDAS PONTALETADAS A CADA 2,00M - 2 UTILIZAÇÕES. AF_10/2018 | AJ12: M
A13: 2.5 | B13: 94342 | C13: ATERRO MANUAL DE VALAS COM AREIA PARA ATERRO E COMPACTAÇÃO MECANIZADA. AF_05/2016 | AJ13: M2
A14: 2 | B14: MOVIMENTO DE TERRA
A15: 2.1 | B15: 93382 | C15: REATERRO MANUAL DE VALAS COM COMPACTAÇÃO MECANIZADA. AF_04/2016 | AJ15: M3
A16: 2.2 | B16: 93358 | C16: ESCAVAÇÃO MANUAL DE VALA COM PROFUNDIDADE MENOR OU IGUAL A 1,30 M. AF_02/2021 | AJ16: M3
C17: S1=S2=S3=S4=S5=S7=S8=S9=S12=S13=S15=S16=S17=S21=S22=S23=S24=S25=S28=S31=S32=S33=S34=S35=S36=S37=S38=S39=S40=S42=S43=S44=S45=S47=S48S=S49=S50=S52=S53=S54=S55=S56=S57=S58=S59=S60 | D17: 0.6 | E17: X | F17: 0.75 | G17: X | H17: 1 | AG17: x | AH17: 47 | AI17: = | AJ17: =(D17*F17*H17)*AH17 -> 21.15
C18: S11=S51 | D18: 0.65 | E18: X | F18: 0.65 | G18: X | H18: 1 | AG18: x | AH18: 2 | AI18: = | AJ18: =(D18*F18*H18)*AH18 -> 0.845
C19: S19 | D19: 0.55 | E19: X | F19: 1 | G19: X | H19: 1 | AG19: x | AH19: 1 | AI19: = | AJ19: =(D19*F19*H19)*AH19 -> 0.55
C20: S14=S18=S20=S27=S30 | D20: 0.7 | E20: X | F20: 0.85 | G20: X | H20: 1 | AG20: x | AH20: 5 | AI20: = | AJ20: =(D20*F20*H20)*AH20 -> 2.975
C21: S10 | D21: 0.75 | E21: X | F21: 0.75 | G21: X | H21: 1 | AG21: x | AH21: 1 | AI21: = | AJ21: =(D21*F21*H21)*AH21 -> 0.5625
C22: S46 | D22: 0.85 | E22: X | F22: 1 | G22: X | H22: 1 | AG22: x | AH22: 1 | AI22: = | AJ22: =(D22*F22*H22)*AH22 -> 0.85
C23: S26=S29=S41 | D23: 0.8 | E23: X | F23: 0.95 | G23: x | H23: 1 | AG23: x | AH23: 3 | AI23: = | AJ23: =(D23*F23*H23)*AH23 -> 2.28
B24: TOTAL | AI24: = | AJ24: =SUM(AJ17:AJ23) -> 29.2125
D25: ESCAVAÇÃO DAS VALAS HORIZONATAIS E VERTICAIS
C26: V1 | D26: 5.082 | E26: + | F26: 2.246 | G26: + | H26: 2.299 | I26: + | J26: 4.641 | K26: + | L26: 2.197 | AE26: x | AF26: 0.15 | AG26: x | AH26: 0.3 | AI26: = | AJ26: =(D26+F26+H26+J26+L26+N26)*AF26*AH26 -> 0.740925
C27: V2 | D27: 2.934 | E27: + | G27: + | AE27: x | AF27: 0.15 | AG27: x | AH27: 0.3 | AI27: = | AJ27: =(D27+F27+H27+J27+L27+N27)*AF27*AH27 -> 0.13203
C28: V3 | D28: 3.657 | E28: + | G28: + | AE28: x | AF28: 0.15 | AG28: x | AH28: 0.3 | AI28: = | AJ28: =(D28+F28+H28+J28+L28+N28)*AF28*AH28 -> 0.164565
C29: V4 | D29: 4.528 | E29: + | F29: 3.912 | G29: + | H29: 1.537 | AE29: x | AF29: 0.15 | AG29: x | AH29: 0.3 | AI29: = | AJ29: =(D29+F29+H29+J29+L29+N29)*AF29*AH29 -> 0.448965
C30: V5 | D30: 4.641 | E30: + | F30: 2.197 | G30: + | AE30: x | AF30: 0.15 | AG30: x | AH30: 0.3 | AI30: = | AJ30: =(D30+F30+H30+J30+L30+N30)*AF30*AH30 -> 0.30771
C31: V6 | D31: 2.934 | E31: + | G31: + | AE31: x | AF31: 0.15 | AG31: x | AH31: 0.3 | AI31: = | AJ31: =(D31+F31+H31+J31+L31+N31)*AF31*AH31 -> 0.13203
C32: V7 | D32: 3.807 | E32: + | G32: + | AE32: x | AF32: 0.15 | AG32: x | AH32: 0.3 | AI32: = | AJ32: =(D32+F32+H32+J32+L32+N32)*AF32*AH32 -> 0.171315
C33: V8 | D33: 4.553 | E33: + | F33: 3.962 | G33: + | H33: 1.712 | AE33: x | AF33: 0.15 | AG33: x | AH33: 0.3 | AI33: = | AJ33: =(D33+F33+H33+J33+L33+N33)*AF33*AH33 -> 0.460215
C34: V9 | D34: 5.157 | E34: + | AE34: x | AF34: 0.15 | AG34: x | AH34: 0.3 | AI34: = | AJ34: =(D34+F34+H34+J34+L34+N34)*AF34*AH34 -> 0.232065
C35: V10 | D35: 0 | E35: + | AE35: x | AF35: 0.15 | AG35: x | AH35: 0.3 | AI35: = | AJ35: =(D35+F35+H35+J35+L35+N35)*AF35*AH35 -> 0
C36: V11 | D36: 2.324 | E36: + | AE36: x | AF36: 0.15 | AG36: x | AH36: 0.3 | AI36: = | AJ36: =(D36+F36+H36+J36+L36+N36)*AF36*AH36 -> 0.10458
C37: V12 | D37: 2.295 | E37: + | AE37: x | AF37: 0.15 | AG37: x | AH37: 0.3 | AI37: = | AJ37: =(D37+F37+H37+J37+L37+N37)*AF37*AH37 -> 0.103275
C38: V13 | D38: 0.922 | E38: + | F38: 2.74 | AE38: x | AF38: 0.15 | AG38: x | AH38: 0.3 | AI38: = | AJ38: =(D38+F38+H38+J38+L38+N38)*AF38*AH38 -> 0.16479
C39: V14 | D39: 4.55 | E39: + | AE39: x | AF39: 0.15 | AG39: x | AH39: 0.3 | AI39: = | AJ39: =(D39+F39+H39+J39+L39+N39)*AF39*AH39 -> 0.20475
C40: V15 | D40: 3.962 | E40: + | AE40: x | AF40: 0.15 | AG40: x | AH40: 0.3 | AI40: = | AJ40: =(D40+F40+H40+J40+L40+N40)*AF40*AH40 -> 0.17829
C41: V16 | D41: 3.371 | E41: + | F41: 3.962 | AE41: x | AF41: 0.15 | AG41: x | AH41: 0.3 | AI41: = | AJ41: =(D41+F41+H41+J41+L41+N41)*AF41*AH41 -> 0.329985
C42: V17 | D42: 4.297 | E42: + | AE42: x | AF42: 0.15 | AG42: x | AH42: 0.3 | AI42: = | AJ42: =(D42+F42+H42+J42+L42+N42)*AF42*AH42 -> 0.193365
C43: V18 | D43: 4.8 | E43: + | AE43: x | AF43: 0.15 | AG43: x | AH43: 0.3 | AI43: = | AJ43: =(D43+F43+H43+J43+L43+N43)*AF43*AH43 -> 0.216
C44: V19 | D44: 0.772 | E44: + | AE44: x | AF44: 0.15 | AG44: x | AH44: 0.3 | AI44: = | AJ44: =(D44+F44+H44+J44+L44+N44)*AF44*AH44 -> 0.03474
C45: V20 | D45: 2.122 | E45: + | AE45: x | AF45: 0.15 | AG45: x | AH45: 0.3 | AI45: = | AJ45: =(D45+F45+H45+J45+L45+N45)*AF45*AH45 -> 0.09549
C46: V21 | D46: 6.896 | E46: + | F46: 4.55 | G46: + | H46: 3.962 | I46: + | J46: 3.371 | K46: + | AE46: x | AF46: 0.15 | AG46: x | AH46: 0.3 | AI46: = | AJ46: =(D46+F46+H46+J46+L46+N46)*AF46*AH46 -> 0.845055
C47: V22 | D47: 4.55 | E47: + | F47: 3.962 | AE47: x | AF47: 0.15 | AG47: x | AH47: 0.3 | AI47: = | AJ47: =(D47+F47+H47+J47+L47+N47)*AF47*AH47 -> 0.38304
C48: V23 | D48: 4.187 | E48: + | AE48: x | AF48: 0.15 | AG48: x | AH48: 0.3 | AI48: = | AJ48: =(D48+F48+H48+J48+L48+N48)*AF48*AH48 -> 0.188415
C49: V24 | D49: 2.768 | E49: + | F49: 1.249 | G49: + | H49: 2.559 | I49: + | J49: 4.559 | K49: + | L49: 3.962 | M49: + | N49: 3.371 | AE49: x | AF49: 0.15 | AG49: x | AH49: 0.3 | AI49: = | AJ49: =(D49+F49+H49+J49+L49+N49)*AF49*AH49 -> 0.83106
C50: V25 | D50: 2.917 | E50: + | F50: 5.183 | G50: + | AE50: x | AF50: 0.15 | AG50: x | AH50: 0.3 | AI50: = | AJ50: =(D50+F50+H50+J50+L50+N50)*AF50*AH50 -> 0.3645
C51: V26 | D51: 1.515 | E51: + | F51: 2.629 | G51: + | H51: 2.206 | AE51: x | AF51: 0.15 | AG51: x | AH51: 0.3 | AI51: = | AJ51: =(D51+F51+H51+J51+L51+N51)*AF51*AH51 -> 0.28575
C52: V27 | D52: 1.915 | E52: + | AE52: x | AF52: 0.15 | AG52: x | AH52: 0.3 | AI52: = | AJ52: =(D52+F52+H52+J52+L52+N52)*AF52*AH52 -> 0.086175
C53: V28 | D53: 2.179 | E53: + | AE53: x | AF53: 0.15 | AG53: x | AH53: 0.3 | AI53: = | AJ53: =(D53+F53+H53+J53+L53+N53)*AF53*AH53 -> 0.098055
C54: V29 | D54: 1.515 | E54: + | AE54: x | AF54: 0.15 | AG54: x | AH54: 0.3 | AI54: = | AJ54: =(D54+F54+H54+J54+L54+N54)*AF54*AH54 -> 0.068175
C55: V30 | D55: 1.915 | E55: + | AE55: x | AF55: 0.15 | AG55: x | AH55: 0.3 | AI55: = | AJ55: =(D55+F55+H55+J55+L55+N55)*AF55*AH55 -> 0.086175
C56: V31 | D56: 1.515 | E56: + | F56: 2.779 | G56: + | AE56: x | AF56: 0.15 | AG56: x | AH56: 0.3 | AI56: = | AJ56: =(D56+F56+H56+J56+L56+N56)*AF56*AH56 -> 0.19323
C57: V32 | D57: 2.179 | E57: + | AE57: x | AF57: 0.15 | AG57: x | AH57: 0.3 | AI57: = | AJ57: =(D57+F57+H57+J57+L57+N57)*AF57*AH57 -> 0.098055
C58: V33 | D58: =2.788-0.15 -> 2.638 | E58: + | AE58: x | AF58: 0.15 | AG58: x | AH58: 0.3 | AI58: = | AJ58: =(D58+F58+H58+J58+L58+N58)*AF58*AH58 -> 0.11871
C59: V34 | D59: 1.606 | E59: + | AE59: x | AF59: 0.15 | AG59: x | AH59: 0.3 | AI59: = | AJ59: =(D59+F59+H59+J59+L59+N59)*AF59*AH59 -> 0.07227
C60: V35 | D60: 1.615 | E60: + | AE60: x | AF60: 0.15 | AG60: x | AH60: 0.3 | AI60: = | AJ60: =(D60+F60+H60+J60+L60+N60)*AF60*AH60 -> 0.072675
C61: V36 | D61: 2.771 | E61: + | AE61: x | AF61: 0.15 | AG61: x | AH61: 0.3 | AI61: = | AJ61: =(D61+F61+H61+J61+L61+N61)*AF61*AH61 -> 0.124695
C62: V37 | D62: 2.215 | E62: + | AE62: x | AF62: 0.15 | AG62: x | AH62: 0.3 | AI62: = | AJ62: =(D62+F62+H62+J62+L62+N62)*AF62*AH62 -> 0.099675
C63: V38 | D63: 2.788 | E63: + | F63: 1.606 | G63: + | H63: 1.615 | I63: + | J63: 2.771 | K63: + | L63: 2.215 | AE63: x | AF63: 0.15 | AG63: x | AH63: 0.3 | AI63: = | AJ63: =(D63+F63+H63+J63+L63+N63)*AF63*AH63 -> 0.494775
C64: V39 | D64: 2.788 | E64: + | F64: 1.606 | G64: + | H64: 1.615 | I64: + | J64: 2.771 | K64: + | L64: 2.215 | AE64: x | AF64: 0.15 | AG64: x | AH64: 0.3 | AI64: = | AJ64: =(D64+F64+H64+J64+L64+N64)*AF64*AH64 -> 0.494775
C65: V40 | D65: 2.215 | E65: + | F65: 0.874 | G65: + | AE65: x | AF65: 0.15 | AG65: x | AH65: 0.3 | AI65: = | AJ65: =(D65+F65+H65+J65+L65+N65)*AF65*AH65 -> 0.139005
C66: V41 | D66: =4.544-0.3 -> 4.244 | E66: + | F66: 1.615 | G66: + | AE66: x | AF66: 0.15 | AG66: x | AH66: 0.3 | AI66: = | AJ66: =(D66+F66+H66+J66+L66+N66)*AF66*AH66 -> 0.263655
C67: V42 | D67: 2.453 | E67: + | AE67: x | AF67: 0.15 | AG67: x | AH67: 0.3 | AI67: = | AJ67: =(D67+F67+H67+J67+L67+N67)*AF67*AH67 -> 0.110385
C68: V43 | D68: =6.309-0.3-0.3-0.3 -> 5.409 | E68: + | AE68: x | AF68: 0.15 | AG68: x | AH68: 0.3 | AI68: = | AJ68: =(D68+F68+H68+J68+L68+N68)*AF68*AH68 -> 0.243405
C69: V44 | D69: 2.453 | E69: + | AE69: x | AF69: 0.15 | AG69: x | AH69: 0.3 | AI69: = | AJ69: =(D69+F69+H69+J69+L69+N69)*AF69*AH69 -> 0.110385
C70: V45 | D70: 3.706 | E70: + | AE70: x | AF70: 0.15 | AG70: x | AH70: 0.3 | AI70: = | AJ70: =(D70+F70+H70+J70+L70+N70)*AF70*AH70 -> 0.16677
C71: V46 | D71: 4.676 | E71: + | AE71: x | AF71: 0.15 | AG71: x | AH71: 0.3 | AI71: = | AJ71: =(D71+F71+H71+J71+L71+N71)*AF71*AH71 -> 0.21042
C72: V47 | D72: =6.309-0.6 -> 5.709 | E72: + | AE72: x | AF72: 0.15 | AG72: x | AH72: 0.3 | AI72: = | AJ72: =(D72+F72+H72+J72+L72+N72)*AF72*AH72 -> 0.256905
C73: V48 | D73: 1.482 | E73: + | AE73: x | AF73: 0.15 | AG73: x | AH73: 0.3 | AI73: = | AJ73: =(D73+F73+H73+J73+L73+N73)*AF73*AH73 -> 0.06669
C74: V49 | D74: 4.676 | E74: + | AE74: x | AF74: 0.15 | AG74: x | AH74: 0.3 | AI74: = | AJ74: =(D74+F74+H74+J74+L74+N74)*AF74*AH74 -> 0.21042
C75: V50 | D75: =6.309-0.6 -> 5.709 | E75: + | AE75: x | AF75: 0.15 | AG75: x | AH75: 0.3 | AI75: = | AJ75: =(D75+F75+H75+J75+L75+N75)*AF75*AH75 -> 0.256905
C76: V51 | D76: 3.759 | E76: + | F76: 2.4 | AE76: x | AF76: 0.15 | AG76: x | AH76: 0.3 | AI76: = | AJ76: =(D76+F76+H76+J76+L76+N76)*AF76*AH76 -> 0.277155
C77: V52 | D77: 3.759 | E77: + | F77: 2.25 | AE77: x | AF77: 0.15 | AG77: x | AH77: 0.3 | AI77: = | AJ77: =(D77+F77+H77+J77+L77+N77)*AF77*AH77 -> 0.270405
D78: TOTAL | AI78: = | AJ78: =SUM(AJ26:AJ77) -> 12.00285
D79: ESCAVAÇÃO DAS VALAS
C80: Calçada contorno da creche | D80: 2.2 | E80: x | F80: 7.35 | G80: + | H80: 2.22 | I80: x | J80: 1.25 | K80: + | L80: 6 | M80: x | N80: 1.46 | O80: + | P80: 1.2 | Q80: x | R80: 19.95 | S80: + | T80: 4.05 | U80: x | V80: 3.85 | W80: + | X80: 0.63 | Y80: x | Z80: 4.65 | AG80: x | AH80: 0.2 | AI80: = | AJ80: =(D80*F80+H80*J80+L80*N80+P80*R80+T80*V80+X80*Z80)*AH80 -> 14.0334
C81: Calçada externa/ passeio | D81: 40 | E81: x | F81: 1.2 | AG81: x | AH81: 0.4 | AI81: = | AJ81: =(D81*F81+H81*J81+L81*N81+P81*R81+T81*V81+X81*Z81)*AH81 -> 19.2
C82: Jardim/mastro | D82: 1.5 | E82: x | F82: 3.17 | AG82: x | AH82: 0.3 | AI82: = | AJ82: =(D82*F82+H82*J82+L82*N82+P82*R82+T82*V82+X82*Z82)*AH82 -> 1.4265
C83: Parquinho | D83: 15.1 | E83: x | F83: 3.3 | AG83: x | AH83: 0.3 | AI83: = | AJ83: =(D83*F83+H83*J83+L83*N83+P83*R83+T83*V83+X83*Z83)*AH83 -> 14.949
C84: Casa de gás | D84: 1.1 | E84: x | F84: 3.7 | AG84: x | AH84: 0.3 | AI84: = | AJ84: =(D84*F84+H84*J84+L84*N84+P84*R84+T84*V84+X84*Z84)*AH84 -> 1.221
C85: Reservatório inferior-cisterna | D85: 2.8 | E85: x | F85: 2.8 | AG85: x | AH85: 0.3 | AI85: = | AJ85: =(D85*F85+H85*J85+L85*N85+P85*R85+T85*V85+X85*Z85)*AH85 -> 2.352
D86: TOTAL | AI86: = | AJ86: =SUM(AJ80:AJ85) -> 53.1819
D87: TOTAL GERAL | AI87: = | AJ87: =AJ24+AJ78+AJ86 -> 94.39725
A88: 2.3 | B88: 93382 | C88: REATERRO MANUAL DE VALAS COM COMPACTAÇÃO MECANIZADA. AF_04/2016 | AJ88: M3
A89: 2.4 | B89: 96995 | C89: REATERRO MANUAL APILOADO COM SOQUETE. AF_10/2017 | AJ89: M3
A90: 2.5 | B90: 94342 | C90: ATERRO MANUAL DE VALAS COM AREIA PARA ATERRO E COMPACTAÇÃO MECANIZADA. AF_05/2016 | AJ90: M3
A91: 2.6 | B91: 94342 | C91: ATERRO MANUAL DE VALAS COM AREIA PARA ATERRO E COMPACTAÇÃO MECANIZADA. AF_05/2016 | AJ91: M3
C92: Passeio externo | D92: 40 | E92: x | F92: 1.3 | AG92: X | AH92: =0.35-0.05 -> 0.3 | AI92: = | AJ92: =(D92*F92+H92*J92+L92*N92)*AH92 -> 15.6
C93: Passeio do contorno da edificação fachada | D93: 2.2 | E93: x | F93: =7.35-0.2 -> 7.15 | G93: + | H93: =1.5-0.2 -> 1.3 | I93: x | J93: 6 | AG93: X | AH93: 0.05 | AI93: = | AJ93: =(D93*F93+H93*J93+L93*N93)*AH93 -> 1.1765
C94: Passeio do contorno da edificação lado esquerdo | D94: 19.95 | E94: x | F94: =1.2-0.2 -> 1 | G94: + | H94: 4.65 | I94: x | J94: 0.63 | K94: + | L94: =4.05-0.2-0.2 -> 3.65 | M94: X | N94: 3.85 | AG94: X | AH94: 0.05 | AI94: = | AJ94: =(D94*F94+H94*J94+L94*N94)*AH94 -> 1.8466
C95: Mastro | D95: 3.17 | E95: X | F95: =1.5-0.4 -> 1.1 | AG95: X | AH95: =0.2-0.05 -> 0.15 | AI95: = | AJ95: =(D95*F95+H95*J95+L95*N95)*AH95 -> 0.52305
D96: TOTAL | AJ96: =SUM(AJ92:AJ95) -> 19.14615
A97: 3 | B97: SAPATAS
A98: 3.1 | B98: 96616 | C98: LASTRO DE CONCRETO MAGRO, APLICADO EM BLOCOS DE COROAMENTO OU SAPATAS. AF_08/2017 | AJ98: M3
C99: S1=S2=S3=S4=S5=S7=S8=S9=S12=S13=S15=S16=S17=S21=S22=S23=S24=S25=S28=S31=S32=S33=S34=S35=S36=S37=S38=S39=S40=S42=S43=S44=S45=S47=S48S=S49=S50=S52=S53=S54=S55=S56=S57=S58=S59=S60 | D99: 0.6 | E99: X | F99: 0.75 | G99: X | H99: 0.05 | AG99: x | AH99: 47 | AI99: = | AJ99: =(D99*F99*H99)*AH99 -> 1.0575
C100: S11=S51 | D100: 0.65 | E100: X | F100: 0.65 | G100: X | H100: 0.05 | AG100: x | AH100: 2 | AI100: = | AJ100: =(D100*F100*H100)*AH100 -> 0.04225
C101: S19 | D101: 0.55 | E101: X | F101: 1 | G101: X | H101: 0.05 | AG101: x | AH101: 1 | AI101: = | AJ101: =(D101*F101*H101)*AH101 -> 0.0275
...
